Workbook

Sheet Read Me
A1: 🏆 MONIT MULTIBAGGER RESEARCH ENGINE & SCANNER
A2: Daily Analytics Report | Generated: Thursday, 04 June 2026
A5: 📖 QUICK REFERENCE RUNBOOK & SYSTEM FLOW
A6: Step 1: Reference this Read Me | B6: Understand terms, formulas, and underlying investment theses directly in this glossary dashboard.
A7: Step 2: Check Leaderboard Tab | B7: Locate long-term compounders with high Persistence Scores and streaks (institutional accumulation footprint).
A8: Step 3: Analyze Confluence Overlap | B8: Review the ultimate high-conviction candidates intersecting our scanner signals and StockScans overlaps.
A9: Step 4: Scoring Monit Tabs | B9: Open 'Monit Non Financial' or 'Monit Banks NBFC' to fill out your qualitative checks (Tailwinds, Promoters, Triggers).
A10: Step 5: Track Scan Matches | B10: Confirm consensus using 'Scan Match' tabs which score companies by total appearances across allStockScans.
A13: 📊 RESEARCH ENGINE GLOSSARY, METRICS & THESES
A15: Metric Term / Tab Name | B15: Practical Meaning & Underlying Investment Thesis | C15: Automated DB Query / Logic & Excel Formula
A16: EMA Crossover (Birth of a Trend) | B16: An entry signal triggered when price crosses above its 200-day EMA. [THESIS]: Represents the birth of a new long-term uptrend. Buying here provides maximum asymmetrical risk-to-reward because the entry is close to the logical stop-loss (the EMA itself). | C16: pine_signal == 'EMA Crossover' Sized at 7% capital allocation (~₹70,000 per position).
A17: 52W Breakout (Momentum Confirmation) | B17: A momentum signal triggered when a stock above its 200-day EMA breaks out to fresh 52-week highs. [THESIS]: Represents a confirmed breakout where institutional buying pressure clears all historical supply. High momentum outperformance. | C17: pine_signal == '52W Breakout' Sized at 5% capital allocation (~₹50,000 per position).
A18: ATH Momentum (Runaway Leader) | B18: An established trend signal triggered when the price is actively running near its All-Time Highs. [THESIS]: Identifies the strongest runaway leaders in the market. Ideal for high-velocity momentum trading where price experiences immediate continuation. | C18: pine_signal == 'ATH Momentum' Sized at 4% capital allocation (~₹40,000 per position).
A19: Persistence Score (30D) (Accumulation Footprint) | B19: The count of times a stock has appeared in the daily screener during the last 30 active trading days. [THESIS]: Represents persistent institutional buying. Random spikes appear 1-2 times, but compounders appear 10+ times as institutions accumulate. | C19: Queries the local SQLite database (`logs/backtest.db`) to sum the total number of distinct dates the ticker appeared on the screener during the last 30 active trading days. Formula: COUNT(DISTINCT date)
A20: Consecutive Streak Days (Uninterrupted Trend) | B20: The number of consecutive trading days that the stock has appeared in the screener up to today. [THESIS]: High streaks indicate an exceptionally strong, uninterrupted runaway trend with heavy daily buying pressure. | C20: Checks the chronological sequence of scanner dates in SQLite starting from the most recent run date and counting backward. The streak increments for every contiguous date the ticker appears.
A21: Sector Velocity WoW (Early Sector Rotation) | B21: Compares the volume of screener signals in a sector over the last 5 trading days (W1) against the previous 5 trading days (W2). [THESIS]: Detects early sector rotation. A sudden positive surge warns you of capital flowing aggressively into a specific theme. | C21: Counts appearances of all tickers categorized by their sector. Formula: W1_Count = COUNT(records WHERE date IN last 5 trading days) W2_Count = COUNT(records WHERE date IN days -10 to -5) Velocity % = ((W1_Count - W2_Count) / W2_Count) * 100
A22: Emerging Leaders (Momentum Expansion) | B22: Identifies breakout stocks experiencing a sudden momentum expansion. [THESIS]: Finds stocks with a high concentration of appearances recently but almost zero history in the preceding months. Represents new institutional entries. | C22: Finds stocks with at least 5 appearances in the last 10 trading days, but less than or equal to 3 appearances in the prior 50 trading days (i.e. trading days -60 to -10). Formula: COUNT(recent) >= 5 AND COUNT(historical) <= 3
A23: Tab: Confluence Overlap (The Ultimate Overlap) | B23: This sheet displays the absolute highest conviction watchlist candidates intersecting multiple strategies. [THESIS]: Filters out market noise by only displaying stocks appearing in at least two out of three major momentum dimensions: (1) Chartink screener universe, (2) Active scanner signals, and (3) StockScans overlap list. | C23: Calculates the mathematical intersection of the three sets: In_Universe + In_Scanner + In_StockScans >= 2 Single-dimension matches are automatically filtered out to eliminate market noise.
A24: Tab: Monit Non Financial (CHECKLIST SHEET) | B24: Your main watchlist scoring sheet for non-financial companies. [THESIS]: Keeps watchlist scoring fully formula-driven using Excel formulas. It combines automated metrics (RSI, ADX, V-stop, Persistence) with your qualitative scores (Promoter Buying, Near-Term Trigger, Headwind/Tailwind). | C24: Uses relative index-matching formulas to populate automated close prices, RSI, ADX, V-stop, and Persistence from the SQLite and Chartink universe sheets. Formula: INDEX-MATCH left-lookup.
A25: Tab: Monit Banks NBFC (BANKING CHECKLIST) | B25: Your main watchlist scoring sheet for banking and NBFC companies. [THESIS]: Tailored specifically for banking structures, incorporating specialized metrics like Net Interest Margins (NIM) and Credit Costs alongside technical indicators. | C25: Features banking-specific checklist criteria to ensure qualitative analyst inputs align with bank metrics.
A26: Tab: Scan Match tabs (StockScans Confluence) | B26: Displays the top 100 stocks appearing across all StockScans screeners. [THESIS]: Scores stocks qualitatively by scan volume. Stocks appearing in >20 scans receive a premium 10-point bonus, proving market-wide momentum consensus. | C26: Applies a nested Excel IF formula: `=IF(D8>20,10,IF(D8>=10,5,2))` Scores: >20 scans = 10 pts; 10-20 scans = 5 pts; <10 scans = 2 pts.
... A36: Weekly Tracking Highlighting (Additions / Removals) | B36: Visual highlights indicating weekly changes in the StockScans 100 (Scan Match) list. [THESIS]: Helps track the weekly turnover. Newly added candidates indicate fresh institutional attention, while removed candidates represent names losing relative strength. | C36: Compares daily lists against Monday's baseline database: - Added stocks: Highlighted in Soft Blue. - Removed stocks: Listed in the bottom section of Scan Match sheets.

Sheet Leaderboard
A1: 🌟 MULTIBAGGER MOMENTUM & SECTOR ROTATION LEADERBOARD 🌟
A4: TOP PERSISTENT MOMENTUM LEADERS (30D) | J4: SECTOR MOMENTUM VELOCITY HEATMAP (WoW)
A5: Rank | B5: Score | C5: Symbol | D5: Company Name | E5: Sector | F5: Streak (Days) | G5: Market Cap Cr | H5: Classification | J5: Sector Name | K5: Current Wk Count | L5: Previous Wk Count | M5: Velocity WoW %
A6: 1 | B6: 390 | C6: GRANULES | D6: Granules India Limited | E6: healthcare | F6: 50 | G6: 19670.12 | H6: Potential Leader | J6: services | K6: 41 | L6: 20 | M6: 105.0%
A7: 2 | B7: 378 | C7: HONASA | D7: Honasa Consumer Ltd | E7: services | F7: 48 | G7: 13083.12 | H7: Potential Leader | J7: building materials | K7: 34 | L7: 18 | M7: 88.9%
A8: 3 | B8: 366 | C8: ADANIPOWER | D8: Adani Power Limited | E8: power & utilities | F8: 46 | G8: 448407.72 | H8: Potential Leader | J8: textiles | K8: 90 | L8: 51 | M8: 76.5%
A9: 4 | B9: 366 | C9: BLISSGVS | D9: Bliss Gvs Pharma Limited | E9: healthcare | F9: 46 | G9: 4651.01 | H9: Potential Leader | J9: consumer discretionary | K9: 107 | L9: 62 | M9: 72.6%
A10: 5 | B10: 366 | C10: DEEDEV | D10: DEE Development Engineers Ltd | E10: metals & mining | F10: 46 | G10: 4555.45 | H10: Potential Leader | J10: fmcg | K10: 69 | L10: 40 | M10: 72.5%
A11: 6 | B11: 360 | C11: ARVIND | D11: Arvind Limited | E11: textiles | F11: 45 | G11: 12713.87 | H11: Potential Leader | J11: metals & mining | K11: 118 | L11: 69 | M11: 71.0%
A12: 7 | B12: 360 | C12: NITINSPIN | D12: Nitin Spinners Limited | E12: textiles | F12: 45 | G12: 2854.85 | H12: Potential Leader | J12: energy | K12: 41 | L12: 24 | M12: 70.8%
A13: 8 | B13: 360 | C13: RPTECH | D13: Rashi Peripherals Ltd | E13: services | F13: 45 | G13: 3573.41 | H13: Potential Leader | J13: telecom-service | K13: 10 | L13: 6 | M13: 66.7%
A14: 9 | B14: 360 | C14: WELCORP | D14: Welspun Corp Limited | E14: industrials | F14: 45 | G14: 37289.45 | H14: Potential Leader | J14: media | K14: 10 | L14: 6 | M14: 66.7%
A15: 10 | B15: 354 | C15: BAJAJCON | D15: Bajaj Consumer Care Ltd | E15: fmcg | F15: 44 | G15: 7254.54 | H15: Potential Leader | J15: transportation | K15: 16 | L15: 10 | M15: 60.0%
A16: 11 | B16: 354 | C16: STLTECH | D16: Sterlite Technologies Limited | E16: industrials | F16: 44 | G16: 30293.51 | H16: Potential Leader | J16: i.t | K16: 69 | L16: 45 | M16: 53.3%
A17: 12 | B17: 354 | C17: STYLAMIND | D17: Stylam Industries Ltd | E17: building materials | F17: 44 | G17: 5067.13 | H17: Potential Leader | J17: auto | K17: 129 | L17: 85 | M17: 51.8%
... A20: 15 | B20: 342 | C20: ADANIPORTS | D20: Adani Ports And Special Economic Zone Limited | E20: transportation | F20: 42 | G20: 415588.14 | H20: Potential Leader | J20: aerospace & defence | K20: 58 | L20: 39 | M20: 48.7%
A21: 16 | B21: 342 | C21: APCOTEXIND | D21: Apcotex Industries Limited | E21: chemicals | F21: 42 | G21: 2584.21 | H21: Potential Leader
A22: 17 | B22: 342 | C22: CRAFTSMAN | D22: Craftsman Automation Ltd | E22: auto | F22: 42 | G22: 21227.89 | H22: Potential Leader
A23: 18 | B23: 342 | C23: HFCL | D23: HFCL Ltd | E23: telecom | F23: 42 | G23: 30521.74 | H23: Potential Leader
A24: 19 | B24: 342 | C24: SATIN | D24: Satin Creditcare Network Limited | E24: financials | F24: 42 | G24: 2598.83 | H24: Potential Leader
A25: 20 | B25: 342 | C25: SHILPAMED | D25: Shilpa Medicare Limited | E25: healthcare | F25: 42 | G25: 10080.29 | H25: Potential Leader
A28: 🌟 EMERGING LEADERS (MOMENTUM EXPANSION) | J28: 💎 SATELLITE HOLDINGS SHORTLIST (MCAP < 25K CR)
A29: Symbol | B29: Company Name | C29: Sector | D29: Recent Matches (10D) | E29: Historical Matches | F29: Market Cap Cr | J29: Symbol | K29: Sector | L29: Monit Score | M29: Market Cap Cr | N29: Appearances (30D)
A30: TMPV | B30: Tata Motors Passenger Vehicles Ltd | C30: auto | D30: 10 | E30: 1 | F30: 146613.86 | J30: BAJAJCON | K30: fmcg | L30: 297 | M30: 7254.54 | N30: 30
A31: HESTERBIO | B31: Hester Biosciences Limited | C31: healthcare | D31: 10 | E31: 2 | F31: 1664.71 | J31: OMAXAUTO | K31: auto | L31: 293 | M31: 507.54 | N31: 26
A32: ASAHIINDIA | B32: Asahi India Glass Limited | C32: building materials | D32: 10 | E32: 0 | F32: 23032.67 | J32: IBULLSLTD | K32: miscellaneous | L32: 290 | M32: 5655.22 | N32: 25
A33: AVANTEL | B33: Avantel Ltd | C33: aerospace & defence | D33: 10 | E33: 0 | F33: 4668.54 | J33: CONFIPET | K33: miscellaneous | L33: 288 | M33: 2551.28 | N33: 28
A34: MONARCH | B34: Monarch Networth Capital Ltd | C34: financials | D34: 10 | E34: 2 | F34: 2685.61 | J34: FEDFINA | K34: financials | L34: 285 | M34: 5875.41 | N34: 24
A35: KOPRAN | B35: Kopran Limited | C35: healthcare | D35: 10 | E35: 2 | F35: 900.19 | J35: RBLBANK | K35: bank | L35: 285 | M35: 21522.64 | N35: 22
A36: DIAMONDYD | B36: Prataap Snacks Ltd | C36: fmcg | D36: 10 | E36: 0 | F36: 2836.39 | J36: TMB | K36: bank | L36: 285 | M36: 11725.13 | N36: 13
A37: SPECTRUM | B37: Spectrum Electrical Industries Ltd | C37: industrials | D37: 9 | E37: 1 | F37: 2547.37 | J37: GAYAPROJ | K37: realty | L37: 283 | M37: 595.36 | N37: 23
A38: VINCOFE | B38: Vintage Coffee & Beverages Ltd | C38: consumer discretionary | D38: 9 | E38: 0 | F38: 2167.99 | J38: DHANBANK | K38: bank | L38: 282 | M38: 1341.58 | N38: 30
A39: TEGA | B39: Tega Industries Ltd | C39: industrials | D39: 7 | E39: 1 | F39: 13681.51 | J39: VENUSREM | K39: healthcare | L39: 282 | M39: 1980.72 | N39: 17
A40: GUFICBIO | B40: Gufic Biosciences Limited | C40: healthcare | D40: 7 | E40: 0 | F40: 3629.73 | J40: WELINV | K40: financials | L40: 280 | M40: 678.97 | N40: 30
A41: BFINVEST | B41: Bf Investment Limited | C41: financials | D41: 7 | E41: 0 | F41: 1660.39 | J41: INDOBORAX | K41: chemicals | L41: 280 | M41: 1110.63 | N41: 28
A45: 🚀 HIGH MOMENTUM LEADERS (RS RATING >= 90)
A46: Rank | B46: RS Rating | C46: O'Neil Score | D46: Monit Score | E46: Symbol | F46: Company Name | G46: Sector | H46: Market Cap Cr
A47: 1 | B47: 99 | C47: 127.42 | D47: 260 | E47: STLTECH | F47: Sterlite Technologies Limited | G47: industrials | H47: 30293.51
A48: 2 | B48: 99 | C48: 89.41 | D48: 255 | E48: SIGMAADV | F48: Sigma Advanced System Ltd | G48: aerospace & defence | H48: 7699.91
A49: 3 | B49: 98 | C49: 68.45 | D49: 255 | E49: HFCL | F49: HFCL Ltd | G49: telecom | H49: 30521.74
A50: 4 | B50: 98 | C50: 63.52 | D50: 280 | E50: MTARTECH | F50: MTAR Technologies Ltd | G50: aerospace & defence | H50: 22971.26
A51: 5 | B51: 98 | C51: 62.33 | D51: 247 | E51: CUPID | F51: Cupid Limited | G51: fmcg | H51: 17453.7
A52: 6 | B52: 98 | C52: 62.19 | D52: 270 | E52: MODISONLTD | F52: Modison Ltd | G52: industrials | H52: 1067.61
A53: 7 | B53: 97 | C53: 61.02 | D53: 282 | E53: VENUSREM | F53: Venus Remedies Limited | G53: healthcare | H53: 1980.72
A54: 8 | B54: 97 | C54: 60.96 | D54: 285 | E54: VMARCIND | F54: VMARCIND | G54: unknown | H54: 441.28
A55: 9 | B55: 97 | C55: 60.16 | D55: 293 | E55: OMAXAUTO | F55: Omax Autos Limited | G55: auto | H55: 507.54
A56: 10 | B56: 97 | C56: 56.81 | D56: 270 | E56: BHAGYANGR | F56: Bhagyanagar India | G56: power & utilities | H56: 1085.75
A57: 11 | B57: 96 | C57: 55.24 | D57: 272 | E57: BLISSGVS | F57: Bliss Gvs Pharma Limited | G57: healthcare | H57: 4651.01
A58: 12 | B58: 96 | C58: 53.19 | D58: 290 | E58: IBULLSLTD | F58: Indiabulls Limited | G58: miscellaneous | H58: 5655.22
... A81: 35 | B81: 90 | C81: 35.59 | D81: 260 | E81: CEMPRO | F81: Cemindia Projects Ltd | G81: realty | H81: 17606.51

Sheet Chartink Universe
A1: symbol | B1: company | C1: sector | D1: industry | E1: marketcap_bucket | F1: marketcap_cr | G1: close | H1: today_return_pct | I1: volume | J1: bse_code
A2: PANACEABIO | B2: Panacea Biotec Limited | C2: healthcare | D2: pharmaceuticals - indian - bulk drugs & formln | E2: smallcap | F2: 2655.83 | G2: 520.3 | H2: 20 | I2: 3632208 | J2: 531349
A3: MSTCLTD | B3: MSTC Ltd | C3: i.t | D3: trading | E3: smallcap | F3: 3143.01 | G3: 531.85 | H3: 19.13 | I3: 13124225 | J3: 542597
A4: RUBYMILLS | B4: The Ruby Mills Limited | C4: textiles | D4: textiles - composite | E4: smallcap | F4: 949.7 | G4: 336.2 | H4: 18.38 | I4: 1383749 | J4: 503169
A5: THANGAMAYL | B5: Thangamayil Jewellery Limited | C5: consumer discretionary | D5: diamond cutting / jewellery | E5: midcap | F5: 14903.83 | G5: 5520.6 | H5: 15.13 | I5: 1263774 | J5: 533158
A6: RICOAUTO | B6: Rico Auto Industries Limited | C6: auto | D6: auto ancillaries | E6: smallcap | F6: 1573.5 | G6: 131.37 | H6: 12.95 | I6: 44524758 | J6: 520008
A7: YASHO | B7: Yasho Industries Ltd | C7: chemicals | D7: chemicals | E7: smallcap | F7: 2702.12 | G7: 2475.2 | H7: 10.45 | I7: 87457 | J7: 541167
A8: ITDC | B8: India Tourism Development Corporation Ltd | C8: services | D8: hotels | E8: smallcap | F8: 4593.81 | G8: 589.15 | H8: 10 | I8: 357669 | J8: 532189
A9: JNKINDIA | B9: JNK India Ltd | C9: realty | D9: engineering - turnkey services | E9: smallcap | F9: 2144.71 | G9: 421.6 | H9: 9.99 | I9: 912000 | J9: 544167
A10: CEMPRO | B10: Cemindia Projects Ltd | C10: realty | D10: construction | E10: midcap | F10: 17606.51 | G10: 1127.3 | H10: 9.99 | I10: 1435282 | J10: 509496
A11: SOTL | B11: Savita Oil Technologies Limited | C11: energy | D11: petrochemicals | E11: smallcap | F11: 3528.12 | G11: 564.3 | H11: 9.66 | I11: 10971069 | J11: 524667
A12: PSPPROJECT | B12: PSP Projects Ltd | C12: realty | D12: construction | E12: smallcap | F12: 3250.83 | G12: 898.65 | H12: 9.58 | I12: 793302 | J12: 540544
A13: AVALON | B13: Avalon Technologies Ltd | C13: consumer discretionary | D13: electronics - components | E13: midcap | F13: 10120.42 | G13: 1637.7 | H13: 8.04 | I13: 781827 | J13: 543896
... A189: TIINDIA | B189: Tube Investments of India Ltd | C189: industrials | D189: steel - large | E189: largecap | F189: 59424.6 | G189: 3098.4 | H189: 0.92 | I189: 207106 | J189: 540762
A190: ANGELONE | B190: Angel One Ltd | C190: financials | D190: finance & investments | E190: largecap | F190: 30491.01 | G190: 337.7 | H190: 0.88 | I190: 6699518
A191: BIOCON | B191: Biocon Limited | C191: healthcare | D191: pharmaceuticals - indian - bulk drugs & formln | E191: largecap | F191: 66854.34 | G191: 416.05 | H191: 0.87 | I191: 2493074 | J191: 532523
A192: LLOYDSENGG | B192: Lloyds Engineering Works Ltd | C192: industrials | D192: engineering | E192: midcap | F192: 10495.26 | G192: 71.51 | H192: 0.85 | I192: 7197429 | J192: 539992
A193: RML | B193: Rane (madras) Limited | C193: auto | D193: auto ancillaries | E193: smallcap | F193: 2503.23 | G193: 913.35 | H193: 0.84 | I193: 13588 | J193: 532661
A194: NAVINFLUOR | B194: Navin Fluorine International Limited | C194: chemicals | D194: chemicals | E194: largecap | F194: 36055.93 | G194: 7090.5 | H194: 0.78 | I194: 77756 | J194: 532504
A195: RATEGAIN | B195: Rategain Travel Technologies Ltd | C195: i.t | D195: computers - software - medium / small | E195: midcap | F195: 9042.61 | G195: 771 | H195: 0.75 | I195: 451261 | J195: 543417
A196: ZYDUSLIFE | B196: Zydus Lifesciences Ltd | C196: healthcare | D196: pharmaceuticals - indian - bulk drugs & formln | E196: largecap | F196: 108331.15 | G196: 1084.6 | H196: 0.74 | I196: 1016000 | J196: 532321
A197: SKIPPER | B197: Skipper Limited | C197: industrials | D197: engineering | E197: midcap | F197: 6441.18 | G197: 574.65 | H197: 0.73 | I197: 2598018 | J197: 538562
A198: AJAXENGG | B198: Ajax Engineering Ltd | C198: industrials | D198: engineering | E198: midcap | F198: 6824.37 | G198: 600.85 | H198: 0.73 | I198: 50936 | J198: 544356
A199: SOUTHWEST | B199: South West Pinnacle Exploration Ltd | C199: metals & mining | D199: mining / minerals / metals | E199: smallcap | F199: 783.04 | G199: 264.25 | H199: 0.67 | I199: 458761 | J199: 535049
A200: GPTHEALTH | B200: GPT Healthcare Ltd | C200: healthcare | D200: healthcare | E200: smallcap | F200: 1242.64 | G200: 152.43 | H200: 0.65 | I200: 184805 | J200: 544131
A201: KERNEX | B201: Kernex Microsystems (india) Limited | C201: consumer discretionary | D201: electronics - components | E201: smallcap | F201: 3155.33 | G201: 1890.1 | H201: 0.65 | I201: 257159 | J201: 532686
A202: BAJAJCON | B202: Bajaj Consumer Care Ltd | C202: fmcg | D202: personal care - indian | E202: midcap | F202: 7254.54 | G202: 558.8 | H202: 0.61 | I202: 312589 | J202: 533229
... A255: RAINBOW | B255: Rainbow Childrens Medicare Ltd | C255: healthcare | D255: healthcare | E255: midcap | F255: 13753.14 | G255: 1347 | H255: -0.53 | I255: 102088 | J255: 543524
A256: RPTECH | B256: Rashi Peripherals Ltd | C256: services | D256: trading | E256: smallcap | F256: 3573.41 | G256: 539.25 | H256: -0.55 | I256: 159059
A257: ABB | B257: Abb India Limited | C257: industrials | D257: electric equipment | E257: largecap | F257: 152489.27 | G257: 7156 | H257: -0.56 | I257: 298566 | J257: 500002
A258: FIEMIND | B258: Fiem Industries Limited | C258: auto | D258: auto ancillaries | E258: midcap | F258: 6177.22 | G258: 2333.8 | H258: -0.56 | I258: 58528 | J258: 532768
A259: GLAND | B259: Gland Pharma Ltd | C259: healthcare | D259: pharmaceuticals - indian - formulations | E259: largecap | F259: 36778.58 | G259: 2219.5 | H259: -0.57 | I259: 204659 | J259: 543245
A260: CEIGALL | B260: Ceigall India Ltd | C260: realty | D260: construction | E260: midcap | F260: 6281.83 | G260: 358.5 | H260: -0.58 | I260: 805250 | J260: 544223
A261: AEGISLOG | B261: Aegis Logistics Ltd | C261: services | D261: trading | E261: largecap | F261: 26693.55 | G261: 755.8 | H261: -0.62 | I261: 199411 | J261: 500003
A262: LMW | B262: LMW Ltd | C262: industrials | D262: textile machinery | E262: midcap | F262: 16984.9 | G262: 15799 | H262: -0.63 | I262: 2683 | J262: 500252
A263: J&KBANK | B263: The Jammu & Kashmir Bank Limited | C263: bank | D263: banks - private sector | E263: midcap | F263: 16369.08 | G263: 147.68 | H263: -0.65 | I263: 4046091 | J263: 532209
A264: YESBANK | B264: Yes Bank Limited | C264: bank | D264: banks - private sector | E264: largecap | F264: 71950.77 | G264: 22.77 | H264: -0.7 | I264: 77191326 | J264: 532648
A265: STARHEALTH | B265: Star Health & Allied Insurance Company Ltd | C265: financials | D265: finance & investments | E265: largecap | F265: 31188.33 | G265: 526.25 | H265: -0.72 | I265: 222957 | J265: 543412
A266: ADANIPORTS | B266: Adani Ports And Special Economic Zone Limited | C266: transportation | D266: miscellaneous | E266: largecap | F266: 415588.14 | G266: 1790.9 | H266: -0.72 | I266: 1369988 | J266: 532921
A267: HONAUT | B267: Honeywell Automation India Limited | C267: consumer discretionary | D267: electronics - components | E267: largecap | F267: 30724.29 | G267: 34485 | H267: -0.76 | I267: 3125 | J267: 517174
A268: WELCORP | B268: Welspun Corp Limited | C268: industrials | D268: steel - large | E268: largecap | F268: 37289.45 | G268: 1402.7 | H268: -0.77 | I268: 622728 | J268: 532144
... A281: SANDHAR | B281: Sandhar Technologies Limited | C281: auto | D281: auto ancillaries | E281: smallcap | F281: 4323.2 | G281: 711.75 | H281: -0.91 | I281: 1117000 | J281: 541163
A282: NORTHARC | B282: Northern ARC Capital Ltd | C282: financials | D282: finance & investments | E282: smallcap | F282: 4734.86 | G282: 290.3 | H282: -0.94 | I282: 1051408
A283: VBL | B283: Varun Beverages Limited | C283: fmcg | D283: food - processing - indian | E283: largecap | F283: 180400.92 | G283: 528.4 | H283: -0.94 | I283: 2968198 | J283: 540180
A284: VISHNU | B284: Vishnu Chemicals Limited | C284: chemicals | D284: chemicals | E284: smallcap | F284: 4141.91 | G284: 609.45 | H284: -0.95 | I284: 153226 | J284: 516072
A285: NEOGEN | B285: Neogen Chemicals Ltd | C285: chemicals | D285: chemicals | E285: midcap | F285: 5205.8 | G285: 1882.9 | H285: -0.96 | I285: 84433 | J285: 542665
A286: LLOYDSME | B286: Lloyds Metals & Energy Ltd | C286: metals & mining | D286: mining / minerals / metals | E286: largecap | F286: 100896.11 | G286: 1775.5 | H286: -0.97 | I286: 472979 | J286: 512455
A287: ADVENZYMES | B287: Advanced Enzyme Technologies Limited | C287: healthcare | D287: pharmaceuticals - indian - bulk drugs & formln | E287: smallcap | F287: 4256.02 | G287: 376.5 | H287: -0.99 | I287: 84860 | J287: 540025
A288: NINSYS | B288: NINtec Systems Ltd | C288: i.t | D288: computers - software - medium / small | E288: smallcap | F288: 1342.86 | G288: 715.55 | H288: -1.02 | I288: 6835 | J288: 539843
A289: INDOTECH | B289: Indo Tech Transformers Limited | C289: industrials | D289: electric equipment | E289: smallcap | F289: 2986.03 | G289: 2782.8 | H289: -1.03 | I289: 18184 | J289: 532717
A290: PREMIERENE | B290: Premier Energies Ltd | C290: services | D290: trading | E290: largecap | F290: 49331.09 | G290: 1077.8 | H290: -1.03 | I290: 1366622
A291: BANDHANBNK | B291: Bandhan Bank Ltd | C291: bank | D291: banks - private sector | E291: largecap | F291: 33447.01 | G291: 205.44 | H291: -1.05 | I291: 4284782 | J291: 541153
A292: BALAMINES | B292: Balaji Amines Limited | C292: chemicals | D292: chemicals | E292: midcap | F292: 6876.14 | G292: 2099.9 | H292: -1.05 | I292: 487135 | J292: 530999
A293: ADANIPOWER | B293: Adani Power Limited | C293: power & utilities | D293: power generation and supply | E293: largecap | F293: 448407.72 | G293: 230.03 | H293: -1.07 | I293: 23485301 | J293: 533096
A294: TBZ | B294: Tribhovandas Bhimji Zaveri Limited | C294: consumer discretionary | D294: diamond cutting / jewellery | E294: smallcap | F294: 1184.4 | G294: 175.51 | H294: -1.12 | I294: 370294 | J294: 534369
A295: HINDALCO | B295: Hindalco Industries Limited | C295: metals & mining | D295: aluminium and aluminium products | E295: largecap | F295: 255936.63 | G295: 1125.6 | H295: -1.17 | I295: 3868557 | J295: 500440
A296: SILVERTUC | B296: Silver Touch Technologies Ltd | C296: i.t | D296: computers - software - medium / small | E296: smallcap | F296: 2220.82 | G296: 173.08 | H296: -1.17 | I296: 428381 | J296: 535031
A297: HFCL | B297: HFCL Ltd | C297: telecom | D297: cables - telephone | E297: largecap | F297: 30521.74 | G297: 197.08 | H297: -1.17 | I297: 78777077 | J297: 500183
A298: SPORTKING | B298: Sportking India Ltd | C298: textiles | D298: textiles - spinning - synthetic / blended | E298: smallcap | F298: 2318.17 | G298: 180.27 | H298: -1.18 | I298: 442089 | J298: 539221
A299: PRECWIRE | B299: Precision Wires India Limited | C299: metals & mining | D299: mining / minerals / metals | E299: midcap | F299: 7983.22 | G299: 431.4 | H299: -1.21 | I299: 722600 | J299: 523539
A300: PTCIL | B300: PTC Industries Ltd | C300: industrials | D300: castings & forgings | E300: largecap | F300: 28364.4 | G300: 18688 | H300: -1.22 | I300: 24471 | J300: 539006
A301: KOPRAN | B301: Kopran Limited | C301: healthcare | D301: pharmaceuticals - indian - bulk drugs & formln | E301: smallcap | F301: 900.19 | G301: 184.08 | H301: -1.26 | I301: 133592 | J301: 524280
A302: ARVINDFASN | B302: Arvind Fashions Ltd | C302: consumer discretionary | D302: trading | E302: midcap | F302: 6378.02 | G302: 471.1 | H302: -1.28 | I302: 117793 | J302: 542484
... A331: RAIN | B331: Rain Industries Limited | C331: miscellaneous | D331: miscellaneous | E331: midcap | F331: 6742.72 | G331: 195.51 | H331: -2.47 | I331: 6026877 | J331: 500339
A332: DEEDEV | B332: DEE Development Engineers Ltd | C332: metals & mining | D332: steel - medium / small | E332: smallcap | F332: 4555.45 | G332: 639.2 | H332: -2.81 | I332: 213363
A333: SANSTAR | B333: Sanstar Ltd | C333: fmcg | D333: miscellaneous | E333: smallcap | F333: 2155.4 | G333: 114.76 | H333: -2.97 | I333: 378671 | J333: 544217
A334: CENTUM | B334: Centum Electronics Limited | C334: consumer discretionary | D334: electronics - components | E334: midcap | F334: 5291.87 | G334: 3482.6 | H334: -2.99 | I334: 79833 | J334: 517544
A335: IBULLSLTD | B335: Indiabulls Limited | C335: miscellaneous | D335: diversified - medium / small | E335: midcap | F335: 5655.22 | G335: 23.58 | H335: -3.08 | I335: 11394938 | J335: 533520
A336: UFBL | B336: United Foodbrands Ltd | C336: consumer discretionary | D336: hotels | E336: smallcap | F336: 1856.02 | G336: 460 | H336: -3.13 | I336: 124882 | J336: 543283
A337: MAITHANALL | B337: Maithan Alloys Limited | C337: metals & mining | D337: mining / minerals / metals | E337: smallcap | F337: 3117.26 | G337: 1035.8 | H337: -3.27 | I337: 52384 | J337: 590078
A338: SUVEN | B338: Suven Life Sciences Limited | C338: healthcare | D338: miscellaneous | E338: midcap | F338: 7261.55 | G338: 266.35 | H338: -3.27 | I338: 2968995 | J338: 530239
A339: NSLNISP | B339: NMDC Steel Ltd | C339: metals & mining | D339: steel - large | E339: midcap | F339: 15371.03 | G339: 50.72 | H339: -3.3 | I339: 9943384 | J339: 543768
A340: ATHERENERG | B340: Ather Energy Ltd | C340: auto | D340: automobiles - scooters and 3 - wheelers | E340: largecap | F340: 39111.11 | G340: 988.15 | H340: -3.32 | I340: 5992440 | J340: 544397
A341: ICIL | B341: Indo Count Industries Limited | C341: textiles | D341: textiles - cotton/blended | E341: midcap | F341: 6825.94 | G341: 333.1 | H341: -3.35 | I341: 427920 | J341: 521016
A342: CARYSIL | B342: Carysil Ltd | C342: consumer discretionary | D342: domestic appliances | E342: smallcap | F342: 3236.77 | G342: 1095.2 | H342: -3.76 | I342: 249308 | J342: 524091
A343: WELINV | B343: Welspun Investments And Commercials Limited | C343: financials | D343: finance & investments | E343: smallcap | F343: 678.97 | G343: 1773.8 | H343: -4.53 | I343: 33 | J343: 533252
A344: BHAGYANGR | B344: Bhagyanagar India | C344: power & utilities | D344: power generation and supply | E344: smallcap | F344: 1085.75 | G344: 322.75 | H344: -4.89 | I344: 210603 | J344: 512296
A345: FCL | B345: Fineotex Chemical Limited | C345: chemicals | D345: chemicals | E345: midcap | F345: 5070.24 | G345: 41.03 | H345: -5.76 | I345: 20805048 | J345: 533333

Sheet Monit Non Financial
A1: Rank (Non Financial) | B1: Total Score | C1: Symbol | D1: Company | E1: Sector | F1: Industry | G1: Market Cap Bucket | H1: Market Cap Cr | I1: Close | J1: Today Return % | K1: Volume | L1: Relative Strength Rating | M1: Relative Strength Status | N1: Relative Strength Score | O1: Calculated RSI (14) | P1: Calculated ADX (14) | Q1: Calculated V-stop Line | R1: Calculated Near-term Trigger | S1: Sector Benchmark | T1: Benchmark 1Y Return % | U1: Stock 1Y Return % | V1: Relative Strength 1Y (%) | W1: O'Neil Weighted Score | X1: Industry Growth | Y1: Industry Growth Score | Z1: Competitiveness | AA1: Competitiveness Score | AB1: Regulation | AC1: Regulation Score | AD1: Sector Headwinds/Tailwind | AE1: Sector Headwinds/Tailwind Score | AF1: Industry Type | AG1: Industry Type Score | AH1: Margins | AI1: Margins Score | AJ1: Margins Stability | AK1: Margins Stability Score | AL1: Growth | AM1: Growth Score | AN1: Business Type | AO1: Business Type Score | AP1: Near term triggers | AQ1: Near term triggers Score | AR1: Type of Revenue | AS1: Type of Revenue Score | AT1: Capital Allocation | AU1: Capital Allocation Score | AV1: Medium term Growth | AW1: Medium term Growth Score | AX1: ADX | AY1: ADX Score | AZ1: RSI | BA1: RSI Score | BB1: Stage Analysis | BC1: Stage Analysis Score | BD1: Price Volume Action | BE1: Price Volume Action Score | BF1: Secondary Trend | BG1: Secondary Trend Score | BH1: Primary Trend | BI1: Primary Trend Score | BJ1: Resistance | BK1: Resistance Score | BL1: V-stop | BM1: V-stop Score | BN1: PAT Growth | BO1: PAT Growth Score | BP1: Stock History | BQ1: Stock History Score | BR1: PE Ratio | BS1: PE Ratio Score | BT1: PEG Ratio | BU1: PEG Ratio Score | BV1: CFO to EBITDA | BW1: CFO to EBITDA Score | BX1: Debt to Equity | BY1: Debt to Equity Score | BZ1: Auditor Resignation | CA1: Auditor Resignation Score | CB1: Contingent Liability | CC1: Contingent Liability Score | CD1: Pledging | CE1: Pledging Score
A2: =IF(B2=0,"",RANK(B2,$B$2:$B$314,0)) | B2: =SUM(N2,Y2,AA2,AC2,AE2,AG2,AI2,AK2,AM2,AO2,AQ2,AS2,AU2,AW2,AY2,BA2,BC2,BE2,BG2,BI2,BK2,BM2,BO2,BQ2,BS2,BU2,BW2,BY2,CA2,CC2,CE2) | C2: BAJAJCON | D2: Bajaj Consumer Care Ltd | E2: fmcg | F2: personal care - indian | G2: midcap | H2: 7254.54 | I2: 558.8 | J2: 0.61 | K2: 312589 | L2: 91 | M2: Outperforming | N2: =IF(M2="Underperforming",-5,IF(L2>=95,15,IF(L2>=90,10,IF(L2>=80,5,0)))) | O2: 74.91 | P2: 51.77 | Q2: 441.56 | R2: Near 52W High Breakout | S2: Nifty FMCG | T2: -13.6 | U2: 221.06 | V2: 271.57 | W2: 37.53 | X2: Growing Industry | Y2: =IF(X2="Growing Industry",10,IF(X2="Cyclical in an Upturn",5,0)) | Z2: Too Many Players with High ROCE | AA2: =IF(Z2="Monopoly",10,IF(Z2="Oligopoly",5,IF(Z2="Duopoly that cooperate",10,IF(Z2="Duopoly that compete",5,IF(Z2="Too many players with High ROCE",5,0))))) | AB2: No | AC2: =IF(AB2="No",5,0) | AD2: Tailwind | AE2: =IF(AD2="Tailwind",10,0) | AF2: Structural (10 Years Consistency) | AG2: =IF(AF2="Structural (10 Years Consistency)",10,IF(AF2="Shallow Cyclical (2 to 3 years growth)",5,0)) | AH2: No | AI2: =IF(AH2="Yes due to Product Mix change or Operating Leverage",10,IF(AH2="Yes, these are peak margins",-5,IF(AH2="No",5,0))) | AJ2: Stable | AK2: =IF(AJ2="Stable",10,0) | AL2: Yes | AM2: =IF(AL2="Yes",10,0) | AN2: B2C | AO2: =IF(AN2="B2C",10,IF(AN2="B2B",5,0)) | AP2: Yes | AQ2: =IF(AP2="Yes",10,0) | AR2: Higher Annuity, Lower One Time | AS2: =IF(AR2="Fully Annuity",10,IF(AR2="Higher Annuity, Lower One Time",5,IF(AR2="Higher One Time, Lower Annuity",3,0))) | AT2: Good | AU2: =IF(AT2="Good",10,0) | AV2: Yes for more than 2 years | AW2: =IF(AV2="Yes for more than 2 years",10,IF(AV2="Yes only for next 1 to 2 years",5,0)) | AX2: Above 40 | AY2: =IF(AX2="Above 40",20,IF(AX2="20 to 40",10,IF(AX2="0 to 20",-5,0))) | AZ2: Between 50 to 75 | BA2: =IF(AZ2="Between 50 to 75",10,IF(AZ2="Above 75",0,0)) | BB2: Stage 2 | BC2: =IF(BB2="Stage 2",20,IF(BB2="Stage 1",0,IF(BB2="Stage 3",5,IF(BB2="Stage 4",-5,0)))) | BD2: Positive Trend | BE2: =IF(BD2="Positive Trend",20,IF(BD2="Negative Trend",-10,0)) | BF2: Uptrend | BG2: =IF(BF2="Uptrend",10,IF(BF2="Sideways",5,0)) | BH2: Uptrend | BI2: =IF(BH2="Uptrend",10,IF(BH2="Sideways",5,0)) | BJ2: Blue sky scenario | BK2: =IF(BJ2="Overhead supply in last 2 years in last 2 years",-5,IF(BJ2="Close to 52 week high or retracement",5,IF(BJ2="Blue sky scenario",10,IF(BJ2="Long term Downtrend",-10,0)))) | BL2: Yes | BM2: =IF(BL2="Yes",10,0) | BN2: More than 20% | BO2: =IF(BN2="More than 20%",10,IF(BN2="Between 12 to 20%",5,IF(BN2="Less than 12%",0,0))) | BP2: No | BQ2: =IF(BP2="No",10,0) | BR2: No | BS2: =IF(BR2="NO",5,0) | BT2: Above 2 | BU2: =IF(BT2="Above 2",0,IF(BT2="Between 1.5 to 2",5,IF(BT2="Less than 1.5",10,0))) | BV2: Above 70% | BW2: =IF(BV2="Above 70%",10,IF(BV2="Between 50% to 70%",5,IF(BV2="Less than 50%",0,IF(BV2="Negative",-10,IF(BV2="Less than 50% and Borrowings are increasing",-5,0))))) | BX2: Less than 0.7 | BY2: =IF(BX2="More than 1.2",-10,IF(BX2="Between 0.7 to 1.2",0,IF(BX2="Less than 0.7",10,0))) | BZ2: No | CA2: =IF(BZ2="Yes",-10,0) | CB2: Less than 15% | CC2: =IF(CB2="More than 15%",-10,IF(CB2="Less than 15%",10,0)) | CD2: No | CE2: =IF(CD2="Yes, more than 10%",-10,IF(CD2="No",10,0))
A3: =IF(B3=0,"",RANK(B3,$B$2:$B$314,0)) | B3: =SUM(N3,Y3,AA3,AC3,AE3,AG3,AI3,AK3,AM3,AO3,AQ3,AS3,AU3,AW3,AY3,BA3,BC3,BE3,BG3,BI3,BK3,BM3,BO3,BQ3,BS3,BU3,BW3,BY3,CA3,CC3,CE3) | C3: OMAXAUTO | D3: Omax Autos Limited | E3: auto | F3: auto ancillaries | G3: smallcap | H3: 507.54 | I3: 236.98 | J3: -0.13 | K3: 63118 | L3: 97 | M3: Outperforming | N3: =IF(M3="Underperforming",-5,IF(L3>=95,15,IF(L3>=90,10,IF(L3>=80,5,0)))) | O3: 74.13 | P3: 35.13 | Q3: 176.72 | R3: Near 52W High Breakout | S3: Nifty Auto | T3: 10.49 | U3: 165.63 | V3: 140.4 | W3: 60.16 | X3: Growing Industry | Y3: =IF(X3="Growing Industry",10,IF(X3="Cyclical in an Upturn",5,0)) | Z3: Too Many Players with High ROCE | AA3: =IF(Z3="Monopoly",10,IF(Z3="Oligopoly",5,IF(Z3="Duopoly that cooperate",10,IF(Z3="Duopoly that compete",5,IF(Z3="Too many players with High ROCE",5,0))))) | AB3: No | AC3: =IF(AB3="No",5,0) | AD3: Tailwind | AE3: =IF(AD3="Tailwind",10,0) | AF3: Structural (10 Years Consistency) | AG3: =IF(AF3="Structural (10 Years Consistency)",10,IF(AF3="Shallow Cyclical (2 to 3 years growth)",5,0)) | AH3: No | AI3: =IF(AH3="Yes due to Product Mix change or Operating Leverage",10,IF(AH3="Yes, these are peak margins",-5,IF(AH3="No",5,0))) | AJ3: Stable | AK3: =IF(AJ3="Stable",10,0) | AL3: Yes | AM3: =IF(AL3="Yes",10,0) | AN3: B2B | AO3: =IF(AN3="B2C",10,IF(AN3="B2B",5,0)) | AP3: Yes | AQ3: =IF(AP3="Yes",10,0) | AR3: Higher One Time, Lower Annuity | AS3: =IF(AR3="Fully Annuity",10,IF(AR3="Higher Annuity, Lower One Time",5,IF(AR3="Higher One Time, Lower Annuity",3,0))) | AT3: Good | AU3: =IF(AT3="Good",10,0) | AV3: Yes for more than 2 years | AW3: =IF(AV3="Yes for more than 2 years",10,IF(AV3="Yes only for next 1 to 2 years",5,0)) | AX3: 20 to 40 | AY3: =IF(AX3="Above 40",20,IF(AX3="20 to 40",10,IF(AX3="0 to 20",-5,0))) | AZ3: Between 50 to 75 | BA3: =IF(AZ3="Between 50 to 75",10,IF(AZ3="Above 75",0,0)) | BB3: Stage 2 | BC3: =IF(BB3="Stage 2",20,IF(BB3="Stage 1",0,IF(BB3="Stage 3",5,IF(BB3="Stage 4",-5,0)))) | BD3: Positive Trend | BE3: =IF(BD3="Positive Trend",20,IF(BD3="Negative Trend",-10,0)) | BF3: Uptrend | BG3: =IF(BF3="Uptrend",10,IF(BF3="Sideways",5,0)) | BH3: Uptrend | BI3: =IF(BH3="Uptrend",10,IF(BH3="Sideways",5,0)) | BJ3: Blue sky scenario | BK3: =IF(BJ3="Overhead supply in last 2 years in last 2 years",-5,IF(BJ3="Close to 52 week high or retracement",5,IF(BJ3="Blue sky scenario",10,IF(BJ3="Long term Downtrend",-10,0)))) | BL3: Yes | BM3: =IF(BL3="Yes",10,0) | BN3: More than 20% | BO3: =IF(BN3="More than 20%",10,IF(BN3="Between 12 to 20%",5,IF(BN3="Less than 12%",0,0))) | BP3: No | BQ3: =IF(BP3="No",10,0) | BR3: No | BS3: =IF(BR3="NO",5,0) | BT3: Less than 1.5 | BU3: =IF(BT3="Above 2",0,IF(BT3="Between 1.5 to 2",5,IF(BT3="Less than 1.5",10,0))) | BV3: Above 70% | BW3: =IF(BV3="Above 70%",10,IF(BV3="Between 50% to 70%",5,IF(BV3="Less than 50%",0,IF(BV3="Negative",-10,IF(BV3="Less than 50% and Borrowings are increasing",-5,0))))) | BX3: Less than 0.7 | BY3: =IF(BX3="More than 1.2",-10,IF(BX3="Between 0.7 to 1.2",0,IF(BX3="Less than 0.7",10,0))) | BZ3: No | CA3: =IF(BZ3="Yes",-10,0) | CB3: Less than 15% | CC3: =IF(CB3="More than 15%",-10,IF(CB3="Less than 15%",10,0)) | CD3: No | CE3: =IF(CD3="Yes, more than 10%",-10,IF(CD3="No",10,0))
A4: =IF(B4=0,"",RANK(B4,$B$2:$B$314,0)) | B4: =SUM(N4,Y4,AA4,AC4,AE4,AG4,AI4,AK4,AM4,AO4,AQ4,AS4,AU4,AW4,AY4,BA4,BC4,BE4,BG4,BI4,BK4,BM4,BO4,BQ4,BS4,BU4,BW4,BY4,CA4,CC4,CE4) | C4: CONFIPET | D4: Confidence Petroleum India Ltd | E4: miscellaneous | F4: miscellaneous | G4: smallcap | H4: 2551.28 | I4: 76.89 | J4: 0.13 | K4: 7910840 | L4: 95 | M4: Outperforming | N4: =IF(M4="Underperforming",-5,IF(L4>=95,15,IF(L4>=90,10,IF(L4>=80,5,0)))) | O4: 78.6 | P4: 46.05 | Q4: 52.09 | R4: Near 52W High Breakout | S4: Nifty 50 | T4: -6.35 | U4: 29.26 | V4: 38.02 | W4: 51.11 | X4: Growing Industry | Y4: =IF(X4="Growing Industry",10,IF(X4="Cyclical in an Upturn",5,0)) | Z4: Too Many Players with High ROCE | AA4: =IF(Z4="Monopoly",10,IF(Z4="Oligopoly",5,IF(Z4="Duopoly that cooperate",10,IF(Z4="Duopoly that compete",5,IF(Z4="Too many players with High ROCE",5,0))))) | AB4: No | AC4: =IF(AB4="No",5,0) | AD4: Tailwind | AE4: =IF(AD4="Tailwind",10,0) | AF4: Structural (10 Years Consistency) | AG4: =IF(AF4="Structural (10 Years Consistency)",10,IF(AF4="Shallow Cyclical (2 to 3 years growth)",5,0)) | AH4: No | AI4: =IF(AH4="Yes due to Product Mix change or Operating Leverage",10,IF(AH4="Yes, these are peak margins",-5,IF(AH4="No",5,0))) | AJ4: Stable | AK4: =IF(AJ4="Stable",10,0) | AL4: Yes | AM4: =IF(AL4="Yes",10,0) | AN4: B2B | AO4: =IF(AN4="B2C",10,IF(AN4="B2B",5,0)) | AP4: Yes | AQ4: =IF(AP4="Yes",10,0) | AR4: Higher One Time, Lower Annuity | AS4: =IF(AR4="Fully Annuity",10,IF(AR4="Higher Annuity, Lower One Time",5,IF(AR4="Higher One Time, Lower Annuity",3,0))) | AT4: Good | AU4: =IF(AT4="Good",10,0) | AV4: Yes for more than 2 years | AW4: =IF(AV4="Yes for more than 2 years",10,IF(AV4="Yes only for next 1 to 2 years",5,0)) | AX4: Above 40 | AY4: =IF(AX4="Above 40",20,IF(AX4="20 to 40",10,IF(AX4="0 to 20",-5,0))) | AZ4: Above 75 | BA4: =IF(AZ4="Between 50 to 75",10,IF(AZ4="Above 75",0,0)) | BB4: Stage 2 | BC4: =IF(BB4="Stage 2",20,IF(BB4="Stage 1",0,IF(BB4="Stage 3",5,IF(BB4="Stage 4",-5,0)))) | BD4: Positive Trend | BE4: =IF(BD4="Positive Trend",20,IF(BD4="Negative Trend",-10,0)) | BF4: Uptrend | BG4: =IF(BF4="Uptrend",10,IF(BF4="Sideways",5,0)) | BH4: Uptrend | BI4: =IF(BH4="Uptrend",10,IF(BH4="Sideways",5,0)) | BJ4: Close to 52 week high or retracement | BK4: =IF(BJ4="Overhead supply in last 2 years in last 2 years",-5,IF(BJ4="Close to 52 week high or retracement",5,IF(BJ4="Blue sky scenario",10,IF(BJ4="Long term Downtrend",-10,0)))) | BL4: Yes | BM4: =IF(BL4="Yes",10,0) | BN4: More than 20% | BO4: =IF(BN4="More than 20%",10,IF(BN4="Between 12 to 20%",5,IF(BN4="Less than 12%",0,0))) | BP4: No | BQ4: =IF(BP4="No",10,0) | BR4: No | BS4: =IF(BR4="NO",5,0) | BT4: Less than 1.5 | BU4: =IF(BT4="Above 2",0,IF(BT4="Between 1.5 to 2",5,IF(BT4="Less than 1.5",10,0))) | BV4: Above 70% | BW4: =IF(BV4="Above 70%",10,IF(BV4="Between 50% to 70%",5,IF(BV4="Less than 50%",0,IF(BV4="Negative",-10,IF(BV4="Less than 50% and Borrowings are increasing",-5,0))))) | BX4: Less than 0.7 | BY4: =IF(BX4="More than 1.2",-10,IF(BX4="Between 0.7 to 1.2",0,IF(BX4="Less than 0.7",10,0))) | BZ4: No | CA4: =IF(BZ4="Yes",-10,0) | CB4: Less than 15% | CC4: =IF(CB4="More than 15%",-10,IF(CB4="Less than 15%",10,0)) | CD4: No | CE4: =IF(CD4="Yes, more than 10%",-10,IF(CD4="No",10,0))
A5: =IF(B5=0,"",RANK(B5,$B$2:$B$314,0)) | B5: =SUM(N5,Y5,AA5,AC5,AE5,AG5,AI5,AK5,AM5,AO5,AQ5,AS5,AU5,AW5,AY5,BA5,BC5,BE5,BG5,BI5,BK5,BM5,BO5,BQ5,BS5,BU5,BW5,BY5,CA5,CC5,CE5) | C5: IBULLSLTD | D5: Indiabulls Limited | E5: miscellaneous | F5: diversified - medium / small | G5: midcap | H5: 5655.22 | I5: 23.58 | J5: -3.08 | K5: 11394938 | L5: 96 | M5: Outperforming | N5: =IF(M5="Underperforming",-5,IF(L5>=95,15,IF(L5>=90,10,IF(L5>=80,5,0)))) | O5: 72.16 | P5: 35.91 | Q5: 16.54 | R5: Near 52W High Breakout | S5: Nifty 50 | T5: -6.35 | U5: 49.9 | V5: 60.06 | W5: 53.19 | X5: Growing Industry | Y5: =IF(X5="Growing Industry",10,IF(X5="Cyclical in an Upturn",5,0)) | Z5: Too Many Players with High ROCE | AA5: =IF(Z5="Monopoly",10,IF(Z5="Oligopoly",5,IF(Z5="Duopoly that cooperate",10,IF(Z5="Duopoly that compete",5,IF(Z5="Too many players with High ROCE",5,0))))) | AB5: No | AC5: =IF(AB5="No",5,0) | AD5: Tailwind | AE5: =IF(AD5="Tailwind",10,0) | AF5: Structural (10 Years Consistency) | AG5: =IF(AF5="Structural (10 Years Consistency)",10,IF(AF5="Shallow Cyclical (2 to 3 years growth)",5,0)) | AH5: No | AI5: =IF(AH5="Yes due to Product Mix change or Operating Leverage",10,IF(AH5="Yes, these are peak margins",-5,IF(AH5="No",5,0))) | AJ5: Stable | AK5: =IF(AJ5="Stable",10,0) | AL5: Yes | AM5: =IF(AL5="Yes",10,0) | AN5: B2B | AO5: =IF(AN5="B2C",10,IF(AN5="B2B",5,0)) | AP5: Yes | AQ5: =IF(AP5="Yes",10,0) | AR5: Higher One Time, Lower Annuity | AS5: =IF(AR5="Fully Annuity",10,IF(AR5="Higher Annuity, Lower One Time",5,IF(AR5="Higher One Time, Lower Annuity",3,0))) | AT5: Good | AU5: =IF(AT5="Good",10,0) | AV5: Yes for more than 2 years | AW5: =IF(AV5="Yes for more than 2 years",10,IF(AV5="Yes only for next 1 to 2 years",5,0)) | AX5: 20 to 40 | AY5: =IF(AX5="Above 40",20,IF(AX5="20 to 40",10,IF(AX5="0 to 20",-5,0))) | AZ5: Between 50 to 75 | BA5: =IF(AZ5="Between 50 to 75",10,IF(AZ5="Above 75",0,0)) | BB5: Stage 2 | BC5: =IF(BB5="Stage 2",20,IF(BB5="Stage 1",0,IF(BB5="Stage 3",5,IF(BB5="Stage 4",-5,0)))) | BD5: Positive Trend | BE5: =IF(BD5="Positive Trend",20,IF(BD5="Negative Trend",-10,0)) | BF5: Uptrend | BG5: =IF(BF5="Uptrend",10,IF(BF5="Sideways",5,0)) | BH5: Uptrend | BI5: =IF(BH5="Uptrend",10,IF(BH5="Sideways",5,0)) | BJ5: Blue sky scenario | BK5: =IF(BJ5="Overhead supply in last 2 years in last 2 years",-5,IF(BJ5="Close to 52 week high or retracement",5,IF(BJ5="Blue sky scenario",10,IF(BJ5="Long term Downtrend",-10,0)))) | BL5: Yes | BM5: =IF(BL5="Yes",10,0) | BN5: More than 20% | BO5: =IF(BN5="More than 20%",10,IF(BN5="Between 12 to 20%",5,IF(BN5="Less than 12%",0,0))) | BP5: No | BQ5: =IF(BP5="No",10,0) | BR5: No | BS5: =IF(BR5="NO",5,0) | BT5: Less than 1.5 | BU5: =IF(BT5="Above 2",0,IF(BT5="Between 1.5 to 2",5,IF(BT5="Less than 1.5",10,0))) | BV5: Between 50% to 70% | BW5: =IF(BV5="Above 70%",10,IF(BV5="Between 50% to 70%",5,IF(BV5="Less than 50%",0,IF(BV5="Negative",-10,IF(BV5="Less than 50% and Borrowings are increasing",-5,0))))) | BX5: Less than 0.7 | BY5: =IF(BX5="More than 1.2",-10,IF(BX5="Between 0.7 to 1.2",0,IF(BX5="Less than 0.7",10,0))) | BZ5: No | CA5: =IF(BZ5="Yes",-10,0) | CB5: Less than 15% | CC5: =IF(CB5="More than 15%",-10,IF(CB5="Less than 15%",10,0)) | CD5: No | CE5: =IF(CD5="Yes, more than 10%",-10,IF(CD5="No",10,0))
A6: =IF(B6=0,"",RANK(B6,$B$2:$B$314,0)) | B6: =SUM(N6,Y6,AA6,AC6,AE6,AG6,AI6,AK6,AM6,AO6,AQ6,AS6,AU6,AW6,AY6,BA6,BC6,BE6,BG6,BI6,BK6,BM6,BO6,BQ6,BS6,BU6,BW6,BY6,CA6,CC6,CE6) | C6: GAYAPROJ | D6: Gayatri Projects Limited | E6: realty | F6: construction | G6: smallcap | H6: 595.36 | I6: 20.9 | J6: 3.98 | K6: 779784 | L6: 89 | M6: Outperforming | N6: =IF(M6="Underperforming",-5,IF(L6>=95,15,IF(L6>=90,10,IF(L6>=80,5,0)))) | O6: 73.63 | P6: 62.92 | Q6: 16.78 | R6: Volume Spike & Near 52W High Breakout | S6: Nifty Realty | T6: -26.45 | U6: 144.73 | V6: 232.75 | W6: 34.94 | X6: Growing Industry | Y6: =IF(X6="Growing Industry",10,IF(X6="Cyclical in an Upturn",5,0)) | Z6: Too Many Players with High ROCE | AA6: =IF(Z6="Monopoly",10,IF(Z6="Oligopoly",5,IF(Z6="Duopoly that cooperate",10,IF(Z6="Duopoly that compete",5,IF(Z6="Too many players with High ROCE",5,0))))) | AB6: No | AC6: =IF(AB6="No",5,0) | AD6: Tailwind | AE6: =IF(AD6="Tailwind",10,0) | AF6: Structural (10 Years Consistency) | AG6: =IF(AF6="Structural (10 Years Consistency)",10,IF(AF6="Shallow Cyclical (2 to 3 years growth)",5,0)) | AH6: No | AI6: =IF(AH6="Yes due to Product Mix change or Operating Leverage",10,IF(AH6="Yes, these are peak margins",-5,IF(AH6="No",5,0))) | AJ6: Stable | AK6: =IF(AJ6="Stable",10,0) | AL6: Yes | AM6: =IF(AL6="Yes",10,0) | AN6: B2B | AO6: =IF(AN6="B2C",10,IF(AN6="B2B",5,0)) | AP6: Yes | AQ6: =IF(AP6="Yes",10,0) | AR6: Higher One Time, Lower Annuity | AS6: =IF(AR6="Fully Annuity",10,IF(AR6="Higher Annuity, Lower One Time",5,IF(AR6="Higher One Time, Lower Annuity",3,0))) | AT6: Good | AU6: =IF(AT6="Good",10,0) | AV6: Yes for more than 2 years | AW6: =IF(AV6="Yes for more than 2 years",10,IF(AV6="Yes only for next 1 to 2 years",5,0)) | AX6: Above 40 | AY6: =IF(AX6="Above 40",20,IF(AX6="20 to 40",10,IF(AX6="0 to 20",-5,0))) | AZ6: Between 50 to 75 | BA6: =IF(AZ6="Between 50 to 75",10,IF(AZ6="Above 75",0,0)) | BB6: Stage 2 | BC6: =IF(BB6="Stage 2",20,IF(BB6="Stage 1",0,IF(BB6="Stage 3",5,IF(BB6="Stage 4",-5,0)))) | BD6: Positive Trend | BE6: =IF(BD6="Positive Trend",20,IF(BD6="Negative Trend",-10,0)) | BF6: Uptrend | BG6: =IF(BF6="Uptrend",10,IF(BF6="Sideways",5,0)) | BH6: Uptrend | BI6: =IF(BH6="Uptrend",10,IF(BH6="Sideways",5,0)) | BJ6: Blue sky scenario | BK6: =IF(BJ6="Overhead supply in last 2 years in last 2 years",-5,IF(BJ6="Close to 52 week high or retracement",5,IF(BJ6="Blue sky scenario",10,IF(BJ6="Long term Downtrend",-10,0)))) | BL6: Yes | BM6: =IF(BL6="Yes",10,0) | BN6: More than 20% | BO6: =IF(BN6="More than 20%",10,IF(BN6="Between 12 to 20%",5,IF(BN6="Less than 12%",0,0))) | BP6: No | BQ6: =IF(BP6="No",10,0) | BR6: No | BS6: =IF(BR6="NO",5,0) | BT6: Above 2 | BU6: =IF(BT6="Above 2",0,IF(BT6="Between 1.5 to 2",5,IF(BT6="Less than 1.5",10,0))) | BV6: Above 70% | BW6: =IF(BV6="Above 70%",10,IF(BV6="Between 50% to 70%",5,IF(BV6="Less than 50%",0,IF(BV6="Negative",-10,IF(BV6="Less than 50% and Borrowings are increasing",-5,0))))) | BX6: Less than 0.7 | BY6: =IF(BX6="More than 1.2",-10,IF(BX6="Between 0.7 to 1.2",0,IF(BX6="Less than 0.7",10,0))) | BZ6: No | CA6: =IF(BZ6="Yes",-10,0) | CB6: Less than 15% | CC6: =IF(CB6="More than 15%",-10,IF(CB6="Less than 15%",10,0)) | CD6: No | CE6: =IF(CD6="Yes, more than 10%",-10,IF(CD6="No",10,0))
A7: =IF(B7=0,"",RANK(B7,$B$2:$B$314,0)) | B7: =SUM(N7,Y7,AA7,AC7,AE7,AG7,AI7,AK7,AM7,AO7,AQ7,AS7,AU7,AW7,AY7,BA7,BC7,BE7,BG7,BI7,BK7,BM7,BO7,BQ7,BS7,BU7,BW7,BY7,CA7,CC7,CE7) | C7: VENUSREM | D7: Venus Remedies Limited | E7: healthcare | F7: pharmaceuticals - indian - formulations | G7: smallcap | H7: 1980.72 | I7: 1555.8 | J7: 4.99 | K7: 282923 | L7: 97 | M7: Outperforming | N7: =IF(M7="Underperforming",-5,IF(L7>=95,15,IF(L7>=90,10,IF(L7>=80,5,0)))) | O7: 79.06 | P7: 45.62 | Q7: 1173.22 | R7: Volume Spike & Near 52W High Breakout | S7: Nifty Pharma | T7: 11.5 | U7: 261.81 | V7: 224.5 | W7: 61.02 | X7: Growing Industry | Y7: =IF(X7="Growing Industry",10,IF(X7="Cyclical in an Upturn",5,0)) | Z7: Too Many Players with High ROCE | AA7: =IF(Z7="Monopoly",10,IF(Z7="Oligopoly",5,IF(Z7="Duopoly that cooperate",10,IF(Z7="Duopoly that compete",5,IF(Z7="Too many players with High ROCE",5,0))))) | AB7: Yes | AC7: =IF(AB7="No",5,0) | AD7: Tailwind | AE7: =IF(AD7="Tailwind",10,0) | AF7: Structural (10 Years Consistency) | AG7: =IF(AF7="Structural (10 Years Consistency)",10,IF(AF7="Shallow Cyclical (2 to 3 years growth)",5,0)) | AH7: No | AI7: =IF(AH7="Yes due to Product Mix change or Operating Leverage",10,IF(AH7="Yes, these are peak margins",-5,IF(AH7="No",5,0))) | AJ7: Stable | AK7: =IF(AJ7="Stable",10,0) | AL7: Yes | AM7: =IF(AL7="Yes",10,0) | AN7: B2B | AO7: =IF(AN7="B2C",10,IF(AN7="B2B",5,0)) | AP7: Yes | AQ7: =IF(AP7="Yes",10,0) | AR7: Higher Annuity, Lower One Time | AS7: =IF(AR7="Fully Annuity",10,IF(AR7="Higher Annuity, Lower One Time",5,IF(AR7="Higher One Time, Lower Annuity",3,0))) | AT7: Good | AU7: =IF(AT7="Good",10,0) | AV7: Yes for more than 2 years | AW7: =IF(AV7="Yes for more than 2 years",10,IF(AV7="Yes only for next 1 to 2 years",5,0)) | AX7: Above 40 | AY7: =IF(AX7="Above 40",20,IF(AX7="20 to 40",10,IF(AX7="0 to 20",-5,0))) | AZ7: Above 75 | BA7: =IF(AZ7="Between 50 to 75",10,IF(AZ7="Above 75",0,0)) | BB7: Stage 2 | BC7: =IF(BB7="Stage 2",20,IF(BB7="Stage 1",0,IF(BB7="Stage 3",5,IF(BB7="Stage 4",-5,0)))) | BD7: Positive Trend | BE7: =IF(BD7="Positive Trend",20,IF(BD7="Negative Trend",-10,0)) | BF7: Uptrend | BG7: =IF(BF7="Uptrend",10,IF(BF7="Sideways",5,0)) | BH7: Uptrend | BI7: =IF(BH7="Uptrend",10,IF(BH7="Sideways",5,0)) | BJ7: Blue sky scenario | BK7: =IF(BJ7="Overhead supply in last 2 years in last 2 years",-5,IF(BJ7="Close to 52 week high or retracement",5,IF(BJ7="Blue sky scenario",10,IF(BJ7="Long term Downtrend",-10,0)))) | BL7: Yes | BM7: =IF(BL7="Yes",10,0) | BN7: More than 20% | BO7: =IF(BN7="More than 20%",10,IF(BN7="Between 12 to 20%",5,IF(BN7="Less than 12%",0,0))) | BP7: No | BQ7: =IF(BP7="No",10,0) | BR7: No | BS7: =IF(BR7="NO",5,0) | BT7: Above 2 | BU7: =IF(BT7="Above 2",0,IF(BT7="Between 1.5 to 2",5,IF(BT7="Less than 1.5",10,0))) | BV7: Above 70% | BW7: =IF(BV7="Above 70%",10,IF(BV7="Between 50% to 70%",5,IF(BV7="Less than 50%",0,IF(BV7="Negative",-10,IF(BV7="Less than 50% and Borrowings are increasing",-5,0))))) | BX7: Less than 0.7 | BY7: =IF(BX7="More than 1.2",-10,IF(BX7="Between 0.7 to 1.2",0,IF(BX7="Less than 0.7",10,0))) | BZ7: No | CA7: =IF(BZ7="Yes",-10,0) | CB7: Less than 15% | CC7: =IF(CB7="More than 15%",-10,IF(CB7="Less than 15%",10,0)) | CD7: No | CE7: =IF(CD7="Yes, more than 10%",-10,IF(CD7="No",10,0))
A8: =IF(B8=0,"",RANK(B8,$B$2:$B$314,0)) | B8: =SUM(N8,Y8,AA8,AC8,AE8,AG8,AI8,AK8,AM8,AO8,AQ8,AS8,AU8,AW8,AY8,BA8,BC8,BE8,BG8,BI8,BK8,BM8,BO8,BQ8,BS8,BU8,BW8,BY8,CA8,CC8,CE8) | C8: EMCURE | D8: Emcure Pharmaceuticals Ltd | E8: healthcare | F8: pharmaceuticals - indian - bulk drugs & formln | G8: largecap | H8: 32243.49 | I8: 1745.2 | J8: 2.62 | K8: 173206 | L8: 39 | M8: Outperforming | N8: =IF(M8="Underperforming",-5,IF(L8>=95,15,IF(L8>=90,10,IF(L8>=80,5,0)))) | O8: 65.05 | P8: 40.31 | Q8: 1367.39 | R8: Near 52W High Breakout | S8: Nifty Pharma | T8: 11.5 | U8: 31.75 | V8: 18.16 | W8: 10.65 | X8: Growing Industry | Y8: =IF(X8="Growing Industry",10,IF(X8="Cyclical in an Upturn",5,0)) | Z8: Too Many Players with High ROCE | AA8: =IF(Z8="Monopoly",10,IF(Z8="Oligopoly",5,IF(Z8="Duopoly that cooperate",10,IF(Z8="Duopoly that compete",5,IF(Z8="Too many players with High ROCE",5,0))))) | AB8: Yes | AC8: =IF(AB8="No",5,0) | AD8: Tailwind | AE8: =IF(AD8="Tailwind",10,0) | AF8: Structural (10 Years Consistency) | AG8: =IF(AF8="Structural (10 Years Consistency)",10,IF(AF8="Shallow Cyclical (2 to 3 years growth)",5,0)) | AH8: No | AI8: =IF(AH8="Yes due to Product Mix change or Operating Leverage",10,IF(AH8="Yes, these are peak margins",-5,IF(AH8="No",5,0))) | AJ8: Stable | AK8: =IF(AJ8="Stable",10,0) | AL8: Yes | AM8: =IF(AL8="Yes",10,0) | AN8: B2B | AO8: =IF(AN8="B2C",10,IF(AN8="B2B",5,0)) | AP8: Yes | AQ8: =IF(AP8="Yes",10,0) | AR8: Higher Annuity, Lower One Time | AS8: =IF(AR8="Fully Annuity",10,IF(AR8="Higher Annuity, Lower One Time",5,IF(AR8="Higher One Time, Lower Annuity",3,0))) | AT8: Good | AU8: =IF(AT8="Good",10,0) | AV8: Yes for more than 2 years | AW8: =IF(AV8="Yes for more than 2 years",10,IF(AV8="Yes only for next 1 to 2 years",5,0)) | AX8: Above 40 | AY8: =IF(AX8="Above 40",20,IF(AX8="20 to 40",10,IF(AX8="0 to 20",-5,0))) | AZ8: Between 50 to 75 | BA8: =IF(AZ8="Between 50 to 75",10,IF(AZ8="Above 75",0,0)) | BB8: Stage 2 | BC8: =IF(BB8="Stage 2",20,IF(BB8="Stage 1",0,IF(BB8="Stage 3",5,IF(BB8="Stage 4",-5,0)))) | BD8: Positive Trend | BE8: =IF(BD8="Positive Trend",20,IF(BD8="Negative Trend",-10,0)) | BF8: Uptrend | BG8: =IF(BF8="Uptrend",10,IF(BF8="Sideways",5,0)) | BH8: Uptrend | BI8: =IF(BH8="Uptrend",10,IF(BH8="Sideways",5,0)) | BJ8: Blue sky scenario | BK8: =IF(BJ8="Overhead supply in last 2 years in last 2 years",-5,IF(BJ8="Close to 52 week high or retracement",5,IF(BJ8="Blue sky scenario",10,IF(BJ8="Long term Downtrend",-10,0)))) | BL8: Yes | BM8: =IF(BL8="Yes",10,0) | BN8: More than 20% | BO8: =IF(BN8="More than 20%",10,IF(BN8="Between 12 to 20%",5,IF(BN8="Less than 12%",0,0))) | BP8: No | BQ8: =IF(BP8="No",10,0) | BR8: No | BS8: =IF(BR8="NO",5,0) | BT8: Less than 1.5 | BU8: =IF(BT8="Above 2",0,IF(BT8="Between 1.5 to 2",5,IF(BT8="Less than 1.5",10,0))) | BV8: Between 50% to 70% | BW8: =IF(BV8="Above 70%",10,IF(BV8="Between 50% to 70%",5,IF(BV8="Less than 50%",0,IF(BV8="Negative",-10,IF(BV8="Less than 50% and Borrowings are increasing",-5,0))))) | BX8: Less than 0.7 | BY8: =IF(BX8="More than 1.2",-10,IF(BX8="Between 0.7 to 1.2",0,IF(BX8="Less than 0.7",10,0))) | BZ8: No | CA8: =IF(BZ8="Yes",-10,0) | CB8: Less than 15% | CC8: =IF(CB8="More than 15%",-10,IF(CB8="Less than 15%",10,0)) | CD8: No | CE8: =IF(CD8="Yes, more than 10%",-10,IF(CD8="No",10,0))
A9: =IF(B9=0,"",RANK(B9,$B$2:$B$314,0)) | B9: =SUM(N9,Y9,AA9,AC9,AE9,AG9,AI9,AK9,AM9,AO9,AQ9,AS9,AU9,AW9,AY9,BA9,BC9,BE9,BG9,BI9,BK9,BM9,BO9,BQ9,BS9,BU9,BW9,BY9,CA9,CC9,CE9) | C9: RADICO | D9: Radico Khaitan Limited | E9: fmcg | F9: breweries & distilleries | G9: largecap | H9: 46383.58 | I9: 3502.4 | J9: 1.11 | K9: 247899 | L9: 45 | M9: Outperforming | N9: =IF(M9="Underperforming",-5,IF(L9>=95,15,IF(L9>=90,10,IF(L9>=80,5,0)))) | O9: 67.71 | P9: 30.24 | Q9: 2879.89 | R9: Near 52W High Breakout | S9: Nifty FMCG | T9: -13.6 | U9: 33.34 | V9: 54.33 | W9: 12.11 | X9: Growing Industry | Y9: =IF(X9="Growing Industry",10,IF(X9="Cyclical in an Upturn",5,0)) | Z9: Too Many Players with High ROCE | AA9: =IF(Z9="Monopoly",10,IF(Z9="Oligopoly",5,IF(Z9="Duopoly that cooperate",10,IF(Z9="Duopoly that compete",5,IF(Z9="Too many players with High ROCE",5,0))))) | AB9: No | AC9: =IF(AB9="No",5,0) | AD9: Tailwind | AE9: =IF(AD9="Tailwind",10,0) | AF9: Structural (10 Years Consistency) | AG9: =IF(AF9="Structural (10 Years Consistency)",10,IF(AF9="Shallow Cyclical (2 to 3 years growth)",5,0)) | AH9: No | AI9: =IF(AH9="Yes due to Product Mix change or Operating Leverage",10,IF(AH9="Yes, these are peak margins",-5,IF(AH9="No",5,0))) | AJ9: Stable | AK9: =IF(AJ9="Stable",10,0) | AL9: Yes | AM9: =IF(AL9="Yes",10,0) | AN9: B2C | AO9: =IF(AN9="B2C",10,IF(AN9="B2B",5,0)) | AP9: Yes | AQ9: =IF(AP9="Yes",10,0) | AR9: Higher Annuity, Lower One Time | AS9: =IF(AR9="Fully Annuity",10,IF(AR9="Higher Annuity, Lower One Time",5,IF(AR9="Higher One Time, Lower Annuity",3,0))) | AT9: Good | AU9: =IF(AT9="Good",10,0) | AV9: Yes for more than 2 years | AW9: =IF(AV9="Yes for more than 2 years",10,IF(AV9="Yes only for next 1 to 2 years",5,0)) | AX9: 20 to 40 | AY9: =IF(AX9="Above 40",20,IF(AX9="20 to 40",10,IF(AX9="0 to 20",-5,0))) | AZ9: Between 50 to 75 | BA9: =IF(AZ9="Between 50 to 75",10,IF(AZ9="Above 75",0,0)) | BB9: Stage 2 | BC9: =IF(BB9="Stage 2",20,IF(BB9="Stage 1",0,IF(BB9="Stage 3",5,IF(BB9="Stage 4",-5,0)))) | BD9: Positive Trend | BE9: =IF(BD9="Positive Trend",20,IF(BD9="Negative Trend",-10,0)) | BF9: Uptrend | BG9: =IF(BF9="Uptrend",10,IF(BF9="Sideways",5,0)) | BH9: Uptrend | BI9: =IF(BH9="Uptrend",10,IF(BH9="Sideways",5,0)) | BJ9: Blue sky scenario | BK9: =IF(BJ9="Overhead supply in last 2 years in last 2 years",-5,IF(BJ9="Close to 52 week high or retracement",5,IF(BJ9="Blue sky scenario",10,IF(BJ9="Long term Downtrend",-10,0)))) | BL9: Yes | BM9: =IF(BL9="Yes",10,0) | BN9: More than 20% | BO9: =IF(BN9="More than 20%",10,IF(BN9="Between 12 to 20%",5,IF(BN9="Less than 12%",0,0))) | BP9: No | BQ9: =IF(BP9="No",10,0) | BR9: Yes | BS9: =IF(BR9="NO",5,0) | BT9: Less than 1.5 | BU9: =IF(BT9="Above 2",0,IF(BT9="Between 1.5 to 2",5,IF(BT9="Less than 1.5",10,0))) | BV9: Above 70% | BW9: =IF(BV9="Above 70%",10,IF(BV9="Between 50% to 70%",5,IF(BV9="Less than 50%",0,IF(BV9="Negative",-10,IF(BV9="Less than 50% and Borrowings are increasing",-5,0))))) | BX9: Less than 0.7 | BY9: =IF(BX9="More than 1.2",-10,IF(BX9="Between 0.7 to 1.2",0,IF(BX9="Less than 0.7",10,0))) | BZ9: No | CA9: =IF(BZ9="Yes",-10,0) | CB9: Less than 15% | CC9: =IF(CB9="More than 15%",-10,IF(CB9="Less than 15%",10,0)) | CD9: No | CE9: =IF(CD9="Yes, more than 10%",-10,IF(CD9="No",10,0))
A10: =IF(B10=0,"",RANK(B10,$B$2:$B$314,0)) | B10: =SUM(N10,Y10,AA10,AC10,AE10,AG10,AI10,AK10,AM10,AO10,AQ10,AS10,AU10,AW10,AY10,BA10,BC10,BE10,BG10,BI10,BK10,BM10,BO10,BQ10,BS10,BU10,BW10,BY10,CA10,CC10,CE10) | C10: MTARTECH | D10: MTAR Technologies Ltd | E10: aerospace & defence | F10: engineering | G10: largecap | H10: 22971.26 | I10: 7755.5 | J10: 3.85 | K10: 1275473 | L10: 98 | M10: Outperforming | N10: =IF(M10="Underperforming",-5,IF(L10>=95,15,IF(L10>=90,10,IF(L10>=80,5,0)))) | O10: 85.85 | P10: 64.1 | Q10: 5930.54 | R10: Near 52W High Breakout | S10: Nifty 50 | T10: -6.35 | U10: 337.99 | V10: 367.67 | W10: 63.52 | X10: Growing Industry | Y10: =IF(X10="Growing Industry",10,IF(X10="Cyclical in an Upturn",5,0)) | Z10: Too Many Players with High ROCE | AA10: =IF(Z10="Monopoly",10,IF(Z10="Oligopoly",5,IF(Z10="Duopoly that cooperate",10,IF(Z10="Duopoly that compete",5,IF(Z10="Too many players with High ROCE",5,0))))) | AB10: No | AC10: =IF(AB10="No",5,0) | AD10: Tailwind | AE10: =IF(AD10="Tailwind",10,0) | AF10: Structural (10 Years Consistency) | AG10: =IF(AF10="Structural (10 Years Consistency)",10,IF(AF10="Shallow Cyclical (2 to 3 years growth)",5,0)) | AH10: No | AI10: =IF(AH10="Yes due to Product Mix change or Operating Leverage",10,IF(AH10="Yes, these are peak margins",-5,IF(AH10="No",5,0))) | AJ10: Stable | AK10: =IF(AJ10="Stable",10,0) | AL10: Yes | AM10: =IF(AL10="Yes",10,0) | AN10: B2B | AO10: =IF(AN10="B2C",10,IF(AN10="B2B",5,0)) | AP10: Yes | AQ10: =IF(AP10="Yes",10,0) | AR10: Higher One Time, Lower Annuity | AS10: =IF(AR10="Fully Annuity",10,IF(AR10="Higher Annuity, Lower One Time",5,IF(AR10="Higher One Time, Lower Annuity",3,0))) | AT10: Good | AU10: =IF(AT10="Good",10,0) | AV10: Yes for more than 2 years | AW10: =IF(AV10="Yes for more than 2 years",10,IF(AV10="Yes only for next 1 to 2 years",5,0)) | AX10: Above 40 | AY10: =IF(AX10="Above 40",20,IF(AX10="20 to 40",10,IF(AX10="0 to 20",-5,0))) | AZ10: Above 75 | BA10: =IF(AZ10="Between 50 to 75",10,IF(AZ10="Above 75",0,0)) | BB10: Stage 2 | BC10: =IF(BB10="Stage 2",20,IF(BB10="Stage 1",0,IF(BB10="Stage 3",5,IF(BB10="Stage 4",-5,0)))) | BD10: Positive Trend | BE10: =IF(BD10="Positive Trend",20,IF(BD10="Negative Trend",-10,0)) | BF10: Uptrend | BG10: =IF(BF10="Uptrend",10,IF(BF10="Sideways",5,0)) | BH10: Uptrend | BI10: =IF(BH10="Uptrend",10,IF(BH10="Sideways",5,0)) | BJ10: Blue sky scenario | BK10: =IF(BJ10="Overhead supply in last 2 years in last 2 years",-5,IF(BJ10="Close to 52 week high or retracement",5,IF(BJ10="Blue sky scenario",10,IF(BJ10="Long term Downtrend",-10,0)))) | BL10: Yes | BM10: =IF(BL10="Yes",10,0) | BN10: More than 20% | BO10: =IF(BN10="More than 20%",10,IF(BN10="Between 12 to 20%",5,IF(BN10="Less than 12%",0,0))) | BP10: No | BQ10: =IF(BP10="No",10,0) | BR10: Yes | BS10: =IF(BR10="NO",5,0) | BT10: Above 2 | BU10: =IF(BT10="Above 2",0,IF(BT10="Between 1.5 to 2",5,IF(BT10="Less than 1.5",10,0))) | BV10: Above 70% | BW10: =IF(BV10="Above 70%",10,IF(BV10="Between 50% to 70%",5,IF(BV10="Less than 50%",0,IF(BV10="Negative",-10,IF(BV10="Less than 50% and Borrowings are increasing",-5,0))))) | BX10: Less than 0.7 | BY10: =IF(BX10="More than 1.2",-10,IF(BX10="Between 0.7 to 1.2",0,IF(BX10="Less than 0.7",10,0))) | BZ10: No | CA10: =IF(BZ10="Yes",-10,0) | CB10: Less than 15% | CC10: =IF(CB10="More than 15%",-10,IF(CB10="Less than 15%",10,0)) | CD10: No | CE10: =IF(CD10="Yes, more than 10%",-10,IF(CD10="No",10,0))
A11: =IF(B11=0,"",RANK(B11,$B$2:$B$314,0)) | B11: =SUM(N11,Y11,AA11,AC11,AE11,AG11,AI11,AK11,AM11,AO11,AQ11,AS11,AU11,AW11,AY11,BA11,BC11,BE11,BG11,BI11,BK11,BM11,BO11,BQ11,BS11,BU11,BW11,BY11,CA11,CC11,CE11) | C11: INDOBORAX | D11: Indo Borax & Chemicals Ltd | E11: chemicals | F11: chemicals | G11: smallcap | H11: 1110.63 | I11: 358.7 | J11: 3.64 | K11: 193416 | L11: 74 | M11: Outperforming | N11: =IF(M11="Underperforming",-5,IF(L11>=95,15,IF(L11>=90,10,IF(L11>=80,5,0)))) | O11: 80.7 | P11: 45.78 | Q11: 283.7 | R11: Near 52W High Breakout | S11: Nifty 50 | T11: -6.35 | U11: 83.56 | V11: 96 | W11: 23.41 | X11: Growing Industry | Y11: =IF(X11="Growing Industry",10,IF(X11="Cyclical in an Upturn",5,0)) | Z11: Too Many Players with High ROCE | AA11: =IF(Z11="Monopoly",10,IF(Z11="Oligopoly",5,IF(Z11="Duopoly that cooperate",10,IF(Z11="Duopoly that compete",5,IF(Z11="Too many players with High ROCE",5,0))))) | AB11: No | AC11: =IF(AB11="No",5,0) | AD11: Tailwind | AE11: =IF(AD11="Tailwind",10,0) | AF11: Structural (10 Years Consistency) | AG11: =IF(AF11="Structural (10 Years Consistency)",10,IF(AF11="Shallow Cyclical (2 to 3 years growth)",5,0)) | AH11: No | AI11: =IF(AH11="Yes due to Product Mix change or Operating Leverage",10,IF(AH11="Yes, these are peak margins",-5,IF(AH11="No",5,0))) | AJ11: Stable | AK11: =IF(AJ11="Stable",10,0) | AL11: Yes | AM11: =IF(AL11="Yes",10,0) | AN11: B2B | AO11: =IF(AN11="B2C",10,IF(AN11="B2B",5,0)) | AP11: Yes | AQ11: =IF(AP11="Yes",10,0) | AR11: Higher One Time, Lower Annuity | AS11: =IF(AR11="Fully Annuity",10,IF(AR11="Higher Annuity, Lower One Time",5,IF(AR11="Higher One Time, Lower Annuity",3,0))) | AT11: Good | AU11: =IF(AT11="Good",10,0) | AV11: Yes for more than 2 years | AW11: =IF(AV11="Yes for more than 2 years",10,IF(AV11="Yes only for next 1 to 2 years",5,0)) | AX11: Above 40 | AY11: =IF(AX11="Above 40",20,IF(AX11="20 to 40",10,IF(AX11="0 to 20",-5,0))) | AZ11: Above 75 | BA11: =IF(AZ11="Between 50 to 75",10,IF(AZ11="Above 75",0,0)) | BB11: Stage 2 | BC11: =IF(BB11="Stage 2",20,IF(BB11="Stage 1",0,IF(BB11="Stage 3",5,IF(BB11="Stage 4",-5,0)))) | BD11: Positive Trend | BE11: =IF(BD11="Positive Trend",20,IF(BD11="Negative Trend",-10,0)) | BF11: Uptrend | BG11: =IF(BF11="Uptrend",10,IF(BF11="Sideways",5,0)) | BH11: Uptrend | BI11: =IF(BH11="Uptrend",10,IF(BH11="Sideways",5,0)) | BJ11: Blue sky scenario | BK11: =IF(BJ11="Overhead supply in last 2 years in last 2 years",-5,IF(BJ11="Close to 52 week high or retracement",5,IF(BJ11="Blue sky scenario",10,IF(BJ11="Long term Downtrend",-10,0)))) | BL11: Yes | BM11: =IF(BL11="Yes",10,0) | BN11: More than 20% | BO11: =IF(BN11="More than 20%",10,IF(BN11="Between 12 to 20%",5,IF(BN11="Less than 12%",0,0))) | BP11: No | BQ11: =IF(BP11="No",10,0) | BR11: No | BS11: =IF(BR11="NO",5,0) | BT11: Less than 1.5 | BU11: =IF(BT11="Above 2",0,IF(BT11="Between 1.5 to 2",5,IF(BT11="Less than 1.5",10,0))) | BV11: Above 70% | BW11: =IF(BV11="Above 70%",10,IF(BV11="Between 50% to 70%",5,IF(BV11="Less than 50%",0,IF(BV11="Negative",-10,IF(BV11="Less than 50% and Borrowings are increasing",-5,0))))) | BX11: Less than 0.7 | BY11: =IF(BX11="More than 1.2",-10,IF(BX11="Between 0.7 to 1.2",0,IF(BX11="Less than 0.7",10,0))) | BZ11: No | CA11: =IF(BZ11="Yes",-10,0) | CB11: Less than 15% | CC11: =IF(CB11="More than 15%",-10,IF(CB11="Less than 15%",10,0)) | CD11: No | CE11: =IF(CD11="Yes, more than 10%",-10,IF(CD11="No",10,0))
A12: =IF(B12=0,"",RANK(B12,$B$2:$B$314,0)) | B12: =SUM(N12,Y12,AA12,AC12,AE12,AG12,AI12,AK12,AM12,AO12,AQ12,AS12,AU12,AW12,AY12,BA12,BC12,BE12,BG12,BI12,BK12,BM12,BO12,BQ12,BS12,BU12,BW12,BY12,CA12,CC12,CE12) | C12: GVT&D | D12: GE Vernova T&D India Ltd | E12: industrials | F12: electric equipment | G12: largecap | H12: 127114.3 | I12: 5086.5 | J12: 2.46 | K12: 999168 | L12: 77 | M12: Outperforming | N12: =IF(M12="Underperforming",-5,IF(L12>=95,15,IF(L12>=90,10,IF(L12>=80,5,0)))) | O12: 73.43 | P12: 49.15 | Q12: 3909.14 | R12: Near 52W High Breakout | S12: Nifty 50 | T12: -6.35 | U12: 120.06 | V12: 134.96 | W12: 24.46 | X12: Cyclical in an Upturn | Y12: =IF(X12="Growing Industry",10,IF(X12="Cyclical in an Upturn",5,0)) | Z12: Too Many Players with High ROCE | AA12: =IF(Z12="Monopoly",10,IF(Z12="Oligopoly",5,IF(Z12="Duopoly that cooperate",10,IF(Z12="Duopoly that compete",5,IF(Z12="Too many players with High ROCE",5,0))))) | AB12: No | AC12: =IF(AB12="No",5,0) | AD12: Tailwind | AE12: =IF(AD12="Tailwind",10,0) | AF12: Structural (10 Years Consistency) | AG12: =IF(AF12="Structural (10 Years Consistency)",10,IF(AF12="Shallow Cyclical (2 to 3 years growth)",5,0)) | AH12: No | AI12: =IF(AH12="Yes due to Product Mix change or Operating Leverage",10,IF(AH12="Yes, these are peak margins",-5,IF(AH12="No",5,0))) | AJ12: Stable | AK12: =IF(AJ12="Stable",10,0) | AL12: Yes | AM12: =IF(AL12="Yes",10,0) | AN12: B2B | AO12: =IF(AN12="B2C",10,IF(AN12="B2B",5,0)) | AP12: Yes | AQ12: =IF(AP12="Yes",10,0) | AR12: Higher One Time, Lower Annuity | AS12: =IF(AR12="Fully Annuity",10,IF(AR12="Higher Annuity, Lower One Time",5,IF(AR12="Higher One Time, Lower Annuity",3,0))) | AT12: Good | AU12: =IF(AT12="Good",10,0) | AV12: Yes for more than 2 years | AW12: =IF(AV12="Yes for more than 2 years",10,IF(AV12="Yes only for next 1 to 2 years",5,0)) | AX12: Above 40 | AY12: =IF(AX12="Above 40",20,IF(AX12="20 to 40",10,IF(AX12="0 to 20",-5,0))) | AZ12: Between 50 to 75 | BA12: =IF(AZ12="Between 50 to 75",10,IF(AZ12="Above 75",0,0)) | BB12: Stage 2 | BC12: =IF(BB12="Stage 2",20,IF(BB12="Stage 1",0,IF(BB12="Stage 3",5,IF(BB12="Stage 4",-5,0)))) | BD12: Positive Trend | BE12: =IF(BD12="Positive Trend",20,IF(BD12="Negative Trend",-10,0)) | BF12: Uptrend | BG12: =IF(BF12="Uptrend",10,IF(BF12="Sideways",5,0)) | BH12: Uptrend | BI12: =IF(BH12="Uptrend",10,IF(BH12="Sideways",5,0)) | BJ12: Blue sky scenario | BK12: =IF(BJ12="Overhead supply in last 2 years in last 2 years",-5,IF(BJ12="Close to 52 week high or retracement",5,IF(BJ12="Blue sky scenario",10,IF(BJ12="Long term Downtrend",-10,0)))) | BL12: Yes | BM12: =IF(BL12="Yes",10,0) | BN12: More than 20% | BO12: =IF(BN12="More than 20%",10,IF(BN12="Between 12 to 20%",5,IF(BN12="Less than 12%",0,0))) | BP12: No | BQ12: =IF(BP12="No",10,0) | BR12: Yes | BS12: =IF(BR12="NO",5,0) | BT12: Less than 1.5 | BU12: =IF(BT12="Above 2",0,IF(BT12="Between 1.5 to 2",5,IF(BT12="Less than 1.5",10,0))) | BV12: Above 70% | BW12: =IF(BV12="Above 70%",10,IF(BV12="Between 50% to 70%",5,IF(BV12="Less than 50%",0,IF(BV12="Negative",-10,IF(BV12="Less than 50% and Borrowings are increasing",-5,0))))) | BX12: Less than 0.7 | BY12: =IF(BX12="More than 1.2",-10,IF(BX12="Between 0.7 to 1.2",0,IF(BX12="Less than 0.7",10,0))) | BZ12: No | CA12: =IF(BZ12="Yes",-10,0) | CB12: Less than 15% | CC12: =IF(CB12="More than 15%",-10,IF(CB12="Less than 15%",10,0)) | CD12: No | CE12: =IF(CD12="Yes, more than 10%",-10,IF(CD12="No",10,0))
A13: =IF(B13=0,"",RANK(B13,$B$2:$B$314,0)) | B13: =SUM(N13,Y13,AA13,AC13,AE13,AG13,AI13,AK13,AM13,AO13,AQ13,AS13,AU13,AW13,AY13,BA13,BC13,BE13,BG13,BI13,BK13,BM13,BO13,BQ13,BS13,BU13,BW13,BY13,CA13,CC13,CE13) | C13: STYLAMIND | D13: Stylam Industries Ltd | E13: building materials | F13: miscellaneous | G13: midcap | H13: 5067.13 | I13: 3037 | J13: 1.58 | K13: 49477 | L13: 70 | M13: Outperforming | N13: =IF(M13="Underperforming",-5,IF(L13>=95,15,IF(L13>=90,10,IF(L13>=80,5,0)))) | O13: 88.73 | P13: 54.35 | Q13: 2582.7 | R13: Near 52W High Breakout | S13: Nifty Infra | T13: 1.41 | U13: 79.42 | V13: 76.92 | W13: 20.78 | X13: Growing Industry | Y13: =IF(X13="Growing Industry",10,IF(X13="Cyclical in an Upturn",5,0)) | Z13: Too Many Players with High ROCE | AA13: =IF(Z13="Monopoly",10,IF(Z13="Oligopoly",5,IF(Z13="Duopoly that cooperate",10,IF(Z13="Duopoly that compete",5,IF(Z13="Too many players with High ROCE",5,0))))) | AB13: No | AC13: =IF(AB13="No",5,0) | AD13: Tailwind | AE13: =IF(AD13="Tailwind",10,0) | AF13: Structural (10 Years Consistency) | AG13: =IF(AF13="Structural (10 Years Consistency)",10,IF(AF13="Shallow Cyclical (2 to 3 years growth)",5,0)) | AH13: No | AI13: =IF(AH13="Yes due to Product Mix change or Operating Leverage",10,IF(AH13="Yes, these are peak margins",-5,IF(AH13="No",5,0))) | AJ13: Stable | AK13: =IF(AJ13="Stable",10,0) | AL13: Yes | AM13: =IF(AL13="Yes",10,0) | AN13: B2B | AO13: =IF(AN13="B2C",10,IF(AN13="B2B",5,0)) | AP13: Yes | AQ13: =IF(AP13="Yes",10,0) | AR13: Higher One Time, Lower Annuity | AS13: =IF(AR13="Fully Annuity",10,IF(AR13="Higher Annuity, Lower One Time",5,IF(AR13="Higher One Time, Lower Annuity",3,0))) | AT13: Good | AU13: =IF(AT13="Good",10,0) | AV13: Yes for more than 2 years | AW13: =IF(AV13="Yes for more than 2 years",10,IF(AV13="Yes only for next 1 to 2 years",5,0)) | AX13: Above 40 | AY13: =IF(AX13="Above 40",20,IF(AX13="20 to 40",10,IF(AX13="0 to 20",-5,0))) | AZ13: Above 75 | BA13: =IF(AZ13="Between 50 to 75",10,IF(AZ13="Above 75",0,0)) | BB13: Stage 2 | BC13: =IF(BB13="Stage 2",20,IF(BB13="Stage 1",0,IF(BB13="Stage 3",5,IF(BB13="Stage 4",-5,0)))) | BD13: Positive Trend | BE13: =IF(BD13="Positive Trend",20,IF(BD13="Negative Trend",-10,0)) | BF13: Uptrend | BG13: =IF(BF13="Uptrend",10,IF(BF13="Sideways",5,0)) | BH13: Uptrend | BI13: =IF(BH13="Uptrend",10,IF(BH13="Sideways",5,0)) | BJ13: Blue sky scenario | BK13: =IF(BJ13="Overhead supply in last 2 years in last 2 years",-5,IF(BJ13="Close to 52 week high or retracement",5,IF(BJ13="Blue sky scenario",10,IF(BJ13="Long term Downtrend",-10,0)))) | BL13: Yes | BM13: =IF(BL13="Yes",10,0) | BN13: More than 20% | BO13: =IF(BN13="More than 20%",10,IF(BN13="Between 12 to 20%",5,IF(BN13="Less than 12%",0,0))) | BP13: No | BQ13: =IF(BP13="No",10,0) | BR13: No | BS13: =IF(BR13="NO",5,0) | BT13: Less than 1.5 | BU13: =IF(BT13="Above 2",0,IF(BT13="Between 1.5 to 2",5,IF(BT13="Less than 1.5",10,0))) | BV13: Above 70% | BW13: =IF(BV13="Above 70%",10,IF(BV13="Between 50% to 70%",5,IF(BV13="Less than 50%",0,IF(BV13="Negative",-10,IF(BV13="Less than 50% and Borrowings are increasing",-5,0))))) | BX13: Less than 0.7 | BY13: =IF(BX13="More than 1.2",-10,IF(BX13="Between 0.7 to 1.2",0,IF(BX13="Less than 0.7",10,0))) | BZ13: No | CA13: =IF(BZ13="Yes",-10,0) | CB13: Less than 15% | CC13: =IF(CB13="More than 15%",-10,IF(CB13="Less than 15%",10,0)) | CD13: No | CE13: =IF(CD13="Yes, more than 10%",-10,IF(CD13="No",10,0))
... A314: =IF(B314=0,"",RANK(B314,$B$2:$B$314,0)) | B314: =SUM(N314,Y314,AA314,AC314,AE314,AG314,AI314,AK314,AM314,AO314,AQ314,AS314,AU314,AW314,AY314,BA314,BC314,BE314,BG314,BI314,BK314,BM314,BO314,BQ314,BS314,BU314,BW314,BY314,CA314,CC314,CE314) | C314: TEXINFRA | D314: Texmaco Infrastructure & Holdings Limited | E314: realty | F314: construction | G314: smallcap | H314: 1258.85 | I314: 100.55 | J314: 1.78 | K314: 243490 | L314: 4 | M314: Outperforming | N314: =IF(M314="Underperforming",-5,IF(L314>=95,15,IF(L314>=90,10,IF(L314>=80,5,0)))) | O314: 54.06 | P314: 14.33 | Q314: 81.62 | R314: Earnings / Momentum Support | S314: Nifty Realty | T314: -26.45 | U314: -4.62 | V314: 29.68 | W314: 1.91 | X314: Growing Industry | Y314: =IF(X314="Growing Industry",10,IF(X314="Cyclical in an Upturn",5,0)) | Z314: Too Many Players with High ROCE | AA314: =IF(Z314="Monopoly",10,IF(Z314="Oligopoly",5,IF(Z314="Duopoly that cooperate",10,IF(Z314="Duopoly that compete",5,IF(Z314="Too many players with High ROCE",5,0))))) | AB314: No | AC314: =IF(AB314="No",5,0) | AD314: Headwind | AE314: =IF(AD314="Tailwind",10,0) | AF314: Structural (10 Years Consistency) | AG314: =IF(AF314="Structural (10 Years Consistency)",10,IF(AF314="Shallow Cyclical (2 to 3 years growth)",5,0)) | AH314: No | AI314: =IF(AH314="Yes due to Product Mix change or Operating Leverage",10,IF(AH314="Yes, these are peak margins",-5,IF(AH314="No",5,0))) | AJ314: Stable | AK314: =IF(AJ314="Stable",10,0) | AL314: Yes | AM314: =IF(AL314="Yes",10,0) | AN314: B2B | AO314: =IF(AN314="B2C",10,IF(AN314="B2B",5,0)) | AP314: No | AQ314: =IF(AP314="Yes",10,0) | AR314: Higher One Time, Lower Annuity | AS314: =IF(AR314="Fully Annuity",10,IF(AR314="Higher Annuity, Lower One Time",5,IF(AR314="Higher One Time, Lower Annuity",3,0))) | AT314: Good | AU314: =IF(AT314="Good",10,0) | AV314: Yes for more than 2 years | AW314: =IF(AV314="Yes for more than 2 years",10,IF(AV314="Yes only for next 1 to 2 years",5,0)) | AX314: 0 to 20 | AY314: =IF(AX314="Above 40",20,IF(AX314="20 to 40",10,IF(AX314="0 to 20",-5,0))) | AZ314: Between 50 to 75 | BA314: =IF(AZ314="Between 50 to 75",10,IF(AZ314="Above 75",0,0)) | BB314: Stage 1 | BC314: =IF(BB314="Stage 2",20,IF(BB314="Stage 1",0,IF(BB314="Stage 3",5,IF(BB314="Stage 4",-5,0)))) | BD314: Negative Trend | BE314: =IF(BD314="Positive Trend",20,IF(BD314="Negative Trend",-10,0)) | BF314: Uptrend | BG314: =IF(BF314="Uptrend",10,IF(BF314="Sideways",5,0)) | BH314: Uptrend | BI314: =IF(BH314="Uptrend",10,IF(BH314="Sideways",5,0)) | BJ314: Close to 52 week high or retracement | BK314: =IF(BJ314="Overhead supply in last 2 years in last 2 years",-5,IF(BJ314="Close to 52 week high or retracement",5,IF(BJ314="Blue sky scenario",10,IF(BJ314="Long term Downtrend",-10,0)))) | BL314: Yes | BM314: =IF(BL314="Yes",10,0) | BN314: Less than 12% | BO314: =IF(BN314="More than 20%",10,IF(BN314="Between 12 to 20%",5,IF(BN314="Less than 12%",0,0))) | BP314: No | BQ314: =IF(BP314="No",10,0) | BR314: Yes | BS314: =IF(BR314="NO",5,0) | BT314: Above 2 | BU314: =IF(BT314="Above 2",0,IF(BT314="Between 1.5 to 2",5,IF(BT314="Less than 1.5",10,0))) | BV314: Negative | BW314: =IF(BV314="Above 70%",10,IF(BV314="Between 50% to 70%",5,IF(BV314="Less than 50%",0,IF(BV314="Negative",-10,IF(BV314="Less than 50% and Borrowings are increasing",-5,0))))) | BX314: Less than 0.7 | BY314: =IF(BX314="More than 1.2",-10,IF(BX314="Between 0.7 to 1.2",0,IF(BX314="Less than 0.7",10,0))) | BZ314: No | CA314: =IF(BZ314="Yes",-10,0) | CB314: Less than 15% | CC314: =IF(CB314="More than 15%",-10,IF(CB314="Less than 15%",10,0)) | CD314: No | CE314: =IF(CD314="Yes, more than 10%",-10,IF(CD314="No",10,0))

Sheet Monit Banks NBFC
A1: Rank (Banks & NBFC) | B1: Total Score | C1: Symbol | D1: Company | E1: Sector | F1: Industry | G1: Market Cap Bucket | H1: Market Cap Cr | I1: Close | J1: Today Return % | K1: Volume | L1: Relative Strength Rating | M1: Relative Strength Status | N1: Relative Strength Score | O1: Calculated RSI (14) | P1: Calculated ADX (14) | Q1: Calculated V-stop Line | R1: Calculated Near-term Trigger | S1: Sector Benchmark | T1: Benchmark 1Y Return % | U1: Stock 1Y Return % | V1: Relative Strength 1Y (%) | W1: O'Neil Weighted Score | X1: Industry Growth | Y1: Industry Growth Score | Z1: Competitiveness | AA1: Competitiveness Score | AB1: Regulation | AC1: Regulation Score | AD1: Sector Headwinds/Tailwind | AE1: Sector Headwinds/Tailwind Score | AF1: Industry Type | AG1: Industry Type Score | AH1: NIM | AI1: NIM Score | AJ1: CASA Ratio | AK1: CASA Ratio Score | AL1: Profit cyclicality | AM1: Profit cyclicality Score | AN1: CAR Ratio | AO1: CAR Ratio Score | AP1: Near term triggers | AQ1: Near term triggers Score | AR1: High P/BV | AS1: High P/BV Score | AT1: Asset Quality Divergence | AU1: Asset Quality Divergence Score | AV1: Reported loss | AW1: Reported loss Score | AX1: CEO Resignation | AY1: CEO Resignation Score | AZ1: GNPA | BA1: GNPA Score | BB1: KMP Resignation | BC1: KMP Resignation Score | BD1: Return on Assets | BE1: Return on Assets Score | BF1: Return on Equity | BG1: Return on Equity Score | BH1: AUM Growth | BI1: AUM Growth Score | BJ1: Price to Book Value | BK1: Price to Book Value Score | BL1: ADX | BM1: ADX Score | BN1: RSI | BO1: RSI Score | BP1: Stage Analysis | BQ1: Stage Analysis Score | BR1: Price Volume Action | BS1: Price Volume Action Score | BT1: Secondary Trend | BU1: Secondary Trend Score | BV1: Primary Trend | BW1: Primary Trend Score | BX1: Resistance | BY1: Resistance Score | BZ1: V-stop | CA1: V-stop Score
A2: =IF(B2=0,"",RANK(B2,$B$2:$B$32,0)) | B2: =SUM(N2,Y2,AA2,AC2,AE2,AG2,AI2,AK2,AM2,AO2,AQ2,AS2,AU2,AW2,AY2,BA2,BC2,BE2,BG2,BI2,BK2,BM2,BO2,BQ2,BS2,BU2,BW2,BY2,CA2) | C2: FEDFINA | D2: Fedbank Financial Services Ltd | E2: financials | F2: finance & investments | G2: midcap | H2: 5875.41 | I2: 162.05 | J2: 3.21 | K2: 663731 | L2: 58 | M2: Outperforming | N2: =IF(M2="Underperforming",-5,IF(L2>=95,15,IF(L2>=90,10,IF(L2>=80,5,0)))) | O2: 66 | P2: 21.35 | Q2: 125.06 | R2: Near 52W High Breakout | S2: Nifty Bank | T2: -4.01 | U2: 55.68 | V2: 62.19 | W2: 16.1 | X2: Growing Industry | Y2: =IF(X2="Growing Industry",10,IF(X2="Cyclical in an Upturn",5,0)) | Z2: Fragmented with High ROE | AA2: =IF(Z2="Fragmented with Low ROE",-5,IF(Z2="Fragmented with High ROE",10,IF(Z2= "highly cyclical",5,0))) | AB2: Yes | AC2: =IF(AB2="No",5,0) | AD2: Tailwind | AE2: =IF(AD2="Tailwind",10,0) | AF2: Structural (10 Years Consistency) | AG2: =IF(AF2="Structural (10 Years Consistency)",15,IF(AF2="Shallow Cyclical (2 to 3 years growth)",10,IF(AF2 = "Cyclical in an Uptick",5,IF(AF2 = "Cyclical in an Downtick",-10,0)))) | AH2: Yes | AI2: =IF(AH2="Yes",10,0) | AJ2: Yes | AK2: =IF(AJ2="Yes",10,0) | AM2: =IF(AL2="No",10,0) | AN2: Yes | AO2: =IF(AN2="Yes",10,0) | AP2: Yes | AQ2: =IF(AP2="Yes",10,0) | AR2: Yes | AS2: =IF(AR2="Yes",5,0) | AT2: No | AU2: =IF(AT2="No",10,IF(AT2="Yes",-10,0)) | AV2: No | AW2: =IF(AV2="No",10,0) | AX2: No | AY2: =IF(AX2="No",10,IF(AX2= "Yes CEO Resignation",-5,0)) | AZ2: No | BA2: =IF(AZ2="No",10,IF(AZ2="Yes",-5,0)) | BB2: No | BC2: =IF(BB2="No",5,IF(BB2="Yes",-5,0)) | BD2: Yes | BE2: =IF(BD2="Yes",10,0) | BF2: Yes | BG2: =IF(BF2="Yes",10,0) | BH2: Yes | BI2: =IF(BH2="Yes",10,0) | BJ2: P/BV less than 2.5x and Growth more than 20% | BK2: =IF(BJ2="P/BV less than 2.5x and Growth more than 20%",20,IF(BJ2 = "P/BV less than 2.5x and Growth less than 20%",5,IF(BJ2="P/BV between 2.5x to 5x and Growth more than 20%",10,IF(BJ2= "P/BV between 2.5x to 5x and Growth less than 20%",-5,IF(BJ2= "P/BV above 5x",-5,0))))) | BL2: 20 to 40 | BM2: =IF(BL2="Above 40",20,IF(BL2="20 to 40",10,IF(BL2="0 to 20",-5,0))) | BN2: Between 50 to 75 | BO2: =IF(BN2="Between 50 to 75",10,IF(BN2="Above 75",0,0)) | BP2: Stage 2 | BQ2: =IF(BP2="Stage 2",20,IF(BP2="Stage 1",0,IF(BP2="Stage 3",5,IF(BP2="Stage 4",-5,0)))) | BR2: Positive Trend | BS2: =IF(BR2="Positive Trend",20,IF(BR2="Negative Trend",-10,0)) | BT2: Uptrend | BU2: =IF(BT2="Uptrend",10,IF(BT2="Sideways",5,0)) | BV2: Uptrend | BW2: =IF(BV2="Uptrend",10,IF(BV2="Sideways",5,0)) | BX2: Blue sky scenario | BY2: =IF(BX2="Overhead supply in last 2 years in last 2 years",-5,IF(BX2="Close to 52 week high or retracement",5,IF(BX2="Blue sky scenario",10,IF(BX2="Long term Downtrend",-10,0)))) | BZ2: Yes | CA2: =IF(BZ2="Yes",10,0)
A3: =IF(B3=0,"",RANK(B3,$B$2:$B$32,0)) | B3: =SUM(N3,Y3,AA3,AC3,AE3,AG3,AI3,AK3,AM3,AO3,AQ3,AS3,AU3,AW3,AY3,BA3,BC3,BE3,BG3,BI3,BK3,BM3,BO3,BQ3,BS3,BU3,BW3,BY3,CA3) | C3: RBLBANK | D3: Rbl Bank Limited | E3: bank | F3: banks - private sector | G3: largecap | H3: 21522.64 | I3: 353.75 | J3: 1.59 | K3: 5254858 | L3: 51 | M3: Outperforming | N3: =IF(M3="Underperforming",-5,IF(L3>=95,15,IF(L3>=90,10,IF(L3>=80,5,0)))) | O3: 66.05 | P3: 27.24 | Q3: 292.3 | R3: Near 52W High Breakout | S3: Nifty Bank | T3: -4.01 | U3: 63.14 | V3: 69.96 | W3: 14.05 | X3: Growing Industry | Y3: =IF(X3="Growing Industry",10,IF(X3="Cyclical in an Upturn",5,0)) | Z3: Fragmented with High ROE | AA3: =IF(Z3="Fragmented with Low ROE",-5,IF(Z3="Fragmented with High ROE",10,IF(Z3= "highly cyclical",5,0))) | AB3: Yes | AC3: =IF(AB3="No",5,0) | AD3: Tailwind | AE3: =IF(AD3="Tailwind",10,0) | AF3: Structural (10 Years Consistency) | AG3: =IF(AF3="Structural (10 Years Consistency)",15,IF(AF3="Shallow Cyclical (2 to 3 years growth)",10,IF(AF3 = "Cyclical in an Uptick",5,IF(AF3 = "Cyclical in an Downtick",-10,0)))) | AH3: Yes | AI3: =IF(AH3="Yes",10,0) | AJ3: Yes | AK3: =IF(AJ3="Yes",10,0) | AM3: =IF(AL3="No",10,0) | AN3: Yes | AO3: =IF(AN3="Yes",10,0) | AP3: Yes | AQ3: =IF(AP3="Yes",10,0) | AR3: Yes | AS3: =IF(AR3="Yes",5,0) | AT3: No | AU3: =IF(AT3="No",10,IF(AT3="Yes",-10,0)) | AV3: No | AW3: =IF(AV3="No",10,0) | AX3: No | AY3: =IF(AX3="No",10,IF(AX3= "Yes CEO Resignation",-5,0)) | AZ3: No | BA3: =IF(AZ3="No",10,IF(AZ3="Yes",-5,0)) | BB3: No | BC3: =IF(BB3="No",5,IF(BB3="Yes",-5,0)) | BD3: Yes | BE3: =IF(BD3="Yes",10,0) | BF3: Yes | BG3: =IF(BF3="Yes",10,0) | BH3: Yes | BI3: =IF(BH3="Yes",10,0) | BJ3: P/BV less than 2.5x and Growth more than 20% | BK3: =IF(BJ3="P/BV less than 2.5x and Growth more than 20%",20,IF(BJ3 = "P/BV less than 2.5x and Growth less than 20%",5,IF(BJ3="P/BV between 2.5x to 5x and Growth more than 20%",10,IF(BJ3= "P/BV between 2.5x to 5x and Growth less than 20%",-5,IF(BJ3= "P/BV above 5x",-5,0))))) | BL3: 20 to 40 | BM3: =IF(BL3="Above 40",20,IF(BL3="20 to 40",10,IF(BL3="0 to 20",-5,0))) | BN3: Between 50 to 75 | BO3: =IF(BN3="Between 50 to 75",10,IF(BN3="Above 75",0,0)) | BP3: Stage 2 | BQ3: =IF(BP3="Stage 2",20,IF(BP3="Stage 1",0,IF(BP3="Stage 3",5,IF(BP3="Stage 4",-5,0)))) | BR3: Positive Trend | BS3: =IF(BR3="Positive Trend",20,IF(BR3="Negative Trend",-10,0)) | BT3: Uptrend | BU3: =IF(BT3="Uptrend",10,IF(BT3="Sideways",5,0)) | BV3: Uptrend | BW3: =IF(BV3="Uptrend",10,IF(BV3="Sideways",5,0)) | BX3: Blue sky scenario | BY3: =IF(BX3="Overhead supply in last 2 years in last 2 years",-5,IF(BX3="Close to 52 week high or retracement",5,IF(BX3="Blue sky scenario",10,IF(BX3="Long term Downtrend",-10,0)))) | BZ3: Yes | CA3: =IF(BZ3="Yes",10,0)
A4: =IF(B4=0,"",RANK(B4,$B$2:$B$32,0)) | B4: =SUM(N4,Y4,AA4,AC4,AE4,AG4,AI4,AK4,AM4,AO4,AQ4,AS4,AU4,AW4,AY4,BA4,BC4,BE4,BG4,BI4,BK4,BM4,BO4,BQ4,BS4,BU4,BW4,BY4,CA4) | C4: TMB | D4: Tamilnad Mercantile Bank Ltd | E4: bank | F4: banks - private sector | G4: midcap | H4: 11725.13 | I4: 748.1 | J4: 1.03 | K4: 232194 | L4: 56 | M4: Outperforming | N4: =IF(M4="Underperforming",-5,IF(L4>=95,15,IF(L4>=90,10,IF(L4>=80,5,0)))) | O4: 66.36 | P4: 29.63 | Q4: 589.3 | R4: Near 52W High Breakout | S4: Nifty Bank | T4: -4.01 | U4: 68.12 | V4: 75.14 | W4: 15.34 | X4: Growing Industry | Y4: =IF(X4="Growing Industry",10,IF(X4="Cyclical in an Upturn",5,0)) | Z4: Fragmented with High ROE | AA4: =IF(Z4="Fragmented with Low ROE",-5,IF(Z4="Fragmented with High ROE",10,IF(Z4= "highly cyclical",5,0))) | AB4: Yes | AC4: =IF(AB4="No",5,0) | AD4: Tailwind | AE4: =IF(AD4="Tailwind",10,0) | AF4: Structural (10 Years Consistency) | AG4: =IF(AF4="Structural (10 Years Consistency)",15,IF(AF4="Shallow Cyclical (2 to 3 years growth)",10,IF(AF4 = "Cyclical in an Uptick",5,IF(AF4 = "Cyclical in an Downtick",-10,0)))) | AH4: Yes | AI4: =IF(AH4="Yes",10,0) | AJ4: Yes | AK4: =IF(AJ4="Yes",10,0) | AM4: =IF(AL4="No",10,0) | AN4: Yes | AO4: =IF(AN4="Yes",10,0) | AP4: Yes | AQ4: =IF(AP4="Yes",10,0) | AR4: Yes | AS4: =IF(AR4="Yes",5,0) | AT4: No | AU4: =IF(AT4="No",10,IF(AT4="Yes",-10,0)) | AV4: No | AW4: =IF(AV4="No",10,0) | AX4: No | AY4: =IF(AX4="No",10,IF(AX4= "Yes CEO Resignation",-5,0)) | AZ4: No | BA4: =IF(AZ4="No",10,IF(AZ4="Yes",-5,0)) | BB4: No | BC4: =IF(BB4="No",5,IF(BB4="Yes",-5,0)) | BD4: Yes | BE4: =IF(BD4="Yes",10,0) | BF4: Yes | BG4: =IF(BF4="Yes",10,0) | BH4: Yes | BI4: =IF(BH4="Yes",10,0) | BJ4: P/BV less than 2.5x and Growth more than 20% | BK4: =IF(BJ4="P/BV less than 2.5x and Growth more than 20%",20,IF(BJ4 = "P/BV less than 2.5x and Growth less than 20%",5,IF(BJ4="P/BV between 2.5x to 5x and Growth more than 20%",10,IF(BJ4= "P/BV between 2.5x to 5x and Growth less than 20%",-5,IF(BJ4= "P/BV above 5x",-5,0))))) | BL4: 20 to 40 | BM4: =IF(BL4="Above 40",20,IF(BL4="20 to 40",10,IF(BL4="0 to 20",-5,0))) | BN4: Between 50 to 75 | BO4: =IF(BN4="Between 50 to 75",10,IF(BN4="Above 75",0,0)) | BP4: Stage 2 | BQ4: =IF(BP4="Stage 2",20,IF(BP4="Stage 1",0,IF(BP4="Stage 3",5,IF(BP4="Stage 4",-5,0)))) | BR4: Positive Trend | BS4: =IF(BR4="Positive Trend",20,IF(BR4="Negative Trend",-10,0)) | BT4: Uptrend | BU4: =IF(BT4="Uptrend",10,IF(BT4="Sideways",5,0)) | BV4: Uptrend | BW4: =IF(BV4="Uptrend",10,IF(BV4="Sideways",5,0)) | BX4: Blue sky scenario | BY4: =IF(BX4="Overhead supply in last 2 years in last 2 years",-5,IF(BX4="Close to 52 week high or retracement",5,IF(BX4="Blue sky scenario",10,IF(BX4="Long term Downtrend",-10,0)))) | BZ4: Yes | CA4: =IF(BZ4="Yes",10,0)
A5: =IF(B5=0,"",RANK(B5,$B$2:$B$32,0)) | B5: =SUM(N5,Y5,AA5,AC5,AE5,AG5,AI5,AK5,AM5,AO5,AQ5,AS5,AU5,AW5,AY5,BA5,BC5,BE5,BG5,BI5,BK5,BM5,BO5,BQ5,BS5,BU5,BW5,BY5,CA5) | C5: DHANBANK | D5: Dhanlaxmi Bank Limited | E5: bank | F5: banks - private sector | G5: smallcap | H5: 1341.58 | I5: 33.87 | J5: -0.35 | K5: 1367599 | L5: 46 | M5: Outperforming | N5: =IF(M5="Underperforming",-5,IF(L5>=95,15,IF(L5>=90,10,IF(L5>=80,5,0)))) | O5: 71.01 | P5: 28.77 | Q5: 25.85 | R5: Near 52W High Breakout | S5: Nifty Bank | T5: -4.01 | U5: 6.81 | V5: 11.28 | W5: 12.5 | X5: Growing Industry | Y5: =IF(X5="Growing Industry",10,IF(X5="Cyclical in an Upturn",5,0)) | Z5: Fragmented with High ROE | AA5: =IF(Z5="Fragmented with Low ROE",-5,IF(Z5="Fragmented with High ROE",10,IF(Z5= "highly cyclical",5,0))) | AB5: Yes | AC5: =IF(AB5="No",5,0) | AD5: Tailwind | AE5: =IF(AD5="Tailwind",10,0) | AF5: Structural (10 Years Consistency) | AG5: =IF(AF5="Structural (10 Years Consistency)",15,IF(AF5="Shallow Cyclical (2 to 3 years growth)",10,IF(AF5 = "Cyclical in an Uptick",5,IF(AF5 = "Cyclical in an Downtick",-10,0)))) | AH5: Yes | AI5: =IF(AH5="Yes",10,0) | AJ5: Yes | AK5: =IF(AJ5="Yes",10,0) | AM5: =IF(AL5="No",10,0) | AN5: Yes | AO5: =IF(AN5="Yes",10,0) | AP5: Yes | AQ5: =IF(AP5="Yes",10,0) | AR5: Yes | AS5: =IF(AR5="Yes",5,0) | AT5: No | AU5: =IF(AT5="No",10,IF(AT5="Yes",-10,0)) | AV5: No | AW5: =IF(AV5="No",10,0) | AX5: No | AY5: =IF(AX5="No",10,IF(AX5= "Yes CEO Resignation",-5,0)) | AZ5: No | BA5: =IF(AZ5="No",10,IF(AZ5="Yes",-5,0)) | BB5: No | BC5: =IF(BB5="No",5,IF(BB5="Yes",-5,0)) | BD5: Yes | BE5: =IF(BD5="Yes",10,0) | BF5: Yes | BG5: =IF(BF5="Yes",10,0) | BH5: Yes | BI5: =IF(BH5="Yes",10,0) | BJ5: P/BV less than 2.5x and Growth more than 20% | BK5: =IF(BJ5="P/BV less than 2.5x and Growth more than 20%",20,IF(BJ5 = "P/BV less than 2.5x and Growth less than 20%",5,IF(BJ5="P/BV between 2.5x to 5x and Growth more than 20%",10,IF(BJ5= "P/BV between 2.5x to 5x and Growth less than 20%",-5,IF(BJ5= "P/BV above 5x",-5,0))))) | BL5: 20 to 40 | BM5: =IF(BL5="Above 40",20,IF(BL5="20 to 40",10,IF(BL5="0 to 20",-5,0))) | BN5: Between 50 to 75 | BO5: =IF(BN5="Between 50 to 75",10,IF(BN5="Above 75",0,0)) | BP5: Stage 2 | BQ5: =IF(BP5="Stage 2",20,IF(BP5="Stage 1",0,IF(BP5="Stage 3",5,IF(BP5="Stage 4",-5,0)))) | BR5: Positive Trend | BS5: =IF(BR5="Positive Trend",20,IF(BR5="Negative Trend",-10,0)) | BT5: Uptrend | BU5: =IF(BT5="Uptrend",10,IF(BT5="Sideways",5,0)) | BV5: Uptrend | BW5: =IF(BV5="Uptrend",10,IF(BV5="Sideways",5,0)) | BX5: Close to 52 week high or retracement | BY5: =IF(BX5="Overhead supply in last 2 years in last 2 years",-5,IF(BX5="Close to 52 week high or retracement",5,IF(BX5="Blue sky scenario",10,IF(BX5="Long term Downtrend",-10,0)))) | BZ5: Yes | CA5: =IF(BZ5="Yes",10,0)
A6: =IF(B6=0,"",RANK(B6,$B$2:$B$32,0)) | B6: =SUM(N6,Y6,AA6,AC6,AE6,AG6,AI6,AK6,AM6,AO6,AQ6,AS6,AU6,AW6,AY6,BA6,BC6,BE6,BG6,BI6,BK6,BM6,BO6,BQ6,BS6,BU6,BW6,BY6,CA6) | C6: J&KBANK | D6: The Jammu & Kashmir Bank Limited | E6: bank | F6: banks - private sector | G6: midcap | H6: 16369.08 | I6: 147.68 | J6: -0.65 | K6: 4046091 | L6: 47 | M6: Outperforming | N6: =IF(M6="Underperforming",-5,IF(L6>=95,15,IF(L6>=90,10,IF(L6>=80,5,0)))) | O6: 69.6 | P6: 48.37 | Q6: 116.79 | R6: Near 52W High Breakout | S6: Nifty Bank | T6: -4.01 | U6: 41.05 | V6: 46.95 | W6: 12.52 | X6: Growing Industry | Y6: =IF(X6="Growing Industry",10,IF(X6="Cyclical in an Upturn",5,0)) | Z6: Fragmented with High ROE | AA6: =IF(Z6="Fragmented with Low ROE",-5,IF(Z6="Fragmented with High ROE",10,IF(Z6= "highly cyclical",5,0))) | AB6: Yes | AC6: =IF(AB6="No",5,0) | AD6: Tailwind | AE6: =IF(AD6="Tailwind",10,0) | AF6: Structural (10 Years Consistency) | AG6: =IF(AF6="Structural (10 Years Consistency)",15,IF(AF6="Shallow Cyclical (2 to 3 years growth)",10,IF(AF6 = "Cyclical in an Uptick",5,IF(AF6 = "Cyclical in an Downtick",-10,0)))) | AH6: Yes | AI6: =IF(AH6="Yes",10,0) | AJ6: Yes | AK6: =IF(AJ6="Yes",10,0) | AM6: =IF(AL6="No",10,0) | AN6: Yes | AO6: =IF(AN6="Yes",10,0) | AP6: Yes | AQ6: =IF(AP6="Yes",10,0) | AR6: Yes | AS6: =IF(AR6="Yes",5,0) | AT6: No | AU6: =IF(AT6="No",10,IF(AT6="Yes",-10,0)) | AV6: No | AW6: =IF(AV6="No",10,0) | AX6: No | AY6: =IF(AX6="No",10,IF(AX6= "Yes CEO Resignation",-5,0)) | AZ6: No | BA6: =IF(AZ6="No",10,IF(AZ6="Yes",-5,0)) | BB6: No | BC6: =IF(BB6="No",5,IF(BB6="Yes",-5,0)) | BD6: Yes | BE6: =IF(BD6="Yes",10,0) | BF6: Yes | BG6: =IF(BF6="Yes",10,0) | BH6: Yes | BI6: =IF(BH6="Yes",10,0) | BJ6: P/BV less than 2.5x and Growth less than 20% | BK6: =IF(BJ6="P/BV less than 2.5x and Growth more than 20%",20,IF(BJ6 = "P/BV less than 2.5x and Growth less than 20%",5,IF(BJ6="P/BV between 2.5x to 5x and Growth more than 20%",10,IF(BJ6= "P/BV between 2.5x to 5x and Growth less than 20%",-5,IF(BJ6= "P/BV above 5x",-5,0))))) | BL6: Above 40 | BM6: =IF(BL6="Above 40",20,IF(BL6="20 to 40",10,IF(BL6="0 to 20",-5,0))) | BN6: Between 50 to 75 | BO6: =IF(BN6="Between 50 to 75",10,IF(BN6="Above 75",0,0)) | BP6: Stage 2 | BQ6: =IF(BP6="Stage 2",20,IF(BP6="Stage 1",0,IF(BP6="Stage 3",5,IF(BP6="Stage 4",-5,0)))) | BR6: Positive Trend | BS6: =IF(BR6="Positive Trend",20,IF(BR6="Negative Trend",-10,0)) | BT6: Uptrend | BU6: =IF(BT6="Uptrend",10,IF(BT6="Sideways",5,0)) | BV6: Uptrend | BW6: =IF(BV6="Uptrend",10,IF(BV6="Sideways",5,0)) | BX6: Blue sky scenario | BY6: =IF(BX6="Overhead supply in last 2 years in last 2 years",-5,IF(BX6="Close to 52 week high or retracement",5,IF(BX6="Blue sky scenario",10,IF(BX6="Long term Downtrend",-10,0)))) | BZ6: Yes | CA6: =IF(BZ6="Yes",10,0)
A7: =IF(B7=0,"",RANK(B7,$B$2:$B$32,0)) | B7: =SUM(N7,Y7,AA7,AC7,AE7,AG7,AI7,AK7,AM7,AO7,AQ7,AS7,AU7,AW7,AY7,BA7,BC7,BE7,BG7,BI7,BK7,BM7,BO7,BQ7,BS7,BU7,BW7,BY7,CA7) | C7: NORTHARC | D7: Northern ARC Capital Ltd | E7: financials | F7: finance & investments | G7: smallcap | H7: 4734.86 | I7: 290.3 | J7: -0.94 | K7: 1051408 | L7: 39 | M7: Outperforming | N7: =IF(M7="Underperforming",-5,IF(L7>=95,15,IF(L7>=90,10,IF(L7>=80,5,0)))) | O7: 63.47 | P7: 29.23 | Q7: 222.37 | R7: Near 52W High Breakout | S7: Nifty Bank | T7: -4.01 | U7: 33.67 | V7: 39.26 | W7: 10.6 | X7: Growing Industry | Y7: =IF(X7="Growing Industry",10,IF(X7="Cyclical in an Upturn",5,0)) | Z7: Fragmented with High ROE | AA7: =IF(Z7="Fragmented with Low ROE",-5,IF(Z7="Fragmented with High ROE",10,IF(Z7= "highly cyclical",5,0))) | AB7: Yes | AC7: =IF(AB7="No",5,0) | AD7: Tailwind | AE7: =IF(AD7="Tailwind",10,0) | AF7: Structural (10 Years Consistency) | AG7: =IF(AF7="Structural (10 Years Consistency)",15,IF(AF7="Shallow Cyclical (2 to 3 years growth)",10,IF(AF7 = "Cyclical in an Uptick",5,IF(AF7 = "Cyclical in an Downtick",-10,0)))) | AH7: Yes | AI7: =IF(AH7="Yes",10,0) | AJ7: Yes | AK7: =IF(AJ7="Yes",10,0) | AM7: =IF(AL7="No",10,0) | AN7: Yes | AO7: =IF(AN7="Yes",10,0) | AP7: Yes | AQ7: =IF(AP7="Yes",10,0) | AR7: Yes | AS7: =IF(AR7="Yes",5,0) | AT7: No | AU7: =IF(AT7="No",10,IF(AT7="Yes",-10,0)) | AV7: No | AW7: =IF(AV7="No",10,0) | AX7: No | AY7: =IF(AX7="No",10,IF(AX7= "Yes CEO Resignation",-5,0)) | AZ7: No | BA7: =IF(AZ7="No",10,IF(AZ7="Yes",-5,0)) | BB7: No | BC7: =IF(BB7="No",5,IF(BB7="Yes",-5,0)) | BD7: Yes | BE7: =IF(BD7="Yes",10,0) | BF7: Yes | BG7: =IF(BF7="Yes",10,0) | BH7: Yes | BI7: =IF(BH7="Yes",10,0) | BJ7: P/BV less than 2.5x and Growth more than 20% | BK7: =IF(BJ7="P/BV less than 2.5x and Growth more than 20%",20,IF(BJ7 = "P/BV less than 2.5x and Growth less than 20%",5,IF(BJ7="P/BV between 2.5x to 5x and Growth more than 20%",10,IF(BJ7= "P/BV between 2.5x to 5x and Growth less than 20%",-5,IF(BJ7= "P/BV above 5x",-5,0))))) | BL7: 20 to 40 | BM7: =IF(BL7="Above 40",20,IF(BL7="20 to 40",10,IF(BL7="0 to 20",-5,0))) | BN7: Between 50 to 75 | BO7: =IF(BN7="Between 50 to 75",10,IF(BN7="Above 75",0,0)) | BP7: Stage 2 | BQ7: =IF(BP7="Stage 2",20,IF(BP7="Stage 1",0,IF(BP7="Stage 3",5,IF(BP7="Stage 4",-5,0)))) | BR7: Positive Trend | BS7: =IF(BR7="Positive Trend",20,IF(BR7="Negative Trend",-10,0)) | BT7: Uptrend | BU7: =IF(BT7="Uptrend",10,IF(BT7="Sideways",5,0)) | BV7: Uptrend | BW7: =IF(BV7="Uptrend",10,IF(BV7="Sideways",5,0)) | BX7: Close to 52 week high or retracement | BY7: =IF(BX7="Overhead supply in last 2 years in last 2 years",-5,IF(BX7="Close to 52 week high or retracement",5,IF(BX7="Blue sky scenario",10,IF(BX7="Long term Downtrend",-10,0)))) | BZ7: Yes | CA7: =IF(BZ7="Yes",10,0)
A8: =IF(B8=0,"",RANK(B8,$B$2:$B$32,0)) | B8: =SUM(N8,Y8,AA8,AC8,AE8,AG8,AI8,AK8,AM8,AO8,AQ8,AS8,AU8,AW8,AY8,BA8,BC8,BE8,BG8,BI8,BK8,BM8,BO8,BQ8,BS8,BU8,BW8,BY8,CA8) | C8: WELINV | D8: Welspun Investments And Commercials Limited | E8: financials | F8: finance & investments | G8: smallcap | H8: 678.97 | I8: 1773.8 | J8: -4.53 | K8: 33 | L8: 65 | M8: Outperforming | N8: =IF(M8="Underperforming",-5,IF(L8>=95,15,IF(L8>=90,10,IF(L8>=80,5,0)))) | O8: 71.09 | P8: 40.7 | Q8: 1417.85 | R8: Earnings / Momentum Support | S8: Nifty Bank | T8: -4.01 | U8: 52.07 | V8: 58.43 | W8: 18.27 | X8: Growing Industry | Y8: =IF(X8="Growing Industry",10,IF(X8="Cyclical in an Upturn",5,0)) | Z8: Fragmented with High ROE | AA8: =IF(Z8="Fragmented with Low ROE",-5,IF(Z8="Fragmented with High ROE",10,IF(Z8= "highly cyclical",5,0))) | AB8: Yes | AC8: =IF(AB8="No",5,0) | AD8: Tailwind | AE8: =IF(AD8="Tailwind",10,0) | AF8: Structural (10 Years Consistency) | AG8: =IF(AF8="Structural (10 Years Consistency)",15,IF(AF8="Shallow Cyclical (2 to 3 years growth)",10,IF(AF8 = "Cyclical in an Uptick",5,IF(AF8 = "Cyclical in an Downtick",-10,0)))) | AH8: Yes | AI8: =IF(AH8="Yes",10,0) | AJ8: Yes | AK8: =IF(AJ8="Yes",10,0) | AM8: =IF(AL8="No",10,0) | AN8: Yes | AO8: =IF(AN8="Yes",10,0) | AP8: No | AQ8: =IF(AP8="Yes",10,0) | AR8: Yes | AS8: =IF(AR8="Yes",5,0) | AT8: No | AU8: =IF(AT8="No",10,IF(AT8="Yes",-10,0)) | AV8: No | AW8: =IF(AV8="No",10,0) | AX8: No | AY8: =IF(AX8="No",10,IF(AX8= "Yes CEO Resignation",-5,0)) | AZ8: No | BA8: =IF(AZ8="No",10,IF(AZ8="Yes",-5,0)) | BB8: No | BC8: =IF(BB8="No",5,IF(BB8="Yes",-5,0)) | BD8: Yes | BE8: =IF(BD8="Yes",10,0) | BF8: Yes | BG8: =IF(BF8="Yes",10,0) | BH8: Yes | BI8: =IF(BH8="Yes",10,0) | BJ8: P/BV less than 2.5x and Growth more than 20% | BK8: =IF(BJ8="P/BV less than 2.5x and Growth more than 20%",20,IF(BJ8 = "P/BV less than 2.5x and Growth less than 20%",5,IF(BJ8="P/BV between 2.5x to 5x and Growth more than 20%",10,IF(BJ8= "P/BV between 2.5x to 5x and Growth less than 20%",-5,IF(BJ8= "P/BV above 5x",-5,0))))) | BL8: Above 40 | BM8: =IF(BL8="Above 40",20,IF(BL8="20 to 40",10,IF(BL8="0 to 20",-5,0))) | BN8: Between 50 to 75 | BO8: =IF(BN8="Between 50 to 75",10,IF(BN8="Above 75",0,0)) | BP8: Stage 2 | BQ8: =IF(BP8="Stage 2",20,IF(BP8="Stage 1",0,IF(BP8="Stage 3",5,IF(BP8="Stage 4",-5,0)))) | BR8: Positive Trend | BS8: =IF(BR8="Positive Trend",20,IF(BR8="Negative Trend",-10,0)) | BT8: Uptrend | BU8: =IF(BT8="Uptrend",10,IF(BT8="Sideways",5,0)) | BV8: Uptrend | BW8: =IF(BV8="Uptrend",10,IF(BV8="Sideways",5,0)) | BX8: Close to 52 week high or retracement | BY8: =IF(BX8="Overhead supply in last 2 years in last 2 years",-5,IF(BX8="Close to 52 week high or retracement",5,IF(BX8="Blue sky scenario",10,IF(BX8="Long term Downtrend",-10,0)))) | BZ8: Yes | CA8: =IF(BZ8="Yes",10,0)
A9: =IF(B9=0,"",RANK(B9,$B$2:$B$32,0)) | B9: =SUM(N9,Y9,AA9,AC9,AE9,AG9,AI9,AK9,AM9,AO9,AQ9,AS9,AU9,AW9,AY9,BA9,BC9,BE9,BG9,BI9,BK9,BM9,BO9,BQ9,BS9,BU9,BW9,BY9,CA9) | C9: SATIN | D9: Satin Creditcare Network Limited | E9: financials | F9: finance & investments | G9: smallcap | H9: 2598.83 | I9: 241.93 | J9: 2.84 | K9: 2487322 | L9: 74 | M9: Outperforming | N9: =IF(M9="Underperforming",-5,IF(L9>=95,15,IF(L9>=90,10,IF(L9>=80,5,0)))) | O9: 77.25 | P9: 37.11 | Q9: 189.94 | R9: Near 52W High Breakout | S9: Nifty Bank | T9: -4.01 | U9: 53.21 | V9: 59.61 | W9: 23.26 | X9: Growing Industry | Y9: =IF(X9="Growing Industry",10,IF(X9="Cyclical in an Upturn",5,0)) | Z9: Fragmented with High ROE | AA9: =IF(Z9="Fragmented with Low ROE",-5,IF(Z9="Fragmented with High ROE",10,IF(Z9= "highly cyclical",5,0))) | AB9: Yes | AC9: =IF(AB9="No",5,0) | AD9: Tailwind | AE9: =IF(AD9="Tailwind",10,0) | AF9: Structural (10 Years Consistency) | AG9: =IF(AF9="Structural (10 Years Consistency)",15,IF(AF9="Shallow Cyclical (2 to 3 years growth)",10,IF(AF9 = "Cyclical in an Uptick",5,IF(AF9 = "Cyclical in an Downtick",-10,0)))) | AH9: Yes | AI9: =IF(AH9="Yes",10,0) | AJ9: Yes | AK9: =IF(AJ9="Yes",10,0) | AM9: =IF(AL9="No",10,0) | AN9: Yes | AO9: =IF(AN9="Yes",10,0) | AP9: Yes | AQ9: =IF(AP9="Yes",10,0) | AR9: Yes | AS9: =IF(AR9="Yes",5,0) | AT9: No | AU9: =IF(AT9="No",10,IF(AT9="Yes",-10,0)) | AV9: No | AW9: =IF(AV9="No",10,0) | AX9: No | AY9: =IF(AX9="No",10,IF(AX9= "Yes CEO Resignation",-5,0)) | AZ9: No | BA9: =IF(AZ9="No",10,IF(AZ9="Yes",-5,0)) | BB9: No | BC9: =IF(BB9="No",5,IF(BB9="Yes",-5,0)) | BD9: Yes | BE9: =IF(BD9="Yes",10,0) | BF9: Yes | BG9: =IF(BF9="Yes",10,0) | BH9: Yes | BI9: =IF(BH9="Yes",10,0) | BJ9: P/BV less than 2.5x and Growth more than 20% | BK9: =IF(BJ9="P/BV less than 2.5x and Growth more than 20%",20,IF(BJ9 = "P/BV less than 2.5x and Growth less than 20%",5,IF(BJ9="P/BV between 2.5x to 5x and Growth more than 20%",10,IF(BJ9= "P/BV between 2.5x to 5x and Growth less than 20%",-5,IF(BJ9= "P/BV above 5x",-5,0))))) | BL9: 20 to 40 | BM9: =IF(BL9="Above 40",20,IF(BL9="20 to 40",10,IF(BL9="0 to 20",-5,0))) | BN9: Above 75 | BO9: =IF(BN9="Between 50 to 75",10,IF(BN9="Above 75",0,0)) | BP9: Stage 2 | BQ9: =IF(BP9="Stage 2",20,IF(BP9="Stage 1",0,IF(BP9="Stage 3",5,IF(BP9="Stage 4",-5,0)))) | BR9: Positive Trend | BS9: =IF(BR9="Positive Trend",20,IF(BR9="Negative Trend",-10,0)) | BT9: Uptrend | BU9: =IF(BT9="Uptrend",10,IF(BT9="Sideways",5,0)) | BV9: Uptrend | BW9: =IF(BV9="Uptrend",10,IF(BV9="Sideways",5,0)) | BX9: Blue sky scenario | BY9: =IF(BX9="Overhead supply in last 2 years in last 2 years",-5,IF(BX9="Close to 52 week high or retracement",5,IF(BX9="Blue sky scenario",10,IF(BX9="Long term Downtrend",-10,0)))) | BZ9: Yes | CA9: =IF(BZ9="Yes",10,0)
A10: =IF(B10=0,"",RANK(B10,$B$2:$B$32,0)) | B10: =SUM(N10,Y10,AA10,AC10,AE10,AG10,AI10,AK10,AM10,AO10,AQ10,AS10,AU10,AW10,AY10,BA10,BC10,BE10,BG10,BI10,BK10,BM10,BO10,BQ10,BS10,BU10,BW10,BY10,CA10) | C10: FEDERALBNK | D10: The Federal Bank Limited | E10: bank | F10: banks - private sector | G10: largecap | H10: 74187.22 | I10: 300.1 | J10: -0.32 | K10: 11947303 | L10: 35 | M10: Outperforming | N10: =IF(M10="Underperforming",-5,IF(L10>=95,15,IF(L10>=90,10,IF(L10>=80,5,0)))) | O10: 62.86 | P10: 19.64 | Q10: 253.53 | R10: Near 52W High Breakout | S10: Nifty Bank | T10: -4.01 | U10: 45.31 | V10: 51.38 | W10: 9.66 | X10: Growing Industry | Y10: =IF(X10="Growing Industry",10,IF(X10="Cyclical in an Upturn",5,0)) | Z10: Fragmented with High ROE | AA10: =IF(Z10="Fragmented with Low ROE",-5,IF(Z10="Fragmented with High ROE",10,IF(Z10= "highly cyclical",5,0))) | AB10: Yes | AC10: =IF(AB10="No",5,0) | AD10: Tailwind | AE10: =IF(AD10="Tailwind",10,0) | AF10: Structural (10 Years Consistency) | AG10: =IF(AF10="Structural (10 Years Consistency)",15,IF(AF10="Shallow Cyclical (2 to 3 years growth)",10,IF(AF10 = "Cyclical in an Uptick",5,IF(AF10 = "Cyclical in an Downtick",-10,0)))) | AH10: Yes | AI10: =IF(AH10="Yes",10,0) | AJ10: Yes | AK10: =IF(AJ10="Yes",10,0) | AM10: =IF(AL10="No",10,0) | AN10: Yes | AO10: =IF(AN10="Yes",10,0) | AP10: Yes | AQ10: =IF(AP10="Yes",10,0) | AR10: Yes | AS10: =IF(AR10="Yes",5,0) | AT10: No | AU10: =IF(AT10="No",10,IF(AT10="Yes",-10,0)) | AV10: No | AW10: =IF(AV10="No",10,0) | AX10: No | AY10: =IF(AX10="No",10,IF(AX10= "Yes CEO Resignation",-5,0)) | AZ10: No | BA10: =IF(AZ10="No",10,IF(AZ10="Yes",-5,0)) | BB10: No | BC10: =IF(BB10="No",5,IF(BB10="Yes",-5,0)) | BD10: Yes | BE10: =IF(BD10="Yes",10,0) | BF10: Yes | BG10: =IF(BF10="Yes",10,0) | BH10: Yes | BI10: =IF(BH10="Yes",10,0) | BJ10: P/BV less than 2.5x and Growth more than 20% | BK10: =IF(BJ10="P/BV less than 2.5x and Growth more than 20%",20,IF(BJ10 = "P/BV less than 2.5x and Growth less than 20%",5,IF(BJ10="P/BV between 2.5x to 5x and Growth more than 20%",10,IF(BJ10= "P/BV between 2.5x to 5x and Growth less than 20%",-5,IF(BJ10= "P/BV above 5x",-5,0))))) | BL10: 0 to 20 | BM10: =IF(BL10="Above 40",20,IF(BL10="20 to 40",10,IF(BL10="0 to 20",-5,0))) | BN10: Between 50 to 75 | BO10: =IF(BN10="Between 50 to 75",10,IF(BN10="Above 75",0,0)) | BP10: Stage 2 | BQ10: =IF(BP10="Stage 2",20,IF(BP10="Stage 1",0,IF(BP10="Stage 3",5,IF(BP10="Stage 4",-5,0)))) | BR10: Positive Trend | BS10: =IF(BR10="Positive Trend",20,IF(BR10="Negative Trend",-10,0)) | BT10: Uptrend | BU10: =IF(BT10="Uptrend",10,IF(BT10="Sideways",5,0)) | BV10: Uptrend | BW10: =IF(BV10="Uptrend",10,IF(BV10="Sideways",5,0)) | BX10: Blue sky scenario | BY10: =IF(BX10="Overhead supply in last 2 years in last 2 years",-5,IF(BX10="Close to 52 week high or retracement",5,IF(BX10="Blue sky scenario",10,IF(BX10="Long term Downtrend",-10,0)))) | BZ10: Yes | CA10: =IF(BZ10="Yes",10,0)
A11: =IF(B11=0,"",RANK(B11,$B$2:$B$32,0)) | B11: =SUM(N11,Y11,AA11,AC11,AE11,AG11,AI11,AK11,AM11,AO11,AQ11,AS11,AU11,AW11,AY11,BA11,BC11,BE11,BG11,BI11,BK11,BM11,BO11,BQ11,BS11,BU11,BW11,BY11,CA11) | C11: STARHEALTH | D11: Star Health & Allied Insurance Company Ltd | E11: financials | F11: finance & investments | G11: largecap | H11: 31188.33 | I11: 526.25 | J11: -0.72 | K11: 222957 | L11: 17 | M11: Outperforming | N11: =IF(M11="Underperforming",-5,IF(L11>=95,15,IF(L11>=90,10,IF(L11>=80,5,0)))) | O11: 62.63 | P11: 23.71 | Q11: 434.55 | R11: Near 52W High Breakout | S11: Nifty Bank | T11: -4.01 | U11: 11.97 | V11: 16.65 | W11: 5.45 | X11: Growing Industry | Y11: =IF(X11="Growing Industry",10,IF(X11="Cyclical in an Upturn",5,0)) | Z11: Fragmented with High ROE | AA11: =IF(Z11="Fragmented with Low ROE",-5,IF(Z11="Fragmented with High ROE",10,IF(Z11= "highly cyclical",5,0))) | AB11: Yes | AC11: =IF(AB11="No",5,0) | AD11: Tailwind | AE11: =IF(AD11="Tailwind",10,0) | AF11: Structural (10 Years Consistency) | AG11: =IF(AF11="Structural (10 Years Consistency)",15,IF(AF11="Shallow Cyclical (2 to 3 years growth)",10,IF(AF11 = "Cyclical in an Uptick",5,IF(AF11 = "Cyclical in an Downtick",-10,0)))) | AH11: Yes | AI11: =IF(AH11="Yes",10,0) | AJ11: Yes | AK11: =IF(AJ11="Yes",10,0) | AM11: =IF(AL11="No",10,0) | AN11: Yes | AO11: =IF(AN11="Yes",10,0) | AP11: Yes | AQ11: =IF(AP11="Yes",10,0) | AR11: Yes | AS11: =IF(AR11="Yes",5,0) | AT11: No | AU11: =IF(AT11="No",10,IF(AT11="Yes",-10,0)) | AV11: No | AW11: =IF(AV11="No",10,0) | AX11: No | AY11: =IF(AX11="No",10,IF(AX11= "Yes CEO Resignation",-5,0)) | AZ11: No | BA11: =IF(AZ11="No",10,IF(AZ11="Yes",-5,0)) | BB11: No | BC11: =IF(BB11="No",5,IF(BB11="Yes",-5,0)) | BD11: Yes | BE11: =IF(BD11="Yes",10,0) | BF11: Yes | BG11: =IF(BF11="Yes",10,0) | BH11: Yes | BI11: =IF(BH11="Yes",10,0) | BJ11: P/BV between 2.5x to 5x and Growth more than 20% | BK11: =IF(BJ11="P/BV less than 2.5x and Growth more than 20%",20,IF(BJ11 = "P/BV less than 2.5x and Growth less than 20%",5,IF(BJ11="P/BV between 2.5x to 5x and Growth more than 20%",10,IF(BJ11= "P/BV between 2.5x to 5x and Growth less than 20%",-5,IF(BJ11= "P/BV above 5x",-5,0))))) | BL11: 20 to 40 | BM11: =IF(BL11="Above 40",20,IF(BL11="20 to 40",10,IF(BL11="0 to 20",-5,0))) | BN11: Between 50 to 75 | BO11: =IF(BN11="Between 50 to 75",10,IF(BN11="Above 75",0,0)) | BP11: Stage 2 | BQ11: =IF(BP11="Stage 2",20,IF(BP11="Stage 1",0,IF(BP11="Stage 3",5,IF(BP11="Stage 4",-5,0)))) | BR11: Positive Trend | BS11: =IF(BR11="Positive Trend",20,IF(BR11="Negative Trend",-10,0)) | BT11: Uptrend | BU11: =IF(BT11="Uptrend",10,IF(BT11="Sideways",5,0)) | BV11: Uptrend | BW11: =IF(BV11="Uptrend",10,IF(BV11="Sideways",5,0)) | BX11: Close to 52 week high or retracement | BY11: =IF(BX11="Overhead supply in last 2 years in last 2 years",-5,IF(BX11="Close to 52 week high or retracement",5,IF(BX11="Blue sky scenario",10,IF(BX11="Long term Downtrend",-10,0)))) | BZ11: Yes | CA11: =IF(BZ11="Yes",10,0)
A12: =IF(B12=0,"",RANK(B12,$B$2:$B$32,0)) | B12: =SUM(N12,Y12,AA12,AC12,AE12,AG12,AI12,AK12,AM12,AO12,AQ12,AS12,AU12,AW12,AY12,BA12,BC12,BE12,BG12,BI12,BK12,BM12,BO12,BQ12,BS12,BU12,BW12,BY12,CA12) | C12: RANEHOLDIN | D12: Rane Holdings Limited | E12: financials | F12: finance & investments | G12: smallcap | H12: 2118.54 | I12: 1459.4 | J12: -1.64 | K12: 40357 | L12: 10 | M12: Outperforming | N12: =IF(M12="Underperforming",-5,IF(L12>=95,15,IF(L12>=90,10,IF(L12>=80,5,0)))) | O12: 61.66 | P12: 24.35 | Q12: 1070.79 | R12: Earnings / Momentum Support | S12: Nifty Bank | T12: -4.01 | U12: -3.86 | V12: 0.16 | W12: 3.92 | X12: Growing Industry | Y12: =IF(X12="Growing Industry",10,IF(X12="Cyclical in an Upturn",5,0)) | Z12: Fragmented with High ROE | AA12: =IF(Z12="Fragmented with Low ROE",-5,IF(Z12="Fragmented with High ROE",10,IF(Z12= "highly cyclical",5,0))) | AB12: Yes | AC12: =IF(AB12="No",5,0) | AD12: Tailwind | AE12: =IF(AD12="Tailwind",10,0) | AF12: Structural (10 Years Consistency) | AG12: =IF(AF12="Structural (10 Years Consistency)",15,IF(AF12="Shallow Cyclical (2 to 3 years growth)",10,IF(AF12 = "Cyclical in an Uptick",5,IF(AF12 = "Cyclical in an Downtick",-10,0)))) | AH12: Yes | AI12: =IF(AH12="Yes",10,0) | AJ12: Yes | AK12: =IF(AJ12="Yes",10,0) | AM12: =IF(AL12="No",10,0) | AN12: Yes | AO12: =IF(AN12="Yes",10,0) | AP12: No | AQ12: =IF(AP12="Yes",10,0) | AR12: Yes | AS12: =IF(AR12="Yes",5,0) | AT12: No | AU12: =IF(AT12="No",10,IF(AT12="Yes",-10,0)) | AV12: No | AW12: =IF(AV12="No",10,0) | AX12: No | AY12: =IF(AX12="No",10,IF(AX12= "Yes CEO Resignation",-5,0)) | AZ12: No | BA12: =IF(AZ12="No",10,IF(AZ12="Yes",-5,0)) | BB12: No | BC12: =IF(BB12="No",5,IF(BB12="Yes",-5,0)) | BD12: Yes | BE12: =IF(BD12="Yes",10,0) | BF12: Yes | BG12: =IF(BF12="Yes",10,0) | BH12: Yes | BI12: =IF(BH12="Yes",10,0) | BJ12: P/BV less than 2.5x and Growth more than 20% | BK12: =IF(BJ12="P/BV less than 2.5x and Growth more than 20%",20,IF(BJ12 = "P/BV less than 2.5x and Growth less than 20%",5,IF(BJ12="P/BV between 2.5x to 5x and Growth more than 20%",10,IF(BJ12= "P/BV between 2.5x to 5x and Growth less than 20%",-5,IF(BJ12= "P/BV above 5x",-5,0))))) | BL12: 20 to 40 | BM12: =IF(BL12="Above 40",20,IF(BL12="20 to 40",10,IF(BL12="0 to 20",-5,0))) | BN12: Between 50 to 75 | BO12: =IF(BN12="Between 50 to 75",10,IF(BN12="Above 75",0,0)) | BP12: Stage 2 | BQ12: =IF(BP12="Stage 2",20,IF(BP12="Stage 1",0,IF(BP12="Stage 3",5,IF(BP12="Stage 4",-5,0)))) | BR12: Positive Trend | BS12: =IF(BR12="Positive Trend",20,IF(BR12="Negative Trend",-10,0)) | BT12: Uptrend | BU12: =IF(BT12="Uptrend",10,IF(BT12="Sideways",5,0)) | BV12: Uptrend | BW12: =IF(BV12="Uptrend",10,IF(BV12="Sideways",5,0)) | BX12: Close to 52 week high or retracement | BY12: =IF(BX12="Overhead supply in last 2 years in last 2 years",-5,IF(BX12="Close to 52 week high or retracement",5,IF(BX12="Blue sky scenario",10,IF(BX12="Long term Downtrend",-10,0)))) | BZ12: Yes | CA12: =IF(BZ12="Yes",10,0)
A13: =IF(B13=0,"",RANK(B13,$B$2:$B$32,0)) | B13: =SUM(N13,Y13,AA13,AC13,AE13,AG13,AI13,AK13,AM13,AO13,AQ13,AS13,AU13,AW13,AY13,BA13,BC13,BE13,BG13,BI13,BK13,BM13,BO13,BQ13,BS13,BU13,BW13,BY13,CA13) | C13: CONSOFINVT | D13: Consolidated Finvest & Holdings Limited | E13: financials | F13: finance & investments | G13: smallcap | H13: 785.43 | I13: 238.68 | J13: -1.77 | K13: 4986 | L13: 20 | M13: Outperforming | N13: =IF(M13="Underperforming",-5,IF(L13>=95,15,IF(L13>=90,10,IF(L13>=80,5,0)))) | O13: 65.54 | P13: 23.63 | Q13: 185.74 | R13: Volume Spike & Near 52W High Breakout | S13: Nifty Bank | T13: -4.01 | U13: 19.41 | V13: 24.4 | W13: 6.05 | X13: Growing Industry | Y13: =IF(X13="Growing Industry",10,IF(X13="Cyclical in an Upturn",5,0)) | Z13: Fragmented with High ROE | AA13: =IF(Z13="Fragmented with Low ROE",-5,IF(Z13="Fragmented with High ROE",10,IF(Z13= "highly cyclical",5,0))) | AB13: Yes | AC13: =IF(AB13="No",5,0) | AD13: Tailwind | AE13: =IF(AD13="Tailwind",10,0) | AF13: Structural (10 Years Consistency) | AG13: =IF(AF13="Structural (10 Years Consistency)",15,IF(AF13="Shallow Cyclical (2 to 3 years growth)",10,IF(AF13 = "Cyclical in an Uptick",5,IF(AF13 = "Cyclical in an Downtick",-10,0)))) | AH13: Yes | AI13: =IF(AH13="Yes",10,0) | AJ13: Yes | AK13: =IF(AJ13="Yes",10,0) | AM13: =IF(AL13="No",10,0) | AN13: Yes | AO13: =IF(AN13="Yes",10,0) | AP13: Yes | AQ13: =IF(AP13="Yes",10,0) | AR13: Yes | AS13: =IF(AR13="Yes",5,0) | AT13: No | AU13: =IF(AT13="No",10,IF(AT13="Yes",-10,0)) | AV13: No | AW13: =IF(AV13="No",10,0) | AX13: No | AY13: =IF(AX13="No",10,IF(AX13= "Yes CEO Resignation",-5,0)) | AZ13: No | BA13: =IF(AZ13="No",10,IF(AZ13="Yes",-5,0)) | BB13: No | BC13: =IF(BB13="No",5,IF(BB13="Yes",-5,0)) | BD13: Yes | BE13: =IF(BD13="Yes",10,0) | BF13: Yes | BG13: =IF(BF13="Yes",10,0) | BH13: Yes | BI13: =IF(BH13="Yes",10,0) | BJ13: P/BV less than 2.5x and Growth less than 20% | BK13: =IF(BJ13="P/BV less than 2.5x and Growth more than 20%",20,IF(BJ13 = "P/BV less than 2.5x and Growth less than 20%",5,IF(BJ13="P/BV between 2.5x to 5x and Growth more than 20%",10,IF(BJ13= "P/BV between 2.5x to 5x and Growth less than 20%",-5,IF(BJ13= "P/BV above 5x",-5,0))))) | BL13: 20 to 40 | BM13: =IF(BL13="Above 40",20,IF(BL13="20 to 40",10,IF(BL13="0 to 20",-5,0))) | BN13: Between 50 to 75 | BO13: =IF(BN13="Between 50 to 75",10,IF(BN13="Above 75",0,0)) | BP13: Stage 2 | BQ13: =IF(BP13="Stage 2",20,IF(BP13="Stage 1",0,IF(BP13="Stage 3",5,IF(BP13="Stage 4",-5,0)))) | BR13: Positive Trend | BS13: =IF(BR13="Positive Trend",20,IF(BR13="Negative Trend",-10,0)) | BT13: Uptrend | BU13: =IF(BT13="Uptrend",10,IF(BT13="Sideways",5,0)) | BV13: Uptrend | BW13: =IF(BV13="Uptrend",10,IF(BV13="Sideways",5,0)) | BX13: Blue sky scenario | BY13: =IF(BX13="Overhead supply in last 2 years in last 2 years",-5,IF(BX13="Close to 52 week high or retracement",5,IF(BX13="Blue sky scenario",10,IF(BX13="Long term Downtrend",-10,0)))) | BZ13: Yes | CA13: =IF(BZ13="Yes",10,0)
... A22: =IF(B22=0,"",RANK(B22,$B$2:$B$32,0)) | B22: =SUM(N22,Y22,AA22,AC22,AE22,AG22,AI22,AK22,AM22,AO22,AQ22,AS22,AU22,AW22,AY22,BA22,BC22,BE22,BG22,BI22,BK22,BM22,BO22,BQ22,BS22,BU22,BW22,BY22,CA22) | C22: SOUTHBANK | D22: The South Indian Bank Limited | E22: bank | F22: banks - private sector | G22: midcap | H22: 11412.6 | I22: 44.61 | J22: 2.32 | K22: 26453430 | L22: 47 | M22: Outperforming | N22: =IF(M22="Underperforming",-5,IF(L22>=95,15,IF(L22>=90,10,IF(L22>=80,5,0)))) | O22: 64.43 | P22: 11.36 | Q22: 35.07 | R22: Near 52W High Breakout | S22: Nifty Bank | T22: -4.01 | U22: 55.11 | V22: 61.6 | W22: 12.53 | X22: Growing Industry | Y22: =IF(X22="Growing Industry",10,IF(X22="Cyclical in an Upturn",5,0)) | Z22: Fragmented with High ROE | AA22: =IF(Z22="Fragmented with Low ROE",-5,IF(Z22="Fragmented with High ROE",10,IF(Z22= "highly cyclical",5,0))) | AB22: Yes | AC22: =IF(AB22="No",5,0) | AD22: Tailwind | AE22: =IF(AD22="Tailwind",10,0) | AF22: Structural (10 Years Consistency) | AG22: =IF(AF22="Structural (10 Years Consistency)",15,IF(AF22="Shallow Cyclical (2 to 3 years growth)",10,IF(AF22 = "Cyclical in an Uptick",5,IF(AF22 = "Cyclical in an Downtick",-10,0)))) | AH22: Yes | AI22: =IF(AH22="Yes",10,0) | AJ22: Yes | AK22: =IF(AJ22="Yes",10,0) | AM22: =IF(AL22="No",10,0) | AN22: Yes | AO22: =IF(AN22="Yes",10,0) | AP22: Yes | AQ22: =IF(AP22="Yes",10,0) | AR22: Yes | AS22: =IF(AR22="Yes",5,0) | AT22: No | AU22: =IF(AT22="No",10,IF(AT22="Yes",-10,0)) | AV22: No | AW22: =IF(AV22="No",10,0) | AX22: No | AY22: =IF(AX22="No",10,IF(AX22= "Yes CEO Resignation",-5,0)) | AZ22: No | BA22: =IF(AZ22="No",10,IF(AZ22="Yes",-5,0)) | BB22: No | BC22: =IF(BB22="No",5,IF(BB22="Yes",-5,0)) | BD22: Yes | BE22: =IF(BD22="Yes",10,0) | BF22: Yes | BG22: =IF(BF22="Yes",10,0) | BH22: Yes | BI22: =IF(BH22="Yes",10,0) | BJ22: P/BV less than 2.5x and Growth less than 20% | BK22: =IF(BJ22="P/BV less than 2.5x and Growth more than 20%",20,IF(BJ22 = "P/BV less than 2.5x and Growth less than 20%",5,IF(BJ22="P/BV between 2.5x to 5x and Growth more than 20%",10,IF(BJ22= "P/BV between 2.5x to 5x and Growth less than 20%",-5,IF(BJ22= "P/BV above 5x",-5,0))))) | BL22: 0 to 20 | BM22: =IF(BL22="Above 40",20,IF(BL22="20 to 40",10,IF(BL22="0 to 20",-5,0))) | BN22: Between 50 to 75 | BO22: =IF(BN22="Between 50 to 75",10,IF(BN22="Above 75",0,0)) | BP22: Stage 2 | BQ22: =IF(BP22="Stage 2",20,IF(BP22="Stage 1",0,IF(BP22="Stage 3",5,IF(BP22="Stage 4",-5,0)))) | BR22: Positive Trend | BS22: =IF(BR22="Positive Trend",20,IF(BR22="Negative Trend",-10,0)) | BT22: Uptrend | BU22: =IF(BT22="Uptrend",10,IF(BT22="Sideways",5,0)) | BV22: Uptrend | BW22: =IF(BV22="Uptrend",10,IF(BV22="Sideways",5,0)) | BX22: Blue sky scenario | BY22: =IF(BX22="Overhead supply in last 2 years in last 2 years",-5,IF(BX22="Close to 52 week high or retracement",5,IF(BX22="Blue sky scenario",10,IF(BX22="Long term Downtrend",-10,0)))) | BZ22: Yes | CA22: =IF(BZ22="Yes",10,0)
A23: =IF(B23=0,"",RANK(B23,$B$2:$B$32,0)) | B23: =SUM(N23,Y23,AA23,AC23,AE23,AG23,AI23,AK23,AM23,AO23,AQ23,AS23,AU23,AW23,AY23,BA23,BC23,BE23,BG23,BI23,BK23,BM23,BO23,BQ23,BS23,BU23,BW23,BY23,CA23) | C23: EQUITASBNK | D23: Equitas Small Finance Bank Ltd | E23: bank | F23: banks - private sector | G23: midcap | H23: 8090 | I23: 72.3 | J23: 1.97 | K23: 8173933 | L23: 25 | M23: Outperforming | N23: =IF(M23="Underperforming",-5,IF(L23>=95,15,IF(L23>=90,10,IF(L23>=80,5,0)))) | O23: 60.72 | P23: 19.41 | Q23: 57.14 | R23: Near 52W High Breakout | S23: Nifty Bank | T23: -4.01 | U23: 8.48 | V23: 13.01 | W23: 6.98 | X23: Cyclical in an Upturn | Y23: =IF(X23="Growing Industry",10,IF(X23="Cyclical in an Upturn",5,0)) | Z23: Fragmented with High ROE | AA23: =IF(Z23="Fragmented with Low ROE",-5,IF(Z23="Fragmented with High ROE",10,IF(Z23= "highly cyclical",5,0))) | AB23: No | AC23: =IF(AB23="No",5,0) | AD23: Tailwind | AE23: =IF(AD23="Tailwind",10,0) | AF23: Cyclical in an Uptick | AG23: =IF(AF23="Structural (10 Years Consistency)",15,IF(AF23="Shallow Cyclical (2 to 3 years growth)",10,IF(AF23 = "Cyclical in an Uptick",5,IF(AF23 = "Cyclical in an Downtick",-10,0)))) | AH23: Yes | AI23: =IF(AH23="Yes",10,0) | AJ23: Yes | AK23: =IF(AJ23="Yes",10,0) | AL23: Yes | AM23: =IF(AL23="No",10,0) | AN23: Yes | AO23: =IF(AN23="Yes",10,0) | AP23: Yes | AQ23: =IF(AP23="Yes",10,0) | AR23: No | AS23: =IF(AR23="Yes",5,0) | AT23: No | AU23: =IF(AT23="No",10,IF(AT23="Yes",-10,0)) | AV23: No | AW23: =IF(AV23="No",10,0) | AX23: No | AY23: =IF(AX23="No",10,IF(AX23= "Yes CEO Resignation",-5,0)) | AZ23: No | BA23: =IF(AZ23="No",10,IF(AZ23="Yes",-5,0)) | BB23: No | BC23: =IF(BB23="No",5,IF(BB23="Yes",-5,0)) | BD23: Yes | BE23: =IF(BD23="Yes",10,0) | BF23: No | BG23: =IF(BF23="Yes",10,0) | BH23: Yes | BI23: =IF(BH23="Yes",10,0) | BJ23: P/BV less than 2.5x and Growth more than 20% | BK23: =IF(BJ23="P/BV less than 2.5x and Growth more than 20%",20,IF(BJ23 = "P/BV less than 2.5x and Growth less than 20%",5,IF(BJ23="P/BV between 2.5x to 5x and Growth more than 20%",10,IF(BJ23= "P/BV between 2.5x to 5x and Growth less than 20%",-5,IF(BJ23= "P/BV above 5x",-5,0))))) | BL23: 20 to 40 | BM23: =IF(BL23="Above 40",20,IF(BL23="20 to 40",10,IF(BL23="0 to 20",-5,0))) | BN23: Between 50 to 75 | BO23: =IF(BN23="Between 50 to 75",10,IF(BN23="Above 75",0,0)) | BP23: Stage 2 | BQ23: =IF(BP23="Stage 2",20,IF(BP23="Stage 1",0,IF(BP23="Stage 3",5,IF(BP23="Stage 4",-5,0)))) | BR23: Positive Trend | BS23: =IF(BR23="Positive Trend",20,IF(BR23="Negative Trend",-10,0)) | BT23: Uptrend | BU23: =IF(BT23="Uptrend",10,IF(BT23="Sideways",5,0)) | BV23: Uptrend | BW23: =IF(BV23="Uptrend",10,IF(BV23="Sideways",5,0)) | BX23: Close to 52 week high or retracement | BY23: =IF(BX23="Overhead supply in last 2 years in last 2 years",-5,IF(BX23="Close to 52 week high or retracement",5,IF(BX23="Blue sky scenario",10,IF(BX23="Long term Downtrend",-10,0)))) | BZ23: Yes | CA23: =IF(BZ23="Yes",10,0)
A24: =IF(B24=0,"",RANK(B24,$B$2:$B$32,0)) | B24: =SUM(N24,Y24,AA24,AC24,AE24,AG24,AI24,AK24,AM24,AO24,AQ24,AS24,AU24,AW24,AY24,BA24,BC24,BE24,BG24,BI24,BK24,BM24,BO24,BQ24,BS24,BU24,BW24,BY24,CA24) | C24: GEECEE | D24: Geecee Ventures Limited | E24: financials | F24: finance & investments | G24: smallcap | H24: 680.57 | I24: 330.2 | J24: 1.46 | K24: 8700 | L24: 4 | M24: Underperforming | N24: =IF(M24="Underperforming",-5,IF(L24>=95,15,IF(L24>=90,10,IF(L24>=80,5,0)))) | O24: 56.31 | P24: 26.26 | Q24: 244.94 | R24: Earnings / Momentum Support | S24: Nifty Bank | T24: -4.01 | U24: -14.27 | V24: -10.68 | W24: 1.7 | X24: Growing Industry | Y24: =IF(X24="Growing Industry",10,IF(X24="Cyclical in an Upturn",5,0)) | Z24: Fragmented with High ROE | AA24: =IF(Z24="Fragmented with Low ROE",-5,IF(Z24="Fragmented with High ROE",10,IF(Z24= "highly cyclical",5,0))) | AB24: Yes | AC24: =IF(AB24="No",5,0) | AD24: Headwind | AE24: =IF(AD24="Tailwind",10,0) | AF24: Structural (10 Years Consistency) | AG24: =IF(AF24="Structural (10 Years Consistency)",15,IF(AF24="Shallow Cyclical (2 to 3 years growth)",10,IF(AF24 = "Cyclical in an Uptick",5,IF(AF24 = "Cyclical in an Downtick",-10,0)))) | AH24: Yes | AI24: =IF(AH24="Yes",10,0) | AJ24: Yes | AK24: =IF(AJ24="Yes",10,0) | AM24: =IF(AL24="No",10,0) | AN24: Yes | AO24: =IF(AN24="Yes",10,0) | AP24: No | AQ24: =IF(AP24="Yes",10,0) | AR24: Yes | AS24: =IF(AR24="Yes",5,0) | AT24: No | AU24: =IF(AT24="No",10,IF(AT24="Yes",-10,0)) | AV24: No | AW24: =IF(AV24="No",10,0) | AX24: No | AY24: =IF(AX24="No",10,IF(AX24= "Yes CEO Resignation",-5,0)) | AZ24: No | BA24: =IF(AZ24="No",10,IF(AZ24="Yes",-5,0)) | BB24: No | BC24: =IF(BB24="No",5,IF(BB24="Yes",-5,0)) | BD24: Yes | BE24: =IF(BD24="Yes",10,0) | BF24: Yes | BG24: =IF(BF24="Yes",10,0) | BH24: Yes | BI24: =IF(BH24="Yes",10,0) | BJ24: P/BV less than 2.5x and Growth more than 20% | BK24: =IF(BJ24="P/BV less than 2.5x and Growth more than 20%",20,IF(BJ24 = "P/BV less than 2.5x and Growth less than 20%",5,IF(BJ24="P/BV between 2.5x to 5x and Growth more than 20%",10,IF(BJ24= "P/BV between 2.5x to 5x and Growth less than 20%",-5,IF(BJ24= "P/BV above 5x",-5,0))))) | BL24: 20 to 40 | BM24: =IF(BL24="Above 40",20,IF(BL24="20 to 40",10,IF(BL24="0 to 20",-5,0))) | BN24: Between 50 to 75 | BO24: =IF(BN24="Between 50 to 75",10,IF(BN24="Above 75",0,0)) | BP24: Stage 2 | BQ24: =IF(BP24="Stage 2",20,IF(BP24="Stage 1",0,IF(BP24="Stage 3",5,IF(BP24="Stage 4",-5,0)))) | BR24: Positive Trend | BS24: =IF(BR24="Positive Trend",20,IF(BR24="Negative Trend",-10,0)) | BT24: Uptrend | BU24: =IF(BT24="Uptrend",10,IF(BT24="Sideways",5,0)) | BV24: Uptrend | BW24: =IF(BV24="Uptrend",10,IF(BV24="Sideways",5,0)) | BX24: Close to 52 week high or retracement | BY24: =IF(BX24="Overhead supply in last 2 years in last 2 years",-5,IF(BX24="Close to 52 week high or retracement",5,IF(BX24="Blue sky scenario",10,IF(BX24="Long term Downtrend",-10,0)))) | BZ24: Yes | CA24: =IF(BZ24="Yes",10,0)
A25: =IF(B25=0,"",RANK(B25,$B$2:$B$32,0)) | B25: =SUM(N25,Y25,AA25,AC25,AE25,AG25,AI25,AK25,AM25,AO25,AQ25,AS25,AU25,AW25,AY25,BA25,BC25,BE25,BG25,BI25,BK25,BM25,BO25,BQ25,BS25,BU25,BW25,BY25,CA25) | C25: CGCL | D25: Capri Global Capital Limited | E25: financials | F25: finance & investments | G25: midcap | H25: 19373.93 | I25: 202.53 | J25: 0.58 | K25: 3552907 | L25: 45 | M25: Outperforming | N25: =IF(M25="Underperforming",-5,IF(L25>=95,15,IF(L25>=90,10,IF(L25>=80,5,0)))) | O25: 62.92 | P25: 17.37 | Q25: 162 | R25: Near 52W High Breakout | S25: Nifty Bank | T25: -4.01 | U25: 33.35 | V25: 38.93 | W25: 12.08 | X25: Growing Industry | Y25: =IF(X25="Growing Industry",10,IF(X25="Cyclical in an Upturn",5,0)) | Z25: Fragmented with High ROE | AA25: =IF(Z25="Fragmented with Low ROE",-5,IF(Z25="Fragmented with High ROE",10,IF(Z25= "highly cyclical",5,0))) | AB25: Yes | AC25: =IF(AB25="No",5,0) | AD25: Tailwind | AE25: =IF(AD25="Tailwind",10,0) | AF25: Structural (10 Years Consistency) | AG25: =IF(AF25="Structural (10 Years Consistency)",15,IF(AF25="Shallow Cyclical (2 to 3 years growth)",10,IF(AF25 = "Cyclical in an Uptick",5,IF(AF25 = "Cyclical in an Downtick",-10,0)))) | AH25: Yes | AI25: =IF(AH25="Yes",10,0) | AJ25: Yes | AK25: =IF(AJ25="Yes",10,0) | AM25: =IF(AL25="No",10,0) | AN25: Yes | AO25: =IF(AN25="Yes",10,0) | AP25: Yes | AQ25: =IF(AP25="Yes",10,0) | AR25: Yes | AS25: =IF(AR25="Yes",5,0) | AT25: No | AU25: =IF(AT25="No",10,IF(AT25="Yes",-10,0)) | AV25: No | AW25: =IF(AV25="No",10,0) | AX25: No | AY25: =IF(AX25="No",10,IF(AX25= "Yes CEO Resignation",-5,0)) | AZ25: No | BA25: =IF(AZ25="No",10,IF(AZ25="Yes",-5,0)) | BB25: No | BC25: =IF(BB25="No",5,IF(BB25="Yes",-5,0)) | BD25: Yes | BE25: =IF(BD25="Yes",10,0) | BF25: Yes | BG25: =IF(BF25="Yes",10,0) | BH25: Yes | BI25: =IF(BH25="Yes",10,0) | BJ25: P/BV between 2.5x to 5x and Growth more than 20% | BK25: =IF(BJ25="P/BV less than 2.5x and Growth more than 20%",20,IF(BJ25 = "P/BV less than 2.5x and Growth less than 20%",5,IF(BJ25="P/BV between 2.5x to 5x and Growth more than 20%",10,IF(BJ25= "P/BV between 2.5x to 5x and Growth less than 20%",-5,IF(BJ25= "P/BV above 5x",-5,0))))) | BL25: 0 to 20 | BM25: =IF(BL25="Above 40",20,IF(BL25="20 to 40",10,IF(BL25="0 to 20",-5,0))) | BN25: Between 50 to 75 | BO25: =IF(BN25="Between 50 to 75",10,IF(BN25="Above 75",0,0)) | BP25: Stage 2 | BQ25: =IF(BP25="Stage 2",20,IF(BP25="Stage 1",0,IF(BP25="Stage 3",5,IF(BP25="Stage 4",-5,0)))) | BR25: Positive Trend | BS25: =IF(BR25="Positive Trend",20,IF(BR25="Negative Trend",-10,0)) | BT25: Uptrend | BU25: =IF(BT25="Uptrend",10,IF(BT25="Sideways",5,0)) | BV25: Uptrend | BW25: =IF(BV25="Uptrend",10,IF(BV25="Sideways",5,0)) | BX25: Close to 52 week high or retracement | BY25: =IF(BX25="Overhead supply in last 2 years in last 2 years",-5,IF(BX25="Close to 52 week high or retracement",5,IF(BX25="Blue sky scenario",10,IF(BX25="Long term Downtrend",-10,0)))) | BZ25: Yes | CA25: =IF(BZ25="Yes",10,0)
A26: =IF(B26=0,"",RANK(B26,$B$2:$B$32,0)) | B26: =SUM(N26,Y26,AA26,AC26,AE26,AG26,AI26,AK26,AM26,AO26,AQ26,AS26,AU26,AW26,AY26,BA26,BC26,BE26,BG26,BI26,BK26,BM26,BO26,BQ26,BS26,BU26,BW26,BY26,CA26) | C26: BANDHANBNK | D26: Bandhan Bank Ltd | E26: bank | F26: banks - private sector | G26: largecap | H26: 33447.01 | I26: 205.44 | J26: -1.05 | K26: 4284782 | L26: 26 | M26: Outperforming | N26: =IF(M26="Underperforming",-5,IF(L26>=95,15,IF(L26>=90,10,IF(L26>=80,5,0)))) | O26: 64.65 | P26: 28.23 | Q26: 167.51 | R26: Near 52W High Breakout | S26: Nifty Bank | T26: -4.01 | U26: 19.46 | V26: 24.45 | W26: 7.18 | X26: Growing Industry | Y26: =IF(X26="Growing Industry",10,IF(X26="Cyclical in an Upturn",5,0)) | Z26: Fragmented with High ROE | AA26: =IF(Z26="Fragmented with Low ROE",-5,IF(Z26="Fragmented with High ROE",10,IF(Z26= "highly cyclical",5,0))) | AB26: Yes | AC26: =IF(AB26="No",5,0) | AD26: Tailwind | AE26: =IF(AD26="Tailwind",10,0) | AF26: Structural (10 Years Consistency) | AG26: =IF(AF26="Structural (10 Years Consistency)",15,IF(AF26="Shallow Cyclical (2 to 3 years growth)",10,IF(AF26 = "Cyclical in an Uptick",5,IF(AF26 = "Cyclical in an Downtick",-10,0)))) | AH26: Yes | AI26: =IF(AH26="Yes",10,0) | AJ26: Yes | AK26: =IF(AJ26="Yes",10,0) | AM26: =IF(AL26="No",10,0) | AN26: Yes | AO26: =IF(AN26="Yes",10,0) | AP26: Yes | AQ26: =IF(AP26="Yes",10,0) | AR26: Yes | AS26: =IF(AR26="Yes",5,0) | AT26: No | AU26: =IF(AT26="No",10,IF(AT26="Yes",-10,0)) | AV26: No | AW26: =IF(AV26="No",10,0) | AX26: No | AY26: =IF(AX26="No",10,IF(AX26= "Yes CEO Resignation",-5,0)) | AZ26: No | BA26: =IF(AZ26="No",10,IF(AZ26="Yes",-5,0)) | BB26: No | BC26: =IF(BB26="No",5,IF(BB26="Yes",-5,0)) | BD26: Yes | BE26: =IF(BD26="Yes",10,0) | BF26: Yes | BG26: =IF(BF26="Yes",10,0) | BH26: Yes | BI26: =IF(BH26="Yes",10,0) | BJ26: P/BV less than 2.5x and Growth more than 20% | BK26: =IF(BJ26="P/BV less than 2.5x and Growth more than 20%",20,IF(BJ26 = "P/BV less than 2.5x and Growth less than 20%",5,IF(BJ26="P/BV between 2.5x to 5x and Growth more than 20%",10,IF(BJ26= "P/BV between 2.5x to 5x and Growth less than 20%",-5,IF(BJ26= "P/BV above 5x",-5,0))))) | BL26: 20 to 40 | BM26: =IF(BL26="Above 40",20,IF(BL26="20 to 40",10,IF(BL26="0 to 20",-5,0))) | BN26: Between 50 to 75 | BO26: =IF(BN26="Between 50 to 75",10,IF(BN26="Above 75",0,0)) | BP26: Stage 2 | BQ26: =IF(BP26="Stage 2",20,IF(BP26="Stage 1",0,IF(BP26="Stage 3",5,IF(BP26="Stage 4",-5,0)))) | BR26: Negative Trend | BS26: =IF(BR26="Positive Trend",20,IF(BR26="Negative Trend",-10,0)) | BT26: Uptrend | BU26: =IF(BT26="Uptrend",10,IF(BT26="Sideways",5,0)) | BV26: Uptrend | BW26: =IF(BV26="Uptrend",10,IF(BV26="Sideways",5,0)) | BX26: Blue sky scenario | BY26: =IF(BX26="Overhead supply in last 2 years in last 2 years",-5,IF(BX26="Close to 52 week high or retracement",5,IF(BX26="Blue sky scenario",10,IF(BX26="Long term Downtrend",-10,0)))) | BZ26: Yes | CA26: =IF(BZ26="Yes",10,0)
A27: =IF(B27=0,"",RANK(B27,$B$2:$B$32,0)) | B27: =SUM(N27,Y27,AA27,AC27,AE27,AG27,AI27,AK27,AM27,AO27,AQ27,AS27,AU27,AW27,AY27,BA27,BC27,BE27,BG27,BI27,BK27,BM27,BO27,BQ27,BS27,BU27,BW27,BY27,CA27) | C27: SURYODAY | D27: Suryoday Small Finance Bank Ltd | E27: bank | F27: banks - private sector | G27: smallcap | H27: 1803.42 | I27: 171.39 | J27: 1.01 | K27: 393247 | L27: 41 | M27: Outperforming | N27: =IF(M27="Underperforming",-5,IF(L27>=95,15,IF(L27>=90,10,IF(L27>=80,5,0)))) | O27: 63.71 | P27: 27.71 | Q27: 138.24 | R27: Near 52W High Breakout | S27: Nifty Bank | T27: -4.01 | U27: 18.24 | V27: 23.18 | W27: 11.18 | X27: Growing Industry | Y27: =IF(X27="Growing Industry",10,IF(X27="Cyclical in an Upturn",5,0)) | Z27: Fragmented with High ROE | AA27: =IF(Z27="Fragmented with Low ROE",-5,IF(Z27="Fragmented with High ROE",10,IF(Z27= "highly cyclical",5,0))) | AB27: Yes | AC27: =IF(AB27="No",5,0) | AD27: Tailwind | AE27: =IF(AD27="Tailwind",10,0) | AF27: Structural (10 Years Consistency) | AG27: =IF(AF27="Structural (10 Years Consistency)",15,IF(AF27="Shallow Cyclical (2 to 3 years growth)",10,IF(AF27 = "Cyclical in an Uptick",5,IF(AF27 = "Cyclical in an Downtick",-10,0)))) | AH27: Yes | AI27: =IF(AH27="Yes",10,0) | AJ27: Yes | AK27: =IF(AJ27="Yes",10,0) | AM27: =IF(AL27="No",10,0) | AN27: Yes | AO27: =IF(AN27="Yes",10,0) | AP27: Yes | AQ27: =IF(AP27="Yes",10,0) | AR27: Yes | AS27: =IF(AR27="Yes",5,0) | AT27: No | AU27: =IF(AT27="No",10,IF(AT27="Yes",-10,0)) | AV27: No | AW27: =IF(AV27="No",10,0) | AX27: No | AY27: =IF(AX27="No",10,IF(AX27= "Yes CEO Resignation",-5,0)) | AZ27: No | BA27: =IF(AZ27="No",10,IF(AZ27="Yes",-5,0)) | BB27: No | BC27: =IF(BB27="No",5,IF(BB27="Yes",-5,0)) | BD27: Yes | BE27: =IF(BD27="Yes",10,0) | BF27: Yes | BG27: =IF(BF27="Yes",10,0) | BH27: Yes | BI27: =IF(BH27="Yes",10,0) | BJ27: P/BV less than 2.5x and Growth more than 20% | BK27: =IF(BJ27="P/BV less than 2.5x and Growth more than 20%",20,IF(BJ27 = "P/BV less than 2.5x and Growth less than 20%",5,IF(BJ27="P/BV between 2.5x to 5x and Growth more than 20%",10,IF(BJ27= "P/BV between 2.5x to 5x and Growth less than 20%",-5,IF(BJ27= "P/BV above 5x",-5,0))))) | BL27: 20 to 40 | BM27: =IF(BL27="Above 40",20,IF(BL27="20 to 40",10,IF(BL27="0 to 20",-5,0))) | BN27: Between 50 to 75 | BO27: =IF(BN27="Between 50 to 75",10,IF(BN27="Above 75",0,0)) | BP27: Stage 2 | BQ27: =IF(BP27="Stage 2",20,IF(BP27="Stage 1",0,IF(BP27="Stage 3",5,IF(BP27="Stage 4",-5,0)))) | BR27: Negative Trend | BS27: =IF(BR27="Positive Trend",20,IF(BR27="Negative Trend",-10,0)) | BT27: Uptrend | BU27: =IF(BT27="Uptrend",10,IF(BT27="Sideways",5,0)) | BV27: Uptrend | BW27: =IF(BV27="Uptrend",10,IF(BV27="Sideways",5,0)) | BX27: Close to 52 week high or retracement | BY27: =IF(BX27="Overhead supply in last 2 years in last 2 years",-5,IF(BX27="Close to 52 week high or retracement",5,IF(BX27="Blue sky scenario",10,IF(BX27="Long term Downtrend",-10,0)))) | BZ27: Yes | CA27: =IF(BZ27="Yes",10,0)
A28: =IF(B28=0,"",RANK(B28,$B$2:$B$32,0)) | B28: =SUM(N28,Y28,AA28,AC28,AE28,AG28,AI28,AK28,AM28,AO28,AQ28,AS28,AU28,AW28,AY28,BA28,BC28,BE28,BG28,BI28,BK28,BM28,BO28,BQ28,BS28,BU28,BW28,BY28,CA28) | C28: IFCI | D28: Ifci Limited | E28: financials | F28: finance - term-lending institutions | G28: largecap | H28: 21667.68 | I28: 81.98 | J28: 1.94 | K28: 202071793 | L28: 60 | M28: Outperforming | N28: =IF(M28="Underperforming",-5,IF(L28>=95,15,IF(L28>=90,10,IF(L28>=80,5,0)))) | O28: 71.36 | P28: 19.96 | Q28: 61.41 | R28: Volume Spike & Near 52W High Breakout | S28: Nifty Bank | T28: -4.01 | U28: 24.16 | V28: 29.35 | W28: 16.9 | X28: Growing Industry | Y28: =IF(X28="Growing Industry",10,IF(X28="Cyclical in an Upturn",5,0)) | Z28: Fragmented with High ROE | AA28: =IF(Z28="Fragmented with Low ROE",-5,IF(Z28="Fragmented with High ROE",10,IF(Z28= "highly cyclical",5,0))) | AB28: Yes | AC28: =IF(AB28="No",5,0) | AD28: Tailwind | AE28: =IF(AD28="Tailwind",10,0) | AF28: Structural (10 Years Consistency) | AG28: =IF(AF28="Structural (10 Years Consistency)",15,IF(AF28="Shallow Cyclical (2 to 3 years growth)",10,IF(AF28 = "Cyclical in an Uptick",5,IF(AF28 = "Cyclical in an Downtick",-10,0)))) | AH28: Yes | AI28: =IF(AH28="Yes",10,0) | AJ28: Yes | AK28: =IF(AJ28="Yes",10,0) | AM28: =IF(AL28="No",10,0) | AN28: Yes | AO28: =IF(AN28="Yes",10,0) | AP28: Yes | AQ28: =IF(AP28="Yes",10,0) | AR28: Yes | AS28: =IF(AR28="Yes",5,0) | AT28: No | AU28: =IF(AT28="No",10,IF(AT28="Yes",-10,0)) | AV28: No | AW28: =IF(AV28="No",10,0) | AX28: No | AY28: =IF(AX28="No",10,IF(AX28= "Yes CEO Resignation",-5,0)) | AZ28: No | BA28: =IF(AZ28="No",10,IF(AZ28="Yes",-5,0)) | BB28: No | BC28: =IF(BB28="No",5,IF(BB28="Yes",-5,0)) | BD28: Yes | BE28: =IF(BD28="Yes",10,0) | BF28: Yes | BG28: =IF(BF28="Yes",10,0) | BH28: Yes | BI28: =IF(BH28="Yes",10,0) | BJ28: P/BV between 2.5x to 5x and Growth less than 20% | BK28: =IF(BJ28="P/BV less than 2.5x and Growth more than 20%",20,IF(BJ28 = "P/BV less than 2.5x and Growth less than 20%",5,IF(BJ28="P/BV between 2.5x to 5x and Growth more than 20%",10,IF(BJ28= "P/BV between 2.5x to 5x and Growth less than 20%",-5,IF(BJ28= "P/BV above 5x",-5,0))))) | BL28: 0 to 20 | BM28: =IF(BL28="Above 40",20,IF(BL28="20 to 40",10,IF(BL28="0 to 20",-5,0))) | BN28: Between 50 to 75 | BO28: =IF(BN28="Between 50 to 75",10,IF(BN28="Above 75",0,0)) | BP28: Stage 2 | BQ28: =IF(BP28="Stage 2",20,IF(BP28="Stage 1",0,IF(BP28="Stage 3",5,IF(BP28="Stage 4",-5,0)))) | BR28: Positive Trend | BS28: =IF(BR28="Positive Trend",20,IF(BR28="Negative Trend",-10,0)) | BT28: Uptrend | BU28: =IF(BT28="Uptrend",10,IF(BT28="Sideways",5,0)) | BV28: Uptrend | BW28: =IF(BV28="Uptrend",10,IF(BV28="Sideways",5,0)) | BX28: Blue sky scenario | BY28: =IF(BX28="Overhead supply in last 2 years in last 2 years",-5,IF(BX28="Close to 52 week high or retracement",5,IF(BX28="Blue sky scenario",10,IF(BX28="Long term Downtrend",-10,0)))) | BZ28: Yes | CA28: =IF(BZ28="Yes",10,0)
A29: =IF(B29=0,"",RANK(B29,$B$2:$B$32,0)) | B29: =SUM(N29,Y29,AA29,AC29,AE29,AG29,AI29,AK29,AM29,AO29,AQ29,AS29,AU29,AW29,AY29,BA29,BC29,BE29,BG29,BI29,BK29,BM29,BO29,BQ29,BS29,BU29,BW29,BY29,CA29) | C29: MUFIN | D29: Mufin Green Finance Ltd | E29: financials | F29: finance & investments | G29: smallcap | H29: 2427.09 | I29: 122.05 | J29: -0.35 | K29: 1183401 | L29: 46 | M29: Outperforming | N29: =IF(M29="Underperforming",-5,IF(L29>=95,15,IF(L29>=90,10,IF(L29>=80,5,0)))) | O29: 61.27 | P29: 15.5 | Q29: 97.33 | R29: Near 52W High Breakout | S29: Nifty Bank | T29: -4.01 | U29: 54.14 | V29: 60.59 | W29: 12.24 | X29: Growing Industry | Y29: =IF(X29="Growing Industry",10,IF(X29="Cyclical in an Upturn",5,0)) | Z29: Fragmented with High ROE | AA29: =IF(Z29="Fragmented with Low ROE",-5,IF(Z29="Fragmented with High ROE",10,IF(Z29= "highly cyclical",5,0))) | AB29: Yes | AC29: =IF(AB29="No",5,0) | AD29: Tailwind | AE29: =IF(AD29="Tailwind",10,0) | AF29: Structural (10 Years Consistency) | AG29: =IF(AF29="Structural (10 Years Consistency)",15,IF(AF29="Shallow Cyclical (2 to 3 years growth)",10,IF(AF29 = "Cyclical in an Uptick",5,IF(AF29 = "Cyclical in an Downtick",-10,0)))) | AH29: Yes | AI29: =IF(AH29="Yes",10,0) | AJ29: Yes | AK29: =IF(AJ29="Yes",10,0) | AM29: =IF(AL29="No",10,0) | AN29: Yes | AO29: =IF(AN29="Yes",10,0) | AP29: Yes | AQ29: =IF(AP29="Yes",10,0) | AR29: Yes | AS29: =IF(AR29="Yes",5,0) | AT29: No | AU29: =IF(AT29="No",10,IF(AT29="Yes",-10,0)) | AV29: No | AW29: =IF(AV29="No",10,0) | AX29: No | AY29: =IF(AX29="No",10,IF(AX29= "Yes CEO Resignation",-5,0)) | AZ29: No | BA29: =IF(AZ29="No",10,IF(AZ29="Yes",-5,0)) | BB29: No | BC29: =IF(BB29="No",5,IF(BB29="Yes",-5,0)) | BD29: Yes | BE29: =IF(BD29="Yes",10,0) | BF29: Yes | BG29: =IF(BF29="Yes",10,0) | BH29: Yes | BI29: =IF(BH29="Yes",10,0) | BJ29: P/BV above 5x | BK29: =IF(BJ29="P/BV less than 2.5x and Growth more than 20%",20,IF(BJ29 = "P/BV less than 2.5x and Growth less than 20%",5,IF(BJ29="P/BV between 2.5x to 5x and Growth more than 20%",10,IF(BJ29= "P/BV between 2.5x to 5x and Growth less than 20%",-5,IF(BJ29= "P/BV above 5x",-5,0))))) | BL29: 0 to 20 | BM29: =IF(BL29="Above 40",20,IF(BL29="20 to 40",10,IF(BL29="0 to 20",-5,0))) | BN29: Between 50 to 75 | BO29: =IF(BN29="Between 50 to 75",10,IF(BN29="Above 75",0,0)) | BP29: Stage 2 | BQ29: =IF(BP29="Stage 2",20,IF(BP29="Stage 1",0,IF(BP29="Stage 3",5,IF(BP29="Stage 4",-5,0)))) | BR29: Positive Trend | BS29: =IF(BR29="Positive Trend",20,IF(BR29="Negative Trend",-10,0)) | BT29: Uptrend | BU29: =IF(BT29="Uptrend",10,IF(BT29="Sideways",5,0)) | BV29: Uptrend | BW29: =IF(BV29="Uptrend",10,IF(BV29="Sideways",5,0)) | BX29: Close to 52 week high or retracement | BY29: =IF(BX29="Overhead supply in last 2 years in last 2 years",-5,IF(BX29="Close to 52 week high or retracement",5,IF(BX29="Blue sky scenario",10,IF(BX29="Long term Downtrend",-10,0)))) | BZ29: Yes | CA29: =IF(BZ29="Yes",10,0)
A30: =IF(B30=0,"",RANK(B30,$B$2:$B$32,0)) | B30: =SUM(N30,Y30,AA30,AC30,AE30,AG30,AI30,AK30,AM30,AO30,AQ30,AS30,AU30,AW30,AY30,BA30,BC30,BE30,BG30,BI30,BK30,BM30,BO30,BQ30,BS30,BU30,BW30,BY30,CA30) | C30: BFINVEST | D30: Bf Investment Limited | E30: financials | F30: finance & investments | G30: smallcap | H30: 1660.39 | I30: 448.25 | J30: 1.69 | K30: 119074 | L30: 3 | M30: Underperforming | N30: =IF(M30="Underperforming",-5,IF(L30>=95,15,IF(L30>=90,10,IF(L30>=80,5,0)))) | O30: 57.46 | P30: 19.14 | Q30: 341.87 | R30: Earnings / Momentum Support | S30: Nifty Bank | T30: -4.01 | U30: -12.51 | V30: -8.85 | W30: 1.15 | X30: Growing Industry | Y30: =IF(X30="Growing Industry",10,IF(X30="Cyclical in an Upturn",5,0)) | Z30: Fragmented with High ROE | AA30: =IF(Z30="Fragmented with Low ROE",-5,IF(Z30="Fragmented with High ROE",10,IF(Z30= "highly cyclical",5,0))) | AB30: Yes | AC30: =IF(AB30="No",5,0) | AD30: Tailwind | AE30: =IF(AD30="Tailwind",10,0) | AF30: Structural (10 Years Consistency) | AG30: =IF(AF30="Structural (10 Years Consistency)",15,IF(AF30="Shallow Cyclical (2 to 3 years growth)",10,IF(AF30 = "Cyclical in an Uptick",5,IF(AF30 = "Cyclical in an Downtick",-10,0)))) | AH30: Yes | AI30: =IF(AH30="Yes",10,0) | AJ30: Yes | AK30: =IF(AJ30="Yes",10,0) | AM30: =IF(AL30="No",10,0) | AN30: Yes | AO30: =IF(AN30="Yes",10,0) | AP30: No | AQ30: =IF(AP30="Yes",10,0) | AR30: Yes | AS30: =IF(AR30="Yes",5,0) | AT30: No | AU30: =IF(AT30="No",10,IF(AT30="Yes",-10,0)) | AV30: No | AW30: =IF(AV30="No",10,0) | AX30: No | AY30: =IF(AX30="No",10,IF(AX30= "Yes CEO Resignation",-5,0)) | AZ30: No | BA30: =IF(AZ30="No",10,IF(AZ30="Yes",-5,0)) | BB30: No | BC30: =IF(BB30="No",5,IF(BB30="Yes",-5,0)) | BD30: Yes | BE30: =IF(BD30="Yes",10,0) | BF30: Yes | BG30: =IF(BF30="Yes",10,0) | BH30: Yes | BI30: =IF(BH30="Yes",10,0) | BJ30: P/BV less than 2.5x and Growth more than 20% | BK30: =IF(BJ30="P/BV less than 2.5x and Growth more than 20%",20,IF(BJ30 = "P/BV less than 2.5x and Growth less than 20%",5,IF(BJ30="P/BV between 2.5x to 5x and Growth more than 20%",10,IF(BJ30= "P/BV between 2.5x to 5x and Growth less than 20%",-5,IF(BJ30= "P/BV above 5x",-5,0))))) | BL30: 0 to 20 | BM30: =IF(BL30="Above 40",20,IF(BL30="20 to 40",10,IF(BL30="0 to 20",-5,0))) | BN30: Between 50 to 75 | BO30: =IF(BN30="Between 50 to 75",10,IF(BN30="Above 75",0,0)) | BP30: Stage 1 | BQ30: =IF(BP30="Stage 2",20,IF(BP30="Stage 1",0,IF(BP30="Stage 3",5,IF(BP30="Stage 4",-5,0)))) | BR30: Positive Trend | BS30: =IF(BR30="Positive Trend",20,IF(BR30="Negative Trend",-10,0)) | BT30: Uptrend | BU30: =IF(BT30="Uptrend",10,IF(BT30="Sideways",5,0)) | BV30: Uptrend | BW30: =IF(BV30="Uptrend",10,IF(BV30="Sideways",5,0)) | BX30: Close to 52 week high or retracement | BY30: =IF(BX30="Overhead supply in last 2 years in last 2 years",-5,IF(BX30="Close to 52 week high or retracement",5,IF(BX30="Blue sky scenario",10,IF(BX30="Long term Downtrend",-10,0)))) | BZ30: Yes | CA30: =IF(BZ30="Yes",10,0)
A31: =IF(B31=0,"",RANK(B31,$B$2:$B$32,0)) | B31: =SUM(N31,Y31,AA31,AC31,AE31,AG31,AI31,AK31,AM31,AO31,AQ31,AS31,AU31,AW31,AY31,BA31,BC31,BE31,BG31,BI31,BK31,BM31,BO31,BQ31,BS31,BU31,BW31,BY31,CA31) | C31: NUVAMA | D31: Nuvama Wealth Management Ltd | E31: financials | F31: finance & investments | G31: largecap | H31: 28363.89 | I31: 1566.6 | J31: 0.55 | K31: 260107 | L31: 33 | M31: Outperforming | N31: =IF(M31="Underperforming",-5,IF(L31>=95,15,IF(L31>=90,10,IF(L31>=80,5,0)))) | O31: 60.06 | P31: 28.92 | Q31: 1259.66 | R31: Near 52W High Breakout | S31: Nifty Bank | T31: -4.01 | U31: 9.41 | V31: 13.98 | W31: 8.81 | X31: Growing Industry | Y31: =IF(X31="Growing Industry",10,IF(X31="Cyclical in an Upturn",5,0)) | Z31: Fragmented with High ROE | AA31: =IF(Z31="Fragmented with Low ROE",-5,IF(Z31="Fragmented with High ROE",10,IF(Z31= "highly cyclical",5,0))) | AB31: Yes | AC31: =IF(AB31="No",5,0) | AD31: Tailwind | AE31: =IF(AD31="Tailwind",10,0) | AF31: Structural (10 Years Consistency) | AG31: =IF(AF31="Structural (10 Years Consistency)",15,IF(AF31="Shallow Cyclical (2 to 3 years growth)",10,IF(AF31 = "Cyclical in an Uptick",5,IF(AF31 = "Cyclical in an Downtick",-10,0)))) | AH31: Yes | AI31: =IF(AH31="Yes",10,0) | AJ31: Yes | AK31: =IF(AJ31="Yes",10,0) | AM31: =IF(AL31="No",10,0) | AN31: Yes | AO31: =IF(AN31="Yes",10,0) | AP31: Yes | AQ31: =IF(AP31="Yes",10,0) | AR31: Yes | AS31: =IF(AR31="Yes",5,0) | AT31: No | AU31: =IF(AT31="No",10,IF(AT31="Yes",-10,0)) | AV31: No | AW31: =IF(AV31="No",10,0) | AX31: No | AY31: =IF(AX31="No",10,IF(AX31= "Yes CEO Resignation",-5,0)) | AZ31: No | BA31: =IF(AZ31="No",10,IF(AZ31="Yes",-5,0)) | BB31: No | BC31: =IF(BB31="No",5,IF(BB31="Yes",-5,0)) | BD31: Yes | BE31: =IF(BD31="Yes",10,0) | BF31: Yes | BG31: =IF(BF31="Yes",10,0) | BH31: Yes | BI31: =IF(BH31="Yes",10,0) | BJ31: P/BV above 5x | BK31: =IF(BJ31="P/BV less than 2.5x and Growth more than 20%",20,IF(BJ31 = "P/BV less than 2.5x and Growth less than 20%",5,IF(BJ31="P/BV between 2.5x to 5x and Growth more than 20%",10,IF(BJ31= "P/BV between 2.5x to 5x and Growth less than 20%",-5,IF(BJ31= "P/BV above 5x",-5,0))))) | BL31: 20 to 40 | BM31: =IF(BL31="Above 40",20,IF(BL31="20 to 40",10,IF(BL31="0 to 20",-5,0))) | BN31: Between 50 to 75 | BO31: =IF(BN31="Between 50 to 75",10,IF(BN31="Above 75",0,0)) | BP31: Stage 2 | BQ31: =IF(BP31="Stage 2",20,IF(BP31="Stage 1",0,IF(BP31="Stage 3",5,IF(BP31="Stage 4",-5,0)))) | BR31: Negative Trend | BS31: =IF(BR31="Positive Trend",20,IF(BR31="Negative Trend",-10,0)) | BT31: Uptrend | BU31: =IF(BT31="Uptrend",10,IF(BT31="Sideways",5,0)) | BV31: Uptrend | BW31: =IF(BV31="Uptrend",10,IF(BV31="Sideways",5,0)) | BX31: Blue sky scenario | BY31: =IF(BX31="Overhead supply in last 2 years in last 2 years",-5,IF(BX31="Close to 52 week high or retracement",5,IF(BX31="Blue sky scenario",10,IF(BX31="Long term Downtrend",-10,0)))) | BZ31: Yes | CA31: =IF(BZ31="Yes",10,0)
A32: =IF(B32=0,"",RANK(B32,$B$2:$B$32,0)) | B32: =SUM(N32,Y32,AA32,AC32,AE32,AG32,AI32,AK32,AM32,AO32,AQ32,AS32,AU32,AW32,AY32,BA32,BC32,BE32,BG32,BI32,BK32,BM32,BO32,BQ32,BS32,BU32,BW32,BY32,CA32) | C32: YESBANK | D32: Yes Bank Limited | E32: bank | F32: banks - private sector | G32: largecap | H32: 71950.77 | I32: 22.77 | J32: -0.7 | K32: 77191326 | L32: 13 | M32: Outperforming | N32: =IF(M32="Underperforming",-5,IF(L32>=95,15,IF(L32>=90,10,IF(L32>=80,5,0)))) | O32: 59.09 | P32: 20.62 | Q32: 19.12 | R32: Earnings / Momentum Support | S32: Nifty Bank | T32: -4.01 | U32: 9.21 | V32: 13.77 | W32: 4.79 | X32: Growing Industry | Y32: =IF(X32="Growing Industry",10,IF(X32="Cyclical in an Upturn",5,0)) | Z32: Fragmented with High ROE | AA32: =IF(Z32="Fragmented with Low ROE",-5,IF(Z32="Fragmented with High ROE",10,IF(Z32= "highly cyclical",5,0))) | AB32: Yes | AC32: =IF(AB32="No",5,0) | AD32: Tailwind | AE32: =IF(AD32="Tailwind",10,0) | AF32: Structural (10 Years Consistency) | AG32: =IF(AF32="Structural (10 Years Consistency)",15,IF(AF32="Shallow Cyclical (2 to 3 years growth)",10,IF(AF32 = "Cyclical in an Uptick",5,IF(AF32 = "Cyclical in an Downtick",-10,0)))) | AH32: Yes | AI32: =IF(AH32="Yes",10,0) | AJ32: Yes | AK32: =IF(AJ32="Yes",10,0) | AM32: =IF(AL32="No",10,0) | AN32: Yes | AO32: =IF(AN32="Yes",10,0) | AP32: No | AQ32: =IF(AP32="Yes",10,0) | AR32: Yes | AS32: =IF(AR32="Yes",5,0) | AT32: No | AU32: =IF(AT32="No",10,IF(AT32="Yes",-10,0)) | AV32: No | AW32: =IF(AV32="No",10,0) | AX32: No | AY32: =IF(AX32="No",10,IF(AX32= "Yes CEO Resignation",-5,0)) | AZ32: No | BA32: =IF(AZ32="No",10,IF(AZ32="Yes",-5,0)) | BB32: No | BC32: =IF(BB32="No",5,IF(BB32="Yes",-5,0)) | BD32: Yes | BE32: =IF(BD32="Yes",10,0) | BF32: Yes | BG32: =IF(BF32="Yes",10,0) | BH32: Yes | BI32: =IF(BH32="Yes",10,0) | BJ32: P/BV less than 2.5x and Growth less than 20% | BK32: =IF(BJ32="P/BV less than 2.5x and Growth more than 20%",20,IF(BJ32 = "P/BV less than 2.5x and Growth less than 20%",5,IF(BJ32="P/BV between 2.5x to 5x and Growth more than 20%",10,IF(BJ32= "P/BV between 2.5x to 5x and Growth less than 20%",-5,IF(BJ32= "P/BV above 5x",-5,0))))) | BL32: 20 to 40 | BM32: =IF(BL32="Above 40",20,IF(BL32="20 to 40",10,IF(BL32="0 to 20",-5,0))) | BN32: Between 50 to 75 | BO32: =IF(BN32="Between 50 to 75",10,IF(BN32="Above 75",0,0)) | BP32: Stage 2 | BQ32: =IF(BP32="Stage 2",20,IF(BP32="Stage 1",0,IF(BP32="Stage 3",5,IF(BP32="Stage 4",-5,0)))) | BR32: Negative Trend | BS32: =IF(BR32="Positive Trend",20,IF(BR32="Negative Trend",-10,0)) | BT32: Uptrend | BU32: =IF(BT32="Uptrend",10,IF(BT32="Sideways",5,0)) | BV32: Uptrend | BW32: =IF(BV32="Uptrend",10,IF(BV32="Sideways",5,0)) | BX32: Close to 52 week high or retracement | BY32: =IF(BX32="Overhead supply in last 2 years in last 2 years",-5,IF(BX32="Close to 52 week high or retracement",5,IF(BX32="Blue sky scenario",10,IF(BX32="Long term Downtrend",-10,0)))) | BZ32: Yes | CA32: =IF(BZ32="Yes",10,0)

Sheet Scanner Non Financial
A1: Rank (Non Financial) | B1: Total Score | C1: Entry | D1: Entry Score | E1: Allocation % | F1: Allocation (₹) | G1: Quantity | H1: Symbol | I1: Company | J1: Sector | K1: Industry | L1: Market Cap Bucket | M1: Market Cap Cr | N1: Close | O1: Today Return % | P1: Volume | Q1: Relative Strength Rating | R1: Relative Strength Status | S1: Relative Strength Score | T1: Calculated RSI (14) | U1: Calculated ADX (14) | V1: Calculated V-stop Line | W1: Calculated Near-term Trigger | X1: Sector Benchmark | Y1: Benchmark 1Y Return % | Z1: Stock 1Y Return % | AA1: Relative Strength 1Y (%) | AB1: O'Neil Weighted Score | AC1: Industry Growth | AD1: Industry Growth Score | AE1: Competitiveness | AF1: Competitiveness Score | AG1: Regulation | AH1: Regulation Score | AI1: Sector Headwinds/Tailwind | AJ1: Sector Headwinds/Tailwind Score | AK1: Industry Type | AL1: Industry Type Score | AM1: Margins | AN1: Margins Score | AO1: Margins Stability | AP1: Margins Stability Score | AQ1: Growth | AR1: Growth Score | AS1: Business Type | AT1: Business Type Score | AU1: Near term triggers | AV1: Near term triggers Score | AW1: Type of Revenue | AX1: Type of Revenue Score | AY1: Capital Allocation | AZ1: Capital Allocation Score | BA1: Medium term Growth | BB1: Medium term Growth Score | BC1: ADX | BD1: ADX Score | BE1: RSI | BF1: RSI Score | BG1: Stage Analysis | BH1: Stage Analysis Score | BI1: Price Volume Action | BJ1: Price Volume Action Score | BK1: Secondary Trend | BL1: Secondary Trend Score | BM1: Primary Trend | BN1: Primary Trend Score | BO1: Resistance | BP1: Resistance Score | BQ1: V-stop | BR1: V-stop Score | BS1: PAT Growth | BT1: PAT Growth Score | BU1: Stock History | BV1: Stock History Score | BW1: PE Ratio | BX1: PE Ratio Score | BY1: PEG Ratio | BZ1: PEG Ratio Score | CA1: CFO to EBITDA | CB1: CFO to EBITDA Score | CC1: Debt to Equity | CD1: Debt to Equity Score | CE1: Auditor Resignation | CF1: Auditor Resignation Score | CG1: Contingent Liability | CH1: Contingent Liability Score | CI1: Pledging | CJ1: Pledging Score
A2: =IF(B2=0,"",RANK(B2,$B$2:$B$22,0)) | B2: =SUM(S2,AD2,AF2,AH2,AJ2,AL2,AN2,AP2,AR2,AT2,AV2,AX2,AZ2,BB2,BD2,BF2,BH2,BJ2,BL2,BN2,BP2,BR2,BT2,BV2,BX2,BZ2,CB2,CD2,CF2,CH2,CJ2) | C2: 52W Breakout | D2: 139.1 | E2: 5% | F2: 50000 | G2: 2392 | H2: GAYAPROJ | I2: Gayatri Projects Limited | J2: realty | K2: construction | L2: smallcap | M2: 595.36 | N2: 20.9 | O2: 3.98 | P2: 779784 | Q2: 89 | R2: Outperforming | S2: =IF(R2="Underperforming",-5,IF(Q2>=95,15,IF(Q2>=90,10,IF(Q2>=80,5,0)))) | T2: 73.63 | U2: 62.92 | V2: 16.78 | W2: Volume Spike & Near 52W High Breakout | X2: Nifty Realty | Y2: -26.45 | Z2: 144.73 | AA2: 232.75 | AB2: 34.94 | AC2: Growing Industry | AD2: =IF(AC2="Growing Industry",10,IF(AC2="Cyclical in an Upturn",5,0)) | AE2: Too Many Players with High ROCE | AF2: =IF(AE2="Monopoly",10,IF(AE2="Oligopoly",5,IF(AE2="Duopoly that cooperate",10,IF(AE2="Duopoly that compete",5,IF(AE2="Too many players with High ROCE",5,0))))) | AG2: No | AH2: =IF(AG2="No",5,0) | AI2: Tailwind | AJ2: =IF(AI2="Tailwind",10,0) | AK2: Structural (10 Years Consistency) | AL2: =IF(AK2="Structural (10 Years Consistency)",10,IF(AK2="Shallow Cyclical (2 to 3 years growth)",5,0)) | AM2: No | AN2: =IF(AM2="Yes due to Product Mix change or Operating Leverage",10,IF(AM2="Yes, these are peak margins",-5,IF(AM2="No",5,0))) | AO2: Stable | AP2: =IF(AO2="Stable",10,0) | AQ2: Yes | AR2: =IF(AQ2="Yes",10,0) | AS2: B2B | AT2: =IF(AS2="B2C",10,IF(AS2="B2B",5,0)) | AU2: Yes | AV2: =IF(AU2="Yes",10,0) | AW2: Higher One Time, Lower Annuity | AX2: =IF(AW2="Fully Annuity",10,IF(AW2="Higher Annuity, Lower One Time",5,IF(AW2="Higher One Time, Lower Annuity",3,0))) | AY2: Good | AZ2: =IF(AY2="Good",10,0) | BA2: Yes for more than 2 years | BB2: =IF(BA2="Yes for more than 2 years",10,IF(BA2="Yes only for next 1 to 2 years",5,0)) | BC2: Above 40 | BD2: =IF(BC2="Above 40",20,IF(BC2="20 to 40",10,IF(BC2="0 to 20",-5,0))) | BE2: Between 50 to 75 | BF2: =IF(BE2="Between 50 to 75",10,IF(BE2="Above 75",0,0)) | BG2: Stage 2 | BH2: =IF(BG2="Stage 2",20,IF(BG2="Stage 1",0,IF(BG2="Stage 3",5,IF(BG2="Stage 4",-5,0)))) | BI2: Positive Trend | BJ2: =IF(BI2="Positive Trend",20,IF(BI2="Negative Trend",-10,0)) | BK2: Uptrend | BL2: =IF(BK2="Uptrend",10,IF(BK2="Sideways",5,0)) | BM2: Uptrend | BN2: =IF(BM2="Uptrend",10,IF(BM2="Sideways",5,0)) | BO2: Blue sky scenario | BP2: =IF(BO2="Overhead supply in last 2 years in last 2 years",-5,IF(BO2="Close to 52 week high or retracement",5,IF(BO2="Blue sky scenario",10,IF(BO2="Long term Downtrend",-10,0)))) | BQ2: Yes | BR2: =IF(BQ2="Yes",10,0) | BS2: More than 20% | BT2: =IF(BS2="More than 20%",10,IF(BS2="Between 12 to 20%",5,IF(BS2="Less than 12%",0,0))) | BU2: No | BV2: =IF(BU2="No",10,0) | BW2: No | BX2: =IF(BW2="NO",5,0) | BY2: Above 2 | BZ2: =IF(BY2="Above 2",0,IF(BY2="Between 1.5 to 2",5,IF(BY2="Less than 1.5",10,0))) | CA2: Above 70% | CB2: =IF(CA2="Above 70%",10,IF(CA2="Between 50% to 70%",5,IF(CA2="Less than 50%",0,IF(CA2="Negative",-10,IF(CA2="Less than 50% and Borrowings are increasing",-5,0))))) | CC2: Less than 0.7 | CD2: =IF(CC2="More than 1.2",-10,IF(CC2="Between 0.7 to 1.2",0,IF(CC2="Less than 0.7",10,0))) | CE2: No | CF2: =IF(CE2="Yes",-10,0) | CG2: Less than 15% | CH2: =IF(CG2="More than 15%",-10,IF(CG2="Less than 15%",10,0)) | CI2: No | CJ2: =IF(CI2="Yes, more than 10%",-10,IF(CI2="No",10,0))
A3: =IF(B3=0,"",RANK(B3,$B$2:$B$22,0)) | B3: =SUM(S3,AD3,AF3,AH3,AJ3,AL3,AN3,AP3,AR3,AT3,AV3,AX3,AZ3,BB3,BD3,BF3,BH3,BJ3,BL3,BN3,BP3,BR3,BT3,BV3,BX3,BZ3,CB3,CD3,CF3,CH3,CJ3) | C3: 52W Breakout | D3: 140 | E3: 5% | F3: 50000 | G3: 32 | H3: VENUSREM | I3: Venus Remedies Limited | J3: healthcare | K3: pharmaceuticals - indian - formulations | L3: smallcap | M3: 1980.72 | N3: 1555.8 | O3: 4.99 | P3: 282923 | Q3: 97 | R3: Outperforming | S3: =IF(R3="Underperforming",-5,IF(Q3>=95,15,IF(Q3>=90,10,IF(Q3>=80,5,0)))) | T3: 79.06 | U3: 45.62 | V3: 1173.22 | W3: Volume Spike & Near 52W High Breakout | X3: Nifty Pharma | Y3: 11.5 | Z3: 261.81 | AA3: 224.5 | AB3: 61.02 | AC3: Growing Industry | AD3: =IF(AC3="Growing Industry",10,IF(AC3="Cyclical in an Upturn",5,0)) | AE3: Too Many Players with High ROCE | AF3: =IF(AE3="Monopoly",10,IF(AE3="Oligopoly",5,IF(AE3="Duopoly that cooperate",10,IF(AE3="Duopoly that compete",5,IF(AE3="Too many players with High ROCE",5,0))))) | AG3: Yes | AH3: =IF(AG3="No",5,0) | AI3: Tailwind | AJ3: =IF(AI3="Tailwind",10,0) | AK3: Structural (10 Years Consistency) | AL3: =IF(AK3="Structural (10 Years Consistency)",10,IF(AK3="Shallow Cyclical (2 to 3 years growth)",5,0)) | AM3: No | AN3: =IF(AM3="Yes due to Product Mix change or Operating Leverage",10,IF(AM3="Yes, these are peak margins",-5,IF(AM3="No",5,0))) | AO3: Stable | AP3: =IF(AO3="Stable",10,0) | AQ3: Yes | AR3: =IF(AQ3="Yes",10,0) | AS3: B2B | AT3: =IF(AS3="B2C",10,IF(AS3="B2B",5,0)) | AU3: Yes | AV3: =IF(AU3="Yes",10,0) | AW3: Higher Annuity, Lower One Time | AX3: =IF(AW3="Fully Annuity",10,IF(AW3="Higher Annuity, Lower One Time",5,IF(AW3="Higher One Time, Lower Annuity",3,0))) | AY3: Good | AZ3: =IF(AY3="Good",10,0) | BA3: Yes for more than 2 years | BB3: =IF(BA3="Yes for more than 2 years",10,IF(BA3="Yes only for next 1 to 2 years",5,0)) | BC3: Above 40 | BD3: =IF(BC3="Above 40",20,IF(BC3="20 to 40",10,IF(BC3="0 to 20",-5,0))) | BE3: Above 75 | BF3: =IF(BE3="Between 50 to 75",10,IF(BE3="Above 75",0,0)) | BG3: Stage 2 | BH3: =IF(BG3="Stage 2",20,IF(BG3="Stage 1",0,IF(BG3="Stage 3",5,IF(BG3="Stage 4",-5,0)))) | BI3: Positive Trend | BJ3: =IF(BI3="Positive Trend",20,IF(BI3="Negative Trend",-10,0)) | BK3: Uptrend | BL3: =IF(BK3="Uptrend",10,IF(BK3="Sideways",5,0)) | BM3: Uptrend | BN3: =IF(BM3="Uptrend",10,IF(BM3="Sideways",5,0)) | BO3: Blue sky scenario | BP3: =IF(BO3="Overhead supply in last 2 years in last 2 years",-5,IF(BO3="Close to 52 week high or retracement",5,IF(BO3="Blue sky scenario",10,IF(BO3="Long term Downtrend",-10,0)))) | BQ3: Yes | BR3: =IF(BQ3="Yes",10,0) | BS3: More than 20% | BT3: =IF(BS3="More than 20%",10,IF(BS3="Between 12 to 20%",5,IF(BS3="Less than 12%",0,0))) | BU3: No | BV3: =IF(BU3="No",10,0) | BW3: No | BX3: =IF(BW3="NO",5,0) | BY3: Above 2 | BZ3: =IF(BY3="Above 2",0,IF(BY3="Between 1.5 to 2",5,IF(BY3="Less than 1.5",10,0))) | CA3: Above 70% | CB3: =IF(CA3="Above 70%",10,IF(CA3="Between 50% to 70%",5,IF(CA3="Less than 50%",0,IF(CA3="Negative",-10,IF(CA3="Less than 50% and Borrowings are increasing",-5,0))))) | CC3: Less than 0.7 | CD3: =IF(CC3="More than 1.2",-10,IF(CC3="Between 0.7 to 1.2",0,IF(CC3="Less than 0.7",10,0))) | CE3: No | CF3: =IF(CE3="Yes",-10,0) | CG3: Less than 15% | CH3: =IF(CG3="More than 15%",-10,IF(CG3="Less than 15%",10,0)) | CI3: No | CJ3: =IF(CI3="Yes, more than 10%",-10,IF(CI3="No",10,0))
A4: =IF(B4=0,"",RANK(B4,$B$2:$B$22,0)) | B4: =SUM(S4,AD4,AF4,AH4,AJ4,AL4,AN4,AP4,AR4,AT4,AV4,AX4,AZ4,BB4,BD4,BF4,BH4,BJ4,BL4,BN4,BP4,BR4,BT4,BV4,BX4,BZ4,CB4,CD4,CF4,CH4,CJ4) | C4: 52W Breakout | D4: 139.4 | E4: 5% | F4: 50000 | G4: 10 | H4: NETWEB | I4: Netweb Technologies India Ltd | J4: i.t | K4: computers - hardware | L4: largecap | M4: 26792.3 | N4: 4934.2 | O4: 4.86 | P4: 2758303 | Q4: 88 | R4: Outperforming | S4: =IF(R4="Underperforming",-5,IF(Q4>=95,15,IF(Q4>=90,10,IF(Q4>=80,5,0)))) | T4: 68.63 | U4: 43.6 | V4: 3523.58 | W4: Volume Spike & Near 52W High Breakout | X4: Nifty IT | Y4: -21.44 | Z4: 149.93 | AA4: 218.12 | AB4: 33.37 | AC4: Growing Industry | AD4: =IF(AC4="Growing Industry",10,IF(AC4="Cyclical in an Upturn",5,0)) | AE4: Too Many Players with High ROCE | AF4: =IF(AE4="Monopoly",10,IF(AE4="Oligopoly",5,IF(AE4="Duopoly that cooperate",10,IF(AE4="Duopoly that compete",5,IF(AE4="Too many players with High ROCE",5,0))))) | AG4: No | AH4: =IF(AG4="No",5,0) | AI4: Tailwind | AJ4: =IF(AI4="Tailwind",10,0) | AK4: Structural (10 Years Consistency) | AL4: =IF(AK4="Structural (10 Years Consistency)",10,IF(AK4="Shallow Cyclical (2 to 3 years growth)",5,0)) | AM4: No | AN4: =IF(AM4="Yes due to Product Mix change or Operating Leverage",10,IF(AM4="Yes, these are peak margins",-5,IF(AM4="No",5,0))) | AO4: Stable | AP4: =IF(AO4="Stable",10,0) | AQ4: Yes | AR4: =IF(AQ4="Yes",10,0) | AS4: B2B | AT4: =IF(AS4="B2C",10,IF(AS4="B2B",5,0)) | AU4: Yes | AV4: =IF(AU4="Yes",10,0) | AW4: Higher One Time, Lower Annuity | AX4: =IF(AW4="Fully Annuity",10,IF(AW4="Higher Annuity, Lower One Time",5,IF(AW4="Higher One Time, Lower Annuity",3,0))) | AY4: Good | AZ4: =IF(AY4="Good",10,0) | BA4: Yes for more than 2 years | BB4: =IF(BA4="Yes for more than 2 years",10,IF(BA4="Yes only for next 1 to 2 years",5,0)) | BC4: Above 40 | BD4: =IF(BC4="Above 40",20,IF(BC4="20 to 40",10,IF(BC4="0 to 20",-5,0))) | BE4: Between 50 to 75 | BF4: =IF(BE4="Between 50 to 75",10,IF(BE4="Above 75",0,0)) | BG4: Stage 2 | BH4: =IF(BG4="Stage 2",20,IF(BG4="Stage 1",0,IF(BG4="Stage 3",5,IF(BG4="Stage 4",-5,0)))) | BI4: Positive Trend | BJ4: =IF(BI4="Positive Trend",20,IF(BI4="Negative Trend",-10,0)) | BK4: Uptrend | BL4: =IF(BK4="Uptrend",10,IF(BK4="Sideways",5,0)) | BM4: Uptrend | BN4: =IF(BM4="Uptrend",10,IF(BM4="Sideways",5,0)) | BO4: Blue sky scenario | BP4: =IF(BO4="Overhead supply in last 2 years in last 2 years",-5,IF(BO4="Close to 52 week high or retracement",5,IF(BO4="Blue sky scenario",10,IF(BO4="Long term Downtrend",-10,0)))) | BQ4: Yes | BR4: =IF(BQ4="Yes",10,0) | BS4: More than 20% | BT4: =IF(BS4="More than 20%",10,IF(BS4="Between 12 to 20%",5,IF(BS4="Less than 12%",0,0))) | BU4: No | BV4: =IF(BU4="No",10,0) | BW4: Yes | BX4: =IF(BW4="NO",5,0) | BY4: Above 2 | BZ4: =IF(BY4="Above 2",0,IF(BY4="Between 1.5 to 2",5,IF(BY4="Less than 1.5",10,0))) | CA4: Between 50% to 70% | CB4: =IF(CA4="Above 70%",10,IF(CA4="Between 50% to 70%",5,IF(CA4="Less than 50%",0,IF(CA4="Negative",-10,IF(CA4="Less than 50% and Borrowings are increasing",-5,0))))) | CC4: Less than 0.7 | CD4: =IF(CC4="More than 1.2",-10,IF(CC4="Between 0.7 to 1.2",0,IF(CC4="Less than 0.7",10,0))) | CE4: No | CF4: =IF(CE4="Yes",-10,0) | CG4: Less than 15% | CH4: =IF(CG4="More than 15%",-10,IF(CG4="Less than 15%",10,0)) | CI4: No | CJ4: =IF(CI4="Yes, more than 10%",-10,IF(CI4="No",10,0))
A5: =IF(B5=0,"",RANK(B5,$B$2:$B$22,0)) | B5: =SUM(S5,AD5,AF5,AH5,AJ5,AL5,AN5,AP5,AR5,AT5,AV5,AX5,AZ5,BB5,BD5,BF5,BH5,BJ5,BL5,BN5,BP5,BR5,BT5,BV5,BX5,BZ5,CB5,CD5,CF5,CH5,CJ5) | C5: 52W Breakout | D5: 139.5 | E5: 5% | F5: 50000 | G5: 55 | H5: GVPIL | I5: GE Power India Ltd | J5: realty | K5: engineering - turnkey services | L5: midcap | M5: 5838.37 | N5: 907.55 | O5: 4.5 | P5: 687596 | Q5: 95 | R5: Outperforming | S5: =IF(R5="Underperforming",-5,IF(Q5>=95,15,IF(Q5>=90,10,IF(Q5>=80,5,0)))) | T5: 87.66 | U5: 53.88 | V5: 695.02 | W5: Volume Spike & Near 52W High Breakout | X5: Nifty Realty | Y5: -26.45 | Z5: 232.86 | AA5: 352.58 | AB5: 52.68 | AC5: Growing Industry | AD5: =IF(AC5="Growing Industry",10,IF(AC5="Cyclical in an Upturn",5,0)) | AE5: Duopoly That Cooperate | AF5: =IF(AE5="Monopoly",10,IF(AE5="Oligopoly",5,IF(AE5="Duopoly that cooperate",10,IF(AE5="Duopoly that compete",5,IF(AE5="Too many players with High ROCE",5,0))))) | AG5: No | AH5: =IF(AG5="No",5,0) | AI5: Tailwind | AJ5: =IF(AI5="Tailwind",10,0) | AK5: Shallow Cyclical (2 to 3 Years Growth) | AL5: =IF(AK5="Structural (10 Years Consistency)",10,IF(AK5="Shallow Cyclical (2 to 3 years growth)",5,0)) | AM5: Yes due to Product Mix change or Operating Leverage | AN5: =IF(AM5="Yes due to Product Mix change or Operating Leverage",10,IF(AM5="Yes, these are peak margins",-5,IF(AM5="No",5,0))) | AO5: Stable | AP5: =IF(AO5="Stable",10,0) | AQ5: Yes | AR5: =IF(AQ5="Yes",10,0) | AS5: B2C | AT5: =IF(AS5="B2C",10,IF(AS5="B2B",5,0)) | AU5: Yes | AV5: =IF(AU5="Yes",10,0) | AW5: Fully Annuity | AX5: =IF(AW5="Fully Annuity",10,IF(AW5="Higher Annuity, Lower One Time",5,IF(AW5="Higher One Time, Lower Annuity",3,0))) | AY5: Good | AZ5: =IF(AY5="Good",10,0) | BA5: Yes only for next 1 to 2 years | BB5: =IF(BA5="Yes for more than 2 years",10,IF(BA5="Yes only for next 1 to 2 years",5,0)) | BC5: Above 40 | BD5: =IF(BC5="Above 40",20,IF(BC5="20 to 40",10,IF(BC5="0 to 20",-5,0))) | BE5: Above 75 | BF5: =IF(BE5="Between 50 to 75",10,IF(BE5="Above 75",0,0)) | BG5: Stage 2 | BH5: =IF(BG5="Stage 2",20,IF(BG5="Stage 1",0,IF(BG5="Stage 3",5,IF(BG5="Stage 4",-5,0)))) | BI5: Positive Trend | BJ5: =IF(BI5="Positive Trend",20,IF(BI5="Negative Trend",-10,0)) | BK5: Uptrend | BL5: =IF(BK5="Uptrend",10,IF(BK5="Sideways",5,0)) | BM5: Uptrend | BN5: =IF(BM5="Uptrend",10,IF(BM5="Sideways",5,0)) | BO5: Close to 52 week high or retracement | BP5: =IF(BO5="Overhead supply in last 2 years in last 2 years",-5,IF(BO5="Close to 52 week high or retracement",5,IF(BO5="Blue sky scenario",10,IF(BO5="Long term Downtrend",-10,0)))) | BQ5: Yes | BR5: =IF(BQ5="Yes",10,0) | BS5: More than 20% | BT5: =IF(BS5="More than 20%",10,IF(BS5="Between 12 to 20%",5,IF(BS5="Less than 12%",0,0))) | BU5: No | BV5: =IF(BU5="No",10,0) | BW5: Yes | BX5: =IF(BW5="NO",5,0) | BY5: Above 2 | BZ5: =IF(BY5="Above 2",0,IF(BY5="Between 1.5 to 2",5,IF(BY5="Less than 1.5",10,0))) | CA5: Between 50% to 70% | CB5: =IF(CA5="Above 70%",10,IF(CA5="Between 50% to 70%",5,IF(CA5="Less than 50%",0,IF(CA5="Negative",-10,IF(CA5="Less than 50% and Borrowings are increasing",-5,0))))) | CC5: Between 0.7 to 1.2 | CD5: =IF(CC5="More than 1.2",-10,IF(CC5="Between 0.7 to 1.2",0,IF(CC5="Less than 0.7",10,0))) | CE5: No | CF5: =IF(CE5="Yes",-10,0) | CG5: Less than 15% | CH5: =IF(CG5="More than 15%",-10,IF(CG5="Less than 15%",10,0)) | CI5: No | CJ5: =IF(CI5="Yes, more than 10%",-10,IF(CI5="No",10,0))
A6: =IF(B6=0,"",RANK(B6,$B$2:$B$22,0)) | B6: =SUM(S6,AD6,AF6,AH6,AJ6,AL6,AN6,AP6,AR6,AT6,AV6,AX6,AZ6,BB6,BD6,BF6,BH6,BJ6,BL6,BN6,BP6,BR6,BT6,BV6,BX6,BZ6,CB6,CD6,CF6,CH6,CJ6) | C6: 52W Breakout | D6: 140 | E6: 5% | F6: 50000 | G6: 144 | H6: MODISONLTD | I6: Modison Ltd | J6: industrials | K6: electric equipment | L6: smallcap | M6: 1067.61 | N6: 345.45 | O6: 5 | P6: 247079 | Q6: 98 | R6: Outperforming | S6: =IF(R6="Underperforming",-5,IF(Q6>=95,15,IF(Q6>=90,10,IF(Q6>=80,5,0)))) | T6: 86.51 | U6: 28.93 | V6: 265.88 | W6: Near 52W High Breakout | X6: Nifty 50 | Y6: -6.35 | Z6: 118.85 | AA6: 133.68 | AB6: 62.19 | AC6: Cyclical in an Upturn | AD6: =IF(AC6="Growing Industry",10,IF(AC6="Cyclical in an Upturn",5,0)) | AE6: Too Many Players with High ROCE | AF6: =IF(AE6="Monopoly",10,IF(AE6="Oligopoly",5,IF(AE6="Duopoly that cooperate",10,IF(AE6="Duopoly that compete",5,IF(AE6="Too many players with High ROCE",5,0))))) | AG6: No | AH6: =IF(AG6="No",5,0) | AI6: Tailwind | AJ6: =IF(AI6="Tailwind",10,0) | AK6: Structural (10 Years Consistency) | AL6: =IF(AK6="Structural (10 Years Consistency)",10,IF(AK6="Shallow Cyclical (2 to 3 years growth)",5,0)) | AM6: No | AN6: =IF(AM6="Yes due to Product Mix change or Operating Leverage",10,IF(AM6="Yes, these are peak margins",-5,IF(AM6="No",5,0))) | AO6: Stable | AP6: =IF(AO6="Stable",10,0) | AQ6: Yes | AR6: =IF(AQ6="Yes",10,0) | AS6: B2B | AT6: =IF(AS6="B2C",10,IF(AS6="B2B",5,0)) | AU6: Yes | AV6: =IF(AU6="Yes",10,0) | AW6: Higher One Time, Lower Annuity | AX6: =IF(AW6="Fully Annuity",10,IF(AW6="Higher Annuity, Lower One Time",5,IF(AW6="Higher One Time, Lower Annuity",3,0))) | AY6: Good | AZ6: =IF(AY6="Good",10,0) | BA6: Yes for more than 2 years | BB6: =IF(BA6="Yes for more than 2 years",10,IF(BA6="Yes only for next 1 to 2 years",5,0)) | BC6: 20 to 40 | BD6: =IF(BC6="Above 40",20,IF(BC6="20 to 40",10,IF(BC6="0 to 20",-5,0))) | BE6: Above 75 | BF6: =IF(BE6="Between 50 to 75",10,IF(BE6="Above 75",0,0)) | BG6: Stage 2 | BH6: =IF(BG6="Stage 2",20,IF(BG6="Stage 1",0,IF(BG6="Stage 3",5,IF(BG6="Stage 4",-5,0)))) | BI6: Positive Trend | BJ6: =IF(BI6="Positive Trend",20,IF(BI6="Negative Trend",-10,0)) | BK6: Uptrend | BL6: =IF(BK6="Uptrend",10,IF(BK6="Sideways",5,0)) | BM6: Uptrend | BN6: =IF(BM6="Uptrend",10,IF(BM6="Sideways",5,0)) | BO6: Blue sky scenario | BP6: =IF(BO6="Overhead supply in last 2 years in last 2 years",-5,IF(BO6="Close to 52 week high or retracement",5,IF(BO6="Blue sky scenario",10,IF(BO6="Long term Downtrend",-10,0)))) | BQ6: Yes | BR6: =IF(BQ6="Yes",10,0) | BS6: More than 20% | BT6: =IF(BS6="More than 20%",10,IF(BS6="Between 12 to 20%",5,IF(BS6="Less than 12%",0,0))) | BU6: No | BV6: =IF(BU6="No",10,0) | BW6: No | BX6: =IF(BW6="NO",5,0) | BY6: Above 2 | BZ6: =IF(BY6="Above 2",0,IF(BY6="Between 1.5 to 2",5,IF(BY6="Less than 1.5",10,0))) | CA6: Above 70% | CB6: =IF(CA6="Above 70%",10,IF(CA6="Between 50% to 70%",5,IF(CA6="Less than 50%",0,IF(CA6="Negative",-10,IF(CA6="Less than 50% and Borrowings are increasing",-5,0))))) | CC6: Less than 0.7 | CD6: =IF(CC6="More than 1.2",-10,IF(CC6="Between 0.7 to 1.2",0,IF(CC6="Less than 0.7",10,0))) | CE6: No | CF6: =IF(CE6="Yes",-10,0) | CG6: Less than 15% | CH6: =IF(CG6="More than 15%",-10,IF(CG6="Less than 15%",10,0)) | CI6: No | CJ6: =IF(CI6="Yes, more than 10%",-10,IF(CI6="No",10,0))
A7: =IF(B7=0,"",RANK(B7,$B$2:$B$22,0)) | B7: =SUM(S7,AD7,AF7,AH7,AJ7,AL7,AN7,AP7,AR7,AT7,AV7,AX7,AZ7,BB7,BD7,BF7,BH7,BJ7,BL7,BN7,BP7,BR7,BT7,BV7,BX7,BZ7,CB7,CD7,CF7,CH7,CJ7) | C7: 52W Breakout | D7: 139.2 | E7: 5% | F7: 50000 | G7: 92 | H7: NITINSPIN | I7: Nitin Spinners Limited | J7: textiles | K7: textiles - cotton/blended | L7: smallcap | M7: 2854.85 | N7: 541.55 | O7: 6.65 | P7: 485090 | Q7: 62 | R7: Outperforming | S7: =IF(R7="Underperforming",-5,IF(Q7>=95,15,IF(Q7>=90,10,IF(Q7>=80,5,0)))) | T7: 79.56 | U7: 51.26 | V7: 421.48 | W7: Near 52W High Breakout | X7: Nifty 50 | Y7: -6.35 | Z7: 37.4 | AA7: 46.71 | AB7: 17.51 | AC7: Growing Industry | AD7: =IF(AC7="Growing Industry",10,IF(AC7="Cyclical in an Upturn",5,0)) | AE7: Too Many Players with High ROCE | AF7: =IF(AE7="Monopoly",10,IF(AE7="Oligopoly",5,IF(AE7="Duopoly that cooperate",10,IF(AE7="Duopoly that compete",5,IF(AE7="Too many players with High ROCE",5,0))))) | AG7: No | AH7: =IF(AG7="No",5,0) | AI7: Tailwind | AJ7: =IF(AI7="Tailwind",10,0) | AK7: Structural (10 Years Consistency) | AL7: =IF(AK7="Structural (10 Years Consistency)",10,IF(AK7="Shallow Cyclical (2 to 3 years growth)",5,0)) | AM7: No | AN7: =IF(AM7="Yes due to Product Mix change or Operating Leverage",10,IF(AM7="Yes, these are peak margins",-5,IF(AM7="No",5,0))) | AO7: Stable | AP7: =IF(AO7="Stable",10,0) | AQ7: Yes | AR7: =IF(AQ7="Yes",10,0) | AS7: B2B | AT7: =IF(AS7="B2C",10,IF(AS7="B2B",5,0)) | AU7: Yes | AV7: =IF(AU7="Yes",10,0) | AW7: Higher One Time, Lower Annuity | AX7: =IF(AW7="Fully Annuity",10,IF(AW7="Higher Annuity, Lower One Time",5,IF(AW7="Higher One Time, Lower Annuity",3,0))) | AY7: Good | AZ7: =IF(AY7="Good",10,0) | BA7: Yes for more than 2 years | BB7: =IF(BA7="Yes for more than 2 years",10,IF(BA7="Yes only for next 1 to 2 years",5,0)) | BC7: Above 40 | BD7: =IF(BC7="Above 40",20,IF(BC7="20 to 40",10,IF(BC7="0 to 20",-5,0))) | BE7: Above 75 | BF7: =IF(BE7="Between 50 to 75",10,IF(BE7="Above 75",0,0)) | BG7: Stage 2 | BH7: =IF(BG7="Stage 2",20,IF(BG7="Stage 1",0,IF(BG7="Stage 3",5,IF(BG7="Stage 4",-5,0)))) | BI7: Positive Trend | BJ7: =IF(BI7="Positive Trend",20,IF(BI7="Negative Trend",-10,0)) | BK7: Uptrend | BL7: =IF(BK7="Uptrend",10,IF(BK7="Sideways",5,0)) | BM7: Uptrend | BN7: =IF(BM7="Uptrend",10,IF(BM7="Sideways",5,0)) | BO7: Blue sky scenario | BP7: =IF(BO7="Overhead supply in last 2 years in last 2 years",-5,IF(BO7="Close to 52 week high or retracement",5,IF(BO7="Blue sky scenario",10,IF(BO7="Long term Downtrend",-10,0)))) | BQ7: Yes | BR7: =IF(BQ7="Yes",10,0) | BS7: More than 20% | BT7: =IF(BS7="More than 20%",10,IF(BS7="Between 12 to 20%",5,IF(BS7="Less than 12%",0,0))) | BU7: No | BV7: =IF(BU7="No",10,0) | BW7: No | BX7: =IF(BW7="NO",5,0) | BY7: Less than 1.5 | BZ7: =IF(BY7="Above 2",0,IF(BY7="Between 1.5 to 2",5,IF(BY7="Less than 1.5",10,0))) | CA7: Above 70% | CB7: =IF(CA7="Above 70%",10,IF(CA7="Between 50% to 70%",5,IF(CA7="Less than 50%",0,IF(CA7="Negative",-10,IF(CA7="Less than 50% and Borrowings are increasing",-5,0))))) | CC7: Between 0.7 to 1.2 | CD7: =IF(CC7="More than 1.2",-10,IF(CC7="Between 0.7 to 1.2",0,IF(CC7="Less than 0.7",10,0))) | CE7: No | CF7: =IF(CE7="Yes",-10,0) | CG7: Less than 15% | CH7: =IF(CG7="More than 15%",-10,IF(CG7="Less than 15%",10,0)) | CI7: No | CJ7: =IF(CI7="Yes, more than 10%",-10,IF(CI7="No",10,0))
A8: =IF(B8=0,"",RANK(B8,$B$2:$B$22,0)) | B8: =SUM(S8,AD8,AF8,AH8,AJ8,AL8,AN8,AP8,AR8,AT8,AV8,AX8,AZ8,BB8,BD8,BF8,BH8,BJ8,BL8,BN8,BP8,BR8,BT8,BV8,BX8,BZ8,CB8,CD8,CF8,CH8,CJ8) | C8: 52W Breakout | D8: 139 | E8: 5% | F8: 50000 | G8: 40 | H8: SYRMA | I8: Syrma SGS Technology Ltd | J8: consumer discretionary | K8: electronics - components | L8: largecap | M8: 23049.03 | N8: 1221.6 | O8: 2.2 | P8: 1378327 | Q8: 88 | R8: Outperforming | S8: =IF(R8="Underperforming",-5,IF(Q8>=95,15,IF(Q8>=90,10,IF(Q8>=80,5,0)))) | T8: 72.83 | U8: 29.35 | V8: 937.22 | W8: Near 52W High Breakout | X8: Nifty 50 | Y8: -6.35 | Z8: 128.8 | AA8: 144.3 | AB8: 33.65 | AC8: Growing Industry | AD8: =IF(AC8="Growing Industry",10,IF(AC8="Cyclical in an Upturn",5,0)) | AE8: Too Many Players with High ROCE | AF8: =IF(AE8="Monopoly",10,IF(AE8="Oligopoly",5,IF(AE8="Duopoly that cooperate",10,IF(AE8="Duopoly that compete",5,IF(AE8="Too many players with High ROCE",5,0))))) | AG8: No | AH8: =IF(AG8="No",5,0) | AI8: Tailwind | AJ8: =IF(AI8="Tailwind",10,0) | AK8: Structural (10 Years Consistency) | AL8: =IF(AK8="Structural (10 Years Consistency)",10,IF(AK8="Shallow Cyclical (2 to 3 years growth)",5,0)) | AM8: No | AN8: =IF(AM8="Yes due to Product Mix change or Operating Leverage",10,IF(AM8="Yes, these are peak margins",-5,IF(AM8="No",5,0))) | AO8: Stable | AP8: =IF(AO8="Stable",10,0) | AQ8: Yes | AR8: =IF(AQ8="Yes",10,0) | AS8: B2B | AT8: =IF(AS8="B2C",10,IF(AS8="B2B",5,0)) | AU8: Yes | AV8: =IF(AU8="Yes",10,0) | AW8: Higher One Time, Lower Annuity | AX8: =IF(AW8="Fully Annuity",10,IF(AW8="Higher Annuity, Lower One Time",5,IF(AW8="Higher One Time, Lower Annuity",3,0))) | AY8: Good | AZ8: =IF(AY8="Good",10,0) | BA8: Yes for more than 2 years | BB8: =IF(BA8="Yes for more than 2 years",10,IF(BA8="Yes only for next 1 to 2 years",5,0)) | BC8: 20 to 40 | BD8: =IF(BC8="Above 40",20,IF(BC8="20 to 40",10,IF(BC8="0 to 20",-5,0))) | BE8: Between 50 to 75 | BF8: =IF(BE8="Between 50 to 75",10,IF(BE8="Above 75",0,0)) | BG8: Stage 2 | BH8: =IF(BG8="Stage 2",20,IF(BG8="Stage 1",0,IF(BG8="Stage 3",5,IF(BG8="Stage 4",-5,0)))) | BI8: Positive Trend | BJ8: =IF(BI8="Positive Trend",20,IF(BI8="Negative Trend",-10,0)) | BK8: Uptrend | BL8: =IF(BK8="Uptrend",10,IF(BK8="Sideways",5,0)) | BM8: Uptrend | BN8: =IF(BM8="Uptrend",10,IF(BM8="Sideways",5,0)) | BO8: Blue sky scenario | BP8: =IF(BO8="Overhead supply in last 2 years in last 2 years",-5,IF(BO8="Close to 52 week high or retracement",5,IF(BO8="Blue sky scenario",10,IF(BO8="Long term Downtrend",-10,0)))) | BQ8: Yes | BR8: =IF(BQ8="Yes",10,0) | BS8: More than 20% | BT8: =IF(BS8="More than 20%",10,IF(BS8="Between 12 to 20%",5,IF(BS8="Less than 12%",0,0))) | BU8: No | BV8: =IF(BU8="No",10,0) | BW8: Yes | BX8: =IF(BW8="NO",5,0) | BY8: Between 1.5 to 2 | BZ8: =IF(BY8="Above 2",0,IF(BY8="Between 1.5 to 2",5,IF(BY8="Less than 1.5",10,0))) | CA8: Between 50% to 70% | CB8: =IF(CA8="Above 70%",10,IF(CA8="Between 50% to 70%",5,IF(CA8="Less than 50%",0,IF(CA8="Negative",-10,IF(CA8="Less than 50% and Borrowings are increasing",-5,0))))) | CC8: Less than 0.7 | CD8: =IF(CC8="More than 1.2",-10,IF(CC8="Between 0.7 to 1.2",0,IF(CC8="Less than 0.7",10,0))) | CE8: No | CF8: =IF(CE8="Yes",-10,0) | CG8: Less than 15% | CH8: =IF(CG8="More than 15%",-10,IF(CG8="Less than 15%",10,0)) | CI8: No | CJ8: =IF(CI8="Yes, more than 10%",-10,IF(CI8="No",10,0))
A9: =IF(B9=0,"",RANK(B9,$B$2:$B$22,0)) | B9: =SUM(S9,AD9,AF9,AH9,AJ9,AL9,AN9,AP9,AR9,AT9,AV9,AX9,AZ9,BB9,BD9,BF9,BH9,BJ9,BL9,BN9,BP9,BR9,BT9,BV9,BX9,BZ9,CB9,CD9,CF9,CH9,CJ9) | C9: 52W Breakout | D9: 140 | E9: 5% | F9: 50000 | G9: 76 | H9: STLTECH | I9: Sterlite Technologies Limited | J9: industrials | K9: cables - telephone | L9: largecap | M9: 30293.51 | N9: 651.6 | O9: 5 | P9: 6119470 | Q9: 99 | R9: Outperforming | S9: =IF(R9="Underperforming",-5,IF(Q9>=95,15,IF(Q9>=90,10,IF(Q9>=80,5,0)))) | T9: 96.36 | U9: 76.46 | V9: 522.62 | W9: Near 52W High Breakout | X9: Nifty Infra | Y9: 1.41 | Z9: 759.63 | AA9: 747.68 | AB9: 127.42 | AC9: Cyclical in an Upturn | AD9: =IF(AC9="Growing Industry",10,IF(AC9="Cyclical in an Upturn",5,0)) | AE9: Too Many Players with High ROCE | AF9: =IF(AE9="Monopoly",10,IF(AE9="Oligopoly",5,IF(AE9="Duopoly that cooperate",10,IF(AE9="Duopoly that compete",5,IF(AE9="Too many players with High ROCE",5,0))))) | AG9: No | AH9: =IF(AG9="No",5,0) | AI9: Tailwind | AJ9: =IF(AI9="Tailwind",10,0) | AK9: Structural (10 Years Consistency) | AL9: =IF(AK9="Structural (10 Years Consistency)",10,IF(AK9="Shallow Cyclical (2 to 3 years growth)",5,0)) | AM9: No | AN9: =IF(AM9="Yes due to Product Mix change or Operating Leverage",10,IF(AM9="Yes, these are peak margins",-5,IF(AM9="No",5,0))) | AO9: Stable | AP9: =IF(AO9="Stable",10,0) | AQ9: Yes | AR9: =IF(AQ9="Yes",10,0) | AS9: B2B | AT9: =IF(AS9="B2C",10,IF(AS9="B2B",5,0)) | AU9: Yes | AV9: =IF(AU9="Yes",10,0) | AW9: Higher One Time, Lower Annuity | AX9: =IF(AW9="Fully Annuity",10,IF(AW9="Higher Annuity, Lower One Time",5,IF(AW9="Higher One Time, Lower Annuity",3,0))) | AY9: Good | AZ9: =IF(AY9="Good",10,0) | BA9: Yes for more than 2 years | BB9: =IF(BA9="Yes for more than 2 years",10,IF(BA9="Yes only for next 1 to 2 years",5,0)) | BC9: Above 40 | BD9: =IF(BC9="Above 40",20,IF(BC9="20 to 40",10,IF(BC9="0 to 20",-5,0))) | BE9: Above 75 | BF9: =IF(BE9="Between 50 to 75",10,IF(BE9="Above 75",0,0)) | BG9: Stage 2 | BH9: =IF(BG9="Stage 2",20,IF(BG9="Stage 1",0,IF(BG9="Stage 3",5,IF(BG9="Stage 4",-5,0)))) | BI9: Positive Trend | BJ9: =IF(BI9="Positive Trend",20,IF(BI9="Negative Trend",-10,0)) | BK9: Uptrend | BL9: =IF(BK9="Uptrend",10,IF(BK9="Sideways",5,0)) | BM9: Uptrend | BN9: =IF(BM9="Uptrend",10,IF(BM9="Sideways",5,0)) | BO9: Blue sky scenario | BP9: =IF(BO9="Overhead supply in last 2 years in last 2 years",-5,IF(BO9="Close to 52 week high or retracement",5,IF(BO9="Blue sky scenario",10,IF(BO9="Long term Downtrend",-10,0)))) | BQ9: Yes | BR9: =IF(BQ9="Yes",10,0) | BS9: More than 20% | BT9: =IF(BS9="More than 20%",10,IF(BS9="Between 12 to 20%",5,IF(BS9="Less than 12%",0,0))) | BU9: No | BV9: =IF(BU9="No",10,0) | BW9: Yes | BX9: =IF(BW9="NO",5,0) | BY9: Above 2 | BZ9: =IF(BY9="Above 2",0,IF(BY9="Between 1.5 to 2",5,IF(BY9="Less than 1.5",10,0))) | CA9: Above 70% | CB9: =IF(CA9="Above 70%",10,IF(CA9="Between 50% to 70%",5,IF(CA9="Less than 50%",0,IF(CA9="Negative",-10,IF(CA9="Less than 50% and Borrowings are increasing",-5,0))))) | CC9: Between 0.7 to 1.2 | CD9: =IF(CC9="More than 1.2",-10,IF(CC9="Between 0.7 to 1.2",0,IF(CC9="Less than 0.7",10,0))) | CE9: No | CF9: =IF(CE9="Yes",-10,0) | CG9: Less than 15% | CH9: =IF(CG9="More than 15%",-10,IF(CG9="Less than 15%",10,0)) | CI9: No | CJ9: =IF(CI9="Yes, more than 10%",-10,IF(CI9="No",10,0))
A10: =IF(B10=0,"",RANK(B10,$B$2:$B$22,0)) | B10: =SUM(S10,AD10,AF10,AH10,AJ10,AL10,AN10,AP10,AR10,AT10,AV10,AX10,AZ10,BB10,BD10,BF10,BH10,BJ10,BL10,BN10,BP10,BR10,BT10,BV10,BX10,BZ10,CB10,CD10,CF10,CH10,CJ10) | C10: 52W Breakout | D10: 139.3 | E10: 5% | F10: 50000 | G10: 15 | H10: ACUTAAS | I10: Acutaas Chemicals Ltd | J10: healthcare | K10: pharmaceuticals - indian - bulk drugs | L10: largecap | M10: 25672.33 | N10: 3164.7 | O10: 0.92 | P10: 250577 | Q10: 85 | R10: Outperforming | S10: =IF(R10="Underperforming",-5,IF(Q10>=95,15,IF(Q10>=90,10,IF(Q10>=80,5,0)))) | T10: 77.44 | U10: 64.17 | V10: 2474.32 | W10: Near 52W High Breakout | X10: Nifty Pharma | Y10: 11.5 | Z10: 177.77 | AA10: 149.12 | AB10: 31.65 | AC10: Growing Industry | AD10: =IF(AC10="Growing Industry",10,IF(AC10="Cyclical in an Upturn",5,0)) | AE10: Too Many Players with High ROCE | AF10: =IF(AE10="Monopoly",10,IF(AE10="Oligopoly",5,IF(AE10="Duopoly that cooperate",10,IF(AE10="Duopoly that compete",5,IF(AE10="Too many players with High ROCE",5,0))))) | AG10: Yes | AH10: =IF(AG10="No",5,0) | AI10: Tailwind | AJ10: =IF(AI10="Tailwind",10,0) | AK10: Structural (10 Years Consistency) | AL10: =IF(AK10="Structural (10 Years Consistency)",10,IF(AK10="Shallow Cyclical (2 to 3 years growth)",5,0)) | AM10: No | AN10: =IF(AM10="Yes due to Product Mix change or Operating Leverage",10,IF(AM10="Yes, these are peak margins",-5,IF(AM10="No",5,0))) | AO10: Stable | AP10: =IF(AO10="Stable",10,0) | AQ10: Yes | AR10: =IF(AQ10="Yes",10,0) | AS10: B2B | AT10: =IF(AS10="B2C",10,IF(AS10="B2B",5,0)) | AU10: Yes | AV10: =IF(AU10="Yes",10,0) | AW10: Higher Annuity, Lower One Time | AX10: =IF(AW10="Fully Annuity",10,IF(AW10="Higher Annuity, Lower One Time",5,IF(AW10="Higher One Time, Lower Annuity",3,0))) | AY10: Good | AZ10: =IF(AY10="Good",10,0) | BA10: Yes for more than 2 years | BB10: =IF(BA10="Yes for more than 2 years",10,IF(BA10="Yes only for next 1 to 2 years",5,0)) | BC10: Above 40 | BD10: =IF(BC10="Above 40",20,IF(BC10="20 to 40",10,IF(BC10="0 to 20",-5,0))) | BE10: Above 75 | BF10: =IF(BE10="Between 50 to 75",10,IF(BE10="Above 75",0,0)) | BG10: Stage 2 | BH10: =IF(BG10="Stage 2",20,IF(BG10="Stage 1",0,IF(BG10="Stage 3",5,IF(BG10="Stage 4",-5,0)))) | BI10: Positive Trend | BJ10: =IF(BI10="Positive Trend",20,IF(BI10="Negative Trend",-10,0)) | BK10: Uptrend | BL10: =IF(BK10="Uptrend",10,IF(BK10="Sideways",5,0)) | BM10: Uptrend | BN10: =IF(BM10="Uptrend",10,IF(BM10="Sideways",5,0)) | BO10: Blue sky scenario | BP10: =IF(BO10="Overhead supply in last 2 years in last 2 years",-5,IF(BO10="Close to 52 week high or retracement",5,IF(BO10="Blue sky scenario",10,IF(BO10="Long term Downtrend",-10,0)))) | BQ10: Yes | BR10: =IF(BQ10="Yes",10,0) | BS10: More than 20% | BT10: =IF(BS10="More than 20%",10,IF(BS10="Between 12 to 20%",5,IF(BS10="Less than 12%",0,0))) | BU10: No | BV10: =IF(BU10="No",10,0) | BW10: Yes | BX10: =IF(BW10="NO",5,0) | BY10: Above 2 | BZ10: =IF(BY10="Above 2",0,IF(BY10="Between 1.5 to 2",5,IF(BY10="Less than 1.5",10,0))) | CA10: Between 50% to 70% | CB10: =IF(CA10="Above 70%",10,IF(CA10="Between 50% to 70%",5,IF(CA10="Less than 50%",0,IF(CA10="Negative",-10,IF(CA10="Less than 50% and Borrowings are increasing",-5,0))))) | CC10: Less than 0.7 | CD10: =IF(CC10="More than 1.2",-10,IF(CC10="Between 0.7 to 1.2",0,IF(CC10="Less than 0.7",10,0))) | CE10: No | CF10: =IF(CE10="Yes",-10,0) | CG10: Less than 15% | CH10: =IF(CG10="More than 15%",-10,IF(CG10="Less than 15%",10,0)) | CI10: No | CJ10: =IF(CI10="Yes, more than 10%",-10,IF(CI10="No",10,0))
A11: =IF(B11=0,"",RANK(B11,$B$2:$B$22,0)) | B11: =SUM(S11,AD11,AF11,AH11,AJ11,AL11,AN11,AP11,AR11,AT11,AV11,AX11,AZ11,BB11,BD11,BF11,BH11,BJ11,BL11,BN11,BP11,BR11,BT11,BV11,BX11,BZ11,CB11,CD11,CF11,CH11,CJ11) | C11: 52W Breakout | D11: 140 | E11: 5% | F11: 50000 | G11: 44 | H11: CEMPRO | I11: Cemindia Projects Ltd | J11: realty | K11: construction | L11: midcap | M11: 17606.51 | N11: 1127.3 | O11: 9.99 | P11: 1435282 | Q11: 90 | R11: Outperforming | S11: =IF(R11="Underperforming",-5,IF(Q11>=95,15,IF(Q11>=90,10,IF(Q11>=80,5,0)))) | T11: 75.32 | U11: 35.28 | V11: 860.77 | W11: Near 52W High Breakout | X11: Nifty Realty | Y11: -26.45 | Z11: 51.12 | AA11: 105.48 | AB11: 35.59 | AC11: Growing Industry | AD11: =IF(AC11="Growing Industry",10,IF(AC11="Cyclical in an Upturn",5,0)) | AE11: Too Many Players with High ROCE | AF11: =IF(AE11="Monopoly",10,IF(AE11="Oligopoly",5,IF(AE11="Duopoly that cooperate",10,IF(AE11="Duopoly that compete",5,IF(AE11="Too many players with High ROCE",5,0))))) | AG11: No | AH11: =IF(AG11="No",5,0) | AI11: Tailwind | AJ11: =IF(AI11="Tailwind",10,0) | AK11: Structural (10 Years Consistency) | AL11: =IF(AK11="Structural (10 Years Consistency)",10,IF(AK11="Shallow Cyclical (2 to 3 years growth)",5,0)) | AM11: No | AN11: =IF(AM11="Yes due to Product Mix change or Operating Leverage",10,IF(AM11="Yes, these are peak margins",-5,IF(AM11="No",5,0))) | AO11: Stable | AP11: =IF(AO11="Stable",10,0) | AQ11: Yes | AR11: =IF(AQ11="Yes",10,0) | AS11: B2B | AT11: =IF(AS11="B2C",10,IF(AS11="B2B",5,0)) | AU11: Yes | AV11: =IF(AU11="Yes",10,0) | AW11: Higher One Time, Lower Annuity | AX11: =IF(AW11="Fully Annuity",10,IF(AW11="Higher Annuity, Lower One Time",5,IF(AW11="Higher One Time, Lower Annuity",3,0))) | AY11: Good | AZ11: =IF(AY11="Good",10,0) | BA11: Yes for more than 2 years | BB11: =IF(BA11="Yes for more than 2 years",10,IF(BA11="Yes only for next 1 to 2 years",5,0)) | BC11: 20 to 40 | BD11: =IF(BC11="Above 40",20,IF(BC11="20 to 40",10,IF(BC11="0 to 20",-5,0))) | BE11: Above 75 | BF11: =IF(BE11="Between 50 to 75",10,IF(BE11="Above 75",0,0)) | BG11: Stage 2 | BH11: =IF(BG11="Stage 2",20,IF(BG11="Stage 1",0,IF(BG11="Stage 3",5,IF(BG11="Stage 4",-5,0)))) | BI11: Positive Trend | BJ11: =IF(BI11="Positive Trend",20,IF(BI11="Negative Trend",-10,0)) | BK11: Uptrend | BL11: =IF(BK11="Uptrend",10,IF(BK11="Sideways",5,0)) | BM11: Uptrend | BN11: =IF(BM11="Uptrend",10,IF(BM11="Sideways",5,0)) | BO11: Blue sky scenario | BP11: =IF(BO11="Overhead supply in last 2 years in last 2 years",-5,IF(BO11="Close to 52 week high or retracement",5,IF(BO11="Blue sky scenario",10,IF(BO11="Long term Downtrend",-10,0)))) | BQ11: Yes | BR11: =IF(BQ11="Yes",10,0) | BS11: More than 20% | BT11: =IF(BS11="More than 20%",10,IF(BS11="Between 12 to 20%",5,IF(BS11="Less than 12%",0,0))) | BU11: No | BV11: =IF(BU11="No",10,0) | BW11: No | BX11: =IF(BW11="NO",5,0) | BY11: Above 2 | BZ11: =IF(BY11="Above 2",0,IF(BY11="Between 1.5 to 2",5,IF(BY11="Less than 1.5",10,0))) | CA11: Less than 50% | CB11: =IF(CA11="Above 70%",10,IF(CA11="Between 50% to 70%",5,IF(CA11="Less than 50%",0,IF(CA11="Negative",-10,IF(CA11="Less than 50% and Borrowings are increasing",-5,0))))) | CC11: Less than 0.7 | CD11: =IF(CC11="More than 1.2",-10,IF(CC11="Between 0.7 to 1.2",0,IF(CC11="Less than 0.7",10,0))) | CE11: No | CF11: =IF(CE11="Yes",-10,0) | CG11: Less than 15% | CH11: =IF(CG11="More than 15%",-10,IF(CG11="Less than 15%",10,0)) | CI11: No | CJ11: =IF(CI11="Yes, more than 10%",-10,IF(CI11="No",10,0))
A12: =IF(B12=0,"",RANK(B12,$B$2:$B$22,0)) | B12: =SUM(S12,AD12,AF12,AH12,AJ12,AL12,AN12,AP12,AR12,AT12,AV12,AX12,AZ12,BB12,BD12,BF12,BH12,BJ12,BL12,BN12,BP12,BR12,BT12,BV12,BX12,BZ12,CB12,CD12,CF12,CH12,CJ12) | C12: 52W Breakout | D12: 140 | E12: 5% | F12: 50000 | G12: 109 | H12: SIGMAADV | I12: Sigma Advanced System Ltd | J12: aerospace & defence | K12: electronics - components | L12: midcap | M12: 7699.91 | N12: 458.7 | O12: 4.99 | P12: 224154 | Q12: 99 | R12: Outperforming | S12: =IF(R12="Underperforming",-5,IF(Q12>=95,15,IF(Q12>=90,10,IF(Q12>=80,5,0)))) | T12: 85.09 | U12: 34.03 | V12: 352.92 | W12: Volume Spike & Near 52W High Breakout | X12: Nifty 50 | Y12: -6.35 | Z12: 396.75 | AA12: 430.41 | AB12: 89.41 | AC12: Growing Industry | AD12: =IF(AC12="Growing Industry",10,IF(AC12="Cyclical in an Upturn",5,0)) | AE12: Too Many Players with High ROCE | AF12: =IF(AE12="Monopoly",10,IF(AE12="Oligopoly",5,IF(AE12="Duopoly that cooperate",10,IF(AE12="Duopoly that compete",5,IF(AE12="Too many players with High ROCE",5,0))))) | AG12: No | AH12: =IF(AG12="No",5,0) | AI12: Tailwind | AJ12: =IF(AI12="Tailwind",10,0) | AK12: Structural (10 Years Consistency) | AL12: =IF(AK12="Structural (10 Years Consistency)",10,IF(AK12="Shallow Cyclical (2 to 3 years growth)",5,0)) | AM12: No | AN12: =IF(AM12="Yes due to Product Mix change or Operating Leverage",10,IF(AM12="Yes, these are peak margins",-5,IF(AM12="No",5,0))) | AO12: Stable | AP12: =IF(AO12="Stable",10,0) | AQ12: Yes | AR12: =IF(AQ12="Yes",10,0) | AS12: B2B | AT12: =IF(AS12="B2C",10,IF(AS12="B2B",5,0)) | AU12: Yes | AV12: =IF(AU12="Yes",10,0) | AW12: Higher One Time, Lower Annuity | AX12: =IF(AW12="Fully Annuity",10,IF(AW12="Higher Annuity, Lower One Time",5,IF(AW12="Higher One Time, Lower Annuity",3,0))) | AY12: Good | AZ12: =IF(AY12="Good",10,0) | BA12: Yes for more than 2 years | BB12: =IF(BA12="Yes for more than 2 years",10,IF(BA12="Yes only for next 1 to 2 years",5,0)) | BC12: 20 to 40 | BD12: =IF(BC12="Above 40",20,IF(BC12="20 to 40",10,IF(BC12="0 to 20",-5,0))) | BE12: Above 75 | BF12: =IF(BE12="Between 50 to 75",10,IF(BE12="Above 75",0,0)) | BG12: Stage 2 | BH12: =IF(BG12="Stage 2",20,IF(BG12="Stage 1",0,IF(BG12="Stage 3",5,IF(BG12="Stage 4",-5,0)))) | BI12: Positive Trend | BJ12: =IF(BI12="Positive Trend",20,IF(BI12="Negative Trend",-10,0)) | BK12: Uptrend | BL12: =IF(BK12="Uptrend",10,IF(BK12="Sideways",5,0)) | BM12: Uptrend | BN12: =IF(BM12="Uptrend",10,IF(BM12="Sideways",5,0)) | BO12: Blue sky scenario | BP12: =IF(BO12="Overhead supply in last 2 years in last 2 years",-5,IF(BO12="Close to 52 week high or retracement",5,IF(BO12="Blue sky scenario",10,IF(BO12="Long term Downtrend",-10,0)))) | BQ12: Yes | BR12: =IF(BQ12="Yes",10,0) | BS12: More than 20% | BT12: =IF(BS12="More than 20%",10,IF(BS12="Between 12 to 20%",5,IF(BS12="Less than 12%",0,0))) | BU12: No | BV12: =IF(BU12="No",10,0) | BW12: No | BX12: =IF(BW12="NO",5,0) | BY12: Less than 1.5 | BZ12: =IF(BY12="Above 2",0,IF(BY12="Between 1.5 to 2",5,IF(BY12="Less than 1.5",10,0))) | CA12: Negative | CB12: =IF(CA12="Above 70%",10,IF(CA12="Between 50% to 70%",5,IF(CA12="Less than 50%",0,IF(CA12="Negative",-10,IF(CA12="Less than 50% and Borrowings are increasing",-5,0))))) | CC12: Between 0.7 to 1.2 | CD12: =IF(CC12="More than 1.2",-10,IF(CC12="Between 0.7 to 1.2",0,IF(CC12="Less than 0.7",10,0))) | CE12: No | CF12: =IF(CE12="Yes",-10,0) | CG12: Less than 15% | CH12: =IF(CG12="More than 15%",-10,IF(CG12="Less than 15%",10,0)) | CI12: No | CJ12: =IF(CI12="Yes, more than 10%",-10,IF(CI12="No",10,0))
A13: =IF(B13=0,"",RANK(B13,$B$2:$B$22,0)) | B13: =SUM(S13,AD13,AF13,AH13,AJ13,AL13,AN13,AP13,AR13,AT13,AV13,AX13,AZ13,BB13,BD13,BF13,BH13,BJ13,BL13,BN13,BP13,BR13,BT13,BV13,BX13,BZ13,CB13,CD13,CF13,CH13,CJ13) | C13: 52W Breakout | D13: 139.5 | E13: 5% | F13: 50000 | G13: 35 | H13: LAURUSLABS | I13: Laurus Labs Limited | J13: healthcare | K13: pharmaceuticals - indian - bulk drugs & formln | L13: largecap | M13: 75272.2 | N13: 1427.2 | O13: 2.36 | P13: 1983191 | Q13: 82 | R13: Outperforming | S13: =IF(R13="Underperforming",-5,IF(Q13>=95,15,IF(Q13>=90,10,IF(Q13>=80,5,0)))) | T13: 79.21 | U13: 29.88 | V13: 1208.41 | W13: Near 52W High Breakout | X13: Nifty Pharma | Y13: 11.5 | Z13: 122.69 | AA13: 99.73 | AB13: 26.44 | AC13: Growing Industry | AD13: =IF(AC13="Growing Industry",10,IF(AC13="Cyclical in an Upturn",5,0)) | AE13: Too Many Players with High ROCE | AF13: =IF(AE13="Monopoly",10,IF(AE13="Oligopoly",5,IF(AE13="Duopoly that cooperate",10,IF(AE13="Duopoly that compete",5,IF(AE13="Too many players with High ROCE",5,0))))) | AG13: Yes | AH13: =IF(AG13="No",5,0) | AI13: Tailwind | AJ13: =IF(AI13="Tailwind",10,0) | AK13: Structural (10 Years Consistency) | AL13: =IF(AK13="Structural (10 Years Consistency)",10,IF(AK13="Shallow Cyclical (2 to 3 years growth)",5,0)) | AM13: No | AN13: =IF(AM13="Yes due to Product Mix change or Operating Leverage",10,IF(AM13="Yes, these are peak margins",-5,IF(AM13="No",5,0))) | AO13: Stable | AP13: =IF(AO13="Stable",10,0) | AQ13: Yes | AR13: =IF(AQ13="Yes",10,0) | AS13: B2B | AT13: =IF(AS13="B2C",10,IF(AS13="B2B",5,0)) | AU13: Yes | AV13: =IF(AU13="Yes",10,0) | AW13: Higher Annuity, Lower One Time | AX13: =IF(AW13="Fully Annuity",10,IF(AW13="Higher Annuity, Lower One Time",5,IF(AW13="Higher One Time, Lower Annuity",3,0))) | AY13: Good | AZ13: =IF(AY13="Good",10,0) | BA13: Yes for more than 2 years | BB13: =IF(BA13="Yes for more than 2 years",10,IF(BA13="Yes only for next 1 to 2 years",5,0)) | BC13: 20 to 40 | BD13: =IF(BC13="Above 40",20,IF(BC13="20 to 40",10,IF(BC13="0 to 20",-5,0))) | BE13: Above 75 | BF13: =IF(BE13="Between 50 to 75",10,IF(BE13="Above 75",0,0)) | BG13: Stage 2 | BH13: =IF(BG13="Stage 2",20,IF(BG13="Stage 1",0,IF(BG13="Stage 3",5,IF(BG13="Stage 4",-5,0)))) | BI13: Positive Trend | BJ13: =IF(BI13="Positive Trend",20,IF(BI13="Negative Trend",-10,0)) | BK13: Uptrend | BL13: =IF(BK13="Uptrend",10,IF(BK13="Sideways",5,0)) | BM13: Uptrend | BN13: =IF(BM13="Uptrend",10,IF(BM13="Sideways",5,0)) | BO13: Blue sky scenario | BP13: =IF(BO13="Overhead supply in last 2 years in last 2 years",-5,IF(BO13="Close to 52 week high or retracement",5,IF(BO13="Blue sky scenario",10,IF(BO13="Long term Downtrend",-10,0)))) | BQ13: Yes | BR13: =IF(BQ13="Yes",10,0) | BS13: Between 12 to 20% | BT13: =IF(BS13="More than 20%",10,IF(BS13="Between 12 to 20%",5,IF(BS13="Less than 12%",0,0))) | BU13: No | BV13: =IF(BU13="No",10,0) | BW13: Yes | BX13: =IF(BW13="NO",5,0) | BY13: Above 2 | BZ13: =IF(BY13="Above 2",0,IF(BY13="Between 1.5 to 2",5,IF(BY13="Less than 1.5",10,0))) | CA13: Above 70% | CB13: =IF(CA13="Above 70%",10,IF(CA13="Between 50% to 70%",5,IF(CA13="Less than 50%",0,IF(CA13="Negative",-10,IF(CA13="Less than 50% and Borrowings are increasing",-5,0))))) | CC13: Less than 0.7 | CD13: =IF(CC13="More than 1.2",-10,IF(CC13="Between 0.7 to 1.2",0,IF(CC13="Less than 0.7",10,0))) | CE13: No | CF13: =IF(CE13="Yes",-10,0) | CG13: Less than 15% | CH13: =IF(CG13="More than 15%",-10,IF(CG13="Less than 15%",10,0)) | CI13: No | CJ13: =IF(CI13="Yes, more than 10%",-10,IF(CI13="No",10,0))
... A22: =IF(B22=0,"",RANK(B22,$B$2:$B$22,0)) | B22: =SUM(S22,AD22,AF22,AH22,AJ22,AL22,AN22,AP22,AR22,AT22,AV22,AX22,AZ22,BB22,BD22,BF22,BH22,BJ22,BL22,BN22,BP22,BR22,BT22,BV22,BX22,BZ22,CB22,CD22,CF22,CH22,CJ22) | C22: 52W Breakout | D22: 139.5 | E22: 5% | F22: 50000 | G22: 144 | H22: ACMESOLAR | I22: ACME Solar Holdings Ltd | J22: realty | K22: engineering - turnkey services | L22: midcap | M22: 19939.5 | N22: 345.85 | O22: 5.11 | P22: 4610275 | Q22: 69 | R22: Outperforming | S22: =IF(R22="Underperforming",-5,IF(Q22>=95,15,IF(Q22>=90,10,IF(Q22>=80,5,0)))) | T22: 70.44 | U22: 18.4 | V22: 267.19 | W22: Volume Spike & Near 52W High Breakout | X22: Nifty Realty | Y22: -26.45 | Z22: 37.99 | AA22: 87.62 | AB22: 20.05 | AC22: Growing Industry | AD22: =IF(AC22="Growing Industry",10,IF(AC22="Cyclical in an Upturn",5,0)) | AE22: Too Many Players with High ROCE | AF22: =IF(AE22="Monopoly",10,IF(AE22="Oligopoly",5,IF(AE22="Duopoly that cooperate",10,IF(AE22="Duopoly that compete",5,IF(AE22="Too many players with High ROCE",5,0))))) | AG22: No | AH22: =IF(AG22="No",5,0) | AI22: Tailwind | AJ22: =IF(AI22="Tailwind",10,0) | AK22: Structural (10 Years Consistency) | AL22: =IF(AK22="Structural (10 Years Consistency)",10,IF(AK22="Shallow Cyclical (2 to 3 years growth)",5,0)) | AM22: No | AN22: =IF(AM22="Yes due to Product Mix change or Operating Leverage",10,IF(AM22="Yes, these are peak margins",-5,IF(AM22="No",5,0))) | AO22: Stable | AP22: =IF(AO22="Stable",10,0) | AQ22: Yes | AR22: =IF(AQ22="Yes",10,0) | AS22: B2B | AT22: =IF(AS22="B2C",10,IF(AS22="B2B",5,0)) | AU22: Yes | AV22: =IF(AU22="Yes",10,0) | AW22: Higher One Time, Lower Annuity | AX22: =IF(AW22="Fully Annuity",10,IF(AW22="Higher Annuity, Lower One Time",5,IF(AW22="Higher One Time, Lower Annuity",3,0))) | AY22: Good | AZ22: =IF(AY22="Good",10,0) | BA22: Yes for more than 2 years | BB22: =IF(BA22="Yes for more than 2 years",10,IF(BA22="Yes only for next 1 to 2 years",5,0)) | BC22: 0 to 20 | BD22: =IF(BC22="Above 40",20,IF(BC22="20 to 40",10,IF(BC22="0 to 20",-5,0))) | BE22: Between 50 to 75 | BF22: =IF(BE22="Between 50 to 75",10,IF(BE22="Above 75",0,0)) | BG22: Stage 2 | BH22: =IF(BG22="Stage 2",20,IF(BG22="Stage 1",0,IF(BG22="Stage 3",5,IF(BG22="Stage 4",-5,0)))) | BI22: Positive Trend | BJ22: =IF(BI22="Positive Trend",20,IF(BI22="Negative Trend",-10,0)) | BK22: Uptrend | BL22: =IF(BK22="Uptrend",10,IF(BK22="Sideways",5,0)) | BM22: Uptrend | BN22: =IF(BM22="Uptrend",10,IF(BM22="Sideways",5,0)) | BO22: Blue sky scenario | BP22: =IF(BO22="Overhead supply in last 2 years in last 2 years",-5,IF(BO22="Close to 52 week high or retracement",5,IF(BO22="Blue sky scenario",10,IF(BO22="Long term Downtrend",-10,0)))) | BQ22: Yes | BR22: =IF(BQ22="Yes",10,0) | BS22: Less than 12% | BT22: =IF(BS22="More than 20%",10,IF(BS22="Between 12 to 20%",5,IF(BS22="Less than 12%",0,0))) | BU22: No | BV22: =IF(BU22="No",10,0) | BW22: Yes | BX22: =IF(BW22="NO",5,0) | BY22: Above 2 | BZ22: =IF(BY22="Above 2",0,IF(BY22="Between 1.5 to 2",5,IF(BY22="Less than 1.5",10,0))) | CA22: Between 50% to 70% | CB22: =IF(CA22="Above 70%",10,IF(CA22="Between 50% to 70%",5,IF(CA22="Less than 50%",0,IF(CA22="Negative",-10,IF(CA22="Less than 50% and Borrowings are increasing",-5,0))))) | CC22: More than 1.2 | CD22: =IF(CC22="More than 1.2",-10,IF(CC22="Between 0.7 to 1.2",0,IF(CC22="Less than 0.7",10,0))) | CE22: No | CF22: =IF(CE22="Yes",-10,0) | CG22: Less than 15% | CH22: =IF(CG22="More than 15%",-10,IF(CG22="Less than 15%",10,0)) | CI22: No | CJ22: =IF(CI22="Yes, more than 10%",-10,IF(CI22="No",10,0))

Sheet Scanner Banks NBFC
A1: Rank (Banks & NBFC) | B1: Total Score | C1: Entry | D1: Entry Score | E1: Allocation % | F1: Allocation (₹) | G1: Quantity | H1: Symbol | I1: Company | J1: Sector | K1: Industry | L1: Market Cap Bucket | M1: Market Cap Cr | N1: Close | O1: Today Return % | P1: Volume | Q1: Relative Strength Rating | R1: Relative Strength Status | S1: Relative Strength Score | T1: Calculated RSI (14) | U1: Calculated ADX (14) | V1: Calculated V-stop Line | W1: Calculated Near-term Trigger | X1: Sector Benchmark | Y1: Benchmark 1Y Return % | Z1: Stock 1Y Return % | AA1: Relative Strength 1Y (%) | AB1: O'Neil Weighted Score | AC1: Industry Growth | AD1: Industry Growth Score | AE1: Competitiveness | AF1: Competitiveness Score | AG1: Regulation | AH1: Regulation Score | AI1: Sector Headwinds/Tailwind | AJ1: Sector Headwinds/Tailwind Score | AK1: Industry Type | AL1: Industry Type Score | AM1: NIM | AN1: NIM Score | AO1: CASA Ratio | AP1: CASA Ratio Score | AQ1: Profit cyclicality | AR1: Profit cyclicality Score | AS1: CAR Ratio | AT1: CAR Ratio Score | AU1: Near term triggers | AV1: Near term triggers Score | AW1: High P/BV | AX1: High P/BV Score | AY1: Asset Quality Divergence | AZ1: Asset Quality Divergence Score | BA1: Reported loss | BB1: Reported loss Score | BC1: CEO Resignation | BD1: CEO Resignation Score | BE1: GNPA | BF1: GNPA Score | BG1: KMP Resignation | BH1: KMP Resignation Score | BI1: Return on Assets | BJ1: Return on Assets Score | BK1: Return on Equity | BL1: Return on Equity Score | BM1: AUM Growth | BN1: AUM Growth Score | BO1: Price to Book Value | BP1: Price to Book Value Score | BQ1: ADX | BR1: ADX Score | BS1: RSI | BT1: RSI Score | BU1: Stage Analysis | BV1: Stage Analysis Score | BW1: Price Volume Action | BX1: Price Volume Action Score | BY1: Secondary Trend | BZ1: Secondary Trend Score | CA1: Primary Trend | CB1: Primary Trend Score | CC1: Resistance | CD1: Resistance Score | CE1: V-stop | CF1: V-stop Score
A2: =IF(B2=0,"",RANK(B2,$B$2:$B$2,0)) | B2: =SUM(S2,AD2,AF2,AH2,AJ2,AL2,AN2,AP2,AR2,AT2,AV2,AX2,AZ2,BB2,BD2,BF2,BH2,BJ2,BL2,BN2,BP2,BR2,BT2,BV2,BX2,BZ2,CB2,CD2,CF2) | C2: 52W Breakout | D2: 139.4 | E2: 5% | F2: 50000 | G2: 141 | H2: RBLBANK | I2: Rbl Bank Limited | J2: bank | K2: banks - private sector | L2: largecap | M2: 21522.64 | N2: 353.75 | O2: 1.59 | P2: 5254858 | Q2: 51 | R2: Outperforming | S2: =IF(R2="Underperforming",-5,IF(Q2>=95,15,IF(Q2>=90,10,IF(Q2>=80,5,0)))) | T2: 66.05 | U2: 27.24 | V2: 292.3 | W2: Near 52W High Breakout | X2: Nifty Bank | Y2: -4.01 | Z2: 63.14 | AA2: 69.96 | AB2: 14.05 | AC2: Growing Industry | AD2: =IF(AC2="Growing Industry",10,IF(AC2="Cyclical in an Upturn",5,0)) | AE2: Fragmented with High ROE | AF2: =IF(AE2="Fragmented with Low ROE",-5,IF(AE2="Fragmented with High ROE",10,IF(AE2= "highly cyclical",5,0))) | AG2: Yes | AH2: =IF(AG2="No",5,0) | AI2: Tailwind | AJ2: =IF(AI2="Tailwind",10,0) | AK2: Structural (10 Years Consistency) | AL2: =IF(AK2="Structural (10 Years Consistency)",15,IF(AK2="Shallow Cyclical (2 to 3 years growth)",10,IF(AK2 = "Cyclical in an Uptick",5,IF(AK2 = "Cyclical in an Downtick",-10,0)))) | AM2: Yes | AN2: =IF(AM2="Yes",10,0) | AO2: Yes | AP2: =IF(AO2="Yes",10,0) | AR2: =IF(AQ2="No",10,0) | AS2: Yes | AT2: =IF(AS2="Yes",10,0) | AU2: Yes | AV2: =IF(AU2="Yes",10,0) | AW2: Yes | AX2: =IF(AW2="Yes",5,0) | AY2: No | AZ2: =IF(AY2="No",10,IF(AY2="Yes",-10,0)) | BA2: No | BB2: =IF(BA2="No",10,0) | BC2: No | BD2: =IF(BC2="No",10,IF(BC2= "Yes CEO Resignation",-5,0)) | BE2: No | BF2: =IF(BE2="No",10,IF(BE2="Yes",-5,0)) | BG2: No | BH2: =IF(BG2="No",5,IF(BG2="Yes",-5,0)) | BI2: Yes | BJ2: =IF(BI2="Yes",10,0) | BK2: Yes | BL2: =IF(BK2="Yes",10,0) | BM2: Yes | BN2: =IF(BM2="Yes",10,0) | BO2: P/BV less than 2.5x and Growth more than 20% | BP2: =IF(BO2="P/BV less than 2.5x and Growth more than 20%",20,IF(BO2 = "P/BV less than 2.5x and Growth less than 20%",5,IF(BO2="P/BV between 2.5x to 5x and Growth more than 20%",10,IF(BO2= "P/BV between 2.5x to 5x and Growth less than 20%",-5,IF(BO2= "P/BV above 5x",-5,0))))) | BQ2: 20 to 40 | BR2: =IF(BQ2="Above 40",20,IF(BQ2="20 to 40",10,IF(BQ2="0 to 20",-5,0))) | BS2: Between 50 to 75 | BT2: =IF(BS2="Between 50 to 75",10,IF(BS2="Above 75",0,0)) | BU2: Stage 2 | BV2: =IF(BU2="Stage 2",20,IF(BU2="Stage 1",0,IF(BU2="Stage 3",5,IF(BU2="Stage 4",-5,0)))) | BW2: Positive Trend | BX2: =IF(BW2="Positive Trend",20,IF(BW2="Negative Trend",-10,0)) | BY2: Uptrend | BZ2: =IF(BY2="Uptrend",10,IF(BY2="Sideways",5,0)) | CA2: Uptrend | CB2: =IF(CA2="Uptrend",10,IF(CA2="Sideways",5,0)) | CC2: Blue sky scenario | CD2: =IF(CC2="Overhead supply in last 2 years in last 2 years",-5,IF(CC2="Close to 52 week high or retracement",5,IF(CC2="Blue sky scenario",10,IF(CC2="Long term Downtrend",-10,0)))) | CE2: Yes | CF2: =IF(CE2="Yes",10,0)

Sheet Scan Match Non Financial
A1: Rank (Non Financial) | B1: Total Score | C1: Symbol | D1: Company | E1: Sector | F1: Industry | G1: Market Cap Bucket | H1: Market Cap Cr | I1: Close | J1: Today Return % | K1: Volume | L1: Relative Strength Rating | M1: Relative Strength Status | N1: Relative Strength Score | O1: Calculated RSI (14) | P1: Calculated ADX (14) | Q1: Calculated V-stop Line | R1: Calculated Near-term Trigger | S1: Sector Benchmark | T1: Benchmark 1Y Return % | U1: Stock 1Y Return % | V1: Relative Strength 1Y (%) | W1: O'Neil Weighted Score | X1: Industry Growth | Y1: Industry Growth Score | Z1: Competitiveness | AA1: Competitiveness Score | AB1: Regulation | AC1: Regulation Score | AD1: Sector Headwinds/Tailwind | AE1: Sector Headwinds/Tailwind Score | AF1: Industry Type | AG1: Industry Type Score | AH1: Margins | AI1: Margins Score | AJ1: Margins Stability | AK1: Margins Stability Score | AL1: Growth | AM1: Growth Score | AN1: Business Type | AO1: Business Type Score | AP1: Near term triggers | AQ1: Near term triggers Score | AR1: Type of Revenue | AS1: Type of Revenue Score | AT1: Capital Allocation | AU1: Capital Allocation Score | AV1: Medium term Growth | AW1: Medium term Growth Score | AX1: ADX | AY1: ADX Score | AZ1: RSI | BA1: RSI Score | BB1: Stage Analysis | BC1: Stage Analysis Score | BD1: Price Volume Action | BE1: Price Volume Action Score | BF1: Secondary Trend | BG1: Secondary Trend Score | BH1: Primary Trend | BI1: Primary Trend Score | BJ1: Resistance | BK1: Resistance Score | BL1: V-stop | BM1: V-stop Score | BN1: PAT Growth | BO1: PAT Growth Score | BP1: Stock History | BQ1: Stock History Score | BR1: PE Ratio | BS1: PE Ratio Score | BT1: PEG Ratio | BU1: PEG Ratio Score | BV1: CFO to EBITDA | BW1: CFO to EBITDA Score | BX1: Debt to Equity | BY1: Debt to Equity Score | BZ1: Auditor Resignation | CA1: Auditor Resignation Score | CB1: Contingent Liability | CC1: Contingent Liability Score | CD1: Pledging | CE1: Pledging Score | CF1: Scan Matches | CG1: Scan Matches Score
A2: =IF(B2=0,"",RANK(B2,$B$2:$B$94,0)) | B2: =SUM(N2,Y2,AA2,AC2,AE2,AG2,AI2,AK2,AM2,AO2,AQ2,AS2,AU2,AW2,AY2,BA2,BC2,BE2,BG2,BI2,BK2,BM2,BO2,BQ2,BS2,BU2,BW2,BY2,CA2,CC2,CE2,CG2) | C2: BAJAJCON | D2: Bajaj Consumer Care Ltd | E2: fmcg | F2: FMCG - Personal Care | G2: midcap | H2: 7298.95 | I2: 558.8 | J2: 0.61 | K2: 0 | L2: 91 | M2: Outperforming | N2: =IF(M2="Underperforming",-5,IF(L2>=95,15,IF(L2>=90,10,IF(L2>=80,5,0)))) | O2: 74.91 | P2: 51.77 | Q2: 441.56 | R2: Near 52W High Breakout | S2: Nifty FMCG | T2: -13.6 | U2: 221.06 | V2: 271.57 | W2: 37.53 | X2: Growing Industry | Y2: =IF(X2="Growing Industry",10,IF(X2="Cyclical in an Upturn",5,0)) | Z2: Too Many Players with High ROCE | AA2: =IF(Z2="Monopoly",10,IF(Z2="Oligopoly",5,IF(Z2="Duopoly that cooperate",10,IF(Z2="Duopoly that compete",5,IF(Z2="Too many players with High ROCE",5,0))))) | AB2: No | AC2: =IF(AB2="No",5,0) | AD2: Tailwind | AE2: =IF(AD2="Tailwind",10,0) | AF2: Structural (10 Years Consistency) | AG2: =IF(AF2="Structural (10 Years Consistency)",10,IF(AF2="Shallow Cyclical (2 to 3 years growth)",5,0)) | AH2: No | AI2: =IF(AH2="Yes due to Product Mix change or Operating Leverage",10,IF(AH2="Yes, these are peak margins",-5,IF(AH2="No",5,0))) | AJ2: Stable | AK2: =IF(AJ2="Stable",10,0) | AL2: Yes | AM2: =IF(AL2="Yes",10,0) | AN2: B2C | AO2: =IF(AN2="B2C",10,IF(AN2="B2B",5,0)) | AP2: Yes | AQ2: =IF(AP2="Yes",10,0) | AR2: Higher Annuity, Lower One Time | AS2: =IF(AR2="Fully Annuity",10,IF(AR2="Higher Annuity, Lower One Time",5,IF(AR2="Higher One Time, Lower Annuity",3,0))) | AT2: Good | AU2: =IF(AT2="Good",10,0) | AV2: Yes for more than 2 years | AW2: =IF(AV2="Yes for more than 2 years",10,IF(AV2="Yes only for next 1 to 2 years",5,0)) | AX2: Above 40 | AY2: =IF(AX2="Above 40",20,IF(AX2="20 to 40",10,IF(AX2="0 to 20",-5,0))) | AZ2: Between 50 to 75 | BA2: =IF(AZ2="Between 50 to 75",10,IF(AZ2="Above 75",0,0)) | BB2: Stage 2 | BC2: =IF(BB2="Stage 2",20,IF(BB2="Stage 1",0,IF(BB2="Stage 3",5,IF(BB2="Stage 4",-5,0)))) | BD2: Positive Trend | BE2: =IF(BD2="Positive Trend",20,IF(BD2="Negative Trend",-10,0)) | BF2: Uptrend | BG2: =IF(BF2="Uptrend",10,IF(BF2="Sideways",5,0)) | BH2: Uptrend | BI2: =IF(BH2="Uptrend",10,IF(BH2="Sideways",5,0)) | BJ2: Blue sky scenario | BK2: =IF(BJ2="Overhead supply in last 2 years in last 2 years",-5,IF(BJ2="Close to 52 week high or retracement",5,IF(BJ2="Blue sky scenario",10,IF(BJ2="Long term Downtrend",-10,0)))) | BL2: Yes | BM2: =IF(BL2="Yes",10,0) | BN2: More than 20% | BO2: =IF(BN2="More than 20%",10,IF(BN2="Between 12 to 20%",5,IF(BN2="Less than 12%",0,0))) | BP2: No | BQ2: =IF(BP2="No",10,0) | BR2: No | BS2: =IF(BR2="NO",5,0) | BT2: Above 2 | BU2: =IF(BT2="Above 2",0,IF(BT2="Between 1.5 to 2",5,IF(BT2="Less than 1.5",10,0))) | BV2: Above 70% | BW2: =IF(BV2="Above 70%",10,IF(BV2="Between 50% to 70%",5,IF(BV2="Less than 50%",0,IF(BV2="Negative",-10,IF(BV2="Less than 50% and Borrowings are increasing",-5,0))))) | BX2: Less than 0.7 | BY2: =IF(BX2="More than 1.2",-10,IF(BX2="Between 0.7 to 1.2",0,IF(BX2="Less than 0.7",10,0))) | BZ2: No | CA2: =IF(BZ2="Yes",-10,0) | CB2: Less than 15% | CC2: =IF(CB2="More than 15%",-10,IF(CB2="Less than 15%",10,0)) | CD2: No | CE2: =IF(CD2="Yes, more than 10%",-10,IF(CD2="No",10,0)) | CF2: 25 | CG2: =IF(CF2>20,10,IF(CF2>=10,5,2))
