Workbook

Sheet Read Me
A1: 🏆 MONIT MULTIBAGGER RESEARCH ENGINE & SCANNER
A2: Daily Analytics Report | Generated: Wednesday, 16 September 2026
A5: 📖 QUICK REFERENCE RUNBOOK & SYSTEM FLOW
A6: Step 1: Reference this Read Me | B6: Understand terms, formulas, and underlying investment theses directly in this glossary dashboard.
A7: Step 2: Check Leaderboard Tab | B7: Locate long-term compounders with high Persistence Scores and streaks (institutional accumulation footprint).
A8: Step 3: Analyze Confluence Overlap | B8: Review the ultimate high-conviction candidates intersecting our scanner signals and StockScans overlaps.
A9: Step 4: Scoring Monit Tabs | B9: Open 'Monit Non Financial' or 'Monit Banks NBFC' to fill out your qualitative checks (Tailwinds, Promoters, Triggers).
A10: Step 5: Track Scan Matches | B10: Confirm consensus using 'Scan Match' tabs which score companies by total appearances across allStockScans.
A13: 📊 RESEARCH ENGINE GLOSSARY, METRICS & THESES
A15: Metric Term / Tab Name | B15: Practical Meaning & Underlying Investment Thesis | C15: Automated DB Query / Logic & Excel Formula
A16: EMA Crossover (Birth of a Trend) | B16: An entry signal triggered when price crosses above its 200-day EMA. [THESIS]: Represents the birth of a new long-term uptrend. Buying here provides maximum asymmetrical risk-to-reward because the entry is close to the logical stop-loss (the EMA itself). | C16: pine_signal == 'EMA Crossover' Sized at 7% capital allocation (~₹70,000 per position).
A17: 52W Breakout (Momentum Confirmation) | B17: A momentum signal triggered when a stock above its 200-day EMA breaks out to fresh 52-week highs. [THESIS]: Represents a confirmed breakout where institutional buying pressure clears all historical supply. High momentum outperformance. | C17: pine_signal == '52W Breakout' Sized at 5% capital allocation (~₹50,000 per position).
A18: ATH Momentum (Runaway Leader) | B18: An established trend signal triggered when the price is actively running near its All-Time Highs. [THESIS]: Identifies the strongest runaway leaders in the market. Ideal for high-velocity momentum trading where price experiences immediate continuation. | C18: pine_signal == 'ATH Momentum' Sized at 4% capital allocation (~₹40,000 per position).
A19: Persistence Score (30D) (Accumulation Footprint) | B19: The count of times a stock has appeared in the daily screener during the last 30 active trading days. [THESIS]: Represents persistent institutional buying. Random spikes appear 1-2 times, but compounders appear 10+ times as institutions accumulate. | C19: Queries the local SQLite database (`logs/backtest.db`) to sum the total number of distinct dates the ticker appeared on the screener during the last 30 active trading days. Formula: COUNT(DISTINCT date)
A20: Consecutive Streak Days (Uninterrupted Trend) | B20: The number of consecutive trading days that the stock has appeared in the screener up to today. [THESIS]: High streaks indicate an exceptionally strong, uninterrupted runaway trend with heavy daily buying pressure. | C20: Checks the chronological sequence of scanner dates in SQLite starting from the most recent run date and counting backward. The streak increments for every contiguous date the ticker appears.
A21: Sector Velocity WoW (Early Sector Rotation) | B21: Compares the volume of screener signals in a sector over the last 5 trading days (W1) against the previous 5 trading days (W2). [THESIS]: Detects early sector rotation. A sudden positive surge warns you of capital flowing aggressively into a specific theme. | C21: Counts appearances of all tickers categorized by their sector. Formula: W1_Count = COUNT(records WHERE date IN last 5 trading days) W2_Count = COUNT(records WHERE date IN days -10 to -5) Velocity % = ((W1_Count - W2_Count) / W2_Count) * 100
A22: Emerging Leaders (Momentum Expansion) | B22: Identifies breakout stocks experiencing a sudden momentum expansion. [THESIS]: Finds stocks with a high concentration of appearances recently but almost zero history in the preceding months. Represents new institutional entries. | C22: Finds stocks with at least 5 appearances in the last 10 trading days, but less than or equal to 3 appearances in the prior 50 trading days (i.e. trading days -60 to -10). Formula: COUNT(recent) >= 5 AND COUNT(historical) <= 3
A23: Tab: Confluence Overlap (The Ultimate Overlap) | B23: This sheet displays the absolute highest conviction watchlist candidates intersecting multiple strategies. [THESIS]: Filters out market noise by only displaying stocks appearing in at least two out of three major momentum dimensions: (1) Chartink screener universe, (2) Active scanner signals, and (3) StockScans overlap list. | C23: Calculates the mathematical intersection of the three sets: In_Universe + In_Scanner + In_StockScans >= 2 Single-dimension matches are automatically filtered out to eliminate market noise.
A24: Tab: Monit Non Financial (CHECKLIST SHEET) | B24: Your main watchlist scoring sheet for non-financial companies. [THESIS]: Keeps watchlist scoring fully formula-driven using Excel formulas. It combines automated metrics (RSI, ADX, V-stop, Persistence) with your qualitative scores (Promoter Buying, Near-Term Trigger, Headwind/Tailwind). | C24: Uses relative index-matching formulas to populate automated close prices, RSI, ADX, V-stop, and Persistence from the SQLite and Chartink universe sheets. Formula: INDEX-MATCH left-lookup.
A25: Tab: Monit Banks NBFC (BANKING CHECKLIST) | B25: Your main watchlist scoring sheet for banking and NBFC companies. [THESIS]: Tailored specifically for banking structures, incorporating specialized metrics like Net Interest Margins (NIM) and Credit Costs alongside technical indicators. | C25: Features banking-specific checklist criteria to ensure qualitative analyst inputs align with bank metrics.
A26: Tab: Scan Match tabs (StockScans Confluence) | B26: Displays the top 100 stocks appearing across all StockScans screeners. [THESIS]: Scores stocks qualitatively by scan volume. Stocks appearing in >20 scans receive a premium 10-point bonus, proving market-wide momentum consensus. | C26: Applies a nested Excel IF formula: `=IF(D8>20,10,IF(D8>=10,5,2))` Scores: >20 scans = 10 pts; 10-20 scans = 5 pts; <10 scans = 2 pts.
... A36: Weekly Tracking Highlighting (Additions / Removals) | B36: Visual highlights indicating weekly changes in the StockScans 100 (Scan Match) list. [THESIS]: Helps track the weekly turnover. Newly added candidates indicate fresh institutional attention, while removed candidates represent names losing relative strength. | C36: Compares daily lists against Monday's baseline database: - Added stocks: Highlighted in Soft Blue. - Removed stocks: Listed in the bottom section of Scan Match sheets.

Sheet Leaderboard
A1: 🌟 MULTIBAGGER MOMENTUM & SECTOR ROTATION LEADERBOARD 🌟
A4: TOP PERSISTENT MOMENTUM LEADERS (30D) | J4: SECTOR MOMENTUM VELOCITY HEATMAP (WoW)
A5: Rank | B5: Score | C5: Symbol | D5: Company Name | E5: Sector | F5: Streak (Days) | G5: Market Cap Cr | H5: Classification | J5: Sector Name | K5: Current Wk Count | L5: Previous Wk Count | M5: Velocity WoW %
A6: 1 | B6: 426 | C6: CYIENTDLM | D6: Cyient DLM Ltd | E6: aerospace & defence | F6: 56 | G6: 7007.17 | H6: Potential Leader | J6: telecom-service | K6: 9 | L6: 7 | M6: 28.6%
A7: 2 | B7: 420 | C7: SETL | D7: Standard Enginnering Technology Ltd | E7: industrials | F7: 55 | G7: 8872.39 | H7: Potential Leader | J7: services | K7: 40 | L7: 40 | M7: 0.0%
A8: 3 | B8: 378 | C8: SUNDRMFAST | D8: Sundram Fasteners Limited | E8: auto | F8: 48 | G8: 25999.18 | H8: Potential Leader | J8: power & utilities | K8: 9 | L8: 10 | M8: -10.0%
A9: 4 | B9: 354 | C9: KABRAEXTRU | D9: Kabra Extrusion Technik Limited | E9: industrials | F9: 44 | G9: 2276.21 | H9: Potential Leader | J9: aerospace & defence | K9: 54 | L9: 66 | M9: -18.2%
A10: 5 | B10: 342 | C10: DIVISLAB | D10: Divi's Laboratories Limited | E10: healthcare | F10: 42 | G10: 244178 | H10: Potential Leader | J10: healthcare | K10: 211 | L10: 269 | M10: -21.6%
A11: 6 | B11: 342 | C11: MENONBE | D11: Menon Bearings Limited | E11: auto | F11: 42 | G11: 1705.58 | H11: Potential Leader | J11: realty | K11: 77 | L11: 100 | M11: -23.0%
A12: 7 | B12: 342 | C12: TFCILTD | D12: Tourism Finance Corporation Of India Limited | E12: financials | F12: 42 | G12: 6397.42 | H12: Potential Leader | J12: auto | K12: 78 | L12: 102 | M12: -23.5%
A13: 8 | B13: 342 | C13: VSSL | D13: Vardhman Special Steels Limited | E13: metals & mining | F13: 42 | G13: 3762.04 | H13: Potential Leader | J13: co-working | K13: 6 | L13: 8 | M13: -25.0%
A14: 9 | B14: 330 | C14: WSTCSTPAPR | D14: West Coast Paper Mills Limited | E14: building materials | F14: 40 | G14: 4711.27 | H14: Potential Leader | J14: transportation | K14: 34 | L14: 46 | M14: -26.1%
A15: 10 | B15: 318 | C15: PAYTM | D15: One 97 Communications Ltd | E15: i.t | F15: 38 | G15: 110778.3 | H15: Potential Leader | J15: energy | K15: 56 | L15: 76 | M15: -26.3%
A16: 11 | B16: 312 | C16: DEEPINDS | D16: Deep Industries Ltd | E16: energy | F16: 37 | G16: 4674.56 | H16: Potential Leader | J16: industrials | K16: 193 | L16: 269 | M16: -28.3%
A17: 12 | B17: 312 | C17: REDINGTON | D17: Redington (india) Limited | E17: services | F17: 37 | G17: 29625.34 | H17: Potential Leader | J17: miscellaneous | K17: 31 | L17: 46 | M17: -32.6%
... A20: 15 | B20: 294 | C20: BIRLACABLE | D20: Birla Cable Limited | E20: industrials | F20: 34 | G20: 1133.85 | H20: Potential Leader | J20: metals & mining | K20: 94 | L20: 142 | M20: -33.8%
A21: 16 | B21: 294 | C21: MMP | D21: MMP Industries Ltd | E21: metals & mining | F21: 34 | G21: 866 | H21: Potential Leader
A22: 17 | B22: 288 | C22: DOLPHIN | D22: Dolphin Offshore Enterprises (India) Ltd | E22: energy | F22: 33 | G22: 2604.5 | H22: Potential Leader
A23: 18 | B23: 288 | C23: PTCIL | D23: PTC Industries Ltd | E23: industrials | F23: 33 | G23: 33823.19 | H23: Potential Leader
A24: 19 | B24: 288 | C24: RATNAVEER | D24: Ratnaveer Precision Engineering Ltd | E24: metals & mining | F24: 33 | G24: 2068.52 | H24: Potential Leader
A25: 20 | B25: 288 | C25: SHILPAMED | D25: Shilpa Medicare Limited | E25: healthcare | F25: 33 | G25: 17835.11 | H25: Potential Leader
A28: 🌟 EMERGING LEADERS (MOMENTUM EXPANSION) | J28: 💎 SATELLITE HOLDINGS SHORTLIST (MCAP < 25K CR)
A29: Symbol | B29: Company Name | C29: Sector | D29: Recent Matches (10D) | E29: Historical Matches | F29: Market Cap Cr | J29: Symbol | K29: Sector | L29: Monit Score | M29: Market Cap Cr | N29: Appearances (30D)
A30: GMMPFAUDLR | B30: GMM Pfaudler Ltd | C30: industrials | D30: 10 | E30: 2 | F30: 6060.23 | J30: WELINV | K30: financials | L30: 295 | M30: 831.76 | N30: 21
A31: PRABHA | B31: Prabha Energy Ltd | C31: energy | D31: 10 | E31: 2 | F31: 3509.25 | J31: VISHNU | K31: chemicals | L31: 288 | M31: 4596.29 | N31: 23
A32: SHREEJISPG | B32: Shreeji Shipping Global Ltd | C32: transportation | D32: 10 | E32: 0 | F32: 11143.61 | J32: UNIVPHOTO | K32: consumer discretionary | L32: 288 | M32: 620.4 | N32: 14
A33: MVGJL | B33: Manoj Vaibhav Gems N Jewellers Ltd | C33: consumer discretionary | D33: 10 | E33: 0 | F33: 957.65 | J33: DCBBANK | K33: bank | L33: 285 | M33: 7146.58 | N33: 20
A34: UNITEDPOLY | B34: United Polyfab Gujarat Ltd | C34: textiles | D34: 9 | E34: 0 | F34: 981.18 | J34: WELSPUNLIV | K34: textiles | L34: 283 | M34: 19049.04 | N34: 24
A35: IONEXCHANG | B35: Ion Exchange (India) Ltd | C35: realty | D35: 9 | E35: 1 | F35: 6336 | J35: TBZ | K35: consumer discretionary | L35: 283 | M35: 3499.69 | N35: 23
A36: BLUESTONE | B36: Bluestone Jewellery and Lifestyle Ltd | C36: consumer discretionary | D36: 8 | E36: 1 | F36: 12627.25 | J36: PASUPTAC | K36: textiles | L36: 283 | M36: 628.21 | N36: 13
A37: SMSPHARMA | B37: SMS Pharmaceuticals Limited | C37: Healthcare | D37: 8 | E37: 2 | F37: 3773.71 | J37: TFCILTD | K37: financials | L37: 280 | M37: 6397.42 | N37: 30
A38: PCJEWELLER | B38: Pc Jeweller Limited | C38: consumer discretionary | D38: 8 | E38: 0 | F38: 12516.88 | J38: INNOVACAP | K38: healthcare | L38: 280 | M38: 6524.21 | N38: 25
A39: INDIQUBE | B39: Indiqube Spaces Ltd | C39: co-working | D39: 8 | E39: 0 | F39: 4227.87 | J39: PAISALO | K39: financials | L39: 280 | M39: 7682.73 | N39: 10
A40: WENDT | B40: Wendt (india) Limited | C40: industrials | D40: 8 | E40: 0 | F40: 1716 | J40: SHAREINDIA | K40: financials | L40: 280 | M40: 4315.24 | N40: 7
A41: SPLPETRO | B41: Supreme Petrochem Ltd | C41: energy | D41: 8 | E41: 0 | F41: 14843.04 | J41: ARIES | K41: chemicals | L41: 278 | M41: 615.5 | N41: 24
A45: 🚀 HIGH MOMENTUM LEADERS (RS RATING >= 90)
A46: Rank | B46: RS Rating | C46: O'Neil Score | D46: Monit Score | E46: Symbol | F46: Company Name | G46: Sector | H46: Market Cap Cr
A47: 1 | B47: 99 | C47: 79.17 | D47: 283 | E47: TBZ | F47: Tribhovandas Bhimji Zaveri Limited | G47: consumer discretionary | H47: 3499.69
A48: 2 | B48: 98 | C48: 65.19 | D48: 258 | E48: SIGMAADV | F48: Sigma Advanced System Ltd | G48: aerospace & defence | H48: 15058.31
A49: 3 | B49: 98 | C49: 63.73 | D49: 268 | E49: KABRAEXTRU | F49: Kabra Extrusion Technik Limited | G49: industrials | H49: 2276.21
A50: 4 | B50: 97 | C50: 60.71 | D50: 273 | E50: BODALCHEM | F50: Bodal Chemicals Limited | G50: chemicals | H50: 2224.93
A51: 5 | B51: 96 | C51: 53.71 | D51: 258 | E51: SETL | F51: Standard Enginnering Technology Ltd | G51: industrials | H51: 8872.39
A52: 6 | B52: 95 | C52: 52.68 | D52: 275 | E52: MOREPENLAB | F52: Morepen Laboratories Limited | G52: healthcare | H52: 5820.36
A53: 7 | B53: 95 | C53: 52.41 | D53: 260 | E53: INDSWFTLAB | F53: Ind-swift Laboratories Limited | G53: healthcare | H53: 3293.67
A54: 8 | B54: 94 | C54: 51.23 | D54: 278 | E54: SWANDEF | F54: Swan Defence and Heavy Industries Ltd | G54: transportation | H54: 13963.4
A55: 9 | B55: 93 | C55: 49.69 | D55: 250 | E55: BLISSGVS | F55: Bliss Gvs Pharma Limited | G55: healthcare | H55: 7264.32
A56: 10 | B56: 92 | C56: 47.7 | D56: 278 | E56: BHAGYANGR | F56: Bhagyanagar India | G56: power & utilities | H56: 1356.61
A57: 11 | B57: 92 | C57: 43.92 | D57: 268 | E57: MODISONLTD | F57: Modison Ltd | G57: industrials | H57: 1551.6
A58: 12 | B58: 91 | C58: 41.09 | D58: 270 | E58: BAFNAPH | F58: Bafna Pharmaceuticals Ltd | G58: healthcare | H58: 726.96
... A60: 14 | B60: 90 | C60: 37.14 | D60: 270 | E60: SHILPAMED | F60: Shilpa Medicare Limited | G60: healthcare | H60: 17835.11

Sheet Chartink Universe
A1: symbol | B1: company | C1: sector | D1: industry | E1: marketcap_bucket | F1: marketcap_cr | G1: close | H1: today_return_pct | I1: volume | J1: bse_code
A2: NPST | B2: Network People Services Technologies Ltd | C2: i.t | D2: computers - software - medium / small | E2: smallcap | F2: 3420.57 | G2: 1834.6 | H2: 11.9 | I2: 3028115 | J2: 535391
A3: ANTELOPUS | B3: Antelopus Selan Energy Ltd | C3: energy | D3: oil drilling / allied services | E3: smallcap | F3: 3719.47 | G3: 1170.95 | H3: 10.7 | I3: 4319113 | J3: 530075
A4: FOSECOIND | B4: Foseco India Limited | C4: chemicals | D4: chemicals | E4: smallcap | F4: 4690.81 | G4: 6846.5 | H4: 10.01 | I4: 178685 | J4: 500150
A5: IOLCP | B5: Iol Chemicals And Pharmaceuticals Limited | C5: healthcare | D5: pharmaceuticals - indian - bulk drugs & formln | E5: midcap | F5: 5269.41 | G5: 194.57 | H5: 8.38 | I5: 8624277 | J5: 524164
A6: EMUDHRA | B6: eMudhra Ltd | C6: i.t | D6: computers - software - medium / small | E6: smallcap | F6: 4909.49 | G6: 642.3 | H6: 8.34 | I6: 30254888 | J6: 543533
A7: ARROWGREEN | B7: Arrow Greentech Limited | C7: plastic products | D7: plastics products | E7: smallcap | F7: 1265.2 | G7: 907.45 | H7: 8.22 | I7: 311513 | J7: 516064
A8: KANPRPLA | B8: Kanpur Plastipack Ltd | C8: industrials | D8: packaging | E8: smallcap | F8: 602.18 | G8: 265.85 | H8: 8.07 | I8: 27577 | J8: 507779
A9: MOREPENLAB | B9: Morepen Laboratories Limited | C9: healthcare | D9: pharmaceuticals - indian - bulk drugs & formln | E9: midcap | F9: 5820.36 | G9: 114.73 | H9: 8.01 | I9: 39424210 | J9: 500288
A10: KRYSTAL | B10: Krystal Integrated Services Ltd | C10: miscellaneous | D10: miscellaneous | E10: smallcap | F10: 849.22 | G10: 655.6 | H10: 7.86 | I10: 174712 | J10: 544149
A11: MOTISONS | B11: Motisons Jewellers Ltd | C11: consumer discretionary | D11: diamond cutting / jewellery | E11: smallcap | F11: 1759.72 | G11: 16.62 | H11: 7.43 | I11: 93614476 | J11: 544053
A12: MATRIMONY | B12: Matrimony.com Ltd | C12: miscellaneous | D12: miscellaneous | E12: smallcap | F12: 1029.12 | G12: 533.4 | H12: 7.15 | I12: 40915 | J12: 540704
A13: RUBYMILLS | B13: The Ruby Mills Limited | C13: textiles | D13: textiles - composite | E13: smallcap | F13: 1445.95 | G13: 462.1 | H13: 6.87 | I13: 90742 | J13: 503169
... A35: INDORAMA | B35: Indo Rama Synthetics (india) Limited | C35: textiles | D35: textiles - manmade | E35: smallcap | F35: 2162.28 | G35: 85.6 | H35: 3.37 | I35: 3645127 | J35: 500207
A36: BLUESTONE | B36: Bluestone Jewellery and Lifestyle Ltd | C36: consumer discretionary | D36: diamond cutting / jewellery | E36: midcap | F36: 12627.25 | G36: 856 | H36: 3.31 | I36: 806703
A37: SSWL | B37: Steel Strips Wheels Limited | C37: auto | D37: auto ancillaries | E37: midcap | F37: 5328.42 | G37: 350.05 | H37: 3.26 | I37: 1772756 | J37: 513262
A38: GRAPHITE | B38: Graphite India Limited | C38: industrials | D38: electrodes - graphites | E38: midcap | F38: 15268.6 | G38: 805.05 | H38: 3.01 | I38: 3021853 | J38: 509488
A39: TATACOMM | B39: Tata Communications Limited | C39: telecom-service | D39: telecommunications - service provider | E39: largecap | F39: 49826.63 | G39: 1799.3 | H39: 2.92 | I39: 317034 | J39: 500483
A40: DICIND | B40: Dic India Limited | C40: chemicals | D40: chemicals | E40: smallcap | F40: 544.45 | G40: 610.3 | H40: 2.89 | I40: 3625 | J40: 500089
A41: STAR | B41: Strides Shasun Limited | C41: healthcare | D41: pharmaceuticals - indian - bulk drugs & formln | E41: midcap | F41: 10605.39 | G41: 1183.9 | H41: 2.89 | I41: 398309 | J41: 532531
A42: SIGMAADV | B42: Sigma Advanced System Ltd | C42: aerospace & defence | D42: electronics - components | E42: midcap | F42: 15058.31 | G42: 817.05 | H42: 2.82 | I42: 250590 | J42: 532408
A43: PVRINOX | B43: PVR Inox Ltd | C43: media | D43: entertainment / electronic media software | E43: midcap | F43: 11990.22 | G43: 1254.6 | H43: 2.75 | I43: 456245 | J43: 532689
A44: TEGA | B44: Tega Industries Ltd | C44: industrials | D44: engineering | E44: midcap | F44: 12554.59 | G44: 1717.1 | H44: 2.75 | I44: 225032 | J44: 543413
A45: MANALIPETC | B45: Manali Petrochemicals Limited | C45: energy | D45: petrochemicals | E45: smallcap | F45: 1379.26 | G45: 82.37 | H45: 2.72 | I45: 2637453 | J45: 500268
A46: HINDOILEXP | B46: Hindustan Oil Exploration Company Limited | C46: energy | D46: oil drilling / allied services | E46: smallcap | F46: 2323.78 | G46: 180.44 | H46: 2.69 | I46: 971364 | J46: 500186
A47: SANSERA | B47: Sansera Engineering Ltd | C47: auto | D47: auto ancillaries | E47: largecap | F47: 24160.79 | G47: 3971.2 | H47: 2.57 | I47: 229404 | J47: 543358
A48: ABDL | B48: Allied Blenders & Distillers Ltd | C48: fmcg | D48: breweries & distilleries | E48: midcap | F48: 17666.49 | G48: 647.55 | H48: 2.53 | I48: 1453879 | J48: 544203
... A79: SWANDEF | B79: Swan Defence and Heavy Industries Ltd | C79: transportation | D79: miscellaneous | E79: midcap | F79: 13963.4 | G79: 2687.2 | H79: 1.38 | I79: 17649 | J79: 533107
A80: FIVESTAR | B80: Five-Star Business Finance Ltd | C80: financials | D80: finance & investments | E80: midcap | F80: 15997.27 | G80: 549.4 | H80: 1.37 | I80: 549733
A81: LOTUSDEV | B81: Sri Lotus Developers & Realty Ltd | C81: realty | D81: construction | E81: midcap | F81: 10436.21 | G81: 216.4 | H81: 1.34 | I81: 1914804 | J81: 544469
A82: KIRLFER | B82: Kirloskar Ferrous Industries Ltd | C82: metals & mining | D82: steel - large | E82: midcap | F82: 7669.67 | G82: 470.9 | H82: 1.3 | I82: 140176 | J82: 500245
A83: BIRLACABLE | B83: Birla Cable Limited | C83: industrials | D83: cables - telephone | E83: smallcap | F83: 1133.85 | G83: 382.55 | H83: 1.22 | I83: 734776 | J83: 500060
A84: CEIGALL | B84: Ceigall India Ltd | C84: realty | D84: construction | E84: midcap | F84: 6658.98 | G84: 386.8 | H84: 1.19 | I84: 393782 | J84: 544223
A85: BLACKBUCK | B85: BlackBuck Ltd | C85: transportation | D85: miscellaneous | E85: midcap | F85: 11145.06 | G85: 619.05 | H85: 1.17 | I85: 892263 | J85: 544288
A86: SURAKSHA | B86: Suraksha Diagnostic Ltd | C86: healthcare | D86: healthcare | E86: smallcap | F86: 1682.47 | G86: 326.8 | H86: 1.16 | I86: 98905 | J86: 544293
A87: SHREEPUSHK | B87: Shree Pushkar Chemicals & Fertilisers Limited | C87: chemicals | D87: dyes and pigments | E87: smallcap | F87: 1621.57 | G87: 506.95 | H87: 1.1 | I87: 123748 | J87: 539334
A88: UNITEDPOLY | B88: United Polyfab Gujarat Ltd | C88: textiles | D88: textiles - products | E88: smallcap | F88: 981.18 | G88: 43.19 | H88: 1.03 | I88: 143829 | J88: 533024
A89: ANANDRATHI | B89: Anand Rathi Wealth Ltd | C89: financials | D89: finance & investments | E89: largecap | F89: 36261.75 | G89: 2206.2 | H89: 1.02 | I89: 279080 | J89: 543415
A90: WENDT | B90: Wendt (india) Limited | C90: industrials | D90: abrasives and grinding wheels | E90: smallcap | F90: 1716 | G90: 8663.5 | H90: 0.97 | I90: 16389 | J90: 505412
A91: IPCALAB | B91: Ipca Laboratories Limited | C91: healthcare | D91: pharmaceuticals - indian - bulk drugs & formln | E91: largecap | F91: 49025.8 | G91: 1950.7 | H91: 0.95 | I91: 337123 | J91: 524494
A92: SHREEJISPG | B92: Shreeji Shipping Global Ltd | C92: transportation | D92: shipping | E92: midcap | F92: 11143.61 | G92: 690.2 | H92: 0.91 | I92: 809303 | J92: 544490
... A186: SMLMAH | B186: SML Mahindra Ltd | C186: auto | D186: automobiles - lcvs / hcvs | E186: midcap | F186: 9050.57 | G186: 5971.5 | H186: -4.52 | I186: 83297 | J186: 505192
A187: VALIANTLAB | B187: Valiant Laboratories Ltd | C187: healthcare | D187: pharmaceuticals - indian - bulk drugs & formln | E187: smallcap | F187: 666.03 | G187: 116.91 | H187: -4.66 | I187: 111457
A188: HATSUN | B188: Hatsun Agro Product Limited | C188: fmcg | D188: food - processing - indian | E188: largecap | F188: 28400.4 | G188: 1214 | H188: -4.78 | I188: 88440 | J188: 531531
A189: MODISONLTD | B189: Modison Ltd | C189: industrials | D189: electric equipment | E189: smallcap | F189: 1551.6 | G189: 455.05 | H189: -4.83 | I189: 80064 | J189: 506261
A190: GAYAPROJ | B190: Gayatri Projects Limited | C190: realty | D190: construction | E190: smallcap | F190: 1214.14 | G190: 24.85 | H190: -4.97 | I190: 1543449 | J190: 532767
A191: SETL | B191: Standard Enginnering Technology Ltd | C191: industrials | D191: engineering | E191: midcap | F191: 8872.39 | G191: 422.55 | H191: -4.99 | I191: 64549 | J191: 544333
A192: PVP | B192: Pvp Ventures Limited | C192: realty | D192: construction | E192: smallcap | F192: 1603.57 | G192: 58.51 | H192: -4.99 | I192: 342199 | J192: 517556
A193: MANAKSTEEL | B193: Manaksia Steels Limited | C193: metals & mining | D193: steel - medium / small | E193: smallcap | F193: 734.11 | G193: 106.42 | H193: -5 | I193: 75116 | J193: 539044
A194: INDIAGLYCO | B194: India Glycols Limited | C194: fmcg | D194: breweries & distilleries | E194: smallcap | F194: 1878.09 | G194: 266.2 | H194: -5 | I194: 39549 | J194: 500201
A195: PRABHA | B195: Prabha Energy Ltd | C195: energy | D195: oil drilling / allied services | E195: smallcap | F195: 3509.25 | G195: 226.58 | H195: -5.36 | I195: 175244 | J195: 544379
A196: MUKKA | B196: Mukka Proteins Ltd | C196: fmcg | D196: food - processing - indian | E196: smallcap | F196: 941.7 | G196: 29.53 | H196: -5.93 | I196: 1355601 | J196: 544135

Sheet Confluence Overlap
A1: Confluence Rank | B1: Total Score | C1: Relative Strength Rating | D1: Symbol | E1: Company Name | F1: Industry | G1: Common Count | H1: Scanner Signal | I1: Chartink Universe | J1: Scan Matches Count | K1: Backtest Recurrence (30D)
A2: =IF(B2=0,"",ROW()-1) | B2: =IFERROR(INDEX('Monit Non Financial'!$B$2:$B$400, MATCH(D2, 'Monit Non Financial'!$C$2:$C$400, 0)), IFERROR(INDEX('Monit Banks NBFC'!$B$2:$B$100, MATCH(D2, 'Monit Banks NBFC'!$C$2:$C$100, 0)), 0)) | C2: =IFERROR(INDEX('Monit Non Financial'!$L$2:$L$400, MATCH(D2, 'Monit Non Financial'!$C$2:$C$400, 0)), IFERROR(INDEX('Monit Banks NBFC'!$L$2:$L$100, MATCH(D2, 'Monit Banks NBFC'!$C$2:$C$100, 0)), "")) | D2: REDINGTON | E2: Redington (india) Limited | F2: unknown | G2: 2 | H2: ATH Momentum | I2: Yes | J2: 0 | K2: 30
A3: =IF(B3=0,"",ROW()-1) | B3: =IFERROR(INDEX('Monit Non Financial'!$B$2:$B$400, MATCH(D3, 'Monit Non Financial'!$C$2:$C$400, 0)), IFERROR(INDEX('Monit Banks NBFC'!$B$2:$B$100, MATCH(D3, 'Monit Banks NBFC'!$C$2:$C$100, 0)), 0)) | C3: =IFERROR(INDEX('Monit Non Financial'!$L$2:$L$400, MATCH(D3, 'Monit Non Financial'!$C$2:$C$400, 0)), IFERROR(INDEX('Monit Banks NBFC'!$L$2:$L$100, MATCH(D3, 'Monit Banks NBFC'!$C$2:$C$100, 0)), "")) | D3: TBZ | E3: Tribhovandas Bhimji Zaveri Limited | F3: unknown | G3: 2 | H3: ATH Momentum | I3: Yes | J3: 0 | K3: 23
A4: =IF(B4=0,"",ROW()-1) | B4: =IFERROR(INDEX('Monit Non Financial'!$B$2:$B$400, MATCH(D4, 'Monit Non Financial'!$C$2:$C$400, 0)), IFERROR(INDEX('Monit Banks NBFC'!$B$2:$B$100, MATCH(D4, 'Monit Banks NBFC'!$C$2:$C$100, 0)), 0)) | C4: =IFERROR(INDEX('Monit Non Financial'!$L$2:$L$400, MATCH(D4, 'Monit Non Financial'!$C$2:$C$400, 0)), IFERROR(INDEX('Monit Banks NBFC'!$L$2:$L$100, MATCH(D4, 'Monit Banks NBFC'!$C$2:$C$100, 0)), "")) | D4: PAISALO | E4: Paisalo Digital Ltd | F4: unknown | G4: 2 | H4: 52W Breakout | I4: Yes | J4: 0 | K4: 10
A5: =IF(B5=0,"",ROW()-1) | B5: =IFERROR(INDEX('Monit Non Financial'!$B$2:$B$400, MATCH(D5, 'Monit Non Financial'!$C$2:$C$400, 0)), IFERROR(INDEX('Monit Banks NBFC'!$B$2:$B$100, MATCH(D5, 'Monit Banks NBFC'!$C$2:$C$100, 0)), 0)) | C5: =IFERROR(INDEX('Monit Non Financial'!$L$2:$L$400, MATCH(D5, 'Monit Non Financial'!$C$2:$C$400, 0)), IFERROR(INDEX('Monit Banks NBFC'!$L$2:$L$100, MATCH(D5, 'Monit Banks NBFC'!$C$2:$C$100, 0)), "")) | D5: NRL | E5: Nupur Recyclers Ltd | F5: unknown | G5: 2 | H5: ATH Momentum | I5: Yes | J5: 0 | K5: 23
A6: =IF(B6=0,"",ROW()-1) | B6: =IFERROR(INDEX('Monit Non Financial'!$B$2:$B$400, MATCH(D6, 'Monit Non Financial'!$C$2:$C$400, 0)), IFERROR(INDEX('Monit Banks NBFC'!$B$2:$B$100, MATCH(D6, 'Monit Banks NBFC'!$C$2:$C$100, 0)), 0)) | C6: =IFERROR(INDEX('Monit Non Financial'!$L$2:$L$400, MATCH(D6, 'Monit Non Financial'!$C$2:$C$400, 0)), IFERROR(INDEX('Monit Banks NBFC'!$L$2:$L$100, MATCH(D6, 'Monit Banks NBFC'!$C$2:$C$100, 0)), "")) | D6: SWANDEF | E6: Swan Defence and Heavy Industries Ltd | F6: unknown | G6: 2 | H6: ATH Momentum | I6: Yes | J6: 0 | K6: 15
A7: =IF(B7=0,"",ROW()-1) | B7: =IFERROR(INDEX('Monit Non Financial'!$B$2:$B$400, MATCH(D7, 'Monit Non Financial'!$C$2:$C$400, 0)), IFERROR(INDEX('Monit Banks NBFC'!$B$2:$B$100, MATCH(D7, 'Monit Banks NBFC'!$C$2:$C$100, 0)), 0)) | C7: =IFERROR(INDEX('Monit Non Financial'!$L$2:$L$400, MATCH(D7, 'Monit Non Financial'!$C$2:$C$400, 0)), IFERROR(INDEX('Monit Banks NBFC'!$L$2:$L$100, MATCH(D7, 'Monit Banks NBFC'!$C$2:$C$100, 0)), "")) | D7: BHAGYANGR | E7: Bhagyanagar India | F7: unknown | G7: 2 | H7: ATH Momentum | I7: Yes | J7: 0 | K7: 7
A8: =IF(B8=0,"",ROW()-1) | B8: =IFERROR(INDEX('Monit Non Financial'!$B$2:$B$400, MATCH(D8, 'Monit Non Financial'!$C$2:$C$400, 0)), IFERROR(INDEX('Monit Banks NBFC'!$B$2:$B$100, MATCH(D8, 'Monit Banks NBFC'!$C$2:$C$100, 0)), 0)) | C8: =IFERROR(INDEX('Monit Non Financial'!$L$2:$L$400, MATCH(D8, 'Monit Non Financial'!$C$2:$C$400, 0)), IFERROR(INDEX('Monit Banks NBFC'!$L$2:$L$100, MATCH(D8, 'Monit Banks NBFC'!$C$2:$C$100, 0)), "")) | D8: BIRLACABLE | E8: Birla Cable Limited | F8: unknown | G8: 2 | H8: ATH Momentum | I8: Yes | J8: 0 | K8: 30
A9: =IF(B9=0,"",ROW()-1) | B9: =IFERROR(INDEX('Monit Non Financial'!$B$2:$B$400, MATCH(D9, 'Monit Non Financial'!$C$2:$C$400, 0)), IFERROR(INDEX('Monit Banks NBFC'!$B$2:$B$100, MATCH(D9, 'Monit Banks NBFC'!$C$2:$C$100, 0)), 0)) | C9: =IFERROR(INDEX('Monit Non Financial'!$L$2:$L$400, MATCH(D9, 'Monit Non Financial'!$C$2:$C$400, 0)), IFERROR(INDEX('Monit Banks NBFC'!$L$2:$L$100, MATCH(D9, 'Monit Banks NBFC'!$C$2:$C$100, 0)), "")) | D9: FILATEX | E9: Filatex India Limited | F9: unknown | G9: 2 | H9: 52W Breakout | I9: Yes | J9: 0 | K9: 18
A10: =IF(B10=0,"",ROW()-1) | B10: =IFERROR(INDEX('Monit Non Financial'!$B$2:$B$400, MATCH(D10, 'Monit Non Financial'!$C$2:$C$400, 0)), IFERROR(INDEX('Monit Banks NBFC'!$B$2:$B$100, MATCH(D10, 'Monit Banks NBFC'!$C$2:$C$100, 0)), 0)) | C10: =IFERROR(INDEX('Monit Non Financial'!$L$2:$L$400, MATCH(D10, 'Monit Non Financial'!$C$2:$C$400, 0)), IFERROR(INDEX('Monit Banks NBFC'!$L$2:$L$100, MATCH(D10, 'Monit Banks NBFC'!$C$2:$C$100, 0)), "")) | D10: KANORICHEM | E10: Kanoria Chemicals & Industries Limited | F10: unknown | G10: 2 | H10: 52W Breakout | I10: Yes | J10: 0 | K10: 28
A11: =IF(B11=0,"",ROW()-1) | B11: =IFERROR(INDEX('Monit Non Financial'!$B$2:$B$400, MATCH(D11, 'Monit Non Financial'!$C$2:$C$400, 0)), IFERROR(INDEX('Monit Banks NBFC'!$B$2:$B$100, MATCH(D11, 'Monit Banks NBFC'!$C$2:$C$100, 0)), 0)) | C11: =IFERROR(INDEX('Monit Non Financial'!$L$2:$L$400, MATCH(D11, 'Monit Non Financial'!$C$2:$C$400, 0)), IFERROR(INDEX('Monit Banks NBFC'!$L$2:$L$100, MATCH(D11, 'Monit Banks NBFC'!$C$2:$C$100, 0)), "")) | D11: LOTUSDEV | E11: Sri Lotus Developers & Realty Ltd | F11: unknown | G11: 2 | H11: 52W Breakout | I11: Yes | J11: 0 | K11: 15
A12: =IF(B12=0,"",ROW()-1) | B12: =IFERROR(INDEX('Monit Non Financial'!$B$2:$B$400, MATCH(D12, 'Monit Non Financial'!$C$2:$C$400, 0)), IFERROR(INDEX('Monit Banks NBFC'!$B$2:$B$100, MATCH(D12, 'Monit Banks NBFC'!$C$2:$C$100, 0)), 0)) | C12: =IFERROR(INDEX('Monit Non Financial'!$L$2:$L$400, MATCH(D12, 'Monit Non Financial'!$C$2:$C$400, 0)), IFERROR(INDEX('Monit Banks NBFC'!$L$2:$L$100, MATCH(D12, 'Monit Banks NBFC'!$C$2:$C$100, 0)), "")) | D12: ZIMLAB | E12: Zim Laboratories Ltd | F12: unknown | G12: 2 | H12: ATH Momentum | I12: Yes | J12: 0 | K12: 20
A13: =IF(B13=0,"",ROW()-1) | B13: =IFERROR(INDEX('Monit Non Financial'!$B$2:$B$400, MATCH(D13, 'Monit Non Financial'!$C$2:$C$400, 0)), IFERROR(INDEX('Monit Banks NBFC'!$B$2:$B$100, MATCH(D13, 'Monit Banks NBFC'!$C$2:$C$100, 0)), 0)) | C13: =IFERROR(INDEX('Monit Non Financial'!$L$2:$L$400, MATCH(D13, 'Monit Non Financial'!$C$2:$C$400, 0)), IFERROR(INDEX('Monit Banks NBFC'!$L$2:$L$100, MATCH(D13, 'Monit Banks NBFC'!$C$2:$C$100, 0)), "")) | D13: SHREEPUSHK | E13: Shree Pushkar Chemicals & Fertilisers Limited | F13: unknown | G13: 2 | H13: ATH Momentum | I13: Yes | J13: 0 | K13: 19
... A23: =IF(B23=0,"",ROW()-1) | B23: =IFERROR(INDEX('Monit Non Financial'!$B$2:$B$400, MATCH(D23, 'Monit Non Financial'!$C$2:$C$400, 0)), IFERROR(INDEX('Monit Banks NBFC'!$B$2:$B$100, MATCH(D23, 'Monit Banks NBFC'!$C$2:$C$100, 0)), 0)) | C23: =IFERROR(INDEX('Monit Non Financial'!$L$2:$L$400, MATCH(D23, 'Monit Non Financial'!$C$2:$C$400, 0)), IFERROR(INDEX('Monit Banks NBFC'!$L$2:$L$100, MATCH(D23, 'Monit Banks NBFC'!$C$2:$C$100, 0)), "")) | D23: ROSSTECH | E23: Rossell Techsys Ltd | F23: unknown | G23: 2 | H23: 52W Breakout | I23: Yes | J23: 0 | K23: 28

Sheet Monit Non Financial
A1: Rank (Non Financial) | B1: Total Score | C1: Symbol | D1: Company | E1: Sector | F1: Industry | G1: Market Cap Bucket | H1: Market Cap Cr | I1: Close | J1: Today Return % | K1: Volume | L1: Relative Strength Rating | M1: Relative Strength Status | N1: Relative Strength Score | O1: Calculated RSI (14) | P1: Calculated ADX (14) | Q1: Calculated V-stop Line | R1: Calculated Near-term Trigger | S1: Sector Benchmark | T1: Benchmark 1Y Return % | U1: Stock 1Y Return % | V1: Relative Strength 1Y (%) | W1: O'Neil Weighted Score | X1: Industry Growth | Y1: Industry Growth Score | Z1: Competitiveness | AA1: Competitiveness Score | AB1: Regulation | AC1: Regulation Score | AD1: Sector Headwinds/Tailwind | AE1: Sector Headwinds/Tailwind Score | AF1: Industry Type | AG1: Industry Type Score | AH1: Margins | AI1: Margins Score | AJ1: Margins Stability | AK1: Margins Stability Score | AL1: Growth | AM1: Growth Score | AN1: Business Type | AO1: Business Type Score | AP1: Near term triggers | AQ1: Near term triggers Score | AR1: Type of Revenue | AS1: Type of Revenue Score | AT1: Capital Allocation | AU1: Capital Allocation Score | AV1: Medium term Growth | AW1: Medium term Growth Score | AX1: ADX | AY1: ADX Score | AZ1: RSI | BA1: RSI Score | BB1: Stage Analysis | BC1: Stage Analysis Score | BD1: Price Volume Action | BE1: Price Volume Action Score | BF1: Secondary Trend | BG1: Secondary Trend Score | BH1: Primary Trend | BI1: Primary Trend Score | BJ1: Resistance | BK1: Resistance Score | BL1: V-stop | BM1: V-stop Score | BN1: PAT Growth | BO1: PAT Growth Score | BP1: Stock History | BQ1: Stock History Score | BR1: PE Ratio | BS1: PE Ratio Score | BT1: PEG Ratio | BU1: PEG Ratio Score | BV1: CFO to EBITDA | BW1: CFO to EBITDA Score | BX1: Debt to Equity | BY1: Debt to Equity Score | BZ1: Auditor Resignation | CA1: Auditor Resignation Score | CB1: Contingent Liability | CC1: Contingent Liability Score | CD1: Pledging | CE1: Pledging Score
A2: =IF(B2=0,"",RANK(B2,$B$2:$B$184,0)) | B2: =SUM(N2,Y2,AA2,AC2,AE2,AG2,AI2,AK2,AM2,AO2,AQ2,AS2,AU2,AW2,AY2,BA2,BC2,BE2,BG2,BI2,BK2,BM2,BO2,BQ2,BS2,BU2,BW2,BY2,CA2,CC2,CE2) | C2: UNIVPHOTO | D2: Universus Photo Imagings Ltd | E2: consumer discretionary | F2: photographic and allied products | G2: smallcap | H2: 620.4 | I2: 595.05 | J2: 4.99 | K2: 19469 | L2: 90 | M2: Outperforming | N2: =IF(M2="Underperforming",-5,IF(L2>=95,15,IF(L2>=90,10,IF(L2>=80,5,0)))) | O2: 73.34 | P2: 21.63 | Q2: 445.68 | R2: Volume Spike & Near 52W High Breakout | S2: Nifty 50 | T2: -8.33 | U2: 130.06 | V2: 150.96 | W2: 40.72 | X2: Growing Industry | Y2: =IF(X2="Growing Industry",10,IF(X2="Cyclical in an Upturn",5,0)) | Z2: Too Many Players with High ROCE | AA2: =IF(Z2="Monopoly",10,IF(Z2="Oligopoly",5,IF(Z2="Duopoly that cooperate",10,IF(Z2="Duopoly that compete",5,IF(Z2="Too many players with High ROCE",5,0))))) | AB2: No | AC2: =IF(AB2="No",5,0) | AD2: Tailwind | AE2: =IF(AD2="Tailwind",10,0) | AF2: Structural (10 Years Consistency) | AG2: =IF(AF2="Structural (10 Years Consistency)",10,IF(AF2="Shallow Cyclical (2 to 3 years growth)",5,0)) | AH2: No | AI2: =IF(AH2="Yes due to Product Mix change or Operating Leverage",10,IF(AH2="Yes, these are peak margins",-5,IF(AH2="No",5,0))) | AJ2: Stable | AK2: =IF(AJ2="Stable",10,0) | AL2: Yes | AM2: =IF(AL2="Yes",10,0) | AN2: B2B | AO2: =IF(AN2="B2C",10,IF(AN2="B2B",5,0)) | AP2: Yes | AQ2: =IF(AP2="Yes",10,0) | AR2: Higher One Time, Lower Annuity | AS2: =IF(AR2="Fully Annuity",10,IF(AR2="Higher Annuity, Lower One Time",5,IF(AR2="Higher One Time, Lower Annuity",3,0))) | AT2: Good | AU2: =IF(AT2="Good",10,0) | AV2: Yes for more than 2 years | AW2: =IF(AV2="Yes for more than 2 years",10,IF(AV2="Yes only for next 1 to 2 years",5,0)) | AX2: 20 to 40 | AY2: =IF(AX2="Above 40",20,IF(AX2="20 to 40",10,IF(AX2="0 to 20",-5,0))) | AZ2: Between 50 to 75 | BA2: =IF(AZ2="Between 50 to 75",10,IF(AZ2="Above 75",0,0)) | BB2: Stage 2 | BC2: =IF(BB2="Stage 2",20,IF(BB2="Stage 1",0,IF(BB2="Stage 3",5,IF(BB2="Stage 4",-5,0)))) | BD2: Positive Trend | BE2: =IF(BD2="Positive Trend",20,IF(BD2="Negative Trend",-10,0)) | BF2: Uptrend | BG2: =IF(BF2="Uptrend",10,IF(BF2="Sideways",5,0)) | BH2: Uptrend | BI2: =IF(BH2="Uptrend",10,IF(BH2="Sideways",5,0)) | BJ2: Blue sky scenario | BK2: =IF(BJ2="Overhead supply in last 2 years in last 2 years",-5,IF(BJ2="Close to 52 week high or retracement",5,IF(BJ2="Blue sky scenario",10,IF(BJ2="Long term Downtrend",-10,0)))) | BL2: Yes | BM2: =IF(BL2="Yes",10,0) | BN2: More than 20% | BO2: =IF(BN2="More than 20%",10,IF(BN2="Between 12 to 20%",5,IF(BN2="Less than 12%",0,0))) | BP2: No | BQ2: =IF(BP2="No",10,0) | BR2: No | BS2: =IF(BR2="NO",5,0) | BT2: Less than 1.5 | BU2: =IF(BT2="Above 2",0,IF(BT2="Between 1.5 to 2",5,IF(BT2="Less than 1.5",10,0))) | BV2: Above 70% | BW2: =IF(BV2="Above 70%",10,IF(BV2="Between 50% to 70%",5,IF(BV2="Less than 50%",0,IF(BV2="Negative",-10,IF(BV2="Less than 50% and Borrowings are increasing",-5,0))))) | BX2: Less than 0.7 | BY2: =IF(BX2="More than 1.2",-10,IF(BX2="Between 0.7 to 1.2",0,IF(BX2="Less than 0.7",10,0))) | BZ2: No | CA2: =IF(BZ2="Yes",-10,0) | CB2: Less than 15% | CC2: =IF(CB2="More than 15%",-10,IF(CB2="Less than 15%",10,0)) | CD2: No | CE2: =IF(CD2="Yes, more than 10%",-10,IF(CD2="No",10,0))
A3: =IF(B3=0,"",RANK(B3,$B$2:$B$184,0)) | B3: =SUM(N3,Y3,AA3,AC3,AE3,AG3,AI3,AK3,AM3,AO3,AQ3,AS3,AU3,AW3,AY3,BA3,BC3,BE3,BG3,BI3,BK3,BM3,BO3,BQ3,BS3,BU3,BW3,BY3,CA3,CC3,CE3) | C3: REDINGTON | D3: Redington (india) Limited | E3: services | F3: trading | G3: largecap | H3: 29625.34 | I3: 388.15 | J3: 2.43 | K3: 5640367 | L3: 55 | M3: Outperforming | N3: =IF(M3="Underperforming",-5,IF(L3>=95,15,IF(L3>=90,10,IF(L3>=80,5,0)))) | O3: 72.37 | P3: 47.51 | Q3: 307.49 | R3: Near 52W High Breakout | S3: Nifty 50 | T3: -8.33 | U3: 32.34 | V3: 44.37 | W3: 16.48 | X3: Growing Industry | Y3: =IF(X3="Growing Industry",10,IF(X3="Cyclical in an Upturn",5,0)) | Z3: Too Many Players with High ROCE | AA3: =IF(Z3="Monopoly",10,IF(Z3="Oligopoly",5,IF(Z3="Duopoly that cooperate",10,IF(Z3="Duopoly that compete",5,IF(Z3="Too many players with High ROCE",5,0))))) | AB3: No | AC3: =IF(AB3="No",5,0) | AD3: Tailwind | AE3: =IF(AD3="Tailwind",10,0) | AF3: Structural (10 Years Consistency) | AG3: =IF(AF3="Structural (10 Years Consistency)",10,IF(AF3="Shallow Cyclical (2 to 3 years growth)",5,0)) | AH3: No | AI3: =IF(AH3="Yes due to Product Mix change or Operating Leverage",10,IF(AH3="Yes, these are peak margins",-5,IF(AH3="No",5,0))) | AJ3: Stable | AK3: =IF(AJ3="Stable",10,0) | AL3: Yes | AM3: =IF(AL3="Yes",10,0) | AN3: B2B | AO3: =IF(AN3="B2C",10,IF(AN3="B2B",5,0)) | AP3: Yes | AQ3: =IF(AP3="Yes",10,0) | AR3: Higher One Time, Lower Annuity | AS3: =IF(AR3="Fully Annuity",10,IF(AR3="Higher Annuity, Lower One Time",5,IF(AR3="Higher One Time, Lower Annuity",3,0))) | AT3: Good | AU3: =IF(AT3="Good",10,0) | AV3: Yes for more than 2 years | AW3: =IF(AV3="Yes for more than 2 years",10,IF(AV3="Yes only for next 1 to 2 years",5,0)) | AX3: Above 40 | AY3: =IF(AX3="Above 40",20,IF(AX3="20 to 40",10,IF(AX3="0 to 20",-5,0))) | AZ3: Between 50 to 75 | BA3: =IF(AZ3="Between 50 to 75",10,IF(AZ3="Above 75",0,0)) | BB3: Stage 2 | BC3: =IF(BB3="Stage 2",20,IF(BB3="Stage 1",0,IF(BB3="Stage 3",5,IF(BB3="Stage 4",-5,0)))) | BD3: Positive Trend | BE3: =IF(BD3="Positive Trend",20,IF(BD3="Negative Trend",-10,0)) | BF3: Uptrend | BG3: =IF(BF3="Uptrend",10,IF(BF3="Sideways",5,0)) | BH3: Uptrend | BI3: =IF(BH3="Uptrend",10,IF(BH3="Sideways",5,0)) | BJ3: Blue sky scenario | BK3: =IF(BJ3="Overhead supply in last 2 years in last 2 years",-5,IF(BJ3="Close to 52 week high or retracement",5,IF(BJ3="Blue sky scenario",10,IF(BJ3="Long term Downtrend",-10,0)))) | BL3: Yes | BM3: =IF(BL3="Yes",10,0) | BN3: More than 20% | BO3: =IF(BN3="More than 20%",10,IF(BN3="Between 12 to 20%",5,IF(BN3="Less than 12%",0,0))) | BP3: No | BQ3: =IF(BP3="No",10,0) | BR3: No | BS3: =IF(BR3="NO",5,0) | BT3: Less than 1.5 | BU3: =IF(BT3="Above 2",0,IF(BT3="Between 1.5 to 2",5,IF(BT3="Less than 1.5",10,0))) | BV3: Above 70% | BW3: =IF(BV3="Above 70%",10,IF(BV3="Between 50% to 70%",5,IF(BV3="Less than 50%",0,IF(BV3="Negative",-10,IF(BV3="Less than 50% and Borrowings are increasing",-5,0))))) | BX3: Less than 0.7 | BY3: =IF(BX3="More than 1.2",-10,IF(BX3="Between 0.7 to 1.2",0,IF(BX3="Less than 0.7",10,0))) | BZ3: No | CA3: =IF(BZ3="Yes",-10,0) | CB3: Less than 15% | CC3: =IF(CB3="More than 15%",-10,IF(CB3="Less than 15%",10,0)) | CD3: No | CE3: =IF(CD3="Yes, more than 10%",-10,IF(CD3="No",10,0))
A4: =IF(B4=0,"",RANK(B4,$B$2:$B$184,0)) | B4: =SUM(N4,Y4,AA4,AC4,AE4,AG4,AI4,AK4,AM4,AO4,AQ4,AS4,AU4,AW4,AY4,BA4,BC4,BE4,BG4,BI4,BK4,BM4,BO4,BQ4,BS4,BU4,BW4,BY4,CA4,CC4,CE4) | C4: VISHNU | D4: Vishnu Chemicals Limited | E4: chemicals | F4: chemicals | G4: smallcap | H4: 4596.29 | I4: 693.9 | J4: 1.63 | K4: 112259 | L4: 35 | M4: Outperforming | N4: =IF(M4="Underperforming",-5,IF(L4>=95,15,IF(L4>=90,10,IF(L4>=80,5,0)))) | O4: 66.28 | P4: 44.89 | Q4: 576.22 | R4: Near 52W High Breakout | S4: Nifty 50 | T4: -8.33 | U4: 39.47 | V4: 52.15 | W4: 10.26 | X4: Growing Industry | Y4: =IF(X4="Growing Industry",10,IF(X4="Cyclical in an Upturn",5,0)) | Z4: Too Many Players with High ROCE | AA4: =IF(Z4="Monopoly",10,IF(Z4="Oligopoly",5,IF(Z4="Duopoly that cooperate",10,IF(Z4="Duopoly that compete",5,IF(Z4="Too many players with High ROCE",5,0))))) | AB4: No | AC4: =IF(AB4="No",5,0) | AD4: Tailwind | AE4: =IF(AD4="Tailwind",10,0) | AF4: Structural (10 Years Consistency) | AG4: =IF(AF4="Structural (10 Years Consistency)",10,IF(AF4="Shallow Cyclical (2 to 3 years growth)",5,0)) | AH4: No | AI4: =IF(AH4="Yes due to Product Mix change or Operating Leverage",10,IF(AH4="Yes, these are peak margins",-5,IF(AH4="No",5,0))) | AJ4: Stable | AK4: =IF(AJ4="Stable",10,0) | AL4: Yes | AM4: =IF(AL4="Yes",10,0) | AN4: B2B | AO4: =IF(AN4="B2C",10,IF(AN4="B2B",5,0)) | AP4: Yes | AQ4: =IF(AP4="Yes",10,0) | AR4: Higher One Time, Lower Annuity | AS4: =IF(AR4="Fully Annuity",10,IF(AR4="Higher Annuity, Lower One Time",5,IF(AR4="Higher One Time, Lower Annuity",3,0))) | AT4: Good | AU4: =IF(AT4="Good",10,0) | AV4: Yes for more than 2 years | AW4: =IF(AV4="Yes for more than 2 years",10,IF(AV4="Yes only for next 1 to 2 years",5,0)) | AX4: Above 40 | AY4: =IF(AX4="Above 40",20,IF(AX4="20 to 40",10,IF(AX4="0 to 20",-5,0))) | AZ4: Between 50 to 75 | BA4: =IF(AZ4="Between 50 to 75",10,IF(AZ4="Above 75",0,0)) | BB4: Stage 2 | BC4: =IF(BB4="Stage 2",20,IF(BB4="Stage 1",0,IF(BB4="Stage 3",5,IF(BB4="Stage 4",-5,0)))) | BD4: Positive Trend | BE4: =IF(BD4="Positive Trend",20,IF(BD4="Negative Trend",-10,0)) | BF4: Uptrend | BG4: =IF(BF4="Uptrend",10,IF(BF4="Sideways",5,0)) | BH4: Uptrend | BI4: =IF(BH4="Uptrend",10,IF(BH4="Sideways",5,0)) | BJ4: Blue sky scenario | BK4: =IF(BJ4="Overhead supply in last 2 years in last 2 years",-5,IF(BJ4="Close to 52 week high or retracement",5,IF(BJ4="Blue sky scenario",10,IF(BJ4="Long term Downtrend",-10,0)))) | BL4: Yes | BM4: =IF(BL4="Yes",10,0) | BN4: More than 20% | BO4: =IF(BN4="More than 20%",10,IF(BN4="Between 12 to 20%",5,IF(BN4="Less than 12%",0,0))) | BP4: No | BQ4: =IF(BP4="No",10,0) | BR4: No | BS4: =IF(BR4="NO",5,0) | BT4: Less than 1.5 | BU4: =IF(BT4="Above 2",0,IF(BT4="Between 1.5 to 2",5,IF(BT4="Less than 1.5",10,0))) | BV4: Above 70% | BW4: =IF(BV4="Above 70%",10,IF(BV4="Between 50% to 70%",5,IF(BV4="Less than 50%",0,IF(BV4="Negative",-10,IF(BV4="Less than 50% and Borrowings are increasing",-5,0))))) | BX4: Less than 0.7 | BY4: =IF(BX4="More than 1.2",-10,IF(BX4="Between 0.7 to 1.2",0,IF(BX4="Less than 0.7",10,0))) | BZ4: No | CA4: =IF(BZ4="Yes",-10,0) | CB4: Less than 15% | CC4: =IF(CB4="More than 15%",-10,IF(CB4="Less than 15%",10,0)) | CD4: No | CE4: =IF(CD4="Yes, more than 10%",-10,IF(CD4="No",10,0))
A5: =IF(B5=0,"",RANK(B5,$B$2:$B$184,0)) | B5: =SUM(N5,Y5,AA5,AC5,AE5,AG5,AI5,AK5,AM5,AO5,AQ5,AS5,AU5,AW5,AY5,BA5,BC5,BE5,BG5,BI5,BK5,BM5,BO5,BQ5,BS5,BU5,BW5,BY5,CA5,CC5,CE5) | C5: IPCALAB | D5: Ipca Laboratories Limited | E5: healthcare | F5: pharmaceuticals - indian - bulk drugs & formln | G5: largecap | H5: 49025.8 | I5: 1950.7 | J5: 0.95 | K5: 337123 | L5: 40 | M5: Outperforming | N5: =IF(M5="Underperforming",-5,IF(L5>=95,15,IF(L5>=90,10,IF(L5>=80,5,0)))) | O5: 67.71 | P5: 44.28 | Q5: 1614.76 | R5: Near 52W High Breakout | S5: Nifty Pharma | T5: 15.25 | U5: 35.84 | V5: 17.87 | W5: 11.37 | X5: Growing Industry | Y5: =IF(X5="Growing Industry",10,IF(X5="Cyclical in an Upturn",5,0)) | Z5: Too Many Players with High ROCE | AA5: =IF(Z5="Monopoly",10,IF(Z5="Oligopoly",5,IF(Z5="Duopoly that cooperate",10,IF(Z5="Duopoly that compete",5,IF(Z5="Too many players with High ROCE",5,0))))) | AB5: Yes | AC5: =IF(AB5="No",5,0) | AD5: Tailwind | AE5: =IF(AD5="Tailwind",10,0) | AF5: Structural (10 Years Consistency) | AG5: =IF(AF5="Structural (10 Years Consistency)",10,IF(AF5="Shallow Cyclical (2 to 3 years growth)",5,0)) | AH5: No | AI5: =IF(AH5="Yes due to Product Mix change or Operating Leverage",10,IF(AH5="Yes, these are peak margins",-5,IF(AH5="No",5,0))) | AJ5: Stable | AK5: =IF(AJ5="Stable",10,0) | AL5: Yes | AM5: =IF(AL5="Yes",10,0) | AN5: B2B | AO5: =IF(AN5="B2C",10,IF(AN5="B2B",5,0)) | AP5: Yes | AQ5: =IF(AP5="Yes",10,0) | AR5: Higher Annuity, Lower One Time | AS5: =IF(AR5="Fully Annuity",10,IF(AR5="Higher Annuity, Lower One Time",5,IF(AR5="Higher One Time, Lower Annuity",3,0))) | AT5: Good | AU5: =IF(AT5="Good",10,0) | AV5: Yes for more than 2 years | AW5: =IF(AV5="Yes for more than 2 years",10,IF(AV5="Yes only for next 1 to 2 years",5,0)) | AX5: Above 40 | AY5: =IF(AX5="Above 40",20,IF(AX5="20 to 40",10,IF(AX5="0 to 20",-5,0))) | AZ5: Between 50 to 75 | BA5: =IF(AZ5="Between 50 to 75",10,IF(AZ5="Above 75",0,0)) | BB5: Stage 2 | BC5: =IF(BB5="Stage 2",20,IF(BB5="Stage 1",0,IF(BB5="Stage 3",5,IF(BB5="Stage 4",-5,0)))) | BD5: Positive Trend | BE5: =IF(BD5="Positive Trend",20,IF(BD5="Negative Trend",-10,0)) | BF5: Uptrend | BG5: =IF(BF5="Uptrend",10,IF(BF5="Sideways",5,0)) | BH5: Uptrend | BI5: =IF(BH5="Uptrend",10,IF(BH5="Sideways",5,0)) | BJ5: Blue sky scenario | BK5: =IF(BJ5="Overhead supply in last 2 years in last 2 years",-5,IF(BJ5="Close to 52 week high or retracement",5,IF(BJ5="Blue sky scenario",10,IF(BJ5="Long term Downtrend",-10,0)))) | BL5: Yes | BM5: =IF(BL5="Yes",10,0) | BN5: More than 20% | BO5: =IF(BN5="More than 20%",10,IF(BN5="Between 12 to 20%",5,IF(BN5="Less than 12%",0,0))) | BP5: No | BQ5: =IF(BP5="No",10,0) | BR5: No | BS5: =IF(BR5="NO",5,0) | BT5: Less than 1.5 | BU5: =IF(BT5="Above 2",0,IF(BT5="Between 1.5 to 2",5,IF(BT5="Less than 1.5",10,0))) | BV5: Above 70% | BW5: =IF(BV5="Above 70%",10,IF(BV5="Between 50% to 70%",5,IF(BV5="Less than 50%",0,IF(BV5="Negative",-10,IF(BV5="Less than 50% and Borrowings are increasing",-5,0))))) | BX5: Less than 0.7 | BY5: =IF(BX5="More than 1.2",-10,IF(BX5="Between 0.7 to 1.2",0,IF(BX5="Less than 0.7",10,0))) | BZ5: No | CA5: =IF(BZ5="Yes",-10,0) | CB5: Less than 15% | CC5: =IF(CB5="More than 15%",-10,IF(CB5="Less than 15%",10,0)) | CD5: No | CE5: =IF(CD5="Yes, more than 10%",-10,IF(CD5="No",10,0))
A6: =IF(B6=0,"",RANK(B6,$B$2:$B$184,0)) | B6: =SUM(N6,Y6,AA6,AC6,AE6,AG6,AI6,AK6,AM6,AO6,AQ6,AS6,AU6,AW6,AY6,BA6,BC6,BE6,BG6,BI6,BK6,BM6,BO6,BQ6,BS6,BU6,BW6,BY6,CA6,CC6,CE6) | C6: TBZ | D6: Tribhovandas Bhimji Zaveri Limited | E6: consumer discretionary | F6: diamond cutting / jewellery | G6: smallcap | H6: 3499.69 | I6: 547.5 | J6: 4.4 | K6: 1564537 | L6: 99 | M6: Outperforming | N6: =IF(M6="Underperforming",-5,IF(L6>=95,15,IF(L6>=90,10,IF(L6>=80,5,0)))) | O6: 90.49 | P6: 56.37 | Q6: 412.89 | R6: Near 52W High Breakout | S6: Nifty 50 | T6: -8.33 | U6: 193.21 | V6: 219.85 | W6: 79.17 | X6: Growing Industry | Y6: =IF(X6="Growing Industry",10,IF(X6="Cyclical in an Upturn",5,0)) | Z6: Too Many Players with High ROCE | AA6: =IF(Z6="Monopoly",10,IF(Z6="Oligopoly",5,IF(Z6="Duopoly that cooperate",10,IF(Z6="Duopoly that compete",5,IF(Z6="Too many players with High ROCE",5,0))))) | AB6: No | AC6: =IF(AB6="No",5,0) | AD6: Tailwind | AE6: =IF(AD6="Tailwind",10,0) | AF6: Structural (10 Years Consistency) | AG6: =IF(AF6="Structural (10 Years Consistency)",10,IF(AF6="Shallow Cyclical (2 to 3 years growth)",5,0)) | AH6: No | AI6: =IF(AH6="Yes due to Product Mix change or Operating Leverage",10,IF(AH6="Yes, these are peak margins",-5,IF(AH6="No",5,0))) | AJ6: Stable | AK6: =IF(AJ6="Stable",10,0) | AL6: Yes | AM6: =IF(AL6="Yes",10,0) | AN6: B2B | AO6: =IF(AN6="B2C",10,IF(AN6="B2B",5,0)) | AP6: Yes | AQ6: =IF(AP6="Yes",10,0) | AR6: Higher One Time, Lower Annuity | AS6: =IF(AR6="Fully Annuity",10,IF(AR6="Higher Annuity, Lower One Time",5,IF(AR6="Higher One Time, Lower Annuity",3,0))) | AT6: Good | AU6: =IF(AT6="Good",10,0) | AV6: Yes for more than 2 years | AW6: =IF(AV6="Yes for more than 2 years",10,IF(AV6="Yes only for next 1 to 2 years",5,0)) | AX6: Above 40 | AY6: =IF(AX6="Above 40",20,IF(AX6="20 to 40",10,IF(AX6="0 to 20",-5,0))) | AZ6: Above 75 | BA6: =IF(AZ6="Between 50 to 75",10,IF(AZ6="Above 75",0,0)) | BB6: Stage 2 | BC6: =IF(BB6="Stage 2",20,IF(BB6="Stage 1",0,IF(BB6="Stage 3",5,IF(BB6="Stage 4",-5,0)))) | BD6: Positive Trend | BE6: =IF(BD6="Positive Trend",20,IF(BD6="Negative Trend",-10,0)) | BF6: Uptrend | BG6: =IF(BF6="Uptrend",10,IF(BF6="Sideways",5,0)) | BH6: Uptrend | BI6: =IF(BH6="Uptrend",10,IF(BH6="Sideways",5,0)) | BJ6: Blue sky scenario | BK6: =IF(BJ6="Overhead supply in last 2 years in last 2 years",-5,IF(BJ6="Close to 52 week high or retracement",5,IF(BJ6="Blue sky scenario",10,IF(BJ6="Long term Downtrend",-10,0)))) | BL6: Yes | BM6: =IF(BL6="Yes",10,0) | BN6: More than 20% | BO6: =IF(BN6="More than 20%",10,IF(BN6="Between 12 to 20%",5,IF(BN6="Less than 12%",0,0))) | BP6: No | BQ6: =IF(BP6="No",10,0) | BR6: No | BS6: =IF(BR6="NO",5,0) | BT6: Less than 1.5 | BU6: =IF(BT6="Above 2",0,IF(BT6="Between 1.5 to 2",5,IF(BT6="Less than 1.5",10,0))) | BV6: Above 70% | BW6: =IF(BV6="Above 70%",10,IF(BV6="Between 50% to 70%",5,IF(BV6="Less than 50%",0,IF(BV6="Negative",-10,IF(BV6="Less than 50% and Borrowings are increasing",-5,0))))) | BX6: Between 0.7 to 1.2 | BY6: =IF(BX6="More than 1.2",-10,IF(BX6="Between 0.7 to 1.2",0,IF(BX6="Less than 0.7",10,0))) | BZ6: No | CA6: =IF(BZ6="Yes",-10,0) | CB6: Less than 15% | CC6: =IF(CB6="More than 15%",-10,IF(CB6="Less than 15%",10,0)) | CD6: No | CE6: =IF(CD6="Yes, more than 10%",-10,IF(CD6="No",10,0))
A7: =IF(B7=0,"",RANK(B7,$B$2:$B$184,0)) | B7: =SUM(N7,Y7,AA7,AC7,AE7,AG7,AI7,AK7,AM7,AO7,AQ7,AS7,AU7,AW7,AY7,BA7,BC7,BE7,BG7,BI7,BK7,BM7,BO7,BQ7,BS7,BU7,BW7,BY7,CA7,CC7,CE7) | C7: WELSPUNLIV | D7: Welspun Living Ltd | E7: textiles | F7: textiles - products | G7: midcap | H7: 19049.04 | I7: 202.82 | J7: 0.59 | K7: 3113066 | L7: 56 | M7: Outperforming | N7: =IF(M7="Underperforming",-5,IF(L7>=95,15,IF(L7>=90,10,IF(L7>=80,5,0)))) | O7: 73.82 | P7: 42.65 | Q7: 166.86 | R7: Near 52W High Breakout | S7: Nifty 50 | T7: -8.33 | U7: 63.12 | V7: 77.94 | W7: 17.06 | X7: Growing Industry | Y7: =IF(X7="Growing Industry",10,IF(X7="Cyclical in an Upturn",5,0)) | Z7: Too Many Players with High ROCE | AA7: =IF(Z7="Monopoly",10,IF(Z7="Oligopoly",5,IF(Z7="Duopoly that cooperate",10,IF(Z7="Duopoly that compete",5,IF(Z7="Too many players with High ROCE",5,0))))) | AB7: No | AC7: =IF(AB7="No",5,0) | AD7: Tailwind | AE7: =IF(AD7="Tailwind",10,0) | AF7: Structural (10 Years Consistency) | AG7: =IF(AF7="Structural (10 Years Consistency)",10,IF(AF7="Shallow Cyclical (2 to 3 years growth)",5,0)) | AH7: No | AI7: =IF(AH7="Yes due to Product Mix change or Operating Leverage",10,IF(AH7="Yes, these are peak margins",-5,IF(AH7="No",5,0))) | AJ7: Stable | AK7: =IF(AJ7="Stable",10,0) | AL7: Yes | AM7: =IF(AL7="Yes",10,0) | AN7: B2B | AO7: =IF(AN7="B2C",10,IF(AN7="B2B",5,0)) | AP7: Yes | AQ7: =IF(AP7="Yes",10,0) | AR7: Higher One Time, Lower Annuity | AS7: =IF(AR7="Fully Annuity",10,IF(AR7="Higher Annuity, Lower One Time",5,IF(AR7="Higher One Time, Lower Annuity",3,0))) | AT7: Good | AU7: =IF(AT7="Good",10,0) | AV7: Yes for more than 2 years | AW7: =IF(AV7="Yes for more than 2 years",10,IF(AV7="Yes only for next 1 to 2 years",5,0)) | AX7: Above 40 | AY7: =IF(AX7="Above 40",20,IF(AX7="20 to 40",10,IF(AX7="0 to 20",-5,0))) | AZ7: Between 50 to 75 | BA7: =IF(AZ7="Between 50 to 75",10,IF(AZ7="Above 75",0,0)) | BB7: Stage 2 | BC7: =IF(BB7="Stage 2",20,IF(BB7="Stage 1",0,IF(BB7="Stage 3",5,IF(BB7="Stage 4",-5,0)))) | BD7: Positive Trend | BE7: =IF(BD7="Positive Trend",20,IF(BD7="Negative Trend",-10,0)) | BF7: Uptrend | BG7: =IF(BF7="Uptrend",10,IF(BF7="Sideways",5,0)) | BH7: Uptrend | BI7: =IF(BH7="Uptrend",10,IF(BH7="Sideways",5,0)) | BJ7: Blue sky scenario | BK7: =IF(BJ7="Overhead supply in last 2 years in last 2 years",-5,IF(BJ7="Close to 52 week high or retracement",5,IF(BJ7="Blue sky scenario",10,IF(BJ7="Long term Downtrend",-10,0)))) | BL7: Yes | BM7: =IF(BL7="Yes",10,0) | BN7: More than 20% | BO7: =IF(BN7="More than 20%",10,IF(BN7="Between 12 to 20%",5,IF(BN7="Less than 12%",0,0))) | BP7: No | BQ7: =IF(BP7="No",10,0) | BR7: Yes | BS7: =IF(BR7="NO",5,0) | BT7: Less than 1.5 | BU7: =IF(BT7="Above 2",0,IF(BT7="Between 1.5 to 2",5,IF(BT7="Less than 1.5",10,0))) | BV7: Above 70% | BW7: =IF(BV7="Above 70%",10,IF(BV7="Between 50% to 70%",5,IF(BV7="Less than 50%",0,IF(BV7="Negative",-10,IF(BV7="Less than 50% and Borrowings are increasing",-5,0))))) | BX7: Less than 0.7 | BY7: =IF(BX7="More than 1.2",-10,IF(BX7="Between 0.7 to 1.2",0,IF(BX7="Less than 0.7",10,0))) | BZ7: No | CA7: =IF(BZ7="Yes",-10,0) | CB7: Less than 15% | CC7: =IF(CB7="More than 15%",-10,IF(CB7="Less than 15%",10,0)) | CD7: No | CE7: =IF(CD7="Yes, more than 10%",-10,IF(CD7="No",10,0))
A8: =IF(B8=0,"",RANK(B8,$B$2:$B$184,0)) | B8: =SUM(N8,Y8,AA8,AC8,AE8,AG8,AI8,AK8,AM8,AO8,AQ8,AS8,AU8,AW8,AY8,BA8,BC8,BE8,BG8,BI8,BK8,BM8,BO8,BQ8,BS8,BU8,BW8,BY8,CA8,CC8,CE8) | C8: PASUPTAC | D8: Pasupati Acrylon Ltd | E8: textiles | F8: textiles - manmade | G8: smallcap | H8: 628.21 | I8: 68.07 | J8: -3.42 | K8: 159716 | L8: 33 | M8: Outperforming | N8: =IF(M8="Underperforming",-5,IF(L8>=95,15,IF(L8>=90,10,IF(L8>=80,5,0)))) | O8: 62.2 | P8: 46.9 | Q8: 49.52 | R8: Volume Spike / Accumulation | S8: Nifty 50 | T8: -8.33 | U8: 46.07 | V8: 59.34 | W8: 10.15 | X8: Growing Industry | Y8: =IF(X8="Growing Industry",10,IF(X8="Cyclical in an Upturn",5,0)) | Z8: Too Many Players with High ROCE | AA8: =IF(Z8="Monopoly",10,IF(Z8="Oligopoly",5,IF(Z8="Duopoly that cooperate",10,IF(Z8="Duopoly that compete",5,IF(Z8="Too many players with High ROCE",5,0))))) | AB8: No | AC8: =IF(AB8="No",5,0) | AD8: Tailwind | AE8: =IF(AD8="Tailwind",10,0) | AF8: Structural (10 Years Consistency) | AG8: =IF(AF8="Structural (10 Years Consistency)",10,IF(AF8="Shallow Cyclical (2 to 3 years growth)",5,0)) | AH8: No | AI8: =IF(AH8="Yes due to Product Mix change or Operating Leverage",10,IF(AH8="Yes, these are peak margins",-5,IF(AH8="No",5,0))) | AJ8: Stable | AK8: =IF(AJ8="Stable",10,0) | AL8: Yes | AM8: =IF(AL8="Yes",10,0) | AN8: B2B | AO8: =IF(AN8="B2C",10,IF(AN8="B2B",5,0)) | AP8: Yes | AQ8: =IF(AP8="Yes",10,0) | AR8: Higher One Time, Lower Annuity | AS8: =IF(AR8="Fully Annuity",10,IF(AR8="Higher Annuity, Lower One Time",5,IF(AR8="Higher One Time, Lower Annuity",3,0))) | AT8: Good | AU8: =IF(AT8="Good",10,0) | AV8: Yes for more than 2 years | AW8: =IF(AV8="Yes for more than 2 years",10,IF(AV8="Yes only for next 1 to 2 years",5,0)) | AX8: Above 40 | AY8: =IF(AX8="Above 40",20,IF(AX8="20 to 40",10,IF(AX8="0 to 20",-5,0))) | AZ8: Between 50 to 75 | BA8: =IF(AZ8="Between 50 to 75",10,IF(AZ8="Above 75",0,0)) | BB8: Stage 2 | BC8: =IF(BB8="Stage 2",20,IF(BB8="Stage 1",0,IF(BB8="Stage 3",5,IF(BB8="Stage 4",-5,0)))) | BD8: Positive Trend | BE8: =IF(BD8="Positive Trend",20,IF(BD8="Negative Trend",-10,0)) | BF8: Uptrend | BG8: =IF(BF8="Uptrend",10,IF(BF8="Sideways",5,0)) | BH8: Uptrend | BI8: =IF(BH8="Uptrend",10,IF(BH8="Sideways",5,0)) | BJ8: Close to 52 week high or retracement | BK8: =IF(BJ8="Overhead supply in last 2 years in last 2 years",-5,IF(BJ8="Close to 52 week high or retracement",5,IF(BJ8="Blue sky scenario",10,IF(BJ8="Long term Downtrend",-10,0)))) | BL8: Yes | BM8: =IF(BL8="Yes",10,0) | BN8: More than 20% | BO8: =IF(BN8="More than 20%",10,IF(BN8="Between 12 to 20%",5,IF(BN8="Less than 12%",0,0))) | BP8: No | BQ8: =IF(BP8="No",10,0) | BR8: No | BS8: =IF(BR8="NO",5,0) | BT8: Less than 1.5 | BU8: =IF(BT8="Above 2",0,IF(BT8="Between 1.5 to 2",5,IF(BT8="Less than 1.5",10,0))) | BV8: Above 70% | BW8: =IF(BV8="Above 70%",10,IF(BV8="Between 50% to 70%",5,IF(BV8="Less than 50%",0,IF(BV8="Negative",-10,IF(BV8="Less than 50% and Borrowings are increasing",-5,0))))) | BX8: Less than 0.7 | BY8: =IF(BX8="More than 1.2",-10,IF(BX8="Between 0.7 to 1.2",0,IF(BX8="Less than 0.7",10,0))) | BZ8: No | CA8: =IF(BZ8="Yes",-10,0) | CB8: Less than 15% | CC8: =IF(CB8="More than 15%",-10,IF(CB8="Less than 15%",10,0)) | CD8: No | CE8: =IF(CD8="Yes, more than 10%",-10,IF(CD8="No",10,0))
A9: =IF(B9=0,"",RANK(B9,$B$2:$B$184,0)) | B9: =SUM(N9,Y9,AA9,AC9,AE9,AG9,AI9,AK9,AM9,AO9,AQ9,AS9,AU9,AW9,AY9,BA9,BC9,BE9,BG9,BI9,BK9,BM9,BO9,BQ9,BS9,BU9,BW9,BY9,CA9,CC9,CE9) | C9: INNOVACAP | D9: Innova Captab Ltd | E9: healthcare | F9: pharmaceuticals - indian - bulk drugs & formln | G9: midcap | H9: 6524.21 | I9: 1133.4 | J9: -0.59 | K9: 119085 | L9: 40 | M9: Outperforming | N9: =IF(M9="Underperforming",-5,IF(L9>=95,15,IF(L9>=90,10,IF(L9>=80,5,0)))) | O9: 69.76 | P9: 62.71 | Q9: 912.13 | R9: Near 52W High Breakout | S9: Nifty Pharma | T9: 15.25 | U9: 32.01 | V9: 14.54 | W9: 11.48 | X9: Growing Industry | Y9: =IF(X9="Growing Industry",10,IF(X9="Cyclical in an Upturn",5,0)) | Z9: Too Many Players with High ROCE | AA9: =IF(Z9="Monopoly",10,IF(Z9="Oligopoly",5,IF(Z9="Duopoly that cooperate",10,IF(Z9="Duopoly that compete",5,IF(Z9="Too many players with High ROCE",5,0))))) | AB9: Yes | AC9: =IF(AB9="No",5,0) | AD9: Tailwind | AE9: =IF(AD9="Tailwind",10,0) | AF9: Structural (10 Years Consistency) | AG9: =IF(AF9="Structural (10 Years Consistency)",10,IF(AF9="Shallow Cyclical (2 to 3 years growth)",5,0)) | AH9: No | AI9: =IF(AH9="Yes due to Product Mix change or Operating Leverage",10,IF(AH9="Yes, these are peak margins",-5,IF(AH9="No",5,0))) | AJ9: Stable | AK9: =IF(AJ9="Stable",10,0) | AL9: Yes | AM9: =IF(AL9="Yes",10,0) | AN9: B2B | AO9: =IF(AN9="B2C",10,IF(AN9="B2B",5,0)) | AP9: Yes | AQ9: =IF(AP9="Yes",10,0) | AR9: Higher Annuity, Lower One Time | AS9: =IF(AR9="Fully Annuity",10,IF(AR9="Higher Annuity, Lower One Time",5,IF(AR9="Higher One Time, Lower Annuity",3,0))) | AT9: Good | AU9: =IF(AT9="Good",10,0) | AV9: Yes for more than 2 years | AW9: =IF(AV9="Yes for more than 2 years",10,IF(AV9="Yes only for next 1 to 2 years",5,0)) | AX9: Above 40 | AY9: =IF(AX9="Above 40",20,IF(AX9="20 to 40",10,IF(AX9="0 to 20",-5,0))) | AZ9: Between 50 to 75 | BA9: =IF(AZ9="Between 50 to 75",10,IF(AZ9="Above 75",0,0)) | BB9: Stage 2 | BC9: =IF(BB9="Stage 2",20,IF(BB9="Stage 1",0,IF(BB9="Stage 3",5,IF(BB9="Stage 4",-5,0)))) | BD9: Positive Trend | BE9: =IF(BD9="Positive Trend",20,IF(BD9="Negative Trend",-10,0)) | BF9: Uptrend | BG9: =IF(BF9="Uptrend",10,IF(BF9="Sideways",5,0)) | BH9: Uptrend | BI9: =IF(BH9="Uptrend",10,IF(BH9="Sideways",5,0)) | BJ9: Blue sky scenario | BK9: =IF(BJ9="Overhead supply in last 2 years in last 2 years",-5,IF(BJ9="Close to 52 week high or retracement",5,IF(BJ9="Blue sky scenario",10,IF(BJ9="Long term Downtrend",-10,0)))) | BL9: Yes | BM9: =IF(BL9="Yes",10,0) | BN9: More than 20% | BO9: =IF(BN9="More than 20%",10,IF(BN9="Between 12 to 20%",5,IF(BN9="Less than 12%",0,0))) | BP9: No | BQ9: =IF(BP9="No",10,0) | BR9: Yes | BS9: =IF(BR9="NO",5,0) | BT9: Less than 1.5 | BU9: =IF(BT9="Above 2",0,IF(BT9="Between 1.5 to 2",5,IF(BT9="Less than 1.5",10,0))) | BV9: Above 70% | BW9: =IF(BV9="Above 70%",10,IF(BV9="Between 50% to 70%",5,IF(BV9="Less than 50%",0,IF(BV9="Negative",-10,IF(BV9="Less than 50% and Borrowings are increasing",-5,0))))) | BX9: Less than 0.7 | BY9: =IF(BX9="More than 1.2",-10,IF(BX9="Between 0.7 to 1.2",0,IF(BX9="Less than 0.7",10,0))) | BZ9: No | CA9: =IF(BZ9="Yes",-10,0) | CB9: Less than 15% | CC9: =IF(CB9="More than 15%",-10,IF(CB9="Less than 15%",10,0)) | CD9: No | CE9: =IF(CD9="Yes, more than 10%",-10,IF(CD9="No",10,0))
A10: =IF(B10=0,"",RANK(B10,$B$2:$B$184,0)) | B10: =SUM(N10,Y10,AA10,AC10,AE10,AG10,AI10,AK10,AM10,AO10,AQ10,AS10,AU10,AW10,AY10,BA10,BC10,BE10,BG10,BI10,BK10,BM10,BO10,BQ10,BS10,BU10,BW10,BY10,CA10,CC10,CE10) | C10: MBECL | D10: Mcnally Bharat Engineering Company Limited | E10: realty | F10: engineering - turnkey services | G10: smallcap | H10: 1156.4 | I10: 364.26 | J10: 5 | K10: 28195 | N10: =IF(M10="Underperforming",-5,IF(L10>=95,15,IF(L10>=90,10,IF(L10>=80,5,0)))) | O10: 99.97 | P10: 61.59 | Q10: 306.78 | R10: Volume Spike & Near 52W High Breakout | S10: Nifty Realty | X10: Growing Industry | Y10: =IF(X10="Growing Industry",10,IF(X10="Cyclical in an Upturn",5,0)) | Z10: Too Many Players with High ROCE | AA10: =IF(Z10="Monopoly",10,IF(Z10="Oligopoly",5,IF(Z10="Duopoly that cooperate",10,IF(Z10="Duopoly that compete",5,IF(Z10="Too many players with High ROCE",5,0))))) | AB10: No | AC10: =IF(AB10="No",5,0) | AD10: Tailwind | AE10: =IF(AD10="Tailwind",10,0) | AF10: Structural (10 Years Consistency) | AG10: =IF(AF10="Structural (10 Years Consistency)",10,IF(AF10="Shallow Cyclical (2 to 3 years growth)",5,0)) | AH10: No | AI10: =IF(AH10="Yes due to Product Mix change or Operating Leverage",10,IF(AH10="Yes, these are peak margins",-5,IF(AH10="No",5,0))) | AJ10: Stable | AK10: =IF(AJ10="Stable",10,0) | AL10: Yes | AM10: =IF(AL10="Yes",10,0) | AN10: B2B | AO10: =IF(AN10="B2C",10,IF(AN10="B2B",5,0)) | AP10: Yes | AQ10: =IF(AP10="Yes",10,0) | AR10: Higher One Time, Lower Annuity | AS10: =IF(AR10="Fully Annuity",10,IF(AR10="Higher Annuity, Lower One Time",5,IF(AR10="Higher One Time, Lower Annuity",3,0))) | AT10: Good | AU10: =IF(AT10="Good",10,0) | AV10: Yes for more than 2 years | AW10: =IF(AV10="Yes for more than 2 years",10,IF(AV10="Yes only for next 1 to 2 years",5,0)) | AX10: Above 40 | AY10: =IF(AX10="Above 40",20,IF(AX10="20 to 40",10,IF(AX10="0 to 20",-5,0))) | AZ10: Above 75 | BA10: =IF(AZ10="Between 50 to 75",10,IF(AZ10="Above 75",0,0)) | BB10: Stage 2 | BC10: =IF(BB10="Stage 2",20,IF(BB10="Stage 1",0,IF(BB10="Stage 3",5,IF(BB10="Stage 4",-5,0)))) | BD10: Positive Trend | BE10: =IF(BD10="Positive Trend",20,IF(BD10="Negative Trend",-10,0)) | BF10: Uptrend | BG10: =IF(BF10="Uptrend",10,IF(BF10="Sideways",5,0)) | BH10: Uptrend | BI10: =IF(BH10="Uptrend",10,IF(BH10="Sideways",5,0)) | BJ10: Blue sky scenario | BK10: =IF(BJ10="Overhead supply in last 2 years in last 2 years",-5,IF(BJ10="Close to 52 week high or retracement",5,IF(BJ10="Blue sky scenario",10,IF(BJ10="Long term Downtrend",-10,0)))) | BL10: Yes | BM10: =IF(BL10="Yes",10,0) | BN10: More than 20% | BO10: =IF(BN10="More than 20%",10,IF(BN10="Between 12 to 20%",5,IF(BN10="Less than 12%",0,0))) | BP10: No | BQ10: =IF(BP10="No",10,0) | BR10: No | BS10: =IF(BR10="NO",5,0) | BT10: Less than 1.5 | BU10: =IF(BT10="Above 2",0,IF(BT10="Between 1.5 to 2",5,IF(BT10="Less than 1.5",10,0))) | BV10: Above 70% | BW10: =IF(BV10="Above 70%",10,IF(BV10="Between 50% to 70%",5,IF(BV10="Less than 50%",0,IF(BV10="Negative",-10,IF(BV10="Less than 50% and Borrowings are increasing",-5,0))))) | BX10: Less than 0.7 | BY10: =IF(BX10="More than 1.2",-10,IF(BX10="Between 0.7 to 1.2",0,IF(BX10="Less than 0.7",10,0))) | BZ10: No | CA10: =IF(BZ10="Yes",-10,0) | CB10: Less than 15% | CC10: =IF(CB10="More than 15%",-10,IF(CB10="Less than 15%",10,0)) | CD10: No | CE10: =IF(CD10="Yes, more than 10%",-10,IF(CD10="No",10,0))
A11: =IF(B11=0,"",RANK(B11,$B$2:$B$184,0)) | B11: =SUM(N11,Y11,AA11,AC11,AE11,AG11,AI11,AK11,AM11,AO11,AQ11,AS11,AU11,AW11,AY11,BA11,BC11,BE11,BG11,BI11,BK11,BM11,BO11,BQ11,BS11,BU11,BW11,BY11,CA11,CC11,CE11) | C11: BHAGYANGR | D11: Bhagyanagar India | E11: power & utilities | F11: power generation and supply | G11: smallcap | H11: 1356.61 | I11: 425.25 | J11: 5 | K11: 328669 | L11: 92 | M11: Outperforming | N11: =IF(M11="Underperforming",-5,IF(L11>=95,15,IF(L11>=90,10,IF(L11>=80,5,0)))) | O11: 68.69 | P11: 66.26 | Q11: 301.28 | R11: Near 52W High Breakout | S11: Nifty IT | T11: -20.48 | U11: 358.19 | V11: 476.19 | W11: 47.7 | X11: Growing Industry | Y11: =IF(X11="Growing Industry",10,IF(X11="Cyclical in an Upturn",5,0)) | Z11: Too Many Players with High ROCE | AA11: =IF(Z11="Monopoly",10,IF(Z11="Oligopoly",5,IF(Z11="Duopoly that cooperate",10,IF(Z11="Duopoly that compete",5,IF(Z11="Too many players with High ROCE",5,0))))) | AB11: No | AC11: =IF(AB11="No",5,0) | AD11: Tailwind | AE11: =IF(AD11="Tailwind",10,0) | AF11: Structural (10 Years Consistency) | AG11: =IF(AF11="Structural (10 Years Consistency)",10,IF(AF11="Shallow Cyclical (2 to 3 years growth)",5,0)) | AH11: No | AI11: =IF(AH11="Yes due to Product Mix change or Operating Leverage",10,IF(AH11="Yes, these are peak margins",-5,IF(AH11="No",5,0))) | AJ11: Stable | AK11: =IF(AJ11="Stable",10,0) | AL11: Yes | AM11: =IF(AL11="Yes",10,0) | AN11: B2B | AO11: =IF(AN11="B2C",10,IF(AN11="B2B",5,0)) | AP11: Yes | AQ11: =IF(AP11="Yes",10,0) | AR11: Higher One Time, Lower Annuity | AS11: =IF(AR11="Fully Annuity",10,IF(AR11="Higher Annuity, Lower One Time",5,IF(AR11="Higher One Time, Lower Annuity",3,0))) | AT11: Good | AU11: =IF(AT11="Good",10,0) | AV11: Yes for more than 2 years | AW11: =IF(AV11="Yes for more than 2 years",10,IF(AV11="Yes only for next 1 to 2 years",5,0)) | AX11: Above 40 | AY11: =IF(AX11="Above 40",20,IF(AX11="20 to 40",10,IF(AX11="0 to 20",-5,0))) | AZ11: Between 50 to 75 | BA11: =IF(AZ11="Between 50 to 75",10,IF(AZ11="Above 75",0,0)) | BB11: Stage 2 | BC11: =IF(BB11="Stage 2",20,IF(BB11="Stage 1",0,IF(BB11="Stage 3",5,IF(BB11="Stage 4",-5,0)))) | BD11: Positive Trend | BE11: =IF(BD11="Positive Trend",20,IF(BD11="Negative Trend",-10,0)) | BF11: Uptrend | BG11: =IF(BF11="Uptrend",10,IF(BF11="Sideways",5,0)) | BH11: Uptrend | BI11: =IF(BH11="Uptrend",10,IF(BH11="Sideways",5,0)) | BJ11: Blue sky scenario | BK11: =IF(BJ11="Overhead supply in last 2 years in last 2 years",-5,IF(BJ11="Close to 52 week high or retracement",5,IF(BJ11="Blue sky scenario",10,IF(BJ11="Long term Downtrend",-10,0)))) | BL11: Yes | BM11: =IF(BL11="Yes",10,0) | BN11: More than 20% | BO11: =IF(BN11="More than 20%",10,IF(BN11="Between 12 to 20%",5,IF(BN11="Less than 12%",0,0))) | BP11: No | BQ11: =IF(BP11="No",10,0) | BR11: No | BS11: =IF(BR11="NO",5,0) | BT11: Above 2 | BU11: =IF(BT11="Above 2",0,IF(BT11="Between 1.5 to 2",5,IF(BT11="Less than 1.5",10,0))) | BV11: Above 70% | BW11: =IF(BV11="Above 70%",10,IF(BV11="Between 50% to 70%",5,IF(BV11="Less than 50%",0,IF(BV11="Negative",-10,IF(BV11="Less than 50% and Borrowings are increasing",-5,0))))) | BX11: Between 0.7 to 1.2 | BY11: =IF(BX11="More than 1.2",-10,IF(BX11="Between 0.7 to 1.2",0,IF(BX11="Less than 0.7",10,0))) | BZ11: No | CA11: =IF(BZ11="Yes",-10,0) | CB11: Less than 15% | CC11: =IF(CB11="More than 15%",-10,IF(CB11="Less than 15%",10,0)) | CD11: No | CE11: =IF(CD11="Yes, more than 10%",-10,IF(CD11="No",10,0))
A12: =IF(B12=0,"",RANK(B12,$B$2:$B$184,0)) | B12: =SUM(N12,Y12,AA12,AC12,AE12,AG12,AI12,AK12,AM12,AO12,AQ12,AS12,AU12,AW12,AY12,BA12,BC12,BE12,BG12,BI12,BK12,BM12,BO12,BQ12,BS12,BU12,BW12,BY12,CA12,CC12,CE12) | C12: SANSERA | D12: Sansera Engineering Ltd | E12: auto | F12: auto ancillaries | G12: largecap | H12: 24160.79 | I12: 3971.2 | J12: 2.57 | K12: 229404 | N12: =IF(M12="Underperforming",-5,IF(L12>=95,15,IF(L12>=90,10,IF(L12>=80,5,0)))) | O12: 73.75 | P12: 63.77 | Q12: 3300.72 | R12: Near 52W High Breakout | S12: Nifty Auto | X12: Growing Industry | Y12: =IF(X12="Growing Industry",10,IF(X12="Cyclical in an Upturn",5,0)) | Z12: Too Many Players with High ROCE | AA12: =IF(Z12="Monopoly",10,IF(Z12="Oligopoly",5,IF(Z12="Duopoly that cooperate",10,IF(Z12="Duopoly that compete",5,IF(Z12="Too many players with High ROCE",5,0))))) | AB12: No | AC12: =IF(AB12="No",5,0) | AD12: Tailwind | AE12: =IF(AD12="Tailwind",10,0) | AF12: Structural (10 Years Consistency) | AG12: =IF(AF12="Structural (10 Years Consistency)",10,IF(AF12="Shallow Cyclical (2 to 3 years growth)",5,0)) | AH12: No | AI12: =IF(AH12="Yes due to Product Mix change or Operating Leverage",10,IF(AH12="Yes, these are peak margins",-5,IF(AH12="No",5,0))) | AJ12: Stable | AK12: =IF(AJ12="Stable",10,0) | AL12: Yes | AM12: =IF(AL12="Yes",10,0) | AN12: B2B | AO12: =IF(AN12="B2C",10,IF(AN12="B2B",5,0)) | AP12: Yes | AQ12: =IF(AP12="Yes",10,0) | AR12: Higher One Time, Lower Annuity | AS12: =IF(AR12="Fully Annuity",10,IF(AR12="Higher Annuity, Lower One Time",5,IF(AR12="Higher One Time, Lower Annuity",3,0))) | AT12: Good | AU12: =IF(AT12="Good",10,0) | AV12: Yes for more than 2 years | AW12: =IF(AV12="Yes for more than 2 years",10,IF(AV12="Yes only for next 1 to 2 years",5,0)) | AX12: Above 40 | AY12: =IF(AX12="Above 40",20,IF(AX12="20 to 40",10,IF(AX12="0 to 20",-5,0))) | AZ12: Between 50 to 75 | BA12: =IF(AZ12="Between 50 to 75",10,IF(AZ12="Above 75",0,0)) | BB12: Stage 2 | BC12: =IF(BB12="Stage 2",20,IF(BB12="Stage 1",0,IF(BB12="Stage 3",5,IF(BB12="Stage 4",-5,0)))) | BD12: Positive Trend | BE12: =IF(BD12="Positive Trend",20,IF(BD12="Negative Trend",-10,0)) | BF12: Uptrend | BG12: =IF(BF12="Uptrend",10,IF(BF12="Sideways",5,0)) | BH12: Uptrend | BI12: =IF(BH12="Uptrend",10,IF(BH12="Sideways",5,0)) | BJ12: Blue sky scenario | BK12: =IF(BJ12="Overhead supply in last 2 years in last 2 years",-5,IF(BJ12="Close to 52 week high or retracement",5,IF(BJ12="Blue sky scenario",10,IF(BJ12="Long term Downtrend",-10,0)))) | BL12: Yes | BM12: =IF(BL12="Yes",10,0) | BN12: More than 20% | BO12: =IF(BN12="More than 20%",10,IF(BN12="Between 12 to 20%",5,IF(BN12="Less than 12%",0,0))) | BP12: No | BQ12: =IF(BP12="No",10,0) | BR12: Yes | BS12: =IF(BR12="NO",5,0) | BT12: Between 1.5 to 2 | BU12: =IF(BT12="Above 2",0,IF(BT12="Between 1.5 to 2",5,IF(BT12="Less than 1.5",10,0))) | BV12: Above 70% | BW12: =IF(BV12="Above 70%",10,IF(BV12="Between 50% to 70%",5,IF(BV12="Less than 50%",0,IF(BV12="Negative",-10,IF(BV12="Less than 50% and Borrowings are increasing",-5,0))))) | BX12: Less than 0.7 | BY12: =IF(BX12="More than 1.2",-10,IF(BX12="Between 0.7 to 1.2",0,IF(BX12="Less than 0.7",10,0))) | BZ12: No | CA12: =IF(BZ12="Yes",-10,0) | CB12: Less than 15% | CC12: =IF(CB12="More than 15%",-10,IF(CB12="Less than 15%",10,0)) | CD12: No | CE12: =IF(CD12="Yes, more than 10%",-10,IF(CD12="No",10,0))
A13: =IF(B13=0,"",RANK(B13,$B$2:$B$184,0)) | B13: =SUM(N13,Y13,AA13,AC13,AE13,AG13,AI13,AK13,AM13,AO13,AQ13,AS13,AU13,AW13,AY13,BA13,BC13,BE13,BG13,BI13,BK13,BM13,BO13,BQ13,BS13,BU13,BW13,BY13,CA13,CC13,CE13) | C13: IL&FSENGG | D13: Il&fs Engineering And Construction Company Limited | E13: realty | F13: construction | G13: smallcap | H13: 513.6 | I13: 39.93 | J13: 1.94 | K13: 36753 | N13: =IF(M13="Underperforming",-5,IF(L13>=95,15,IF(L13>=90,10,IF(L13>=80,5,0)))) | O13: 68.55 | P13: 40.42 | Q13: 29.12 | R13: Near 52W High Breakout | S13: Nifty Realty | X13: Growing Industry | Y13: =IF(X13="Growing Industry",10,IF(X13="Cyclical in an Upturn",5,0)) | Z13: Too Many Players with High ROCE | AA13: =IF(Z13="Monopoly",10,IF(Z13="Oligopoly",5,IF(Z13="Duopoly that cooperate",10,IF(Z13="Duopoly that compete",5,IF(Z13="Too many players with High ROCE",5,0))))) | AB13: No | AC13: =IF(AB13="No",5,0) | AD13: Tailwind | AE13: =IF(AD13="Tailwind",10,0) | AF13: Structural (10 Years Consistency) | AG13: =IF(AF13="Structural (10 Years Consistency)",10,IF(AF13="Shallow Cyclical (2 to 3 years growth)",5,0)) | AH13: No | AI13: =IF(AH13="Yes due to Product Mix change or Operating Leverage",10,IF(AH13="Yes, these are peak margins",-5,IF(AH13="No",5,0))) | AJ13: Stable | AK13: =IF(AJ13="Stable",10,0) | AL13: Yes | AM13: =IF(AL13="Yes",10,0) | AN13: B2B | AO13: =IF(AN13="B2C",10,IF(AN13="B2B",5,0)) | AP13: Yes | AQ13: =IF(AP13="Yes",10,0) | AR13: Higher One Time, Lower Annuity | AS13: =IF(AR13="Fully Annuity",10,IF(AR13="Higher Annuity, Lower One Time",5,IF(AR13="Higher One Time, Lower Annuity",3,0))) | AT13: Good | AU13: =IF(AT13="Good",10,0) | AV13: Yes for more than 2 years | AW13: =IF(AV13="Yes for more than 2 years",10,IF(AV13="Yes only for next 1 to 2 years",5,0)) | AX13: Above 40 | AY13: =IF(AX13="Above 40",20,IF(AX13="20 to 40",10,IF(AX13="0 to 20",-5,0))) | AZ13: Between 50 to 75 | BA13: =IF(AZ13="Between 50 to 75",10,IF(AZ13="Above 75",0,0)) | BB13: Stage 2 | BC13: =IF(BB13="Stage 2",20,IF(BB13="Stage 1",0,IF(BB13="Stage 3",5,IF(BB13="Stage 4",-5,0)))) | BD13: Positive Trend | BE13: =IF(BD13="Positive Trend",20,IF(BD13="Negative Trend",-10,0)) | BF13: Uptrend | BG13: =IF(BF13="Uptrend",10,IF(BF13="Sideways",5,0)) | BH13: Uptrend | BI13: =IF(BH13="Uptrend",10,IF(BH13="Sideways",5,0)) | BJ13: Close to 52 week high or retracement | BK13: =IF(BJ13="Overhead supply in last 2 years in last 2 years",-5,IF(BJ13="Close to 52 week high or retracement",5,IF(BJ13="Blue sky scenario",10,IF(BJ13="Long term Downtrend",-10,0)))) | BL13: Yes | BM13: =IF(BL13="Yes",10,0) | BN13: More than 20% | BO13: =IF(BN13="More than 20%",10,IF(BN13="Between 12 to 20%",5,IF(BN13="Less than 12%",0,0))) | BP13: No | BQ13: =IF(BP13="No",10,0) | BR13: Yes | BS13: =IF(BR13="NO",5,0) | BT13: Less than 1.5 | BU13: =IF(BT13="Above 2",0,IF(BT13="Between 1.5 to 2",5,IF(BT13="Less than 1.5",10,0))) | BV13: Above 70% | BW13: =IF(BV13="Above 70%",10,IF(BV13="Between 50% to 70%",5,IF(BV13="Less than 50%",0,IF(BV13="Negative",-10,IF(BV13="Less than 50% and Borrowings are increasing",-5,0))))) | BX13: Less than 0.7 | BY13: =IF(BX13="More than 1.2",-10,IF(BX13="Between 0.7 to 1.2",0,IF(BX13="Less than 0.7",10,0))) | BZ13: No | CA13: =IF(BZ13="Yes",-10,0) | CB13: Less than 15% | CC13: =IF(CB13="More than 15%",-10,IF(CB13="Less than 15%",10,0)) | CD13: No | CE13: =IF(CD13="Yes, more than 10%",-10,IF(CD13="No",10,0))
A14: =IF(B14=0,"",RANK(B14,$B$2:$B$184,0)) | B14: =SUM(N14,Y14,AA14,AC14,AE14,AG14,AI14,AK14,AM14,AO14,AQ14,AS14,AU14,AW14,AY14,BA14,BC14,BE14,BG14,BI14,BK14,BM14,BO14,BQ14,BS14,BU14,BW14,BY14,CA14,CC14,CE14) | C14: ARIES | D14: Aries Agro Limited | E14: chemicals | F14: fertilizers | G14: smallcap | H14: 615.5 | I14: 480.7 | J14: 1.56 | K14: 14050 | L14: 50 | M14: Outperforming | N14: =IF(M14="Underperforming",-5,IF(L14>=95,15,IF(L14>=90,10,IF(L14>=80,5,0)))) | O14: 72.19 | P14: 29.37 | Q14: 387.57 | R14: Near 52W High Breakout | S14: Nifty 50 | T14: -8.33 | U14: 17.02 | V14: 27.65 | W14: 14.78 | X14: Growing Industry | Y14: =IF(X14="Growing Industry",10,IF(X14="Cyclical in an Upturn",5,0)) | Z14: Too Many Players with High ROCE | AA14: =IF(Z14="Monopoly",10,IF(Z14="Oligopoly",5,IF(Z14="Duopoly that cooperate",10,IF(Z14="Duopoly that compete",5,IF(Z14="Too many players with High ROCE",5,0))))) | AB14: No | AC14: =IF(AB14="No",5,0) | AD14: Tailwind | AE14: =IF(AD14="Tailwind",10,0) | AF14: Structural (10 Years Consistency) | AG14: =IF(AF14="Structural (10 Years Consistency)",10,IF(AF14="Shallow Cyclical (2 to 3 years growth)",5,0)) | AH14: No | AI14: =IF(AH14="Yes due to Product Mix change or Operating Leverage",10,IF(AH14="Yes, these are peak margins",-5,IF(AH14="No",5,0))) | AJ14: Stable | AK14: =IF(AJ14="Stable",10,0) | AL14: Yes | AM14: =IF(AL14="Yes",10,0) | AN14: B2B | AO14: =IF(AN14="B2C",10,IF(AN14="B2B",5,0)) | AP14: Yes | AQ14: =IF(AP14="Yes",10,0) | AR14: Higher One Time, Lower Annuity | AS14: =IF(AR14="Fully Annuity",10,IF(AR14="Higher Annuity, Lower One Time",5,IF(AR14="Higher One Time, Lower Annuity",3,0))) | AT14: Good | AU14: =IF(AT14="Good",10,0) | AV14: Yes for more than 2 years | AW14: =IF(AV14="Yes for more than 2 years",10,IF(AV14="Yes only for next 1 to 2 years",5,0)) | AX14: 20 to 40 | AY14: =IF(AX14="Above 40",20,IF(AX14="20 to 40",10,IF(AX14="0 to 20",-5,0))) | AZ14: Between 50 to 75 | BA14: =IF(AZ14="Between 50 to 75",10,IF(AZ14="Above 75",0,0)) | BB14: Stage 2 | BC14: =IF(BB14="Stage 2",20,IF(BB14="Stage 1",0,IF(BB14="Stage 3",5,IF(BB14="Stage 4",-5,0)))) | BD14: Positive Trend | BE14: =IF(BD14="Positive Trend",20,IF(BD14="Negative Trend",-10,0)) | BF14: Uptrend | BG14: =IF(BF14="Uptrend",10,IF(BF14="Sideways",5,0)) | BH14: Uptrend | BI14: =IF(BH14="Uptrend",10,IF(BH14="Sideways",5,0)) | BJ14: Blue sky scenario | BK14: =IF(BJ14="Overhead supply in last 2 years in last 2 years",-5,IF(BJ14="Close to 52 week high or retracement",5,IF(BJ14="Blue sky scenario",10,IF(BJ14="Long term Downtrend",-10,0)))) | BL14: Yes | BM14: =IF(BL14="Yes",10,0) | BN14: More than 20% | BO14: =IF(BN14="More than 20%",10,IF(BN14="Between 12 to 20%",5,IF(BN14="Less than 12%",0,0))) | BP14: No | BQ14: =IF(BP14="No",10,0) | BR14: No | BS14: =IF(BR14="NO",5,0) | BT14: Less than 1.5 | BU14: =IF(BT14="Above 2",0,IF(BT14="Between 1.5 to 2",5,IF(BT14="Less than 1.5",10,0))) | BV14: Above 70% | BW14: =IF(BV14="Above 70%",10,IF(BV14="Between 50% to 70%",5,IF(BV14="Less than 50%",0,IF(BV14="Negative",-10,IF(BV14="Less than 50% and Borrowings are increasing",-5,0))))) | BX14: Less than 0.7 | BY14: =IF(BX14="More than 1.2",-10,IF(BX14="Between 0.7 to 1.2",0,IF(BX14="Less than 0.7",10,0))) | BZ14: No | CA14: =IF(BZ14="Yes",-10,0) | CB14: Less than 15% | CC14: =IF(CB14="More than 15%",-10,IF(CB14="Less than 15%",10,0)) | CD14: No | CE14: =IF(CD14="Yes, more than 10%",-10,IF(CD14="No",10,0))
A15: =IF(B15=0,"",RANK(B15,$B$2:$B$184,0)) | B15: =SUM(N15,Y15,AA15,AC15,AE15,AG15,AI15,AK15,AM15,AO15,AQ15,AS15,AU15,AW15,AY15,BA15,BC15,BE15,BG15,BI15,BK15,BM15,BO15,BQ15,BS15,BU15,BW15,BY15,CA15,CC15,CE15) | C15: SWANDEF | D15: Swan Defence and Heavy Industries Ltd | E15: transportation | F15: miscellaneous | G15: midcap | H15: 13963.4 | I15: 2687.2 | J15: 1.38 | K15: 17649 | L15: 94 | M15: Outperforming | N15: =IF(M15="Underperforming",-5,IF(L15>=95,15,IF(L15>=90,10,IF(L15>=80,5,0)))) | O15: 66.7 | P15: 56.21 | Q15: 2071.83 | R15: Near 52W High Breakout | S15: Nifty 50 | T15: -8.33 | U15: 388.89 | V15: 433.31 | W15: 51.23 | X15: Growing Industry | Y15: =IF(X15="Growing Industry",10,IF(X15="Cyclical in an Upturn",5,0)) | Z15: Too Many Players with High ROCE | AA15: =IF(Z15="Monopoly",10,IF(Z15="Oligopoly",5,IF(Z15="Duopoly that cooperate",10,IF(Z15="Duopoly that compete",5,IF(Z15="Too many players with High ROCE",5,0))))) | AB15: No | AC15: =IF(AB15="No",5,0) | AD15: Tailwind | AE15: =IF(AD15="Tailwind",10,0) | AF15: Structural (10 Years Consistency) | AG15: =IF(AF15="Structural (10 Years Consistency)",10,IF(AF15="Shallow Cyclical (2 to 3 years growth)",5,0)) | AH15: No | AI15: =IF(AH15="Yes due to Product Mix change or Operating Leverage",10,IF(AH15="Yes, these are peak margins",-5,IF(AH15="No",5,0))) | AJ15: Stable | AK15: =IF(AJ15="Stable",10,0) | AL15: Yes | AM15: =IF(AL15="Yes",10,0) | AN15: B2B | AO15: =IF(AN15="B2C",10,IF(AN15="B2B",5,0)) | AP15: Yes | AQ15: =IF(AP15="Yes",10,0) | AR15: Higher One Time, Lower Annuity | AS15: =IF(AR15="Fully Annuity",10,IF(AR15="Higher Annuity, Lower One Time",5,IF(AR15="Higher One Time, Lower Annuity",3,0))) | AT15: Good | AU15: =IF(AT15="Good",10,0) | AV15: Yes for more than 2 years | AW15: =IF(AV15="Yes for more than 2 years",10,IF(AV15="Yes only for next 1 to 2 years",5,0)) | AX15: Above 40 | AY15: =IF(AX15="Above 40",20,IF(AX15="20 to 40",10,IF(AX15="0 to 20",-5,0))) | AZ15: Between 50 to 75 | BA15: =IF(AZ15="Between 50 to 75",10,IF(AZ15="Above 75",0,0)) | BB15: Stage 2 | BC15: =IF(BB15="Stage 2",20,IF(BB15="Stage 1",0,IF(BB15="Stage 3",5,IF(BB15="Stage 4",-5,0)))) | BD15: Positive Trend | BE15: =IF(BD15="Positive Trend",20,IF(BD15="Negative Trend",-10,0)) | BF15: Uptrend | BG15: =IF(BF15="Uptrend",10,IF(BF15="Sideways",5,0)) | BH15: Uptrend | BI15: =IF(BH15="Uptrend",10,IF(BH15="Sideways",5,0)) | BJ15: Blue sky scenario | BK15: =IF(BJ15="Overhead supply in last 2 years in last 2 years",-5,IF(BJ15="Close to 52 week high or retracement",5,IF(BJ15="Blue sky scenario",10,IF(BJ15="Long term Downtrend",-10,0)))) | BL15: Yes | BM15: =IF(BL15="Yes",10,0) | BN15: More than 20% | BO15: =IF(BN15="More than 20%",10,IF(BN15="Between 12 to 20%",5,IF(BN15="Less than 12%",0,0))) | BP15: No | BQ15: =IF(BP15="No",10,0) | BR15: No | BS15: =IF(BR15="NO",5,0) | BT15: Less than 1.5 | BU15: =IF(BT15="Above 2",0,IF(BT15="Between 1.5 to 2",5,IF(BT15="Less than 1.5",10,0))) | BV15: Above 70% | BW15: =IF(BV15="Above 70%",10,IF(BV15="Between 50% to 70%",5,IF(BV15="Less than 50%",0,IF(BV15="Negative",-10,IF(BV15="Less than 50% and Borrowings are increasing",-5,0))))) | BX15: More than 1.2 | BY15: =IF(BX15="More than 1.2",-10,IF(BX15="Between 0.7 to 1.2",0,IF(BX15="Less than 0.7",10,0))) | BZ15: No | CA15: =IF(BZ15="Yes",-10,0) | CB15: Less than 15% | CC15: =IF(CB15="More than 15%",-10,IF(CB15="Less than 15%",10,0)) | CD15: No | CE15: =IF(CD15="Yes, more than 10%",-10,IF(CD15="No",10,0))
A16: =IF(B16=0,"",RANK(B16,$B$2:$B$184,0)) | B16: =SUM(N16,Y16,AA16,AC16,AE16,AG16,AI16,AK16,AM16,AO16,AQ16,AS16,AU16,AW16,AY16,BA16,BC16,BE16,BG16,BI16,BK16,BM16,BO16,BQ16,BS16,BU16,BW16,BY16,CA16,CC16,CE16) | C16: CEIGALL | D16: Ceigall India Ltd | E16: realty | F16: construction | G16: midcap | H16: 6658.98 | I16: 386.8 | J16: 1.19 | K16: 393782 | N16: =IF(M16="Underperforming",-5,IF(L16>=95,15,IF(L16>=90,10,IF(L16>=80,5,0)))) | O16: 65.77 | P16: 29.74 | Q16: 305.66 | R16: Near 52W High Breakout | S16: Nifty Realty | X16: Growing Industry | Y16: =IF(X16="Growing Industry",10,IF(X16="Cyclical in an Upturn",5,0)) | Z16: Too Many Players with High ROCE | AA16: =IF(Z16="Monopoly",10,IF(Z16="Oligopoly",5,IF(Z16="Duopoly that cooperate",10,IF(Z16="Duopoly that compete",5,IF(Z16="Too many players with High ROCE",5,0))))) | AB16: No | AC16: =IF(AB16="No",5,0) | AD16: Tailwind | AE16: =IF(AD16="Tailwind",10,0) | AF16: Structural (10 Years Consistency) | AG16: =IF(AF16="Structural (10 Years Consistency)",10,IF(AF16="Shallow Cyclical (2 to 3 years growth)",5,0)) | AH16: No | AI16: =IF(AH16="Yes due to Product Mix change or Operating Leverage",10,IF(AH16="Yes, these are peak margins",-5,IF(AH16="No",5,0))) | AJ16: Stable | AK16: =IF(AJ16="Stable",10,0) | AL16: Yes | AM16: =IF(AL16="Yes",10,0) | AN16: B2B | AO16: =IF(AN16="B2C",10,IF(AN16="B2B",5,0)) | AP16: Yes | AQ16: =IF(AP16="Yes",10,0) | AR16: Higher One Time, Lower Annuity | AS16: =IF(AR16="Fully Annuity",10,IF(AR16="Higher Annuity, Lower One Time",5,IF(AR16="Higher One Time, Lower Annuity",3,0))) | AT16: Good | AU16: =IF(AT16="Good",10,0) | AV16: Yes for more than 2 years | AW16: =IF(AV16="Yes for more than 2 years",10,IF(AV16="Yes only for next 1 to 2 years",5,0)) | AX16: 20 to 40 | AY16: =IF(AX16="Above 40",20,IF(AX16="20 to 40",10,IF(AX16="0 to 20",-5,0))) | AZ16: Between 50 to 75 | BA16: =IF(AZ16="Between 50 to 75",10,IF(AZ16="Above 75",0,0)) | BB16: Stage 2 | BC16: =IF(BB16="Stage 2",20,IF(BB16="Stage 1",0,IF(BB16="Stage 3",5,IF(BB16="Stage 4",-5,0)))) | BD16: Positive Trend | BE16: =IF(BD16="Positive Trend",20,IF(BD16="Negative Trend",-10,0)) | BF16: Uptrend | BG16: =IF(BF16="Uptrend",10,IF(BF16="Sideways",5,0)) | BH16: Uptrend | BI16: =IF(BH16="Uptrend",10,IF(BH16="Sideways",5,0)) | BJ16: Blue sky scenario | BK16: =IF(BJ16="Overhead supply in last 2 years in last 2 years",-5,IF(BJ16="Close to 52 week high or retracement",5,IF(BJ16="Blue sky scenario",10,IF(BJ16="Long term Downtrend",-10,0)))) | BL16: Yes | BM16: =IF(BL16="Yes",10,0) | BN16: More than 20% | BO16: =IF(BN16="More than 20%",10,IF(BN16="Between 12 to 20%",5,IF(BN16="Less than 12%",0,0))) | BP16: No | BQ16: =IF(BP16="No",10,0) | BR16: No | BS16: =IF(BR16="NO",5,0) | BT16: Less than 1.5 | BU16: =IF(BT16="Above 2",0,IF(BT16="Between 1.5 to 2",5,IF(BT16="Less than 1.5",10,0))) | BV16: Above 70% | BW16: =IF(BV16="Above 70%",10,IF(BV16="Between 50% to 70%",5,IF(BV16="Less than 50%",0,IF(BV16="Negative",-10,IF(BV16="Less than 50% and Borrowings are increasing",-5,0))))) | BX16: Less than 0.7 | BY16: =IF(BX16="More than 1.2",-10,IF(BX16="Between 0.7 to 1.2",0,IF(BX16="Less than 0.7",10,0))) | BZ16: No | CA16: =IF(BZ16="Yes",-10,0) | CB16: Less than 15% | CC16: =IF(CB16="More than 15%",-10,IF(CB16="Less than 15%",10,0)) | CD16: No | CE16: =IF(CD16="Yes, more than 10%",-10,IF(CD16="No",10,0))
A17: =IF(B17=0,"",RANK(B17,$B$2:$B$184,0)) | B17: =SUM(N17,Y17,AA17,AC17,AE17,AG17,AI17,AK17,AM17,AO17,AQ17,AS17,AU17,AW17,AY17,BA17,BC17,BE17,BG17,BI17,BK17,BM17,BO17,BQ17,BS17,BU17,BW17,BY17,CA17,CC17,CE17) | C17: ASIANHOTNR | D17: Asian Hotels (north) Limited | E17: services | F17: hotels | G17: smallcap | H17: 1643.3 | I17: 388.55 | J17: 0.8 | K17: 33702 | L17: 38 | M17: Outperforming | N17: =IF(M17="Underperforming",-5,IF(L17>=95,15,IF(L17>=90,10,IF(L17>=80,5,0)))) | O17: 69.76 | P17: 38.62 | Q17: 276.77 | R17: Near 52W High Breakout | S17: Nifty 50 | T17: -8.33 | U17: 19.57 | V17: 30.44 | W17: 10.51 | X17: Growing Industry | Y17: =IF(X17="Growing Industry",10,IF(X17="Cyclical in an Upturn",5,0)) | Z17: Too Many Players with High ROCE | AA17: =IF(Z17="Monopoly",10,IF(Z17="Oligopoly",5,IF(Z17="Duopoly that cooperate",10,IF(Z17="Duopoly that compete",5,IF(Z17="Too many players with High ROCE",5,0))))) | AB17: No | AC17: =IF(AB17="No",5,0) | AD17: Tailwind | AE17: =IF(AD17="Tailwind",10,0) | AF17: Structural (10 Years Consistency) | AG17: =IF(AF17="Structural (10 Years Consistency)",10,IF(AF17="Shallow Cyclical (2 to 3 years growth)",5,0)) | AH17: No | AI17: =IF(AH17="Yes due to Product Mix change or Operating Leverage",10,IF(AH17="Yes, these are peak margins",-5,IF(AH17="No",5,0))) | AJ17: Stable | AK17: =IF(AJ17="Stable",10,0) | AL17: Yes | AM17: =IF(AL17="Yes",10,0) | AN17: B2B | AO17: =IF(AN17="B2C",10,IF(AN17="B2B",5,0)) | AP17: Yes | AQ17: =IF(AP17="Yes",10,0) | AR17: Higher One Time, Lower Annuity | AS17: =IF(AR17="Fully Annuity",10,IF(AR17="Higher Annuity, Lower One Time",5,IF(AR17="Higher One Time, Lower Annuity",3,0))) | AT17: Good | AU17: =IF(AT17="Good",10,0) | AV17: Yes for more than 2 years | AW17: =IF(AV17="Yes for more than 2 years",10,IF(AV17="Yes only for next 1 to 2 years",5,0)) | AX17: 20 to 40 | AY17: =IF(AX17="Above 40",20,IF(AX17="20 to 40",10,IF(AX17="0 to 20",-5,0))) | AZ17: Between 50 to 75 | BA17: =IF(AZ17="Between 50 to 75",10,IF(AZ17="Above 75",0,0)) | BB17: Stage 2 | BC17: =IF(BB17="Stage 2",20,IF(BB17="Stage 1",0,IF(BB17="Stage 3",5,IF(BB17="Stage 4",-5,0)))) | BD17: Positive Trend | BE17: =IF(BD17="Positive Trend",20,IF(BD17="Negative Trend",-10,0)) | BF17: Uptrend | BG17: =IF(BF17="Uptrend",10,IF(BF17="Sideways",5,0)) | BH17: Uptrend | BI17: =IF(BH17="Uptrend",10,IF(BH17="Sideways",5,0)) | BJ17: Blue sky scenario | BK17: =IF(BJ17="Overhead supply in last 2 years in last 2 years",-5,IF(BJ17="Close to 52 week high or retracement",5,IF(BJ17="Blue sky scenario",10,IF(BJ17="Long term Downtrend",-10,0)))) | BL17: Yes | BM17: =IF(BL17="Yes",10,0) | BN17: More than 20% | BO17: =IF(BN17="More than 20%",10,IF(BN17="Between 12 to 20%",5,IF(BN17="Less than 12%",0,0))) | BP17: No | BQ17: =IF(BP17="No",10,0) | BR17: No | BS17: =IF(BR17="NO",5,0) | BT17: Less than 1.5 | BU17: =IF(BT17="Above 2",0,IF(BT17="Between 1.5 to 2",5,IF(BT17="Less than 1.5",10,0))) | BV17: Above 70% | BW17: =IF(BV17="Above 70%",10,IF(BV17="Between 50% to 70%",5,IF(BV17="Less than 50%",0,IF(BV17="Negative",-10,IF(BV17="Less than 50% and Borrowings are increasing",-5,0))))) | BX17: Less than 0.7 | BY17: =IF(BX17="More than 1.2",-10,IF(BX17="Between 0.7 to 1.2",0,IF(BX17="Less than 0.7",10,0))) | BZ17: No | CA17: =IF(BZ17="Yes",-10,0) | CB17: Less than 15% | CC17: =IF(CB17="More than 15%",-10,IF(CB17="Less than 15%",10,0)) | CD17: No | CE17: =IF(CD17="Yes, more than 10%",-10,IF(CD17="No",10,0))
A18: =IF(B18=0,"",RANK(B18,$B$2:$B$184,0)) | B18: =SUM(N18,Y18,AA18,AC18,AE18,AG18,AI18,AK18,AM18,AO18,AQ18,AS18,AU18,AW18,AY18,BA18,BC18,BE18,BG18,BI18,BK18,BM18,BO18,BQ18,BS18,BU18,BW18,BY18,CA18,CC18,CE18) | C18: NRL | D18: Nupur Recyclers Ltd | E18: services | F18: trading | G18: smallcap | H18: 934.85 | I18: 133.98 | J18: -1.01 | K18: 80531 | L18: 82 | M18: Outperforming | N18: =IF(M18="Underperforming",-5,IF(L18>=95,15,IF(L18>=90,10,IF(L18>=80,5,0)))) | O18: 89.02 | P18: 71.15 | Q18: 110.48 | R18: Near 52W High Breakout | S18: Nifty 50 | T18: -8.33 | U18: 72.54 | V18: 88.22 | W18: 31.27 | X18: Growing Industry | Y18: =IF(X18="Growing Industry",10,IF(X18="Cyclical in an Upturn",5,0)) | Z18: Too Many Players with High ROCE | AA18: =IF(Z18="Monopoly",10,IF(Z18="Oligopoly",5,IF(Z18="Duopoly that cooperate",10,IF(Z18="Duopoly that compete",5,IF(Z18="Too many players with High ROCE",5,0))))) | AB18: No | AC18: =IF(AB18="No",5,0) | AD18: Tailwind | AE18: =IF(AD18="Tailwind",10,0) | AF18: Structural (10 Years Consistency) | AG18: =IF(AF18="Structural (10 Years Consistency)",10,IF(AF18="Shallow Cyclical (2 to 3 years growth)",5,0)) | AH18: No | AI18: =IF(AH18="Yes due to Product Mix change or Operating Leverage",10,IF(AH18="Yes, these are peak margins",-5,IF(AH18="No",5,0))) | AJ18: Stable | AK18: =IF(AJ18="Stable",10,0) | AL18: Yes | AM18: =IF(AL18="Yes",10,0) | AN18: B2B | AO18: =IF(AN18="B2C",10,IF(AN18="B2B",5,0)) | AP18: Yes | AQ18: =IF(AP18="Yes",10,0) | AR18: Higher One Time, Lower Annuity | AS18: =IF(AR18="Fully Annuity",10,IF(AR18="Higher Annuity, Lower One Time",5,IF(AR18="Higher One Time, Lower Annuity",3,0))) | AT18: Good | AU18: =IF(AT18="Good",10,0) | AV18: Yes for more than 2 years | AW18: =IF(AV18="Yes for more than 2 years",10,IF(AV18="Yes only for next 1 to 2 years",5,0)) | AX18: Above 40 | AY18: =IF(AX18="Above 40",20,IF(AX18="20 to 40",10,IF(AX18="0 to 20",-5,0))) | AZ18: Above 75 | BA18: =IF(AZ18="Between 50 to 75",10,IF(AZ18="Above 75",0,0)) | BB18: Stage 2 | BC18: =IF(BB18="Stage 2",20,IF(BB18="Stage 1",0,IF(BB18="Stage 3",5,IF(BB18="Stage 4",-5,0)))) | BD18: Positive Trend | BE18: =IF(BD18="Positive Trend",20,IF(BD18="Negative Trend",-10,0)) | BF18: Uptrend | BG18: =IF(BF18="Uptrend",10,IF(BF18="Sideways",5,0)) | BH18: Uptrend | BI18: =IF(BH18="Uptrend",10,IF(BH18="Sideways",5,0)) | BJ18: Blue sky scenario | BK18: =IF(BJ18="Overhead supply in last 2 years in last 2 years",-5,IF(BJ18="Close to 52 week high or retracement",5,IF(BJ18="Blue sky scenario",10,IF(BJ18="Long term Downtrend",-10,0)))) | BL18: Yes | BM18: =IF(BL18="Yes",10,0) | BN18: More than 20% | BO18: =IF(BN18="More than 20%",10,IF(BN18="Between 12 to 20%",5,IF(BN18="Less than 12%",0,0))) | BP18: No | BQ18: =IF(BP18="No",10,0) | BR18: Yes | BS18: =IF(BR18="NO",5,0) | BT18: Less than 1.5 | BU18: =IF(BT18="Above 2",0,IF(BT18="Between 1.5 to 2",5,IF(BT18="Less than 1.5",10,0))) | BV18: Above 70% | BW18: =IF(BV18="Above 70%",10,IF(BV18="Between 50% to 70%",5,IF(BV18="Less than 50%",0,IF(BV18="Negative",-10,IF(BV18="Less than 50% and Borrowings are increasing",-5,0))))) | BX18: Less than 0.7 | BY18: =IF(BX18="More than 1.2",-10,IF(BX18="Between 0.7 to 1.2",0,IF(BX18="Less than 0.7",10,0))) | BZ18: No | CA18: =IF(BZ18="Yes",-10,0) | CB18: Less than 15% | CC18: =IF(CB18="More than 15%",-10,IF(CB18="Less than 15%",10,0)) | CD18: No | CE18: =IF(CD18="Yes, more than 10%",-10,IF(CD18="No",10,0))
A19: =IF(B19=0,"",RANK(B19,$B$2:$B$184,0)) | B19: =SUM(N19,Y19,AA19,AC19,AE19,AG19,AI19,AK19,AM19,AO19,AQ19,AS19,AU19,AW19,AY19,BA19,BC19,BE19,BG19,BI19,BK19,BM19,BO19,BQ19,BS19,BU19,BW19,BY19,CA19,CC19,CE19) | C19: NITINSPIN | D19: Nitin Spinners Limited | E19: textiles | F19: textiles - cotton/blended | G19: smallcap | H19: 3615.79 | I19: 628 | J19: -2.36 | K19: 122404 | L19: 54 | M19: Outperforming | N19: =IF(M19="Underperforming",-5,IF(L19>=95,15,IF(L19>=90,10,IF(L19>=80,5,0)))) | O19: 69.96 | P19: 63.17 | Q19: 514.76 | R19: Near 52W High Breakout | S19: Nifty 50 | T19: -8.33 | U19: 79.16 | V19: 95.44 | W19: 16.42 | X19: Growing Industry | Y19: =IF(X19="Growing Industry",10,IF(X19="Cyclical in an Upturn",5,0)) | Z19: Too Many Players with High ROCE | AA19: =IF(Z19="Monopoly",10,IF(Z19="Oligopoly",5,IF(Z19="Duopoly that cooperate",10,IF(Z19="Duopoly that compete",5,IF(Z19="Too many players with High ROCE",5,0))))) | AB19: No | AC19: =IF(AB19="No",5,0) | AD19: Tailwind | AE19: =IF(AD19="Tailwind",10,0) | AF19: Structural (10 Years Consistency) | AG19: =IF(AF19="Structural (10 Years Consistency)",10,IF(AF19="Shallow Cyclical (2 to 3 years growth)",5,0)) | AH19: No | AI19: =IF(AH19="Yes due to Product Mix change or Operating Leverage",10,IF(AH19="Yes, these are peak margins",-5,IF(AH19="No",5,0))) | AJ19: Stable | AK19: =IF(AJ19="Stable",10,0) | AL19: Yes | AM19: =IF(AL19="Yes",10,0) | AN19: B2B | AO19: =IF(AN19="B2C",10,IF(AN19="B2B",5,0)) | AP19: Yes | AQ19: =IF(AP19="Yes",10,0) | AR19: Higher One Time, Lower Annuity | AS19: =IF(AR19="Fully Annuity",10,IF(AR19="Higher Annuity, Lower One Time",5,IF(AR19="Higher One Time, Lower Annuity",3,0))) | AT19: Good | AU19: =IF(AT19="Good",10,0) | AV19: Yes for more than 2 years | AW19: =IF(AV19="Yes for more than 2 years",10,IF(AV19="Yes only for next 1 to 2 years",5,0)) | AX19: Above 40 | AY19: =IF(AX19="Above 40",20,IF(AX19="20 to 40",10,IF(AX19="0 to 20",-5,0))) | AZ19: Between 50 to 75 | BA19: =IF(AZ19="Between 50 to 75",10,IF(AZ19="Above 75",0,0)) | BB19: Stage 2 | BC19: =IF(BB19="Stage 2",20,IF(BB19="Stage 1",0,IF(BB19="Stage 3",5,IF(BB19="Stage 4",-5,0)))) | BD19: Positive Trend | BE19: =IF(BD19="Positive Trend",20,IF(BD19="Negative Trend",-10,0)) | BF19: Uptrend | BG19: =IF(BF19="Uptrend",10,IF(BF19="Sideways",5,0)) | BH19: Uptrend | BI19: =IF(BH19="Uptrend",10,IF(BH19="Sideways",5,0)) | BJ19: Blue sky scenario | BK19: =IF(BJ19="Overhead supply in last 2 years in last 2 years",-5,IF(BJ19="Close to 52 week high or retracement",5,IF(BJ19="Blue sky scenario",10,IF(BJ19="Long term Downtrend",-10,0)))) | BL19: Yes | BM19: =IF(BL19="Yes",10,0) | BN19: More than 20% | BO19: =IF(BN19="More than 20%",10,IF(BN19="Between 12 to 20%",5,IF(BN19="Less than 12%",0,0))) | BP19: No | BQ19: =IF(BP19="No",10,0) | BR19: No | BS19: =IF(BR19="NO",5,0) | BT19: Less than 1.5 | BU19: =IF(BT19="Above 2",0,IF(BT19="Between 1.5 to 2",5,IF(BT19="Less than 1.5",10,0))) | BV19: Above 70% | BW19: =IF(BV19="Above 70%",10,IF(BV19="Between 50% to 70%",5,IF(BV19="Less than 50%",0,IF(BV19="Negative",-10,IF(BV19="Less than 50% and Borrowings are increasing",-5,0))))) | BX19: Between 0.7 to 1.2 | BY19: =IF(BX19="More than 1.2",-10,IF(BX19="Between 0.7 to 1.2",0,IF(BX19="Less than 0.7",10,0))) | BZ19: No | CA19: =IF(BZ19="Yes",-10,0) | CB19: Less than 15% | CC19: =IF(CB19="More than 15%",-10,IF(CB19="Less than 15%",10,0)) | CD19: No | CE19: =IF(CD19="Yes, more than 10%",-10,IF(CD19="No",10,0))
A20: =IF(B20=0,"",RANK(B20,$B$2:$B$184,0)) | B20: =SUM(N20,Y20,AA20,AC20,AE20,AG20,AI20,AK20,AM20,AO20,AQ20,AS20,AU20,AW20,AY20,BA20,BC20,BE20,BG20,BI20,BK20,BM20,BO20,BQ20,BS20,BU20,BW20,BY20,CA20,CC20,CE20) | C20: GAYAPROJ | D20: Gayatri Projects Limited | E20: realty | F20: construction | G20: smallcap | H20: 1214.14 | I20: 24.85 | J20: -4.97 | K20: 1543449 | N20: =IF(M20="Underperforming",-5,IF(L20>=95,15,IF(L20>=90,10,IF(L20>=80,5,0)))) | O20: 67.38 | P20: 29.31 | Q20: 19.39 | R20: Volume Spike & Near 52W High Breakout | S20: Nifty Realty | X20: Growing Industry | Y20: =IF(X20="Growing Industry",10,IF(X20="Cyclical in an Upturn",5,0)) | Z20: Too Many Players with High ROCE | AA20: =IF(Z20="Monopoly",10,IF(Z20="Oligopoly",5,IF(Z20="Duopoly that cooperate",10,IF(Z20="Duopoly that compete",5,IF(Z20="Too many players with High ROCE",5,0))))) | AB20: No | AC20: =IF(AB20="No",5,0) | AD20: Tailwind | AE20: =IF(AD20="Tailwind",10,0) | AF20: Structural (10 Years Consistency) | AG20: =IF(AF20="Structural (10 Years Consistency)",10,IF(AF20="Shallow Cyclical (2 to 3 years growth)",5,0)) | AH20: No | AI20: =IF(AH20="Yes due to Product Mix change or Operating Leverage",10,IF(AH20="Yes, these are peak margins",-5,IF(AH20="No",5,0))) | AJ20: Stable | AK20: =IF(AJ20="Stable",10,0) | AL20: Yes | AM20: =IF(AL20="Yes",10,0) | AN20: B2B | AO20: =IF(AN20="B2C",10,IF(AN20="B2B",5,0)) | AP20: Yes | AQ20: =IF(AP20="Yes",10,0) | AR20: Higher One Time, Lower Annuity | AS20: =IF(AR20="Fully Annuity",10,IF(AR20="Higher Annuity, Lower One Time",5,IF(AR20="Higher One Time, Lower Annuity",3,0))) | AT20: Good | AU20: =IF(AT20="Good",10,0) | AV20: Yes for more than 2 years | AW20: =IF(AV20="Yes for more than 2 years",10,IF(AV20="Yes only for next 1 to 2 years",5,0)) | AX20: 20 to 40 | AY20: =IF(AX20="Above 40",20,IF(AX20="20 to 40",10,IF(AX20="0 to 20",-5,0))) | AZ20: Between 50 to 75 | BA20: =IF(AZ20="Between 50 to 75",10,IF(AZ20="Above 75",0,0)) | BB20: Stage 2 | BC20: =IF(BB20="Stage 2",20,IF(BB20="Stage 1",0,IF(BB20="Stage 3",5,IF(BB20="Stage 4",-5,0)))) | BD20: Positive Trend | BE20: =IF(BD20="Positive Trend",20,IF(BD20="Negative Trend",-10,0)) | BF20: Uptrend | BG20: =IF(BF20="Uptrend",10,IF(BF20="Sideways",5,0)) | BH20: Uptrend | BI20: =IF(BH20="Uptrend",10,IF(BH20="Sideways",5,0)) | BJ20: Blue sky scenario | BK20: =IF(BJ20="Overhead supply in last 2 years in last 2 years",-5,IF(BJ20="Close to 52 week high or retracement",5,IF(BJ20="Blue sky scenario",10,IF(BJ20="Long term Downtrend",-10,0)))) | BL20: Yes | BM20: =IF(BL20="Yes",10,0) | BN20: More than 20% | BO20: =IF(BN20="More than 20%",10,IF(BN20="Between 12 to 20%",5,IF(BN20="Less than 12%",0,0))) | BP20: No | BQ20: =IF(BP20="No",10,0) | BR20: No | BS20: =IF(BR20="NO",5,0) | BT20: Less than 1.5 | BU20: =IF(BT20="Above 2",0,IF(BT20="Between 1.5 to 2",5,IF(BT20="Less than 1.5",10,0))) | BV20: Above 70% | BW20: =IF(BV20="Above 70%",10,IF(BV20="Between 50% to 70%",5,IF(BV20="Less than 50%",0,IF(BV20="Negative",-10,IF(BV20="Less than 50% and Borrowings are increasing",-5,0))))) | BX20: Less than 0.7 | BY20: =IF(BX20="More than 1.2",-10,IF(BX20="Between 0.7 to 1.2",0,IF(BX20="Less than 0.7",10,0))) | BZ20: No | CA20: =IF(BZ20="Yes",-10,0) | CB20: Less than 15% | CC20: =IF(CB20="More than 15%",-10,IF(CB20="Less than 15%",10,0)) | CD20: No | CE20: =IF(CD20="Yes, more than 10%",-10,IF(CD20="No",10,0))
A21: =IF(B21=0,"",RANK(B21,$B$2:$B$184,0)) | B21: =SUM(N21,Y21,AA21,AC21,AE21,AG21,AI21,AK21,AM21,AO21,AQ21,AS21,AU21,AW21,AY21,BA21,BC21,BE21,BG21,BI21,BK21,BM21,BO21,BQ21,BS21,BU21,BW21,BY21,CA21,CC21,CE21) | C21: IOLCP | D21: Iol Chemicals And Pharmaceuticals Limited | E21: healthcare | F21: pharmaceuticals - indian - bulk drugs & formln | G21: midcap | H21: 5269.41 | I21: 194.57 | J21: 8.38 | K21: 8624277 | L21: 77 | M21: Outperforming | N21: =IF(M21="Underperforming",-5,IF(L21>=95,15,IF(L21>=90,10,IF(L21>=80,5,0)))) | O21: 75.38 | P21: 80.98 | Q21: 144.38 | R21: Near 52W High Breakout | S21: Nifty Pharma | T21: 15.25 | U21: 64.44 | V21: 42.68 | W21: 26.83 | X21: Growing Industry | Y21: =IF(X21="Growing Industry",10,IF(X21="Cyclical in an Upturn",5,0)) | Z21: Too Many Players with High ROCE | AA21: =IF(Z21="Monopoly",10,IF(Z21="Oligopoly",5,IF(Z21="Duopoly that cooperate",10,IF(Z21="Duopoly that compete",5,IF(Z21="Too many players with High ROCE",5,0))))) | AB21: Yes | AC21: =IF(AB21="No",5,0) | AD21: Tailwind | AE21: =IF(AD21="Tailwind",10,0) | AF21: Structural (10 Years Consistency) | AG21: =IF(AF21="Structural (10 Years Consistency)",10,IF(AF21="Shallow Cyclical (2 to 3 years growth)",5,0)) | AH21: No | AI21: =IF(AH21="Yes due to Product Mix change or Operating Leverage",10,IF(AH21="Yes, these are peak margins",-5,IF(AH21="No",5,0))) | AJ21: Stable | AK21: =IF(AJ21="Stable",10,0) | AL21: Yes | AM21: =IF(AL21="Yes",10,0) | AN21: B2B | AO21: =IF(AN21="B2C",10,IF(AN21="B2B",5,0)) | AP21: Yes | AQ21: =IF(AP21="Yes",10,0) | AR21: Higher Annuity, Lower One Time | AS21: =IF(AR21="Fully Annuity",10,IF(AR21="Higher Annuity, Lower One Time",5,IF(AR21="Higher One Time, Lower Annuity",3,0))) | AT21: Good | AU21: =IF(AT21="Good",10,0) | AV21: Yes for more than 2 years | AW21: =IF(AV21="Yes for more than 2 years",10,IF(AV21="Yes only for next 1 to 2 years",5,0)) | AX21: Above 40 | AY21: =IF(AX21="Above 40",20,IF(AX21="20 to 40",10,IF(AX21="0 to 20",-5,0))) | AZ21: Above 75 | BA21: =IF(AZ21="Between 50 to 75",10,IF(AZ21="Above 75",0,0)) | BB21: Stage 2 | BC21: =IF(BB21="Stage 2",20,IF(BB21="Stage 1",0,IF(BB21="Stage 3",5,IF(BB21="Stage 4",-5,0)))) | BD21: Positive Trend | BE21: =IF(BD21="Positive Trend",20,IF(BD21="Negative Trend",-10,0)) | BF21: Uptrend | BG21: =IF(BF21="Uptrend",10,IF(BF21="Sideways",5,0)) | BH21: Uptrend | BI21: =IF(BH21="Uptrend",10,IF(BH21="Sideways",5,0)) | BJ21: Blue sky scenario | BK21: =IF(BJ21="Overhead supply in last 2 years in last 2 years",-5,IF(BJ21="Close to 52 week high or retracement",5,IF(BJ21="Blue sky scenario",10,IF(BJ21="Long term Downtrend",-10,0)))) | BL21: Yes | BM21: =IF(BL21="Yes",10,0) | BN21: More than 20% | BO21: =IF(BN21="More than 20%",10,IF(BN21="Between 12 to 20%",5,IF(BN21="Less than 12%",0,0))) | BP21: No | BQ21: =IF(BP21="No",10,0) | BR21: No | BS21: =IF(BR21="NO",5,0) | BT21: Less than 1.5 | BU21: =IF(BT21="Above 2",0,IF(BT21="Between 1.5 to 2",5,IF(BT21="Less than 1.5",10,0))) | BV21: Above 70% | BW21: =IF(BV21="Above 70%",10,IF(BV21="Between 50% to 70%",5,IF(BV21="Less than 50%",0,IF(BV21="Negative",-10,IF(BV21="Less than 50% and Borrowings are increasing",-5,0))))) | BX21: Less than 0.7 | BY21: =IF(BX21="More than 1.2",-10,IF(BX21="Between 0.7 to 1.2",0,IF(BX21="Less than 0.7",10,0))) | BZ21: No | CA21: =IF(BZ21="Yes",-10,0) | CB21: Less than 15% | CC21: =IF(CB21="More than 15%",-10,IF(CB21="Less than 15%",10,0)) | CD21: No | CE21: =IF(CD21="Yes, more than 10%",-10,IF(CD21="No",10,0))
A22: =IF(B22=0,"",RANK(B22,$B$2:$B$184,0)) | B22: =SUM(N22,Y22,AA22,AC22,AE22,AG22,AI22,AK22,AM22,AO22,AQ22,AS22,AU22,AW22,AY22,BA22,BC22,BE22,BG22,BI22,BK22,BM22,BO22,BQ22,BS22,BU22,BW22,BY22,CA22,CC22,CE22) | C22: MOREPENLAB | D22: Morepen Laboratories Limited | E22: healthcare | F22: pharmaceuticals - indian - bulk drugs & formln | G22: midcap | H22: 5820.36 | I22: 114.73 | J22: 8.01 | K22: 39424210 | L22: 95 | M22: Outperforming | N22: =IF(M22="Underperforming",-5,IF(L22>=95,15,IF(L22>=90,10,IF(L22>=80,5,0)))) | O22: 86.3 | P22: 54.03 | Q22: 85.97 | R22: Near 52W High Breakout | S22: Nifty Pharma | T22: 15.25 | U22: 111.91 | V22: 83.87 | W22: 52.68 | X22: Growing Industry | Y22: =IF(X22="Growing Industry",10,IF(X22="Cyclical in an Upturn",5,0)) | Z22: Too Many Players with High ROCE | AA22: =IF(Z22="Monopoly",10,IF(Z22="Oligopoly",5,IF(Z22="Duopoly that cooperate",10,IF(Z22="Duopoly that compete",5,IF(Z22="Too many players with High ROCE",5,0))))) | AB22: Yes | AC22: =IF(AB22="No",5,0) | AD22: Tailwind | AE22: =IF(AD22="Tailwind",10,0) | AF22: Structural (10 Years Consistency) | AG22: =IF(AF22="Structural (10 Years Consistency)",10,IF(AF22="Shallow Cyclical (2 to 3 years growth)",5,0)) | AH22: No | AI22: =IF(AH22="Yes due to Product Mix change or Operating Leverage",10,IF(AH22="Yes, these are peak margins",-5,IF(AH22="No",5,0))) | AJ22: Stable | AK22: =IF(AJ22="Stable",10,0) | AL22: Yes | AM22: =IF(AL22="Yes",10,0) | AN22: B2B | AO22: =IF(AN22="B2C",10,IF(AN22="B2B",5,0)) | AP22: Yes | AQ22: =IF(AP22="Yes",10,0) | AR22: Higher Annuity, Lower One Time | AS22: =IF(AR22="Fully Annuity",10,IF(AR22="Higher Annuity, Lower One Time",5,IF(AR22="Higher One Time, Lower Annuity",3,0))) | AT22: Good | AU22: =IF(AT22="Good",10,0) | AV22: Yes for more than 2 years | AW22: =IF(AV22="Yes for more than 2 years",10,IF(AV22="Yes only for next 1 to 2 years",5,0)) | AX22: Above 40 | AY22: =IF(AX22="Above 40",20,IF(AX22="20 to 40",10,IF(AX22="0 to 20",-5,0))) | AZ22: Above 75 | BA22: =IF(AZ22="Between 50 to 75",10,IF(AZ22="Above 75",0,0)) | BB22: Stage 2 | BC22: =IF(BB22="Stage 2",20,IF(BB22="Stage 1",0,IF(BB22="Stage 3",5,IF(BB22="Stage 4",-5,0)))) | BD22: Positive Trend | BE22: =IF(BD22="Positive Trend",20,IF(BD22="Negative Trend",-10,0)) | BF22: Uptrend | BG22: =IF(BF22="Uptrend",10,IF(BF22="Sideways",5,0)) | BH22: Uptrend | BI22: =IF(BH22="Uptrend",10,IF(BH22="Sideways",5,0)) | BJ22: Blue sky scenario | BK22: =IF(BJ22="Overhead supply in last 2 years in last 2 years",-5,IF(BJ22="Close to 52 week high or retracement",5,IF(BJ22="Blue sky scenario",10,IF(BJ22="Long term Downtrend",-10,0)))) | BL22: Yes | BM22: =IF(BL22="Yes",10,0) | BN22: More than 20% | BO22: =IF(BN22="More than 20%",10,IF(BN22="Between 12 to 20%",5,IF(BN22="Less than 12%",0,0))) | BP22: No | BQ22: =IF(BP22="No",10,0) | BR22: Yes | BS22: =IF(BR22="NO",5,0) | BT22: Above 2 | BU22: =IF(BT22="Above 2",0,IF(BT22="Between 1.5 to 2",5,IF(BT22="Less than 1.5",10,0))) | BV22: Above 70% | BW22: =IF(BV22="Above 70%",10,IF(BV22="Between 50% to 70%",5,IF(BV22="Less than 50%",0,IF(BV22="Negative",-10,IF(BV22="Less than 50% and Borrowings are increasing",-5,0))))) | BX22: Less than 0.7 | BY22: =IF(BX22="More than 1.2",-10,IF(BX22="Between 0.7 to 1.2",0,IF(BX22="Less than 0.7",10,0))) | BZ22: No | CA22: =IF(BZ22="Yes",-10,0) | CB22: Less than 15% | CC22: =IF(CB22="More than 15%",-10,IF(CB22="Less than 15%",10,0)) | CD22: No | CE22: =IF(CD22="Yes, more than 10%",-10,IF(CD22="No",10,0))
A23: =IF(B23=0,"",RANK(B23,$B$2:$B$184,0)) | B23: =SUM(N23,Y23,AA23,AC23,AE23,AG23,AI23,AK23,AM23,AO23,AQ23,AS23,AU23,AW23,AY23,BA23,BC23,BE23,BG23,BI23,BK23,BM23,BO23,BQ23,BS23,BU23,BW23,BY23,CA23,CC23,CE23) | C23: GPTHEALTH | D23: GPT Healthcare Ltd | E23: healthcare | F23: healthcare | G23: smallcap | H23: 1308.36 | I23: 163.3 | J23: 2.41 | K23: 135814 | L23: 20 | M23: Underperforming | N23: =IF(M23="Underperforming",-5,IF(L23>=95,15,IF(L23>=90,10,IF(L23>=80,5,0)))) | O23: 61.67 | P23: 49.79 | Q23: 140.4 | R23: Near 52W High Breakout | S23: Nifty Pharma | T23: 15.25 | U23: 10.69 | V23: -3.96 | W23: 5.11 | X23: Growing Industry | Y23: =IF(X23="Growing Industry",10,IF(X23="Cyclical in an Upturn",5,0)) | Z23: Too Many Players with High ROCE | AA23: =IF(Z23="Monopoly",10,IF(Z23="Oligopoly",5,IF(Z23="Duopoly that cooperate",10,IF(Z23="Duopoly that compete",5,IF(Z23="Too many players with High ROCE",5,0))))) | AB23: Yes | AC23: =IF(AB23="No",5,0) | AD23: Tailwind | AE23: =IF(AD23="Tailwind",10,0) | AF23: Structural (10 Years Consistency) | AG23: =IF(AF23="Structural (10 Years Consistency)",10,IF(AF23="Shallow Cyclical (2 to 3 years growth)",5,0)) | AH23: No | AI23: =IF(AH23="Yes due to Product Mix change or Operating Leverage",10,IF(AH23="Yes, these are peak margins",-5,IF(AH23="No",5,0))) | AJ23: Stable | AK23: =IF(AJ23="Stable",10,0) | AL23: Yes | AM23: =IF(AL23="Yes",10,0) | AN23: B2B | AO23: =IF(AN23="B2C",10,IF(AN23="B2B",5,0)) | AP23: Yes | AQ23: =IF(AP23="Yes",10,0) | AR23: Higher Annuity, Lower One Time | AS23: =IF(AR23="Fully Annuity",10,IF(AR23="Higher Annuity, Lower One Time",5,IF(AR23="Higher One Time, Lower Annuity",3,0))) | AT23: Good | AU23: =IF(AT23="Good",10,0) | AV23: Yes for more than 2 years | AW23: =IF(AV23="Yes for more than 2 years",10,IF(AV23="Yes only for next 1 to 2 years",5,0)) | AX23: Above 40 | AY23: =IF(AX23="Above 40",20,IF(AX23="20 to 40",10,IF(AX23="0 to 20",-5,0))) | AZ23: Between 50 to 75 | BA23: =IF(AZ23="Between 50 to 75",10,IF(AZ23="Above 75",0,0)) | BB23: Stage 2 | BC23: =IF(BB23="Stage 2",20,IF(BB23="Stage 1",0,IF(BB23="Stage 3",5,IF(BB23="Stage 4",-5,0)))) | BD23: Positive Trend | BE23: =IF(BD23="Positive Trend",20,IF(BD23="Negative Trend",-10,0)) | BF23: Uptrend | BG23: =IF(BF23="Uptrend",10,IF(BF23="Sideways",5,0)) | BH23: Uptrend | BI23: =IF(BH23="Uptrend",10,IF(BH23="Sideways",5,0)) | BJ23: Close to 52 week high or retracement | BK23: =IF(BJ23="Overhead supply in last 2 years in last 2 years",-5,IF(BJ23="Close to 52 week high or retracement",5,IF(BJ23="Blue sky scenario",10,IF(BJ23="Long term Downtrend",-10,0)))) | BL23: Yes | BM23: =IF(BL23="Yes",10,0) | BN23: More than 20% | BO23: =IF(BN23="More than 20%",10,IF(BN23="Between 12 to 20%",5,IF(BN23="Less than 12%",0,0))) | BP23: No | BQ23: =IF(BP23="No",10,0) | BR23: No | BS23: =IF(BR23="NO",5,0) | BT23: Less than 1.5 | BU23: =IF(BT23="Above 2",0,IF(BT23="Between 1.5 to 2",5,IF(BT23="Less than 1.5",10,0))) | BV23: Above 70% | BW23: =IF(BV23="Above 70%",10,IF(BV23="Between 50% to 70%",5,IF(BV23="Less than 50%",0,IF(BV23="Negative",-10,IF(BV23="Less than 50% and Borrowings are increasing",-5,0))))) | BX23: Less than 0.7 | BY23: =IF(BX23="More than 1.2",-10,IF(BX23="Between 0.7 to 1.2",0,IF(BX23="Less than 0.7",10,0))) | BZ23: No | CA23: =IF(BZ23="Yes",-10,0) | CB23: Less than 15% | CC23: =IF(CB23="More than 15%",-10,IF(CB23="Less than 15%",10,0)) | CD23: No | CE23: =IF(CD23="Yes, more than 10%",-10,IF(CD23="No",10,0))
A24: =IF(B24=0,"",RANK(B24,$B$2:$B$184,0)) | B24: =SUM(N24,Y24,AA24,AC24,AE24,AG24,AI24,AK24,AM24,AO24,AQ24,AS24,AU24,AW24,AY24,BA24,BC24,BE24,BG24,BI24,BK24,BM24,BO24,BQ24,BS24,BU24,BW24,BY24,CA24,CC24,CE24) | C24: AKUMS | D24: Akums Drugs & Pharmaceuticals Ltd | E24: healthcare | F24: pharmaceuticals - indian - bulk drugs & formln | G24: midcap | H24: 12050.87 | I24: 772 | J24: 0.83 | K24: 235680 | L24: 56 | M24: Outperforming | N24: =IF(M24="Underperforming",-5,IF(L24>=95,15,IF(L24>=90,10,IF(L24>=80,5,0)))) | O24: 72.94 | P24: 62.91 | Q24: 629.87 | R24: Near 52W High Breakout | S24: Nifty Pharma | T24: 15.25 | U24: 62.78 | V24: 41.24 | W24: 16.89 | X24: Growing Industry | Y24: =IF(X24="Growing Industry",10,IF(X24="Cyclical in an Upturn",5,0)) | Z24: Too Many Players with High ROCE | AA24: =IF(Z24="Monopoly",10,IF(Z24="Oligopoly",5,IF(Z24="Duopoly that cooperate",10,IF(Z24="Duopoly that compete",5,IF(Z24="Too many players with High ROCE",5,0))))) | AB24: Yes | AC24: =IF(AB24="No",5,0) | AD24: Tailwind | AE24: =IF(AD24="Tailwind",10,0) | AF24: Structural (10 Years Consistency) | AG24: =IF(AF24="Structural (10 Years Consistency)",10,IF(AF24="Shallow Cyclical (2 to 3 years growth)",5,0)) | AH24: No | AI24: =IF(AH24="Yes due to Product Mix change or Operating Leverage",10,IF(AH24="Yes, these are peak margins",-5,IF(AH24="No",5,0))) | AJ24: Stable | AK24: =IF(AJ24="Stable",10,0) | AL24: Yes | AM24: =IF(AL24="Yes",10,0) | AN24: B2B | AO24: =IF(AN24="B2C",10,IF(AN24="B2B",5,0)) | AP24: Yes | AQ24: =IF(AP24="Yes",10,0) | AR24: Higher Annuity, Lower One Time | AS24: =IF(AR24="Fully Annuity",10,IF(AR24="Higher Annuity, Lower One Time",5,IF(AR24="Higher One Time, Lower Annuity",3,0))) | AT24: Good | AU24: =IF(AT24="Good",10,0) | AV24: Yes for more than 2 years | AW24: =IF(AV24="Yes for more than 2 years",10,IF(AV24="Yes only for next 1 to 2 years",5,0)) | AX24: Above 40 | AY24: =IF(AX24="Above 40",20,IF(AX24="20 to 40",10,IF(AX24="0 to 20",-5,0))) | AZ24: Between 50 to 75 | BA24: =IF(AZ24="Between 50 to 75",10,IF(AZ24="Above 75",0,0)) | BB24: Stage 2 | BC24: =IF(BB24="Stage 2",20,IF(BB24="Stage 1",0,IF(BB24="Stage 3",5,IF(BB24="Stage 4",-5,0)))) | BD24: Positive Trend | BE24: =IF(BD24="Positive Trend",20,IF(BD24="Negative Trend",-10,0)) | BF24: Uptrend | BG24: =IF(BF24="Uptrend",10,IF(BF24="Sideways",5,0)) | BH24: Uptrend | BI24: =IF(BH24="Uptrend",10,IF(BH24="Sideways",5,0)) | BJ24: Close to 52 week high or retracement | BK24: =IF(BJ24="Overhead supply in last 2 years in last 2 years",-5,IF(BJ24="Close to 52 week high or retracement",5,IF(BJ24="Blue sky scenario",10,IF(BJ24="Long term Downtrend",-10,0)))) | BL24: Yes | BM24: =IF(BL24="Yes",10,0) | BN24: More than 20% | BO24: =IF(BN24="More than 20%",10,IF(BN24="Between 12 to 20%",5,IF(BN24="Less than 12%",0,0))) | BP24: No | BQ24: =IF(BP24="No",10,0) | BR24: Yes | BS24: =IF(BR24="NO",5,0) | BT24: Less than 1.5 | BU24: =IF(BT24="Above 2",0,IF(BT24="Between 1.5 to 2",5,IF(BT24="Less than 1.5",10,0))) | BV24: Above 70% | BW24: =IF(BV24="Above 70%",10,IF(BV24="Between 50% to 70%",5,IF(BV24="Less than 50%",0,IF(BV24="Negative",-10,IF(BV24="Less than 50% and Borrowings are increasing",-5,0))))) | BX24: Less than 0.7 | BY24: =IF(BX24="More than 1.2",-10,IF(BX24="Between 0.7 to 1.2",0,IF(BX24="Less than 0.7",10,0))) | BZ24: No | CA24: =IF(BZ24="Yes",-10,0) | CB24: Less than 15% | CC24: =IF(CB24="More than 15%",-10,IF(CB24="Less than 15%",10,0)) | CD24: No | CE24: =IF(CD24="Yes, more than 10%",-10,IF(CD24="No",10,0))
A25: =IF(B25=0,"",RANK(B25,$B$2:$B$184,0)) | B25: =SUM(N25,Y25,AA25,AC25,AE25,AG25,AI25,AK25,AM25,AO25,AQ25,AS25,AU25,AW25,AY25,BA25,BC25,BE25,BG25,BI25,BK25,BM25,BO25,BQ25,BS25,BU25,BW25,BY25,CA25,CC25,CE25) | C25: AHCL | D25: Anlon Healthcare Ltd | E25: healthcare | F25: pharmaceuticals - indian - bulk drugs & formln | G25: smallcap | H25: 1072.6 | I25: 20.04 | J25: -0.69 | K25: 46066495 | L25: 48 | M25: Outperforming | N25: =IF(M25="Underperforming",-5,IF(L25>=95,15,IF(L25>=90,10,IF(L25>=80,5,0)))) | O25: 74.4 | P25: 42.02 | Q25: 14.71 | R25: Volume Spike & Near 52W High Breakout | S25: Nifty Pharma | T25: 15.25 | U25: 48.99 | V25: 29.27 | W25: 14.16 | X25: Growing Industry | Y25: =IF(X25="Growing Industry",10,IF(X25="Cyclical in an Upturn",5,0)) | Z25: Too Many Players with High ROCE | AA25: =IF(Z25="Monopoly",10,IF(Z25="Oligopoly",5,IF(Z25="Duopoly that cooperate",10,IF(Z25="Duopoly that compete",5,IF(Z25="Too many players with High ROCE",5,0))))) | AB25: Yes | AC25: =IF(AB25="No",5,0) | AD25: Tailwind | AE25: =IF(AD25="Tailwind",10,0) | AF25: Structural (10 Years Consistency) | AG25: =IF(AF25="Structural (10 Years Consistency)",10,IF(AF25="Shallow Cyclical (2 to 3 years growth)",5,0)) | AH25: No | AI25: =IF(AH25="Yes due to Product Mix change or Operating Leverage",10,IF(AH25="Yes, these are peak margins",-5,IF(AH25="No",5,0))) | AJ25: Stable | AK25: =IF(AJ25="Stable",10,0) | AL25: Yes | AM25: =IF(AL25="Yes",10,0) | AN25: B2B | AO25: =IF(AN25="B2C",10,IF(AN25="B2B",5,0)) | AP25: Yes | AQ25: =IF(AP25="Yes",10,0) | AR25: Higher Annuity, Lower One Time | AS25: =IF(AR25="Fully Annuity",10,IF(AR25="Higher Annuity, Lower One Time",5,IF(AR25="Higher One Time, Lower Annuity",3,0))) | AT25: Good | AU25: =IF(AT25="Good",10,0) | AV25: Yes for more than 2 years | AW25: =IF(AV25="Yes for more than 2 years",10,IF(AV25="Yes only for next 1 to 2 years",5,0)) | AX25: Above 40 | AY25: =IF(AX25="Above 40",20,IF(AX25="20 to 40",10,IF(AX25="0 to 20",-5,0))) | AZ25: Between 50 to 75 | BA25: =IF(AZ25="Between 50 to 75",10,IF(AZ25="Above 75",0,0)) | BB25: Stage 2 | BC25: =IF(BB25="Stage 2",20,IF(BB25="Stage 1",0,IF(BB25="Stage 3",5,IF(BB25="Stage 4",-5,0)))) | BD25: Positive Trend | BE25: =IF(BD25="Positive Trend",20,IF(BD25="Negative Trend",-10,0)) | BF25: Uptrend | BG25: =IF(BF25="Uptrend",10,IF(BF25="Sideways",5,0)) | BH25: Uptrend | BI25: =IF(BH25="Uptrend",10,IF(BH25="Sideways",5,0)) | BJ25: Blue sky scenario | BK25: =IF(BJ25="Overhead supply in last 2 years in last 2 years",-5,IF(BJ25="Close to 52 week high or retracement",5,IF(BJ25="Blue sky scenario",10,IF(BJ25="Long term Downtrend",-10,0)))) | BL25: Yes | BM25: =IF(BL25="Yes",10,0) | BN25: More than 20% | BO25: =IF(BN25="More than 20%",10,IF(BN25="Between 12 to 20%",5,IF(BN25="Less than 12%",0,0))) | BP25: No | BQ25: =IF(BP25="No",10,0) | BR25: No | BS25: =IF(BR25="NO",5,0) | BT25: Above 2 | BU25: =IF(BT25="Above 2",0,IF(BT25="Between 1.5 to 2",5,IF(BT25="Less than 1.5",10,0))) | BV25: Above 70% | BW25: =IF(BV25="Above 70%",10,IF(BV25="Between 50% to 70%",5,IF(BV25="Less than 50%",0,IF(BV25="Negative",-10,IF(BV25="Less than 50% and Borrowings are increasing",-5,0))))) | BX25: Less than 0.7 | BY25: =IF(BX25="More than 1.2",-10,IF(BX25="Between 0.7 to 1.2",0,IF(BX25="Less than 0.7",10,0))) | BZ25: No | CA25: =IF(BZ25="Yes",-10,0) | CB25: Less than 15% | CC25: =IF(CB25="More than 15%",-10,IF(CB25="Less than 15%",10,0)) | CD25: No | CE25: =IF(CD25="Yes, more than 10%",-10,IF(CD25="No",10,0))
A26: =IF(B26=0,"",RANK(B26,$B$2:$B$184,0)) | B26: =SUM(N26,Y26,AA26,AC26,AE26,AG26,AI26,AK26,AM26,AO26,AQ26,AS26,AU26,AW26,AY26,BA26,BC26,BE26,BG26,BI26,BK26,BM26,BO26,BQ26,BS26,BU26,BW26,BY26,CA26,CC26,CE26) | C26: SAKAR | D26: Sakar Healthcare Ltd | E26: healthcare | F26: pharmaceuticals - indian - bulk drugs & formln | G26: smallcap | H26: 2531.04 | I26: 1105.4 | J26: -2.83 | K26: 164430 | L26: 87 | M26: Outperforming | N26: =IF(M26="Underperforming",-5,IF(L26>=95,15,IF(L26>=90,10,IF(L26>=80,5,0)))) | O26: 71.08 | P26: 52.36 | Q26: 845.44 | R26: Near 52W High Breakout | S26: Nifty Pharma | T26: 15.25 | U26: 221.62 | V26: 179.06 | W26: 35.01 | X26: Growing Industry | Y26: =IF(X26="Growing Industry",10,IF(X26="Cyclical in an Upturn",5,0)) | Z26: Too Many Players with High ROCE | AA26: =IF(Z26="Monopoly",10,IF(Z26="Oligopoly",5,IF(Z26="Duopoly that cooperate",10,IF(Z26="Duopoly that compete",5,IF(Z26="Too many players with High ROCE",5,0))))) | AB26: Yes | AC26: =IF(AB26="No",5,0) | AD26: Tailwind | AE26: =IF(AD26="Tailwind",10,0) | AF26: Structural (10 Years Consistency) | AG26: =IF(AF26="Structural (10 Years Consistency)",10,IF(AF26="Shallow Cyclical (2 to 3 years growth)",5,0)) | AH26: No | AI26: =IF(AH26="Yes due to Product Mix change or Operating Leverage",10,IF(AH26="Yes, these are peak margins",-5,IF(AH26="No",5,0))) | AJ26: Stable | AK26: =IF(AJ26="Stable",10,0) | AL26: Yes | AM26: =IF(AL26="Yes",10,0) | AN26: B2B | AO26: =IF(AN26="B2C",10,IF(AN26="B2B",5,0)) | AP26: Yes | AQ26: =IF(AP26="Yes",10,0) | AR26: Higher Annuity, Lower One Time | AS26: =IF(AR26="Fully Annuity",10,IF(AR26="Higher Annuity, Lower One Time",5,IF(AR26="Higher One Time, Lower Annuity",3,0))) | AT26: Good | AU26: =IF(AT26="Good",10,0) | AV26: Yes for more than 2 years | AW26: =IF(AV26="Yes for more than 2 years",10,IF(AV26="Yes only for next 1 to 2 years",5,0)) | AX26: Above 40 | AY26: =IF(AX26="Above 40",20,IF(AX26="20 to 40",10,IF(AX26="0 to 20",-5,0))) | AZ26: Between 50 to 75 | BA26: =IF(AZ26="Between 50 to 75",10,IF(AZ26="Above 75",0,0)) | BB26: Stage 2 | BC26: =IF(BB26="Stage 2",20,IF(BB26="Stage 1",0,IF(BB26="Stage 3",5,IF(BB26="Stage 4",-5,0)))) | BD26: Positive Trend | BE26: =IF(BD26="Positive Trend",20,IF(BD26="Negative Trend",-10,0)) | BF26: Uptrend | BG26: =IF(BF26="Uptrend",10,IF(BF26="Sideways",5,0)) | BH26: Uptrend | BI26: =IF(BH26="Uptrend",10,IF(BH26="Sideways",5,0)) | BJ26: Blue sky scenario | BK26: =IF(BJ26="Overhead supply in last 2 years in last 2 years",-5,IF(BJ26="Close to 52 week high or retracement",5,IF(BJ26="Blue sky scenario",10,IF(BJ26="Long term Downtrend",-10,0)))) | BL26: Yes | BM26: =IF(BL26="Yes",10,0) | BN26: More than 20% | BO26: =IF(BN26="More than 20%",10,IF(BN26="Between 12 to 20%",5,IF(BN26="Less than 12%",0,0))) | BP26: No | BQ26: =IF(BP26="No",10,0) | BR26: Yes | BS26: =IF(BR26="NO",5,0) | BT26: Above 2 | BU26: =IF(BT26="Above 2",0,IF(BT26="Between 1.5 to 2",5,IF(BT26="Less than 1.5",10,0))) | BV26: Above 70% | BW26: =IF(BV26="Above 70%",10,IF(BV26="Between 50% to 70%",5,IF(BV26="Less than 50%",0,IF(BV26="Negative",-10,IF(BV26="Less than 50% and Borrowings are increasing",-5,0))))) | BX26: Less than 0.7 | BY26: =IF(BX26="More than 1.2",-10,IF(BX26="Between 0.7 to 1.2",0,IF(BX26="Less than 0.7",10,0))) | BZ26: No | CA26: =IF(BZ26="Yes",-10,0) | CB26: Less than 15% | CC26: =IF(CB26="More than 15%",-10,IF(CB26="Less than 15%",10,0)) | CD26: No | CE26: =IF(CD26="Yes, more than 10%",-10,IF(CD26="No",10,0))
A27: =IF(B27=0,"",RANK(B27,$B$2:$B$184,0)) | B27: =SUM(N27,Y27,AA27,AC27,AE27,AG27,AI27,AK27,AM27,AO27,AQ27,AS27,AU27,AW27,AY27,BA27,BC27,BE27,BG27,BI27,BK27,BM27,BO27,BQ27,BS27,BU27,BW27,BY27,CA27,CC27,CE27) | C27: ARROWGREEN | D27: Arrow Greentech Limited | E27: plastic products | F27: plastics products | G27: smallcap | H27: 1265.2 | I27: 907.45 | J27: 8.22 | K27: 311513 | L27: 76 | M27: Outperforming | N27: =IF(M27="Underperforming",-5,IF(L27>=95,15,IF(L27>=90,10,IF(L27>=80,5,0)))) | O27: 71.9 | P27: 45.61 | Q27: 675.36 | R27: Volume Spike & Near 52W High Breakout | S27: Nifty 50 | T27: -8.33 | U27: 60.29 | V27: 74.85 | W27: 25.6 | X27: Growing Industry | Y27: =IF(X27="Growing Industry",10,IF(X27="Cyclical in an Upturn",5,0)) | Z27: Too Many Players with High ROCE | AA27: =IF(Z27="Monopoly",10,IF(Z27="Oligopoly",5,IF(Z27="Duopoly that cooperate",10,IF(Z27="Duopoly that compete",5,IF(Z27="Too many players with High ROCE",5,0))))) | AB27: No | AC27: =IF(AB27="No",5,0) | AD27: Tailwind | AE27: =IF(AD27="Tailwind",10,0) | AF27: Structural (10 Years Consistency) | AG27: =IF(AF27="Structural (10 Years Consistency)",10,IF(AF27="Shallow Cyclical (2 to 3 years growth)",5,0)) | AH27: No | AI27: =IF(AH27="Yes due to Product Mix change or Operating Leverage",10,IF(AH27="Yes, these are peak margins",-5,IF(AH27="No",5,0))) | AJ27: Stable | AK27: =IF(AJ27="Stable",10,0) | AL27: Yes | AM27: =IF(AL27="Yes",10,0) | AN27: B2B | AO27: =IF(AN27="B2C",10,IF(AN27="B2B",5,0)) | AP27: Yes | AQ27: =IF(AP27="Yes",10,0) | AR27: Higher One Time, Lower Annuity | AS27: =IF(AR27="Fully Annuity",10,IF(AR27="Higher Annuity, Lower One Time",5,IF(AR27="Higher One Time, Lower Annuity",3,0))) | AT27: Good | AU27: =IF(AT27="Good",10,0) | AV27: Yes for more than 2 years | AW27: =IF(AV27="Yes for more than 2 years",10,IF(AV27="Yes only for next 1 to 2 years",5,0)) | AX27: Above 40 | AY27: =IF(AX27="Above 40",20,IF(AX27="20 to 40",10,IF(AX27="0 to 20",-5,0))) | AZ27: Between 50 to 75 | BA27: =IF(AZ27="Between 50 to 75",10,IF(AZ27="Above 75",0,0)) | BB27: Stage 2 | BC27: =IF(BB27="Stage 2",20,IF(BB27="Stage 1",0,IF(BB27="Stage 3",5,IF(BB27="Stage 4",-5,0)))) | BD27: Positive Trend | BE27: =IF(BD27="Positive Trend",20,IF(BD27="Negative Trend",-10,0)) | BF27: Uptrend | BG27: =IF(BF27="Uptrend",10,IF(BF27="Sideways",5,0)) | BH27: Uptrend | BI27: =IF(BH27="Uptrend",10,IF(BH27="Sideways",5,0)) | BJ27: Close to 52 week high or retracement | BK27: =IF(BJ27="Overhead supply in last 2 years in last 2 years",-5,IF(BJ27="Close to 52 week high or retracement",5,IF(BJ27="Blue sky scenario",10,IF(BJ27="Long term Downtrend",-10,0)))) | BL27: Yes | BM27: =IF(BL27="Yes",10,0) | BN27: More than 20% | BO27: =IF(BN27="More than 20%",10,IF(BN27="Between 12 to 20%",5,IF(BN27="Less than 12%",0,0))) | BP27: No | BQ27: =IF(BP27="No",10,0) | BR27: No | BS27: =IF(BR27="NO",5,0) | BT27: Above 2 | BU27: =IF(BT27="Above 2",0,IF(BT27="Between 1.5 to 2",5,IF(BT27="Less than 1.5",10,0))) | BV27: Above 70% | BW27: =IF(BV27="Above 70%",10,IF(BV27="Between 50% to 70%",5,IF(BV27="Less than 50%",0,IF(BV27="Negative",-10,IF(BV27="Less than 50% and Borrowings are increasing",-5,0))))) | BX27: Less than 0.7 | BY27: =IF(BX27="More than 1.2",-10,IF(BX27="Between 0.7 to 1.2",0,IF(BX27="Less than 0.7",10,0))) | BZ27: No | CA27: =IF(BZ27="Yes",-10,0) | CB27: Less than 15% | CC27: =IF(CB27="More than 15%",-10,IF(CB27="Less than 15%",10,0)) | CD27: No | CE27: =IF(CD27="Yes, more than 10%",-10,IF(CD27="No",10,0))
A28: =IF(B28=0,"",RANK(B28,$B$2:$B$184,0)) | B28: =SUM(N28,Y28,AA28,AC28,AE28,AG28,AI28,AK28,AM28,AO28,AQ28,AS28,AU28,AW28,AY28,BA28,BC28,BE28,BG28,BI28,BK28,BM28,BO28,BQ28,BS28,BU28,BW28,BY28,CA28,CC28,CE28) | C28: CENTUM | D28: Centum Electronics Limited | E28: aerospace & defence | F28: electronics - components | G28: midcap | H28: 5919.25 | I28: 4276.1 | J28: 6.62 | K28: 90062 | L28: 51 | M28: Outperforming | N28: =IF(M28="Underperforming",-5,IF(L28>=95,15,IF(L28>=90,10,IF(L28>=80,5,0)))) | O28: 70.97 | P28: 51.81 | Q28: 3234.22 | R28: Near 52W High Breakout | S28: Nifty 50 | T28: -8.33 | U28: 51.21 | V28: 64.95 | W28: 14.91 | X28: Growing Industry | Y28: =IF(X28="Growing Industry",10,IF(X28="Cyclical in an Upturn",5,0)) | Z28: Too Many Players with High ROCE | AA28: =IF(Z28="Monopoly",10,IF(Z28="Oligopoly",5,IF(Z28="Duopoly that cooperate",10,IF(Z28="Duopoly that compete",5,IF(Z28="Too many players with High ROCE",5,0))))) | AB28: No | AC28: =IF(AB28="No",5,0) | AD28: Tailwind | AE28: =IF(AD28="Tailwind",10,0) | AF28: Structural (10 Years Consistency) | AG28: =IF(AF28="Structural (10 Years Consistency)",10,IF(AF28="Shallow Cyclical (2 to 3 years growth)",5,0)) | AH28: No | AI28: =IF(AH28="Yes due to Product Mix change or Operating Leverage",10,IF(AH28="Yes, these are peak margins",-5,IF(AH28="No",5,0))) | AJ28: Stable | AK28: =IF(AJ28="Stable",10,0) | AL28: Yes | AM28: =IF(AL28="Yes",10,0) | AN28: B2B | AO28: =IF(AN28="B2C",10,IF(AN28="B2B",5,0)) | AP28: Yes | AQ28: =IF(AP28="Yes",10,0) | AR28: Higher One Time, Lower Annuity | AS28: =IF(AR28="Fully Annuity",10,IF(AR28="Higher Annuity, Lower One Time",5,IF(AR28="Higher One Time, Lower Annuity",3,0))) | AT28: Good | AU28: =IF(AT28="Good",10,0) | AV28: Yes for more than 2 years | AW28: =IF(AV28="Yes for more than 2 years",10,IF(AV28="Yes only for next 1 to 2 years",5,0)) | AX28: Above 40 | AY28: =IF(AX28="Above 40",20,IF(AX28="20 to 40",10,IF(AX28="0 to 20",-5,0))) | AZ28: Between 50 to 75 | BA28: =IF(AZ28="Between 50 to 75",10,IF(AZ28="Above 75",0,0)) | BB28: Stage 2 | BC28: =IF(BB28="Stage 2",20,IF(BB28="Stage 1",0,IF(BB28="Stage 3",5,IF(BB28="Stage 4",-5,0)))) | BD28: Positive Trend | BE28: =IF(BD28="Positive Trend",20,IF(BD28="Negative Trend",-10,0)) | BF28: Uptrend | BG28: =IF(BF28="Uptrend",10,IF(BF28="Sideways",5,0)) | BH28: Uptrend | BI28: =IF(BH28="Uptrend",10,IF(BH28="Sideways",5,0)) | BJ28: Blue sky scenario | BK28: =IF(BJ28="Overhead supply in last 2 years in last 2 years",-5,IF(BJ28="Close to 52 week high or retracement",5,IF(BJ28="Blue sky scenario",10,IF(BJ28="Long term Downtrend",-10,0)))) | BL28: Yes | BM28: =IF(BL28="Yes",10,0) | BN28: More than 20% | BO28: =IF(BN28="More than 20%",10,IF(BN28="Between 12 to 20%",5,IF(BN28="Less than 12%",0,0))) | BP28: No | BQ28: =IF(BP28="No",10,0) | BR28: Yes | BS28: =IF(BR28="NO",5,0) | BT28: Above 2 | BU28: =IF(BT28="Above 2",0,IF(BT28="Between 1.5 to 2",5,IF(BT28="Less than 1.5",10,0))) | BV28: Above 70% | BW28: =IF(BV28="Above 70%",10,IF(BV28="Between 50% to 70%",5,IF(BV28="Less than 50%",0,IF(BV28="Negative",-10,IF(BV28="Less than 50% and Borrowings are increasing",-5,0))))) | BX28: Less than 0.7 | BY28: =IF(BX28="More than 1.2",-10,IF(BX28="Between 0.7 to 1.2",0,IF(BX28="Less than 0.7",10,0))) | BZ28: No | CA28: =IF(BZ28="Yes",-10,0) | CB28: Less than 15% | CC28: =IF(CB28="More than 15%",-10,IF(CB28="Less than 15%",10,0)) | CD28: No | CE28: =IF(CD28="Yes, more than 10%",-10,IF(CD28="No",10,0))
A29: =IF(B29=0,"",RANK(B29,$B$2:$B$184,0)) | B29: =SUM(N29,Y29,AA29,AC29,AE29,AG29,AI29,AK29,AM29,AO29,AQ29,AS29,AU29,AW29,AY29,BA29,BC29,BE29,BG29,BI29,BK29,BM29,BO29,BQ29,BS29,BU29,BW29,BY29,CA29,CC29,CE29) | C29: FILATEX | D29: Filatex India Limited | E29: textiles | F29: textiles - manmade | G29: smallcap | H29: 3659.49 | I29: 87.22 | J29: 5.84 | K29: 4978051 | L29: 73 | M29: Outperforming | N29: =IF(M29="Underperforming",-5,IF(L29>=95,15,IF(L29>=90,10,IF(L29>=80,5,0)))) | O29: 75.47 | P29: 44.63 | Q29: 63.29 | R29: Near 52W High Breakout | S29: Nifty 50 | T29: -8.33 | U29: 53.71 | V29: 67.67 | W29: 24.65 | X29: Growing Industry | Y29: =IF(X29="Growing Industry",10,IF(X29="Cyclical in an Upturn",5,0)) | Z29: Too Many Players with High ROCE | AA29: =IF(Z29="Monopoly",10,IF(Z29="Oligopoly",5,IF(Z29="Duopoly that cooperate",10,IF(Z29="Duopoly that compete",5,IF(Z29="Too many players with High ROCE",5,0))))) | AB29: No | AC29: =IF(AB29="No",5,0) | AD29: Tailwind | AE29: =IF(AD29="Tailwind",10,0) | AF29: Structural (10 Years Consistency) | AG29: =IF(AF29="Structural (10 Years Consistency)",10,IF(AF29="Shallow Cyclical (2 to 3 years growth)",5,0)) | AH29: No | AI29: =IF(AH29="Yes due to Product Mix change or Operating Leverage",10,IF(AH29="Yes, these are peak margins",-5,IF(AH29="No",5,0))) | AJ29: Stable | AK29: =IF(AJ29="Stable",10,0) | AL29: Yes | AM29: =IF(AL29="Yes",10,0) | AN29: B2B | AO29: =IF(AN29="B2C",10,IF(AN29="B2B",5,0)) | AP29: Yes | AQ29: =IF(AP29="Yes",10,0) | AR29: Higher One Time, Lower Annuity | AS29: =IF(AR29="Fully Annuity",10,IF(AR29="Higher Annuity, Lower One Time",5,IF(AR29="Higher One Time, Lower Annuity",3,0))) | AT29: Good | AU29: =IF(AT29="Good",10,0) | AV29: Yes for more than 2 years | AW29: =IF(AV29="Yes for more than 2 years",10,IF(AV29="Yes only for next 1 to 2 years",5,0)) | AX29: Above 40 | AY29: =IF(AX29="Above 40",20,IF(AX29="20 to 40",10,IF(AX29="0 to 20",-5,0))) | AZ29: Above 75 | BA29: =IF(AZ29="Between 50 to 75",10,IF(AZ29="Above 75",0,0)) | BB29: Stage 2 | BC29: =IF(BB29="Stage 2",20,IF(BB29="Stage 1",0,IF(BB29="Stage 3",5,IF(BB29="Stage 4",-5,0)))) | BD29: Positive Trend | BE29: =IF(BD29="Positive Trend",20,IF(BD29="Negative Trend",-10,0)) | BF29: Uptrend | BG29: =IF(BF29="Uptrend",10,IF(BF29="Sideways",5,0)) | BH29: Uptrend | BI29: =IF(BH29="Uptrend",10,IF(BH29="Sideways",5,0)) | BJ29: Blue sky scenario | BK29: =IF(BJ29="Overhead supply in last 2 years in last 2 years",-5,IF(BJ29="Close to 52 week high or retracement",5,IF(BJ29="Blue sky scenario",10,IF(BJ29="Long term Downtrend",-10,0)))) | BL29: Yes | BM29: =IF(BL29="Yes",10,0) | BN29: Between 12 to 20% | BO29: =IF(BN29="More than 20%",10,IF(BN29="Between 12 to 20%",5,IF(BN29="Less than 12%",0,0))) | BP29: No | BQ29: =IF(BP29="No",10,0) | BR29: No | BS29: =IF(BR29="NO",5,0) | BT29: Less than 1.5 | BU29: =IF(BT29="Above 2",0,IF(BT29="Between 1.5 to 2",5,IF(BT29="Less than 1.5",10,0))) | BV29: Above 70% | BW29: =IF(BV29="Above 70%",10,IF(BV29="Between 50% to 70%",5,IF(BV29="Less than 50%",0,IF(BV29="Negative",-10,IF(BV29="Less than 50% and Borrowings are increasing",-5,0))))) | BX29: Less than 0.7 | BY29: =IF(BX29="More than 1.2",-10,IF(BX29="Between 0.7 to 1.2",0,IF(BX29="Less than 0.7",10,0))) | BZ29: No | CA29: =IF(BZ29="Yes",-10,0) | CB29: Less than 15% | CC29: =IF(CB29="More than 15%",-10,IF(CB29="Less than 15%",10,0)) | CD29: No | CE29: =IF(CD29="Yes, more than 10%",-10,IF(CD29="No",10,0))
A30: =IF(B30=0,"",RANK(B30,$B$2:$B$184,0)) | B30: =SUM(N30,Y30,AA30,AC30,AE30,AG30,AI30,AK30,AM30,AO30,AQ30,AS30,AU30,AW30,AY30,BA30,BC30,BE30,BG30,BI30,BK30,BM30,BO30,BQ30,BS30,BU30,BW30,BY30,CA30,CC30,CE30) | C30: KANORICHEM | D30: Kanoria Chemicals & Industries Limited | E30: chemicals | F30: chemicals | G30: smallcap | H30: 778.27 | I30: 186.97 | J30: 4.97 | K30: 214032 | L30: 87 | M30: Outperforming | N30: =IF(M30="Underperforming",-5,IF(L30>=95,15,IF(L30>=90,10,IF(L30>=80,5,0)))) | O30: 78.3 | P30: 69.12 | Q30: 141.6 | R30: Near 52W High Breakout | S30: Nifty 50 | T30: -8.33 | U30: 125.54 | V30: 146.03 | W30: 35.26 | X30: Growing Industry | Y30: =IF(X30="Growing Industry",10,IF(X30="Cyclical in an Upturn",5,0)) | Z30: Too Many Players with High ROCE | AA30: =IF(Z30="Monopoly",10,IF(Z30="Oligopoly",5,IF(Z30="Duopoly that cooperate",10,IF(Z30="Duopoly that compete",5,IF(Z30="Too many players with High ROCE",5,0))))) | AB30: No | AC30: =IF(AB30="No",5,0) | AD30: Tailwind | AE30: =IF(AD30="Tailwind",10,0) | AF30: Structural (10 Years Consistency) | AG30: =IF(AF30="Structural (10 Years Consistency)",10,IF(AF30="Shallow Cyclical (2 to 3 years growth)",5,0)) | AH30: No | AI30: =IF(AH30="Yes due to Product Mix change or Operating Leverage",10,IF(AH30="Yes, these are peak margins",-5,IF(AH30="No",5,0))) | AJ30: Stable | AK30: =IF(AJ30="Stable",10,0) | AL30: Yes | AM30: =IF(AL30="Yes",10,0) | AN30: B2B | AO30: =IF(AN30="B2C",10,IF(AN30="B2B",5,0)) | AP30: Yes | AQ30: =IF(AP30="Yes",10,0) | AR30: Higher One Time, Lower Annuity | AS30: =IF(AR30="Fully Annuity",10,IF(AR30="Higher Annuity, Lower One Time",5,IF(AR30="Higher One Time, Lower Annuity",3,0))) | AT30: Good | AU30: =IF(AT30="Good",10,0) | AV30: Yes for more than 2 years | AW30: =IF(AV30="Yes for more than 2 years",10,IF(AV30="Yes only for next 1 to 2 years",5,0)) | AX30: Above 40 | AY30: =IF(AX30="Above 40",20,IF(AX30="20 to 40",10,IF(AX30="0 to 20",-5,0))) | AZ30: Above 75 | BA30: =IF(AZ30="Between 50 to 75",10,IF(AZ30="Above 75",0,0)) | BB30: Stage 2 | BC30: =IF(BB30="Stage 2",20,IF(BB30="Stage 1",0,IF(BB30="Stage 3",5,IF(BB30="Stage 4",-5,0)))) | BD30: Positive Trend | BE30: =IF(BD30="Positive Trend",20,IF(BD30="Negative Trend",-10,0)) | BF30: Uptrend | BG30: =IF(BF30="Uptrend",10,IF(BF30="Sideways",5,0)) | BH30: Uptrend | BI30: =IF(BH30="Uptrend",10,IF(BH30="Sideways",5,0)) | BJ30: Blue sky scenario | BK30: =IF(BJ30="Overhead supply in last 2 years in last 2 years",-5,IF(BJ30="Close to 52 week high or retracement",5,IF(BJ30="Blue sky scenario",10,IF(BJ30="Long term Downtrend",-10,0)))) | BL30: Yes | BM30: =IF(BL30="Yes",10,0) | BN30: More than 20% | BO30: =IF(BN30="More than 20%",10,IF(BN30="Between 12 to 20%",5,IF(BN30="Less than 12%",0,0))) | BP30: No | BQ30: =IF(BP30="No",10,0) | BR30: No | BS30: =IF(BR30="NO",5,0) | BT30: Above 2 | BU30: =IF(BT30="Above 2",0,IF(BT30="Between 1.5 to 2",5,IF(BT30="Less than 1.5",10,0))) | BV30: Above 70% | BW30: =IF(BV30="Above 70%",10,IF(BV30="Between 50% to 70%",5,IF(BV30="Less than 50%",0,IF(BV30="Negative",-10,IF(BV30="Less than 50% and Borrowings are increasing",-5,0))))) | BX30: Less than 0.7 | BY30: =IF(BX30="More than 1.2",-10,IF(BX30="Between 0.7 to 1.2",0,IF(BX30="Less than 0.7",10,0))) | BZ30: No | CA30: =IF(BZ30="Yes",-10,0) | CB30: Less than 15% | CC30: =IF(CB30="More than 15%",-10,IF(CB30="Less than 15%",10,0)) | CD30: No | CE30: =IF(CD30="Yes, more than 10%",-10,IF(CD30="No",10,0))
A31: =IF(B31=0,"",RANK(B31,$B$2:$B$184,0)) | B31: =SUM(N31,Y31,AA31,AC31,AE31,AG31,AI31,AK31,AM31,AO31,AQ31,AS31,AU31,AW31,AY31,BA31,BC31,BE31,BG31,BI31,BK31,BM31,BO31,BQ31,BS31,BU31,BW31,BY31,CA31,CC31,CE31) | C31: IBULLSLTD | D31: Indiabulls Limited | E31: miscellaneous | F31: diversified - medium / small | G31: midcap | H31: 6392.27 | I31: 28.79 | J31: 4.92 | K31: 62047779 | L31: 79 | M31: Outperforming | N31: =IF(M31="Underperforming",-5,IF(L31>=95,15,IF(L31>=90,10,IF(L31>=80,5,0)))) | O31: 63.48 | P31: 40.9 | Q31: 21.44 | R31: Earnings / Momentum Support | S31: Nifty 50 | T31: -8.33 | U31: 61.2 | V31: 75.84 | W31: 27.5 | X31: Growing Industry | Y31: =IF(X31="Growing Industry",10,IF(X31="Cyclical in an Upturn",5,0)) | Z31: Too Many Players with High ROCE | AA31: =IF(Z31="Monopoly",10,IF(Z31="Oligopoly",5,IF(Z31="Duopoly that cooperate",10,IF(Z31="Duopoly that compete",5,IF(Z31="Too many players with High ROCE",5,0))))) | AB31: No | AC31: =IF(AB31="No",5,0) | AD31: Tailwind | AE31: =IF(AD31="Tailwind",10,0) | AF31: Structural (10 Years Consistency) | AG31: =IF(AF31="Structural (10 Years Consistency)",10,IF(AF31="Shallow Cyclical (2 to 3 years growth)",5,0)) | AH31: No | AI31: =IF(AH31="Yes due to Product Mix change or Operating Leverage",10,IF(AH31="Yes, these are peak margins",-5,IF(AH31="No",5,0))) | AJ31: Stable | AK31: =IF(AJ31="Stable",10,0) | AL31: Yes | AM31: =IF(AL31="Yes",10,0) | AN31: B2B | AO31: =IF(AN31="B2C",10,IF(AN31="B2B",5,0)) | AP31: No | AQ31: =IF(AP31="Yes",10,0) | AR31: Higher One Time, Lower Annuity | AS31: =IF(AR31="Fully Annuity",10,IF(AR31="Higher Annuity, Lower One Time",5,IF(AR31="Higher One Time, Lower Annuity",3,0))) | AT31: Good | AU31: =IF(AT31="Good",10,0) | AV31: Yes for more than 2 years | AW31: =IF(AV31="Yes for more than 2 years",10,IF(AV31="Yes only for next 1 to 2 years",5,0)) | AX31: Above 40 | AY31: =IF(AX31="Above 40",20,IF(AX31="20 to 40",10,IF(AX31="0 to 20",-5,0))) | AZ31: Between 50 to 75 | BA31: =IF(AZ31="Between 50 to 75",10,IF(AZ31="Above 75",0,0)) | BB31: Stage 2 | BC31: =IF(BB31="Stage 2",20,IF(BB31="Stage 1",0,IF(BB31="Stage 3",5,IF(BB31="Stage 4",-5,0)))) | BD31: Positive Trend | BE31: =IF(BD31="Positive Trend",20,IF(BD31="Negative Trend",-10,0)) | BF31: Uptrend | BG31: =IF(BF31="Uptrend",10,IF(BF31="Sideways",5,0)) | BH31: Uptrend | BI31: =IF(BH31="Uptrend",10,IF(BH31="Sideways",5,0)) | BJ31: Close to 52 week high or retracement | BK31: =IF(BJ31="Overhead supply in last 2 years in last 2 years",-5,IF(BJ31="Close to 52 week high or retracement",5,IF(BJ31="Blue sky scenario",10,IF(BJ31="Long term Downtrend",-10,0)))) | BL31: Yes | BM31: =IF(BL31="Yes",10,0) | BN31: More than 20% | BO31: =IF(BN31="More than 20%",10,IF(BN31="Between 12 to 20%",5,IF(BN31="Less than 12%",0,0))) | BP31: No | BQ31: =IF(BP31="No",10,0) | BR31: No | BS31: =IF(BR31="NO",5,0) | BT31: Less than 1.5 | BU31: =IF(BT31="Above 2",0,IF(BT31="Between 1.5 to 2",5,IF(BT31="Less than 1.5",10,0))) | BV31: Above 70% | BW31: =IF(BV31="Above 70%",10,IF(BV31="Between 50% to 70%",5,IF(BV31="Less than 50%",0,IF(BV31="Negative",-10,IF(BV31="Less than 50% and Borrowings are increasing",-5,0))))) | BX31: Less than 0.7 | BY31: =IF(BX31="More than 1.2",-10,IF(BX31="Between 0.7 to 1.2",0,IF(BX31="Less than 0.7",10,0))) | BZ31: No | CA31: =IF(BZ31="Yes",-10,0) | CB31: Less than 15% | CC31: =IF(CB31="More than 15%",-10,IF(CB31="Less than 15%",10,0)) | CD31: No | CE31: =IF(CD31="Yes, more than 10%",-10,IF(CD31="No",10,0))
A32: =IF(B32=0,"",RANK(B32,$B$2:$B$184,0)) | B32: =SUM(N32,Y32,AA32,AC32,AE32,AG32,AI32,AK32,AM32,AO32,AQ32,AS32,AU32,AW32,AY32,BA32,BC32,BE32,BG32,BI32,BK32,BM32,BO32,BQ32,BS32,BU32,BW32,BY32,CA32,CC32,CE32) | C32: JKPAPER | D32: Jk Paper Limited | E32: building materials | F32: paper | G32: midcap | H32: 7290.83 | I32: 417.35 | J32: 3.79 | K32: 708260 | N32: =IF(M32="Underperforming",-5,IF(L32>=95,15,IF(L32>=90,10,IF(L32>=80,5,0)))) | O32: 66.9 | P32: 34.99 | Q32: 340.4 | R32: Near 52W High Breakout | S32: Nifty Infra | X32: Growing Industry | Y32: =IF(X32="Growing Industry",10,IF(X32="Cyclical in an Upturn",5,0)) | Z32: Too Many Players with High ROCE | AA32: =IF(Z32="Monopoly",10,IF(Z32="Oligopoly",5,IF(Z32="Duopoly that cooperate",10,IF(Z32="Duopoly that compete",5,IF(Z32="Too many players with High ROCE",5,0))))) | AB32: No | AC32: =IF(AB32="No",5,0) | AD32: Tailwind | AE32: =IF(AD32="Tailwind",10,0) | AF32: Structural (10 Years Consistency) | AG32: =IF(AF32="Structural (10 Years Consistency)",10,IF(AF32="Shallow Cyclical (2 to 3 years growth)",5,0)) | AH32: No | AI32: =IF(AH32="Yes due to Product Mix change or Operating Leverage",10,IF(AH32="Yes, these are peak margins",-5,IF(AH32="No",5,0))) | AJ32: Stable | AK32: =IF(AJ32="Stable",10,0) | AL32: Yes | AM32: =IF(AL32="Yes",10,0) | AN32: B2B | AO32: =IF(AN32="B2C",10,IF(AN32="B2B",5,0)) | AP32: Yes | AQ32: =IF(AP32="Yes",10,0) | AR32: Higher One Time, Lower Annuity | AS32: =IF(AR32="Fully Annuity",10,IF(AR32="Higher Annuity, Lower One Time",5,IF(AR32="Higher One Time, Lower Annuity",3,0))) | AT32: Good | AU32: =IF(AT32="Good",10,0) | AV32: Yes for more than 2 years | AW32: =IF(AV32="Yes for more than 2 years",10,IF(AV32="Yes only for next 1 to 2 years",5,0)) | AX32: 20 to 40 | AY32: =IF(AX32="Above 40",20,IF(AX32="20 to 40",10,IF(AX32="0 to 20",-5,0))) | AZ32: Between 50 to 75 | BA32: =IF(AZ32="Between 50 to 75",10,IF(AZ32="Above 75",0,0)) | BB32: Stage 2 | BC32: =IF(BB32="Stage 2",20,IF(BB32="Stage 1",0,IF(BB32="Stage 3",5,IF(BB32="Stage 4",-5,0)))) | BD32: Positive Trend | BE32: =IF(BD32="Positive Trend",20,IF(BD32="Negative Trend",-10,0)) | BF32: Uptrend | BG32: =IF(BF32="Uptrend",10,IF(BF32="Sideways",5,0)) | BH32: Uptrend | BI32: =IF(BH32="Uptrend",10,IF(BH32="Sideways",5,0)) | BJ32: Close to 52 week high or retracement | BK32: =IF(BJ32="Overhead supply in last 2 years in last 2 years",-5,IF(BJ32="Close to 52 week high or retracement",5,IF(BJ32="Blue sky scenario",10,IF(BJ32="Long term Downtrend",-10,0)))) | BL32: Yes | BM32: =IF(BL32="Yes",10,0) | BN32: More than 20% | BO32: =IF(BN32="More than 20%",10,IF(BN32="Between 12 to 20%",5,IF(BN32="Less than 12%",0,0))) | BP32: No | BQ32: =IF(BP32="No",10,0) | BR32: No | BS32: =IF(BR32="NO",5,0) | BT32: Less than 1.5 | BU32: =IF(BT32="Above 2",0,IF(BT32="Between 1.5 to 2",5,IF(BT32="Less than 1.5",10,0))) | BV32: Above 70% | BW32: =IF(BV32="Above 70%",10,IF(BV32="Between 50% to 70%",5,IF(BV32="Less than 50%",0,IF(BV32="Negative",-10,IF(BV32="Less than 50% and Borrowings are increasing",-5,0))))) | BX32: Less than 0.7 | BY32: =IF(BX32="More than 1.2",-10,IF(BX32="Between 0.7 to 1.2",0,IF(BX32="Less than 0.7",10,0))) | BZ32: No | CA32: =IF(BZ32="Yes",-10,0) | CB32: Less than 15% | CC32: =IF(CB32="More than 15%",-10,IF(CB32="Less than 15%",10,0)) | CD32: No | CE32: =IF(CD32="Yes, more than 10%",-10,IF(CD32="No",10,0))
A33: =IF(B33=0,"",RANK(B33,$B$2:$B$184,0)) | B33: =SUM(N33,Y33,AA33,AC33,AE33,AG33,AI33,AK33,AM33,AO33,AQ33,AS33,AU33,AW33,AY33,BA33,BC33,BE33,BG33,BI33,BK33,BM33,BO33,BQ33,BS33,BU33,BW33,BY33,CA33,CC33,CE33) | C33: SSWL | D33: Steel Strips Wheels Limited | E33: auto | F33: auto ancillaries | G33: midcap | H33: 5328.42 | I33: 350.05 | J33: 3.26 | K33: 1772756 | N33: =IF(M33="Underperforming",-5,IF(L33>=95,15,IF(L33>=90,10,IF(L33>=80,5,0)))) | O33: 71.12 | P33: 43.9 | Q33: 291.51 | R33: Earnings / Momentum Support | S33: Nifty Auto | X33: Growing Industry | Y33: =IF(X33="Growing Industry",10,IF(X33="Cyclical in an Upturn",5,0)) | Z33: Too Many Players with High ROCE | AA33: =IF(Z33="Monopoly",10,IF(Z33="Oligopoly",5,IF(Z33="Duopoly that cooperate",10,IF(Z33="Duopoly that compete",5,IF(Z33="Too many players with High ROCE",5,0))))) | AB33: No | AC33: =IF(AB33="No",5,0) | AD33: Tailwind | AE33: =IF(AD33="Tailwind",10,0) | AF33: Structural (10 Years Consistency) | AG33: =IF(AF33="Structural (10 Years Consistency)",10,IF(AF33="Shallow Cyclical (2 to 3 years growth)",5,0)) | AH33: No | AI33: =IF(AH33="Yes due to Product Mix change or Operating Leverage",10,IF(AH33="Yes, these are peak margins",-5,IF(AH33="No",5,0))) | AJ33: Stable | AK33: =IF(AJ33="Stable",10,0) | AL33: Yes | AM33: =IF(AL33="Yes",10,0) | AN33: B2B | AO33: =IF(AN33="B2C",10,IF(AN33="B2B",5,0)) | AP33: No | AQ33: =IF(AP33="Yes",10,0) | AR33: Higher One Time, Lower Annuity | AS33: =IF(AR33="Fully Annuity",10,IF(AR33="Higher Annuity, Lower One Time",5,IF(AR33="Higher One Time, Lower Annuity",3,0))) | AT33: Good | AU33: =IF(AT33="Good",10,0) | AV33: Yes for more than 2 years | AW33: =IF(AV33="Yes for more than 2 years",10,IF(AV33="Yes only for next 1 to 2 years",5,0)) | AX33: Above 40 | AY33: =IF(AX33="Above 40",20,IF(AX33="20 to 40",10,IF(AX33="0 to 20",-5,0))) | AZ33: Between 50 to 75 | BA33: =IF(AZ33="Between 50 to 75",10,IF(AZ33="Above 75",0,0)) | BB33: Stage 2 | BC33: =IF(BB33="Stage 2",20,IF(BB33="Stage 1",0,IF(BB33="Stage 3",5,IF(BB33="Stage 4",-5,0)))) | BD33: Positive Trend | BE33: =IF(BD33="Positive Trend",20,IF(BD33="Negative Trend",-10,0)) | BF33: Uptrend | BG33: =IF(BF33="Uptrend",10,IF(BF33="Sideways",5,0)) | BH33: Uptrend | BI33: =IF(BH33="Uptrend",10,IF(BH33="Sideways",5,0)) | BJ33: Close to 52 week high or retracement | BK33: =IF(BJ33="Overhead supply in last 2 years in last 2 years",-5,IF(BJ33="Close to 52 week high or retracement",5,IF(BJ33="Blue sky scenario",10,IF(BJ33="Long term Downtrend",-10,0)))) | BL33: Yes | BM33: =IF(BL33="Yes",10,0) | BN33: More than 20% | BO33: =IF(BN33="More than 20%",10,IF(BN33="Between 12 to 20%",5,IF(BN33="Less than 12%",0,0))) | BP33: No | BQ33: =IF(BP33="No",10,0) | BR33: No | BS33: =IF(BR33="NO",5,0) | BT33: Less than 1.5 | BU33: =IF(BT33="Above 2",0,IF(BT33="Between 1.5 to 2",5,IF(BT33="Less than 1.5",10,0))) | BV33: Above 70% | BW33: =IF(BV33="Above 70%",10,IF(BV33="Between 50% to 70%",5,IF(BV33="Less than 50%",0,IF(BV33="Negative",-10,IF(BV33="Less than 50% and Borrowings are increasing",-5,0))))) | BX33: Less than 0.7 | BY33: =IF(BX33="More than 1.2",-10,IF(BX33="Between 0.7 to 1.2",0,IF(BX33="Less than 0.7",10,0))) | BZ33: No | CA33: =IF(BZ33="Yes",-10,0) | CB33: Less than 15% | CC33: =IF(CB33="More than 15%",-10,IF(CB33="Less than 15%",10,0)) | CD33: No | CE33: =IF(CD33="Yes, more than 10%",-10,IF(CD33="No",10,0))
A34: =IF(B34=0,"",RANK(B34,$B$2:$B$184,0)) | B34: =SUM(N34,Y34,AA34,AC34,AE34,AG34,AI34,AK34,AM34,AO34,AQ34,AS34,AU34,AW34,AY34,BA34,BC34,BE34,BG34,BI34,BK34,BM34,BO34,BQ34,BS34,BU34,BW34,BY34,CA34,CC34,CE34) | C34: FINCABLES | D34: Finolex Cables Limited | E34: industrials | F34: cables - power | G34: largecap | H34: 20492.34 | I34: 1362.6 | J34: 1.69 | K34: 1264308 | N34: =IF(M34="Underperforming",-5,IF(L34>=95,15,IF(L34>=90,10,IF(L34>=80,5,0)))) | O34: 65.8 | P34: 37.6 | Q34: 1070.66 | R34: Near 52W High Breakout | S34: Nifty Energy | X34: Cyclical in an Upturn | Y34: =IF(X34="Growing Industry",10,IF(X34="Cyclical in an Upturn",5,0)) | Z34: Too Many Players with High ROCE | AA34: =IF(Z34="Monopoly",10,IF(Z34="Oligopoly",5,IF(Z34="Duopoly that cooperate",10,IF(Z34="Duopoly that compete",5,IF(Z34="Too many players with High ROCE",5,0))))) | AB34: No | AC34: =IF(AB34="No",5,0) | AD34: Tailwind | AE34: =IF(AD34="Tailwind",10,0) | AF34: Structural (10 Years Consistency) | AG34: =IF(AF34="Structural (10 Years Consistency)",10,IF(AF34="Shallow Cyclical (2 to 3 years growth)",5,0)) | AH34: No | AI34: =IF(AH34="Yes due to Product Mix change or Operating Leverage",10,IF(AH34="Yes, these are peak margins",-5,IF(AH34="No",5,0))) | AJ34: Stable | AK34: =IF(AJ34="Stable",10,0) | AL34: Yes | AM34: =IF(AL34="Yes",10,0) | AN34: B2B | AO34: =IF(AN34="B2C",10,IF(AN34="B2B",5,0)) | AP34: Yes | AQ34: =IF(AP34="Yes",10,0) | AR34: Higher One Time, Lower Annuity | AS34: =IF(AR34="Fully Annuity",10,IF(AR34="Higher Annuity, Lower One Time",5,IF(AR34="Higher One Time, Lower Annuity",3,0))) | AT34: Good | AU34: =IF(AT34="Good",10,0) | AV34: Yes for more than 2 years | AW34: =IF(AV34="Yes for more than 2 years",10,IF(AV34="Yes only for next 1 to 2 years",5,0)) | AX34: 20 to 40 | AY34: =IF(AX34="Above 40",20,IF(AX34="20 to 40",10,IF(AX34="0 to 20",-5,0))) | AZ34: Between 50 to 75 | BA34: =IF(AZ34="Between 50 to 75",10,IF(AZ34="Above 75",0,0)) | BB34: Stage 2 | BC34: =IF(BB34="Stage 2",20,IF(BB34="Stage 1",0,IF(BB34="Stage 3",5,IF(BB34="Stage 4",-5,0)))) | BD34: Positive Trend | BE34: =IF(BD34="Positive Trend",20,IF(BD34="Negative Trend",-10,0)) | BF34: Uptrend | BG34: =IF(BF34="Uptrend",10,IF(BF34="Sideways",5,0)) | BH34: Uptrend | BI34: =IF(BH34="Uptrend",10,IF(BH34="Sideways",5,0)) | BJ34: Blue sky scenario | BK34: =IF(BJ34="Overhead supply in last 2 years in last 2 years",-5,IF(BJ34="Close to 52 week high or retracement",5,IF(BJ34="Blue sky scenario",10,IF(BJ34="Long term Downtrend",-10,0)))) | BL34: Yes | BM34: =IF(BL34="Yes",10,0) | BN34: More than 20% | BO34: =IF(BN34="More than 20%",10,IF(BN34="Between 12 to 20%",5,IF(BN34="Less than 12%",0,0))) | BP34: No | BQ34: =IF(BP34="No",10,0) | BR34: No | BS34: =IF(BR34="NO",5,0) | BT34: Less than 1.5 | BU34: =IF(BT34="Above 2",0,IF(BT34="Between 1.5 to 2",5,IF(BT34="Less than 1.5",10,0))) | BV34: Above 70% | BW34: =IF(BV34="Above 70%",10,IF(BV34="Between 50% to 70%",5,IF(BV34="Less than 50%",0,IF(BV34="Negative",-10,IF(BV34="Less than 50% and Borrowings are increasing",-5,0))))) | BX34: Less than 0.7 | BY34: =IF(BX34="More than 1.2",-10,IF(BX34="Between 0.7 to 1.2",0,IF(BX34="Less than 0.7",10,0))) | BZ34: No | CA34: =IF(BZ34="Yes",-10,0) | CB34: Less than 15% | CC34: =IF(CB34="More than 15%",-10,IF(CB34="Less than 15%",10,0)) | CD34: No | CE34: =IF(CD34="Yes, more than 10%",-10,IF(CD34="No",10,0))
A35: =IF(B35=0,"",RANK(B35,$B$2:$B$184,0)) | B35: =SUM(N35,Y35,AA35,AC35,AE35,AG35,AI35,AK35,AM35,AO35,AQ35,AS35,AU35,AW35,AY35,BA35,BC35,BE35,BG35,BI35,BK35,BM35,BO35,BQ35,BS35,BU35,BW35,BY35,CA35,CC35,CE35) | C35: LOTUSDEV | D35: Sri Lotus Developers & Realty Ltd | E35: realty | F35: construction | G35: midcap | H35: 10436.21 | I35: 216.4 | J35: 1.34 | K35: 1914804 | N35: =IF(M35="Underperforming",-5,IF(L35>=95,15,IF(L35>=90,10,IF(L35>=80,5,0)))) | O35: 67.17 | P35: 23.68 | Q35: 164.04 | R35: Near 52W High Breakout | S35: Nifty Realty | X35: Growing Industry | Y35: =IF(X35="Growing Industry",10,IF(X35="Cyclical in an Upturn",5,0)) | Z35: Too Many Players with High ROCE | AA35: =IF(Z35="Monopoly",10,IF(Z35="Oligopoly",5,IF(Z35="Duopoly that cooperate",10,IF(Z35="Duopoly that compete",5,IF(Z35="Too many players with High ROCE",5,0))))) | AB35: No | AC35: =IF(AB35="No",5,0) | AD35: Tailwind | AE35: =IF(AD35="Tailwind",10,0) | AF35: Structural (10 Years Consistency) | AG35: =IF(AF35="Structural (10 Years Consistency)",10,IF(AF35="Shallow Cyclical (2 to 3 years growth)",5,0)) | AH35: No | AI35: =IF(AH35="Yes due to Product Mix change or Operating Leverage",10,IF(AH35="Yes, these are peak margins",-5,IF(AH35="No",5,0))) | AJ35: Stable | AK35: =IF(AJ35="Stable",10,0) | AL35: Yes | AM35: =IF(AL35="Yes",10,0) | AN35: B2B | AO35: =IF(AN35="B2C",10,IF(AN35="B2B",5,0)) | AP35: Yes | AQ35: =IF(AP35="Yes",10,0) | AR35: Higher One Time, Lower Annuity | AS35: =IF(AR35="Fully Annuity",10,IF(AR35="Higher Annuity, Lower One Time",5,IF(AR35="Higher One Time, Lower Annuity",3,0))) | AT35: Good | AU35: =IF(AT35="Good",10,0) | AV35: Yes for more than 2 years | AW35: =IF(AV35="Yes for more than 2 years",10,IF(AV35="Yes only for next 1 to 2 years",5,0)) | AX35: 20 to 40 | AY35: =IF(AX35="Above 40",20,IF(AX35="20 to 40",10,IF(AX35="0 to 20",-5,0))) | AZ35: Between 50 to 75 | BA35: =IF(AZ35="Between 50 to 75",10,IF(AZ35="Above 75",0,0)) | BB35: Stage 2 | BC35: =IF(BB35="Stage 2",20,IF(BB35="Stage 1",0,IF(BB35="Stage 3",5,IF(BB35="Stage 4",-5,0)))) | BD35: Positive Trend | BE35: =IF(BD35="Positive Trend",20,IF(BD35="Negative Trend",-10,0)) | BF35: Uptrend | BG35: =IF(BF35="Uptrend",10,IF(BF35="Sideways",5,0)) | BH35: Uptrend | BI35: =IF(BH35="Uptrend",10,IF(BH35="Sideways",5,0)) | BJ35: Blue sky scenario | BK35: =IF(BJ35="Overhead supply in last 2 years in last 2 years",-5,IF(BJ35="Close to 52 week high or retracement",5,IF(BJ35="Blue sky scenario",10,IF(BJ35="Long term Downtrend",-10,0)))) | BL35: Yes | BM35: =IF(BL35="Yes",10,0) | BN35: More than 20% | BO35: =IF(BN35="More than 20%",10,IF(BN35="Between 12 to 20%",5,IF(BN35="Less than 12%",0,0))) | BP35: No | BQ35: =IF(BP35="No",10,0) | BR35: Yes | BS35: =IF(BR35="NO",5,0) | BT35: Less than 1.5 | BU35: =IF(BT35="Above 2",0,IF(BT35="Between 1.5 to 2",5,IF(BT35="Less than 1.5",10,0))) | BV35: Above 70% | BW35: =IF(BV35="Above 70%",10,IF(BV35="Between 50% to 70%",5,IF(BV35="Less than 50%",0,IF(BV35="Negative",-10,IF(BV35="Less than 50% and Borrowings are increasing",-5,0))))) | BX35: Less than 0.7 | BY35: =IF(BX35="More than 1.2",-10,IF(BX35="Between 0.7 to 1.2",0,IF(BX35="Less than 0.7",10,0))) | BZ35: No | CA35: =IF(BZ35="Yes",-10,0) | CB35: Less than 15% | CC35: =IF(CB35="More than 15%",-10,IF(CB35="Less than 15%",10,0)) | CD35: No | CE35: =IF(CD35="Yes, more than 10%",-10,IF(CD35="No",10,0))
A36: =IF(B36=0,"",RANK(B36,$B$2:$B$184,0)) | B36: =SUM(N36,Y36,AA36,AC36,AE36,AG36,AI36,AK36,AM36,AO36,AQ36,AS36,AU36,AW36,AY36,BA36,BC36,BE36,BG36,BI36,BK36,BM36,BO36,BQ36,BS36,BU36,BW36,BY36,CA36,CC36,CE36) | C36: BIRLACABLE | D36: Birla Cable Limited | E36: industrials | F36: cables - telephone | G36: smallcap | H36: 1133.85 | I36: 382.55 | J36: 1.22 | K36: 734776 | N36: =IF(M36="Underperforming",-5,IF(L36>=95,15,IF(L36>=90,10,IF(L36>=80,5,0)))) | O36: 77.85 | P36: 52.8 | Q36: 285.73 | R36: Volume Spike & Near 52W High Breakout | S36: Nifty Infra | X36: Cyclical in an Upturn | Y36: =IF(X36="Growing Industry",10,IF(X36="Cyclical in an Upturn",5,0)) | Z36: Too Many Players with High ROCE | AA36: =IF(Z36="Monopoly",10,IF(Z36="Oligopoly",5,IF(Z36="Duopoly that cooperate",10,IF(Z36="Duopoly that compete",5,IF(Z36="Too many players with High ROCE",5,0))))) | AB36: No | AC36: =IF(AB36="No",5,0) | AD36: Tailwind | AE36: =IF(AD36="Tailwind",10,0) | AF36: Structural (10 Years Consistency) | AG36: =IF(AF36="Structural (10 Years Consistency)",10,IF(AF36="Shallow Cyclical (2 to 3 years growth)",5,0)) | AH36: No | AI36: =IF(AH36="Yes due to Product Mix change or Operating Leverage",10,IF(AH36="Yes, these are peak margins",-5,IF(AH36="No",5,0))) | AJ36: Stable | AK36: =IF(AJ36="Stable",10,0) | AL36: Yes | AM36: =IF(AL36="Yes",10,0) | AN36: B2B | AO36: =IF(AN36="B2C",10,IF(AN36="B2B",5,0)) | AP36: Yes | AQ36: =IF(AP36="Yes",10,0) | AR36: Higher One Time, Lower Annuity | AS36: =IF(AR36="Fully Annuity",10,IF(AR36="Higher Annuity, Lower One Time",5,IF(AR36="Higher One Time, Lower Annuity",3,0))) | AT36: Good | AU36: =IF(AT36="Good",10,0) | AV36: Yes for more than 2 years | AW36: =IF(AV36="Yes for more than 2 years",10,IF(AV36="Yes only for next 1 to 2 years",5,0)) | AX36: Above 40 | AY36: =IF(AX36="Above 40",20,IF(AX36="20 to 40",10,IF(AX36="0 to 20",-5,0))) | AZ36: Above 75 | BA36: =IF(AZ36="Between 50 to 75",10,IF(AZ36="Above 75",0,0)) | BB36: Stage 2 | BC36: =IF(BB36="Stage 2",20,IF(BB36="Stage 1",0,IF(BB36="Stage 3",5,IF(BB36="Stage 4",-5,0)))) | BD36: Positive Trend | BE36: =IF(BD36="Positive Trend",20,IF(BD36="Negative Trend",-10,0)) | BF36: Uptrend | BG36: =IF(BF36="Uptrend",10,IF(BF36="Sideways",5,0)) | BH36: Uptrend | BI36: =IF(BH36="Uptrend",10,IF(BH36="Sideways",5,0)) | BJ36: Blue sky scenario | BK36: =IF(BJ36="Overhead supply in last 2 years in last 2 years",-5,IF(BJ36="Close to 52 week high or retracement",5,IF(BJ36="Blue sky scenario",10,IF(BJ36="Long term Downtrend",-10,0)))) | BL36: Yes | BM36: =IF(BL36="Yes",10,0) | BN36: More than 20% | BO36: =IF(BN36="More than 20%",10,IF(BN36="Between 12 to 20%",5,IF(BN36="Less than 12%",0,0))) | BP36: No | BQ36: =IF(BP36="No",10,0) | BR36: No | BS36: =IF(BR36="NO",5,0) | BT36: Less than 1.5 | BU36: =IF(BT36="Above 2",0,IF(BT36="Between 1.5 to 2",5,IF(BT36="Less than 1.5",10,0))) | BV36: Above 70% | BW36: =IF(BV36="Above 70%",10,IF(BV36="Between 50% to 70%",5,IF(BV36="Less than 50%",0,IF(BV36="Negative",-10,IF(BV36="Less than 50% and Borrowings are increasing",-5,0))))) | BX36: Less than 0.7 | BY36: =IF(BX36="More than 1.2",-10,IF(BX36="Between 0.7 to 1.2",0,IF(BX36="Less than 0.7",10,0))) | BZ36: No | CA36: =IF(BZ36="Yes",-10,0) | CB36: Less than 15% | CC36: =IF(CB36="More than 15%",-10,IF(CB36="Less than 15%",10,0)) | CD36: No | CE36: =IF(CD36="Yes, more than 10%",-10,IF(CD36="No",10,0))
A37: =IF(B37=0,"",RANK(B37,$B$2:$B$184,0)) | B37: =SUM(N37,Y37,AA37,AC37,AE37,AG37,AI37,AK37,AM37,AO37,AQ37,AS37,AU37,AW37,AY37,BA37,BC37,BE37,BG37,BI37,BK37,BM37,BO37,BQ37,BS37,BU37,BW37,BY37,CA37,CC37,CE37) | C37: CONFIPET | D37: Confidence Petroleum India Ltd | E37: miscellaneous | F37: miscellaneous | G37: smallcap | H37: 2860.6 | I37: 86.58 | J37: 0.56 | K37: 2646137 | L37: 71 | M37: Outperforming | N37: =IF(M37="Underperforming",-5,IF(L37>=95,15,IF(L37>=90,10,IF(L37>=80,5,0)))) | O37: 67.74 | P37: 59.56 | Q37: 62.7 | R37: Near 52W High Breakout | S37: Nifty 50 | T37: -8.33 | U37: 82.09 | V37: 98.63 | W37: 23.56 | X37: Growing Industry | Y37: =IF(X37="Growing Industry",10,IF(X37="Cyclical in an Upturn",5,0)) | Z37: Too Many Players with High ROCE | AA37: =IF(Z37="Monopoly",10,IF(Z37="Oligopoly",5,IF(Z37="Duopoly that cooperate",10,IF(Z37="Duopoly that compete",5,IF(Z37="Too many players with High ROCE",5,0))))) | AB37: No | AC37: =IF(AB37="No",5,0) | AD37: Tailwind | AE37: =IF(AD37="Tailwind",10,0) | AF37: Structural (10 Years Consistency) | AG37: =IF(AF37="Structural (10 Years Consistency)",10,IF(AF37="Shallow Cyclical (2 to 3 years growth)",5,0)) | AH37: No | AI37: =IF(AH37="Yes due to Product Mix change or Operating Leverage",10,IF(AH37="Yes, these are peak margins",-5,IF(AH37="No",5,0))) | AJ37: Stable | AK37: =IF(AJ37="Stable",10,0) | AL37: Yes | AM37: =IF(AL37="Yes",10,0) | AN37: B2B | AO37: =IF(AN37="B2C",10,IF(AN37="B2B",5,0)) | AP37: Yes | AQ37: =IF(AP37="Yes",10,0) | AR37: Higher One Time, Lower Annuity | AS37: =IF(AR37="Fully Annuity",10,IF(AR37="Higher Annuity, Lower One Time",5,IF(AR37="Higher One Time, Lower Annuity",3,0))) | AT37: Good | AU37: =IF(AT37="Good",10,0) | AV37: Yes for more than 2 years | AW37: =IF(AV37="Yes for more than 2 years",10,IF(AV37="Yes only for next 1 to 2 years",5,0)) | AX37: Above 40 | AY37: =IF(AX37="Above 40",20,IF(AX37="20 to 40",10,IF(AX37="0 to 20",-5,0))) | AZ37: Between 50 to 75 | BA37: =IF(AZ37="Between 50 to 75",10,IF(AZ37="Above 75",0,0)) | BB37: Stage 2 | BC37: =IF(BB37="Stage 2",20,IF(BB37="Stage 1",0,IF(BB37="Stage 3",5,IF(BB37="Stage 4",-5,0)))) | BD37: Positive Trend | BE37: =IF(BD37="Positive Trend",20,IF(BD37="Negative Trend",-10,0)) | BF37: Uptrend | BG37: =IF(BF37="Uptrend",10,IF(BF37="Sideways",5,0)) | BH37: Uptrend | BI37: =IF(BH37="Uptrend",10,IF(BH37="Sideways",5,0)) | BJ37: Close to 52 week high or retracement | BK37: =IF(BJ37="Overhead supply in last 2 years in last 2 years",-5,IF(BJ37="Close to 52 week high or retracement",5,IF(BJ37="Blue sky scenario",10,IF(BJ37="Long term Downtrend",-10,0)))) | BL37: Yes | BM37: =IF(BL37="Yes",10,0) | BN37: More than 20% | BO37: =IF(BN37="More than 20%",10,IF(BN37="Between 12 to 20%",5,IF(BN37="Less than 12%",0,0))) | BP37: No | BQ37: =IF(BP37="No",10,0) | BR37: No | BS37: =IF(BR37="NO",5,0) | BT37: Above 2 | BU37: =IF(BT37="Above 2",0,IF(BT37="Between 1.5 to 2",5,IF(BT37="Less than 1.5",10,0))) | BV37: Above 70% | BW37: =IF(BV37="Above 70%",10,IF(BV37="Between 50% to 70%",5,IF(BV37="Less than 50%",0,IF(BV37="Negative",-10,IF(BV37="Less than 50% and Borrowings are increasing",-5,0))))) | BX37: Less than 0.7 | BY37: =IF(BX37="More than 1.2",-10,IF(BX37="Between 0.7 to 1.2",0,IF(BX37="Less than 0.7",10,0))) | BZ37: No | CA37: =IF(BZ37="Yes",-10,0) | CB37: Less than 15% | CC37: =IF(CB37="More than 15%",-10,IF(CB37="Less than 15%",10,0)) | CD37: No | CE37: =IF(CD37="Yes, more than 10%",-10,IF(CD37="No",10,0))
A38: =IF(B38=0,"",RANK(B38,$B$2:$B$184,0)) | B38: =SUM(N38,Y38,AA38,AC38,AE38,AG38,AI38,AK38,AM38,AO38,AQ38,AS38,AU38,AW38,AY38,BA38,BC38,BE38,BG38,BI38,BK38,BM38,BO38,BQ38,BS38,BU38,BW38,BY38,CA38,CC38,CE38) | C38: BODALCHEM | D38: Bodal Chemicals Limited | E38: chemicals | F38: dyes and pigments | G38: smallcap | H38: 2224.93 | I38: 173.46 | J38: -1.81 | K38: 1821210 | L38: 97 | M38: Outperforming | N38: =IF(M38="Underperforming",-5,IF(L38>=95,15,IF(L38>=90,10,IF(L38>=80,5,0)))) | O38: 88.94 | P38: 40.82 | Q38: 133.89 | R38: Near 52W High Breakout | S38: Nifty 50 | T38: -8.33 | U38: 162.14 | V38: 185.96 | W38: 60.71 | X38: Growing Industry | Y38: =IF(X38="Growing Industry",10,IF(X38="Cyclical in an Upturn",5,0)) | Z38: Too Many Players with High ROCE | AA38: =IF(Z38="Monopoly",10,IF(Z38="Oligopoly",5,IF(Z38="Duopoly that cooperate",10,IF(Z38="Duopoly that compete",5,IF(Z38="Too many players with High ROCE",5,0))))) | AB38: No | AC38: =IF(AB38="No",5,0) | AD38: Tailwind | AE38: =IF(AD38="Tailwind",10,0) | AF38: Structural (10 Years Consistency) | AG38: =IF(AF38="Structural (10 Years Consistency)",10,IF(AF38="Shallow Cyclical (2 to 3 years growth)",5,0)) | AH38: No | AI38: =IF(AH38="Yes due to Product Mix change or Operating Leverage",10,IF(AH38="Yes, these are peak margins",-5,IF(AH38="No",5,0))) | AJ38: Stable | AK38: =IF(AJ38="Stable",10,0) | AL38: Yes | AM38: =IF(AL38="Yes",10,0) | AN38: B2B | AO38: =IF(AN38="B2C",10,IF(AN38="B2B",5,0)) | AP38: Yes | AQ38: =IF(AP38="Yes",10,0) | AR38: Higher One Time, Lower Annuity | AS38: =IF(AR38="Fully Annuity",10,IF(AR38="Higher Annuity, Lower One Time",5,IF(AR38="Higher One Time, Lower Annuity",3,0))) | AT38: Good | AU38: =IF(AT38="Good",10,0) | AV38: Yes for more than 2 years | AW38: =IF(AV38="Yes for more than 2 years",10,IF(AV38="Yes only for next 1 to 2 years",5,0)) | AX38: Above 40 | AY38: =IF(AX38="Above 40",20,IF(AX38="20 to 40",10,IF(AX38="0 to 20",-5,0))) | AZ38: Above 75 | BA38: =IF(AZ38="Between 50 to 75",10,IF(AZ38="Above 75",0,0)) | BB38: Stage 2 | BC38: =IF(BB38="Stage 2",20,IF(BB38="Stage 1",0,IF(BB38="Stage 3",5,IF(BB38="Stage 4",-5,0)))) | BD38: Positive Trend | BE38: =IF(BD38="Positive Trend",20,IF(BD38="Negative Trend",-10,0)) | BF38: Uptrend | BG38: =IF(BF38="Uptrend",10,IF(BF38="Sideways",5,0)) | BH38: Uptrend | BI38: =IF(BH38="Uptrend",10,IF(BH38="Sideways",5,0)) | BJ38: Blue sky scenario | BK38: =IF(BJ38="Overhead supply in last 2 years in last 2 years",-5,IF(BJ38="Close to 52 week high or retracement",5,IF(BJ38="Blue sky scenario",10,IF(BJ38="Long term Downtrend",-10,0)))) | BL38: Yes | BM38: =IF(BL38="Yes",10,0) | BN38: More than 20% | BO38: =IF(BN38="More than 20%",10,IF(BN38="Between 12 to 20%",5,IF(BN38="Less than 12%",0,0))) | BP38: No | BQ38: =IF(BP38="No",10,0) | BR38: No | BS38: =IF(BR38="NO",5,0) | BT38: Above 2 | BU38: =IF(BT38="Above 2",0,IF(BT38="Between 1.5 to 2",5,IF(BT38="Less than 1.5",10,0))) | BV38: Above 70% | BW38: =IF(BV38="Above 70%",10,IF(BV38="Between 50% to 70%",5,IF(BV38="Less than 50%",0,IF(BV38="Negative",-10,IF(BV38="Less than 50% and Borrowings are increasing",-5,0))))) | BX38: Between 0.7 to 1.2 | BY38: =IF(BX38="More than 1.2",-10,IF(BX38="Between 0.7 to 1.2",0,IF(BX38="Less than 0.7",10,0))) | BZ38: No | CA38: =IF(BZ38="Yes",-10,0) | CB38: Less than 15% | CC38: =IF(CB38="More than 15%",-10,IF(CB38="Less than 15%",10,0)) | CD38: No | CE38: =IF(CD38="Yes, more than 10%",-10,IF(CD38="No",10,0))
A39: =IF(B39=0,"",RANK(B39,$B$2:$B$184,0)) | B39: =SUM(N39,Y39,AA39,AC39,AE39,AG39,AI39,AK39,AM39,AO39,AQ39,AS39,AU39,AW39,AY39,BA39,BC39,BE39,BG39,BI39,BK39,BM39,BO39,BQ39,BS39,BU39,BW39,BY39,CA39,CC39,CE39) | C39: ZIMLAB | D39: Zim Laboratories Ltd | E39: healthcare | F39: pharmaceuticals - indian - bulk drugs & formln | G39: smallcap | H39: 715.47 | I39: 136.78 | J39: 2.37 | K39: 104649 | L39: 63 | M39: Outperforming | N39: =IF(M39="Underperforming",-5,IF(L39>=95,15,IF(L39>=90,10,IF(L39>=80,5,0)))) | O39: 70.31 | P39: 60.01 | Q39: 101.75 | R39: Near 52W High Breakout | S39: Nifty Pharma | T39: 15.25 | U39: 81.84 | V39: 57.78 | W39: 19.05 | X39: Growing Industry | Y39: =IF(X39="Growing Industry",10,IF(X39="Cyclical in an Upturn",5,0)) | Z39: Too Many Players with High ROCE | AA39: =IF(Z39="Monopoly",10,IF(Z39="Oligopoly",5,IF(Z39="Duopoly that cooperate",10,IF(Z39="Duopoly that compete",5,IF(Z39="Too many players with High ROCE",5,0))))) | AB39: Yes | AC39: =IF(AB39="No",5,0) | AD39: Tailwind | AE39: =IF(AD39="Tailwind",10,0) | AF39: Structural (10 Years Consistency) | AG39: =IF(AF39="Structural (10 Years Consistency)",10,IF(AF39="Shallow Cyclical (2 to 3 years growth)",5,0)) | AH39: No | AI39: =IF(AH39="Yes due to Product Mix change or Operating Leverage",10,IF(AH39="Yes, these are peak margins",-5,IF(AH39="No",5,0))) | AJ39: Stable | AK39: =IF(AJ39="Stable",10,0) | AL39: Yes | AM39: =IF(AL39="Yes",10,0) | AN39: B2B | AO39: =IF(AN39="B2C",10,IF(AN39="B2B",5,0)) | AP39: Yes | AQ39: =IF(AP39="Yes",10,0) | AR39: Higher Annuity, Lower One Time | AS39: =IF(AR39="Fully Annuity",10,IF(AR39="Higher Annuity, Lower One Time",5,IF(AR39="Higher One Time, Lower Annuity",3,0))) | AT39: Good | AU39: =IF(AT39="Good",10,0) | AV39: Yes for more than 2 years | AW39: =IF(AV39="Yes for more than 2 years",10,IF(AV39="Yes only for next 1 to 2 years",5,0)) | AX39: Above 40 | AY39: =IF(AX39="Above 40",20,IF(AX39="20 to 40",10,IF(AX39="0 to 20",-5,0))) | AZ39: Between 50 to 75 | BA39: =IF(AZ39="Between 50 to 75",10,IF(AZ39="Above 75",0,0)) | BB39: Stage 2 | BC39: =IF(BB39="Stage 2",20,IF(BB39="Stage 1",0,IF(BB39="Stage 3",5,IF(BB39="Stage 4",-5,0)))) | BD39: Positive Trend | BE39: =IF(BD39="Positive Trend",20,IF(BD39="Negative Trend",-10,0)) | BF39: Uptrend | BG39: =IF(BF39="Uptrend",10,IF(BF39="Sideways",5,0)) | BH39: Uptrend | BI39: =IF(BH39="Uptrend",10,IF(BH39="Sideways",5,0)) | BJ39: Blue sky scenario | BK39: =IF(BJ39="Overhead supply in last 2 years in last 2 years",-5,IF(BJ39="Close to 52 week high or retracement",5,IF(BJ39="Blue sky scenario",10,IF(BJ39="Long term Downtrend",-10,0)))) | BL39: Yes | BM39: =IF(BL39="Yes",10,0) | BN39: More than 20% | BO39: =IF(BN39="More than 20%",10,IF(BN39="Between 12 to 20%",5,IF(BN39="Less than 12%",0,0))) | BP39: No | BQ39: =IF(BP39="No",10,0) | BR39: Yes | BS39: =IF(BR39="NO",5,0) | BT39: Above 2 | BU39: =IF(BT39="Above 2",0,IF(BT39="Between 1.5 to 2",5,IF(BT39="Less than 1.5",10,0))) | BV39: Above 70% | BW39: =IF(BV39="Above 70%",10,IF(BV39="Between 50% to 70%",5,IF(BV39="Less than 50%",0,IF(BV39="Negative",-10,IF(BV39="Less than 50% and Borrowings are increasing",-5,0))))) | BX39: Less than 0.7 | BY39: =IF(BX39="More than 1.2",-10,IF(BX39="Between 0.7 to 1.2",0,IF(BX39="Less than 0.7",10,0))) | BZ39: No | CA39: =IF(BZ39="Yes",-10,0) | CB39: Less than 15% | CC39: =IF(CB39="More than 15%",-10,IF(CB39="Less than 15%",10,0)) | CD39: No | CE39: =IF(CD39="Yes, more than 10%",-10,IF(CD39="No",10,0))
A40: =IF(B40=0,"",RANK(B40,$B$2:$B$184,0)) | B40: =SUM(N40,Y40,AA40,AC40,AE40,AG40,AI40,AK40,AM40,AO40,AQ40,AS40,AU40,AW40,AY40,BA40,BC40,BE40,BG40,BI40,BK40,BM40,BO40,BQ40,BS40,BU40,BW40,BY40,CA40,CC40,CE40) | C40: SHILPAMED | D40: Shilpa Medicare Limited | E40: healthcare | F40: pharmaceuticals - indian - formulations | G40: midcap | H40: 17835.11 | I40: 928.05 | J40: 1.77 | K40: 1187365 | L40: 90 | M40: Outperforming | N40: =IF(M40="Underperforming",-5,IF(L40>=95,15,IF(L40>=90,10,IF(L40>=80,5,0)))) | O40: 83.98 | P40: 79.16 | Q40: 778.02 | R40: Near 52W High Breakout | S40: Nifty Pharma | T40: 15.25 | U40: 125.12 | V40: 95.34 | W40: 37.14 | X40: Growing Industry | Y40: =IF(X40="Growing Industry",10,IF(X40="Cyclical in an Upturn",5,0)) | Z40: Too Many Players with High ROCE | AA40: =IF(Z40="Monopoly",10,IF(Z40="Oligopoly",5,IF(Z40="Duopoly that cooperate",10,IF(Z40="Duopoly that compete",5,IF(Z40="Too many players with High ROCE",5,0))))) | AB40: Yes | AC40: =IF(AB40="No",5,0) | AD40: Tailwind | AE40: =IF(AD40="Tailwind",10,0) | AF40: Structural (10 Years Consistency) | AG40: =IF(AF40="Structural (10 Years Consistency)",10,IF(AF40="Shallow Cyclical (2 to 3 years growth)",5,0)) | AH40: No | AI40: =IF(AH40="Yes due to Product Mix change or Operating Leverage",10,IF(AH40="Yes, these are peak margins",-5,IF(AH40="No",5,0))) | AJ40: Stable | AK40: =IF(AJ40="Stable",10,0) | AL40: Yes | AM40: =IF(AL40="Yes",10,0) | AN40: B2B | AO40: =IF(AN40="B2C",10,IF(AN40="B2B",5,0)) | AP40: Yes | AQ40: =IF(AP40="Yes",10,0) | AR40: Higher Annuity, Lower One Time | AS40: =IF(AR40="Fully Annuity",10,IF(AR40="Higher Annuity, Lower One Time",5,IF(AR40="Higher One Time, Lower Annuity",3,0))) | AT40: Good | AU40: =IF(AT40="Good",10,0) | AV40: Yes for more than 2 years | AW40: =IF(AV40="Yes for more than 2 years",10,IF(AV40="Yes only for next 1 to 2 years",5,0)) | AX40: Above 40 | AY40: =IF(AX40="Above 40",20,IF(AX40="20 to 40",10,IF(AX40="0 to 20",-5,0))) | AZ40: Above 75 | BA40: =IF(AZ40="Between 50 to 75",10,IF(AZ40="Above 75",0,0)) | BB40: Stage 2 | BC40: =IF(BB40="Stage 2",20,IF(BB40="Stage 1",0,IF(BB40="Stage 3",5,IF(BB40="Stage 4",-5,0)))) | BD40: Positive Trend | BE40: =IF(BD40="Positive Trend",20,IF(BD40="Negative Trend",-10,0)) | BF40: Uptrend | BG40: =IF(BF40="Uptrend",10,IF(BF40="Sideways",5,0)) | BH40: Uptrend | BI40: =IF(BH40="Uptrend",10,IF(BH40="Sideways",5,0)) | BJ40: Blue sky scenario | BK40: =IF(BJ40="Overhead supply in last 2 years in last 2 years",-5,IF(BJ40="Close to 52 week high or retracement",5,IF(BJ40="Blue sky scenario",10,IF(BJ40="Long term Downtrend",-10,0)))) | BL40: Yes | BM40: =IF(BL40="Yes",10,0) | BN40: More than 20% | BO40: =IF(BN40="More than 20%",10,IF(BN40="Between 12 to 20%",5,IF(BN40="Less than 12%",0,0))) | BP40: No | BQ40: =IF(BP40="No",10,0) | BR40: Yes | BS40: =IF(BR40="NO",5,0) | BT40: Above 2 | BU40: =IF(BT40="Above 2",0,IF(BT40="Between 1.5 to 2",5,IF(BT40="Less than 1.5",10,0))) | BV40: Above 70% | BW40: =IF(BV40="Above 70%",10,IF(BV40="Between 50% to 70%",5,IF(BV40="Less than 50%",0,IF(BV40="Negative",-10,IF(BV40="Less than 50% and Borrowings are increasing",-5,0))))) | BX40: Less than 0.7 | BY40: =IF(BX40="More than 1.2",-10,IF(BX40="Between 0.7 to 1.2",0,IF(BX40="Less than 0.7",10,0))) | BZ40: No | CA40: =IF(BZ40="Yes",-10,0) | CB40: Less than 15% | CC40: =IF(CB40="More than 15%",-10,IF(CB40="Less than 15%",10,0)) | CD40: No | CE40: =IF(CD40="Yes, more than 10%",-10,IF(CD40="No",10,0))
A41: =IF(B41=0,"",RANK(B41,$B$2:$B$184,0)) | B41: =SUM(N41,Y41,AA41,AC41,AE41,AG41,AI41,AK41,AM41,AO41,AQ41,AS41,AU41,AW41,AY41,BA41,BC41,BE41,BG41,BI41,BK41,BM41,BO41,BQ41,BS41,BU41,BW41,BY41,CA41,CC41,CE41) | C41: BAFNAPH | D41: Bafna Pharmaceuticals Ltd | E41: healthcare | F41: pharmaceuticals - indian - formulations | G41: smallcap | H41: 726.96 | I41: 309 | J41: 0.55 | K41: 6535 | L41: 91 | M41: Outperforming | N41: =IF(M41="Underperforming",-5,IF(L41>=95,15,IF(L41>=90,10,IF(L41>=80,5,0)))) | O41: 73.29 | P41: 59.28 | Q41: 240 | R41: Near 52W High Breakout | S41: Nifty Pharma | T41: 15.25 | U41: 123.61 | V41: 94.02 | W41: 41.09 | X41: Growing Industry | Y41: =IF(X41="Growing Industry",10,IF(X41="Cyclical in an Upturn",5,0)) | Z41: Too Many Players with High ROCE | AA41: =IF(Z41="Monopoly",10,IF(Z41="Oligopoly",5,IF(Z41="Duopoly that cooperate",10,IF(Z41="Duopoly that compete",5,IF(Z41="Too many players with High ROCE",5,0))))) | AB41: Yes | AC41: =IF(AB41="No",5,0) | AD41: Tailwind | AE41: =IF(AD41="Tailwind",10,0) | AF41: Structural (10 Years Consistency) | AG41: =IF(AF41="Structural (10 Years Consistency)",10,IF(AF41="Shallow Cyclical (2 to 3 years growth)",5,0)) | AH41: No | AI41: =IF(AH41="Yes due to Product Mix change or Operating Leverage",10,IF(AH41="Yes, these are peak margins",-5,IF(AH41="No",5,0))) | AJ41: Stable | AK41: =IF(AJ41="Stable",10,0) | AL41: Yes | AM41: =IF(AL41="Yes",10,0) | AN41: B2B | AO41: =IF(AN41="B2C",10,IF(AN41="B2B",5,0)) | AP41: Yes | AQ41: =IF(AP41="Yes",10,0) | AR41: Higher Annuity, Lower One Time | AS41: =IF(AR41="Fully Annuity",10,IF(AR41="Higher Annuity, Lower One Time",5,IF(AR41="Higher One Time, Lower Annuity",3,0))) | AT41: Good | AU41: =IF(AT41="Good",10,0) | AV41: Yes for more than 2 years | AW41: =IF(AV41="Yes for more than 2 years",10,IF(AV41="Yes only for next 1 to 2 years",5,0)) | AX41: Above 40 | AY41: =IF(AX41="Above 40",20,IF(AX41="20 to 40",10,IF(AX41="0 to 20",-5,0))) | AZ41: Between 50 to 75 | BA41: =IF(AZ41="Between 50 to 75",10,IF(AZ41="Above 75",0,0)) | BB41: Stage 2 | BC41: =IF(BB41="Stage 2",20,IF(BB41="Stage 1",0,IF(BB41="Stage 3",5,IF(BB41="Stage 4",-5,0)))) | BD41: Positive Trend | BE41: =IF(BD41="Positive Trend",20,IF(BD41="Negative Trend",-10,0)) | BF41: Uptrend | BG41: =IF(BF41="Uptrend",10,IF(BF41="Sideways",5,0)) | BH41: Uptrend | BI41: =IF(BH41="Uptrend",10,IF(BH41="Sideways",5,0)) | BJ41: Blue sky scenario | BK41: =IF(BJ41="Overhead supply in last 2 years in last 2 years",-5,IF(BJ41="Close to 52 week high or retracement",5,IF(BJ41="Blue sky scenario",10,IF(BJ41="Long term Downtrend",-10,0)))) | BL41: Yes | BM41: =IF(BL41="Yes",10,0) | BN41: Less than 12% | BO41: =IF(BN41="More than 20%",10,IF(BN41="Between 12 to 20%",5,IF(BN41="Less than 12%",0,0))) | BP41: No | BQ41: =IF(BP41="No",10,0) | BR41: Yes | BS41: =IF(BR41="NO",5,0) | BT41: Above 2 | BU41: =IF(BT41="Above 2",0,IF(BT41="Between 1.5 to 2",5,IF(BT41="Less than 1.5",10,0))) | BV41: Above 70% | BW41: =IF(BV41="Above 70%",10,IF(BV41="Between 50% to 70%",5,IF(BV41="Less than 50%",0,IF(BV41="Negative",-10,IF(BV41="Less than 50% and Borrowings are increasing",-5,0))))) | BX41: Less than 0.7 | BY41: =IF(BX41="More than 1.2",-10,IF(BX41="Between 0.7 to 1.2",0,IF(BX41="Less than 0.7",10,0))) | BZ41: No | CA41: =IF(BZ41="Yes",-10,0) | CB41: Less than 15% | CC41: =IF(CB41="More than 15%",-10,IF(CB41="Less than 15%",10,0)) | CD41: No | CE41: =IF(CD41="Yes, more than 10%",-10,IF(CD41="No",10,0))
A42: =IF(B42=0,"",RANK(B42,$B$2:$B$184,0)) | B42: =SUM(N42,Y42,AA42,AC42,AE42,AG42,AI42,AK42,AM42,AO42,AQ42,AS42,AU42,AW42,AY42,BA42,BC42,BE42,BG42,BI42,BK42,BM42,BO42,BQ42,BS42,BU42,BW42,BY42,CA42,CC42,CE42) | C42: DIVISLAB | D42: Divi's Laboratories Limited | E42: healthcare | F42: pharmaceuticals - indian - bulk drugs | G42: largecap | H42: 244178 | I42: 9158 | J42: -0.43 | K42: 878300 | L42: 53 | M42: Outperforming | N42: =IF(M42="Underperforming",-5,IF(L42>=95,15,IF(L42>=90,10,IF(L42>=80,5,0)))) | O42: 79.91 | P42: 48.65 | Q42: 8112 | R42: Near 52W High Breakout | S42: Nifty Pharma | T42: 15.25 | U42: 48.32 | V42: 28.69 | W42: 16.39 | X42: Growing Industry | Y42: =IF(X42="Growing Industry",10,IF(X42="Cyclical in an Upturn",5,0)) | Z42: Too Many Players with High ROCE | AA42: =IF(Z42="Monopoly",10,IF(Z42="Oligopoly",5,IF(Z42="Duopoly that cooperate",10,IF(Z42="Duopoly that compete",5,IF(Z42="Too many players with High ROCE",5,0))))) | AB42: Yes | AC42: =IF(AB42="No",5,0) | AD42: Tailwind | AE42: =IF(AD42="Tailwind",10,0) | AF42: Structural (10 Years Consistency) | AG42: =IF(AF42="Structural (10 Years Consistency)",10,IF(AF42="Shallow Cyclical (2 to 3 years growth)",5,0)) | AH42: No | AI42: =IF(AH42="Yes due to Product Mix change or Operating Leverage",10,IF(AH42="Yes, these are peak margins",-5,IF(AH42="No",5,0))) | AJ42: Stable | AK42: =IF(AJ42="Stable",10,0) | AL42: Yes | AM42: =IF(AL42="Yes",10,0) | AN42: B2B | AO42: =IF(AN42="B2C",10,IF(AN42="B2B",5,0)) | AP42: Yes | AQ42: =IF(AP42="Yes",10,0) | AR42: Higher Annuity, Lower One Time | AS42: =IF(AR42="Fully Annuity",10,IF(AR42="Higher Annuity, Lower One Time",5,IF(AR42="Higher One Time, Lower Annuity",3,0))) | AT42: Good | AU42: =IF(AT42="Good",10,0) | AV42: Yes for more than 2 years | AW42: =IF(AV42="Yes for more than 2 years",10,IF(AV42="Yes only for next 1 to 2 years",5,0)) | AX42: Above 40 | AY42: =IF(AX42="Above 40",20,IF(AX42="20 to 40",10,IF(AX42="0 to 20",-5,0))) | AZ42: Above 75 | BA42: =IF(AZ42="Between 50 to 75",10,IF(AZ42="Above 75",0,0)) | BB42: Stage 2 | BC42: =IF(BB42="Stage 2",20,IF(BB42="Stage 1",0,IF(BB42="Stage 3",5,IF(BB42="Stage 4",-5,0)))) | BD42: Positive Trend | BE42: =IF(BD42="Positive Trend",20,IF(BD42="Negative Trend",-10,0)) | BF42: Uptrend | BG42: =IF(BF42="Uptrend",10,IF(BF42="Sideways",5,0)) | BH42: Uptrend | BI42: =IF(BH42="Uptrend",10,IF(BH42="Sideways",5,0)) | BJ42: Blue sky scenario | BK42: =IF(BJ42="Overhead supply in last 2 years in last 2 years",-5,IF(BJ42="Close to 52 week high or retracement",5,IF(BJ42="Blue sky scenario",10,IF(BJ42="Long term Downtrend",-10,0)))) | BL42: Yes | BM42: =IF(BL42="Yes",10,0) | BN42: More than 20% | BO42: =IF(BN42="More than 20%",10,IF(BN42="Between 12 to 20%",5,IF(BN42="Less than 12%",0,0))) | BP42: No | BQ42: =IF(BP42="No",10,0) | BR42: Yes | BS42: =IF(BR42="NO",5,0) | BT42: Less than 1.5 | BU42: =IF(BT42="Above 2",0,IF(BT42="Between 1.5 to 2",5,IF(BT42="Less than 1.5",10,0))) | BV42: Above 70% | BW42: =IF(BV42="Above 70%",10,IF(BV42="Between 50% to 70%",5,IF(BV42="Less than 50%",0,IF(BV42="Negative",-10,IF(BV42="Less than 50% and Borrowings are increasing",-5,0))))) | BX42: Less than 0.7 | BY42: =IF(BX42="More than 1.2",-10,IF(BX42="Between 0.7 to 1.2",0,IF(BX42="Less than 0.7",10,0))) | BZ42: No | CA42: =IF(BZ42="Yes",-10,0) | CB42: Less than 15% | CC42: =IF(CB42="More than 15%",-10,IF(CB42="Less than 15%",10,0)) | CD42: No | CE42: =IF(CD42="Yes, more than 10%",-10,IF(CD42="No",10,0))
A43: =IF(B43=0,"",RANK(B43,$B$2:$B$184,0)) | B43: =SUM(N43,Y43,AA43,AC43,AE43,AG43,AI43,AK43,AM43,AO43,AQ43,AS43,AU43,AW43,AY43,BA43,BC43,BE43,BG43,BI43,BK43,BM43,BO43,BQ43,BS43,BU43,BW43,BY43,CA43,CC43,CE43) | C43: LAURUSLABS | D43: Laurus Labs Limited | E43: healthcare | F43: pharmaceuticals - indian - bulk drugs & formln | G43: largecap | H43: 104100.69 | I43: 1905.5 | J43: -1.11 | K43: 2871410 | L43: 72 | M43: Outperforming | N43: =IF(M43="Underperforming",-5,IF(L43>=95,15,IF(L43>=90,10,IF(L43>=80,5,0)))) | O43: 71.91 | P43: 72.52 | Q43: 1672.12 | R43: Near 52W High Breakout | S43: Nifty Pharma | T43: 15.25 | U43: 104.8 | V43: 77.7 | W43: 23.93 | X43: Growing Industry | Y43: =IF(X43="Growing Industry",10,IF(X43="Cyclical in an Upturn",5,0)) | Z43: Too Many Players with High ROCE | AA43: =IF(Z43="Monopoly",10,IF(Z43="Oligopoly",5,IF(Z43="Duopoly that cooperate",10,IF(Z43="Duopoly that compete",5,IF(Z43="Too many players with High ROCE",5,0))))) | AB43: Yes | AC43: =IF(AB43="No",5,0) | AD43: Tailwind | AE43: =IF(AD43="Tailwind",10,0) | AF43: Structural (10 Years Consistency) | AG43: =IF(AF43="Structural (10 Years Consistency)",10,IF(AF43="Shallow Cyclical (2 to 3 years growth)",5,0)) | AH43: No | AI43: =IF(AH43="Yes due to Product Mix change or Operating Leverage",10,IF(AH43="Yes, these are peak margins",-5,IF(AH43="No",5,0))) | AJ43: Stable | AK43: =IF(AJ43="Stable",10,0) | AL43: Yes | AM43: =IF(AL43="Yes",10,0) | AN43: B2B | AO43: =IF(AN43="B2C",10,IF(AN43="B2B",5,0)) | AP43: Yes | AQ43: =IF(AP43="Yes",10,0) | AR43: Higher Annuity, Lower One Time | AS43: =IF(AR43="Fully Annuity",10,IF(AR43="Higher Annuity, Lower One Time",5,IF(AR43="Higher One Time, Lower Annuity",3,0))) | AT43: Good | AU43: =IF(AT43="Good",10,0) | AV43: Yes for more than 2 years | AW43: =IF(AV43="Yes for more than 2 years",10,IF(AV43="Yes only for next 1 to 2 years",5,0)) | AX43: Above 40 | AY43: =IF(AX43="Above 40",20,IF(AX43="20 to 40",10,IF(AX43="0 to 20",-5,0))) | AZ43: Between 50 to 75 | BA43: =IF(AZ43="Between 50 to 75",10,IF(AZ43="Above 75",0,0)) | BB43: Stage 2 | BC43: =IF(BB43="Stage 2",20,IF(BB43="Stage 1",0,IF(BB43="Stage 3",5,IF(BB43="Stage 4",-5,0)))) | BD43: Positive Trend | BE43: =IF(BD43="Positive Trend",20,IF(BD43="Negative Trend",-10,0)) | BF43: Uptrend | BG43: =IF(BF43="Uptrend",10,IF(BF43="Sideways",5,0)) | BH43: Uptrend | BI43: =IF(BH43="Uptrend",10,IF(BH43="Sideways",5,0)) | BJ43: Blue sky scenario | BK43: =IF(BJ43="Overhead supply in last 2 years in last 2 years",-5,IF(BJ43="Close to 52 week high or retracement",5,IF(BJ43="Blue sky scenario",10,IF(BJ43="Long term Downtrend",-10,0)))) | BL43: Yes | BM43: =IF(BL43="Yes",10,0) | BN43: More than 20% | BO43: =IF(BN43="More than 20%",10,IF(BN43="Between 12 to 20%",5,IF(BN43="Less than 12%",0,0))) | BP43: No | BQ43: =IF(BP43="No",10,0) | BR43: Yes | BS43: =IF(BR43="NO",5,0) | BT43: Above 2 | BU43: =IF(BT43="Above 2",0,IF(BT43="Between 1.5 to 2",5,IF(BT43="Less than 1.5",10,0))) | BV43: Above 70% | BW43: =IF(BV43="Above 70%",10,IF(BV43="Between 50% to 70%",5,IF(BV43="Less than 50%",0,IF(BV43="Negative",-10,IF(BV43="Less than 50% and Borrowings are increasing",-5,0))))) | BX43: Less than 0.7 | BY43: =IF(BX43="More than 1.2",-10,IF(BX43="Between 0.7 to 1.2",0,IF(BX43="Less than 0.7",10,0))) | BZ43: No | CA43: =IF(BZ43="Yes",-10,0) | CB43: Less than 15% | CC43: =IF(CB43="More than 15%",-10,IF(CB43="Less than 15%",10,0)) | CD43: No | CE43: =IF(CD43="Yes, more than 10%",-10,IF(CD43="No",10,0))
A44: =IF(B44=0,"",RANK(B44,$B$2:$B$184,0)) | B44: =SUM(N44,Y44,AA44,AC44,AE44,AG44,AI44,AK44,AM44,AO44,AQ44,AS44,AU44,AW44,AY44,BA44,BC44,BE44,BG44,BI44,BK44,BM44,BO44,BQ44,BS44,BU44,BW44,BY44,CA44,CC44,CE44) | C44: FOSECOIND | D44: Foseco India Limited | E44: chemicals | F44: chemicals | G44: smallcap | H44: 4690.81 | I44: 6846.5 | J44: 10.01 | K44: 178685 | L44: 32 | M44: Outperforming | N44: =IF(M44="Underperforming",-5,IF(L44>=95,15,IF(L44>=90,10,IF(L44>=80,5,0)))) | O44: 73 | P44: 30.43 | Q44: 5381.17 | R44: Volume Spike & Near 52W High Breakout | S44: Nifty 50 | T44: -8.33 | U44: 14.02 | V44: 24.38 | W44: 9.79 | X44: Growing Industry | Y44: =IF(X44="Growing Industry",10,IF(X44="Cyclical in an Upturn",5,0)) | Z44: Too Many Players with High ROCE | AA44: =IF(Z44="Monopoly",10,IF(Z44="Oligopoly",5,IF(Z44="Duopoly that cooperate",10,IF(Z44="Duopoly that compete",5,IF(Z44="Too many players with High ROCE",5,0))))) | AB44: No | AC44: =IF(AB44="No",5,0) | AD44: Tailwind | AE44: =IF(AD44="Tailwind",10,0) | AF44: Structural (10 Years Consistency) | AG44: =IF(AF44="Structural (10 Years Consistency)",10,IF(AF44="Shallow Cyclical (2 to 3 years growth)",5,0)) | AH44: No | AI44: =IF(AH44="Yes due to Product Mix change or Operating Leverage",10,IF(AH44="Yes, these are peak margins",-5,IF(AH44="No",5,0))) | AJ44: Stable | AK44: =IF(AJ44="Stable",10,0) | AL44: Yes | AM44: =IF(AL44="Yes",10,0) | AN44: B2B | AO44: =IF(AN44="B2C",10,IF(AN44="B2B",5,0)) | AP44: Yes | AQ44: =IF(AP44="Yes",10,0) | AR44: Higher One Time, Lower Annuity | AS44: =IF(AR44="Fully Annuity",10,IF(AR44="Higher Annuity, Lower One Time",5,IF(AR44="Higher One Time, Lower Annuity",3,0))) | AT44: Good | AU44: =IF(AT44="Good",10,0) | AV44: Yes for more than 2 years | AW44: =IF(AV44="Yes for more than 2 years",10,IF(AV44="Yes only for next 1 to 2 years",5,0)) | AX44: 20 to 40 | AY44: =IF(AX44="Above 40",20,IF(AX44="20 to 40",10,IF(AX44="0 to 20",-5,0))) | AZ44: Between 50 to 75 | BA44: =IF(AZ44="Between 50 to 75",10,IF(AZ44="Above 75",0,0)) | BB44: Stage 2 | BC44: =IF(BB44="Stage 2",20,IF(BB44="Stage 1",0,IF(BB44="Stage 3",5,IF(BB44="Stage 4",-5,0)))) | BD44: Positive Trend | BE44: =IF(BD44="Positive Trend",20,IF(BD44="Negative Trend",-10,0)) | BF44: Uptrend | BG44: =IF(BF44="Uptrend",10,IF(BF44="Sideways",5,0)) | BH44: Uptrend | BI44: =IF(BH44="Uptrend",10,IF(BH44="Sideways",5,0)) | BJ44: Blue sky scenario | BK44: =IF(BJ44="Overhead supply in last 2 years in last 2 years",-5,IF(BJ44="Close to 52 week high or retracement",5,IF(BJ44="Blue sky scenario",10,IF(BJ44="Long term Downtrend",-10,0)))) | BL44: Yes | BM44: =IF(BL44="Yes",10,0) | BN44: More than 20% | BO44: =IF(BN44="More than 20%",10,IF(BN44="Between 12 to 20%",5,IF(BN44="Less than 12%",0,0))) | BP44: No | BQ44: =IF(BP44="No",10,0) | BR44: Yes | BS44: =IF(BR44="NO",5,0) | BT44: Between 1.5 to 2 | BU44: =IF(BT44="Above 2",0,IF(BT44="Between 1.5 to 2",5,IF(BT44="Less than 1.5",10,0))) | BV44: Above 70% | BW44: =IF(BV44="Above 70%",10,IF(BV44="Between 50% to 70%",5,IF(BV44="Less than 50%",0,IF(BV44="Negative",-10,IF(BV44="Less than 50% and Borrowings are increasing",-5,0))))) | BX44: Less than 0.7 | BY44: =IF(BX44="More than 1.2",-10,IF(BX44="Between 0.7 to 1.2",0,IF(BX44="Less than 0.7",10,0))) | BZ44: No | CA44: =IF(BZ44="Yes",-10,0) | CB44: Less than 15% | CC44: =IF(CB44="More than 15%",-10,IF(CB44="Less than 15%",10,0)) | CD44: No | CE44: =IF(CD44="Yes, more than 10%",-10,IF(CD44="No",10,0))
A45: =IF(B45=0,"",RANK(B45,$B$2:$B$184,0)) | B45: =SUM(N45,Y45,AA45,AC45,AE45,AG45,AI45,AK45,AM45,AO45,AQ45,AS45,AU45,AW45,AY45,BA45,BC45,BE45,BG45,BI45,BK45,BM45,BO45,BQ45,BS45,BU45,BW45,BY45,CA45,CC45,CE45) | C45: RUBYMILLS | D45: The Ruby Mills Limited | E45: textiles | F45: textiles - composite | G45: smallcap | H45: 1445.95 | I45: 462.1 | J45: 6.87 | K45: 90742 | L45: 75 | M45: Outperforming | N45: =IF(M45="Underperforming",-5,IF(L45>=95,15,IF(L45>=90,10,IF(L45>=80,5,0)))) | O45: 74.89 | P45: 53.06 | Q45: 331.82 | R45: Near 52W High Breakout | S45: Nifty 50 | T45: -8.33 | U45: 96.27 | V45: 114.1 | W45: 25.16 | X45: Growing Industry | Y45: =IF(X45="Growing Industry",10,IF(X45="Cyclical in an Upturn",5,0)) | Z45: Too Many Players with High ROCE | AA45: =IF(Z45="Monopoly",10,IF(Z45="Oligopoly",5,IF(Z45="Duopoly that cooperate",10,IF(Z45="Duopoly that compete",5,IF(Z45="Too many players with High ROCE",5,0))))) | AB45: No | AC45: =IF(AB45="No",5,0) | AD45: Tailwind | AE45: =IF(AD45="Tailwind",10,0) | AF45: Structural (10 Years Consistency) | AG45: =IF(AF45="Structural (10 Years Consistency)",10,IF(AF45="Shallow Cyclical (2 to 3 years growth)",5,0)) | AH45: No | AI45: =IF(AH45="Yes due to Product Mix change or Operating Leverage",10,IF(AH45="Yes, these are peak margins",-5,IF(AH45="No",5,0))) | AJ45: Stable | AK45: =IF(AJ45="Stable",10,0) | AL45: Yes | AM45: =IF(AL45="Yes",10,0) | AN45: B2B | AO45: =IF(AN45="B2C",10,IF(AN45="B2B",5,0)) | AP45: Yes | AQ45: =IF(AP45="Yes",10,0) | AR45: Higher One Time, Lower Annuity | AS45: =IF(AR45="Fully Annuity",10,IF(AR45="Higher Annuity, Lower One Time",5,IF(AR45="Higher One Time, Lower Annuity",3,0))) | AT45: Good | AU45: =IF(AT45="Good",10,0) | AV45: Yes for more than 2 years | AW45: =IF(AV45="Yes for more than 2 years",10,IF(AV45="Yes only for next 1 to 2 years",5,0)) | AX45: Above 40 | AY45: =IF(AX45="Above 40",20,IF(AX45="20 to 40",10,IF(AX45="0 to 20",-5,0))) | AZ45: Between 50 to 75 | BA45: =IF(AZ45="Between 50 to 75",10,IF(AZ45="Above 75",0,0)) | BB45: Stage 2 | BC45: =IF(BB45="Stage 2",20,IF(BB45="Stage 1",0,IF(BB45="Stage 3",5,IF(BB45="Stage 4",-5,0)))) | BD45: Positive Trend | BE45: =IF(BD45="Positive Trend",20,IF(BD45="Negative Trend",-10,0)) | BF45: Uptrend | BG45: =IF(BF45="Uptrend",10,IF(BF45="Sideways",5,0)) | BH45: Uptrend | BI45: =IF(BH45="Uptrend",10,IF(BH45="Sideways",5,0)) | BJ45: Blue sky scenario | BK45: =IF(BJ45="Overhead supply in last 2 years in last 2 years",-5,IF(BJ45="Close to 52 week high or retracement",5,IF(BJ45="Blue sky scenario",10,IF(BJ45="Long term Downtrend",-10,0)))) | BL45: Yes | BM45: =IF(BL45="Yes",10,0) | BN45: Less than 12% | BO45: =IF(BN45="More than 20%",10,IF(BN45="Between 12 to 20%",5,IF(BN45="Less than 12%",0,0))) | BP45: No | BQ45: =IF(BP45="No",10,0) | BR45: No | BS45: =IF(BR45="NO",5,0) | BT45: Above 2 | BU45: =IF(BT45="Above 2",0,IF(BT45="Between 1.5 to 2",5,IF(BT45="Less than 1.5",10,0))) | BV45: Above 70% | BW45: =IF(BV45="Above 70%",10,IF(BV45="Between 50% to 70%",5,IF(BV45="Less than 50%",0,IF(BV45="Negative",-10,IF(BV45="Less than 50% and Borrowings are increasing",-5,0))))) | BX45: Less than 0.7 | BY45: =IF(BX45="More than 1.2",-10,IF(BX45="Between 0.7 to 1.2",0,IF(BX45="Less than 0.7",10,0))) | BZ45: No | CA45: =IF(BZ45="Yes",-10,0) | CB45: Less than 15% | CC45: =IF(CB45="More than 15%",-10,IF(CB45="Less than 15%",10,0)) | CD45: No | CE45: =IF(CD45="Yes, more than 10%",-10,IF(CD45="No",10,0))
A46: =IF(B46=0,"",RANK(B46,$B$2:$B$184,0)) | B46: =SUM(N46,Y46,AA46,AC46,AE46,AG46,AI46,AK46,AM46,AO46,AQ46,AS46,AU46,AW46,AY46,BA46,BC46,BE46,BG46,BI46,BK46,BM46,BO46,BQ46,BS46,BU46,BW46,BY46,CA46,CC46,CE46) | C46: KAPSTON | D46: Kapston Services Ltd | E46: miscellaneous | F46: miscellaneous | G46: smallcap | H46: 1714.7 | I46: 577.15 | J46: 2.43 | K46: 43954 | L46: 85 | M46: Outperforming | N46: =IF(M46="Underperforming",-5,IF(L46>=95,15,IF(L46>=90,10,IF(L46>=80,5,0)))) | O46: 72.21 | P46: 41.01 | Q46: 450.03 | R46: Near 52W High Breakout | S46: Nifty 50 | T46: -8.33 | U46: 134.6 | V46: 155.92 | W46: 34.31 | X46: Growing Industry | Y46: =IF(X46="Growing Industry",10,IF(X46="Cyclical in an Upturn",5,0)) | Z46: Too Many Players with High ROCE | AA46: =IF(Z46="Monopoly",10,IF(Z46="Oligopoly",5,IF(Z46="Duopoly that cooperate",10,IF(Z46="Duopoly that compete",5,IF(Z46="Too many players with High ROCE",5,0))))) | AB46: No | AC46: =IF(AB46="No",5,0) | AD46: Tailwind | AE46: =IF(AD46="Tailwind",10,0) | AF46: Structural (10 Years Consistency) | AG46: =IF(AF46="Structural (10 Years Consistency)",10,IF(AF46="Shallow Cyclical (2 to 3 years growth)",5,0)) | AH46: No | AI46: =IF(AH46="Yes due to Product Mix change or Operating Leverage",10,IF(AH46="Yes, these are peak margins",-5,IF(AH46="No",5,0))) | AJ46: Stable | AK46: =IF(AJ46="Stable",10,0) | AL46: Yes | AM46: =IF(AL46="Yes",10,0) | AN46: B2B | AO46: =IF(AN46="B2C",10,IF(AN46="B2B",5,0)) | AP46: Yes | AQ46: =IF(AP46="Yes",10,0) | AR46: Higher One Time, Lower Annuity | AS46: =IF(AR46="Fully Annuity",10,IF(AR46="Higher Annuity, Lower One Time",5,IF(AR46="Higher One Time, Lower Annuity",3,0))) | AT46: Good | AU46: =IF(AT46="Good",10,0) | AV46: Yes for more than 2 years | AW46: =IF(AV46="Yes for more than 2 years",10,IF(AV46="Yes only for next 1 to 2 years",5,0)) | AX46: Above 40 | AY46: =IF(AX46="Above 40",20,IF(AX46="20 to 40",10,IF(AX46="0 to 20",-5,0))) | AZ46: Between 50 to 75 | BA46: =IF(AZ46="Between 50 to 75",10,IF(AZ46="Above 75",0,0)) | BB46: Stage 2 | BC46: =IF(BB46="Stage 2",20,IF(BB46="Stage 1",0,IF(BB46="Stage 3",5,IF(BB46="Stage 4",-5,0)))) | BD46: Positive Trend | BE46: =IF(BD46="Positive Trend",20,IF(BD46="Negative Trend",-10,0)) | BF46: Uptrend | BG46: =IF(BF46="Uptrend",10,IF(BF46="Sideways",5,0)) | BH46: Uptrend | BI46: =IF(BH46="Uptrend",10,IF(BH46="Sideways",5,0)) | BJ46: Blue sky scenario | BK46: =IF(BJ46="Overhead supply in last 2 years in last 2 years",-5,IF(BJ46="Close to 52 week high or retracement",5,IF(BJ46="Blue sky scenario",10,IF(BJ46="Long term Downtrend",-10,0)))) | BL46: Yes | BM46: =IF(BL46="Yes",10,0) | BN46: More than 20% | BO46: =IF(BN46="More than 20%",10,IF(BN46="Between 12 to 20%",5,IF(BN46="Less than 12%",0,0))) | BP46: No | BQ46: =IF(BP46="No",10,0) | BR46: Yes | BS46: =IF(BR46="NO",5,0) | BT46: Less than 1.5 | BU46: =IF(BT46="Above 2",0,IF(BT46="Between 1.5 to 2",5,IF(BT46="Less than 1.5",10,0))) | BV46: Above 70% | BW46: =IF(BV46="Above 70%",10,IF(BV46="Between 50% to 70%",5,IF(BV46="Less than 50%",0,IF(BV46="Negative",-10,IF(BV46="Less than 50% and Borrowings are increasing",-5,0))))) | BX46: More than 1.2 | BY46: =IF(BX46="More than 1.2",-10,IF(BX46="Between 0.7 to 1.2",0,IF(BX46="Less than 0.7",10,0))) | BZ46: No | CA46: =IF(BZ46="Yes",-10,0) | CB46: Less than 15% | CC46: =IF(CB46="More than 15%",-10,IF(CB46="Less than 15%",10,0)) | CD46: No | CE46: =IF(CD46="Yes, more than 10%",-10,IF(CD46="No",10,0))
A47: =IF(B47=0,"",RANK(B47,$B$2:$B$184,0)) | B47: =SUM(N47,Y47,AA47,AC47,AE47,AG47,AI47,AK47,AM47,AO47,AQ47,AS47,AU47,AW47,AY47,BA47,BC47,BE47,BG47,BI47,BK47,BM47,BO47,BQ47,BS47,BU47,BW47,BY47,CA47,CC47,CE47) | C47: QUADFUTURE | D47: Quadrant Future Tek Ltd | E47: industrials | F47: cables - power | G47: smallcap | H47: 1938.4 | I47: 491.95 | J47: 1.52 | K47: 1127715 | N47: =IF(M47="Underperforming",-5,IF(L47>=95,15,IF(L47>=90,10,IF(L47>=80,5,0)))) | O47: 67.23 | P47: 39.49 | Q47: 340.51 | R47: Near 52W High Breakout | S47: Nifty Energy | X47: Cyclical in an Upturn | Y47: =IF(X47="Growing Industry",10,IF(X47="Cyclical in an Upturn",5,0)) | Z47: Too Many Players with High ROCE | AA47: =IF(Z47="Monopoly",10,IF(Z47="Oligopoly",5,IF(Z47="Duopoly that cooperate",10,IF(Z47="Duopoly that compete",5,IF(Z47="Too many players with High ROCE",5,0))))) | AB47: No | AC47: =IF(AB47="No",5,0) | AD47: Tailwind | AE47: =IF(AD47="Tailwind",10,0) | AF47: Structural (10 Years Consistency) | AG47: =IF(AF47="Structural (10 Years Consistency)",10,IF(AF47="Shallow Cyclical (2 to 3 years growth)",5,0)) | AH47: No | AI47: =IF(AH47="Yes due to Product Mix change or Operating Leverage",10,IF(AH47="Yes, these are peak margins",-5,IF(AH47="No",5,0))) | AJ47: Stable | AK47: =IF(AJ47="Stable",10,0) | AL47: Yes | AM47: =IF(AL47="Yes",10,0) | AN47: B2B | AO47: =IF(AN47="B2C",10,IF(AN47="B2B",5,0)) | AP47: Yes | AQ47: =IF(AP47="Yes",10,0) | AR47: Higher One Time, Lower Annuity | AS47: =IF(AR47="Fully Annuity",10,IF(AR47="Higher Annuity, Lower One Time",5,IF(AR47="Higher One Time, Lower Annuity",3,0))) | AT47: Good | AU47: =IF(AT47="Good",10,0) | AV47: Yes for more than 2 years | AW47: =IF(AV47="Yes for more than 2 years",10,IF(AV47="Yes only for next 1 to 2 years",5,0)) | AX47: 20 to 40 | AY47: =IF(AX47="Above 40",20,IF(AX47="20 to 40",10,IF(AX47="0 to 20",-5,0))) | AZ47: Between 50 to 75 | BA47: =IF(AZ47="Between 50 to 75",10,IF(AZ47="Above 75",0,0)) | BB47: Stage 2 | BC47: =IF(BB47="Stage 2",20,IF(BB47="Stage 1",0,IF(BB47="Stage 3",5,IF(BB47="Stage 4",-5,0)))) | BD47: Positive Trend | BE47: =IF(BD47="Positive Trend",20,IF(BD47="Negative Trend",-10,0)) | BF47: Uptrend | BG47: =IF(BF47="Uptrend",10,IF(BF47="Sideways",5,0)) | BH47: Uptrend | BI47: =IF(BH47="Uptrend",10,IF(BH47="Sideways",5,0)) | BJ47: Close to 52 week high or retracement | BK47: =IF(BJ47="Overhead supply in last 2 years in last 2 years",-5,IF(BJ47="Close to 52 week high or retracement",5,IF(BJ47="Blue sky scenario",10,IF(BJ47="Long term Downtrend",-10,0)))) | BL47: Yes | BM47: =IF(BL47="Yes",10,0) | BN47: More than 20% | BO47: =IF(BN47="More than 20%",10,IF(BN47="Between 12 to 20%",5,IF(BN47="Less than 12%",0,0))) | BP47: No | BQ47: =IF(BP47="No",10,0) | BR47: No | BS47: =IF(BR47="NO",5,0) | BT47: Less than 1.5 | BU47: =IF(BT47="Above 2",0,IF(BT47="Between 1.5 to 2",5,IF(BT47="Less than 1.5",10,0))) | BV47: Above 70% | BW47: =IF(BV47="Above 70%",10,IF(BV47="Between 50% to 70%",5,IF(BV47="Less than 50%",0,IF(BV47="Negative",-10,IF(BV47="Less than 50% and Borrowings are increasing",-5,0))))) | BX47: Less than 0.7 | BY47: =IF(BX47="More than 1.2",-10,IF(BX47="Between 0.7 to 1.2",0,IF(BX47="Less than 0.7",10,0))) | BZ47: No | CA47: =IF(BZ47="Yes",-10,0) | CB47: Less than 15% | CC47: =IF(CB47="More than 15%",-10,IF(CB47="Less than 15%",10,0)) | CD47: No | CE47: =IF(CD47="Yes, more than 10%",-10,IF(CD47="No",10,0))
A48: =IF(B48=0,"",RANK(B48,$B$2:$B$184,0)) | B48: =SUM(N48,Y48,AA48,AC48,AE48,AG48,AI48,AK48,AM48,AO48,AQ48,AS48,AU48,AW48,AY48,BA48,BC48,BE48,BG48,BI48,BK48,BM48,BO48,BQ48,BS48,BU48,BW48,BY48,CA48,CC48,CE48) | C48: SHREEPUSHK | D48: Shree Pushkar Chemicals & Fertilisers Limited | E48: chemicals | F48: dyes and pigments | G48: smallcap | H48: 1621.57 | I48: 506.95 | J48: 1.1 | K48: 123748 | L48: 44 | M48: Outperforming | N48: =IF(M48="Underperforming",-5,IF(L48>=95,15,IF(L48>=90,10,IF(L48>=80,5,0)))) | O48: 70.7 | P48: 41.42 | Q48: 372.99 | R48: Near 52W High Breakout | S48: Nifty 50 | T48: -8.33 | U48: 31.95 | V48: 43.94 | W48: 13.21 | X48: Growing Industry | Y48: =IF(X48="Growing Industry",10,IF(X48="Cyclical in an Upturn",5,0)) | Z48: Too Many Players with High ROCE | AA48: =IF(Z48="Monopoly",10,IF(Z48="Oligopoly",5,IF(Z48="Duopoly that cooperate",10,IF(Z48="Duopoly that compete",5,IF(Z48="Too many players with High ROCE",5,0))))) | AB48: No | AC48: =IF(AB48="No",5,0) | AD48: Tailwind | AE48: =IF(AD48="Tailwind",10,0) | AF48: Structural (10 Years Consistency) | AG48: =IF(AF48="Structural (10 Years Consistency)",10,IF(AF48="Shallow Cyclical (2 to 3 years growth)",5,0)) | AH48: No | AI48: =IF(AH48="Yes due to Product Mix change or Operating Leverage",10,IF(AH48="Yes, these are peak margins",-5,IF(AH48="No",5,0))) | AJ48: Stable | AK48: =IF(AJ48="Stable",10,0) | AL48: Yes | AM48: =IF(AL48="Yes",10,0) | AN48: B2B | AO48: =IF(AN48="B2C",10,IF(AN48="B2B",5,0)) | AP48: Yes | AQ48: =IF(AP48="Yes",10,0) | AR48: Higher One Time, Lower Annuity | AS48: =IF(AR48="Fully Annuity",10,IF(AR48="Higher Annuity, Lower One Time",5,IF(AR48="Higher One Time, Lower Annuity",3,0))) | AT48: Good | AU48: =IF(AT48="Good",10,0) | AV48: Yes for more than 2 years | AW48: =IF(AV48="Yes for more than 2 years",10,IF(AV48="Yes only for next 1 to 2 years",5,0)) | AX48: Above 40 | AY48: =IF(AX48="Above 40",20,IF(AX48="20 to 40",10,IF(AX48="0 to 20",-5,0))) | AZ48: Between 50 to 75 | BA48: =IF(AZ48="Between 50 to 75",10,IF(AZ48="Above 75",0,0)) | BB48: Stage 2 | BC48: =IF(BB48="Stage 2",20,IF(BB48="Stage 1",0,IF(BB48="Stage 3",5,IF(BB48="Stage 4",-5,0)))) | BD48: Positive Trend | BE48: =IF(BD48="Positive Trend",20,IF(BD48="Negative Trend",-10,0)) | BF48: Uptrend | BG48: =IF(BF48="Uptrend",10,IF(BF48="Sideways",5,0)) | BH48: Uptrend | BI48: =IF(BH48="Uptrend",10,IF(BH48="Sideways",5,0)) | BJ48: Blue sky scenario | BK48: =IF(BJ48="Overhead supply in last 2 years in last 2 years",-5,IF(BJ48="Close to 52 week high or retracement",5,IF(BJ48="Blue sky scenario",10,IF(BJ48="Long term Downtrend",-10,0)))) | BL48: Yes | BM48: =IF(BL48="Yes",10,0) | BN48: Less than 12% | BO48: =IF(BN48="More than 20%",10,IF(BN48="Between 12 to 20%",5,IF(BN48="Less than 12%",0,0))) | BP48: No | BQ48: =IF(BP48="No",10,0) | BR48: No | BS48: =IF(BR48="NO",5,0) | BT48: Above 2 | BU48: =IF(BT48="Above 2",0,IF(BT48="Between 1.5 to 2",5,IF(BT48="Less than 1.5",10,0))) | BV48: Above 70% | BW48: =IF(BV48="Above 70%",10,IF(BV48="Between 50% to 70%",5,IF(BV48="Less than 50%",0,IF(BV48="Negative",-10,IF(BV48="Less than 50% and Borrowings are increasing",-5,0))))) | BX48: Less than 0.7 | BY48: =IF(BX48="More than 1.2",-10,IF(BX48="Between 0.7 to 1.2",0,IF(BX48="Less than 0.7",10,0))) | BZ48: No | CA48: =IF(BZ48="Yes",-10,0) | CB48: Less than 15% | CC48: =IF(CB48="More than 15%",-10,IF(CB48="Less than 15%",10,0)) | CD48: No | CE48: =IF(CD48="Yes, more than 10%",-10,IF(CD48="No",10,0))
A49: =IF(B49=0,"",RANK(B49,$B$2:$B$184,0)) | B49: =SUM(N49,Y49,AA49,AC49,AE49,AG49,AI49,AK49,AM49,AO49,AQ49,AS49,AU49,AW49,AY49,BA49,BC49,BE49,BG49,BI49,BK49,BM49,BO49,BQ49,BS49,BU49,BW49,BY49,CA49,CC49,CE49) | C49: CASTROLIND | D49: Castrol India Limited | E49: chemicals | F49: chemicals | G49: midcap | H49: 18577.7 | I49: 188.84 | J49: 0.54 | K49: 1359799 | L49: 6 | M49: Outperforming | N49: =IF(M49="Underperforming",-5,IF(L49>=95,15,IF(L49>=90,10,IF(L49>=80,5,0)))) | O49: 63.57 | P49: 34.38 | Q49: 175.79 | R49: Near 52W High Breakout | S49: Nifty 50 | T49: -8.33 | U49: -0.91 | V49: 8.1 | W49: 0.96 | X49: Growing Industry | Y49: =IF(X49="Growing Industry",10,IF(X49="Cyclical in an Upturn",5,0)) | Z49: Too Many Players with High ROCE | AA49: =IF(Z49="Monopoly",10,IF(Z49="Oligopoly",5,IF(Z49="Duopoly that cooperate",10,IF(Z49="Duopoly that compete",5,IF(Z49="Too many players with High ROCE",5,0))))) | AB49: No | AC49: =IF(AB49="No",5,0) | AD49: Tailwind | AE49: =IF(AD49="Tailwind",10,0) | AF49: Structural (10 Years Consistency) | AG49: =IF(AF49="Structural (10 Years Consistency)",10,IF(AF49="Shallow Cyclical (2 to 3 years growth)",5,0)) | AH49: No | AI49: =IF(AH49="Yes due to Product Mix change or Operating Leverage",10,IF(AH49="Yes, these are peak margins",-5,IF(AH49="No",5,0))) | AJ49: Stable | AK49: =IF(AJ49="Stable",10,0) | AL49: Yes | AM49: =IF(AL49="Yes",10,0) | AN49: B2B | AO49: =IF(AN49="B2C",10,IF(AN49="B2B",5,0)) | AP49: Yes | AQ49: =IF(AP49="Yes",10,0) | AR49: Higher One Time, Lower Annuity | AS49: =IF(AR49="Fully Annuity",10,IF(AR49="Higher Annuity, Lower One Time",5,IF(AR49="Higher One Time, Lower Annuity",3,0))) | AT49: Good | AU49: =IF(AT49="Good",10,0) | AV49: Yes for more than 2 years | AW49: =IF(AV49="Yes for more than 2 years",10,IF(AV49="Yes only for next 1 to 2 years",5,0)) | AX49: 20 to 40 | AY49: =IF(AX49="Above 40",20,IF(AX49="20 to 40",10,IF(AX49="0 to 20",-5,0))) | AZ49: Between 50 to 75 | BA49: =IF(AZ49="Between 50 to 75",10,IF(AZ49="Above 75",0,0)) | BB49: Stage 2 | BC49: =IF(BB49="Stage 2",20,IF(BB49="Stage 1",0,IF(BB49="Stage 3",5,IF(BB49="Stage 4",-5,0)))) | BD49: Positive Trend | BE49: =IF(BD49="Positive Trend",20,IF(BD49="Negative Trend",-10,0)) | BF49: Uptrend | BG49: =IF(BF49="Uptrend",10,IF(BF49="Sideways",5,0)) | BH49: Uptrend | BI49: =IF(BH49="Uptrend",10,IF(BH49="Sideways",5,0)) | BJ49: Close to 52 week high or retracement | BK49: =IF(BJ49="Overhead supply in last 2 years in last 2 years",-5,IF(BJ49="Close to 52 week high or retracement",5,IF(BJ49="Blue sky scenario",10,IF(BJ49="Long term Downtrend",-10,0)))) | BL49: Yes | BM49: =IF(BL49="Yes",10,0) | BN49: More than 20% | BO49: =IF(BN49="More than 20%",10,IF(BN49="Between 12 to 20%",5,IF(BN49="Less than 12%",0,0))) | BP49: No | BQ49: =IF(BP49="No",10,0) | BR49: No | BS49: =IF(BR49="NO",5,0) | BT49: Less than 1.5 | BU49: =IF(BT49="Above 2",0,IF(BT49="Between 1.5 to 2",5,IF(BT49="Less than 1.5",10,0))) | BV49: Between 50% to 70% | BW49: =IF(BV49="Above 70%",10,IF(BV49="Between 50% to 70%",5,IF(BV49="Less than 50%",0,IF(BV49="Negative",-10,IF(BV49="Less than 50% and Borrowings are increasing",-5,0))))) | BX49: Less than 0.7 | BY49: =IF(BX49="More than 1.2",-10,IF(BX49="Between 0.7 to 1.2",0,IF(BX49="Less than 0.7",10,0))) | BZ49: No | CA49: =IF(BZ49="Yes",-10,0) | CB49: Less than 15% | CC49: =IF(CB49="More than 15%",-10,IF(CB49="Less than 15%",10,0)) | CD49: No | CE49: =IF(CD49="Yes, more than 10%",-10,IF(CD49="No",10,0))
