Workbook

Sheet Read Me
A1: 🏆 MONIT MULTIBAGGER RESEARCH ENGINE & SCANNER
A2: Daily Analytics Report | Generated: Monday, 10 August 2026
A5: 📖 QUICK REFERENCE RUNBOOK & SYSTEM FLOW
A6: Step 1: Reference this Read Me | B6: Understand terms, formulas, and underlying investment theses directly in this glossary dashboard.
A7: Step 2: Check Leaderboard Tab | B7: Locate long-term compounders with high Persistence Scores and streaks (institutional accumulation footprint).
A8: Step 3: Analyze Confluence Overlap | B8: Review the ultimate high-conviction candidates intersecting our scanner signals and StockScans overlaps.
A9: Step 4: Scoring Monit Tabs | B9: Open 'Monit Non Financial' or 'Monit Banks NBFC' to fill out your qualitative checks (Tailwinds, Promoters, Triggers).
A10: Step 5: Track Scan Matches | B10: Confirm consensus using 'Scan Match' tabs which score companies by total appearances across allStockScans.
A13: 📊 RESEARCH ENGINE GLOSSARY, METRICS & THESES
A15: Metric Term / Tab Name | B15: Practical Meaning & Underlying Investment Thesis | C15: Automated DB Query / Logic & Excel Formula
A16: EMA Crossover (Birth of a Trend) | B16: An entry signal triggered when price crosses above its 200-day EMA. [THESIS]: Represents the birth of a new long-term uptrend. Buying here provides maximum asymmetrical risk-to-reward because the entry is close to the logical stop-loss (the EMA itself). | C16: pine_signal == 'EMA Crossover' Sized at 7% capital allocation (~₹70,000 per position).
A17: 52W Breakout (Momentum Confirmation) | B17: A momentum signal triggered when a stock above its 200-day EMA breaks out to fresh 52-week highs. [THESIS]: Represents a confirmed breakout where institutional buying pressure clears all historical supply. High momentum outperformance. | C17: pine_signal == '52W Breakout' Sized at 5% capital allocation (~₹50,000 per position).
A18: ATH Momentum (Runaway Leader) | B18: An established trend signal triggered when the price is actively running near its All-Time Highs. [THESIS]: Identifies the strongest runaway leaders in the market. Ideal for high-velocity momentum trading where price experiences immediate continuation. | C18: pine_signal == 'ATH Momentum' Sized at 4% capital allocation (~₹40,000 per position).
A19: Persistence Score (30D) (Accumulation Footprint) | B19: The count of times a stock has appeared in the daily screener during the last 30 active trading days. [THESIS]: Represents persistent institutional buying. Random spikes appear 1-2 times, but compounders appear 10+ times as institutions accumulate. | C19: Queries the local SQLite database (`logs/backtest.db`) to sum the total number of distinct dates the ticker appeared on the screener during the last 30 active trading days. Formula: COUNT(DISTINCT date)
A20: Consecutive Streak Days (Uninterrupted Trend) | B20: The number of consecutive trading days that the stock has appeared in the screener up to today. [THESIS]: High streaks indicate an exceptionally strong, uninterrupted runaway trend with heavy daily buying pressure. | C20: Checks the chronological sequence of scanner dates in SQLite starting from the most recent run date and counting backward. The streak increments for every contiguous date the ticker appears.
A21: Sector Velocity WoW (Early Sector Rotation) | B21: Compares the volume of screener signals in a sector over the last 5 trading days (W1) against the previous 5 trading days (W2). [THESIS]: Detects early sector rotation. A sudden positive surge warns you of capital flowing aggressively into a specific theme. | C21: Counts appearances of all tickers categorized by their sector. Formula: W1_Count = COUNT(records WHERE date IN last 5 trading days) W2_Count = COUNT(records WHERE date IN days -10 to -5) Velocity % = ((W1_Count - W2_Count) / W2_Count) * 100
A22: Emerging Leaders (Momentum Expansion) | B22: Identifies breakout stocks experiencing a sudden momentum expansion. [THESIS]: Finds stocks with a high concentration of appearances recently but almost zero history in the preceding months. Represents new institutional entries. | C22: Finds stocks with at least 5 appearances in the last 10 trading days, but less than or equal to 3 appearances in the prior 50 trading days (i.e. trading days -60 to -10). Formula: COUNT(recent) >= 5 AND COUNT(historical) <= 3
A23: Tab: Confluence Overlap (The Ultimate Overlap) | B23: This sheet displays the absolute highest conviction watchlist candidates intersecting multiple strategies. [THESIS]: Filters out market noise by only displaying stocks appearing in at least two out of three major momentum dimensions: (1) Chartink screener universe, (2) Active scanner signals, and (3) StockScans overlap list. | C23: Calculates the mathematical intersection of the three sets: In_Universe + In_Scanner + In_StockScans >= 2 Single-dimension matches are automatically filtered out to eliminate market noise.
A24: Tab: Monit Non Financial (CHECKLIST SHEET) | B24: Your main watchlist scoring sheet for non-financial companies. [THESIS]: Keeps watchlist scoring fully formula-driven using Excel formulas. It combines automated metrics (RSI, ADX, V-stop, Persistence) with your qualitative scores (Promoter Buying, Near-Term Trigger, Headwind/Tailwind). | C24: Uses relative index-matching formulas to populate automated close prices, RSI, ADX, V-stop, and Persistence from the SQLite and Chartink universe sheets. Formula: INDEX-MATCH left-lookup.
A25: Tab: Monit Banks NBFC (BANKING CHECKLIST) | B25: Your main watchlist scoring sheet for banking and NBFC companies. [THESIS]: Tailored specifically for banking structures, incorporating specialized metrics like Net Interest Margins (NIM) and Credit Costs alongside technical indicators. | C25: Features banking-specific checklist criteria to ensure qualitative analyst inputs align with bank metrics.
A26: Tab: Scan Match tabs (StockScans Confluence) | B26: Displays the top 100 stocks appearing across all StockScans screeners. [THESIS]: Scores stocks qualitatively by scan volume. Stocks appearing in >20 scans receive a premium 10-point bonus, proving market-wide momentum consensus. | C26: Applies a nested Excel IF formula: `=IF(D8>20,10,IF(D8>=10,5,2))` Scores: >20 scans = 10 pts; 10-20 scans = 5 pts; <10 scans = 2 pts.
... A36: Weekly Tracking Highlighting (Additions / Removals) | B36: Visual highlights indicating weekly changes in the StockScans 100 (Scan Match) list. [THESIS]: Helps track the weekly turnover. Newly added candidates indicate fresh institutional attention, while removed candidates represent names losing relative strength. | C36: Compares daily lists against Monday's baseline database: - Added stocks: Highlighted in Soft Blue. - Removed stocks: Listed in the bottom section of Scan Match sheets.

Sheet Leaderboard
A1: 🌟 MULTIBAGGER MOMENTUM & SECTOR ROTATION LEADERBOARD 🌟
A4: TOP PERSISTENT MOMENTUM LEADERS (30D) | J4: SECTOR MOMENTUM VELOCITY HEATMAP (WoW)
A5: Rank | B5: Score | C5: Symbol | D5: Company Name | E5: Sector | F5: Streak (Days) | G5: Market Cap Cr | H5: Classification | J5: Sector Name | K5: Current Wk Count | L5: Previous Wk Count | M5: Velocity WoW %
A6: 1 | B6: 576 | C6: WELCORP | D6: Welspun Corp Limited | E6: industrials | F6: 81 | G6: 48532.2 | H6: Potential Leader | J6: power & utilities | K6: 15 | L6: 5 | M6: 200.0%
A7: 2 | B7: 468 | C7: BLSE | D7: BLS E-Services Ltd | E7: i.t | F7: 63 | G7: 2821.55 | H7: Potential Leader | J7: aerospace & defence | K7: 54 | L7: 24 | M7: 125.0%
A8: 3 | B8: 462 | C8: LAURUSLABS | D8: Laurus Labs Limited | E8: healthcare | F8: 62 | G8: 99638.23 | H8: Potential Leader | J8: metals & mining | K8: 127 | L8: 68 | M8: 86.8%
A9: 4 | B9: 396 | C9: YASHO | D9: Yasho Industries Ltd | E9: chemicals | F9: 51 | G9: 5006.95 | H9: Potential Leader | J9: miscellaneous | K9: 64 | L9: 41 | M9: 56.1%
A10: 5 | B10: 390 | C10: CUPID | D10: Cupid Limited | E10: fmcg | F10: 50 | G10: 35247.59 | H10: Potential Leader | J10: industrials | K10: 271 | L10: 182 | M10: 48.9%
A11: 6 | B11: 360 | C11: SPECTRUM | D11: Spectrum Electrical Industries Ltd | E11: industrials | F11: 45 | G11: 3835.28 | H11: Potential Leader | J11: energy | K11: 58 | L11: 39 | M11: 48.7%
A12: 7 | B12: 330 | C12: VADILALIND | D12: Vadilal Industries Limited | E12: fmcg | F12: 40 | G12: 5180.63 | H12: Potential Leader | J12: fmcg | K12: 129 | L12: 92 | M12: 40.2%
A13: 8 | B13: 324 | C13: FEDERALBNK | D13: The Federal Bank Limited | E13: bank | F13: 39 | G13: 87923.89 | H13: Potential Leader | J13: realty | K13: 66 | L13: 48 | M13: 37.5%
A14: 9 | B14: 312 | C14: HITECHCORP | D14: Hitech Corporation | E14: industrials | F14: 37 | G14: 553.57 | H14: Potential Leader | J14: building materials | K14: 74 | L14: 54 | M14: 37.0%
A15: 10 | B15: 282 | C15: SSWL | D15: Steel Strips Wheels Limited | E15: auto | F15: 32 | G15: 4849.02 | H15: Potential Leader | J15: auto | K15: 233 | L15: 171 | M15: 36.3%
A16: 11 | B16: 261 | C16: ADOR | D16: Ador Welding Ltd | E16: industrials | F16: 29 | G16: 2581.53 | H16: Potential Leader | J16: chemicals | K16: 162 | L16: 121 | M16: 33.9%
A17: 12 | B17: 261 | C17: CENTENKA | D17: Century Enka Limited | E17: textiles | F17: 29 | G17: 1333.43 | H17: Potential Leader | J17: textiles | K17: 95 | L17: 72 | M17: 31.9%
... A20: 15 | B20: 261 | C20: KAMDHENU | D20: Kamdhenu Limited | E20: metals & mining | F20: 29 | G20: 991.66 | H20: Potential Leader | J20: healthcare | K20: 222 | L20: 179 | M20: 24.0%
A21: 16 | B21: 261 | C21: RADICO | D21: Radico Khaitan Limited | E21: fmcg | F21: 29 | G21: 60255.71 | H21: Potential Leader
A22: 17 | B22: 261 | C22: RPTECH | D22: Rashi Peripherals Ltd | E22: services | F22: 29 | G22: 5895.71 | H22: Potential Leader
A23: 18 | B23: 261 | C23: TBZ | D23: Tribhovandas Bhimji Zaveri Limited | E23: consumer discretionary | F23: 29 | G23: 1821.75 | H23: Potential Leader
A24: 19 | B24: 252 | C24: ESAFSFB | D24: ESAF Small Finance Bank Ltd | E24: bank | F24: 28 | G24: 2077.74 | H24: Potential Leader
A25: 20 | B25: 252 | C25: GABRIEL | D25: Gabriel India Limited | E25: auto | F25: 28 | G25: 26580.96 | H25: Potential Leader
A28: 🌟 EMERGING LEADERS (MOMENTUM EXPANSION) | J28: 💎 SATELLITE HOLDINGS SHORTLIST (MCAP < 25K CR)
A29: Symbol | B29: Company Name | C29: Sector | D29: Recent Matches (10D) | E29: Historical Matches | F29: Market Cap Cr | J29: Symbol | K29: Sector | L29: Monit Score | M29: Market Cap Cr | N29: Appearances (30D)
A30: M&M | B30: Mahindra & Mahindra Limited | C30: auto | D30: 10 | E30: 2 | F30: 435483.8 | J30: SBCL | K30: metals & mining | L30: 247 | M30: 5304.77 | N30: 21
A31: PNB | B31: Punjab National Bank Ltd | C31: bank | D31: 10 | E31: 2 | F31: 131950.48 | J31: PIXTRANS | K31: fmcg | L31: 237 | M31: 2339.72 | N31: 18
A32: ETERNAL | B32: Eternal Ltd | C32: i.t | D32: 10 | E32: 0 | F32: 303986.05 | J32: ARMANFIN | K32: financials | L32: 235 | M32: 2136.6 | N32: 17
A33: VRLLOG | B33: Vrl Logistics Limited | C33: transportation | D33: 10 | E33: 1 | F33: 4921.85 | J33: APCOTEXIND | K33: chemicals | L33: 232 | M33: 3187.43 | N33: 25
A34: LODHA | B34: Lodha Developers Ltd | C34: realty | D34: 10 | E34: 2 | F34: 121759.64 | J34: IBULLSLTD | K34: Real Estate | L34: 230 | M34: 6447 | N34: 23
A35: GLAXO | B35: Glaxosmithkline Pharmaceuticals Limited | C35: healthcare | D35: 9 | E35: 0 | F35: 44040.49 | J35: CONFIPET | K35: miscellaneous | L35: 228 | M35: 2700.46 | N35: 24
A36: COFORGE | B36: Coforge (Niit Tech) Ltd | C36: i.t | D36: 9 | E36: 0 | F36: 78621.89 | J36: RPEL | K36: building materials | L36: 228 | M36: 5770.09 | N36: 22
A37: PERSISTENT | B37: Persistent Systems Limited | C37: i.t | D37: 9 | E37: 1 | F37: 86368.13 | J37: PRICOLLTD | K37: auto | L37: 227 | M37: 8993.64 | N37: 20
A38: TARSONS | B38: Tarsons Products Ltd | C38: healthcare | D38: 9 | E38: 1 | F38: 1661.63 | J38: IOLCP | K38: healthcare | L38: 227 | M38: 4926.86 | N38: 17
A39: LANDMARK | B39: Landmark Cars Ltd | C39: consumer discretionary | D39: 9 | E39: 2 | F39: 2218.58 | J39: RPTECH | K39: services | L39: 225 | M39: 5895.71 | N39: 29
A40: ANTHEM | B40: Anthem Biosciences Ltd | C40: healthcare | D40: 8 | E40: 0 | F40: 47380.66 | J40: TINNARUBR | K40: fmcg | L40: 225 | M40: 1996.33 | N40: 28
A41: SMLMAH | B41: SML Mahindra Ltd | C41: auto | D41: 8 | E41: 0 | F41: 8037.55 | J41: KTKBANK | K41: bank | L41: 225 | M41: 11724.3 | N41: 23
A45: 🚀 HIGH MOMENTUM LEADERS (RS RATING >= 90)
A46: Rank | B46: RS Rating | C46: O'Neil Score | D46: Monit Score | E46: Symbol | F46: Company Name | G46: Sector | H46: Market Cap Cr
A47: 1 | B47: 99 | C47: 110.03 | D47: 215 | E47: AXISOL | F47: Axis Solutions Limited | G47: Industrials | H47: 2194.45
A48: 2 | B48: 99 | C48: 76.51 | D48: 217 | E48: CUPID | F48: Cupid Limited | G48: fmcg | H48: 35247.59
A49: 3 | B49: 99 | C49: 74.59 | D49: 190 | E49: SIGMAADV | F49: Sigma Advanced System Ltd | G49: aerospace & defence | H49: 13282.73
A50: 4 | B50: 98 | C50: 71.67 | D50: 193 | E50: SWANDEF | F50: Swan Defence and Heavy Industries Ltd | G50: transportation | H50: 14197.31
A51: 5 | B51: 98 | C51: 71.36 | D51: 203 | E51: STLTECH | F51: Sterlite Technologies Limited | G51: industrials | H51: 32832.82
A52: 6 | B52: 98 | C52: 64.93 | D52: 190 | E52: YASHO | F52: Yasho Industries Ltd | G52: chemicals | H52: 5006.95
A53: 7 | B53: 98 | C53: 55.72 | D53: 200 | E53: UFBL | F53: United Foodbrands Ltd | G53: consumer discretionary | H53: 3156.62
A54: 8 | B54: 98 | C54: 53.93 | D54: 215 | E54: HFCL | F54: HFCL Ltd | G54: telecom | H54: 31833.47
A55: 9 | B55: 97 | C55: 47.28 | D55: 203 | E55: HITECHCORP | F55: Hitech Corporation | G55: industrials | H55: 553.57
A56: 10 | B56: 97 | C56: 46.25 | D56: 215 | E56: ATHERENERG | F56: Ather Energy Ltd | G56: auto | H56: 58389.66
A57: 11 | B57: 97 | C57: 42.09 | D57: 225 | E57: RPTECH | F57: Rashi Peripherals Ltd | G57: services | H57: 5895.71
A58: 12 | B58: 97 | C58: 41.12 | D58: 210 | E58: E2E | F58: E2E Networks Ltd | G58: i.t | H58: 11829.23
... A92: 46 | B92: 90 | C92: 25.42 | D92: 218 | E92: KANORICHEM | F92: Kanoria Chemicals & Industries Limited | G92: chemicals | H92: 654.05

Sheet Chartink Universe
A1: symbol | B1: company | C1: sector | D1: industry | E1: marketcap_bucket | F1: marketcap_cr | G1: close | H1: today_return_pct | I1: volume | J1: bse_code
A2: UNIVCABLES | B2: Universal Cables Limited | C2: industrials | D2: cables - power | E2: smallcap | F2: 4896.21 | G2: 1693.4 | H2: 20 | I2: 1907323 | J2: 504212
A3: AARTIPHARM | B3: Aarti Pharmalabs Ltd | C3: healthcare | D3: pharmaceuticals - indian - bulk drugs & formln | E3: midcap | F3: 6219.28 | G3: 823 | H3: 20 | I3: 3125635 | J3: 543748
A4: SBCL | B4: Shivalik Bimetal Controls Ltd | C4: metals & mining | D4: mining / minerals / metals | E4: midcap | F4: 5304.77 | G4: 1105.05 | H4: 20 | I4: 10977326 | J4: 513097
A5: COMSYN | B5: Commercial Syn Bags Ltd | C5: industrials | D5: packaging | E5: smallcap | F5: 906.95 | G5: 269.03 | H5: 19.66 | I5: 7601735 | J5: 539986
A6: PIXTRANS | B6: Pix Transmission Ltd | C6: fmcg | D6: miscellaneous | E6: smallcap | F6: 2339.72 | G6: 1986.5 | H6: 15.68 | I6: 1309397 | J6: 500333
A7: KABRAEXTRU | B7: Kabra Extrusion Technik Limited | C7: industrials | D7: engineering | E7: smallcap | F7: 1568.88 | G7: 510.75 | H7: 13.85 | I7: 2087592 | J7: 524109
A8: ANDHRSUGAR | B8: The Andhra Sugars Limited | C8: chemicals | D8: chlor alkali / soda ash | E8: smallcap | F8: 1192.44 | G8: 99.98 | H8: 13.64 | I8: 17423821 | J8: 590062
A9: DMCC | B9: DMCC Speciality Chemicals Ltd | C9: chemicals | D9: chemicals | E9: smallcap | F9: 692.46 | G9: 313.1 | H9: 12.77 | I9: 1241573 | J9: 506405
A10: JGCHEM | B10: J.G.Chemicals Ltd | C10: chemicals | D10: chemicals | E10: smallcap | F10: 2166.21 | G10: 622.2 | H10: 12.55 | I10: 10811484
A11: RAMCOIND | B11: Ramco Industries Limited | C11: building materials | D11: cement products | E11: smallcap | F11: 2949.57 | G11: 377.2 | H11: 11.06 | I11: 21233222 | J11: 532369
A12: POWERINDIA | B12: Hitachi Energy India Ltd | C12: industrials | D12: electric equipment | E12: largecap | F12: 145305.9 | G12: 36050 | H12: 10.58 | I12: 1348196 | J12: 543187
A13: PAYTM | B13: One 97 Communications Ltd | C13: i.t | D13: miscellaneous | E13: largecap | F13: 92310.98 | G13: 1584.1 | H13: 9.88 | I13: 39982128 | J13: 543396
A14: EMIL | B14: Electronics Mart India Ltd | C14: consumer discretionary | D14: trading | E14: midcap | F14: 6380.29 | G14: 180.77 | H14: 9.01 | I14: 101219512 | J14: 543626
A15: VINDHYATEL | B15: Vindhya Telelinks Limited | C15: realty | D15: construction | E15: smallcap | F15: 2656.61 | G15: 2438.4 | H15: 8.77 | I15: 290828 | J15: 517015
A16: MACPOWER | B16: Macpower CNC Machines Ltd | C16: industrials | D16: engineering | E16: smallcap | F16: 1681.8 | G16: 1824.3 | H16: 8.52 | I16: 138274 | J16: 535057
A17: SKYGOLD | B17: Sky Gold Ltd | C17: consumer discretionary | D17: diamond cutting / jewellery | E17: midcap | F17: 11141.63 | G17: 779.6 | H17: 8.37 | I17: 8041846 | J17: 541967
A18: ORCHPHARMA | B18: Orchid Pharma Ltd | C18: healthcare | D18: pharmaceuticals - indian - bulk drugs & formln | E18: midcap | F18: 5081.29 | G18: 1079.15 | H18: 7.72 | I18: 222143 | J18: 524372
A19: KAPSTON | B19: Kapston Services Ltd | C19: miscellaneous | D19: miscellaneous | E19: smallcap | F19: 1600.43 | G19: 566.05 | H19: 7.63 | I19: 195599 | J19: 535064
A20: NEOGEN | B20: Neogen Chemicals Ltd | C20: chemicals | D20: chemicals | E20: midcap | F20: 5563.68 | G20: 2182.8 | H20: 7.43 | I20: 505295 | J20: 542665
A21: INDOBORAX | B21: Indo Borax & Chemicals Ltd | C21: chemicals | D21: chemicals | E21: smallcap | F21: 1284.88 | G21: 429.5 | H21: 7.27 | I21: 1906898 | J21: 524342
A22: SHAILY | B22: Shaily Engineering Plastics Ltd | C22: plastic products | D22: plastics products | E22: midcap | F22: 14545.08 | G22: 3367.4 | H22: 6.49 | I22: 408713 | J22: 501423
... A166: DPABHUSHAN | B166: D.P. Abhushan Ltd | C166: consumer discretionary | D166: diamond cutting / jewellery | E166: smallcap | F166: 3294.98 | G166: 1470.1 | H166: 1.85 | I166: 28158 | J166: 535026
A167: BELRISE | B167: Belrise Industries Ltd | C167: auto | D167: auto ancillaries | E167: largecap | F167: 24005.68 | G167: 252.77 | H167: 1.84 | I167: 6590771
A168: ETHOSLTD | B168: Ethos Ltd | C168: consumer discretionary | D168: trading | E168: midcap | F168: 7444.26 | G168: 2833.1 | H168: 1.83 | I168: 31526 | J168: 543532
A169: GRAPHITE | B169: Graphite India Limited | C169: industrials | D169: electrodes - graphites | E169: midcap | F169: 13870.69 | G169: 722.9 | H169: 1.82 | I169: 966513 | J169: 509488
A170: VARROC | B170: Varroc Engineering Ltd | C170: auto | D170: auto ancillaries | E170: midcap | F170: 12394.03 | G170: 825.95 | H170: 1.82 | I170: 1417670 | J170: 541578
A171: CONFIPET | B171: Confidence Petroleum India Ltd | C171: miscellaneous | D171: miscellaneous | E171: smallcap | F171: 2700.46 | G171: 82.74 | H171: 1.8 | I171: 5858829 | J171: 526829
A172: GEECEE | B172: Geecee Ventures Limited | C172: financials | D172: finance & investments | E172: smallcap | F172: 760.04 | G172: 370 | H172: 1.8 | I172: 7109 | J172: 532764
A173: NAHARINDUS | B173: Nahar Industrial Enterprises Limited | C173: textiles | D173: textiles - cotton/blended | E173: smallcap | F173: 551.82 | G173: 130 | H173: 1.79 | I173: 147014 | J173: 519136
A174: ACE | B174: Action Construction Equipment Limited | C174: industrials | D174: engineering | E174: midcap | F174: 13031.27 | G174: 1113.6 | H174: 1.76 | I174: 305830 | J174: 532762
A175: SHANTIGOLD | B175: Shanti Gold International Ltd | C175: consumer discretionary | D175: diamond cutting / jewellery | E175: smallcap | F175: 1615.02 | G175: 227.91 | H175: 1.74 | I175: 704322 | J175: 544459
A176: FILATEX | B176: Filatex India Limited | C176: textiles | D176: textiles - manmade | E176: smallcap | F176: 3700.34 | G176: 84.78 | H176: 1.74 | I176: 4575349 | J176: 526227
A177: GRASIM | B177: Grasim Industries Limited | C177: textiles | D177: textiles - manmade | E177: largecap | F177: 226156.93 | G177: 3380.5 | H177: 1.73 | I177: 5122421 | J177: 500300
A178: HNDFDS | B178: Hindustan Foods Ltd | C178: fmcg | D178: diversified - large | E178: midcap | F178: 6981.39 | G178: 586 | H178: 1.7 | I178: 74737 | J178: 519126
A179: TMB | B179: Tamilnad Mercantile Bank Ltd | C179: bank | D179: banks - private sector | E179: midcap | F179: 13870.8 | G179: 890.2 | H179: 1.63 | I179: 181662 | J179: 543596
... A181: GNFC | B181: Gujarat Narmada Valley Fertilizers And Chemicals Limited | C181: chemicals | D181: chemicals | E181: midcap | F181: 7868.67 | G181: 544.1 | H181: 1.61 | I181: 272440 | J181: 500670
A182: BORANA | B182: Borana Weaves Ltd | C182: textiles | D182: textiles - processing | E182: smallcap | F182: 904.87 | G182: 345 | H182: 1.59 | I182: 39480
A183: NGLFINE | B183: NGL Fine Chem Ltd | C183: healthcare | D183: pharmaceuticals - indian - bulk drugs | E183: smallcap | F183: 2102.75 | G183: 3457.8 | H183: 1.59 | I183: 7370 | J183: 524774
A184: VRLLOG | B184: Vrl Logistics Limited | C184: transportation | D184: miscellaneous | E184: smallcap | F184: 4921.85 | G184: 285.8 | H184: 1.58 | I184: 324876 | J184: 539118
A185: KANSAINER | B185: Kansai Nerolac Paints Limited | C185: building materials | D185: paints / varnishes | E185: midcap | F185: 17173.05 | G185: 215.65 | H185: 1.55 | I185: 547826 | J185: 500165
A186: PTCIL | B186: PTC Industries Ltd | C186: industrials | D186: castings & forgings | E186: largecap | F186: 28599.79 | G186: 19370 | H186: 1.54 | I186: 18285 | J186: 539006
A187: SHARDAMOTR | B187: Sharda Motor Industries Limited | C187: auto | D187: auto ancillaries | E187: midcap | F187: 5403.79 | G187: 955.7 | H187: 1.53 | I187: 99362 | J187: 535602
A188: RATNAVEER | B188: Ratnaveer Precision Engineering Ltd | C188: metals & mining | D188: steel - medium / small | E188: smallcap | F188: 1472.1 | G188: 209.25 | H188: 1.53 | I188: 4225309 | J188: 543978
A189: PIDILITIND | B189: Pidilite Industries Limited | C189: chemicals | D189: chemicals | E189: largecap | F189: 168950.71 | G189: 1685 | H189: 1.51 | I189: 1714117 | J189: 500331
A190: APCOTEXIND | B190: Apcotex Industries Limited | C190: chemicals | D190: miscellaneous | E190: smallcap | F190: 3187.43 | G190: 624.05 | H190: 1.5 | I190: 271630 | J190: 523694
A191: INOXINDIA | B191: Inox India Ltd | C191: industrials | D191: packaging | E191: midcap | F191: 17741.54 | G191: 1984.1 | H191: 1.5 | I191: 142077 | J191: 544046
A192: JKPAPER | B192: Jk Paper Limited | C192: building materials | D192: paper | E192: midcap | F192: 7017.94 | G192: 392.7 | H192: 1.46 | I192: 453034 | J192: 532162
A193: DOLPHIN | B193: Dolphin Offshore Enterprises (India) Ltd | C193: energy | D193: oil drilling / allied services | E193: smallcap | F193: 1644.39 | G193: 417.05 | H193: 1.46 | I193: 30109 | J193: 522261
A194: HARSHA | B194: Harsha Engineers International Ltd | C194: industrials | D194: engineering | E194: smallcap | F194: 3882.12 | G194: 432.6 | H194: 1.45 | I194: 424599 | J194: 543600
... A228: M&MFIN | B228: Mahindra & Mahindra Financial Services Limited | C228: financials | D228: finance & investments | E228: largecap | F228: 56773.37 | G228: 412.3 | H228: 0.94 | I228: 3517041 | J228: 532720
A229: SHRIPISTON | B229: Shriram Pistons & Rings Limited | C229: auto | D229: auto ancillaries | E229: midcap | F229: 19350.21 | G229: 4434 | H229: 0.94 | I229: 55392
A230: LUMAXTECH | B230: Lumax Auto Technologies Limited | C230: auto | D230: auto ancillaries | E230: midcap | F230: 11739.48 | G230: 1738.2 | H230: 0.92 | I230: 181394 | J230: 532796
A231: SOLARINDS | B231: Solar Industries India Limited | C231: aerospace & defence | D231: chemicals | E231: largecap | F231: 168763.95 | G231: 18820 | H231: 0.91 | I231: 83343 | J231: 532725
A232: TINNARUBR | B232: Tinna Rubber & Infrastructure Ltd | C232: fmcg | D232: miscellaneous | E232: smallcap | F232: 1996.33 | G232: 1118 | H232: 0.89 | I232: 64083 | J232: 530475
A233: CYIENTDLM | B233: Cyient DLM Ltd | C233: consumer discretionary | D233: electronics - components | E233: midcap | F233: 5442.13 | G233: 691.5 | H233: 0.87 | I233: 965338 | J233: 543933
A234: BOSCH-HCIL | B234: Bosch Home Comfort India Ltd | C234: consumer discretionary | D234: air-conditioners | E234: smallcap | F234: 4574.59 | G234: 1696.8 | H234: 0.86 | I234: 75096 | J234: 523398
A235: EMCURE | B235: Emcure Pharmaceuticals Ltd | C235: healthcare | D235: pharmaceuticals - indian - bulk drugs & formln | E235: largecap | F235: 37526.32 | G235: 1995.2 | H235: 0.85 | I235: 205967 | J235: 544210
A236: KENNAMET | B236: Kennametal India Ltd | C236: industrials | D236: castings & forgings | E236: midcap | F236: 7274.58 | G236: 3335.6 | H236: 0.78 | I236: 33912 | J236: 505890
A237: UFLEX | B237: Uflex Limited | C237: industrials | D237: packaging | E237: smallcap | F237: 3528.98 | G237: 492.45 | H237: 0.77 | I237: 64372 | J237: 500148
A238: SIRCA | B238: Sirca Paints India Ltd | C238: building materials | D238: paints / varnishes | E238: smallcap | F238: 2555.11 | G238: 453.2 | H238: 0.73 | I238: 395993 | J238: 535083
A239: TATATECH | B239: Tata Technologies Ltd | C239: i.t | D239: computers - software - medium / small | E239: largecap | F239: 35440.2 | G239: 879.15 | H239: 0.73 | I239: 4640112 | J239: 544028
A240: RBZJEWEL | B240: RBZ Jewellers Ltd | C240: consumer discretionary | D240: diamond cutting / jewellery | E240: smallcap | F240: 603.64 | G240: 152 | H240: 0.72 | I240: 67934 | J240: 544060
A241: OFSS | B241: Oracle Financial Services Software Limited | C241: i.t | D241: computers - software - large | E241: largecap | F241: 102788.66 | G241: 11890 | H241: 0.72 | I241: 239490 | J241: 532466
... A293: PRUDENT | B293: Prudent Corporate Advisory Services Ltd | C293: financials | D293: finance & investments | E293: midcap | F293: 13961.5 | G293: 3379.7 | H293: 0.23 | I293: 19500 | J293: 543527
A294: RPTECH | B294: Rashi Peripherals Ltd | C294: services | D294: trading | E294: midcap | F294: 5895.71 | G294: 896.7 | H294: 0.23 | I294: 327277
A295: HITECHCORP | B295: Hitech Corporation | C295: industrials | D295: packaging | E295: smallcap | F295: 553.57 | G295: 323 | H295: 0.22 | I295: 11964 | J295: 526217
A296: JUBLINGREA | B296: Jubilant Ingrevia Ltd | C296: chemicals | D296: chemicals | E296: midcap | F296: 11790.79 | G296: 741.85 | H296: 0.22 | I296: 384565 | J296: 543271
A297: CUPID | B297: Cupid Limited | C297: fmcg | D297: personal care - indian | E297: largecap | F297: 35247.59 | G297: 262.71 | H297: 0.22 | I297: 25888287 | J297: 530843
A298: APOLLOTYRE | B298: Apollo Tyres Limited | C298: auto | D298: tyres | E298: largecap | F298: 28261.99 | G298: 445.95 | H298: 0.21 | I298: 709497 | J298: 500877
A299: JSWSTEEL | B299: Jsw Steel Limited | C299: metals & mining | D299: steel - large | E299: largecap | F299: 317786.74 | G299: 1302 | H299: 0.19 | I299: 3012479 | J299: 500228
A300: ROSSTECH | B300: Rossell Techsys Ltd | C300: aerospace & defence | D300: engineering | E300: smallcap | F300: 4118.91 | G300: 1094.5 | H300: 0.17 | I300: 212662 | J300: 544294
A301: SEAMECLTD | B301: Seamec Limited | C301: miscellaneous | D301: miscellaneous | E301: smallcap | F301: 3884.18 | G301: 1530 | H301: 0.15 | I301: 36450 | J301: 526807
A302: FMGOETZE | B302: Federal-mogul Goetze (india) Limited. | C302: auto | D302: auto ancillaries | E302: smallcap | F302: 2738.49 | G302: 492.95 | H302: 0.14 | I302: 44378 | J302: 505744
A303: BAJAJ-AUTO | B303: Bajaj Auto Limited | C303: auto | D303: automobiles - scooters and 3 - wheelers | E303: largecap | F303: 325950.38 | G303: 11677 | H303: 0.13 | I303: 389839 | J303: 532977
A304: ARIHANT | B304: Arihant Foundations & Housing Limited | C304: realty | D304: construction | E304: smallcap | F304: 1120.73 | G304: 1126 | H304: 0.12 | I304: 774 | J304: 531381
A305: AUBANK | B305: AU Small Finance Bank Ltd | C305: bank | D305: banks - private sector | E305: largecap | F305: 79915.31 | G305: 1068 | H305: 0.09 | I305: 1602756 | J305: 540611
A306: MAHLIFE | B306: Mahindra Lifespace Developers Limited | C306: realty | D306: construction | E306: midcap | F306: 8246.76 | G306: 386.85 | H306: 0.08 | I306: 141750 | J306: 532313
... A417: DYNAMATECH | B417: Dynamatic Technologies Limited | C417: industrials | D417: engineering | E417: midcap | F417: 7742.92 | G417: 11148 | H417: -2.22 | I417: 51887 | J417: 505242
A418: ENRIN | B418: Siemens Energy India Ltd | C418: power & utilities | D418: power generation and supply | E418: largecap | F418: 129941.25 | G418: 3567.3 | H418: -2.23 | I418: 1146677
A419: BHARATSE | B419: Bharat Seats Ltd | C419: auto | D419: auto ancillaries | E419: smallcap | F419: 1512.79 | G419: 235.5 | H419: -2.24 | I419: 296898 | J419: 523229
A420: GOCLCORP | B420: Gocl Corporation Limited | C420: miscellaneous | D420: diversified - medium / small | E420: smallcap | F420: 2172.51 | G420: 428.2 | H420: -2.29 | I420: 106192 | J420: 506480
A421: MPSLTD | B421: Mps Limited | C421: i.t | D421: computers - software - medium / small | E421: midcap | F421: 5014.06 | G421: 2864 | H421: -2.29 | I421: 55546 | J421: 532440
A422: LLOYDSME | B422: Lloyds Metals & Energy Ltd | C422: metals & mining | D422: mining / minerals / metals | E422: largecap | F422: 118278.01 | G422: 2052.8 | H422: -2.3 | I422: 783313 | J422: 512455
A423: THELEELA | B423: Leela Palaces Hotels & Resorts Ltd | C423: services | D423: hotels | E423: midcap | F423: 17299.02 | G423: 505.8 | H423: -2.36 | I423: 263638 | J423: 544408
A424: SBIN | B424: State Bank Of India Ltd | C424: bank | D424: banks - public sector | E424: largecap | F424: 1012783.4 | G424: 1071 | H424: -2.39 | I424: 33068816 | J424: 500112
A425: GARFIBRES | B425: Garware Technical Fibres Ltd | C425: textiles | D425: textiles - products | E425: midcap | F425: 7927.58 | G425: 792.25 | H425: -2.41 | I425: 30300 | J425: 509557
A426: ONEPOINT | B426: One Point One Solutions Ltd | C426: i.t | D426: computers - software - medium / small | E426: smallcap | F426: 1586.3 | G426: 58.81 | H426: -2.52 | I426: 1796065 | J426: 535039
A427: KOTHARIPET | B427: Kothari Petrochemicals Limited | C427: energy | D427: petrochemicals | E427: smallcap | F427: 879.87 | G427: 145.51 | H427: -2.68 | I427: 80103 | J427: 532096
A428: NAHARSPING | B428: Nahar Spinning Mills Limited | C428: textiles | D428: textiles - cotton/blended | E428: smallcap | F428: 1140.57 | G428: 307.7 | H428: -2.7 | I428: 37947 | J428: 500296
A429: NEULANDLAB | B429: Neuland Laboratories Limited | C429: healthcare | D429: pharmaceuticals - indian - bulk drugs | E429: largecap | F429: 29322.71 | G429: 22216 | H429: -2.8 | I429: 88428 | J429: 524558
A430: SJS | B430: S J S Enterprises Ltd | C430: auto | D430: plastics products | E430: midcap | F430: 7828.78 | G430: 2372 | H430: -3.03 | I430: 227203 | J430: 543387
... A440: SOTL | B440: Savita Oil Technologies Limited | C440: energy | D440: petrochemicals | E440: midcap | F440: 5186.25 | G440: 691 | H440: -8.65 | I440: 1082651 | J440: 524667

Sheet Confluence Overlap
A1: Confluence Rank | B1: Total Score | C1: Relative Strength Rating | D1: Symbol | E1: Company Name | F1: Industry | G1: Common Count | H1: Scanner Signal | I1: Chartink Universe | J1: Scan Matches Count | K1: Backtest Recurrence (30D)
A2: =IF(B2=0,"",ROW()-1) | B2: =IFERROR(INDEX('Monit Non Financial'!$B$2:$B$400, MATCH(D2, 'Monit Non Financial'!$C$2:$C$400, 0)), IFERROR(INDEX('Monit Banks NBFC'!$B$2:$B$100, MATCH(D2, 'Monit Banks NBFC'!$C$2:$C$100, 0)), 0)) | C2: =IFERROR(INDEX('Monit Non Financial'!$L$2:$L$400, MATCH(D2, 'Monit Non Financial'!$C$2:$C$400, 0)), IFERROR(INDEX('Monit Banks NBFC'!$L$2:$L$100, MATCH(D2, 'Monit Banks NBFC'!$C$2:$C$100, 0)), "")) | D2: SBCL | E2: Shivalik Bimetal Controls Ltd | F2: Shunt Resistors | G2: 3 | H2: 52W Breakout | I2: Yes | J2: 21 | K2: 21
A3: =IF(B3=0,"",ROW()-1) | B3: =IFERROR(INDEX('Monit Non Financial'!$B$2:$B$400, MATCH(D3, 'Monit Non Financial'!$C$2:$C$400, 0)), IFERROR(INDEX('Monit Banks NBFC'!$B$2:$B$100, MATCH(D3, 'Monit Banks NBFC'!$C$2:$C$100, 0)), 0)) | C3: =IFERROR(INDEX('Monit Non Financial'!$L$2:$L$400, MATCH(D3, 'Monit Non Financial'!$C$2:$C$400, 0)), IFERROR(INDEX('Monit Banks NBFC'!$L$2:$L$100, MATCH(D3, 'Monit Banks NBFC'!$C$2:$C$100, 0)), "")) | D3: SYRMA | E3: Syrma SGS Technology Ltd | F3: Consumer Electronics - EMS | G3: 3 | H3: 52W Breakout | I3: Yes | J3: 23 | K3: 20
A4: =IF(B4=0,"",ROW()-1) | B4: =IFERROR(INDEX('Monit Non Financial'!$B$2:$B$400, MATCH(D4, 'Monit Non Financial'!$C$2:$C$400, 0)), IFERROR(INDEX('Monit Banks NBFC'!$B$2:$B$100, MATCH(D4, 'Monit Banks NBFC'!$C$2:$C$100, 0)), 0)) | C4: =IFERROR(INDEX('Monit Non Financial'!$L$2:$L$400, MATCH(D4, 'Monit Non Financial'!$C$2:$C$400, 0)), IFERROR(INDEX('Monit Banks NBFC'!$L$2:$L$100, MATCH(D4, 'Monit Banks NBFC'!$C$2:$C$100, 0)), "")) | D4: MACPOWER | E4: Macpower CNC Machines Ltd | F4: CNC - Machines | G4: 3 | H4: 52W Breakout | I4: Yes | J4: 28 | K4: 22
A5: =IF(B5=0,"",ROW()-1) | B5: =IFERROR(INDEX('Monit Non Financial'!$B$2:$B$400, MATCH(D5, 'Monit Non Financial'!$C$2:$C$400, 0)), IFERROR(INDEX('Monit Banks NBFC'!$B$2:$B$100, MATCH(D5, 'Monit Banks NBFC'!$C$2:$C$100, 0)), 0)) | C5: =IFERROR(INDEX('Monit Non Financial'!$L$2:$L$400, MATCH(D5, 'Monit Non Financial'!$C$2:$C$400, 0)), IFERROR(INDEX('Monit Banks NBFC'!$L$2:$L$100, MATCH(D5, 'Monit Banks NBFC'!$C$2:$C$100, 0)), "")) | D5: COMSYN | E5: Commercial Syn Bags Ltd | F5: Packaging - Polysacks | G5: 3 | H5: 52W Breakout | I5: Yes | J5: 22 | K5: 16
A6: =IF(B6=0,"",ROW()-1) | B6: =IFERROR(INDEX('Monit Non Financial'!$B$2:$B$400, MATCH(D6, 'Monit Non Financial'!$C$2:$C$400, 0)), IFERROR(INDEX('Monit Banks NBFC'!$B$2:$B$100, MATCH(D6, 'Monit Banks NBFC'!$C$2:$C$100, 0)), 0)) | C6: =IFERROR(INDEX('Monit Non Financial'!$L$2:$L$400, MATCH(D6, 'Monit Non Financial'!$C$2:$C$400, 0)), IFERROR(INDEX('Monit Banks NBFC'!$L$2:$L$100, MATCH(D6, 'Monit Banks NBFC'!$C$2:$C$100, 0)), "")) | D6: UEL | E6: Ujaas Energy Ltd | F6: Capital Goods - Transformers | G6: 3 | H6: 52W Breakout | I6: Yes | J6: 19 | K6: 6
A7: =IF(B7=0,"",ROW()-1) | B7: =IFERROR(INDEX('Monit Non Financial'!$B$2:$B$400, MATCH(D7, 'Monit Non Financial'!$C$2:$C$400, 0)), IFERROR(INDEX('Monit Banks NBFC'!$B$2:$B$100, MATCH(D7, 'Monit Banks NBFC'!$C$2:$C$100, 0)), 0)) | C7: =IFERROR(INDEX('Monit Non Financial'!$L$2:$L$400, MATCH(D7, 'Monit Non Financial'!$C$2:$C$400, 0)), IFERROR(INDEX('Monit Banks NBFC'!$L$2:$L$100, MATCH(D7, 'Monit Banks NBFC'!$C$2:$C$100, 0)), "")) | D7: PAYTM | E7: One 97 Communications Ltd | F7: E-Commerce - Platform - Utility | G7: 3 | H7: 52W Breakout | I7: Yes | J7: 23 | K7: 18
A8: =IF(B8=0,"",ROW()-1) | B8: =IFERROR(INDEX('Monit Non Financial'!$B$2:$B$400, MATCH(D8, 'Monit Non Financial'!$C$2:$C$400, 0)), IFERROR(INDEX('Monit Banks NBFC'!$B$2:$B$100, MATCH(D8, 'Monit Banks NBFC'!$C$2:$C$100, 0)), 0)) | C8: =IFERROR(INDEX('Monit Non Financial'!$L$2:$L$400, MATCH(D8, 'Monit Non Financial'!$C$2:$C$400, 0)), IFERROR(INDEX('Monit Banks NBFC'!$L$2:$L$100, MATCH(D8, 'Monit Banks NBFC'!$C$2:$C$100, 0)), "")) | D8: MMFL | E8: Mm Forgings Limited | F8: Castings, Forgings & Fastners | G8: 3 | H8: 52W Breakout | I8: Yes | J8: 21 | K8: 20
A9: =IF(B9=0,"",ROW()-1) | B9: =IFERROR(INDEX('Monit Non Financial'!$B$2:$B$400, MATCH(D9, 'Monit Non Financial'!$C$2:$C$400, 0)), IFERROR(INDEX('Monit Banks NBFC'!$B$2:$B$100, MATCH(D9, 'Monit Banks NBFC'!$C$2:$C$100, 0)), 0)) | C9: =IFERROR(INDEX('Monit Non Financial'!$L$2:$L$400, MATCH(D9, 'Monit Non Financial'!$C$2:$C$400, 0)), IFERROR(INDEX('Monit Banks NBFC'!$L$2:$L$100, MATCH(D9, 'Monit Banks NBFC'!$C$2:$C$100, 0)), "")) | D9: PIXTRANS | E9: Pix Transmission Ltd | F9: Rubber Processing/Rubber Products | G9: 2 | H9: No | I9: Yes | J9: 24 | K9: 18
A10: =IF(B10=0,"",ROW()-1) | B10: =IFERROR(INDEX('Monit Non Financial'!$B$2:$B$400, MATCH(D10, 'Monit Non Financial'!$C$2:$C$400, 0)), IFERROR(INDEX('Monit Banks NBFC'!$B$2:$B$100, MATCH(D10, 'Monit Banks NBFC'!$C$2:$C$100, 0)), 0)) | C10: =IFERROR(INDEX('Monit Non Financial'!$L$2:$L$400, MATCH(D10, 'Monit Non Financial'!$C$2:$C$400, 0)), IFERROR(INDEX('Monit Banks NBFC'!$L$2:$L$100, MATCH(D10, 'Monit Banks NBFC'!$C$2:$C$100, 0)), "")) | D10: NAVINFLUOR | E10: Navin Fluorine International Limited | F10: Chemicals - Flourine | G10: 2 | H10: No | I10: Yes | J10: 21 | K10: 21
A11: =IF(B11=0,"",ROW()-1) | B11: =IFERROR(INDEX('Monit Non Financial'!$B$2:$B$400, MATCH(D11, 'Monit Non Financial'!$C$2:$C$400, 0)), IFERROR(INDEX('Monit Banks NBFC'!$B$2:$B$100, MATCH(D11, 'Monit Banks NBFC'!$C$2:$C$100, 0)), 0)) | C11: =IFERROR(INDEX('Monit Non Financial'!$L$2:$L$400, MATCH(D11, 'Monit Non Financial'!$C$2:$C$400, 0)), IFERROR(INDEX('Monit Banks NBFC'!$L$2:$L$100, MATCH(D11, 'Monit Banks NBFC'!$C$2:$C$100, 0)), "")) | D11: APCOTEXIND | E11: Apcotex Industries Limited | F11: Rubber Processing/Rubber Products | G11: 2 | H11: No | I11: Yes | J11: 20 | K11: 25
A12: =IF(B12=0,"",ROW()-1) | B12: =IFERROR(INDEX('Monit Non Financial'!$B$2:$B$400, MATCH(D12, 'Monit Non Financial'!$C$2:$C$400, 0)), IFERROR(INDEX('Monit Banks NBFC'!$B$2:$B$100, MATCH(D12, 'Monit Banks NBFC'!$C$2:$C$100, 0)), 0)) | C12: =IFERROR(INDEX('Monit Non Financial'!$L$2:$L$400, MATCH(D12, 'Monit Non Financial'!$C$2:$C$400, 0)), IFERROR(INDEX('Monit Banks NBFC'!$L$2:$L$100, MATCH(D12, 'Monit Banks NBFC'!$C$2:$C$100, 0)), "")) | D12: IOLCP | E12: Iol Chemicals And Pharmaceuticals Limited | F12: Pharma - API & CRAMS | G12: 2 | H12: No | I12: Yes | J12: 19 | K12: 17
A13: =IF(B13=0,"",ROW()-1) | B13: =IFERROR(INDEX('Monit Non Financial'!$B$2:$B$400, MATCH(D13, 'Monit Non Financial'!$C$2:$C$400, 0)), IFERROR(INDEX('Monit Banks NBFC'!$B$2:$B$100, MATCH(D13, 'Monit Banks NBFC'!$C$2:$C$100, 0)), 0)) | C13: =IFERROR(INDEX('Monit Non Financial'!$L$2:$L$400, MATCH(D13, 'Monit Non Financial'!$C$2:$C$400, 0)), IFERROR(INDEX('Monit Banks NBFC'!$L$2:$L$100, MATCH(D13, 'Monit Banks NBFC'!$C$2:$C$100, 0)), "")) | D13: PRICOLLTD | E13: Pricol Ltd. | F13: Auto Ancillaries - 2 Wheelers | G13: 2 | H13: No | I13: Yes | J13: 20 | K13: 20
... A97: =IF(B97=0,"",ROW()-1) | B97: =IFERROR(INDEX('Monit Non Financial'!$B$2:$B$400, MATCH(D97, 'Monit Non Financial'!$C$2:$C$400, 0)), IFERROR(INDEX('Monit Banks NBFC'!$B$2:$B$100, MATCH(D97, 'Monit Banks NBFC'!$C$2:$C$100, 0)), 0)) | C97: =IFERROR(INDEX('Monit Non Financial'!$L$2:$L$400, MATCH(D97, 'Monit Non Financial'!$C$2:$C$400, 0)), IFERROR(INDEX('Monit Banks NBFC'!$L$2:$L$100, MATCH(D97, 'Monit Banks NBFC'!$C$2:$C$100, 0)), "")) | D97: JINDALSTEL | E97: Jindal Steel Ltd | F97: Steel Products | G97: 2 | H97: EMA Crossover | I97: Yes | J97: 3 | K97: 4

Sheet Monit Non Financial
A1: Rank (Non Financial) | B1: Total Score | C1: Symbol | D1: Company | E1: Sector | F1: Industry | G1: Market Cap Bucket | H1: Market Cap Cr | I1: Close | J1: Today Return % | K1: Volume | L1: Relative Strength Rating | M1: Relative Strength Status | N1: Relative Strength Score | O1: Calculated RSI (14) | P1: Calculated ADX (14) | Q1: Calculated V-stop Line | R1: Calculated Near-term Trigger | S1: Sector Benchmark | T1: Benchmark 1Y Return % | U1: Stock 1Y Return % | V1: Relative Strength 1Y (%) | W1: O'Neil Weighted Score | X1: Industry Growth | Y1: Industry Growth Score | Z1: Competitiveness | AA1: Competitiveness Score | AB1: Regulation | AC1: Regulation Score | AD1: Sector Headwinds/Tailwind | AE1: Sector Headwinds/Tailwind Score | AF1: Industry Type | AG1: Industry Type Score | AH1: Margins | AI1: Margins Score | AJ1: Margins Stability | AK1: Margins Stability Score | AL1: Growth | AM1: Growth Score | AN1: Business Type | AO1: Business Type Score | AP1: Near term triggers | AQ1: Near term triggers Score | AR1: Type of Revenue | AS1: Type of Revenue Score | AT1: Capital Allocation | AU1: Capital Allocation Score | AV1: Medium term Growth | AW1: Medium term Growth Score | AX1: ADX | AY1: ADX Score | AZ1: RSI | BA1: RSI Score | BB1: Stage Analysis | BC1: Stage Analysis Score | BD1: Price Volume Action | BE1: Price Volume Action Score | BF1: Secondary Trend | BG1: Secondary Trend Score | BH1: Primary Trend | BI1: Primary Trend Score | BJ1: Resistance | BK1: Resistance Score | BL1: V-stop | BM1: V-stop Score | BN1: PAT Growth | BO1: PAT Growth Score | BP1: Stock History | BQ1: Stock History Score | BR1: PE Ratio | BS1: PE Ratio Score | BT1: PEG Ratio | BU1: PEG Ratio Score | BV1: CFO to EBITDA | BW1: CFO to EBITDA Score | BX1: Debt to Equity | BY1: Debt to Equity Score | BZ1: Auditor Resignation | CA1: Auditor Resignation Score | CB1: Contingent Liability | CC1: Contingent Liability Score | CD1: Pledging | CE1: Pledging Score
A2: =IF(B2=0,"",RANK(B2,$B$2:$B$400,0)) | B2: =SUM(N2,Y2,AA2,AC2,AE2,AG2,AI2,AK2,AM2,AO2,AQ2,AS2,AU2,AW2,AY2,BA2,BC2,BE2,BG2,BI2,BK2,BM2,BO2,BQ2,BS2,BU2,BW2,BY2,CA2,CC2,CE2) | C2: KEI | D2: Kei Industries Limited | E2: industrials | F2: cables - power | G2: largecap | H2: 53536.33 | I2: 5659.8 | J2: 1.07 | K2: 736899 | L2: 36 | M2: Outperforming | N2: =IF(M2="Underperforming",-5,IF(L2>=95,15,IF(L2>=90,10,IF(L2>=80,5,0)))) | O2: 64.15 | P2: 25.26 | R2: Earnings / Momentum Support | S2: Nifty Energy | T2: 8.41 | U2: 25.03 | V2: 15.34 | W2: 4.92 | X2: Growing Industry | Y2: =IF(X2="Growing Industry",10,IF(X2="Cyclical in an Upturn",5,0)) | Z2: Too Many Players with High ROCE | AA2: =IF(Z2="Monopoly",10,IF(Z2="Oligopoly",5,IF(Z2="Duopoly that cooperate",10,IF(Z2="Duopoly that compete",5,IF(Z2="Too many players with High ROCE",5,0))))) | AB2: No | AC2: =IF(AB2="No",5,0) | AD2: Tailwind | AE2: =IF(AD2="Tailwind",10,0) | AF2: Structural (10 Years Consistency) | AG2: =IF(AF2="Structural (10 Years Consistency)",10,IF(AF2="Shallow Cyclical (2 to 3 years growth)",5,0)) | AH2: No | AI2: =IF(AH2="Yes due to Product Mix change or Operating Leverage",10,IF(AH2="Yes, these are peak margins",-5,IF(AH2="No",5,0))) | AJ2: Stable | AK2: =IF(AJ2="Stable",10,0) | AL2: Yes | AM2: =IF(AL2="Yes",10,0) | AN2: B2B | AO2: =IF(AN2="B2C",10,IF(AN2="B2B",5,0)) | AP2: Yes | AQ2: =IF(AP2="Yes",10,0) | AR2: Fully Annuity | AS2: =IF(AR2="Fully Annuity",10,IF(AR2="Higher Annuity, Lower One Time",5,IF(AR2="Higher One Time, Lower Annuity",3,0))) | AT2: Good | AU2: =IF(AT2="Good",10,0) | AV2: Yes for more than 2 years | AW2: =IF(AV2="Yes for more than 2 years",10,IF(AV2="Yes only for next 1 to 2 years",5,0)) | AX2: Above 40 | AY2: =IF(AX2="Above 40",20,IF(AX2="20 to 40",10,IF(AX2="0 to 20",-5,0))) | AZ2: Between 50 to 75 | BA2: =IF(AZ2="Between 50 to 75",10,IF(AZ2="Above 75",0,0)) | BB2: Stage 2 | BC2: =IF(BB2="Stage 2",20,IF(BB2="Stage 1",0,IF(BB2="Stage 3",5,IF(BB2="Stage 4",-5,0)))) | BD2: Positive Trend | BE2: =IF(BD2="Positive Trend",20,IF(BD2="Negative Trend",-10,0)) | BF2: Uptrend | BG2: =IF(BF2="Uptrend",10,IF(BF2="Sideways",5,0)) | BH2: Uptrend | BI2: =IF(BH2="Uptrend",10,IF(BH2="Sideways",5,0)) | BJ2: Close to 52 week high or retracement | BK2: =IF(BJ2="Overhead supply in last 2 years in last 2 years",-5,IF(BJ2="Close to 52 week high or retracement",5,IF(BJ2="Blue sky scenario",10,IF(BJ2="Long term Downtrend",-10,0)))) | BL2: Yes | BM2: =IF(BL2="Yes",10,0) | BN2: More than 20% | BO2: =IF(BN2="More than 20%",10,IF(BN2="Between 12 to 20%",5,IF(BN2="Less than 12%",0,0))) | BP2: Yes | BQ2: =IF(BP2="No",10,0) | BR2: No | BS2: =IF(BR2="NO",5,0) | BT2: Less than 1.5 | BU2: =IF(BT2="Above 2",0,IF(BT2="Between 1.5 to 2",5,IF(BT2="Less than 1.5",10,0))) | BV2: Above 70% | BW2: =IF(BV2="Above 70%",10,IF(BV2="Between 50% to 70%",5,IF(BV2="Less than 50%",0,IF(BV2="Negative",-10,IF(BV2="Less than 50% and Borrowings are increasing",-5,0))))) | BX2: Less than 0.7 | BY2: =IF(BX2="More than 1.2",-10,IF(BX2="Between 0.7 to 1.2",0,IF(BX2="Less than 0.7",10,0))) | BZ2: No | CA2: =IF(BZ2="Yes",-10,0) | CB2: Less than 15% | CC2: =IF(CB2="More than 15%",-10,IF(CB2="Less than 15%",10,0)) | CD2: Yes, More Than 10% | CE2: =IF(CD2="Yes, more than 10%",-10,IF(CD2="No",10,0))
A3: =IF(B3=0,"",RANK(B3,$B$2:$B$400,0)) | B3: =SUM(N3,Y3,AA3,AC3,AE3,AG3,AI3,AK3,AM3,AO3,AQ3,AS3,AU3,AW3,AY3,BA3,BC3,BE3,BG3,BI3,BK3,BM3,BO3,BQ3,BS3,BU3,BW3,BY3,CA3,CC3,CE3) | C3: SBCL | D3: Shivalik Bimetal Controls Ltd | E3: metals & mining | F3: mining / minerals / metals | G3: midcap | H3: 5304.77 | I3: 1105.05 | J3: 20 | K3: 10977326 | L3: 72 | M3: Underperforming | N3: =IF(M3="Underperforming",-5,IF(L3>=95,15,IF(L3>=90,10,IF(L3>=80,5,0)))) | O3: 76.2 | P3: 45.6 | R3: Volume Spike / Accumulation | S3: Nifty Metal | T3: 31.49 | U3: 23.64 | V3: -5.97 | W3: 14.67 | X3: Growing Industry | Y3: =IF(X3="Growing Industry",10,IF(X3="Cyclical in an Upturn",5,0)) | Z3: Monopoly | AA3: =IF(Z3="Monopoly",10,IF(Z3="Oligopoly",5,IF(Z3="Duopoly that cooperate",10,IF(Z3="Duopoly that compete",5,IF(Z3="Too many players with High ROCE",5,0))))) | AB3: No | AC3: =IF(AB3="No",5,0) | AD3: Tailwind | AE3: =IF(AD3="Tailwind",10,0) | AF3: Shallow Cyclical (2 to 3 Years Growth) | AG3: =IF(AF3="Structural (10 Years Consistency)",10,IF(AF3="Shallow Cyclical (2 to 3 years growth)",5,0)) | AH3: Yes due to Product Mix change or Operating Leverage | AI3: =IF(AH3="Yes due to Product Mix change or Operating Leverage",10,IF(AH3="Yes, these are peak margins",-5,IF(AH3="No",5,0))) | AJ3: Stable | AK3: =IF(AJ3="Stable",10,0) | AL3: Yes | AM3: =IF(AL3="Yes",10,0) | AN3: B2B | AO3: =IF(AN3="B2C",10,IF(AN3="B2B",5,0)) | AP3: Yes | AQ3: =IF(AP3="Yes",10,0) | AR3: Fully One Time | AS3: =IF(AR3="Fully Annuity",10,IF(AR3="Higher Annuity, Lower One Time",5,IF(AR3="Higher One Time, Lower Annuity",3,0))) | AT3: Good | AU3: =IF(AT3="Good",10,0) | AV3: Yes for more than 2 years | AW3: =IF(AV3="Yes for more than 2 years",10,IF(AV3="Yes only for next 1 to 2 years",5,0)) | AX3: 20 to 40 | AY3: =IF(AX3="Above 40",20,IF(AX3="20 to 40",10,IF(AX3="0 to 20",-5,0))) | AZ3: Between 50 to 75 | BA3: =IF(AZ3="Between 50 to 75",10,IF(AZ3="Above 75",0,0)) | BB3: Stage 2 | BC3: =IF(BB3="Stage 2",20,IF(BB3="Stage 1",0,IF(BB3="Stage 3",5,IF(BB3="Stage 4",-5,0)))) | BD3: Positive Trend | BE3: =IF(BD3="Positive Trend",20,IF(BD3="Negative Trend",-10,0)) | BF3: Uptrend | BG3: =IF(BF3="Uptrend",10,IF(BF3="Sideways",5,0)) | BH3: Uptrend | BI3: =IF(BH3="Uptrend",10,IF(BH3="Sideways",5,0)) | BJ3: Close to 52 week high or retracement | BK3: =IF(BJ3="Overhead supply in last 2 years in last 2 years",-5,IF(BJ3="Close to 52 week high or retracement",5,IF(BJ3="Blue sky scenario",10,IF(BJ3="Long term Downtrend",-10,0)))) | BL3: Yes | BM3: =IF(BL3="Yes",10,0) | BN3: More than 20% | BO3: =IF(BN3="More than 20%",10,IF(BN3="Between 12 to 20%",5,IF(BN3="Less than 12%",0,0))) | BP3: Yes | BQ3: =IF(BP3="No",10,0) | BR3: No | BS3: =IF(BR3="NO",5,0) | BT3: Between 1.5 to 2 | BU3: =IF(BT3="Above 2",0,IF(BT3="Between 1.5 to 2",5,IF(BT3="Less than 1.5",10,0))) | BV3: Less than 50% | BW3: =IF(BV3="Above 70%",10,IF(BV3="Between 50% to 70%",5,IF(BV3="Less than 50%",0,IF(BV3="Negative",-10,IF(BV3="Less than 50% and Borrowings are increasing",-5,0))))) | BX3: Less than 0.7 | BY3: =IF(BX3="More than 1.2",-10,IF(BX3="Between 0.7 to 1.2",0,IF(BX3="Less than 0.7",10,0))) | BZ3: No | CA3: =IF(BZ3="Yes",-10,0) | CB3: Less than 15% | CC3: =IF(CB3="More than 15%",-10,IF(CB3="Less than 15%",10,0)) | CD3: No | CE3: =IF(CD3="Yes, more than 10%",-10,IF(CD3="No",10,0))
A4: =IF(B4=0,"",RANK(B4,$B$2:$B$400,0)) | B4: =SUM(N4,Y4,AA4,AC4,AE4,AG4,AI4,AK4,AM4,AO4,AQ4,AS4,AU4,AW4,AY4,BA4,BC4,BE4,BG4,BI4,BK4,BM4,BO4,BQ4,BS4,BU4,BW4,BY4,CA4,CC4,CE4) | C4: PIXTRANS | D4: Pix Transmission Ltd | E4: fmcg | F4: miscellaneous | G4: smallcap | H4: 2339.72 | I4: 1986.5 | J4: 15.68 | K4: 1309397 | L4: 48 | M4: Outperforming | N4: =IF(M4="Underperforming",-5,IF(L4>=95,15,IF(L4>=90,10,IF(L4>=80,5,0)))) | O4: 59.95 | P4: 43.39 | R4: Volume Spike / Accumulation | S4: Nifty FMCG | T4: -13.73 | U4: 17.79 | V4: 36.54 | W4: 7.69 | X4: Growing Industry | Y4: =IF(X4="Growing Industry",10,IF(X4="Cyclical in an Upturn",5,0)) | Z4: Too Many Players with High ROCE | AA4: =IF(Z4="Monopoly",10,IF(Z4="Oligopoly",5,IF(Z4="Duopoly that cooperate",10,IF(Z4="Duopoly that compete",5,IF(Z4="Too many players with High ROCE",5,0))))) | AB4: No | AC4: =IF(AB4="No",5,0) | AD4: Headwind | AE4: =IF(AD4="Tailwind",10,0) | AF4: Structural (10 Years Consistency) | AG4: =IF(AF4="Structural (10 Years Consistency)",10,IF(AF4="Shallow Cyclical (2 to 3 years growth)",5,0)) | AH4: No | AI4: =IF(AH4="Yes due to Product Mix change or Operating Leverage",10,IF(AH4="Yes, these are peak margins",-5,IF(AH4="No",5,0))) | AJ4: Stable | AK4: =IF(AJ4="Stable",10,0) | AL4: Yes | AM4: =IF(AL4="Yes",10,0) | AN4: B2C | AO4: =IF(AN4="B2C",10,IF(AN4="B2B",5,0)) | AP4: Yes | AQ4: =IF(AP4="Yes",10,0) | AR4: Higher Annuity, Lower One Time | AS4: =IF(AR4="Fully Annuity",10,IF(AR4="Higher Annuity, Lower One Time",5,IF(AR4="Higher One Time, Lower Annuity",3,0))) | AT4: Good | AU4: =IF(AT4="Good",10,0) | AV4: Yes for more than 2 years | AW4: =IF(AV4="Yes for more than 2 years",10,IF(AV4="Yes only for next 1 to 2 years",5,0)) | AX4: Above 40 | AY4: =IF(AX4="Above 40",20,IF(AX4="20 to 40",10,IF(AX4="0 to 20",-5,0))) | AZ4: Between 50 to 75 | BA4: =IF(AZ4="Between 50 to 75",10,IF(AZ4="Above 75",0,0)) | BB4: Stage 3 | BC4: =IF(BB4="Stage 2",20,IF(BB4="Stage 1",0,IF(BB4="Stage 3",5,IF(BB4="Stage 4",-5,0)))) | BD4: Negative Trend | BE4: =IF(BD4="Positive Trend",20,IF(BD4="Negative Trend",-10,0)) | BF4: Uptrend | BG4: =IF(BF4="Uptrend",10,IF(BF4="Sideways",5,0)) | BH4: Uptrend | BI4: =IF(BH4="Uptrend",10,IF(BH4="Sideways",5,0)) | BJ4: Close to 52 week high or retracement | BK4: =IF(BJ4="Overhead supply in last 2 years in last 2 years",-5,IF(BJ4="Close to 52 week high or retracement",5,IF(BJ4="Blue sky scenario",10,IF(BJ4="Long term Downtrend",-10,0)))) | BL4: Yes | BM4: =IF(BL4="Yes",10,0) | BN4: More than 20% | BO4: =IF(BN4="More than 20%",10,IF(BN4="Between 12 to 20%",5,IF(BN4="Less than 12%",0,0))) | BP4: No | BQ4: =IF(BP4="No",10,0) | BR4: No | BS4: =IF(BR4="NO",5,0) | BT4: Less than 1.5 | BU4: =IF(BT4="Above 2",0,IF(BT4="Between 1.5 to 2",5,IF(BT4="Less than 1.5",10,0))) | BV4: Above 70% | BW4: =IF(BV4="Above 70%",10,IF(BV4="Between 50% to 70%",5,IF(BV4="Less than 50%",0,IF(BV4="Negative",-10,IF(BV4="Less than 50% and Borrowings are increasing",-5,0))))) | BX4: Less than 0.7 | BY4: =IF(BX4="More than 1.2",-10,IF(BX4="Between 0.7 to 1.2",0,IF(BX4="Less than 0.7",10,0))) | BZ4: No | CA4: =IF(BZ4="Yes",-10,0) | CB4: Less than 15% | CC4: =IF(CB4="More than 15%",-10,IF(CB4="Less than 15%",10,0)) | CD4: No | CE4: =IF(CD4="Yes, more than 10%",-10,IF(CD4="No",10,0))
A5: =IF(B5=0,"",RANK(B5,$B$2:$B$400,0)) | B5: =SUM(N5,Y5,AA5,AC5,AE5,AG5,AI5,AK5,AM5,AO5,AQ5,AS5,AU5,AW5,AY5,BA5,BC5,BE5,BG5,BI5,BK5,BM5,BO5,BQ5,BS5,BU5,BW5,BY5,CA5,CC5,CE5) | C5: APLAPOLLO | D5: Apl Apollo Tubes Limited | E5: industrials | F5: steel - large | G5: largecap | H5: 54698.71 | I5: 2020 | J5: 2.54 | K5: 1128980 | L5: 10 | M5: Underperforming | N5: =IF(M5="Underperforming",-5,IF(L5>=95,15,IF(L5>=90,10,IF(L5>=80,5,0)))) | O5: 56.06 | P5: 10.78 | R5: Earnings / Momentum Support | S5: Nifty Metal | T5: 31.49 | U5: 8.12 | V5: -17.78 | W5: -0.94 | X5: Cyclical in an Upturn | Y5: =IF(X5="Growing Industry",10,IF(X5="Cyclical in an Upturn",5,0)) | Z5: Oligopoly | AA5: =IF(Z5="Monopoly",10,IF(Z5="Oligopoly",5,IF(Z5="Duopoly that cooperate",10,IF(Z5="Duopoly that compete",5,IF(Z5="Too many players with High ROCE",5,0))))) | AB5: No | AC5: =IF(AB5="No",5,0) | AD5: Tailwind | AE5: =IF(AD5="Tailwind",10,0) | AF5: Cyclical | AG5: =IF(AF5="Structural (10 Years Consistency)",10,IF(AF5="Shallow Cyclical (2 to 3 years growth)",5,0)) | AH5: No | AI5: =IF(AH5="Yes due to Product Mix change or Operating Leverage",10,IF(AH5="Yes, these are peak margins",-5,IF(AH5="No",5,0))) | AJ5: Stable | AK5: =IF(AJ5="Stable",10,0) | AL5: Yes | AM5: =IF(AL5="Yes",10,0) | AN5: B2C | AO5: =IF(AN5="B2C",10,IF(AN5="B2B",5,0)) | AP5: Yes | AQ5: =IF(AP5="Yes",10,0) | AR5: Fully One Time | AS5: =IF(AR5="Fully Annuity",10,IF(AR5="Higher Annuity, Lower One Time",5,IF(AR5="Higher One Time, Lower Annuity",3,0))) | AT5: Good | AU5: =IF(AT5="Good",10,0) | AV5: Yes for more than 2 years | AW5: =IF(AV5="Yes for more than 2 years",10,IF(AV5="Yes only for next 1 to 2 years",5,0)) | AX5: Above 40 | AY5: =IF(AX5="Above 40",20,IF(AX5="20 to 40",10,IF(AX5="0 to 20",-5,0))) | AZ5: Above 75 | BA5: =IF(AZ5="Between 50 to 75",10,IF(AZ5="Above 75",0,0)) | BB5: Stage 2 | BC5: =IF(BB5="Stage 2",20,IF(BB5="Stage 1",0,IF(BB5="Stage 3",5,IF(BB5="Stage 4",-5,0)))) | BD5: Positive Trend | BE5: =IF(BD5="Positive Trend",20,IF(BD5="Negative Trend",-10,0)) | BF5: Uptrend | BG5: =IF(BF5="Uptrend",10,IF(BF5="Sideways",5,0)) | BH5: Uptrend | BI5: =IF(BH5="Uptrend",10,IF(BH5="Sideways",5,0)) | BJ5: Close to 52 week high or retracement | BK5: =IF(BJ5="Overhead supply in last 2 years in last 2 years",-5,IF(BJ5="Close to 52 week high or retracement",5,IF(BJ5="Blue sky scenario",10,IF(BJ5="Long term Downtrend",-10,0)))) | BL5: Yes | BM5: =IF(BL5="Yes",10,0) | BN5: More than 20% | BO5: =IF(BN5="More than 20%",10,IF(BN5="Between 12 to 20%",5,IF(BN5="Less than 12%",0,0))) | BP5: Yes | BQ5: =IF(BP5="No",10,0) | BR5: Yes | BS5: =IF(BR5="NO",5,0) | BT5: Between 1.5 to 2 | BU5: =IF(BT5="Above 2",0,IF(BT5="Between 1.5 to 2",5,IF(BT5="Less than 1.5",10,0))) | BV5: Above 70% | BW5: =IF(BV5="Above 70%",10,IF(BV5="Between 50% to 70%",5,IF(BV5="Less than 50%",0,IF(BV5="Negative",-10,IF(BV5="Less than 50% and Borrowings are increasing",-5,0))))) | BX5: Less than 0.7 | BY5: =IF(BX5="More than 1.2",-10,IF(BX5="Between 0.7 to 1.2",0,IF(BX5="Less than 0.7",10,0))) | BZ5: No | CA5: =IF(BZ5="Yes",-10,0) | CB5: Less than 15% | CC5: =IF(CB5="More than 15%",-10,IF(CB5="Less than 15%",10,0)) | CD5: No | CE5: =IF(CD5="Yes, more than 10%",-10,IF(CD5="No",10,0))
A6: =IF(B6=0,"",RANK(B6,$B$2:$B$400,0)) | B6: =SUM(N6,Y6,AA6,AC6,AE6,AG6,AI6,AK6,AM6,AO6,AQ6,AS6,AU6,AW6,AY6,BA6,BC6,BE6,BG6,BI6,BK6,BM6,BO6,BQ6,BS6,BU6,BW6,BY6,CA6,CC6,CE6) | C6: APOLLOTYRE | D6: Apollo Tyres Limited | E6: auto | F6: tyres | G6: largecap | H6: 28261.99 | I6: 445.95 | J6: 0.21 | K6: 709497 | L6: 10 | M6: Underperforming | N6: =IF(M6="Underperforming",-5,IF(L6>=95,15,IF(L6>=90,10,IF(L6>=80,5,0)))) | O6: 54.37 | P6: 16.91 | R6: Earnings / Momentum Support | S6: Nifty Auto | T6: 13.41 | U6: -4.18 | V6: -15.51 | W6: -1.18 | X6: Cyclical in an Upturn | Y6: =IF(X6="Growing Industry",10,IF(X6="Cyclical in an Upturn",5,0)) | Z6: Oligopoly | AA6: =IF(Z6="Monopoly",10,IF(Z6="Oligopoly",5,IF(Z6="Duopoly that cooperate",10,IF(Z6="Duopoly that compete",5,IF(Z6="Too many players with High ROCE",5,0))))) | AB6: No | AC6: =IF(AB6="No",5,0) | AD6: Tailwind | AE6: =IF(AD6="Tailwind",10,0) | AF6: Cyclical | AG6: =IF(AF6="Structural (10 Years Consistency)",10,IF(AF6="Shallow Cyclical (2 to 3 years growth)",5,0)) | AH6: No | AI6: =IF(AH6="Yes due to Product Mix change or Operating Leverage",10,IF(AH6="Yes, these are peak margins",-5,IF(AH6="No",5,0))) | AJ6: Stable | AK6: =IF(AJ6="Stable",10,0) | AL6: Yes | AM6: =IF(AL6="Yes",10,0) | AN6: B2C | AO6: =IF(AN6="B2C",10,IF(AN6="B2B",5,0)) | AP6: Yes | AQ6: =IF(AP6="Yes",10,0) | AR6: Fully One Time | AS6: =IF(AR6="Fully Annuity",10,IF(AR6="Higher Annuity, Lower One Time",5,IF(AR6="Higher One Time, Lower Annuity",3,0))) | AT6: Good | AU6: =IF(AT6="Good",10,0) | AV6: Yes for more than 2 years | AW6: =IF(AV6="Yes for more than 2 years",10,IF(AV6="Yes only for next 1 to 2 years",5,0)) | AX6: Above 40 | AY6: =IF(AX6="Above 40",20,IF(AX6="20 to 40",10,IF(AX6="0 to 20",-5,0))) | AZ6: Above 75 | BA6: =IF(AZ6="Between 50 to 75",10,IF(AZ6="Above 75",0,0)) | BB6: Stage 2 | BC6: =IF(BB6="Stage 2",20,IF(BB6="Stage 1",0,IF(BB6="Stage 3",5,IF(BB6="Stage 4",-5,0)))) | BD6: Positive Trend | BE6: =IF(BD6="Positive Trend",20,IF(BD6="Negative Trend",-10,0)) | BF6: Uptrend | BG6: =IF(BF6="Uptrend",10,IF(BF6="Sideways",5,0)) | BH6: Uptrend | BI6: =IF(BH6="Uptrend",10,IF(BH6="Sideways",5,0)) | BJ6: Close to 52 week high or retracement | BK6: =IF(BJ6="Overhead supply in last 2 years in last 2 years",-5,IF(BJ6="Close to 52 week high or retracement",5,IF(BJ6="Blue sky scenario",10,IF(BJ6="Long term Downtrend",-10,0)))) | BL6: Yes | BM6: =IF(BL6="Yes",10,0) | BN6: More than 20% | BO6: =IF(BN6="More than 20%",10,IF(BN6="Between 12 to 20%",5,IF(BN6="Less than 12%",0,0))) | BP6: Yes | BQ6: =IF(BP6="No",10,0) | BR6: Yes | BS6: =IF(BR6="NO",5,0) | BT6: Between 1.5 to 2 | BU6: =IF(BT6="Above 2",0,IF(BT6="Between 1.5 to 2",5,IF(BT6="Less than 1.5",10,0))) | BV6: Above 70% | BW6: =IF(BV6="Above 70%",10,IF(BV6="Between 50% to 70%",5,IF(BV6="Less than 50%",0,IF(BV6="Negative",-10,IF(BV6="Less than 50% and Borrowings are increasing",-5,0))))) | BX6: Less than 0.7 | BY6: =IF(BX6="More than 1.2",-10,IF(BX6="Between 0.7 to 1.2",0,IF(BX6="Less than 0.7",10,0))) | BZ6: No | CA6: =IF(BZ6="Yes",-10,0) | CB6: Less than 15% | CC6: =IF(CB6="More than 15%",-10,IF(CB6="Less than 15%",10,0)) | CD6: No | CE6: =IF(CD6="Yes, more than 10%",-10,IF(CD6="No",10,0))
A7: =IF(B7=0,"",RANK(B7,$B$2:$B$400,0)) | B7: =SUM(N7,Y7,AA7,AC7,AE7,AG7,AI7,AK7,AM7,AO7,AQ7,AS7,AU7,AW7,AY7,BA7,BC7,BE7,BG7,BI7,BK7,BM7,BO7,BQ7,BS7,BU7,BW7,BY7,CA7,CC7,CE7) | C7: NAVINFLUOR | D7: Navin Fluorine International Limited | E7: chemicals | F7: chemicals | G7: largecap | H7: 42422.92 | I7: 8196.5 | J7: -0.9 | K7: 190608 | L7: 73 | M7: Outperforming | N7: =IF(M7="Underperforming",-5,IF(L7>=95,15,IF(L7>=90,10,IF(L7>=80,5,0)))) | O7: 76.5 | P7: 55.5 | R7: Earnings / Momentum Support | S7: Nifty 50 | T7: 0.85 | U7: 72.22 | V7: 70.77 | W7: 15.32 | X7: Growing Industry | Y7: =IF(X7="Growing Industry",10,IF(X7="Cyclical in an Upturn",5,0)) | Z7: Oligopoly | AA7: =IF(Z7="Monopoly",10,IF(Z7="Oligopoly",5,IF(Z7="Duopoly that cooperate",10,IF(Z7="Duopoly that compete",5,IF(Z7="Too many players with High ROCE",5,0))))) | AB7: No | AC7: =IF(AB7="No",5,0) | AD7: Tailwind | AE7: =IF(AD7="Tailwind",10,0) | AF7: Shallow Cyclical (2 to 3 Years Growth) | AG7: =IF(AF7="Structural (10 Years Consistency)",10,IF(AF7="Shallow Cyclical (2 to 3 years growth)",5,0)) | AH7: No | AI7: =IF(AH7="Yes due to Product Mix change or Operating Leverage",10,IF(AH7="Yes, these are peak margins",-5,IF(AH7="No",5,0))) | AJ7: Stable | AK7: =IF(AJ7="Stable",10,0) | AL7: Yes | AM7: =IF(AL7="Yes",10,0) | AN7: B2B | AO7: =IF(AN7="B2C",10,IF(AN7="B2B",5,0)) | AP7: Yes | AQ7: =IF(AP7="Yes",10,0) | AR7: Higher One Time, Lower Annuity | AS7: =IF(AR7="Fully Annuity",10,IF(AR7="Higher Annuity, Lower One Time",5,IF(AR7="Higher One Time, Lower Annuity",3,0))) | AT7: Good | AU7: =IF(AT7="Good",10,0) | AV7: Yes for more than 2 years | AW7: =IF(AV7="Yes for more than 2 years",10,IF(AV7="Yes only for next 1 to 2 years",5,0)) | AX7: 20 to 40 | AY7: =IF(AX7="Above 40",20,IF(AX7="20 to 40",10,IF(AX7="0 to 20",-5,0))) | AZ7: Between 50 to 75 | BA7: =IF(AZ7="Between 50 to 75",10,IF(AZ7="Above 75",0,0)) | BB7: Stage 3 | BC7: =IF(BB7="Stage 2",20,IF(BB7="Stage 1",0,IF(BB7="Stage 3",5,IF(BB7="Stage 4",-5,0)))) | BD7: Positive Trend | BE7: =IF(BD7="Positive Trend",20,IF(BD7="Negative Trend",-10,0)) | BF7: Uptrend | BG7: =IF(BF7="Uptrend",10,IF(BF7="Sideways",5,0)) | BH7: Uptrend | BI7: =IF(BH7="Uptrend",10,IF(BH7="Sideways",5,0)) | BJ7: Close to 52 week high or retracement | BK7: =IF(BJ7="Overhead supply in last 2 years in last 2 years",-5,IF(BJ7="Close to 52 week high or retracement",5,IF(BJ7="Blue sky scenario",10,IF(BJ7="Long term Downtrend",-10,0)))) | BL7: Yes | BM7: =IF(BL7="Yes",10,0) | BN7: More than 20% | BO7: =IF(BN7="More than 20%",10,IF(BN7="Between 12 to 20%",5,IF(BN7="Less than 12%",0,0))) | BP7: No | BQ7: =IF(BP7="No",10,0) | BR7: Yes | BS7: =IF(BR7="NO",5,0) | BT7: Above 2 | BU7: =IF(BT7="Above 2",0,IF(BT7="Between 1.5 to 2",5,IF(BT7="Less than 1.5",10,0))) | BV7: Between 50% to 70% | BW7: =IF(BV7="Above 70%",10,IF(BV7="Between 50% to 70%",5,IF(BV7="Less than 50%",0,IF(BV7="Negative",-10,IF(BV7="Less than 50% and Borrowings are increasing",-5,0))))) | BX7: Less than 0.7 | BY7: =IF(BX7="More than 1.2",-10,IF(BX7="Between 0.7 to 1.2",0,IF(BX7="Less than 0.7",10,0))) | BZ7: No | CA7: =IF(BZ7="Yes",-10,0) | CB7: Less than 15% | CC7: =IF(CB7="More than 15%",-10,IF(CB7="Less than 15%",10,0)) | CD7: No | CE7: =IF(CD7="Yes, more than 10%",-10,IF(CD7="No",10,0))
A8: =IF(B8=0,"",RANK(B8,$B$2:$B$400,0)) | B8: =SUM(N8,Y8,AA8,AC8,AE8,AG8,AI8,AK8,AM8,AO8,AQ8,AS8,AU8,AW8,AY8,BA8,BC8,BE8,BG8,BI8,BK8,BM8,BO8,BQ8,BS8,BU8,BW8,BY8,CA8,CC8,CE8) | C8: APCOTEXIND | D8: Apcotex Industries Limited | E8: chemicals | F8: miscellaneous | G8: smallcap | H8: 3187.43 | I8: 624.05 | J8: 1.5 | K8: 271630 | L8: 71 | M8: Outperforming | N8: =IF(M8="Underperforming",-5,IF(L8>=95,15,IF(L8>=90,10,IF(L8>=80,5,0)))) | O8: 73.88 | P8: 64.59 | R8: Earnings / Momentum Support | S8: Nifty 50 | T8: 0.85 | U8: 53.86 | V8: 52.57 | W8: 14.24 | X8: Growing Industry | Y8: =IF(X8="Growing Industry",10,IF(X8="Cyclical in an Upturn",5,0)) | Z8: Oligopoly | AA8: =IF(Z8="Monopoly",10,IF(Z8="Oligopoly",5,IF(Z8="Duopoly that cooperate",10,IF(Z8="Duopoly that compete",5,IF(Z8="Too many players with High ROCE",5,0))))) | AB8: No | AC8: =IF(AB8="No",5,0) | AD8: Tailwind | AE8: =IF(AD8="Tailwind",10,0) | AF8: Cyclical | AG8: =IF(AF8="Structural (10 Years Consistency)",10,IF(AF8="Shallow Cyclical (2 to 3 years growth)",5,0)) | AH8: No | AI8: =IF(AH8="Yes due to Product Mix change or Operating Leverage",10,IF(AH8="Yes, these are peak margins",-5,IF(AH8="No",5,0))) | AJ8: Stable | AK8: =IF(AJ8="Stable",10,0) | AL8: Yes | AM8: =IF(AL8="Yes",10,0) | AN8: B2B | AO8: =IF(AN8="B2C",10,IF(AN8="B2B",5,0)) | AP8: Yes | AQ8: =IF(AP8="Yes",10,0) | AR8: Fully One Time | AS8: =IF(AR8="Fully Annuity",10,IF(AR8="Higher Annuity, Lower One Time",5,IF(AR8="Higher One Time, Lower Annuity",3,0))) | AT8: Good | AU8: =IF(AT8="Good",10,0) | AV8: Yes for more than 2 years | AW8: =IF(AV8="Yes for more than 2 years",10,IF(AV8="Yes only for next 1 to 2 years",5,0)) | AX8: Above 40 | AY8: =IF(AX8="Above 40",20,IF(AX8="20 to 40",10,IF(AX8="0 to 20",-5,0))) | AZ8: Between 50 to 75 | BA8: =IF(AZ8="Between 50 to 75",10,IF(AZ8="Above 75",0,0)) | BB8: Stage 1 | BC8: =IF(BB8="Stage 2",20,IF(BB8="Stage 1",0,IF(BB8="Stage 3",5,IF(BB8="Stage 4",-5,0)))) | BD8: Positive Trend | BE8: =IF(BD8="Positive Trend",20,IF(BD8="Negative Trend",-10,0)) | BF8: Sideways | BG8: =IF(BF8="Uptrend",10,IF(BF8="Sideways",5,0)) | BH8: Uptrend | BI8: =IF(BH8="Uptrend",10,IF(BH8="Sideways",5,0)) | BJ8: Overhead supply in last 2 years in last 2 years | BK8: =IF(BJ8="Overhead supply in last 2 years in last 2 years",-5,IF(BJ8="Close to 52 week high or retracement",5,IF(BJ8="Blue sky scenario",10,IF(BJ8="Long term Downtrend",-10,0)))) | BL8: Yes | BM8: =IF(BL8="Yes",10,0) | BN8: More than 20% | BO8: =IF(BN8="More than 20%",10,IF(BN8="Between 12 to 20%",5,IF(BN8="Less than 12%",0,0))) | BP8: No | BQ8: =IF(BP8="No",10,0) | BR8: No | BS8: =IF(BR8="NO",5,0) | BT8: Less than 1.5 | BU8: =IF(BT8="Above 2",0,IF(BT8="Between 1.5 to 2",5,IF(BT8="Less than 1.5",10,0))) | BV8: Between 50% to 70% | BW8: =IF(BV8="Above 70%",10,IF(BV8="Between 50% to 70%",5,IF(BV8="Less than 50%",0,IF(BV8="Negative",-10,IF(BV8="Less than 50% and Borrowings are increasing",-5,0))))) | BX8: Less than 0.7 | BY8: =IF(BX8="More than 1.2",-10,IF(BX8="Between 0.7 to 1.2",0,IF(BX8="Less than 0.7",10,0))) | BZ8: No | CA8: =IF(BZ8="Yes",-10,0) | CB8: Less than 15% | CC8: =IF(CB8="More than 15%",-10,IF(CB8="Less than 15%",10,0)) | CD8: No | CE8: =IF(CD8="Yes, more than 10%",-10,IF(CD8="No",10,0))
A9: =IF(B9=0,"",RANK(B9,$B$2:$B$400,0)) | B9: =SUM(N9,Y9,AA9,AC9,AE9,AG9,AI9,AK9,AM9,AO9,AQ9,AS9,AU9,AW9,AY9,BA9,BC9,BE9,BG9,BI9,BK9,BM9,BO9,BQ9,BS9,BU9,BW9,BY9,CA9,CC9,CE9) | C9: RPEL | D9: Raghav Productivity Enhancers Ltd | E9: building materials | F9: refractories / intermediates | G9: midcap | H9: 5770.09 | I9: 1313.8 | J9: 4.56 | K9: 101708 | L9: 96 | M9: Outperforming | N9: =IF(M9="Underperforming",-5,IF(L9>=95,15,IF(L9>=90,10,IF(L9>=80,5,0)))) | O9: 69.73 | P9: 51.74 | R9: Earnings / Momentum Support | S9: Nifty Infra | T9: 1.74 | U9: 89.85 | V9: 86.6 | W9: 35.04 | X9: Growing Industry | Y9: =IF(X9="Growing Industry",10,IF(X9="Cyclical in an Upturn",5,0)) | Z9: Too Many Players with High ROCE | AA9: =IF(Z9="Monopoly",10,IF(Z9="Oligopoly",5,IF(Z9="Duopoly that cooperate",10,IF(Z9="Duopoly that compete",5,IF(Z9="Too many players with High ROCE",5,0))))) | AB9: No | AC9: =IF(AB9="No",5,0) | AD9: Headwind | AE9: =IF(AD9="Tailwind",10,0) | AF9: Structural (10 Years Consistency) | AG9: =IF(AF9="Structural (10 Years Consistency)",10,IF(AF9="Shallow Cyclical (2 to 3 years growth)",5,0)) | AH9: No | AI9: =IF(AH9="Yes due to Product Mix change or Operating Leverage",10,IF(AH9="Yes, these are peak margins",-5,IF(AH9="No",5,0))) | AJ9: Stable | AK9: =IF(AJ9="Stable",10,0) | AL9: Yes | AM9: =IF(AL9="Yes",10,0) | AN9: B2B | AO9: =IF(AN9="B2C",10,IF(AN9="B2B",5,0)) | AP9: No | AQ9: =IF(AP9="Yes",10,0) | AR9: Higher One Time, Lower Annuity | AS9: =IF(AR9="Fully Annuity",10,IF(AR9="Higher Annuity, Lower One Time",5,IF(AR9="Higher One Time, Lower Annuity",3,0))) | AT9: Good | AU9: =IF(AT9="Good",10,0) | AV9: Yes for more than 2 years | AW9: =IF(AV9="Yes for more than 2 years",10,IF(AV9="Yes only for next 1 to 2 years",5,0)) | AX9: Above 40 | AY9: =IF(AX9="Above 40",20,IF(AX9="20 to 40",10,IF(AX9="0 to 20",-5,0))) | AZ9: Between 50 to 75 | BA9: =IF(AZ9="Between 50 to 75",10,IF(AZ9="Above 75",0,0)) | BB9: Stage 3 | BC9: =IF(BB9="Stage 2",20,IF(BB9="Stage 1",0,IF(BB9="Stage 3",5,IF(BB9="Stage 4",-5,0)))) | BD9: Negative Trend | BE9: =IF(BD9="Positive Trend",20,IF(BD9="Negative Trend",-10,0)) | BF9: Uptrend | BG9: =IF(BF9="Uptrend",10,IF(BF9="Sideways",5,0)) | BH9: Uptrend | BI9: =IF(BH9="Uptrend",10,IF(BH9="Sideways",5,0)) | BJ9: Close to 52 week high or retracement | BK9: =IF(BJ9="Overhead supply in last 2 years in last 2 years",-5,IF(BJ9="Close to 52 week high or retracement",5,IF(BJ9="Blue sky scenario",10,IF(BJ9="Long term Downtrend",-10,0)))) | BL9: Yes | BM9: =IF(BL9="Yes",10,0) | BN9: More than 20% | BO9: =IF(BN9="More than 20%",10,IF(BN9="Between 12 to 20%",5,IF(BN9="Less than 12%",0,0))) | BP9: No | BQ9: =IF(BP9="No",10,0) | BR9: Yes | BS9: =IF(BR9="NO",5,0) | BT9: Less than 1.5 | BU9: =IF(BT9="Above 2",0,IF(BT9="Between 1.5 to 2",5,IF(BT9="Less than 1.5",10,0))) | BV9: Above 70% | BW9: =IF(BV9="Above 70%",10,IF(BV9="Between 50% to 70%",5,IF(BV9="Less than 50%",0,IF(BV9="Negative",-10,IF(BV9="Less than 50% and Borrowings are increasing",-5,0))))) | BX9: Less than 0.7 | BY9: =IF(BX9="More than 1.2",-10,IF(BX9="Between 0.7 to 1.2",0,IF(BX9="Less than 0.7",10,0))) | BZ9: No | CA9: =IF(BZ9="Yes",-10,0) | CB9: Less than 15% | CC9: =IF(CB9="More than 15%",-10,IF(CB9="Less than 15%",10,0)) | CD9: No | CE9: =IF(CD9="Yes, more than 10%",-10,IF(CD9="No",10,0))
A10: =IF(B10=0,"",RANK(B10,$B$2:$B$400,0)) | B10: =SUM(N10,Y10,AA10,AC10,AE10,AG10,AI10,AK10,AM10,AO10,AQ10,AS10,AU10,AW10,AY10,BA10,BC10,BE10,BG10,BI10,BK10,BM10,BO10,BQ10,BS10,BU10,BW10,BY10,CA10,CC10,CE10) | C10: CONFIPET | D10: Confidence Petroleum India Ltd | E10: miscellaneous | F10: miscellaneous | G10: smallcap | H10: 2700.46 | I10: 82.74 | J10: 1.8 | K10: 5858829 | L10: 90 | M10: Outperforming | N10: =IF(M10="Underperforming",-5,IF(L10>=95,15,IF(L10>=90,10,IF(L10>=80,5,0)))) | O10: 72.7 | P10: 69.01 | R10: Earnings / Momentum Support | S10: Nifty 50 | T10: 0.85 | U10: 66.91 | V10: 65.5 | W10: 26.52 | X10: Growing Industry | Y10: =IF(X10="Growing Industry",10,IF(X10="Cyclical in an Upturn",5,0)) | Z10: Too Many Players with High ROCE | AA10: =IF(Z10="Monopoly",10,IF(Z10="Oligopoly",5,IF(Z10="Duopoly that cooperate",10,IF(Z10="Duopoly that compete",5,IF(Z10="Too many players with High ROCE",5,0))))) | AB10: No | AC10: =IF(AB10="No",5,0) | AD10: Headwind | AE10: =IF(AD10="Tailwind",10,0) | AF10: Structural (10 Years Consistency) | AG10: =IF(AF10="Structural (10 Years Consistency)",10,IF(AF10="Shallow Cyclical (2 to 3 years growth)",5,0)) | AH10: No | AI10: =IF(AH10="Yes due to Product Mix change or Operating Leverage",10,IF(AH10="Yes, these are peak margins",-5,IF(AH10="No",5,0))) | AJ10: Stable | AK10: =IF(AJ10="Stable",10,0) | AL10: Yes | AM10: =IF(AL10="Yes",10,0) | AN10: B2B | AO10: =IF(AN10="B2C",10,IF(AN10="B2B",5,0)) | AP10: No | AQ10: =IF(AP10="Yes",10,0) | AR10: Higher One Time, Lower Annuity | AS10: =IF(AR10="Fully Annuity",10,IF(AR10="Higher Annuity, Lower One Time",5,IF(AR10="Higher One Time, Lower Annuity",3,0))) | AT10: Good | AU10: =IF(AT10="Good",10,0) | AV10: Yes for more than 2 years | AW10: =IF(AV10="Yes for more than 2 years",10,IF(AV10="Yes only for next 1 to 2 years",5,0)) | AX10: Above 40 | AY10: =IF(AX10="Above 40",20,IF(AX10="20 to 40",10,IF(AX10="0 to 20",-5,0))) | AZ10: Between 50 to 75 | BA10: =IF(AZ10="Between 50 to 75",10,IF(AZ10="Above 75",0,0)) | BB10: Stage 3 | BC10: =IF(BB10="Stage 2",20,IF(BB10="Stage 1",0,IF(BB10="Stage 3",5,IF(BB10="Stage 4",-5,0)))) | BD10: Negative Trend | BE10: =IF(BD10="Positive Trend",20,IF(BD10="Negative Trend",-10,0)) | BF10: Uptrend | BG10: =IF(BF10="Uptrend",10,IF(BF10="Sideways",5,0)) | BH10: Uptrend | BI10: =IF(BH10="Uptrend",10,IF(BH10="Sideways",5,0)) | BJ10: Close to 52 week high or retracement | BK10: =IF(BJ10="Overhead supply in last 2 years in last 2 years",-5,IF(BJ10="Close to 52 week high or retracement",5,IF(BJ10="Blue sky scenario",10,IF(BJ10="Long term Downtrend",-10,0)))) | BL10: Yes | BM10: =IF(BL10="Yes",10,0) | BN10: More than 20% | BO10: =IF(BN10="More than 20%",10,IF(BN10="Between 12 to 20%",5,IF(BN10="Less than 12%",0,0))) | BP10: No | BQ10: =IF(BP10="No",10,0) | BR10: No | BS10: =IF(BR10="NO",5,0) | BT10: Less than 1.5 | BU10: =IF(BT10="Above 2",0,IF(BT10="Between 1.5 to 2",5,IF(BT10="Less than 1.5",10,0))) | BV10: Above 70% | BW10: =IF(BV10="Above 70%",10,IF(BV10="Between 50% to 70%",5,IF(BV10="Less than 50%",0,IF(BV10="Negative",-10,IF(BV10="Less than 50% and Borrowings are increasing",-5,0))))) | BX10: Less than 0.7 | BY10: =IF(BX10="More than 1.2",-10,IF(BX10="Between 0.7 to 1.2",0,IF(BX10="Less than 0.7",10,0))) | BZ10: No | CA10: =IF(BZ10="Yes",-10,0) | CB10: Less than 15% | CC10: =IF(CB10="More than 15%",-10,IF(CB10="Less than 15%",10,0)) | CD10: No | CE10: =IF(CD10="Yes, more than 10%",-10,IF(CD10="No",10,0))
A11: =IF(B11=0,"",RANK(B11,$B$2:$B$400,0)) | B11: =SUM(N11,Y11,AA11,AC11,AE11,AG11,AI11,AK11,AM11,AO11,AQ11,AS11,AU11,AW11,AY11,BA11,BC11,BE11,BG11,BI11,BK11,BM11,BO11,BQ11,BS11,BU11,BW11,BY11,CA11,CC11,CE11) | C11: TINNARUBR | D11: Tinna Rubber & Infrastructure Ltd | E11: fmcg | F11: miscellaneous | G11: smallcap | H11: 1996.33 | I11: 1118 | J11: 0.89 | K11: 64083 | L11: 56 | M11: Outperforming | N11: =IF(M11="Underperforming",-5,IF(L11>=95,15,IF(L11>=90,10,IF(L11>=80,5,0)))) | O11: 71.71 | P11: 43.86 | R11: Earnings / Momentum Support | S11: Nifty FMCG | T11: -13.73 | U11: 0.8 | V11: 16.84 | W11: 9.54 | X11: Growing Industry | Y11: =IF(X11="Growing Industry",10,IF(X11="Cyclical in an Upturn",5,0)) | Z11: Too Many Players with High ROCE | AA11: =IF(Z11="Monopoly",10,IF(Z11="Oligopoly",5,IF(Z11="Duopoly that cooperate",10,IF(Z11="Duopoly that compete",5,IF(Z11="Too many players with High ROCE",5,0))))) | AB11: No | AC11: =IF(AB11="No",5,0) | AD11: Headwind | AE11: =IF(AD11="Tailwind",10,0) | AF11: Structural (10 Years Consistency) | AG11: =IF(AF11="Structural (10 Years Consistency)",10,IF(AF11="Shallow Cyclical (2 to 3 years growth)",5,0)) | AH11: No | AI11: =IF(AH11="Yes due to Product Mix change or Operating Leverage",10,IF(AH11="Yes, these are peak margins",-5,IF(AH11="No",5,0))) | AJ11: Stable | AK11: =IF(AJ11="Stable",10,0) | AL11: Yes | AM11: =IF(AL11="Yes",10,0) | AN11: B2C | AO11: =IF(AN11="B2C",10,IF(AN11="B2B",5,0)) | AP11: No | AQ11: =IF(AP11="Yes",10,0) | AR11: Higher Annuity, Lower One Time | AS11: =IF(AR11="Fully Annuity",10,IF(AR11="Higher Annuity, Lower One Time",5,IF(AR11="Higher One Time, Lower Annuity",3,0))) | AT11: Good | AU11: =IF(AT11="Good",10,0) | AV11: Yes for more than 2 years | AW11: =IF(AV11="Yes for more than 2 years",10,IF(AV11="Yes only for next 1 to 2 years",5,0)) | AX11: Above 40 | AY11: =IF(AX11="Above 40",20,IF(AX11="20 to 40",10,IF(AX11="0 to 20",-5,0))) | AZ11: Between 50 to 75 | BA11: =IF(AZ11="Between 50 to 75",10,IF(AZ11="Above 75",0,0)) | BB11: Stage 3 | BC11: =IF(BB11="Stage 2",20,IF(BB11="Stage 1",0,IF(BB11="Stage 3",5,IF(BB11="Stage 4",-5,0)))) | BD11: Negative Trend | BE11: =IF(BD11="Positive Trend",20,IF(BD11="Negative Trend",-10,0)) | BF11: Uptrend | BG11: =IF(BF11="Uptrend",10,IF(BF11="Sideways",5,0)) | BH11: Uptrend | BI11: =IF(BH11="Uptrend",10,IF(BH11="Sideways",5,0)) | BJ11: Close to 52 week high or retracement | BK11: =IF(BJ11="Overhead supply in last 2 years in last 2 years",-5,IF(BJ11="Close to 52 week high or retracement",5,IF(BJ11="Blue sky scenario",10,IF(BJ11="Long term Downtrend",-10,0)))) | BL11: Yes | BM11: =IF(BL11="Yes",10,0) | BN11: More than 20% | BO11: =IF(BN11="More than 20%",10,IF(BN11="Between 12 to 20%",5,IF(BN11="Less than 12%",0,0))) | BP11: No | BQ11: =IF(BP11="No",10,0) | BR11: No | BS11: =IF(BR11="NO",5,0) | BT11: Less than 1.5 | BU11: =IF(BT11="Above 2",0,IF(BT11="Between 1.5 to 2",5,IF(BT11="Less than 1.5",10,0))) | BV11: Above 70% | BW11: =IF(BV11="Above 70%",10,IF(BV11="Between 50% to 70%",5,IF(BV11="Less than 50%",0,IF(BV11="Negative",-10,IF(BV11="Less than 50% and Borrowings are increasing",-5,0))))) | BX11: Less than 0.7 | BY11: =IF(BX11="More than 1.2",-10,IF(BX11="Between 0.7 to 1.2",0,IF(BX11="Less than 0.7",10,0))) | BZ11: No | CA11: =IF(BZ11="Yes",-10,0) | CB11: Less than 15% | CC11: =IF(CB11="More than 15%",-10,IF(CB11="Less than 15%",10,0)) | CD11: No | CE11: =IF(CD11="Yes, more than 10%",-10,IF(CD11="No",10,0))
A12: =IF(B12=0,"",RANK(B12,$B$2:$B$400,0)) | B12: =SUM(N12,Y12,AA12,AC12,AE12,AG12,AI12,AK12,AM12,AO12,AQ12,AS12,AU12,AW12,AY12,BA12,BC12,BE12,BG12,BI12,BK12,BM12,BO12,BQ12,BS12,BU12,BW12,BY12,CA12,CC12,CE12) | C12: PRICOLLTD | D12: Pricol Ltd. | E12: auto | F12: auto ancillaries | G12: midcap | H12: 8993.64 | I12: 732.8 | J12: -0.69 | K12: 579652 | L12: 48 | M12: Outperforming | N12: =IF(M12="Underperforming",-5,IF(L12>=95,15,IF(L12>=90,10,IF(L12>=80,5,0)))) | O12: 71.13 | P12: 25.87 | R12: Earnings / Momentum Support | S12: Nifty Auto | T12: 13.41 | U12: 36.08 | V12: 19.98 | W12: 7.62 | X12: Cyclical in an Upturn | Y12: =IF(X12="Growing Industry",10,IF(X12="Cyclical in an Upturn",5,0)) | Z12: Oligopoly | AA12: =IF(Z12="Monopoly",10,IF(Z12="Oligopoly",5,IF(Z12="Duopoly that cooperate",10,IF(Z12="Duopoly that compete",5,IF(Z12="Too many players with High ROCE",5,0))))) | AB12: No | AC12: =IF(AB12="No",5,0) | AD12: Tailwind | AE12: =IF(AD12="Tailwind",10,0) | AF12: Shallow Cyclical (2 to 3 Years Growth) | AG12: =IF(AF12="Structural (10 Years Consistency)",10,IF(AF12="Shallow Cyclical (2 to 3 years growth)",5,0)) | AH12: No | AI12: =IF(AH12="Yes due to Product Mix change or Operating Leverage",10,IF(AH12="Yes, these are peak margins",-5,IF(AH12="No",5,0))) | AJ12: Stable | AK12: =IF(AJ12="Stable",10,0) | AL12: Yes | AM12: =IF(AL12="Yes",10,0) | AN12: B2B | AO12: =IF(AN12="B2C",10,IF(AN12="B2B",5,0)) | AP12: Yes | AQ12: =IF(AP12="Yes",10,0) | AR12: Fully One Time | AS12: =IF(AR12="Fully Annuity",10,IF(AR12="Higher Annuity, Lower One Time",5,IF(AR12="Higher One Time, Lower Annuity",3,0))) | AT12: Allocated capital in Non-core Areas | AU12: =IF(AT12="Good",10,0) | AV12: Yes only for next 1 to 2 years | AW12: =IF(AV12="Yes for more than 2 years",10,IF(AV12="Yes only for next 1 to 2 years",5,0)) | AX12: 20 to 40 | AY12: =IF(AX12="Above 40",20,IF(AX12="20 to 40",10,IF(AX12="0 to 20",-5,0))) | AZ12: Between 50 to 75 | BA12: =IF(AZ12="Between 50 to 75",10,IF(AZ12="Above 75",0,0)) | BB12: Stage 2 | BC12: =IF(BB12="Stage 2",20,IF(BB12="Stage 1",0,IF(BB12="Stage 3",5,IF(BB12="Stage 4",-5,0)))) | BD12: Positive Trend | BE12: =IF(BD12="Positive Trend",20,IF(BD12="Negative Trend",-10,0)) | BF12: Uptrend | BG12: =IF(BF12="Uptrend",10,IF(BF12="Sideways",5,0)) | BH12: Uptrend | BI12: =IF(BH12="Uptrend",10,IF(BH12="Sideways",5,0)) | BJ12: Blue sky scenario | BK12: =IF(BJ12="Overhead supply in last 2 years in last 2 years",-5,IF(BJ12="Close to 52 week high or retracement",5,IF(BJ12="Blue sky scenario",10,IF(BJ12="Long term Downtrend",-10,0)))) | BL12: Yes | BM12: =IF(BL12="Yes",10,0) | BN12: Between 12 to 20% | BO12: =IF(BN12="More than 20%",10,IF(BN12="Between 12 to 20%",5,IF(BN12="Less than 12%",0,0))) | BP12: Yes | BQ12: =IF(BP12="No",10,0) | BR12: No | BS12: =IF(BR12="NO",5,0) | BT12: Between 1.5 to 2 | BU12: =IF(BT12="Above 2",0,IF(BT12="Between 1.5 to 2",5,IF(BT12="Less than 1.5",10,0))) | BV12: Between 50% to 70% | BW12: =IF(BV12="Above 70%",10,IF(BV12="Between 50% to 70%",5,IF(BV12="Less than 50%",0,IF(BV12="Negative",-10,IF(BV12="Less than 50% and Borrowings are increasing",-5,0))))) | BX12: Less than 0.7 | BY12: =IF(BX12="More than 1.2",-10,IF(BX12="Between 0.7 to 1.2",0,IF(BX12="Less than 0.7",10,0))) | BZ12: No | CA12: =IF(BZ12="Yes",-10,0) | CB12: Less than 15% | CC12: =IF(CB12="More than 15%",-10,IF(CB12="Less than 15%",10,0)) | CD12: No | CE12: =IF(CD12="Yes, more than 10%",-10,IF(CD12="No",10,0))
A13: =IF(B13=0,"",RANK(B13,$B$2:$B$400,0)) | B13: =SUM(N13,Y13,AA13,AC13,AE13,AG13,AI13,AK13,AM13,AO13,AQ13,AS13,AU13,AW13,AY13,BA13,BC13,BE13,BG13,BI13,BK13,BM13,BO13,BQ13,BS13,BU13,BW13,BY13,CA13,CC13,CE13) | C13: IOLCP | D13: Iol Chemicals And Pharmaceuticals Limited | E13: healthcare | F13: pharmaceuticals - indian - bulk drugs & formln | G13: smallcap | H13: 4926.86 | I13: 164.66 | J13: -1.9 | K13: 15141043 | L13: 94 | M13: Outperforming | N13: =IF(M13="Underperforming",-5,IF(L13>=95,15,IF(L13>=90,10,IF(L13>=80,5,0)))) | O13: 73 | P13: 75.97 | R13: Earnings / Momentum Support | S13: Nifty Pharma | T13: 24.01 | U13: 83.54 | V13: 48 | W13: 31.52 | X13: Growing Industry | Y13: =IF(X13="Growing Industry",10,IF(X13="Cyclical in an Upturn",5,0)) | Z13: Too Many Players with High ROCE | AA13: =IF(Z13="Monopoly",10,IF(Z13="Oligopoly",5,IF(Z13="Duopoly that cooperate",10,IF(Z13="Duopoly that compete",5,IF(Z13="Too many players with High ROCE",5,0))))) | AB13: Yes | AC13: =IF(AB13="No",5,0) | AD13: Headwind | AE13: =IF(AD13="Tailwind",10,0) | AF13: Structural (10 Years Consistency) | AG13: =IF(AF13="Structural (10 Years Consistency)",10,IF(AF13="Shallow Cyclical (2 to 3 years growth)",5,0)) | AH13: No | AI13: =IF(AH13="Yes due to Product Mix change or Operating Leverage",10,IF(AH13="Yes, these are peak margins",-5,IF(AH13="No",5,0))) | AJ13: Stable | AK13: =IF(AJ13="Stable",10,0) | AL13: Yes | AM13: =IF(AL13="Yes",10,0) | AN13: B2B | AO13: =IF(AN13="B2C",10,IF(AN13="B2B",5,0)) | AP13: No | AQ13: =IF(AP13="Yes",10,0) | AR13: Higher Annuity, Lower One Time | AS13: =IF(AR13="Fully Annuity",10,IF(AR13="Higher Annuity, Lower One Time",5,IF(AR13="Higher One Time, Lower Annuity",3,0))) | AT13: Good | AU13: =IF(AT13="Good",10,0) | AV13: Yes for more than 2 years | AW13: =IF(AV13="Yes for more than 2 years",10,IF(AV13="Yes only for next 1 to 2 years",5,0)) | AX13: Above 40 | AY13: =IF(AX13="Above 40",20,IF(AX13="20 to 40",10,IF(AX13="0 to 20",-5,0))) | AZ13: Between 50 to 75 | BA13: =IF(AZ13="Between 50 to 75",10,IF(AZ13="Above 75",0,0)) | BB13: Stage 3 | BC13: =IF(BB13="Stage 2",20,IF(BB13="Stage 1",0,IF(BB13="Stage 3",5,IF(BB13="Stage 4",-5,0)))) | BD13: Negative Trend | BE13: =IF(BD13="Positive Trend",20,IF(BD13="Negative Trend",-10,0)) | BF13: Uptrend | BG13: =IF(BF13="Uptrend",10,IF(BF13="Sideways",5,0)) | BH13: Uptrend | BI13: =IF(BH13="Uptrend",10,IF(BH13="Sideways",5,0)) | BJ13: Close to 52 week high or retracement | BK13: =IF(BJ13="Overhead supply in last 2 years in last 2 years",-5,IF(BJ13="Close to 52 week high or retracement",5,IF(BJ13="Blue sky scenario",10,IF(BJ13="Long term Downtrend",-10,0)))) | BL13: Yes | BM13: =IF(BL13="Yes",10,0) | BN13: More than 20% | BO13: =IF(BN13="More than 20%",10,IF(BN13="Between 12 to 20%",5,IF(BN13="Less than 12%",0,0))) | BP13: No | BQ13: =IF(BP13="No",10,0) | BR13: No | BS13: =IF(BR13="NO",5,0) | BT13: Less than 1.5 | BU13: =IF(BT13="Above 2",0,IF(BT13="Between 1.5 to 2",5,IF(BT13="Less than 1.5",10,0))) | BV13: Above 70% | BW13: =IF(BV13="Above 70%",10,IF(BV13="Between 50% to 70%",5,IF(BV13="Less than 50%",0,IF(BV13="Negative",-10,IF(BV13="Less than 50% and Borrowings are increasing",-5,0))))) | BX13: Less than 0.7 | BY13: =IF(BX13="More than 1.2",-10,IF(BX13="Between 0.7 to 1.2",0,IF(BX13="Less than 0.7",10,0))) | BZ13: No | CA13: =IF(BZ13="Yes",-10,0) | CB13: Less than 15% | CC13: =IF(CB13="More than 15%",-10,IF(CB13="Less than 15%",10,0)) | CD13: No | CE13: =IF(CD13="Yes, more than 10%",-10,IF(CD13="No",10,0))
... A400: =IF(B400=0,"",RANK(B400,$B$2:$B$400,0)) | B400: =SUM(N400,Y400,AA400,AC400,AE400,AG400,AI400,AK400,AM400,AO400,AQ400,AS400,AU400,AW400,AY400,BA400,BC400,BE400,BG400,BI400,BK400,BM400,BO400,BQ400,BS400,BU400,BW400,BY400,CA400,CC400,CE400) | C400: JINDALSTEL | D400: Jindal Steel Ltd | E400: metals & mining | F400: steel - large | G400: largecap | H400: 112515.72 | I400: 1125 | J400: 1.99 | K400: 1775160 | L400: 8 | M400: Underperforming | N400: =IF(M400="Underperforming",-5,IF(L400>=95,15,IF(L400>=90,10,IF(L400>=80,5,0)))) | O400: 47.9 | P400: 16.58 | R400: Earnings / Momentum Support | S400: Nifty Metal | T400: 31.49 | U400: 7.3 | V400: -18.4 | W400: -1.56 | X400: Cyclical in an Upturn | Y400: =IF(X400="Growing Industry",10,IF(X400="Cyclical in an Upturn",5,0)) | Z400: Too Many Players with High ROCE | AA400: =IF(Z400="Monopoly",10,IF(Z400="Oligopoly",5,IF(Z400="Duopoly that cooperate",10,IF(Z400="Duopoly that compete",5,IF(Z400="Too many players with High ROCE",5,0))))) | AB400: No | AC400: =IF(AB400="No",5,0) | AD400: Headwind | AE400: =IF(AD400="Tailwind",10,0) | AF400: Cyclical | AG400: =IF(AF400="Structural (10 Years Consistency)",10,IF(AF400="Shallow Cyclical (2 to 3 years growth)",5,0)) | AH400: No | AI400: =IF(AH400="Yes due to Product Mix change or Operating Leverage",10,IF(AH400="Yes, these are peak margins",-5,IF(AH400="No",5,0))) | AJ400: Volatile | AK400: =IF(AJ400="Stable",10,0) | AL400: Yes | AM400: =IF(AL400="Yes",10,0) | AN400: B2B | AO400: =IF(AN400="B2C",10,IF(AN400="B2B",5,0)) | AP400: No | AQ400: =IF(AP400="Yes",10,0) | AR400: Higher One Time, Lower Annuity | AS400: =IF(AR400="Fully Annuity",10,IF(AR400="Higher Annuity, Lower One Time",5,IF(AR400="Higher One Time, Lower Annuity",3,0))) | AT400: Good | AU400: =IF(AT400="Good",10,0) | AV400: Yes for more than 2 years | AW400: =IF(AV400="Yes for more than 2 years",10,IF(AV400="Yes only for next 1 to 2 years",5,0)) | AX400: 0 to 20 | AY400: =IF(AX400="Above 40",20,IF(AX400="20 to 40",10,IF(AX400="0 to 20",-5,0))) | AZ400: Below 45 | BA400: =IF(AZ400="Between 50 to 75",10,IF(AZ400="Above 75",0,0)) | BB400: Stage 4 | BC400: =IF(BB400="Stage 2",20,IF(BB400="Stage 1",0,IF(BB400="Stage 3",5,IF(BB400="Stage 4",-5,0)))) | BD400: Negative Trend | BE400: =IF(BD400="Positive Trend",20,IF(BD400="Negative Trend",-10,0)) | BF400: Uptrend | BG400: =IF(BF400="Uptrend",10,IF(BF400="Sideways",5,0)) | BH400: Uptrend | BI400: =IF(BH400="Uptrend",10,IF(BH400="Sideways",5,0)) | BJ400: Close to 52 week high or retracement | BK400: =IF(BJ400="Overhead supply in last 2 years in last 2 years",-5,IF(BJ400="Close to 52 week high or retracement",5,IF(BJ400="Blue sky scenario",10,IF(BJ400="Long term Downtrend",-10,0)))) | BL400: Yes | BM400: =IF(BL400="Yes",10,0) | BN400: Less than 12% | BO400: =IF(BN400="More than 20%",10,IF(BN400="Between 12 to 20%",5,IF(BN400="Less than 12%",0,0))) | BP400: No | BQ400: =IF(BP400="No",10,0) | BR400: Yes | BS400: =IF(BR400="NO",5,0) | BT400: Above 2 | BU400: =IF(BT400="Above 2",0,IF(BT400="Between 1.5 to 2",5,IF(BT400="Less than 1.5",10,0))) | BV400: Above 70% | BW400: =IF(BV400="Above 70%",10,IF(BV400="Between 50% to 70%",5,IF(BV400="Less than 50%",0,IF(BV400="Negative",-10,IF(BV400="Less than 50% and Borrowings are increasing",-5,0))))) | BX400: Less than 0.7 | BY400: =IF(BX400="More than 1.2",-10,IF(BX400="Between 0.7 to 1.2",0,IF(BX400="Less than 0.7",10,0))) | BZ400: No | CA400: =IF(BZ400="Yes",-10,0) | CB400: Less than 15% | CC400: =IF(CB400="More than 15%",-10,IF(CB400="Less than 15%",10,0)) | CD400: No | CE400: =IF(CD400="Yes, more than 10%",-10,IF(CD400="No",10,0))

Sheet Monit Banks NBFC
A1: Rank (Banks & NBFC) | B1: Total Score | C1: Symbol | D1: Company | E1: Sector | F1: Industry | G1: Market Cap Bucket | H1: Market Cap Cr | I1: Close | J1: Today Return % | K1: Volume | L1: Relative Strength Rating | M1: Relative Strength Status | N1: Relative Strength Score | O1: Calculated RSI (14) | P1: Calculated ADX (14) | Q1: Calculated V-stop Line | R1: Calculated Near-term Trigger | S1: Sector Benchmark | T1: Benchmark 1Y Return % | U1: Stock 1Y Return % | V1: Relative Strength 1Y (%) | W1: O'Neil Weighted Score | X1: Industry Growth | Y1: Industry Growth Score | Z1: Competitiveness | AA1: Competitiveness Score | AB1: Regulation | AC1: Regulation Score | AD1: Sector Headwinds/Tailwind | AE1: Sector Headwinds/Tailwind Score | AF1: Industry Type | AG1: Industry Type Score | AH1: NIM | AI1: NIM Score | AJ1: CASA Ratio | AK1: CASA Ratio Score | AL1: Profit cyclicality | AM1: Profit cyclicality Score | AN1: CAR Ratio | AO1: CAR Ratio Score | AP1: Near term triggers | AQ1: Near term triggers Score | AR1: High P/BV | AS1: High P/BV Score | AT1: Asset Quality Divergence | AU1: Asset Quality Divergence Score | AV1: Reported loss | AW1: Reported loss Score | AX1: CEO Resignation | AY1: CEO Resignation Score | AZ1: GNPA | BA1: GNPA Score | BB1: KMP Resignation | BC1: KMP Resignation Score | BD1: Return on Assets | BE1: Return on Assets Score | BF1: Return on Equity | BG1: Return on Equity Score | BH1: AUM Growth | BI1: AUM Growth Score | BJ1: Price to Book Value | BK1: Price to Book Value Score | BL1: ADX | BM1: ADX Score | BN1: RSI | BO1: RSI Score | BP1: Stage Analysis | BQ1: Stage Analysis Score | BR1: Price Volume Action | BS1: Price Volume Action Score | BT1: Secondary Trend | BU1: Secondary Trend Score | BV1: Primary Trend | BW1: Primary Trend Score | BX1: Resistance | BY1: Resistance Score | BZ1: V-stop | CA1: V-stop Score
A2: =IF(B2=0,"",RANK(B2,$B$2:$B$41,0)) | B2: =SUM(N2,Y2,AA2,AC2,AE2,AG2,AI2,AK2,AM2,AO2,AQ2,AS2,AU2,AW2,AY2,BA2,BC2,BE2,BG2,BI2,BK2,BM2,BO2,BQ2,BS2,BU2,BW2,BY2,CA2) | C2: ARMANFIN | D2: Arman Financial Services Limited | E2: financials | F2: finance & investments | G2: smallcap | H2: 2136.6 | I2: 1990 | J2: -2.07 | K2: 76652 | L2: 58 | M2: Outperforming | N2: =IF(M2="Underperforming",-5,IF(L2>=95,15,IF(L2>=90,10,IF(L2>=80,5,0)))) | O2: 66.54 | P2: 22.88 | R2: Earnings / Momentum Support | S2: Nifty Bank | T2: 4.98 | U2: 37.1 | V2: 30.59 | W2: 9.98 | X2: Cyclical in an Upturn | Y2: =IF(X2="Growing Industry",10,IF(X2="Cyclical in an Upturn",5,0)) | Z2: Fragmented with High ROE | AA2: =IF(Z2="Fragmented with Low ROE",-5,IF(Z2="Fragmented with High ROE",10,IF(Z2= "highly cyclical",5,0))) | AB2: No | AC2: =IF(AB2="No",5,0) | AD2: Tailwind | AE2: =IF(AD2="Tailwind",10,0) | AF2: Cyclical in an Uptick | AG2: =IF(AF2="Structural (10 Years Consistency)",15,IF(AF2="Shallow Cyclical (2 to 3 years growth)",10,IF(AF2 = "Cyclical in an Uptick",5,IF(AF2 = "Cyclical in an Downtick",-10,0)))) | AH2: Yes | AI2: =IF(AH2="Yes",10,0) | AJ2: Not Applicable | AK2: =IF(AJ2="Yes",10,0) | AL2: Yes | AM2: =IF(AL2="No",10,0) | AN2: Yes | AO2: =IF(AN2="Yes",10,0) | AP2: Yes | AQ2: =IF(AP2="Yes",10,0) | AR2: Yes | AS2: =IF(AR2="Yes",5,0) | AT2: Not Applicable | AU2: =IF(AT2="No",10,IF(AT2="Yes",-10,0)) | AV2: No | AW2: =IF(AV2="No",10,0) | AX2: No | AY2: =IF(AX2="No",10,IF(AX2= "Yes CEO Resignation",-5,0)) | AZ2: No | BA2: =IF(AZ2="No",10,IF(AZ2="Yes",-5,0)) | BB2: No | BC2: =IF(BB2="No",5,IF(BB2="Yes",-5,0)) | BD2: Yes | BE2: =IF(BD2="Yes",10,0) | BF2: Yes | BG2: =IF(BF2="Yes",10,0) | BH2: Yes | BI2: =IF(BH2="Yes",10,0) | BJ2: P/BV between 2.5x to 5x and Growth more than 20% | BK2: =IF(BJ2="P/BV less than 2.5x and Growth more than 20%",20,IF(BJ2 = "P/BV less than 2.5x and Growth less than 20%",5,IF(BJ2="P/BV between 2.5x to 5x and Growth more than 20%",10,IF(BJ2= "P/BV between 2.5x to 5x and Growth less than 20%",-5,IF(BJ2= "P/BV above 5x",-5,0))))) | BL2: 20 to 40 | BM2: =IF(BL2="Above 40",20,IF(BL2="20 to 40",10,IF(BL2="0 to 20",-5,0))) | BN2: Between 50 to 75 | BO2: =IF(BN2="Between 50 to 75",10,IF(BN2="Above 75",0,0)) | BP2: Stage 2 | BQ2: =IF(BP2="Stage 2",20,IF(BP2="Stage 1",0,IF(BP2="Stage 3",5,IF(BP2="Stage 4",-5,0)))) | BR2: Positive Trend | BS2: =IF(BR2="Positive Trend",20,IF(BR2="Negative Trend",-10,0)) | BT2: Sideways | BU2: =IF(BT2="Uptrend",10,IF(BT2="Sideways",5,0)) | BV2: Uptrend | BW2: =IF(BV2="Uptrend",10,IF(BV2="Sideways",5,0)) | BX2: Close to 52 week high or retracement | BY2: =IF(BX2="Overhead supply in last 2 years in last 2 years",-5,IF(BX2="Close to 52 week high or retracement",5,IF(BX2="Blue sky scenario",10,IF(BX2="Long term Downtrend",-10,0)))) | BZ2: Yes | CA2: =IF(BZ2="Yes",10,0)
A3: =IF(B3=0,"",RANK(B3,$B$2:$B$41,0)) | B3: =SUM(N3,Y3,AA3,AC3,AE3,AG3,AI3,AK3,AM3,AO3,AQ3,AS3,AU3,AW3,AY3,BA3,BC3,BE3,BG3,BI3,BK3,BM3,BO3,BQ3,BS3,BU3,BW3,BY3,CA3) | C3: KTKBANK | D3: The Karnataka Bank Limited | E3: bank | F3: banks - private sector | G3: midcap | H3: 11724.3 | I3: 305.25 | J3: -1.53 | K3: 1598287 | L3: 78 | M3: Outperforming | N3: =IF(M3="Underperforming",-5,IF(L3>=95,15,IF(L3>=90,10,IF(L3>=80,5,0)))) | O3: 74.62 | P3: 45.49 | R3: Earnings / Momentum Support | S3: Nifty Bank | T3: 4.98 | U3: 85.15 | V3: 76.36 | W3: 17.46 | X3: Growing Industry | Y3: =IF(X3="Growing Industry",10,IF(X3="Cyclical in an Upturn",5,0)) | Z3: Fragmented with High ROE | AA3: =IF(Z3="Fragmented with Low ROE",-5,IF(Z3="Fragmented with High ROE",10,IF(Z3= "highly cyclical",5,0))) | AB3: Yes | AC3: =IF(AB3="No",5,0) | AD3: Headwind | AE3: =IF(AD3="Tailwind",10,0) | AF3: Structural (10 Years Consistency) | AG3: =IF(AF3="Structural (10 Years Consistency)",15,IF(AF3="Shallow Cyclical (2 to 3 years growth)",10,IF(AF3 = "Cyclical in an Uptick",5,IF(AF3 = "Cyclical in an Downtick",-10,0)))) | AH3: Yes | AI3: =IF(AH3="Yes",10,0) | AJ3: Yes | AK3: =IF(AJ3="Yes",10,0) | AM3: =IF(AL3="No",10,0) | AN3: Yes | AO3: =IF(AN3="Yes",10,0) | AP3: No | AQ3: =IF(AP3="Yes",10,0) | AR3: Yes | AS3: =IF(AR3="Yes",5,0) | AT3: No | AU3: =IF(AT3="No",10,IF(AT3="Yes",-10,0)) | AV3: No | AW3: =IF(AV3="No",10,0) | AX3: No | AY3: =IF(AX3="No",10,IF(AX3= "Yes CEO Resignation",-5,0)) | AZ3: No | BA3: =IF(AZ3="No",10,IF(AZ3="Yes",-5,0)) | BB3: No | BC3: =IF(BB3="No",5,IF(BB3="Yes",-5,0)) | BD3: Yes | BE3: =IF(BD3="Yes",10,0) | BF3: Yes | BG3: =IF(BF3="Yes",10,0) | BH3: Yes | BI3: =IF(BH3="Yes",10,0) | BJ3: P/BV less than 2.5x and Growth more than 20% | BK3: =IF(BJ3="P/BV less than 2.5x and Growth more than 20%",20,IF(BJ3 = "P/BV less than 2.5x and Growth less than 20%",5,IF(BJ3="P/BV between 2.5x to 5x and Growth more than 20%",10,IF(BJ3= "P/BV between 2.5x to 5x and Growth less than 20%",-5,IF(BJ3= "P/BV above 5x",-5,0))))) | BL3: Above 40 | BM3: =IF(BL3="Above 40",20,IF(BL3="20 to 40",10,IF(BL3="0 to 20",-5,0))) | BN3: Between 50 to 75 | BO3: =IF(BN3="Between 50 to 75",10,IF(BN3="Above 75",0,0)) | BP3: Stage 3 | BQ3: =IF(BP3="Stage 2",20,IF(BP3="Stage 1",0,IF(BP3="Stage 3",5,IF(BP3="Stage 4",-5,0)))) | BR3: Negative Trend | BS3: =IF(BR3="Positive Trend",20,IF(BR3="Negative Trend",-10,0)) | BT3: Uptrend | BU3: =IF(BT3="Uptrend",10,IF(BT3="Sideways",5,0)) | BV3: Uptrend | BW3: =IF(BV3="Uptrend",10,IF(BV3="Sideways",5,0)) | BX3: Close to 52 week high or retracement | BY3: =IF(BX3="Overhead supply in last 2 years in last 2 years",-5,IF(BX3="Close to 52 week high or retracement",5,IF(BX3="Blue sky scenario",10,IF(BX3="Long term Downtrend",-10,0)))) | BZ3: Yes | CA3: =IF(BZ3="Yes",10,0)
A4: =IF(B4=0,"",RANK(B4,$B$2:$B$41,0)) | B4: =SUM(N4,Y4,AA4,AC4,AE4,AG4,AI4,AK4,AM4,AO4,AQ4,AS4,AU4,AW4,AY4,BA4,BC4,BE4,BG4,BI4,BK4,BM4,BO4,BQ4,BS4,BU4,BW4,BY4,CA4) | C4: TMB | D4: Tamilnad Mercantile Bank Ltd | E4: bank | F4: banks - private sector | G4: midcap | H4: 13870.8 | I4: 890.2 | J4: 1.63 | K4: 181662 | L4: 82 | M4: Outperforming | N4: =IF(M4="Underperforming",-5,IF(L4>=95,15,IF(L4>=90,10,IF(L4>=80,5,0)))) | O4: 73.48 | P4: 37.86 | R4: Earnings / Momentum Support | S4: Nifty Bank | T4: 4.98 | U4: 107.32 | V4: 97.48 | W4: 20.42 | X4: Growing Industry | Y4: =IF(X4="Growing Industry",10,IF(X4="Cyclical in an Upturn",5,0)) | Z4: Fragmented with High ROE | AA4: =IF(Z4="Fragmented with Low ROE",-5,IF(Z4="Fragmented with High ROE",10,IF(Z4= "highly cyclical",5,0))) | AB4: Yes | AC4: =IF(AB4="No",5,0) | AD4: Headwind | AE4: =IF(AD4="Tailwind",10,0) | AF4: Structural (10 Years Consistency) | AG4: =IF(AF4="Structural (10 Years Consistency)",15,IF(AF4="Shallow Cyclical (2 to 3 years growth)",10,IF(AF4 = "Cyclical in an Uptick",5,IF(AF4 = "Cyclical in an Downtick",-10,0)))) | AH4: Yes | AI4: =IF(AH4="Yes",10,0) | AJ4: Yes | AK4: =IF(AJ4="Yes",10,0) | AM4: =IF(AL4="No",10,0) | AN4: Yes | AO4: =IF(AN4="Yes",10,0) | AP4: No | AQ4: =IF(AP4="Yes",10,0) | AR4: Yes | AS4: =IF(AR4="Yes",5,0) | AT4: No | AU4: =IF(AT4="No",10,IF(AT4="Yes",-10,0)) | AV4: No | AW4: =IF(AV4="No",10,0) | AX4: No | AY4: =IF(AX4="No",10,IF(AX4= "Yes CEO Resignation",-5,0)) | AZ4: No | BA4: =IF(AZ4="No",10,IF(AZ4="Yes",-5,0)) | BB4: No | BC4: =IF(BB4="No",5,IF(BB4="Yes",-5,0)) | BD4: Yes | BE4: =IF(BD4="Yes",10,0) | BF4: Yes | BG4: =IF(BF4="Yes",10,0) | BH4: Yes | BI4: =IF(BH4="Yes",10,0) | BJ4: P/BV less than 2.5x and Growth more than 20% | BK4: =IF(BJ4="P/BV less than 2.5x and Growth more than 20%",20,IF(BJ4 = "P/BV less than 2.5x and Growth less than 20%",5,IF(BJ4="P/BV between 2.5x to 5x and Growth more than 20%",10,IF(BJ4= "P/BV between 2.5x to 5x and Growth less than 20%",-5,IF(BJ4= "P/BV above 5x",-5,0))))) | BL4: 20 to 40 | BM4: =IF(BL4="Above 40",20,IF(BL4="20 to 40",10,IF(BL4="0 to 20",-5,0))) | BN4: Between 50 to 75 | BO4: =IF(BN4="Between 50 to 75",10,IF(BN4="Above 75",0,0)) | BP4: Stage 3 | BQ4: =IF(BP4="Stage 2",20,IF(BP4="Stage 1",0,IF(BP4="Stage 3",5,IF(BP4="Stage 4",-5,0)))) | BR4: Negative Trend | BS4: =IF(BR4="Positive Trend",20,IF(BR4="Negative Trend",-10,0)) | BT4: Uptrend | BU4: =IF(BT4="Uptrend",10,IF(BT4="Sideways",5,0)) | BV4: Uptrend | BW4: =IF(BV4="Uptrend",10,IF(BV4="Sideways",5,0)) | BX4: Close to 52 week high or retracement | BY4: =IF(BX4="Overhead supply in last 2 years in last 2 years",-5,IF(BX4="Close to 52 week high or retracement",5,IF(BX4="Blue sky scenario",10,IF(BX4="Long term Downtrend",-10,0)))) | BZ4: Yes | CA4: =IF(BZ4="Yes",10,0)
A5: =IF(B5=0,"",RANK(B5,$B$2:$B$41,0)) | B5: =SUM(N5,Y5,AA5,AC5,AE5,AG5,AI5,AK5,AM5,AO5,AQ5,AS5,AU5,AW5,AY5,BA5,BC5,BE5,BG5,BI5,BK5,BM5,BO5,BQ5,BS5,BU5,BW5,BY5,CA5) | C5: BFINVEST | D5: Bf Investment Limited | E5: financials | F5: finance & investments | G5: smallcap | H5: 1768.68 | I5: 475.65 | J5: 1.3 | K5: 52032 | L5: 28 | M5: Outperforming | N5: =IF(M5="Underperforming",-5,IF(L5>=95,15,IF(L5>=90,10,IF(L5>=80,5,0)))) | O5: 59.56 | P5: 31.7 | R5: Earnings / Momentum Support | S5: Nifty Bank | T5: 4.98 | U5: 6.05 | V5: 1.01 | W5: 3.16 | X5: Growing Industry | Y5: =IF(X5="Growing Industry",10,IF(X5="Cyclical in an Upturn",5,0)) | Z5: Fragmented with High ROE | AA5: =IF(Z5="Fragmented with Low ROE",-5,IF(Z5="Fragmented with High ROE",10,IF(Z5= "highly cyclical",5,0))) | AB5: Yes | AC5: =IF(AB5="No",5,0) | AD5: Headwind | AE5: =IF(AD5="Tailwind",10,0) | AF5: Structural (10 Years Consistency) | AG5: =IF(AF5="Structural (10 Years Consistency)",15,IF(AF5="Shallow Cyclical (2 to 3 years growth)",10,IF(AF5 = "Cyclical in an Uptick",5,IF(AF5 = "Cyclical in an Downtick",-10,0)))) | AH5: Yes | AI5: =IF(AH5="Yes",10,0) | AJ5: Yes | AK5: =IF(AJ5="Yes",10,0) | AM5: =IF(AL5="No",10,0) | AN5: Yes | AO5: =IF(AN5="Yes",10,0) | AP5: No | AQ5: =IF(AP5="Yes",10,0) | AR5: Yes | AS5: =IF(AR5="Yes",5,0) | AT5: No | AU5: =IF(AT5="No",10,IF(AT5="Yes",-10,0)) | AV5: No | AW5: =IF(AV5="No",10,0) | AX5: No | AY5: =IF(AX5="No",10,IF(AX5= "Yes CEO Resignation",-5,0)) | AZ5: No | BA5: =IF(AZ5="No",10,IF(AZ5="Yes",-5,0)) | BB5: No | BC5: =IF(BB5="No",5,IF(BB5="Yes",-5,0)) | BD5: Yes | BE5: =IF(BD5="Yes",10,0) | BF5: Yes | BG5: =IF(BF5="Yes",10,0) | BH5: Yes | BI5: =IF(BH5="Yes",10,0) | BJ5: P/BV less than 2.5x and Growth more than 20% | BK5: =IF(BJ5="P/BV less than 2.5x and Growth more than 20%",20,IF(BJ5 = "P/BV less than 2.5x and Growth less than 20%",5,IF(BJ5="P/BV between 2.5x to 5x and Growth more than 20%",10,IF(BJ5= "P/BV between 2.5x to 5x and Growth less than 20%",-5,IF(BJ5= "P/BV above 5x",-5,0))))) | BL5: 20 to 40 | BM5: =IF(BL5="Above 40",20,IF(BL5="20 to 40",10,IF(BL5="0 to 20",-5,0))) | BN5: Between 50 to 75 | BO5: =IF(BN5="Between 50 to 75",10,IF(BN5="Above 75",0,0)) | BP5: Stage 3 | BQ5: =IF(BP5="Stage 2",20,IF(BP5="Stage 1",0,IF(BP5="Stage 3",5,IF(BP5="Stage 4",-5,0)))) | BR5: Negative Trend | BS5: =IF(BR5="Positive Trend",20,IF(BR5="Negative Trend",-10,0)) | BT5: Uptrend | BU5: =IF(BT5="Uptrend",10,IF(BT5="Sideways",5,0)) | BV5: Uptrend | BW5: =IF(BV5="Uptrend",10,IF(BV5="Sideways",5,0)) | BX5: Close to 52 week high or retracement | BY5: =IF(BX5="Overhead supply in last 2 years in last 2 years",-5,IF(BX5="Close to 52 week high or retracement",5,IF(BX5="Blue sky scenario",10,IF(BX5="Long term Downtrend",-10,0)))) | BZ5: Yes | CA5: =IF(BZ5="Yes",10,0)
A6: =IF(B6=0,"",RANK(B6,$B$2:$B$41,0)) | B6: =SUM(N6,Y6,AA6,AC6,AE6,AG6,AI6,AK6,AM6,AO6,AQ6,AS6,AU6,AW6,AY6,BA6,BC6,BE6,BG6,BI6,BK6,BM6,BO6,BQ6,BS6,BU6,BW6,BY6,CA6) | C6: M&MFIN | D6: Mahindra & Mahindra Financial Services Limited | E6: financials | F6: finance & investments | G6: largecap | H6: 56773.37 | I6: 412.3 | J6: 0.94 | K6: 3517041 | L6: 75 | M6: Outperforming | N6: =IF(M6="Underperforming",-5,IF(L6>=95,15,IF(L6>=90,10,IF(L6>=80,5,0)))) | O6: 69.89 | P6: 22.3 | R6: Earnings / Momentum Support | S6: Nifty Bank | T6: 4.98 | U6: 65.4 | V6: 57.55 | W6: 16.19 | X6: Growing Industry | Y6: =IF(X6="Growing Industry",10,IF(X6="Cyclical in an Upturn",5,0)) | Z6: Fragmented with High ROE | AA6: =IF(Z6="Fragmented with Low ROE",-5,IF(Z6="Fragmented with High ROE",10,IF(Z6= "highly cyclical",5,0))) | AB6: Yes | AC6: =IF(AB6="No",5,0) | AD6: Headwind | AE6: =IF(AD6="Tailwind",10,0) | AF6: Structural (10 Years Consistency) | AG6: =IF(AF6="Structural (10 Years Consistency)",15,IF(AF6="Shallow Cyclical (2 to 3 years growth)",10,IF(AF6 = "Cyclical in an Uptick",5,IF(AF6 = "Cyclical in an Downtick",-10,0)))) | AH6: Yes | AI6: =IF(AH6="Yes",10,0) | AJ6: Yes | AK6: =IF(AJ6="Yes",10,0) | AM6: =IF(AL6="No",10,0) | AN6: Yes | AO6: =IF(AN6="Yes",10,0) | AP6: No | AQ6: =IF(AP6="Yes",10,0) | AR6: Yes | AS6: =IF(AR6="Yes",5,0) | AT6: No | AU6: =IF(AT6="No",10,IF(AT6="Yes",-10,0)) | AV6: No | AW6: =IF(AV6="No",10,0) | AX6: No | AY6: =IF(AX6="No",10,IF(AX6= "Yes CEO Resignation",-5,0)) | AZ6: No | BA6: =IF(AZ6="No",10,IF(AZ6="Yes",-5,0)) | BB6: No | BC6: =IF(BB6="No",5,IF(BB6="Yes",-5,0)) | BD6: Yes | BE6: =IF(BD6="Yes",10,0) | BF6: Yes | BG6: =IF(BF6="Yes",10,0) | BH6: Yes | BI6: =IF(BH6="Yes",10,0) | BJ6: P/BV less than 2.5x and Growth more than 20% | BK6: =IF(BJ6="P/BV less than 2.5x and Growth more than 20%",20,IF(BJ6 = "P/BV less than 2.5x and Growth less than 20%",5,IF(BJ6="P/BV between 2.5x to 5x and Growth more than 20%",10,IF(BJ6= "P/BV between 2.5x to 5x and Growth less than 20%",-5,IF(BJ6= "P/BV above 5x",-5,0))))) | BL6: 20 to 40 | BM6: =IF(BL6="Above 40",20,IF(BL6="20 to 40",10,IF(BL6="0 to 20",-5,0))) | BN6: Between 50 to 75 | BO6: =IF(BN6="Between 50 to 75",10,IF(BN6="Above 75",0,0)) | BP6: Stage 3 | BQ6: =IF(BP6="Stage 2",20,IF(BP6="Stage 1",0,IF(BP6="Stage 3",5,IF(BP6="Stage 4",-5,0)))) | BR6: Negative Trend | BS6: =IF(BR6="Positive Trend",20,IF(BR6="Negative Trend",-10,0)) | BT6: Uptrend | BU6: =IF(BT6="Uptrend",10,IF(BT6="Sideways",5,0)) | BV6: Uptrend | BW6: =IF(BV6="Uptrend",10,IF(BV6="Sideways",5,0)) | BX6: Close to 52 week high or retracement | BY6: =IF(BX6="Overhead supply in last 2 years in last 2 years",-5,IF(BX6="Close to 52 week high or retracement",5,IF(BX6="Blue sky scenario",10,IF(BX6="Long term Downtrend",-10,0)))) | BZ6: Yes | CA6: =IF(BZ6="Yes",10,0)
A7: =IF(B7=0,"",RANK(B7,$B$2:$B$41,0)) | B7: =SUM(N7,Y7,AA7,AC7,AE7,AG7,AI7,AK7,AM7,AO7,AQ7,AS7,AU7,AW7,AY7,BA7,BC7,BE7,BG7,BI7,BK7,BM7,BO7,BQ7,BS7,BU7,BW7,BY7,CA7) | C7: MANAPPURAM | D7: Manappuram Finance Limited | E7: financials | F7: finance & investments | G7: largecap | H7: 34450.15 | I7: 369.3 | J7: 0.7 | K7: 5708346 | L7: 60 | M7: Outperforming | N7: =IF(M7="Underperforming",-5,IF(L7>=95,15,IF(L7>=90,10,IF(L7>=80,5,0)))) | O7: 67.15 | P7: 20.24 | R7: Earnings / Momentum Support | S7: Nifty Bank | T7: 4.98 | U7: 42.88 | V7: 36.1 | W7: 10.79 | X7: Growing Industry | Y7: =IF(X7="Growing Industry",10,IF(X7="Cyclical in an Upturn",5,0)) | Z7: Fragmented with High ROE | AA7: =IF(Z7="Fragmented with Low ROE",-5,IF(Z7="Fragmented with High ROE",10,IF(Z7= "highly cyclical",5,0))) | AB7: Yes | AC7: =IF(AB7="No",5,0) | AD7: Headwind | AE7: =IF(AD7="Tailwind",10,0) | AF7: Structural (10 Years Consistency) | AG7: =IF(AF7="Structural (10 Years Consistency)",15,IF(AF7="Shallow Cyclical (2 to 3 years growth)",10,IF(AF7 = "Cyclical in an Uptick",5,IF(AF7 = "Cyclical in an Downtick",-10,0)))) | AH7: Yes | AI7: =IF(AH7="Yes",10,0) | AJ7: Yes | AK7: =IF(AJ7="Yes",10,0) | AM7: =IF(AL7="No",10,0) | AN7: Yes | AO7: =IF(AN7="Yes",10,0) | AP7: No | AQ7: =IF(AP7="Yes",10,0) | AR7: Yes | AS7: =IF(AR7="Yes",5,0) | AT7: No | AU7: =IF(AT7="No",10,IF(AT7="Yes",-10,0)) | AV7: No | AW7: =IF(AV7="No",10,0) | AX7: No | AY7: =IF(AX7="No",10,IF(AX7= "Yes CEO Resignation",-5,0)) | AZ7: No | BA7: =IF(AZ7="No",10,IF(AZ7="Yes",-5,0)) | BB7: No | BC7: =IF(BB7="No",5,IF(BB7="Yes",-5,0)) | BD7: Yes | BE7: =IF(BD7="Yes",10,0) | BF7: Yes | BG7: =IF(BF7="Yes",10,0) | BH7: Yes | BI7: =IF(BH7="Yes",10,0) | BJ7: P/BV less than 2.5x and Growth more than 20% | BK7: =IF(BJ7="P/BV less than 2.5x and Growth more than 20%",20,IF(BJ7 = "P/BV less than 2.5x and Growth less than 20%",5,IF(BJ7="P/BV between 2.5x to 5x and Growth more than 20%",10,IF(BJ7= "P/BV between 2.5x to 5x and Growth less than 20%",-5,IF(BJ7= "P/BV above 5x",-5,0))))) | BL7: 20 to 40 | BM7: =IF(BL7="Above 40",20,IF(BL7="20 to 40",10,IF(BL7="0 to 20",-5,0))) | BN7: Between 50 to 75 | BO7: =IF(BN7="Between 50 to 75",10,IF(BN7="Above 75",0,0)) | BP7: Stage 3 | BQ7: =IF(BP7="Stage 2",20,IF(BP7="Stage 1",0,IF(BP7="Stage 3",5,IF(BP7="Stage 4",-5,0)))) | BR7: Negative Trend | BS7: =IF(BR7="Positive Trend",20,IF(BR7="Negative Trend",-10,0)) | BT7: Uptrend | BU7: =IF(BT7="Uptrend",10,IF(BT7="Sideways",5,0)) | BV7: Uptrend | BW7: =IF(BV7="Uptrend",10,IF(BV7="Sideways",5,0)) | BX7: Close to 52 week high or retracement | BY7: =IF(BX7="Overhead supply in last 2 years in last 2 years",-5,IF(BX7="Close to 52 week high or retracement",5,IF(BX7="Blue sky scenario",10,IF(BX7="Long term Downtrend",-10,0)))) | BZ7: Yes | CA7: =IF(BZ7="Yes",10,0)
A8: =IF(B8=0,"",RANK(B8,$B$2:$B$41,0)) | B8: =SUM(N8,Y8,AA8,AC8,AE8,AG8,AI8,AK8,AM8,AO8,AQ8,AS8,AU8,AW8,AY8,BA8,BC8,BE8,BG8,BI8,BK8,BM8,BO8,BQ8,BS8,BU8,BW8,BY8,CA8) | C8: INDUSINDBK | D8: Indusind Bank Limited | E8: bank | F8: banks - private sector | G8: largecap | H8: 79627.37 | I8: 1027.3 | J8: 0.52 | K8: 2062731 | L8: 47 | M8: Outperforming | N8: =IF(M8="Underperforming",-5,IF(L8>=95,15,IF(L8>=90,10,IF(L8>=80,5,0)))) | O8: 63.46 | P8: 27.71 | R8: Earnings / Momentum Support | S8: Nifty Bank | T8: 4.98 | U8: 30.83 | V8: 24.62 | W8: 7.16 | X8: Growing Industry | Y8: =IF(X8="Growing Industry",10,IF(X8="Cyclical in an Upturn",5,0)) | Z8: Fragmented with High ROE | AA8: =IF(Z8="Fragmented with Low ROE",-5,IF(Z8="Fragmented with High ROE",10,IF(Z8= "highly cyclical",5,0))) | AB8: Yes | AC8: =IF(AB8="No",5,0) | AD8: Headwind | AE8: =IF(AD8="Tailwind",10,0) | AF8: Structural (10 Years Consistency) | AG8: =IF(AF8="Structural (10 Years Consistency)",15,IF(AF8="Shallow Cyclical (2 to 3 years growth)",10,IF(AF8 = "Cyclical in an Uptick",5,IF(AF8 = "Cyclical in an Downtick",-10,0)))) | AH8: Yes | AI8: =IF(AH8="Yes",10,0) | AJ8: Yes | AK8: =IF(AJ8="Yes",10,0) | AM8: =IF(AL8="No",10,0) | AN8: Yes | AO8: =IF(AN8="Yes",10,0) | AP8: No | AQ8: =IF(AP8="Yes",10,0) | AR8: Yes | AS8: =IF(AR8="Yes",5,0) | AT8: No | AU8: =IF(AT8="No",10,IF(AT8="Yes",-10,0)) | AV8: No | AW8: =IF(AV8="No",10,0) | AX8: No | AY8: =IF(AX8="No",10,IF(AX8= "Yes CEO Resignation",-5,0)) | AZ8: No | BA8: =IF(AZ8="No",10,IF(AZ8="Yes",-5,0)) | BB8: No | BC8: =IF(BB8="No",5,IF(BB8="Yes",-5,0)) | BD8: Yes | BE8: =IF(BD8="Yes",10,0) | BF8: Yes | BG8: =IF(BF8="Yes",10,0) | BH8: Yes | BI8: =IF(BH8="Yes",10,0) | BJ8: P/BV less than 2.5x and Growth more than 20% | BK8: =IF(BJ8="P/BV less than 2.5x and Growth more than 20%",20,IF(BJ8 = "P/BV less than 2.5x and Growth less than 20%",5,IF(BJ8="P/BV between 2.5x to 5x and Growth more than 20%",10,IF(BJ8= "P/BV between 2.5x to 5x and Growth less than 20%",-5,IF(BJ8= "P/BV above 5x",-5,0))))) | BL8: 20 to 40 | BM8: =IF(BL8="Above 40",20,IF(BL8="20 to 40",10,IF(BL8="0 to 20",-5,0))) | BN8: Between 50 to 75 | BO8: =IF(BN8="Between 50 to 75",10,IF(BN8="Above 75",0,0)) | BP8: Stage 3 | BQ8: =IF(BP8="Stage 2",20,IF(BP8="Stage 1",0,IF(BP8="Stage 3",5,IF(BP8="Stage 4",-5,0)))) | BR8: Negative Trend | BS8: =IF(BR8="Positive Trend",20,IF(BR8="Negative Trend",-10,0)) | BT8: Uptrend | BU8: =IF(BT8="Uptrend",10,IF(BT8="Sideways",5,0)) | BV8: Uptrend | BW8: =IF(BV8="Uptrend",10,IF(BV8="Sideways",5,0)) | BX8: Close to 52 week high or retracement | BY8: =IF(BX8="Overhead supply in last 2 years in last 2 years",-5,IF(BX8="Close to 52 week high or retracement",5,IF(BX8="Blue sky scenario",10,IF(BX8="Long term Downtrend",-10,0)))) | BZ8: Yes | CA8: =IF(BZ8="Yes",10,0)
A9: =IF(B9=0,"",RANK(B9,$B$2:$B$41,0)) | B9: =SUM(N9,Y9,AA9,AC9,AE9,AG9,AI9,AK9,AM9,AO9,AQ9,AS9,AU9,AW9,AY9,BA9,BC9,BE9,BG9,BI9,BK9,BM9,BO9,BQ9,BS9,BU9,BW9,BY9,CA9) | C9: RBLBANK | D9: Rbl Bank Limited | E9: bank | F9: banks - private sector | G9: largecap | H9: 60362.79 | I9: 391 | J9: 0.31 | K9: 3804712 | L9: 63 | M9: Outperforming | N9: =IF(M9="Underperforming",-5,IF(L9>=95,15,IF(L9>=90,10,IF(L9>=80,5,0)))) | O9: 65.29 | P9: 36.9 | R9: Earnings / Momentum Support | S9: Nifty Bank | T9: 4.98 | U9: 49.49 | V9: 42.39 | W9: 11.72 | X9: Growing Industry | Y9: =IF(X9="Growing Industry",10,IF(X9="Cyclical in an Upturn",5,0)) | Z9: Fragmented with High ROE | AA9: =IF(Z9="Fragmented with Low ROE",-5,IF(Z9="Fragmented with High ROE",10,IF(Z9= "highly cyclical",5,0))) | AB9: Yes | AC9: =IF(AB9="No",5,0) | AD9: Headwind | AE9: =IF(AD9="Tailwind",10,0) | AF9: Structural (10 Years Consistency) | AG9: =IF(AF9="Structural (10 Years Consistency)",15,IF(AF9="Shallow Cyclical (2 to 3 years growth)",10,IF(AF9 = "Cyclical in an Uptick",5,IF(AF9 = "Cyclical in an Downtick",-10,0)))) | AH9: Yes | AI9: =IF(AH9="Yes",10,0) | AJ9: Yes | AK9: =IF(AJ9="Yes",10,0) | AM9: =IF(AL9="No",10,0) | AN9: Yes | AO9: =IF(AN9="Yes",10,0) | AP9: No | AQ9: =IF(AP9="Yes",10,0) | AR9: Yes | AS9: =IF(AR9="Yes",5,0) | AT9: No | AU9: =IF(AT9="No",10,IF(AT9="Yes",-10,0)) | AV9: No | AW9: =IF(AV9="No",10,0) | AX9: No | AY9: =IF(AX9="No",10,IF(AX9= "Yes CEO Resignation",-5,0)) | AZ9: No | BA9: =IF(AZ9="No",10,IF(AZ9="Yes",-5,0)) | BB9: No | BC9: =IF(BB9="No",5,IF(BB9="Yes",-5,0)) | BD9: Yes | BE9: =IF(BD9="Yes",10,0) | BF9: Yes | BG9: =IF(BF9="Yes",10,0) | BH9: Yes | BI9: =IF(BH9="Yes",10,0) | BJ9: P/BV less than 2.5x and Growth more than 20% | BK9: =IF(BJ9="P/BV less than 2.5x and Growth more than 20%",20,IF(BJ9 = "P/BV less than 2.5x and Growth less than 20%",5,IF(BJ9="P/BV between 2.5x to 5x and Growth more than 20%",10,IF(BJ9= "P/BV between 2.5x to 5x and Growth less than 20%",-5,IF(BJ9= "P/BV above 5x",-5,0))))) | BL9: 20 to 40 | BM9: =IF(BL9="Above 40",20,IF(BL9="20 to 40",10,IF(BL9="0 to 20",-5,0))) | BN9: Between 50 to 75 | BO9: =IF(BN9="Between 50 to 75",10,IF(BN9="Above 75",0,0)) | BP9: Stage 3 | BQ9: =IF(BP9="Stage 2",20,IF(BP9="Stage 1",0,IF(BP9="Stage 3",5,IF(BP9="Stage 4",-5,0)))) | BR9: Negative Trend | BS9: =IF(BR9="Positive Trend",20,IF(BR9="Negative Trend",-10,0)) | BT9: Uptrend | BU9: =IF(BT9="Uptrend",10,IF(BT9="Sideways",5,0)) | BV9: Uptrend | BW9: =IF(BV9="Uptrend",10,IF(BV9="Sideways",5,0)) | BX9: Close to 52 week high or retracement | BY9: =IF(BX9="Overhead supply in last 2 years in last 2 years",-5,IF(BX9="Close to 52 week high or retracement",5,IF(BX9="Blue sky scenario",10,IF(BX9="Long term Downtrend",-10,0)))) | BZ9: Yes | CA9: =IF(BZ9="Yes",10,0)
A10: =IF(B10=0,"",RANK(B10,$B$2:$B$41,0)) | B10: =SUM(N10,Y10,AA10,AC10,AE10,AG10,AI10,AK10,AM10,AO10,AQ10,AS10,AU10,AW10,AY10,BA10,BC10,BE10,BG10,BI10,BK10,BM10,BO10,BQ10,BS10,BU10,BW10,BY10,CA10) | C10: UJJIVANSFB | D10: Ujjivan Small Finance Bank Ltd | E10: bank | F10: banks - private sector | G10: midcap | H10: 13638.19 | I10: 69.76 | J10: -0.5 | K10: 6802846 | L10: 65 | M10: Outperforming | N10: =IF(M10="Underperforming",-5,IF(L10>=95,15,IF(L10>=90,10,IF(L10>=80,5,0)))) | O10: 65.93 | P10: 35.92 | R10: Earnings / Momentum Support | S10: Nifty Bank | T10: 4.98 | U10: 58.98 | V10: 51.43 | W10: 12.55 | X10: Growing Industry | Y10: =IF(X10="Growing Industry",10,IF(X10="Cyclical in an Upturn",5,0)) | Z10: Fragmented with High ROE | AA10: =IF(Z10="Fragmented with Low ROE",-5,IF(Z10="Fragmented with High ROE",10,IF(Z10= "highly cyclical",5,0))) | AB10: Yes | AC10: =IF(AB10="No",5,0) | AD10: Headwind | AE10: =IF(AD10="Tailwind",10,0) | AF10: Structural (10 Years Consistency) | AG10: =IF(AF10="Structural (10 Years Consistency)",15,IF(AF10="Shallow Cyclical (2 to 3 years growth)",10,IF(AF10 = "Cyclical in an Uptick",5,IF(AF10 = "Cyclical in an Downtick",-10,0)))) | AH10: Yes | AI10: =IF(AH10="Yes",10,0) | AJ10: Yes | AK10: =IF(AJ10="Yes",10,0) | AM10: =IF(AL10="No",10,0) | AN10: Yes | AO10: =IF(AN10="Yes",10,0) | AP10: No | AQ10: =IF(AP10="Yes",10,0) | AR10: Yes | AS10: =IF(AR10="Yes",5,0) | AT10: No | AU10: =IF(AT10="No",10,IF(AT10="Yes",-10,0)) | AV10: No | AW10: =IF(AV10="No",10,0) | AX10: No | AY10: =IF(AX10="No",10,IF(AX10= "Yes CEO Resignation",-5,0)) | AZ10: No | BA10: =IF(AZ10="No",10,IF(AZ10="Yes",-5,0)) | BB10: No | BC10: =IF(BB10="No",5,IF(BB10="Yes",-5,0)) | BD10: Yes | BE10: =IF(BD10="Yes",10,0) | BF10: Yes | BG10: =IF(BF10="Yes",10,0) | BH10: Yes | BI10: =IF(BH10="Yes",10,0) | BJ10: P/BV less than 2.5x and Growth more than 20% | BK10: =IF(BJ10="P/BV less than 2.5x and Growth more than 20%",20,IF(BJ10 = "P/BV less than 2.5x and Growth less than 20%",5,IF(BJ10="P/BV between 2.5x to 5x and Growth more than 20%",10,IF(BJ10= "P/BV between 2.5x to 5x and Growth less than 20%",-5,IF(BJ10= "P/BV above 5x",-5,0))))) | BL10: 20 to 40 | BM10: =IF(BL10="Above 40",20,IF(BL10="20 to 40",10,IF(BL10="0 to 20",-5,0))) | BN10: Between 50 to 75 | BO10: =IF(BN10="Between 50 to 75",10,IF(BN10="Above 75",0,0)) | BP10: Stage 3 | BQ10: =IF(BP10="Stage 2",20,IF(BP10="Stage 1",0,IF(BP10="Stage 3",5,IF(BP10="Stage 4",-5,0)))) | BR10: Negative Trend | BS10: =IF(BR10="Positive Trend",20,IF(BR10="Negative Trend",-10,0)) | BT10: Uptrend | BU10: =IF(BT10="Uptrend",10,IF(BT10="Sideways",5,0)) | BV10: Uptrend | BW10: =IF(BV10="Uptrend",10,IF(BV10="Sideways",5,0)) | BX10: Close to 52 week high or retracement | BY10: =IF(BX10="Overhead supply in last 2 years in last 2 years",-5,IF(BX10="Close to 52 week high or retracement",5,IF(BX10="Blue sky scenario",10,IF(BX10="Long term Downtrend",-10,0)))) | BZ10: Yes | CA10: =IF(BZ10="Yes",10,0)
A11: =IF(B11=0,"",RANK(B11,$B$2:$B$41,0)) | B11: =SUM(N11,Y11,AA11,AC11,AE11,AG11,AI11,AK11,AM11,AO11,AQ11,AS11,AU11,AW11,AY11,BA11,BC11,BE11,BG11,BI11,BK11,BM11,BO11,BQ11,BS11,BU11,BW11,BY11,CA11) | C11: ESAFSFB | D11: ESAF Small Finance Bank Ltd | E11: bank | F11: banks - private sector | G11: smallcap | H11: 2077.74 | I11: 39.85 | J11: -1.04 | K11: 2058165 | L11: 71 | M11: Outperforming | N11: =IF(M11="Underperforming",-5,IF(L11>=95,15,IF(L11>=90,10,IF(L11>=80,5,0)))) | O11: 68.1 | P11: 33.46 | R11: Earnings / Momentum Support | S11: Nifty Bank | T11: 4.98 | U11: 32.55 | V11: 26.26 | W11: 14.14 | X11: Growing Industry | Y11: =IF(X11="Growing Industry",10,IF(X11="Cyclical in an Upturn",5,0)) | Z11: Fragmented with High ROE | AA11: =IF(Z11="Fragmented with Low ROE",-5,IF(Z11="Fragmented with High ROE",10,IF(Z11= "highly cyclical",5,0))) | AB11: Yes | AC11: =IF(AB11="No",5,0) | AD11: Headwind | AE11: =IF(AD11="Tailwind",10,0) | AF11: Structural (10 Years Consistency) | AG11: =IF(AF11="Structural (10 Years Consistency)",15,IF(AF11="Shallow Cyclical (2 to 3 years growth)",10,IF(AF11 = "Cyclical in an Uptick",5,IF(AF11 = "Cyclical in an Downtick",-10,0)))) | AH11: Yes | AI11: =IF(AH11="Yes",10,0) | AJ11: Yes | AK11: =IF(AJ11="Yes",10,0) | AM11: =IF(AL11="No",10,0) | AN11: Yes | AO11: =IF(AN11="Yes",10,0) | AP11: No | AQ11: =IF(AP11="Yes",10,0) | AR11: Yes | AS11: =IF(AR11="Yes",5,0) | AT11: No | AU11: =IF(AT11="No",10,IF(AT11="Yes",-10,0)) | AV11: No | AW11: =IF(AV11="No",10,0) | AX11: No | AY11: =IF(AX11="No",10,IF(AX11= "Yes CEO Resignation",-5,0)) | AZ11: No | BA11: =IF(AZ11="No",10,IF(AZ11="Yes",-5,0)) | BB11: No | BC11: =IF(BB11="No",5,IF(BB11="Yes",-5,0)) | BD11: Yes | BE11: =IF(BD11="Yes",10,0) | BF11: Yes | BG11: =IF(BF11="Yes",10,0) | BH11: Yes | BI11: =IF(BH11="Yes",10,0) | BJ11: P/BV less than 2.5x and Growth more than 20% | BK11: =IF(BJ11="P/BV less than 2.5x and Growth more than 20%",20,IF(BJ11 = "P/BV less than 2.5x and Growth less than 20%",5,IF(BJ11="P/BV between 2.5x to 5x and Growth more than 20%",10,IF(BJ11= "P/BV between 2.5x to 5x and Growth less than 20%",-5,IF(BJ11= "P/BV above 5x",-5,0))))) | BL11: 20 to 40 | BM11: =IF(BL11="Above 40",20,IF(BL11="20 to 40",10,IF(BL11="0 to 20",-5,0))) | BN11: Between 50 to 75 | BO11: =IF(BN11="Between 50 to 75",10,IF(BN11="Above 75",0,0)) | BP11: Stage 3 | BQ11: =IF(BP11="Stage 2",20,IF(BP11="Stage 1",0,IF(BP11="Stage 3",5,IF(BP11="Stage 4",-5,0)))) | BR11: Negative Trend | BS11: =IF(BR11="Positive Trend",20,IF(BR11="Negative Trend",-10,0)) | BT11: Uptrend | BU11: =IF(BT11="Uptrend",10,IF(BT11="Sideways",5,0)) | BV11: Uptrend | BW11: =IF(BV11="Uptrend",10,IF(BV11="Sideways",5,0)) | BX11: Close to 52 week high or retracement | BY11: =IF(BX11="Overhead supply in last 2 years in last 2 years",-5,IF(BX11="Close to 52 week high or retracement",5,IF(BX11="Blue sky scenario",10,IF(BX11="Long term Downtrend",-10,0)))) | BZ11: Yes | CA11: =IF(BZ11="Yes",10,0)
A12: =IF(B12=0,"",RANK(B12,$B$2:$B$41,0)) | B12: =SUM(N12,Y12,AA12,AC12,AE12,AG12,AI12,AK12,AM12,AO12,AQ12,AS12,AU12,AW12,AY12,BA12,BC12,BE12,BG12,BI12,BK12,BM12,BO12,BQ12,BS12,BU12,BW12,BY12,CA12) | C12: GEECEE | D12: Geecee Ventures Limited | E12: financials | F12: finance & investments | G12: smallcap | H12: 760.04 | I12: 370 | J12: 1.8 | K12: 7109 | L12: 35 | M12: Underperforming | N12: =IF(M12="Underperforming",-5,IF(L12>=95,15,IF(L12>=90,10,IF(L12>=80,5,0)))) | O12: 60.85 | P12: 31.1 | R12: Earnings / Momentum Support | S12: Nifty Bank | T12: 4.98 | U12: -0.62 | V12: -5.34 | W12: 4.86 | X12: Growing Industry | Y12: =IF(X12="Growing Industry",10,IF(X12="Cyclical in an Upturn",5,0)) | Z12: Fragmented with High ROE | AA12: =IF(Z12="Fragmented with Low ROE",-5,IF(Z12="Fragmented with High ROE",10,IF(Z12= "highly cyclical",5,0))) | AB12: Yes | AC12: =IF(AB12="No",5,0) | AD12: Headwind | AE12: =IF(AD12="Tailwind",10,0) | AF12: Structural (10 Years Consistency) | AG12: =IF(AF12="Structural (10 Years Consistency)",15,IF(AF12="Shallow Cyclical (2 to 3 years growth)",10,IF(AF12 = "Cyclical in an Uptick",5,IF(AF12 = "Cyclical in an Downtick",-10,0)))) | AH12: Yes | AI12: =IF(AH12="Yes",10,0) | AJ12: Yes | AK12: =IF(AJ12="Yes",10,0) | AM12: =IF(AL12="No",10,0) | AN12: Yes | AO12: =IF(AN12="Yes",10,0) | AP12: No | AQ12: =IF(AP12="Yes",10,0) | AR12: Yes | AS12: =IF(AR12="Yes",5,0) | AT12: No | AU12: =IF(AT12="No",10,IF(AT12="Yes",-10,0)) | AV12: No | AW12: =IF(AV12="No",10,0) | AX12: No | AY12: =IF(AX12="No",10,IF(AX12= "Yes CEO Resignation",-5,0)) | AZ12: No | BA12: =IF(AZ12="No",10,IF(AZ12="Yes",-5,0)) | BB12: No | BC12: =IF(BB12="No",5,IF(BB12="Yes",-5,0)) | BD12: Yes | BE12: =IF(BD12="Yes",10,0) | BF12: Yes | BG12: =IF(BF12="Yes",10,0) | BH12: Yes | BI12: =IF(BH12="Yes",10,0) | BJ12: P/BV less than 2.5x and Growth more than 20% | BK12: =IF(BJ12="P/BV less than 2.5x and Growth more than 20%",20,IF(BJ12 = "P/BV less than 2.5x and Growth less than 20%",5,IF(BJ12="P/BV between 2.5x to 5x and Growth more than 20%",10,IF(BJ12= "P/BV between 2.5x to 5x and Growth less than 20%",-5,IF(BJ12= "P/BV above 5x",-5,0))))) | BL12: 20 to 40 | BM12: =IF(BL12="Above 40",20,IF(BL12="20 to 40",10,IF(BL12="0 to 20",-5,0))) | BN12: Between 50 to 75 | BO12: =IF(BN12="Between 50 to 75",10,IF(BN12="Above 75",0,0)) | BP12: Stage 3 | BQ12: =IF(BP12="Stage 2",20,IF(BP12="Stage 1",0,IF(BP12="Stage 3",5,IF(BP12="Stage 4",-5,0)))) | BR12: Negative Trend | BS12: =IF(BR12="Positive Trend",20,IF(BR12="Negative Trend",-10,0)) | BT12: Uptrend | BU12: =IF(BT12="Uptrend",10,IF(BT12="Sideways",5,0)) | BV12: Uptrend | BW12: =IF(BV12="Uptrend",10,IF(BV12="Sideways",5,0)) | BX12: Close to 52 week high or retracement | BY12: =IF(BX12="Overhead supply in last 2 years in last 2 years",-5,IF(BX12="Close to 52 week high or retracement",5,IF(BX12="Blue sky scenario",10,IF(BX12="Long term Downtrend",-10,0)))) | BZ12: Yes | CA12: =IF(BZ12="Yes",10,0)
A13: =IF(B13=0,"",RANK(B13,$B$2:$B$41,0)) | B13: =SUM(N13,Y13,AA13,AC13,AE13,AG13,AI13,AK13,AM13,AO13,AQ13,AS13,AU13,AW13,AY13,BA13,BC13,BE13,BG13,BI13,BK13,BM13,BO13,BQ13,BS13,BU13,BW13,BY13,CA13) | C13: TFCILTD | D13: Tourism Finance Corporation Of India Limited | E13: financials | F13: finance - term-lending institutions | G13: midcap | H13: 5439.06 | I13: 115.22 | J13: -1.92 | K13: 20454753 | L13: 89 | M13: Outperforming | N13: =IF(M13="Underperforming",-5,IF(L13>=95,15,IF(L13>=90,10,IF(L13>=80,5,0)))) | O13: 79.68 | P13: 51.36 | R13: Earnings / Momentum Support | S13: Nifty Bank | T13: 4.98 | U13: 108.68 | V13: 98.77 | W13: 25.07 | X13: Growing Industry | Y13: =IF(X13="Growing Industry",10,IF(X13="Cyclical in an Upturn",5,0)) | Z13: Fragmented with High ROE | AA13: =IF(Z13="Fragmented with Low ROE",-5,IF(Z13="Fragmented with High ROE",10,IF(Z13= "highly cyclical",5,0))) | AB13: Yes | AC13: =IF(AB13="No",5,0) | AD13: Headwind | AE13: =IF(AD13="Tailwind",10,0) | AF13: Structural (10 Years Consistency) | AG13: =IF(AF13="Structural (10 Years Consistency)",15,IF(AF13="Shallow Cyclical (2 to 3 years growth)",10,IF(AF13 = "Cyclical in an Uptick",5,IF(AF13 = "Cyclical in an Downtick",-10,0)))) | AH13: Yes | AI13: =IF(AH13="Yes",10,0) | AJ13: Yes | AK13: =IF(AJ13="Yes",10,0) | AM13: =IF(AL13="No",10,0) | AN13: Yes | AO13: =IF(AN13="Yes",10,0) | AP13: No | AQ13: =IF(AP13="Yes",10,0) | AR13: Yes | AS13: =IF(AR13="Yes",5,0) | AT13: No | AU13: =IF(AT13="No",10,IF(AT13="Yes",-10,0)) | AV13: No | AW13: =IF(AV13="No",10,0) | AX13: No | AY13: =IF(AX13="No",10,IF(AX13= "Yes CEO Resignation",-5,0)) | AZ13: No | BA13: =IF(AZ13="No",10,IF(AZ13="Yes",-5,0)) | BB13: No | BC13: =IF(BB13="No",5,IF(BB13="Yes",-5,0)) | BD13: Yes | BE13: =IF(BD13="Yes",10,0) | BF13: Yes | BG13: =IF(BF13="Yes",10,0) | BH13: Yes | BI13: =IF(BH13="Yes",10,0) | BJ13: P/BV between 2.5x to 5x and Growth more than 20% | BK13: =IF(BJ13="P/BV less than 2.5x and Growth more than 20%",20,IF(BJ13 = "P/BV less than 2.5x and Growth less than 20%",5,IF(BJ13="P/BV between 2.5x to 5x and Growth more than 20%",10,IF(BJ13= "P/BV between 2.5x to 5x and Growth less than 20%",-5,IF(BJ13= "P/BV above 5x",-5,0))))) | BL13: Above 40 | BM13: =IF(BL13="Above 40",20,IF(BL13="20 to 40",10,IF(BL13="0 to 20",-5,0))) | BN13: Above 75 | BO13: =IF(BN13="Between 50 to 75",10,IF(BN13="Above 75",0,0)) | BP13: Stage 3 | BQ13: =IF(BP13="Stage 2",20,IF(BP13="Stage 1",0,IF(BP13="Stage 3",5,IF(BP13="Stage 4",-5,0)))) | BR13: Negative Trend | BS13: =IF(BR13="Positive Trend",20,IF(BR13="Negative Trend",-10,0)) | BT13: Uptrend | BU13: =IF(BT13="Uptrend",10,IF(BT13="Sideways",5,0)) | BV13: Uptrend | BW13: =IF(BV13="Uptrend",10,IF(BV13="Sideways",5,0)) | BX13: Close to 52 week high or retracement | BY13: =IF(BX13="Overhead supply in last 2 years in last 2 years",-5,IF(BX13="Close to 52 week high or retracement",5,IF(BX13="Blue sky scenario",10,IF(BX13="Long term Downtrend",-10,0)))) | BZ13: Yes | CA13: =IF(BZ13="Yes",10,0)
A14: =IF(B14=0,"",RANK(B14,$B$2:$B$41,0)) | B14: =SUM(N14,Y14,AA14,AC14,AE14,AG14,AI14,AK14,AM14,AO14,AQ14,AS14,AU14,AW14,AY14,BA14,BC14,BE14,BG14,BI14,BK14,BM14,BO14,BQ14,BS14,BU14,BW14,BY14,CA14) | C14: MONARCH | D14: Monarch Networth Capital Ltd | E14: financials | F14: finance & investments | G14: smallcap | H14: 3098.18 | I14: 393.15 | J14: 0.64 | K14: 197141 | L14: 54 | M14: Outperforming | N14: =IF(M14="Underperforming",-5,IF(L14>=95,15,IF(L14>=90,10,IF(L14>=80,5,0)))) | O14: 72.32 | P14: 32.5 | R14: Earnings / Momentum Support | S14: Nifty Bank | T14: 4.98 | U14: 16.86 | V14: 11.31 | W14: 9 | X14: Growing Industry | Y14: =IF(X14="Growing Industry",10,IF(X14="Cyclical in an Upturn",5,0)) | Z14: Fragmented with High ROE | AA14: =IF(Z14="Fragmented with Low ROE",-5,IF(Z14="Fragmented with High ROE",10,IF(Z14= "highly cyclical",5,0))) | AB14: Yes | AC14: =IF(AB14="No",5,0) | AD14: Headwind | AE14: =IF(AD14="Tailwind",10,0) | AF14: Structural (10 Years Consistency) | AG14: =IF(AF14="Structural (10 Years Consistency)",15,IF(AF14="Shallow Cyclical (2 to 3 years growth)",10,IF(AF14 = "Cyclical in an Uptick",5,IF(AF14 = "Cyclical in an Downtick",-10,0)))) | AH14: Yes | AI14: =IF(AH14="Yes",10,0) | AJ14: Yes | AK14: =IF(AJ14="Yes",10,0) | AM14: =IF(AL14="No",10,0) | AN14: Yes | AO14: =IF(AN14="Yes",10,0) | AP14: No | AQ14: =IF(AP14="Yes",10,0) | AR14: Yes | AS14: =IF(AR14="Yes",5,0) | AT14: No | AU14: =IF(AT14="No",10,IF(AT14="Yes",-10,0)) | AV14: No | AW14: =IF(AV14="No",10,0) | AX14: No | AY14: =IF(AX14="No",10,IF(AX14= "Yes CEO Resignation",-5,0)) | AZ14: No | BA14: =IF(AZ14="No",10,IF(AZ14="Yes",-5,0)) | BB14: No | BC14: =IF(BB14="No",5,IF(BB14="Yes",-5,0)) | BD14: Yes | BE14: =IF(BD14="Yes",10,0) | BF14: Yes | BG14: =IF(BF14="Yes",10,0) | BH14: Yes | BI14: =IF(BH14="Yes",10,0) | BJ14: P/BV between 2.5x to 5x and Growth more than 20% | BK14: =IF(BJ14="P/BV less than 2.5x and Growth more than 20%",20,IF(BJ14 = "P/BV less than 2.5x and Growth less than 20%",5,IF(BJ14="P/BV between 2.5x to 5x and Growth more than 20%",10,IF(BJ14= "P/BV between 2.5x to 5x and Growth less than 20%",-5,IF(BJ14= "P/BV above 5x",-5,0))))) | BL14: 20 to 40 | BM14: =IF(BL14="Above 40",20,IF(BL14="20 to 40",10,IF(BL14="0 to 20",-5,0))) | BN14: Between 50 to 75 | BO14: =IF(BN14="Between 50 to 75",10,IF(BN14="Above 75",0,0)) | BP14: Stage 3 | BQ14: =IF(BP14="Stage 2",20,IF(BP14="Stage 1",0,IF(BP14="Stage 3",5,IF(BP14="Stage 4",-5,0)))) | BR14: Negative Trend | BS14: =IF(BR14="Positive Trend",20,IF(BR14="Negative Trend",-10,0)) | BT14: Uptrend | BU14: =IF(BT14="Uptrend",10,IF(BT14="Sideways",5,0)) | BV14: Uptrend | BW14: =IF(BV14="Uptrend",10,IF(BV14="Sideways",5,0)) | BX14: Close to 52 week high or retracement | BY14: =IF(BX14="Overhead supply in last 2 years in last 2 years",-5,IF(BX14="Close to 52 week high or retracement",5,IF(BX14="Blue sky scenario",10,IF(BX14="Long term Downtrend",-10,0)))) | BZ14: Yes | CA14: =IF(BZ14="Yes",10,0)
... A41: =IF(B41=0,"",RANK(B41,$B$2:$B$41,0)) | B41: =SUM(N41,Y41,AA41,AC41,AE41,AG41,AI41,AK41,AM41,AO41,AQ41,AS41,AU41,AW41,AY41,BA41,BC41,BE41,BG41,BI41,BK41,BM41,BO41,BQ41,BS41,BU41,BW41,BY41,CA41) | C41: AIIL | D41: Authum Investment & Infrastructure Ltd | E41: financials | F41: finance & investments | G41: largecap | H41: 50664.79 | I41: 588.45 | J41: -1.37 | K41: 184819 | L41: 39 | M41: Underperforming | N41: =IF(M41="Underperforming",-5,IF(L41>=95,15,IF(L41>=90,10,IF(L41>=80,5,0)))) | O41: 60.58 | P41: 15.48 | R41: Earnings / Momentum Support | S41: Nifty Bank | T41: 4.98 | U41: 4.9 | V41: -0.08 | W41: 5.55 | X41: Growing Industry | Y41: =IF(X41="Growing Industry",10,IF(X41="Cyclical in an Upturn",5,0)) | Z41: Fragmented with High ROE | AA41: =IF(Z41="Fragmented with Low ROE",-5,IF(Z41="Fragmented with High ROE",10,IF(Z41= "highly cyclical",5,0))) | AB41: Yes | AC41: =IF(AB41="No",5,0) | AD41: Headwind | AE41: =IF(AD41="Tailwind",10,0) | AF41: Structural (10 Years Consistency) | AG41: =IF(AF41="Structural (10 Years Consistency)",15,IF(AF41="Shallow Cyclical (2 to 3 years growth)",10,IF(AF41 = "Cyclical in an Uptick",5,IF(AF41 = "Cyclical in an Downtick",-10,0)))) | AH41: Yes | AI41: =IF(AH41="Yes",10,0) | AJ41: Yes | AK41: =IF(AJ41="Yes",10,0) | AM41: =IF(AL41="No",10,0) | AN41: Yes | AO41: =IF(AN41="Yes",10,0) | AP41: No | AQ41: =IF(AP41="Yes",10,0) | AR41: Yes | AS41: =IF(AR41="Yes",5,0) | AT41: No | AU41: =IF(AT41="No",10,IF(AT41="Yes",-10,0)) | AV41: No | AW41: =IF(AV41="No",10,0) | AX41: No | AY41: =IF(AX41="No",10,IF(AX41= "Yes CEO Resignation",-5,0)) | AZ41: No | BA41: =IF(AZ41="No",10,IF(AZ41="Yes",-5,0)) | BB41: No | BC41: =IF(BB41="No",5,IF(BB41="Yes",-5,0)) | BD41: Yes | BE41: =IF(BD41="Yes",10,0) | BF41: Yes | BG41: =IF(BF41="Yes",10,0) | BH41: Yes | BI41: =IF(BH41="Yes",10,0) | BJ41: P/BV between 2.5x to 5x and Growth less than 20% | BK41: =IF(BJ41="P/BV less than 2.5x and Growth more than 20%",20,IF(BJ41 = "P/BV less than 2.5x and Growth less than 20%",5,IF(BJ41="P/BV between 2.5x to 5x and Growth more than 20%",10,IF(BJ41= "P/BV between 2.5x to 5x and Growth less than 20%",-5,IF(BJ41= "P/BV above 5x",-5,0))))) | BL41: 0 to 20 | BM41: =IF(BL41="Above 40",20,IF(BL41="20 to 40",10,IF(BL41="0 to 20",-5,0))) | BN41: Between 50 to 75 | BO41: =IF(BN41="Between 50 to 75",10,IF(BN41="Above 75",0,0)) | BP41: Stage 3 | BQ41: =IF(BP41="Stage 2",20,IF(BP41="Stage 1",0,IF(BP41="Stage 3",5,IF(BP41="Stage 4",-5,0)))) | BR41: Negative Trend | BS41: =IF(BR41="Positive Trend",20,IF(BR41="Negative Trend",-10,0)) | BT41: Uptrend | BU41: =IF(BT41="Uptrend",10,IF(BT41="Sideways",5,0)) | BV41: Uptrend | BW41: =IF(BV41="Uptrend",10,IF(BV41="Sideways",5,0)) | BX41: Close to 52 week high or retracement | BY41: =IF(BX41="Overhead supply in last 2 years in last 2 years",-5,IF(BX41="Close to 52 week high or retracement",5,IF(BX41="Blue sky scenario",10,IF(BX41="Long term Downtrend",-10,0)))) | BZ41: Yes | CA41: =IF(BZ41="Yes",10,0)

Sheet Scanner Non Financial
A1: Rank (Non Financial) | B1: Total Score | C1: Entry | D1: Entry Score | E1: Allocation % | F1: Allocation (₹) | G1: Quantity | H1: Symbol | I1: Company | J1: Sector | K1: Industry | L1: Market Cap Bucket | M1: Market Cap Cr | N1: Close | O1: Today Return % | P1: Volume | Q1: Relative Strength Rating | R1: Relative Strength Status | S1: Relative Strength Score | T1: Calculated RSI (14) | U1: Calculated ADX (14) | V1: Calculated V-stop Line | W1: Calculated Near-term Trigger | X1: Sector Benchmark | Y1: Benchmark 1Y Return % | Z1: Stock 1Y Return % | AA1: Relative Strength 1Y (%) | AB1: O'Neil Weighted Score | AC1: Industry Growth | AD1: Industry Growth Score | AE1: Competitiveness | AF1: Competitiveness Score | AG1: Regulation | AH1: Regulation Score | AI1: Sector Headwinds/Tailwind | AJ1: Sector Headwinds/Tailwind Score | AK1: Industry Type | AL1: Industry Type Score | AM1: Margins | AN1: Margins Score | AO1: Margins Stability | AP1: Margins Stability Score | AQ1: Growth | AR1: Growth Score | AS1: Business Type | AT1: Business Type Score | AU1: Near term triggers | AV1: Near term triggers Score | AW1: Type of Revenue | AX1: Type of Revenue Score | AY1: Capital Allocation | AZ1: Capital Allocation Score | BA1: Medium term Growth | BB1: Medium term Growth Score | BC1: ADX | BD1: ADX Score | BE1: RSI | BF1: RSI Score | BG1: Stage Analysis | BH1: Stage Analysis Score | BI1: Price Volume Action | BJ1: Price Volume Action Score | BK1: Secondary Trend | BL1: Secondary Trend Score | BM1: Primary Trend | BN1: Primary Trend Score | BO1: Resistance | BP1: Resistance Score | BQ1: V-stop | BR1: V-stop Score | BS1: PAT Growth | BT1: PAT Growth Score | BU1: Stock History | BV1: Stock History Score | BW1: PE Ratio | BX1: PE Ratio Score | BY1: PEG Ratio | BZ1: PEG Ratio Score | CA1: CFO to EBITDA | CB1: CFO to EBITDA Score | CC1: Debt to Equity | CD1: Debt to Equity Score | CE1: Auditor Resignation | CF1: Auditor Resignation Score | CG1: Contingent Liability | CH1: Contingent Liability Score | CI1: Pledging | CJ1: Pledging Score
A2: =IF(B2=0,"",RANK(B2,$B$2:$B$22,0)) | B2: =SUM(S2,AD2,AF2,AH2,AJ2,AL2,AN2,AP2,AR2,AT2,AV2,AX2,AZ2,BB2,BD2,BF2,BH2,BJ2,BL2,BN2,BP2,BR2,BT2,BV2,BX2,BZ2,CB2,CD2,CF2,CH2,CJ2) | C2: 52W Breakout | D2: 140 | E2: 5% | F2: 50000 | G2: 45 | H2: SBCL | I2: Shivalik Bimetal Controls Ltd | J2: metals & mining | K2: mining / minerals / metals | L2: midcap | M2: 5304.77 | N2: 1105.05 | O2: 20 | P2: 10977326 | Q2: 72 | R2: Underperforming | S2: =IF(R2="Underperforming",-5,IF(Q2>=95,15,IF(Q2>=90,10,IF(Q2>=80,5,0)))) | T2: 76.2 | U2: 45.6 | W2: Volume Spike / Accumulation | X2: Nifty Metal | Y2: 31.49 | Z2: 23.64 | AA2: -5.97 | AB2: 14.67 | AC2: Growing Industry | AD2: =IF(AC2="Growing Industry",10,IF(AC2="Cyclical in an Upturn",5,0)) | AE2: Monopoly | AF2: =IF(AE2="Monopoly",10,IF(AE2="Oligopoly",5,IF(AE2="Duopoly that cooperate",10,IF(AE2="Duopoly that compete",5,IF(AE2="Too many players with High ROCE",5,0))))) | AG2: No | AH2: =IF(AG2="No",5,0) | AI2: Tailwind | AJ2: =IF(AI2="Tailwind",10,0) | AK2: Shallow Cyclical (2 to 3 Years Growth) | AL2: =IF(AK2="Structural (10 Years Consistency)",10,IF(AK2="Shallow Cyclical (2 to 3 years growth)",5,0)) | AM2: Yes due to Product Mix change or Operating Leverage | AN2: =IF(AM2="Yes due to Product Mix change or Operating Leverage",10,IF(AM2="Yes, these are peak margins",-5,IF(AM2="No",5,0))) | AO2: Stable | AP2: =IF(AO2="Stable",10,0) | AQ2: Yes | AR2: =IF(AQ2="Yes",10,0) | AS2: B2B | AT2: =IF(AS2="B2C",10,IF(AS2="B2B",5,0)) | AU2: Yes | AV2: =IF(AU2="Yes",10,0) | AW2: Fully One Time | AX2: =IF(AW2="Fully Annuity",10,IF(AW2="Higher Annuity, Lower One Time",5,IF(AW2="Higher One Time, Lower Annuity",3,0))) | AY2: Good | AZ2: =IF(AY2="Good",10,0) | BA2: Yes for more than 2 years | BB2: =IF(BA2="Yes for more than 2 years",10,IF(BA2="Yes only for next 1 to 2 years",5,0)) | BC2: 20 to 40 | BD2: =IF(BC2="Above 40",20,IF(BC2="20 to 40",10,IF(BC2="0 to 20",-5,0))) | BE2: Between 50 to 75 | BF2: =IF(BE2="Between 50 to 75",10,IF(BE2="Above 75",0,0)) | BG2: Stage 2 | BH2: =IF(BG2="Stage 2",20,IF(BG2="Stage 1",0,IF(BG2="Stage 3",5,IF(BG2="Stage 4",-5,0)))) | BI2: Positive Trend | BJ2: =IF(BI2="Positive Trend",20,IF(BI2="Negative Trend",-10,0)) | BK2: Uptrend | BL2: =IF(BK2="Uptrend",10,IF(BK2="Sideways",5,0)) | BM2: Uptrend | BN2: =IF(BM2="Uptrend",10,IF(BM2="Sideways",5,0)) | BO2: Close to 52 week high or retracement | BP2: =IF(BO2="Overhead supply in last 2 years in last 2 years",-5,IF(BO2="Close to 52 week high or retracement",5,IF(BO2="Blue sky scenario",10,IF(BO2="Long term Downtrend",-10,0)))) | BQ2: Yes | BR2: =IF(BQ2="Yes",10,0) | BS2: More than 20% | BT2: =IF(BS2="More than 20%",10,IF(BS2="Between 12 to 20%",5,IF(BS2="Less than 12%",0,0))) | BU2: Yes | BV2: =IF(BU2="No",10,0) | BW2: No | BX2: =IF(BW2="NO",5,0) | BY2: Between 1.5 to 2 | BZ2: =IF(BY2="Above 2",0,IF(BY2="Between 1.5 to 2",5,IF(BY2="Less than 1.5",10,0))) | CA2: Less than 50% | CB2: =IF(CA2="Above 70%",10,IF(CA2="Between 50% to 70%",5,IF(CA2="Less than 50%",0,IF(CA2="Negative",-10,IF(CA2="Less than 50% and Borrowings are increasing",-5,0))))) | CC2: Less than 0.7 | CD2: =IF(CC2="More than 1.2",-10,IF(CC2="Between 0.7 to 1.2",0,IF(CC2="Less than 0.7",10,0))) | CE2: No | CF2: =IF(CE2="Yes",-10,0) | CG2: Less than 15% | CH2: =IF(CG2="More than 15%",-10,IF(CG2="Less than 15%",10,0)) | CI2: No | CJ2: =IF(CI2="Yes, more than 10%",-10,IF(CI2="No",10,0))
A3: =IF(B3=0,"",RANK(B3,$B$2:$B$22,0)) | B3: =SUM(S3,AD3,AF3,AH3,AJ3,AL3,AN3,AP3,AR3,AT3,AV3,AX3,AZ3,BB3,BD3,BF3,BH3,BJ3,BL3,BN3,BP3,BR3,BT3,BV3,BX3,BZ3,CB3,CD3,CF3,CH3,CJ3) | C3: 52W Breakout | D3: 139.6 | E3: 5% | F3: 50000 | G3: 32 | H3: SYRMA | I3: Syrma SGS Technology Ltd | J3: consumer discretionary | K3: electronics - components | L3: largecap | M3: 27472.56 | N3: 1516.4 | O3: 6.44 | P3: 3864241 | Q3: 84 | R3: Outperforming | S3: =IF(R3="Underperforming",-5,IF(Q3>=95,15,IF(Q3>=90,10,IF(Q3>=80,5,0)))) | T3: 67.89 | U3: 59.69 | W3: Earnings / Momentum Support | X3: Nifty 50 | Y3: 0.85 | Z3: 103.05 | AA3: 101.34 | AB3: 21.65 | AC3: Growing Industry | AD3: =IF(AC3="Growing Industry",10,IF(AC3="Cyclical in an Upturn",5,0)) | AE3: Too Many Players with High ROCE | AF3: =IF(AE3="Monopoly",10,IF(AE3="Oligopoly",5,IF(AE3="Duopoly that cooperate",10,IF(AE3="Duopoly that compete",5,IF(AE3="Too many players with High ROCE",5,0))))) | AG3: No | AH3: =IF(AG3="No",5,0) | AI3: Headwind | AJ3: =IF(AI3="Tailwind",10,0) | AK3: Structural (10 Years Consistency) | AL3: =IF(AK3="Structural (10 Years Consistency)",10,IF(AK3="Shallow Cyclical (2 to 3 years growth)",5,0)) | AM3: No | AN3: =IF(AM3="Yes due to Product Mix change or Operating Leverage",10,IF(AM3="Yes, these are peak margins",-5,IF(AM3="No",5,0))) | AO3: Stable | AP3: =IF(AO3="Stable",10,0) | AQ3: Yes | AR3: =IF(AQ3="Yes",10,0) | AS3: B2B | AT3: =IF(AS3="B2C",10,IF(AS3="B2B",5,0)) | AU3: No | AV3: =IF(AU3="Yes",10,0) | AW3: Higher One Time, Lower Annuity | AX3: =IF(AW3="Fully Annuity",10,IF(AW3="Higher Annuity, Lower One Time",5,IF(AW3="Higher One Time, Lower Annuity",3,0))) | AY3: Good | AZ3: =IF(AY3="Good",10,0) | BA3: Yes for more than 2 years | BB3: =IF(BA3="Yes for more than 2 years",10,IF(BA3="Yes only for next 1 to 2 years",5,0)) | BC3: Above 40 | BD3: =IF(BC3="Above 40",20,IF(BC3="20 to 40",10,IF(BC3="0 to 20",-5,0))) | BE3: Between 50 to 75 | BF3: =IF(BE3="Between 50 to 75",10,IF(BE3="Above 75",0,0)) | BG3: Stage 3 | BH3: =IF(BG3="Stage 2",20,IF(BG3="Stage 1",0,IF(BG3="Stage 3",5,IF(BG3="Stage 4",-5,0)))) | BI3: Negative Trend | BJ3: =IF(BI3="Positive Trend",20,IF(BI3="Negative Trend",-10,0)) | BK3: Uptrend | BL3: =IF(BK3="Uptrend",10,IF(BK3="Sideways",5,0)) | BM3: Uptrend | BN3: =IF(BM3="Uptrend",10,IF(BM3="Sideways",5,0)) | BO3: Close to 52 week high or retracement | BP3: =IF(BO3="Overhead supply in last 2 years in last 2 years",-5,IF(BO3="Close to 52 week high or retracement",5,IF(BO3="Blue sky scenario",10,IF(BO3="Long term Downtrend",-10,0)))) | BQ3: Yes | BR3: =IF(BQ3="Yes",10,0) | BS3: More than 20% | BT3: =IF(BS3="More than 20%",10,IF(BS3="Between 12 to 20%",5,IF(BS3="Less than 12%",0,0))) | BU3: No | BV3: =IF(BU3="No",10,0) | BW3: Yes | BX3: =IF(BW3="NO",5,0) | BY3: Less than 1.5 | BZ3: =IF(BY3="Above 2",0,IF(BY3="Between 1.5 to 2",5,IF(BY3="Less than 1.5",10,0))) | CA3: Above 70% | CB3: =IF(CA3="Above 70%",10,IF(CA3="Between 50% to 70%",5,IF(CA3="Less than 50%",0,IF(CA3="Negative",-10,IF(CA3="Less than 50% and Borrowings are increasing",-5,0))))) | CC3: Less than 0.7 | CD3: =IF(CC3="More than 1.2",-10,IF(CC3="Between 0.7 to 1.2",0,IF(CC3="Less than 0.7",10,0))) | CE3: No | CF3: =IF(CE3="Yes",-10,0) | CG3: Less than 15% | CH3: =IF(CG3="More than 15%",-10,IF(CG3="Less than 15%",10,0)) | CI3: No | CJ3: =IF(CI3="Yes, more than 10%",-10,IF(CI3="No",10,0))
A4: =IF(B4=0,"",RANK(B4,$B$2:$B$22,0)) | B4: =SUM(S4,AD4,AF4,AH4,AJ4,AL4,AN4,AP4,AR4,AT4,AV4,AX4,AZ4,BB4,BD4,BF4,BH4,BJ4,BL4,BN4,BP4,BR4,BT4,BV4,BX4,BZ4,CB4,CD4,CF4,CH4,CJ4) | C4: 52W Breakout | D4: 139.1 | E4: 5% | F4: 50000 | G4: 10 | H4: RADICO | I4: Radico Khaitan Limited | J4: fmcg | K4: breweries & distilleries | L4: largecap | M4: 60255.71 | N4: 4550 | O4: 1.13 | P4: 751749 | Q4: 73 | R4: Outperforming | S4: =IF(R4="Underperforming",-5,IF(Q4>=95,15,IF(Q4>=90,10,IF(Q4>=80,5,0)))) | T4: 85.51 | U4: 62.9 | W4: Earnings / Momentum Support | X4: Nifty FMCG | Y4: -13.73 | Z4: 50.97 | AA4: 75 | AB4: 14.99 | AC4: Growing Industry | AD4: =IF(AC4="Growing Industry",10,IF(AC4="Cyclical in an Upturn",5,0)) | AE4: Too Many Players with High ROCE | AF4: =IF(AE4="Monopoly",10,IF(AE4="Oligopoly",5,IF(AE4="Duopoly that cooperate",10,IF(AE4="Duopoly that compete",5,IF(AE4="Too many players with High ROCE",5,0))))) | AG4: No | AH4: =IF(AG4="No",5,0) | AI4: Headwind | AJ4: =IF(AI4="Tailwind",10,0) | AK4: Structural (10 Years Consistency) | AL4: =IF(AK4="Structural (10 Years Consistency)",10,IF(AK4="Shallow Cyclical (2 to 3 years growth)",5,0)) | AM4: No | AN4: =IF(AM4="Yes due to Product Mix change or Operating Leverage",10,IF(AM4="Yes, these are peak margins",-5,IF(AM4="No",5,0))) | AO4: Stable | AP4: =IF(AO4="Stable",10,0) | AQ4: Yes | AR4: =IF(AQ4="Yes",10,0) | AS4: B2C | AT4: =IF(AS4="B2C",10,IF(AS4="B2B",5,0)) | AU4: No | AV4: =IF(AU4="Yes",10,0) | AW4: Higher Annuity, Lower One Time | AX4: =IF(AW4="Fully Annuity",10,IF(AW4="Higher Annuity, Lower One Time",5,IF(AW4="Higher One Time, Lower Annuity",3,0))) | AY4: Good | AZ4: =IF(AY4="Good",10,0) | BA4: Yes for more than 2 years | BB4: =IF(BA4="Yes for more than 2 years",10,IF(BA4="Yes only for next 1 to 2 years",5,0)) | BC4: Above 40 | BD4: =IF(BC4="Above 40",20,IF(BC4="20 to 40",10,IF(BC4="0 to 20",-5,0))) | BE4: Above 75 | BF4: =IF(BE4="Between 50 to 75",10,IF(BE4="Above 75",0,0)) | BG4: Stage 3 | BH4: =IF(BG4="Stage 2",20,IF(BG4="Stage 1",0,IF(BG4="Stage 3",5,IF(BG4="Stage 4",-5,0)))) | BI4: Negative Trend | BJ4: =IF(BI4="Positive Trend",20,IF(BI4="Negative Trend",-10,0)) | BK4: Uptrend | BL4: =IF(BK4="Uptrend",10,IF(BK4="Sideways",5,0)) | BM4: Uptrend | BN4: =IF(BM4="Uptrend",10,IF(BM4="Sideways",5,0)) | BO4: Close to 52 week high or retracement | BP4: =IF(BO4="Overhead supply in last 2 years in last 2 years",-5,IF(BO4="Close to 52 week high or retracement",5,IF(BO4="Blue sky scenario",10,IF(BO4="Long term Downtrend",-10,0)))) | BQ4: Yes | BR4: =IF(BQ4="Yes",10,0) | BS4: More than 20% | BT4: =IF(BS4="More than 20%",10,IF(BS4="Between 12 to 20%",5,IF(BS4="Less than 12%",0,0))) | BU4: No | BV4: =IF(BU4="No",10,0) | BW4: Yes | BX4: =IF(BW4="NO",5,0) | BY4: Less than 1.5 | BZ4: =IF(BY4="Above 2",0,IF(BY4="Between 1.5 to 2",5,IF(BY4="Less than 1.5",10,0))) | CA4: Above 70% | CB4: =IF(CA4="Above 70%",10,IF(CA4="Between 50% to 70%",5,IF(CA4="Less than 50%",0,IF(CA4="Negative",-10,IF(CA4="Less than 50% and Borrowings are increasing",-5,0))))) | CC4: Less than 0.7 | CD4: =IF(CC4="More than 1.2",-10,IF(CC4="Between 0.7 to 1.2",0,IF(CC4="Less than 0.7",10,0))) | CE4: No | CF4: =IF(CE4="Yes",-10,0) | CG4: Less than 15% | CH4: =IF(CG4="More than 15%",-10,IF(CG4="Less than 15%",10,0)) | CI4: No | CJ4: =IF(CI4="Yes, more than 10%",-10,IF(CI4="No",10,0))
A5: =IF(B5=0,"",RANK(B5,$B$2:$B$22,0)) | B5: =SUM(S5,AD5,AF5,AH5,AJ5,AL5,AN5,AP5,AR5,AT5,AV5,AX5,AZ5,BB5,BD5,BF5,BH5,BJ5,BL5,BN5,BP5,BR5,BT5,BV5,BX5,BZ5,CB5,CD5,CF5,CH5,CJ5) | C5: 52W Breakout | D5: 139.6 | E5: 5% | F5: 50000 | G5: 80 | H5: THYROCARE | I5: Thyrocare Technologies Limited | J5: healthcare | K5: healthcare | L5: midcap | M5: 9601.65 | N5: 622.1 | O5: 3.12 | P5: 342145 | Q5: 65 | R5: Outperforming | S5: =IF(R5="Underperforming",-5,IF(Q5>=95,15,IF(Q5>=90,10,IF(Q5>=80,5,0)))) | T5: 71.43 | U5: 57.05 | W5: Earnings / Momentum Support | X5: Nifty Pharma | Y5: 24.01 | Z5: 37.85 | AA5: 11.16 | AB5: 12.65 | AC5: Growing Industry | AD5: =IF(AC5="Growing Industry",10,IF(AC5="Cyclical in an Upturn",5,0)) | AE5: Too Many Players with High ROCE | AF5: =IF(AE5="Monopoly",10,IF(AE5="Oligopoly",5,IF(AE5="Duopoly that cooperate",10,IF(AE5="Duopoly that compete",5,IF(AE5="Too many players with High ROCE",5,0))))) | AG5: Yes | AH5: =IF(AG5="No",5,0) | AI5: Headwind | AJ5: =IF(AI5="Tailwind",10,0) | AK5: Structural (10 Years Consistency) | AL5: =IF(AK5="Structural (10 Years Consistency)",10,IF(AK5="Shallow Cyclical (2 to 3 years growth)",5,0)) | AM5: No | AN5: =IF(AM5="Yes due to Product Mix change or Operating Leverage",10,IF(AM5="Yes, these are peak margins",-5,IF(AM5="No",5,0))) | AO5: Stable | AP5: =IF(AO5="Stable",10,0) | AQ5: Yes | AR5: =IF(AQ5="Yes",10,0) | AS5: B2B | AT5: =IF(AS5="B2C",10,IF(AS5="B2B",5,0)) | AU5: No | AV5: =IF(AU5="Yes",10,0) | AW5: Higher Annuity, Lower One Time | AX5: =IF(AW5="Fully Annuity",10,IF(AW5="Higher Annuity, Lower One Time",5,IF(AW5="Higher One Time, Lower Annuity",3,0))) | AY5: Good | AZ5: =IF(AY5="Good",10,0) | BA5: Yes for more than 2 years | BB5: =IF(BA5="Yes for more than 2 years",10,IF(BA5="Yes only for next 1 to 2 years",5,0)) | BC5: Above 40 | BD5: =IF(BC5="Above 40",20,IF(BC5="20 to 40",10,IF(BC5="0 to 20",-5,0))) | BE5: Between 50 to 75 | BF5: =IF(BE5="Between 50 to 75",10,IF(BE5="Above 75",0,0)) | BG5: Stage 3 | BH5: =IF(BG5="Stage 2",20,IF(BG5="Stage 1",0,IF(BG5="Stage 3",5,IF(BG5="Stage 4",-5,0)))) | BI5: Negative Trend | BJ5: =IF(BI5="Positive Trend",20,IF(BI5="Negative Trend",-10,0)) | BK5: Uptrend | BL5: =IF(BK5="Uptrend",10,IF(BK5="Sideways",5,0)) | BM5: Uptrend | BN5: =IF(BM5="Uptrend",10,IF(BM5="Sideways",5,0)) | BO5: Close to 52 week high or retracement | BP5: =IF(BO5="Overhead supply in last 2 years in last 2 years",-5,IF(BO5="Close to 52 week high or retracement",5,IF(BO5="Blue sky scenario",10,IF(BO5="Long term Downtrend",-10,0)))) | BQ5: Yes | BR5: =IF(BQ5="Yes",10,0) | BS5: More than 20% | BT5: =IF(BS5="More than 20%",10,IF(BS5="Between 12 to 20%",5,IF(BS5="Less than 12%",0,0))) | BU5: No | BV5: =IF(BU5="No",10,0) | BW5: Yes | BX5: =IF(BW5="NO",5,0) | BY5: Between 1.5 to 2 | BZ5: =IF(BY5="Above 2",0,IF(BY5="Between 1.5 to 2",5,IF(BY5="Less than 1.5",10,0))) | CA5: Above 70% | CB5: =IF(CA5="Above 70%",10,IF(CA5="Between 50% to 70%",5,IF(CA5="Less than 50%",0,IF(CA5="Negative",-10,IF(CA5="Less than 50% and Borrowings are increasing",-5,0))))) | CC5: Less than 0.7 | CD5: =IF(CC5="More than 1.2",-10,IF(CC5="Between 0.7 to 1.2",0,IF(CC5="Less than 0.7",10,0))) | CE5: No | CF5: =IF(CE5="Yes",-10,0) | CG5: Less than 15% | CH5: =IF(CG5="More than 15%",-10,IF(CG5="Less than 15%",10,0)) | CI5: No | CJ5: =IF(CI5="Yes, more than 10%",-10,IF(CI5="No",10,0))
A6: =IF(B6=0,"",RANK(B6,$B$2:$B$22,0)) | B6: =SUM(S6,AD6,AF6,AH6,AJ6,AL6,AN6,AP6,AR6,AT6,AV6,AX6,AZ6,BB6,BD6,BF6,BH6,BJ6,BL6,BN6,BP6,BR6,BT6,BV6,BX6,BZ6,CB6,CD6,CF6,CH6,CJ6) | C6: 52W Breakout | D6: 139.3 | E6: 5% | F6: 50000 | G6: 18 | H6: GLAND | I6: Gland Pharma Ltd | J6: healthcare | K6: pharmaceuticals - indian - formulations | L6: largecap | M6: 42906.01 | N6: 2667.3 | O6: 2.55 | P6: 720772 | Q6: 72 | R6: Outperforming | S6: =IF(R6="Underperforming",-5,IF(Q6>=95,15,IF(Q6>=90,10,IF(Q6>=80,5,0)))) | T6: 72.26 | U6: 57.92 | W6: Earnings / Momentum Support | X6: Nifty Pharma | Y6: 24.01 | Z6: 35.7 | AA6: 9.42 | AB6: 14.52 | AC6: Growing Industry | AD6: =IF(AC6="Growing Industry",10,IF(AC6="Cyclical in an Upturn",5,0)) | AE6: Too Many Players with High ROCE | AF6: =IF(AE6="Monopoly",10,IF(AE6="Oligopoly",5,IF(AE6="Duopoly that cooperate",10,IF(AE6="Duopoly that compete",5,IF(AE6="Too many players with High ROCE",5,0))))) | AG6: Yes | AH6: =IF(AG6="No",5,0) | AI6: Headwind | AJ6: =IF(AI6="Tailwind",10,0) | AK6: Structural (10 Years Consistency) | AL6: =IF(AK6="Structural (10 Years Consistency)",10,IF(AK6="Shallow Cyclical (2 to 3 years growth)",5,0)) | AM6: No | AN6: =IF(AM6="Yes due to Product Mix change or Operating Leverage",10,IF(AM6="Yes, these are peak margins",-5,IF(AM6="No",5,0))) | AO6: Stable | AP6: =IF(AO6="Stable",10,0) | AQ6: Yes | AR6: =IF(AQ6="Yes",10,0) | AS6: B2B | AT6: =IF(AS6="B2C",10,IF(AS6="B2B",5,0)) | AU6: No | AV6: =IF(AU6="Yes",10,0) | AW6: Higher Annuity, Lower One Time | AX6: =IF(AW6="Fully Annuity",10,IF(AW6="Higher Annuity, Lower One Time",5,IF(AW6="Higher One Time, Lower Annuity",3,0))) | AY6: Good | AZ6: =IF(AY6="Good",10,0) | BA6: Yes for more than 2 years | BB6: =IF(BA6="Yes for more than 2 years",10,IF(BA6="Yes only for next 1 to 2 years",5,0)) | BC6: Above 40 | BD6: =IF(BC6="Above 40",20,IF(BC6="20 to 40",10,IF(BC6="0 to 20",-5,0))) | BE6: Between 50 to 75 | BF6: =IF(BE6="Between 50 to 75",10,IF(BE6="Above 75",0,0)) | BG6: Stage 3 | BH6: =IF(BG6="Stage 2",20,IF(BG6="Stage 1",0,IF(BG6="Stage 3",5,IF(BG6="Stage 4",-5,0)))) | BI6: Negative Trend | BJ6: =IF(BI6="Positive Trend",20,IF(BI6="Negative Trend",-10,0)) | BK6: Uptrend | BL6: =IF(BK6="Uptrend",10,IF(BK6="Sideways",5,0)) | BM6: Uptrend | BN6: =IF(BM6="Uptrend",10,IF(BM6="Sideways",5,0)) | BO6: Close to 52 week high or retracement | BP6: =IF(BO6="Overhead supply in last 2 years in last 2 years",-5,IF(BO6="Close to 52 week high or retracement",5,IF(BO6="Blue sky scenario",10,IF(BO6="Long term Downtrend",-10,0)))) | BQ6: Yes | BR6: =IF(BQ6="Yes",10,0) | BS6: More than 20% | BT6: =IF(BS6="More than 20%",10,IF(BS6="Between 12 to 20%",5,IF(BS6="Less than 12%",0,0))) | BU6: No | BV6: =IF(BU6="No",10,0) | BW6: Yes | BX6: =IF(BW6="NO",5,0) | BY6: Less than 1.5 | BZ6: =IF(BY6="Above 2",0,IF(BY6="Between 1.5 to 2",5,IF(BY6="Less than 1.5",10,0))) | CA6: Between 50% to 70% | CB6: =IF(CA6="Above 70%",10,IF(CA6="Between 50% to 70%",5,IF(CA6="Less than 50%",0,IF(CA6="Negative",-10,IF(CA6="Less than 50% and Borrowings are increasing",-5,0))))) | CC6: Less than 0.7 | CD6: =IF(CC6="More than 1.2",-10,IF(CC6="Between 0.7 to 1.2",0,IF(CC6="Less than 0.7",10,0))) | CE6: No | CF6: =IF(CE6="Yes",-10,0) | CG6: Less than 15% | CH6: =IF(CG6="More than 15%",-10,IF(CG6="Less than 15%",10,0)) | CI6: No | CJ6: =IF(CI6="Yes, more than 10%",-10,IF(CI6="No",10,0))
A7: =IF(B7=0,"",RANK(B7,$B$2:$B$22,0)) | B7: =SUM(S7,AD7,AF7,AH7,AJ7,AL7,AN7,AP7,AR7,AT7,AV7,AX7,AZ7,BB7,BD7,BF7,BH7,BJ7,BL7,BN7,BP7,BR7,BT7,BV7,BX7,BZ7,CB7,CD7,CF7,CH7,CJ7) | C7: 52W Breakout | D7: 139.2 | E7: 5% | F7: 50000 | G7: 104 | H7: NRBBEARING | I7: Nrb Bearing Limited | J7: industrials | K7: bearings | L7: smallcap | M7: 4472.98 | N7: 478.25 | O7: 3.63 | P7: 2221157 | Q7: 84 | R7: Outperforming | S7: =IF(R7="Underperforming",-5,IF(Q7>=95,15,IF(Q7>=90,10,IF(Q7>=80,5,0)))) | T7: 74.79 | U7: 49.29 | W7: Earnings / Momentum Support | X7: Nifty 50 | Y7: 0.85 | Z7: 71.51 | AA7: 70.07 | AB7: 21.92 | AC7: Cyclical in an Upturn | AD7: =IF(AC7="Growing Industry",10,IF(AC7="Cyclical in an Upturn",5,0)) | AE7: Too Many Players with High ROCE | AF7: =IF(AE7="Monopoly",10,IF(AE7="Oligopoly",5,IF(AE7="Duopoly that cooperate",10,IF(AE7="Duopoly that compete",5,IF(AE7="Too many players with High ROCE",5,0))))) | AG7: No | AH7: =IF(AG7="No",5,0) | AI7: Headwind | AJ7: =IF(AI7="Tailwind",10,0) | AK7: Structural (10 Years Consistency) | AL7: =IF(AK7="Structural (10 Years Consistency)",10,IF(AK7="Shallow Cyclical (2 to 3 years growth)",5,0)) | AM7: No | AN7: =IF(AM7="Yes due to Product Mix change or Operating Leverage",10,IF(AM7="Yes, these are peak margins",-5,IF(AM7="No",5,0))) | AO7: Stable | AP7: =IF(AO7="Stable",10,0) | AQ7: Yes | AR7: =IF(AQ7="Yes",10,0) | AS7: B2B | AT7: =IF(AS7="B2C",10,IF(AS7="B2B",5,0)) | AU7: No | AV7: =IF(AU7="Yes",10,0) | AW7: Higher One Time, Lower Annuity | AX7: =IF(AW7="Fully Annuity",10,IF(AW7="Higher Annuity, Lower One Time",5,IF(AW7="Higher One Time, Lower Annuity",3,0))) | AY7: Good | AZ7: =IF(AY7="Good",10,0) | BA7: Yes for more than 2 years | BB7: =IF(BA7="Yes for more than 2 years",10,IF(BA7="Yes only for next 1 to 2 years",5,0)) | BC7: Above 40 | BD7: =IF(BC7="Above 40",20,IF(BC7="20 to 40",10,IF(BC7="0 to 20",-5,0))) | BE7: Between 50 to 75 | BF7: =IF(BE7="Between 50 to 75",10,IF(BE7="Above 75",0,0)) | BG7: Stage 3 | BH7: =IF(BG7="Stage 2",20,IF(BG7="Stage 1",0,IF(BG7="Stage 3",5,IF(BG7="Stage 4",-5,0)))) | BI7: Negative Trend | BJ7: =IF(BI7="Positive Trend",20,IF(BI7="Negative Trend",-10,0)) | BK7: Uptrend | BL7: =IF(BK7="Uptrend",10,IF(BK7="Sideways",5,0)) | BM7: Uptrend | BN7: =IF(BM7="Uptrend",10,IF(BM7="Sideways",5,0)) | BO7: Close to 52 week high or retracement | BP7: =IF(BO7="Overhead supply in last 2 years in last 2 years",-5,IF(BO7="Close to 52 week high or retracement",5,IF(BO7="Blue sky scenario",10,IF(BO7="Long term Downtrend",-10,0)))) | BQ7: Yes | BR7: =IF(BQ7="Yes",10,0) | BS7: Between 12 to 20% | BT7: =IF(BS7="More than 20%",10,IF(BS7="Between 12 to 20%",5,IF(BS7="Less than 12%",0,0))) | BU7: No | BV7: =IF(BU7="No",10,0) | BW7: No | BX7: =IF(BW7="NO",5,0) | BY7: Above 2 | BZ7: =IF(BY7="Above 2",0,IF(BY7="Between 1.5 to 2",5,IF(BY7="Less than 1.5",10,0))) | CA7: Above 70% | CB7: =IF(CA7="Above 70%",10,IF(CA7="Between 50% to 70%",5,IF(CA7="Less than 50%",0,IF(CA7="Negative",-10,IF(CA7="Less than 50% and Borrowings are increasing",-5,0))))) | CC7: Less than 0.7 | CD7: =IF(CC7="More than 1.2",-10,IF(CC7="Between 0.7 to 1.2",0,IF(CC7="Less than 0.7",10,0))) | CE7: No | CF7: =IF(CE7="Yes",-10,0) | CG7: Less than 15% | CH7: =IF(CG7="More than 15%",-10,IF(CG7="Less than 15%",10,0)) | CI7: No | CJ7: =IF(CI7="Yes, more than 10%",-10,IF(CI7="No",10,0))
A8: =IF(B8=0,"",RANK(B8,$B$2:$B$22,0)) | B8: =SUM(S8,AD8,AF8,AH8,AJ8,AL8,AN8,AP8,AR8,AT8,AV8,AX8,AZ8,BB8,BD8,BF8,BH8,BJ8,BL8,BN8,BP8,BR8,BT8,BV8,BX8,BZ8,CB8,CD8,CF8,CH8,CJ8) | C8: 52W Breakout | D8: 139.1 | E8: 5% | F8: 50000 | G8: 27 | H8: WELCORP | I8: Welspun Corp Limited | J8: industrials | K8: steel - large | L8: largecap | M8: 48532.2 | N8: 1848.5 | O8: 0.47 | P8: 446106 | Q8: 87 | R8: Outperforming | S8: =IF(R8="Underperforming",-5,IF(Q8>=95,15,IF(Q8>=90,10,IF(Q8>=80,5,0)))) | T8: 88.33 | U8: 70.72 | W8: Earnings / Momentum Support | X8: Nifty Metal | Y8: 31.49 | Z8: 71.82 | AA8: 30.67 | AB8: 23.89 | AC8: Cyclical in an Upturn | AD8: =IF(AC8="Growing Industry",10,IF(AC8="Cyclical in an Upturn",5,0)) | AE8: Too Many Players with High ROCE | AF8: =IF(AE8="Monopoly",10,IF(AE8="Oligopoly",5,IF(AE8="Duopoly that cooperate",10,IF(AE8="Duopoly that compete",5,IF(AE8="Too many players with High ROCE",5,0))))) | AG8: No | AH8: =IF(AG8="No",5,0) | AI8: Headwind | AJ8: =IF(AI8="Tailwind",10,0) | AK8: Structural (10 Years Consistency) | AL8: =IF(AK8="Structural (10 Years Consistency)",10,IF(AK8="Shallow Cyclical (2 to 3 years growth)",5,0)) | AM8: No | AN8: =IF(AM8="Yes due to Product Mix change or Operating Leverage",10,IF(AM8="Yes, these are peak margins",-5,IF(AM8="No",5,0))) | AO8: Stable | AP8: =IF(AO8="Stable",10,0) | AQ8: Yes | AR8: =IF(AQ8="Yes",10,0) | AS8: B2B | AT8: =IF(AS8="B2C",10,IF(AS8="B2B",5,0)) | AU8: No | AV8: =IF(AU8="Yes",10,0) | AW8: Higher One Time, Lower Annuity | AX8: =IF(AW8="Fully Annuity",10,IF(AW8="Higher Annuity, Lower One Time",5,IF(AW8="Higher One Time, Lower Annuity",3,0))) | AY8: Good | AZ8: =IF(AY8="Good",10,0) | BA8: Yes for more than 2 years | BB8: =IF(BA8="Yes for more than 2 years",10,IF(BA8="Yes only for next 1 to 2 years",5,0)) | BC8: Above 40 | BD8: =IF(BC8="Above 40",20,IF(BC8="20 to 40",10,IF(BC8="0 to 20",-5,0))) | BE8: Above 75 | BF8: =IF(BE8="Between 50 to 75",10,IF(BE8="Above 75",0,0)) | BG8: Stage 3 | BH8: =IF(BG8="Stage 2",20,IF(BG8="Stage 1",0,IF(BG8="Stage 3",5,IF(BG8="Stage 4",-5,0)))) | BI8: Negative Trend | BJ8: =IF(BI8="Positive Trend",20,IF(BI8="Negative Trend",-10,0)) | BK8: Uptrend | BL8: =IF(BK8="Uptrend",10,IF(BK8="Sideways",5,0)) | BM8: Uptrend | BN8: =IF(BM8="Uptrend",10,IF(BM8="Sideways",5,0)) | BO8: Close to 52 week high or retracement | BP8: =IF(BO8="Overhead supply in last 2 years in last 2 years",-5,IF(BO8="Close to 52 week high or retracement",5,IF(BO8="Blue sky scenario",10,IF(BO8="Long term Downtrend",-10,0)))) | BQ8: Yes | BR8: =IF(BQ8="Yes",10,0) | BS8: More than 20% | BT8: =IF(BS8="More than 20%",10,IF(BS8="Between 12 to 20%",5,IF(BS8="Less than 12%",0,0))) | BU8: No | BV8: =IF(BU8="No",10,0) | BW8: No | BX8: =IF(BW8="NO",5,0) | BY8: Above 2 | BZ8: =IF(BY8="Above 2",0,IF(BY8="Between 1.5 to 2",5,IF(BY8="Less than 1.5",10,0))) | CA8: Above 70% | CB8: =IF(CA8="Above 70%",10,IF(CA8="Between 50% to 70%",5,IF(CA8="Less than 50%",0,IF(CA8="Negative",-10,IF(CA8="Less than 50% and Borrowings are increasing",-5,0))))) | CC8: Less than 0.7 | CD8: =IF(CC8="More than 1.2",-10,IF(CC8="Between 0.7 to 1.2",0,IF(CC8="Less than 0.7",10,0))) | CE8: No | CF8: =IF(CE8="Yes",-10,0) | CG8: Less than 15% | CH8: =IF(CG8="More than 15%",-10,IF(CG8="Less than 15%",10,0)) | CI8: No | CJ8: =IF(CI8="Yes, more than 10%",-10,IF(CI8="No",10,0))
A9: =IF(B9=0,"",RANK(B9,$B$2:$B$22,0)) | B9: =SUM(S9,AD9,AF9,AH9,AJ9,AL9,AN9,AP9,AR9,AT9,AV9,AX9,AZ9,BB9,BD9,BF9,BH9,BJ9,BL9,BN9,BP9,BR9,BT9,BV9,BX9,BZ9,CB9,CD9,CF9,CH9,CJ9) | C9: 52W Breakout | D9: 139.1 | E9: 5% | F9: 50000 | G9: 36 | H9: ALIVUS | I9: Alivus Life Sciences Ltd | J9: healthcare | K9: pharmaceuticals - indian - bulk drugs & formln | L9: midcap | M9: 16321.48 | N9: 1374.5 | O9: 3.36 | P9: 342677 | Q9: 62 | R9: Outperforming | S9: =IF(R9="Underperforming",-5,IF(Q9>=95,15,IF(Q9>=90,10,IF(Q9>=80,5,0)))) | T9: 76.02 | U9: 39.61 | W9: Earnings / Momentum Support | X9: Nifty Pharma | Y9: 24.01 | Z9: 43.01 | AA9: 15.32 | AB9: 11.55 | AC9: Growing Industry | AD9: =IF(AC9="Growing Industry",10,IF(AC9="Cyclical in an Upturn",5,0)) | AE9: Too Many Players with High ROCE | AF9: =IF(AE9="Monopoly",10,IF(AE9="Oligopoly",5,IF(AE9="Duopoly that cooperate",10,IF(AE9="Duopoly that compete",5,IF(AE9="Too many players with High ROCE",5,0))))) | AG9: Yes | AH9: =IF(AG9="No",5,0) | AI9: Headwind | AJ9: =IF(AI9="Tailwind",10,0) | AK9: Structural (10 Years Consistency) | AL9: =IF(AK9="Structural (10 Years Consistency)",10,IF(AK9="Shallow Cyclical (2 to 3 years growth)",5,0)) | AM9: No | AN9: =IF(AM9="Yes due to Product Mix change or Operating Leverage",10,IF(AM9="Yes, these are peak margins",-5,IF(AM9="No",5,0))) | AO9: Stable | AP9: =IF(AO9="Stable",10,0) | AQ9: Yes | AR9: =IF(AQ9="Yes",10,0) | AS9: B2B | AT9: =IF(AS9="B2C",10,IF(AS9="B2B",5,0)) | AU9: No | AV9: =IF(AU9="Yes",10,0) | AW9: Higher Annuity, Lower One Time | AX9: =IF(AW9="Fully Annuity",10,IF(AW9="Higher Annuity, Lower One Time",5,IF(AW9="Higher One Time, Lower Annuity",3,0))) | AY9: Good | AZ9: =IF(AY9="Good",10,0) | BA9: Yes for more than 2 years | BB9: =IF(BA9="Yes for more than 2 years",10,IF(BA9="Yes only for next 1 to 2 years",5,0)) | BC9: 20 to 40 | BD9: =IF(BC9="Above 40",20,IF(BC9="20 to 40",10,IF(BC9="0 to 20",-5,0))) | BE9: Above 75 | BF9: =IF(BE9="Between 50 to 75",10,IF(BE9="Above 75",0,0)) | BG9: Stage 3 | BH9: =IF(BG9="Stage 2",20,IF(BG9="Stage 1",0,IF(BG9="Stage 3",5,IF(BG9="Stage 4",-5,0)))) | BI9: Negative Trend | BJ9: =IF(BI9="Positive Trend",20,IF(BI9="Negative Trend",-10,0)) | BK9: Uptrend | BL9: =IF(BK9="Uptrend",10,IF(BK9="Sideways",5,0)) | BM9: Uptrend | BN9: =IF(BM9="Uptrend",10,IF(BM9="Sideways",5,0)) | BO9: Close to 52 week high or retracement | BP9: =IF(BO9="Overhead supply in last 2 years in last 2 years",-5,IF(BO9="Close to 52 week high or retracement",5,IF(BO9="Blue sky scenario",10,IF(BO9="Long term Downtrend",-10,0)))) | BQ9: Yes | BR9: =IF(BQ9="Yes",10,0) | BS9: More than 20% | BT9: =IF(BS9="More than 20%",10,IF(BS9="Between 12 to 20%",5,IF(BS9="Less than 12%",0,0))) | BU9: No | BV9: =IF(BU9="No",10,0) | BW9: No | BX9: =IF(BW9="NO",5,0) | BY9: Less than 1.5 | BZ9: =IF(BY9="Above 2",0,IF(BY9="Between 1.5 to 2",5,IF(BY9="Less than 1.5",10,0))) | CA9: Above 70% | CB9: =IF(CA9="Above 70%",10,IF(CA9="Between 50% to 70%",5,IF(CA9="Less than 50%",0,IF(CA9="Negative",-10,IF(CA9="Less than 50% and Borrowings are increasing",-5,0))))) | CC9: Less than 0.7 | CD9: =IF(CC9="More than 1.2",-10,IF(CC9="Between 0.7 to 1.2",0,IF(CC9="Less than 0.7",10,0))) | CE9: No | CF9: =IF(CE9="Yes",-10,0) | CG9: Less than 15% | CH9: =IF(CG9="More than 15%",-10,IF(CG9="Less than 15%",10,0)) | CI9: No | CJ9: =IF(CI9="Yes, more than 10%",-10,IF(CI9="No",10,0))
A10: =IF(B10=0,"",RANK(B10,$B$2:$B$22,0)) | B10: =SUM(S10,AD10,AF10,AH10,AJ10,AL10,AN10,AP10,AR10,AT10,AV10,AX10,AZ10,BB10,BD10,BF10,BH10,BJ10,BL10,BN10,BP10,BR10,BT10,BV10,BX10,BZ10,CB10,CD10,CF10,CH10,CJ10) | C10: 52W Breakout | D10: 139.2 | E10: 5% | F10: 50000 | G10: 27 | H10: MACPOWER | I10: Macpower CNC Machines Ltd | J10: industrials | K10: engineering | L10: smallcap | M10: 1681.8 | N10: 1824.3 | O10: 8.52 | P10: 138274 | Q10: 89 | R10: Outperforming | S10: =IF(R10="Underperforming",-5,IF(Q10>=95,15,IF(Q10>=90,10,IF(Q10>=80,5,0)))) | T10: 73.51 | U10: 30.88 | W10: Earnings / Momentum Support | X10: Nifty 50 | Y10: 0.85 | Z10: 105.66 | AA10: 103.92 | AB10: 24.91 | AC10: Cyclical in an Upturn | AD10: =IF(AC10="Growing Industry",10,IF(AC10="Cyclical in an Upturn",5,0)) | AE10: Too Many Players with High ROCE | AF10: =IF(AE10="Monopoly",10,IF(AE10="Oligopoly",5,IF(AE10="Duopoly that cooperate",10,IF(AE10="Duopoly that compete",5,IF(AE10="Too many players with High ROCE",5,0))))) | AG10: No | AH10: =IF(AG10="No",5,0) | AI10: Headwind | AJ10: =IF(AI10="Tailwind",10,0) | AK10: Structural (10 Years Consistency) | AL10: =IF(AK10="Structural (10 Years Consistency)",10,IF(AK10="Shallow Cyclical (2 to 3 years growth)",5,0)) | AM10: No | AN10: =IF(AM10="Yes due to Product Mix change or Operating Leverage",10,IF(AM10="Yes, these are peak margins",-5,IF(AM10="No",5,0))) | AO10: Stable | AP10: =IF(AO10="Stable",10,0) | AQ10: Yes | AR10: =IF(AQ10="Yes",10,0) | AS10: B2B | AT10: =IF(AS10="B2C",10,IF(AS10="B2B",5,0)) | AU10: No | AV10: =IF(AU10="Yes",10,0) | AW10: Higher One Time, Lower Annuity | AX10: =IF(AW10="Fully Annuity",10,IF(AW10="Higher Annuity, Lower One Time",5,IF(AW10="Higher One Time, Lower Annuity",3,0))) | AY10: Good | AZ10: =IF(AY10="Good",10,0) | BA10: Yes for more than 2 years | BB10: =IF(BA10="Yes for more than 2 years",10,IF(BA10="Yes only for next 1 to 2 years",5,0)) | BC10: 20 to 40 | BD10: =IF(BC10="Above 40",20,IF(BC10="20 to 40",10,IF(BC10="0 to 20",-5,0))) | BE10: Between 50 to 75 | BF10: =IF(BE10="Between 50 to 75",10,IF(BE10="Above 75",0,0)) | BG10: Stage 3 | BH10: =IF(BG10="Stage 2",20,IF(BG10="Stage 1",0,IF(BG10="Stage 3",5,IF(BG10="Stage 4",-5,0)))) | BI10: Negative Trend | BJ10: =IF(BI10="Positive Trend",20,IF(BI10="Negative Trend",-10,0)) | BK10: Uptrend | BL10: =IF(BK10="Uptrend",10,IF(BK10="Sideways",5,0)) | BM10: Uptrend | BN10: =IF(BM10="Uptrend",10,IF(BM10="Sideways",5,0)) | BO10: Close to 52 week high or retracement | BP10: =IF(BO10="Overhead supply in last 2 years in last 2 years",-5,IF(BO10="Close to 52 week high or retracement",5,IF(BO10="Blue sky scenario",10,IF(BO10="Long term Downtrend",-10,0)))) | BQ10: Yes | BR10: =IF(BQ10="Yes",10,0) | BS10: More than 20% | BT10: =IF(BS10="More than 20%",10,IF(BS10="Between 12 to 20%",5,IF(BS10="Less than 12%",0,0))) | BU10: No | BV10: =IF(BU10="No",10,0) | BW10: Yes | BX10: =IF(BW10="NO",5,0) | BY10: Above 2 | BZ10: =IF(BY10="Above 2",0,IF(BY10="Between 1.5 to 2",5,IF(BY10="Less than 1.5",10,0))) | CA10: Above 70% | CB10: =IF(CA10="Above 70%",10,IF(CA10="Between 50% to 70%",5,IF(CA10="Less than 50%",0,IF(CA10="Negative",-10,IF(CA10="Less than 50% and Borrowings are increasing",-5,0))))) | CC10: Less than 0.7 | CD10: =IF(CC10="More than 1.2",-10,IF(CC10="Between 0.7 to 1.2",0,IF(CC10="Less than 0.7",10,0))) | CE10: No | CF10: =IF(CE10="Yes",-10,0) | CG10: Less than 15% | CH10: =IF(CG10="More than 15%",-10,IF(CG10="Less than 15%",10,0)) | CI10: No | CJ10: =IF(CI10="Yes, more than 10%",-10,IF(CI10="No",10,0))
A11: =IF(B11=0,"",RANK(B11,$B$2:$B$22,0)) | B11: =SUM(S11,AD11,AF11,AH11,AJ11,AL11,AN11,AP11,AR11,AT11,AV11,AX11,AZ11,BB11,BD11,BF11,BH11,BJ11,BL11,BN11,BP11,BR11,BT11,BV11,BX11,BZ11,CB11,CD11,CF11,CH11,CJ11) | C11: 52W Breakout | D11: 140 | E11: 5% | F11: 50000 | G11: 184 | H11: UEL | I11: Ujaas Energy Ltd | J11: power & utilities | K11: power generation and supply | L11: smallcap | M11: 3438.86 | N11: 270.67 | O11: 5 | P11: 37036 | Q11: 95 | R11: Outperforming | S11: =IF(R11="Underperforming",-5,IF(Q11>=95,15,IF(Q11>=90,10,IF(Q11>=80,5,0)))) | T11: 77.87 | U11: 15.23 | W11: Earnings / Momentum Support | X11: Nifty IT | Y11: -8.29 | Z11: 110.93 | AA11: 129.99 | AB11: 32.09 | AC11: Growing Industry | AD11: =IF(AC11="Growing Industry",10,IF(AC11="Cyclical in an Upturn",5,0)) | AE11: Too Many Players with High ROCE | AF11: =IF(AE11="Monopoly",10,IF(AE11="Oligopoly",5,IF(AE11="Duopoly that cooperate",10,IF(AE11="Duopoly that compete",5,IF(AE11="Too many players with High ROCE",5,0))))) | AG11: No | AH11: =IF(AG11="No",5,0) | AI11: Headwind | AJ11: =IF(AI11="Tailwind",10,0) | AK11: Structural (10 Years Consistency) | AL11: =IF(AK11="Structural (10 Years Consistency)",10,IF(AK11="Shallow Cyclical (2 to 3 years growth)",5,0)) | AM11: No | AN11: =IF(AM11="Yes due to Product Mix change or Operating Leverage",10,IF(AM11="Yes, these are peak margins",-5,IF(AM11="No",5,0))) | AO11: Stable | AP11: =IF(AO11="Stable",10,0) | AQ11: Yes | AR11: =IF(AQ11="Yes",10,0) | AS11: B2B | AT11: =IF(AS11="B2C",10,IF(AS11="B2B",5,0)) | AU11: No | AV11: =IF(AU11="Yes",10,0) | AW11: Higher One Time, Lower Annuity | AX11: =IF(AW11="Fully Annuity",10,IF(AW11="Higher Annuity, Lower One Time",5,IF(AW11="Higher One Time, Lower Annuity",3,0))) | AY11: Good | AZ11: =IF(AY11="Good",10,0) | BA11: Yes for more than 2 years | BB11: =IF(BA11="Yes for more than 2 years",10,IF(BA11="Yes only for next 1 to 2 years",5,0)) | BC11: 0 to 20 | BD11: =IF(BC11="Above 40",20,IF(BC11="20 to 40",10,IF(BC11="0 to 20",-5,0))) | BE11: Above 75 | BF11: =IF(BE11="Between 50 to 75",10,IF(BE11="Above 75",0,0)) | BG11: Stage 3 | BH11: =IF(BG11="Stage 2",20,IF(BG11="Stage 1",0,IF(BG11="Stage 3",5,IF(BG11="Stage 4",-5,0)))) | BI11: Negative Trend | BJ11: =IF(BI11="Positive Trend",20,IF(BI11="Negative Trend",-10,0)) | BK11: Uptrend | BL11: =IF(BK11="Uptrend",10,IF(BK11="Sideways",5,0)) | BM11: Uptrend | BN11: =IF(BM11="Uptrend",10,IF(BM11="Sideways",5,0)) | BO11: Close to 52 week high or retracement | BP11: =IF(BO11="Overhead supply in last 2 years in last 2 years",-5,IF(BO11="Close to 52 week high or retracement",5,IF(BO11="Blue sky scenario",10,IF(BO11="Long term Downtrend",-10,0)))) | BQ11: Yes | BR11: =IF(BQ11="Yes",10,0) | BS11: More than 20% | BT11: =IF(BS11="More than 20%",10,IF(BS11="Between 12 to 20%",5,IF(BS11="Less than 12%",0,0))) | BU11: No | BV11: =IF(BU11="No",10,0) | BW11: Yes | BX11: =IF(BW11="NO",5,0) | BY11: Above 2 | BZ11: =IF(BY11="Above 2",0,IF(BY11="Between 1.5 to 2",5,IF(BY11="Less than 1.5",10,0))) | CA11: Above 70% | CB11: =IF(CA11="Above 70%",10,IF(CA11="Between 50% to 70%",5,IF(CA11="Less than 50%",0,IF(CA11="Negative",-10,IF(CA11="Less than 50% and Borrowings are increasing",-5,0))))) | CC11: Less than 0.7 | CD11: =IF(CC11="More than 1.2",-10,IF(CC11="Between 0.7 to 1.2",0,IF(CC11="Less than 0.7",10,0))) | CE11: No | CF11: =IF(CE11="Yes",-10,0) | CG11: Less than 15% | CH11: =IF(CG11="More than 15%",-10,IF(CG11="Less than 15%",10,0)) | CI11: No | CJ11: =IF(CI11="Yes, more than 10%",-10,IF(CI11="No",10,0))
A12: =IF(B12=0,"",RANK(B12,$B$2:$B$22,0)) | B12: =SUM(S12,AD12,AF12,AH12,AJ12,AL12,AN12,AP12,AR12,AT12,AV12,AX12,AZ12,BB12,BD12,BF12,BH12,BJ12,BL12,BN12,BP12,BR12,BT12,BV12,BX12,BZ12,CB12,CD12,CF12,CH12,CJ12) | C12: 52W Breakout | D12: 139.7 | E12: 5% | F12: 50000 | G12: 185 | H12: COMSYN | I12: Commercial Syn Bags Ltd | J12: industrials | K12: packaging | L12: smallcap | M12: 906.95 | N12: 269.03 | O12: 19.66 | P12: 7601735 | Q12: 84 | R12: Outperforming | S12: =IF(R12="Underperforming",-5,IF(Q12>=95,15,IF(Q12>=90,10,IF(Q12>=80,5,0)))) | T12: 71.96 | U12: 58.68 | W12: Earnings / Momentum Support | X12: Nifty 50 | Y12: 0.85 | Z12: 68.75 | AA12: 67.32 | AB12: 21.99 | AC12: Cyclical in an Upturn | AD12: =IF(AC12="Growing Industry",10,IF(AC12="Cyclical in an Upturn",5,0)) | AE12: Too Many Players with High ROCE | AF12: =IF(AE12="Monopoly",10,IF(AE12="Oligopoly",5,IF(AE12="Duopoly that cooperate",10,IF(AE12="Duopoly that compete",5,IF(AE12="Too many players with High ROCE",5,0))))) | AG12: No | AH12: =IF(AG12="No",5,0) | AI12: Headwind | AJ12: =IF(AI12="Tailwind",10,0) | AK12: Structural (10 Years Consistency) | AL12: =IF(AK12="Structural (10 Years Consistency)",10,IF(AK12="Shallow Cyclical (2 to 3 years growth)",5,0)) | AM12: No | AN12: =IF(AM12="Yes due to Product Mix change or Operating Leverage",10,IF(AM12="Yes, these are peak margins",-5,IF(AM12="No",5,0))) | AO12: Stable | AP12: =IF(AO12="Stable",10,0) | AQ12: Yes | AR12: =IF(AQ12="Yes",10,0) | AS12: B2B | AT12: =IF(AS12="B2C",10,IF(AS12="B2B",5,0)) | AU12: No | AV12: =IF(AU12="Yes",10,0) | AW12: Higher One Time, Lower Annuity | AX12: =IF(AW12="Fully Annuity",10,IF(AW12="Higher Annuity, Lower One Time",5,IF(AW12="Higher One Time, Lower Annuity",3,0))) | AY12: Good | AZ12: =IF(AY12="Good",10,0) | BA12: Yes for more than 2 years | BB12: =IF(BA12="Yes for more than 2 years",10,IF(BA12="Yes only for next 1 to 2 years",5,0)) | BC12: Above 40 | BD12: =IF(BC12="Above 40",20,IF(BC12="20 to 40",10,IF(BC12="0 to 20",-5,0))) | BE12: Between 50 to 75 | BF12: =IF(BE12="Between 50 to 75",10,IF(BE12="Above 75",0,0)) | BG12: Stage 3 | BH12: =IF(BG12="Stage 2",20,IF(BG12="Stage 1",0,IF(BG12="Stage 3",5,IF(BG12="Stage 4",-5,0)))) | BI12: Negative Trend | BJ12: =IF(BI12="Positive Trend",20,IF(BI12="Negative Trend",-10,0)) | BK12: Uptrend | BL12: =IF(BK12="Uptrend",10,IF(BK12="Sideways",5,0)) | BM12: Uptrend | BN12: =IF(BM12="Uptrend",10,IF(BM12="Sideways",5,0)) | BO12: Close to 52 week high or retracement | BP12: =IF(BO12="Overhead supply in last 2 years in last 2 years",-5,IF(BO12="Close to 52 week high or retracement",5,IF(BO12="Blue sky scenario",10,IF(BO12="Long term Downtrend",-10,0)))) | BQ12: Yes | BR12: =IF(BQ12="Yes",10,0) | BS12: Less than 12% | BT12: =IF(BS12="More than 20%",10,IF(BS12="Between 12 to 20%",5,IF(BS12="Less than 12%",0,0))) | BU12: No | BV12: =IF(BU12="No",10,0) | BW12: Yes | BX12: =IF(BW12="NO",5,0) | BY12: Above 2 | BZ12: =IF(BY12="Above 2",0,IF(BY12="Between 1.5 to 2",5,IF(BY12="Less than 1.5",10,0))) | CA12: Above 70% | CB12: =IF(CA12="Above 70%",10,IF(CA12="Between 50% to 70%",5,IF(CA12="Less than 50%",0,IF(CA12="Negative",-10,IF(CA12="Less than 50% and Borrowings are increasing",-5,0))))) | CC12: Between 0.7 to 1.2 | CD12: =IF(CC12="More than 1.2",-10,IF(CC12="Between 0.7 to 1.2",0,IF(CC12="Less than 0.7",10,0))) | CE12: No | CF12: =IF(CE12="Yes",-10,0) | CG12: Less than 15% | CH12: =IF(CG12="More than 15%",-10,IF(CG12="Less than 15%",10,0)) | CI12: No | CJ12: =IF(CI12="Yes, more than 10%",-10,IF(CI12="No",10,0))
A13: =IF(B13=0,"",RANK(B13,$B$2:$B$22,0)) | B13: =SUM(S13,AD13,AF13,AH13,AJ13,AL13,AN13,AP13,AR13,AT13,AV13,AX13,AZ13,BB13,BD13,BF13,BH13,BJ13,BL13,BN13,BP13,BR13,BT13,BV13,BX13,BZ13,CB13,CD13,CF13,CH13,CJ13) | C13: 52W Breakout | D13: 139.4 | E13: 5% | F13: 50000 | G13: 9 | H13: TITAN | I13: Titan Company Limited | J13: consumer discretionary | K13: diamond cutting / jewellery | L13: largecap | M13: 438655.14 | N13: 5090 | O13: 3.02 | P13: 7293715 | Q13: 56 | R13: Outperforming | S13: =IF(R13="Underperforming",-5,IF(Q13>=95,15,IF(Q13>=90,10,IF(Q13>=80,5,0)))) | T13: 69.54 | U13: 23.49 | W13: Earnings / Momentum Support | X13: Nifty 50 | Y13: 0.85 | Z13: 43.26 | AA13: 42.05 | AB13: 9.51 | AC13: Growing Industry | AD13: =IF(AC13="Growing Industry",10,IF(AC13="Cyclical in an Upturn",5,0)) | AE13: Too Many Players with High ROCE | AF13: =IF(AE13="Monopoly",10,IF(AE13="Oligopoly",5,IF(AE13="Duopoly that cooperate",10,IF(AE13="Duopoly that compete",5,IF(AE13="Too many players with High ROCE",5,0))))) | AG13: No | AH13: =IF(AG13="No",5,0) | AI13: Headwind | AJ13: =IF(AI13="Tailwind",10,0) | AK13: Structural (10 Years Consistency) | AL13: =IF(AK13="Structural (10 Years Consistency)",10,IF(AK13="Shallow Cyclical (2 to 3 years growth)",5,0)) | AM13: No | AN13: =IF(AM13="Yes due to Product Mix change or Operating Leverage",10,IF(AM13="Yes, these are peak margins",-5,IF(AM13="No",5,0))) | AO13: Stable | AP13: =IF(AO13="Stable",10,0) | AQ13: Yes | AR13: =IF(AQ13="Yes",10,0) | AS13: B2B | AT13: =IF(AS13="B2C",10,IF(AS13="B2B",5,0)) | AU13: No | AV13: =IF(AU13="Yes",10,0) | AW13: Higher One Time, Lower Annuity | AX13: =IF(AW13="Fully Annuity",10,IF(AW13="Higher Annuity, Lower One Time",5,IF(AW13="Higher One Time, Lower Annuity",3,0))) | AY13: Good | AZ13: =IF(AY13="Good",10,0) | BA13: Yes for more than 2 years | BB13: =IF(BA13="Yes for more than 2 years",10,IF(BA13="Yes only for next 1 to 2 years",5,0)) | BC13: 20 to 40 | BD13: =IF(BC13="Above 40",20,IF(BC13="20 to 40",10,IF(BC13="0 to 20",-5,0))) | BE13: Between 50 to 75 | BF13: =IF(BE13="Between 50 to 75",10,IF(BE13="Above 75",0,0)) | BG13: Stage 3 | BH13: =IF(BG13="Stage 2",20,IF(BG13="Stage 1",0,IF(BG13="Stage 3",5,IF(BG13="Stage 4",-5,0)))) | BI13: Negative Trend | BJ13: =IF(BI13="Positive Trend",20,IF(BI13="Negative Trend",-10,0)) | BK13: Uptrend | BL13: =IF(BK13="Uptrend",10,IF(BK13="Sideways",5,0)) | BM13: Uptrend | BN13: =IF(BM13="Uptrend",10,IF(BM13="Sideways",5,0)) | BO13: Close to 52 week high or retracement | BP13: =IF(BO13="Overhead supply in last 2 years in last 2 years",-5,IF(BO13="Close to 52 week high or retracement",5,IF(BO13="Blue sky scenario",10,IF(BO13="Long term Downtrend",-10,0)))) | BQ13: Yes | BR13: =IF(BQ13="Yes",10,0) | BS13: More than 20% | BT13: =IF(BS13="More than 20%",10,IF(BS13="Between 12 to 20%",5,IF(BS13="Less than 12%",0,0))) | BU13: No | BV13: =IF(BU13="No",10,0) | BW13: Yes | BX13: =IF(BW13="NO",5,0) | BY13: Less than 1.5 | BZ13: =IF(BY13="Above 2",0,IF(BY13="Between 1.5 to 2",5,IF(BY13="Less than 1.5",10,0))) | CA13: Above 70% | CB13: =IF(CA13="Above 70%",10,IF(CA13="Between 50% to 70%",5,IF(CA13="Less than 50%",0,IF(CA13="Negative",-10,IF(CA13="Less than 50% and Borrowings are increasing",-5,0))))) | CC13: More than 1.2 | CD13: =IF(CC13="More than 1.2",-10,IF(CC13="Between 0.7 to 1.2",0,IF(CC13="Less than 0.7",10,0))) | CE13: No | CF13: =IF(CE13="Yes",-10,0) | CG13: Less than 15% | CH13: =IF(CG13="More than 15%",-10,IF(CG13="Less than 15%",10,0)) | CI13: No | CJ13: =IF(CI13="Yes, more than 10%",-10,IF(CI13="No",10,0))
... A22: =IF(B22=0,"",RANK(B22,$B$2:$B$22,0)) | B22: =SUM(S22,AD22,AF22,AH22,AJ22,AL22,AN22,AP22,AR22,AT22,AV22,AX22,AZ22,BB22,BD22,BF22,BH22,BJ22,BL22,BN22,BP22,BR22,BT22,BV22,BX22,BZ22,CB22,CD22,CF22,CH22,CJ22) | C22: EMA Crossover | D22: 146.1 | E22: 7% | F22: 70000 | G22: 62 | H22: JINDALSTEL | I22: Jindal Steel Ltd | J22: metals & mining | K22: steel - large | L22: largecap | M22: 112515.72 | N22: 1125 | O22: 1.99 | P22: 1775160 | Q22: 8 | R22: Underperforming | S22: =IF(R22="Underperforming",-5,IF(Q22>=95,15,IF(Q22>=90,10,IF(Q22>=80,5,0)))) | T22: 47.9 | U22: 16.58 | W22: Earnings / Momentum Support | X22: Nifty Metal | Y22: 31.49 | Z22: 7.3 | AA22: -18.4 | AB22: -1.56 | AC22: Cyclical in an Upturn | AD22: =IF(AC22="Growing Industry",10,IF(AC22="Cyclical in an Upturn",5,0)) | AE22: Too Many Players with High ROCE | AF22: =IF(AE22="Monopoly",10,IF(AE22="Oligopoly",5,IF(AE22="Duopoly that cooperate",10,IF(AE22="Duopoly that compete",5,IF(AE22="Too many players with High ROCE",5,0))))) | AG22: No | AH22: =IF(AG22="No",5,0) | AI22: Headwind | AJ22: =IF(AI22="Tailwind",10,0) | AK22: Cyclical | AL22: =IF(AK22="Structural (10 Years Consistency)",10,IF(AK22="Shallow Cyclical (2 to 3 years growth)",5,0)) | AM22: No | AN22: =IF(AM22="Yes due to Product Mix change or Operating Leverage",10,IF(AM22="Yes, these are peak margins",-5,IF(AM22="No",5,0))) | AO22: Volatile | AP22: =IF(AO22="Stable",10,0) | AQ22: Yes | AR22: =IF(AQ22="Yes",10,0) | AS22: B2B | AT22: =IF(AS22="B2C",10,IF(AS22="B2B",5,0)) | AU22: No | AV22: =IF(AU22="Yes",10,0) | AW22: Higher One Time, Lower Annuity | AX22: =IF(AW22="Fully Annuity",10,IF(AW22="Higher Annuity, Lower One Time",5,IF(AW22="Higher One Time, Lower Annuity",3,0))) | AY22: Good | AZ22: =IF(AY22="Good",10,0) | BA22: Yes for more than 2 years | BB22: =IF(BA22="Yes for more than 2 years",10,IF(BA22="Yes only for next 1 to 2 years",5,0)) | BC22: 0 to 20 | BD22: =IF(BC22="Above 40",20,IF(BC22="20 to 40",10,IF(BC22="0 to 20",-5,0))) | BE22: Below 45 | BF22: =IF(BE22="Between 50 to 75",10,IF(BE22="Above 75",0,0)) | BG22: Stage 4 | BH22: =IF(BG22="Stage 2",20,IF(BG22="Stage 1",0,IF(BG22="Stage 3",5,IF(BG22="Stage 4",-5,0)))) | BI22: Negative Trend | BJ22: =IF(BI22="Positive Trend",20,IF(BI22="Negative Trend",-10,0)) | BK22: Uptrend | BL22: =IF(BK22="Uptrend",10,IF(BK22="Sideways",5,0)) | BM22: Uptrend | BN22: =IF(BM22="Uptrend",10,IF(BM22="Sideways",5,0)) | BO22: Close to 52 week high or retracement | BP22: =IF(BO22="Overhead supply in last 2 years in last 2 years",-5,IF(BO22="Close to 52 week high or retracement",5,IF(BO22="Blue sky scenario",10,IF(BO22="Long term Downtrend",-10,0)))) | BQ22: Yes | BR22: =IF(BQ22="Yes",10,0) | BS22: Less than 12% | BT22: =IF(BS22="More than 20%",10,IF(BS22="Between 12 to 20%",5,IF(BS22="Less than 12%",0,0))) | BU22: No | BV22: =IF(BU22="No",10,0) | BW22: Yes | BX22: =IF(BW22="NO",5,0) | BY22: Above 2 | BZ22: =IF(BY22="Above 2",0,IF(BY22="Between 1.5 to 2",5,IF(BY22="Less than 1.5",10,0))) | CA22: Above 70% | CB22: =IF(CA22="Above 70%",10,IF(CA22="Between 50% to 70%",5,IF(CA22="Less than 50%",0,IF(CA22="Negative",-10,IF(CA22="Less than 50% and Borrowings are increasing",-5,0))))) | CC22: Less than 0.7 | CD22: =IF(CC22="More than 1.2",-10,IF(CC22="Between 0.7 to 1.2",0,IF(CC22="Less than 0.7",10,0))) | CE22: No | CF22: =IF(CE22="Yes",-10,0) | CG22: Less than 15% | CH22: =IF(CG22="More than 15%",-10,IF(CG22="Less than 15%",10,0)) | CI22: No | CJ22: =IF(CI22="Yes, more than 10%",-10,IF(CI22="No",10,0))

Sheet Scanner Banks NBFC
A1: Rank (Banks & NBFC) | B1: Total Score | C1: Entry | D1: Entry Score | E1: Allocation % | F1: Allocation (₹) | G1: Quantity | H1: Symbol | I1: Company | J1: Sector | K1: Industry | L1: Market Cap Bucket | M1: Market Cap Cr | N1: Close | O1: Today Return % | P1: Volume | Q1: Relative Strength Rating | R1: Relative Strength Status | S1: Relative Strength Score | T1: Calculated RSI (14) | U1: Calculated ADX (14) | V1: Calculated V-stop Line | W1: Calculated Near-term Trigger | X1: Sector Benchmark | Y1: Benchmark 1Y Return % | Z1: Stock 1Y Return % | AA1: Relative Strength 1Y (%) | AB1: O'Neil Weighted Score | AC1: Industry Growth | AD1: Industry Growth Score | AE1: Competitiveness | AF1: Competitiveness Score | AG1: Regulation | AH1: Regulation Score | AI1: Sector Headwinds/Tailwind | AJ1: Sector Headwinds/Tailwind Score | AK1: Industry Type | AL1: Industry Type Score | AM1: NIM | AN1: NIM Score | AO1: CASA Ratio | AP1: CASA Ratio Score | AQ1: Profit cyclicality | AR1: Profit cyclicality Score | AS1: CAR Ratio | AT1: CAR Ratio Score | AU1: Near term triggers | AV1: Near term triggers Score | AW1: High P/BV | AX1: High P/BV Score | AY1: Asset Quality Divergence | AZ1: Asset Quality Divergence Score | BA1: Reported loss | BB1: Reported loss Score | BC1: CEO Resignation | BD1: CEO Resignation Score | BE1: GNPA | BF1: GNPA Score | BG1: KMP Resignation | BH1: KMP Resignation Score | BI1: Return on Assets | BJ1: Return on Assets Score | BK1: Return on Equity | BL1: Return on Equity Score | BM1: AUM Growth | BN1: AUM Growth Score | BO1: Price to Book Value | BP1: Price to Book Value Score | BQ1: ADX | BR1: ADX Score | BS1: RSI | BT1: RSI Score | BU1: Stage Analysis | BV1: Stage Analysis Score | BW1: Price Volume Action | BX1: Price Volume Action Score | BY1: Secondary Trend | BZ1: Secondary Trend Score | CA1: Primary Trend | CB1: Primary Trend Score | CC1: Resistance | CD1: Resistance Score | CE1: V-stop | CF1: V-stop Score
A2: =IF(B2=0,"",RANK(B2,$B$2:$B$2,0)) | B2: =SUM(S2,AD2,AF2,AH2,AJ2,AL2,AN2,AP2,AR2,AT2,AV2,AX2,AZ2,BB2,BD2,BF2,BH2,BJ2,BL2,BN2,BP2,BR2,BT2,BV2,BX2,BZ2,CB2,CD2,CF2) | C2: 52W Breakout | D2: 139.3 | E2: 5% | F2: 50000 | G2: 121 | H2: M&MFIN | I2: Mahindra & Mahindra Financial Services Limited | J2: financials | K2: finance & investments | L2: largecap | M2: 56773.37 | N2: 412.3 | O2: 0.94 | P2: 3517041 | Q2: 75 | R2: Outperforming | S2: =IF(R2="Underperforming",-5,IF(Q2>=95,15,IF(Q2>=90,10,IF(Q2>=80,5,0)))) | T2: 69.89 | U2: 22.3 | W2: Earnings / Momentum Support | X2: Nifty Bank | Y2: 4.98 | Z2: 65.4 | AA2: 57.55 | AB2: 16.19 | AC2: Growing Industry | AD2: =IF(AC2="Growing Industry",10,IF(AC2="Cyclical in an Upturn",5,0)) | AE2: Fragmented with High ROE | AF2: =IF(AE2="Fragmented with Low ROE",-5,IF(AE2="Fragmented with High ROE",10,IF(AE2= "highly cyclical",5,0))) | AG2: Yes | AH2: =IF(AG2="No",5,0) | AI2: Headwind | AJ2: =IF(AI2="Tailwind",10,0) | AK2: Structural (10 Years Consistency) | AL2: =IF(AK2="Structural (10 Years Consistency)",15,IF(AK2="Shallow Cyclical (2 to 3 years growth)",10,IF(AK2 = "Cyclical in an Uptick",5,IF(AK2 = "Cyclical in an Downtick",-10,0)))) | AM2: Yes | AN2: =IF(AM2="Yes",10,0) | AO2: Yes | AP2: =IF(AO2="Yes",10,0) | AR2: =IF(AQ2="No",10,0) | AS2: Yes | AT2: =IF(AS2="Yes",10,0) | AU2: No | AV2: =IF(AU2="Yes",10,0) | AW2: Yes | AX2: =IF(AW2="Yes",5,0) | AY2: No | AZ2: =IF(AY2="No",10,IF(AY2="Yes",-10,0)) | BA2: No | BB2: =IF(BA2="No",10,0) | BC2: No | BD2: =IF(BC2="No",10,IF(BC2= "Yes CEO Resignation",-5,0)) | BE2: No | BF2: =IF(BE2="No",10,IF(BE2="Yes",-5,0)) | BG2: No | BH2: =IF(BG2="No",5,IF(BG2="Yes",-5,0)) | BI2: Yes | BJ2: =IF(BI2="Yes",10,0) | BK2: Yes | BL2: =IF(BK2="Yes",10,0) | BM2: Yes | BN2: =IF(BM2="Yes",10,0) | BO2: P/BV less than 2.5x and Growth more than 20% | BP2: =IF(BO2="P/BV less than 2.5x and Growth more than 20%",20,IF(BO2 = "P/BV less than 2.5x and Growth less than 20%",5,IF(BO2="P/BV between 2.5x to 5x and Growth more than 20%",10,IF(BO2= "P/BV between 2.5x to 5x and Growth less than 20%",-5,IF(BO2= "P/BV above 5x",-5,0))))) | BQ2: 20 to 40 | BR2: =IF(BQ2="Above 40",20,IF(BQ2="20 to 40",10,IF(BQ2="0 to 20",-5,0))) | BS2: Between 50 to 75 | BT2: =IF(BS2="Between 50 to 75",10,IF(BS2="Above 75",0,0)) | BU2: Stage 3 | BV2: =IF(BU2="Stage 2",20,IF(BU2="Stage 1",0,IF(BU2="Stage 3",5,IF(BU2="Stage 4",-5,0)))) | BW2: Negative Trend | BX2: =IF(BW2="Positive Trend",20,IF(BW2="Negative Trend",-10,0)) | BY2: Uptrend | BZ2: =IF(BY2="Uptrend",10,IF(BY2="Sideways",5,0)) | CA2: Uptrend | CB2: =IF(CA2="Uptrend",10,IF(CA2="Sideways",5,0)) | CC2: Close to 52 week high or retracement | CD2: =IF(CC2="Overhead supply in last 2 years in last 2 years",-5,IF(CC2="Close to 52 week high or retracement",5,IF(CC2="Blue sky scenario",10,IF(CC2="Long term Downtrend",-10,0)))) | CE2: Yes | CF2: =IF(CE2="Yes",10,0)

Sheet Scan Match Non Financial
A1: Rank (Non Financial) | B1: Total Score | C1: Symbol | D1: Company | E1: Sector | F1: Industry | G1: Market Cap Bucket | H1: Market Cap Cr | I1: Close | J1: Today Return % | K1: Volume | L1: Relative Strength Rating | M1: Relative Strength Status | N1: Relative Strength Score | O1: Calculated RSI (14) | P1: Calculated ADX (14) | Q1: Calculated V-stop Line | R1: Calculated Near-term Trigger | S1: Sector Benchmark | T1: Benchmark 1Y Return % | U1: Stock 1Y Return % | V1: Relative Strength 1Y (%) | W1: O'Neil Weighted Score | X1: Industry Growth | Y1: Industry Growth Score | Z1: Competitiveness | AA1: Competitiveness Score | AB1: Regulation | AC1: Regulation Score | AD1: Sector Headwinds/Tailwind | AE1: Sector Headwinds/Tailwind Score | AF1: Industry Type | AG1: Industry Type Score | AH1: Margins | AI1: Margins Score | AJ1: Margins Stability | AK1: Margins Stability Score | AL1: Growth | AM1: Growth Score | AN1: Business Type | AO1: Business Type Score | AP1: Near term triggers | AQ1: Near term triggers Score | AR1: Type of Revenue | AS1: Type of Revenue Score | AT1: Capital Allocation | AU1: Capital Allocation Score | AV1: Medium term Growth | AW1: Medium term Growth Score | AX1: ADX | AY1: ADX Score | AZ1: RSI | BA1: RSI Score | BB1: Stage Analysis | BC1: Stage Analysis Score | BD1: Price Volume Action | BE1: Price Volume Action Score | BF1: Secondary Trend | BG1: Secondary Trend Score | BH1: Primary Trend | BI1: Primary Trend Score | BJ1: Resistance | BK1: Resistance Score | BL1: V-stop | BM1: V-stop Score | BN1: PAT Growth | BO1: PAT Growth Score | BP1: Stock History | BQ1: Stock History Score | BR1: PE Ratio | BS1: PE Ratio Score | BT1: PEG Ratio | BU1: PEG Ratio Score | BV1: CFO to EBITDA | BW1: CFO to EBITDA Score | BX1: Debt to Equity | BY1: Debt to Equity Score | BZ1: Auditor Resignation | CA1: Auditor Resignation Score | CB1: Contingent Liability | CC1: Contingent Liability Score | CD1: Pledging | CE1: Pledging Score | CF1: Scan Matches | CG1: Scan Matches Score
A2: =IF(B2=0,"",RANK(B2,$B$2:$B$94,0)) | B2: =SUM(N2,Y2,AA2,AC2,AE2,AG2,AI2,AK2,AM2,AO2,AQ2,AS2,AU2,AW2,AY2,BA2,BC2,BE2,BG2,BI2,BK2,BM2,BO2,BQ2,BS2,BU2,BW2,BY2,CA2,CC2,CE2,CG2) | C2: AIMTRON | D2: Aimtron Electronics Ltd | E2: unknown | F2: EMS | G2: smallcap | H2: 3578.46 | I2: 1717 | J2: 3.66 | K2: 0 | L2: 94 | M2: Outperforming | N2: =IF(M2="Underperforming",-5,IF(L2>=95,15,IF(L2>=90,10,IF(L2>=80,5,0)))) | O2: 79.29 | P2: 61.28 | Q2: 1257.38 | R2: Volume Spike & Near 52W High Breakout | S2: Nifty 50 | T2: 0.85 | U2: 138.4 | V2: 136.39 | W2: 31.4 | X2: Growing Industry | Y2: =IF(X2="Growing Industry",10,IF(X2="Cyclical in an Upturn",5,0)) | Z2: Too Many Players with High ROCE | AA2: =IF(Z2="Monopoly",10,IF(Z2="Oligopoly",5,IF(Z2="Duopoly that cooperate",10,IF(Z2="Duopoly that compete",5,IF(Z2="Too many players with High ROCE",5,0))))) | AB2: No | AC2: =IF(AB2="No",5,0) | AD2: Tailwind | AE2: =IF(AD2="Tailwind",10,0) | AF2: Structural (10 Years Consistency) | AG2: =IF(AF2="Structural (10 Years Consistency)",10,IF(AF2="Shallow Cyclical (2 to 3 years growth)",5,0)) | AH2: No | AI2: =IF(AH2="Yes due to Product Mix change or Operating Leverage",10,IF(AH2="Yes, these are peak margins",-5,IF(AH2="No",5,0))) | AJ2: Stable | AK2: =IF(AJ2="Stable",10,0) | AL2: Yes | AM2: =IF(AL2="Yes",10,0) | AN2: B2B | AO2: =IF(AN2="B2C",10,IF(AN2="B2B",5,0)) | AP2: Yes | AQ2: =IF(AP2="Yes",10,0) | AR2: Higher One Time, Lower Annuity | AS2: =IF(AR2="Fully Annuity",10,IF(AR2="Higher Annuity, Lower One Time",5,IF(AR2="Higher One Time, Lower Annuity",3,0))) | AT2: Good | AU2: =IF(AT2="Good",10,0) | AV2: Yes for more than 2 years | AW2: =IF(AV2="Yes for more than 2 years",10,IF(AV2="Yes only for next 1 to 2 years",5,0)) | AX2: Above 40 | AY2: =IF(AX2="Above 40",20,IF(AX2="20 to 40",10,IF(AX2="0 to 20",-5,0))) | AZ2: Above 75 | BA2: =IF(AZ2="Between 50 to 75",10,IF(AZ2="Above 75",0,0)) | BB2: Stage 2 | BC2: =IF(BB2="Stage 2",20,IF(BB2="Stage 1",0,IF(BB2="Stage 3",5,IF(BB2="Stage 4",-5,0)))) | BD2: Positive Trend | BE2: =IF(BD2="Positive Trend",20,IF(BD2="Negative Trend",-10,0)) | BF2: Uptrend | BG2: =IF(BF2="Uptrend",10,IF(BF2="Sideways",5,0)) | BH2: Uptrend | BI2: =IF(BH2="Uptrend",10,IF(BH2="Sideways",5,0)) | BJ2: Blue sky scenario | BK2: =IF(BJ2="Overhead supply in last 2 years in last 2 years",-5,IF(BJ2="Close to 52 week high or retracement",5,IF(BJ2="Blue sky scenario",10,IF(BJ2="Long term Downtrend",-10,0)))) | BL2: Yes | BM2: =IF(BL2="Yes",10,0) | BN2: More than 20% | BO2: =IF(BN2="More than 20%",10,IF(BN2="Between 12 to 20%",5,IF(BN2="Less than 12%",0,0))) | BP2: No | BQ2: =IF(BP2="No",10,0) | BR2: No | BS2: =IF(BR2="NO",5,0) | BT2: Less than 1.5 | BU2: =IF(BT2="Above 2",0,IF(BT2="Between 1.5 to 2",5,IF(BT2="Less than 1.5",10,0))) | BV2: Above 70% | BW2: =IF(BV2="Above 70%",10,IF(BV2="Between 50% to 70%",5,IF(BV2="Less than 50%",0,IF(BV2="Negative",-10,IF(BV2="Less than 50% and Borrowings are increasing",-5,0))))) | BX2: Less than 0.7 | BY2: =IF(BX2="More than 1.2",-10,IF(BX2="Between 0.7 to 1.2",0,IF(BX2="Less than 0.7",10,0))) | BZ2: No | CA2: =IF(BZ2="Yes",-10,0) | CB2: Less than 15% | CC2: =IF(CB2="More than 15%",-10,IF(CB2="Less than 15%",10,0)) | CD2: No | CE2: =IF(CD2="Yes, more than 10%",-10,IF(CD2="No",10,0)) | CF2: 20 | CG2: =IF(CF2>20,10,IF(CF2>=10,5,2))
A3: =IF(B3=0,"",RANK(B3,$B$2:$B$94,0)) | B3: =SUM(N3,Y3,AA3,AC3,AE3,AG3,AI3,AK3,AM3,AO3,AQ3,AS3,AU3,AW3,AY3,BA3,BC3,BE3,BG3,BI3,BK3,BM3,BO3,BQ3,BS3,BU3,BW3,BY3,CA3,CC3,CE3,CG3) | C3: SBCL | D3: Shivalik Bimetal Controls Ltd | E3: metals & mining | F3: Shunt Resistors | G3: midcap | H3: 6365.55 | I3: 1105.05 | J3: 20 | K3: 0 | L3: 72 | M3: Underperforming | N3: =IF(M3="Underperforming",-5,IF(L3>=95,15,IF(L3>=90,10,IF(L3>=80,5,0)))) | O3: 76.2 | P3: 45.6 | R3: Volume Spike / Accumulation | S3: Nifty Metal | T3: 31.49 | U3: 23.64 | V3: -5.97 | W3: 14.67 | X3: Growing Industry | Y3: =IF(X3="Growing Industry",10,IF(X3="Cyclical in an Upturn",5,0)) | Z3: Monopoly | AA3: =IF(Z3="Monopoly",10,IF(Z3="Oligopoly",5,IF(Z3="Duopoly that cooperate",10,IF(Z3="Duopoly that compete",5,IF(Z3="Too many players with High ROCE",5,0))))) | AB3: No | AC3: =IF(AB3="No",5,0) | AD3: Tailwind | AE3: =IF(AD3="Tailwind",10,0) | AF3: Shallow Cyclical (2 to 3 Years Growth) | AG3: =IF(AF3="Structural (10 Years Consistency)",10,IF(AF3="Shallow Cyclical (2 to 3 years growth)",5,0)) | AH3: Yes due to Product Mix change or Operating Leverage | AI3: =IF(AH3="Yes due to Product Mix change or Operating Leverage",10,IF(AH3="Yes, these are peak margins",-5,IF(AH3="No",5,0))) | AJ3: Stable | AK3: =IF(AJ3="Stable",10,0) | AL3: Yes | AM3: =IF(AL3="Yes",10,0) | AN3: B2B | AO3: =IF(AN3="B2C",10,IF(AN3="B2B",5,0)) | AP3: Yes | AQ3: =IF(AP3="Yes",10,0) | AR3: Fully One Time | AS3: =IF(AR3="Fully Annuity",10,IF(AR3="Higher Annuity, Lower One Time",5,IF(AR3="Higher One Time, Lower Annuity",3,0))) | AT3: Good | AU3: =IF(AT3="Good",10,0) | AV3: Yes for more than 2 years | AW3: =IF(AV3="Yes for more than 2 years",10,IF(AV3="Yes only for next 1 to 2 years",5,0)) | AX3: 20 to 40 | AY3: =IF(AX3="Above 40",20,IF(AX3="20 to 40",10,IF(AX3="0 to 20",-5,0))) | AZ3: Between 50 to 75 | BA3: =IF(AZ3="Between 50 to 75",10,IF(AZ3="Above 75",0,0)) | BB3: Stage 2 | BC3: =IF(BB3="Stage 2",20,IF(BB3="Stage 1",0,IF(BB3="Stage 3",5,IF(BB3="Stage 4",-5,0)))) | BD3: Positive Trend | BE3: =IF(BD3="Positive Trend",20,IF(BD3="Negative Trend",-10,0)) | BF3: Uptrend | BG3: =IF(BF3="Uptrend",10,IF(BF3="Sideways",5,0)) | BH3: Uptrend | BI3: =IF(BH3="Uptrend",10,IF(BH3="Sideways",5,0)) | BJ3: Close to 52 week high or retracement | BK3: =IF(BJ3="Overhead supply in last 2 years in last 2 years",-5,IF(BJ3="Close to 52 week high or retracement",5,IF(BJ3="Blue sky scenario",10,IF(BJ3="Long term Downtrend",-10,0)))) | BL3: Yes | BM3: =IF(BL3="Yes",10,0) | BN3: More than 20% | BO3: =IF(BN3="More than 20%",10,IF(BN3="Between 12 to 20%",5,IF(BN3="Less than 12%",0,0))) | BP3: Yes | BQ3: =IF(BP3="No",10,0) | BR3: No | BS3: =IF(BR3="NO",5,0) | BT3: Between 1.5 to 2 | BU3: =IF(BT3="Above 2",0,IF(BT3="Between 1.5 to 2",5,IF(BT3="Less than 1.5",10,0))) | BV3: Less than 50% | BW3: =IF(BV3="Above 70%",10,IF(BV3="Between 50% to 70%",5,IF(BV3="Less than 50%",0,IF(BV3="Negative",-10,IF(BV3="Less than 50% and Borrowings are increasing",-5,0))))) | BX3: Less than 0.7 | BY3: =IF(BX3="More than 1.2",-10,IF(BX3="Between 0.7 to 1.2",0,IF(BX3="Less than 0.7",10,0))) | BZ3: No | CA3: =IF(BZ3="Yes",-10,0) | CB3: Less than 15% | CC3: =IF(CB3="More than 15%",-10,IF(CB3="Less than 15%",10,0)) | CD3: No | CE3: =IF(CD3="Yes, more than 10%",-10,IF(CD3="No",10,0)) | CF3: 21 | CG3: =IF(CF3>20,10,IF(CF3>=10,5,2))
A4: =IF(B4=0,"",RANK(B4,$B$2:$B$94,0)) | B4: =SUM(N4,Y4,AA4,AC4,AE4,AG4,AI4,AK4,AM4,AO4,AQ4,AS4,AU4,AW4,AY4,BA4,BC4,BE4,BG4,BI4,BK4,BM4,BO4,BQ4,BS4,BU4,BW4,BY4,CA4,CC4,CE4,CG4) | C4: PIXTRANS | D4: Pix Transmission Ltd | E4: fmcg | F4: Rubber Processing/Rubber Products | G4: smallcap | H4: 2793.17 | I4: 2050 | J4: 19.38 | K4: 0 | L4: 48 | M4: Outperforming | N4: =IF(M4="Underperforming",-5,IF(L4>=95,15,IF(L4>=90,10,IF(L4>=80,5,0)))) | O4: 59.95 | P4: 43.39 | R4: Volume Spike / Accumulation | S4: Nifty FMCG | T4: -13.73 | U4: 17.79 | V4: 36.54 | W4: 7.69 | X4: Growing Industry | Y4: =IF(X4="Growing Industry",10,IF(X4="Cyclical in an Upturn",5,0)) | Z4: Too Many Players with High ROCE | AA4: =IF(Z4="Monopoly",10,IF(Z4="Oligopoly",5,IF(Z4="Duopoly that cooperate",10,IF(Z4="Duopoly that compete",5,IF(Z4="Too many players with High ROCE",5,0))))) | AB4: No | AC4: =IF(AB4="No",5,0) | AD4: Headwind | AE4: =IF(AD4="Tailwind",10,0) | AF4: Structural (10 Years Consistency) | AG4: =IF(AF4="Structural (10 Years Consistency)",10,IF(AF4="Shallow Cyclical (2 to 3 years growth)",5,0)) | AH4: No | AI4: =IF(AH4="Yes due to Product Mix change or Operating Leverage",10,IF(AH4="Yes, these are peak margins",-5,IF(AH4="No",5,0))) | AJ4: Stable | AK4: =IF(AJ4="Stable",10,0) | AL4: Yes | AM4: =IF(AL4="Yes",10,0) | AN4: B2C | AO4: =IF(AN4="B2C",10,IF(AN4="B2B",5,0)) | AP4: Yes | AQ4: =IF(AP4="Yes",10,0) | AR4: Higher Annuity, Lower One Time | AS4: =IF(AR4="Fully Annuity",10,IF(AR4="Higher Annuity, Lower One Time",5,IF(AR4="Higher One Time, Lower Annuity",3,0))) | AT4: Good | AU4: =IF(AT4="Good",10,0) | AV4: Yes for more than 2 years | AW4: =IF(AV4="Yes for more than 2 years",10,IF(AV4="Yes only for next 1 to 2 years",5,0)) | AX4: Above 40 | AY4: =IF(AX4="Above 40",20,IF(AX4="20 to 40",10,IF(AX4="0 to 20",-5,0))) | AZ4: Between 50 to 75 | BA4: =IF(AZ4="Between 50 to 75",10,IF(AZ4="Above 75",0,0)) | BB4: Stage 3 | BC4: =IF(BB4="Stage 2",20,IF(BB4="Stage 1",0,IF(BB4="Stage 3",5,IF(BB4="Stage 4",-5,0)))) | BD4: Negative Trend | BE4: =IF(BD4="Positive Trend",20,IF(BD4="Negative Trend",-10,0)) | BF4: Uptrend | BG4: =IF(BF4="Uptrend",10,IF(BF4="Sideways",5,0)) | BH4: Uptrend | BI4: =IF(BH4="Uptrend",10,IF(BH4="Sideways",5,0)) | BJ4: Close to 52 week high or retracement | BK4: =IF(BJ4="Overhead supply in last 2 years in last 2 years",-5,IF(BJ4="Close to 52 week high or retracement",5,IF(BJ4="Blue sky scenario",10,IF(BJ4="Long term Downtrend",-10,0)))) | BL4: Yes | BM4: =IF(BL4="Yes",10,0) | BN4: More than 20% | BO4: =IF(BN4="More than 20%",10,IF(BN4="Between 12 to 20%",5,IF(BN4="Less than 12%",0,0))) | BP4: No | BQ4: =IF(BP4="No",10,0) | BR4: No | BS4: =IF(BR4="NO",5,0) | BT4: Less than 1.5 | BU4: =IF(BT4="Above 2",0,IF(BT4="Between 1.5 to 2",5,IF(BT4="Less than 1.5",10,0))) | BV4: Above 70% | BW4: =IF(BV4="Above 70%",10,IF(BV4="Between 50% to 70%",5,IF(BV4="Less than 50%",0,IF(BV4="Negative",-10,IF(BV4="Less than 50% and Borrowings are increasing",-5,0))))) | BX4: Less than 0.7 | BY4: =IF(BX4="More than 1.2",-10,IF(BX4="Between 0.7 to 1.2",0,IF(BX4="Less than 0.7",10,0))) | BZ4: No | CA4: =IF(BZ4="Yes",-10,0) | CB4: Less than 15% | CC4: =IF(CB4="More than 15%",-10,IF(CB4="Less than 15%",10,0)) | CD4: No | CE4: =IF(CD4="Yes, more than 10%",-10,IF(CD4="No",10,0)) | CF4: 24 | CG4: =IF(CF4>20,10,IF(CF4>=10,5,2))
A5: =IF(B5=0,"",RANK(B5,$B$2:$B$94,0)) | B5: =SUM(N5,Y5,AA5,AC5,AE5,AG5,AI5,AK5,AM5,AO5,AQ5,AS5,AU5,AW5,AY5,BA5,BC5,BE5,BG5,BI5,BK5,BM5,BO5,BQ5,BS5,BU5,BW5,BY5,CA5,CC5,CE5,CG5) | C5: NAVINFLUOR | D5: Navin Fluorine International Ltd | E5: chemicals | F5: Chemicals - Flourine | G5: largecap | H5: 42117.52 | I5: 8209 | J5: -0.75 | K5: 0 | L5: 73 | M5: Outperforming | N5: =IF(M5="Underperforming",-5,IF(L5>=95,15,IF(L5>=90,10,IF(L5>=80,5,0)))) | O5: 76.5 | P5: 55.5 | R5: Earnings / Momentum Support | S5: Nifty 50 | T5: 0.85 | U5: 72.22 | V5: 70.77 | W5: 15.32 | X5: Growing Industry | Y5: =IF(X5="Growing Industry",10,IF(X5="Cyclical in an Upturn",5,0)) | Z5: Oligopoly | AA5: =IF(Z5="Monopoly",10,IF(Z5="Oligopoly",5,IF(Z5="Duopoly that cooperate",10,IF(Z5="Duopoly that compete",5,IF(Z5="Too many players with High ROCE",5,0))))) | AB5: No | AC5: =IF(AB5="No",5,0) | AD5: Tailwind | AE5: =IF(AD5="Tailwind",10,0) | AF5: Shallow Cyclical (2 to 3 Years Growth) | AG5: =IF(AF5="Structural (10 Years Consistency)",10,IF(AF5="Shallow Cyclical (2 to 3 years growth)",5,0)) | AH5: No | AI5: =IF(AH5="Yes due to Product Mix change or Operating Leverage",10,IF(AH5="Yes, these are peak margins",-5,IF(AH5="No",5,0))) | AJ5: Stable | AK5: =IF(AJ5="Stable",10,0) | AL5: Yes | AM5: =IF(AL5="Yes",10,0) | AN5: B2B | AO5: =IF(AN5="B2C",10,IF(AN5="B2B",5,0)) | AP5: Yes | AQ5: =IF(AP5="Yes",10,0) | AR5: Higher One Time, Lower Annuity | AS5: =IF(AR5="Fully Annuity",10,IF(AR5="Higher Annuity, Lower One Time",5,IF(AR5="Higher One Time, Lower Annuity",3,0))) | AT5: Good | AU5: =IF(AT5="Good",10,0) | AV5: Yes for more than 2 years | AW5: =IF(AV5="Yes for more than 2 years",10,IF(AV5="Yes only for next 1 to 2 years",5,0)) | AX5: 20 to 40 | AY5: =IF(AX5="Above 40",20,IF(AX5="20 to 40",10,IF(AX5="0 to 20",-5,0))) | AZ5: Between 50 to 75 | BA5: =IF(AZ5="Between 50 to 75",10,IF(AZ5="Above 75",0,0)) | BB5: Stage 3 | BC5: =IF(BB5="Stage 2",20,IF(BB5="Stage 1",0,IF(BB5="Stage 3",5,IF(BB5="Stage 4",-5,0)))) | BD5: Positive Trend | BE5: =IF(BD5="Positive Trend",20,IF(BD5="Negative Trend",-10,0)) | BF5: Uptrend | BG5: =IF(BF5="Uptrend",10,IF(BF5="Sideways",5,0)) | BH5: Uptrend | BI5: =IF(BH5="Uptrend",10,IF(BH5="Sideways",5,0)) | BJ5: Close to 52 week high or retracement | BK5: =IF(BJ5="Overhead supply in last 2 years in last 2 years",-5,IF(BJ5="Close to 52 week high or retracement",5,IF(BJ5="Blue sky scenario",10,IF(BJ5="Long term Downtrend",-10,0)))) | BL5: Yes | BM5: =IF(BL5="Yes",10,0) | BN5: More than 20% | BO5: =IF(BN5="More than 20%",10,IF(BN5="Between 12 to 20%",5,IF(BN5="Less than 12%",0,0))) | BP5: No | BQ5: =IF(BP5="No",10,0) | BR5: Yes | BS5: =IF(BR5="NO",5,0) | BT5: Above 2 | BU5: =IF(BT5="Above 2",0,IF(BT5="Between 1.5 to 2",5,IF(BT5="Less than 1.5",10,0))) | BV5: Between 50% to 70% | BW5: =IF(BV5="Above 70%",10,IF(BV5="Between 50% to 70%",5,IF(BV5="Less than 50%",0,IF(BV5="Negative",-10,IF(BV5="Less than 50% and Borrowings are increasing",-5,0))))) | BX5: Less than 0.7 | BY5: =IF(BX5="More than 1.2",-10,IF(BX5="Between 0.7 to 1.2",0,IF(BX5="Less than 0.7",10,0))) | BZ5: No | CA5: =IF(BZ5="Yes",-10,0) | CB5: Less than 15% | CC5: =IF(CB5="More than 15%",-10,IF(CB5="Less than 15%",10,0)) | CD5: No | CE5: =IF(CD5="Yes, more than 10%",-10,IF(CD5="No",10,0)) | CF5: 21 | CG5: =IF(CF5>20,10,IF(CF5>=10,5,2))
A6: =IF(B6=0,"",RANK(B6,$B$2:$B$94,0)) | B6: =SUM(N6,Y6,AA6,AC6,AE6,AG6,AI6,AK6,AM6,AO6,AQ6,AS6,AU6,AW6,AY6,BA6,BC6,BE6,BG6,BI6,BK6,BM6,BO6,BQ6,BS6,BU6,BW6,BY6,CA6,CC6,CE6,CG6) | C6: APCOTEXIND | D6: Apcotex Industries Ltd | E6: chemicals | F6: Rubber Processing/Rubber Products | G6: smallcap | H6: 3235.38 | I6: 624.05 | J6: 1.5 | K6: 0 | L6: 71 | M6: Outperforming | N6: =IF(M6="Underperforming",-5,IF(L6>=95,15,IF(L6>=90,10,IF(L6>=80,5,0)))) | O6: 73.88 | P6: 64.59 | R6: Earnings / Momentum Support | S6: Nifty 50 | T6: 0.85 | U6: 53.86 | V6: 52.57 | W6: 14.24 | X6: Growing Industry | Y6: =IF(X6="Growing Industry",10,IF(X6="Cyclical in an Upturn",5,0)) | Z6: Oligopoly | AA6: =IF(Z6="Monopoly",10,IF(Z6="Oligopoly",5,IF(Z6="Duopoly that cooperate",10,IF(Z6="Duopoly that compete",5,IF(Z6="Too many players with High ROCE",5,0))))) | AB6: No | AC6: =IF(AB6="No",5,0) | AD6: Tailwind | AE6: =IF(AD6="Tailwind",10,0) | AF6: Cyclical | AG6: =IF(AF6="Structural (10 Years Consistency)",10,IF(AF6="Shallow Cyclical (2 to 3 years growth)",5,0)) | AH6: No | AI6: =IF(AH6="Yes due to Product Mix change or Operating Leverage",10,IF(AH6="Yes, these are peak margins",-5,IF(AH6="No",5,0))) | AJ6: Stable | AK6: =IF(AJ6="Stable",10,0) | AL6: Yes | AM6: =IF(AL6="Yes",10,0) | AN6: B2B | AO6: =IF(AN6="B2C",10,IF(AN6="B2B",5,0)) | AP6: Yes | AQ6: =IF(AP6="Yes",10,0) | AR6: Fully One Time | AS6: =IF(AR6="Fully Annuity",10,IF(AR6="Higher Annuity, Lower One Time",5,IF(AR6="Higher One Time, Lower Annuity",3,0))) | AT6: Good | AU6: =IF(AT6="Good",10,0) | AV6: Yes for more than 2 years | AW6: =IF(AV6="Yes for more than 2 years",10,IF(AV6="Yes only for next 1 to 2 years",5,0)) | AX6: Above 40 | AY6: =IF(AX6="Above 40",20,IF(AX6="20 to 40",10,IF(AX6="0 to 20",-5,0))) | AZ6: Between 50 to 75 | BA6: =IF(AZ6="Between 50 to 75",10,IF(AZ6="Above 75",0,0)) | BB6: Stage 1 | BC6: =IF(BB6="Stage 2",20,IF(BB6="Stage 1",0,IF(BB6="Stage 3",5,IF(BB6="Stage 4",-5,0)))) | BD6: Positive Trend | BE6: =IF(BD6="Positive Trend",20,IF(BD6="Negative Trend",-10,0)) | BF6: Sideways | BG6: =IF(BF6="Uptrend",10,IF(BF6="Sideways",5,0)) | BH6: Uptrend | BI6: =IF(BH6="Uptrend",10,IF(BH6="Sideways",5,0)) | BJ6: Overhead supply in last 2 years in last 2 years | BK6: =IF(BJ6="Overhead supply in last 2 years in last 2 years",-5,IF(BJ6="Close to 52 week high or retracement",5,IF(BJ6="Blue sky scenario",10,IF(BJ6="Long term Downtrend",-10,0)))) | BL6: Yes | BM6: =IF(BL6="Yes",10,0) | BN6: More than 20% | BO6: =IF(BN6="More than 20%",10,IF(BN6="Between 12 to 20%",5,IF(BN6="Less than 12%",0,0))) | BP6: No | BQ6: =IF(BP6="No",10,0) | BR6: No | BS6: =IF(BR6="NO",5,0) | BT6: Less than 1.5 | BU6: =IF(BT6="Above 2",0,IF(BT6="Between 1.5 to 2",5,IF(BT6="Less than 1.5",10,0))) | BV6: Between 50% to 70% | BW6: =IF(BV6="Above 70%",10,IF(BV6="Between 50% to 70%",5,IF(BV6="Less than 50%",0,IF(BV6="Negative",-10,IF(BV6="Less than 50% and Borrowings are increasing",-5,0))))) | BX6: Less than 0.7 | BY6: =IF(BX6="More than 1.2",-10,IF(BX6="Between 0.7 to 1.2",0,IF(BX6="Less than 0.7",10,0))) | BZ6: No | CA6: =IF(BZ6="Yes",-10,0) | CB6: Less than 15% | CC6: =IF(CB6="More than 15%",-10,IF(CB6="Less than 15%",10,0)) | CD6: No | CE6: =IF(CD6="Yes, more than 10%",-10,IF(CD6="No",10,0)) | CF6: 20 | CG6: =IF(CF6>20,10,IF(CF6>=10,5,2))
A7: =IF(B7=0,"",RANK(B7,$B$2:$B$94,0)) | B7: =SUM(N7,Y7,AA7,AC7,AE7,AG7,AI7,AK7,AM7,AO7,AQ7,AS7,AU7,AW7,AY7,BA7,BC7,BE7,BG7,BI7,BK7,BM7,BO7,BQ7,BS7,BU7,BW7,BY7,CA7,CC7,CE7,CG7) | C7: IBULLSLTD | D7: Indiabulls Limited | E7: Real Estate | F7: Diversified | G7: midcap | H7: 6690.45 | I7: 28.72 | J7: -2.41 | K7: 0 | L7: 93 | M7: Outperforming | N7: =IF(M7="Underperforming",-5,IF(L7>=95,15,IF(L7>=90,10,IF(L7>=80,5,0)))) | O7: 69.07 | P7: 45.53 | R7: Earnings / Momentum Support | S7: Nifty Realty | T7: -8.12 | U7: 85.95 | V7: 102.39 | W7: 30.45 | X7: Growing Industry | Y7: =IF(X7="Growing Industry",10,IF(X7="Cyclical in an Upturn",5,0)) | Z7: Too Many Players with High ROCE | AA7: =IF(Z7="Monopoly",10,IF(Z7="Oligopoly",5,IF(Z7="Duopoly that cooperate",10,IF(Z7="Duopoly that compete",5,IF(Z7="Too many players with High ROCE",5,0))))) | AB7: No | AC7: =IF(AB7="No",5,0) | AD7: Headwind | AE7: =IF(AD7="Tailwind",10,0) | AF7: Structural (10 Years Consistency) | AG7: =IF(AF7="Structural (10 Years Consistency)",10,IF(AF7="Shallow Cyclical (2 to 3 years growth)",5,0)) | AH7: No | AI7: =IF(AH7="Yes due to Product Mix change or Operating Leverage",10,IF(AH7="Yes, these are peak margins",-5,IF(AH7="No",5,0))) | AJ7: Stable | AK7: =IF(AJ7="Stable",10,0) | AL7: Yes | AM7: =IF(AL7="Yes",10,0) | AN7: B2B | AO7: =IF(AN7="B2C",10,IF(AN7="B2B",5,0)) | AP7: No | AQ7: =IF(AP7="Yes",10,0) | AR7: Higher One Time, Lower Annuity | AS7: =IF(AR7="Fully Annuity",10,IF(AR7="Higher Annuity, Lower One Time",5,IF(AR7="Higher One Time, Lower Annuity",3,0))) | AT7: Good | AU7: =IF(AT7="Good",10,0) | AV7: Yes for more than 2 years | AW7: =IF(AV7="Yes for more than 2 years",10,IF(AV7="Yes only for next 1 to 2 years",5,0)) | AX7: Above 40 | AY7: =IF(AX7="Above 40",20,IF(AX7="20 to 40",10,IF(AX7="0 to 20",-5,0))) | AZ7: Between 50 to 75 | BA7: =IF(AZ7="Between 50 to 75",10,IF(AZ7="Above 75",0,0)) | BB7: Stage 3 | BC7: =IF(BB7="Stage 2",20,IF(BB7="Stage 1",0,IF(BB7="Stage 3",5,IF(BB7="Stage 4",-5,0)))) | BD7: Negative Trend | BE7: =IF(BD7="Positive Trend",20,IF(BD7="Negative Trend",-10,0)) | BF7: Uptrend | BG7: =IF(BF7="Uptrend",10,IF(BF7="Sideways",5,0)) | BH7: Uptrend | BI7: =IF(BH7="Uptrend",10,IF(BH7="Sideways",5,0)) | BJ7: Close to 52 week high or retracement | BK7: =IF(BJ7="Overhead supply in last 2 years in last 2 years",-5,IF(BJ7="Close to 52 week high or retracement",5,IF(BJ7="Blue sky scenario",10,IF(BJ7="Long term Downtrend",-10,0)))) | BL7: Yes | BM7: =IF(BL7="Yes",10,0) | BN7: More than 20% | BO7: =IF(BN7="More than 20%",10,IF(BN7="Between 12 to 20%",5,IF(BN7="Less than 12%",0,0))) | BP7: No | BQ7: =IF(BP7="No",10,0) | BR7: No | BS7: =IF(BR7="NO",5,0) | BT7: Less than 1.5 | BU7: =IF(BT7="Above 2",0,IF(BT7="Between 1.5 to 2",5,IF(BT7="Less than 1.5",10,0))) | BV7: Above 70% | BW7: =IF(BV7="Above 70%",10,IF(BV7="Between 50% to 70%",5,IF(BV7="Less than 50%",0,IF(BV7="Negative",-10,IF(BV7="Less than 50% and Borrowings are increasing",-5,0))))) | BX7: Less than 0.7 | BY7: =IF(BX7="More than 1.2",-10,IF(BX7="Between 0.7 to 1.2",0,IF(BX7="Less than 0.7",10,0))) | BZ7: No | CA7: =IF(BZ7="Yes",-10,0) | CB7: Less than 15% | CC7: =IF(CB7="More than 15%",-10,IF(CB7="Less than 15%",10,0)) | CD7: No | CE7: =IF(CD7="Yes, more than 10%",-10,IF(CD7="No",10,0)) | CF7: 19 | CG7: =IF(CF7>20,10,IF(CF7>=10,5,2))
